Workbook

Sheet Dashboard
A1: E-COMMERCE FINANCIAL DASHBOARD — Q1 2025
A2: EdShop Global Ltd | Prepared by HSG AURINKO GmbH | Confidential
A4: KEY FINANCIAL KPIs
A6: Total Revenue ($) | B6: ='P&L Statement'!B11 | C6: ='P&L Statement'!C11 | D6: ='P&L Statement'!D11 | E6: ='P&L Statement'!E11 | F6: ='P&L Statement'!F11 | G6: =E6-F6 | H6: ✅ On Track
A7: Total COGS ($) | B7: ='P&L Statement'!B13 | C7: ='P&L Statement'!C13 | D7: ='P&L Statement'!D13 | E7: ='P&L Statement'!E13 | F7: ='P&L Statement'!F13 | G7: =E7-F7 | H7: ✅ On Track
A8: Gross Profit ($) | B8: ='P&L Statement'!B14 | C8: ='P&L Statement'!C14 | D8: ='P&L Statement'!D14 | E8: ='P&L Statement'!E14 | F8: ='P&L Statement'!F14 | G8: =E8-F8 | H8: ✅ On Track
A9: Gross Margin % | B9: ='P&L Statement'!B15 | C9: ='P&L Statement'!C15 | D9: ='P&L Statement'!D15 | E9: ='P&L Statement'!E15 | F9: ='P&L Statement'!F15 | G9: =E9-F9 | H9: ✅ On Track
A10: Total OpEx ($) | B10: ='P&L Statement'!B24 | C10: ='P&L Statement'!C24 | D10: ='P&L Statement'!D24 | E10: ='P&L Statement'!E24 | F10: ='P&L Statement'!F24 | G10: =E10-F10 | H10: ✅ On Track
A11: EBITDA ($) | B11: ='P&L Statement'!B25 | C11: ='P&L Statement'!C25 | D11: ='P&L Statement'!D25 | E11: ='P&L Statement'!E25 | F11: ='P&L Statement'!F25 | G11: =E11-F11 | H11: ✅ On Track
A12: EBITDA Margin % | B12: ='P&L Statement'!B26 | C12: ='P&L Statement'!C26 | D12: ='P&L Statement'!D26 | E12: ='P&L Statement'!E26 | F12: ='P&L Statement'!F26 | G12: =E12-F12 | H12: ✅ On Track
A14: CONTRIBUTION MARGIN SUMMARY BY PRODUCT
A16: Fashion | B16: ='Contribution Margin'!B5 | C16: ='Contribution Margin'!B7 | D16: ='Contribution Margin'!B8 | E16: ='Contribution Margin'!B11 | F16: ='Contribution Margin'!B12 | G16: ='Contribution Margin'!B14 | H16: ='Contribution Margin'!B15
A17: Electronics | B17: ='Contribution Margin'!C5 | C17: ='Contribution Margin'!C7 | D17: ='Contribution Margin'!C8 | E17: ='Contribution Margin'!C11 | F17: ='Contribution Margin'!C12 | G17: ='Contribution Margin'!C14 | H17: ='Contribution Margin'!C15
A18: Beauty | B18: ='Contribution Margin'!D5 | C18: ='Contribution Margin'!D7 | D18: ='Contribution Margin'!D8 | E18: ='Contribution Margin'!D11 | F18: ='Contribution Margin'!D12 | G18: ='Contribution Margin'!D14 | H18: ='Contribution Margin'!D15
A19: Home & Living | B19: ='Contribution Margin'!E5 | C19: ='Contribution Margin'!E7 | D19: ='Contribution Margin'!E8 | E19: ='Contribution Margin'!E11 | F19: ='Contribution Margin'!E12 | G19: ='Contribution Margin'!E14 | H19: ='Contribution Margin'!E15
A20: Sports | B20: ='Contribution Margin'!F5 | C20: ='Contribution Margin'!F7 | D20: ='Contribution Margin'!F8 | E20: ='Contribution Margin'!F11 | F20: ='Contribution Margin'!F12 | G20: ='Contribution Margin'!F14 | H20: ='Contribution Margin'!F15

Sheet Assumptions
A1: E-COMMERCE FINANCIAL MODEL — ASSUMPTIONS & INPUTS
A2: All blue cells are inputs. Black cells are calculated. Change assumptions here — all sheets update automatically.
A4: COMPANY INFORMATION
A5: Company Name | B5: EdShop Global Ltd
A6: Reporting Currency | B6: USD ($)
A7: Fiscal Year | B7: 2025
A8: Reporting Period | B8: Q1 2025 (Jan–Mar)
A9: Prepared By | B9: HSG AURINKO GmbH
A11: REVENUE ASSUMPTIONS (Monthly)
A13: Fashion & Apparel | B13: 850 | C13: 920 | D13: 1050 | E13: 65 | F13: 0.08
A14: Electronics & Tech | B14: 420 | C14: 450 | D14: 510 | E14: 180 | F14: 0.06
A15: Beauty & Cosmetics | B15: 630 | C15: 680 | D15: 750 | E15: 45 | F15: 0.1
A16: Home & Living | B16: 380 | C16: 400 | D16: 440 | E16: 85 | F16: 0.07
A17: Sports & Outdoors | B17: 290 | C17: 320 | D17: 370 | E17: 95 | F17: 0.09
A19: COST ASSUMPTIONS
A21: COGS — Fashion | B21: Variable | C21: 28000 | D21: 30000 | E21: 34000 | F21: ~43% of revenue
A22: COGS — Electronics | B22: Variable | C22: 54000 | D22: 58000 | E22: 66000 | F22: ~67% of revenue
A23: COGS — Beauty | B23: Variable | C23: 12000 | D23: 13000 | E23: 14000 | F23: ~42% of revenue
A24: COGS — Home & Living | B24: Variable | C24: 13000 | D24: 14000 | E24: 15000 | F24: ~45% of revenue
A25: COGS — Sports | B25: Variable | C25: 11000 | D25: 12000 | E25: 14000 | F25: ~40% of revenue
A26: Warehouse & Fulfilment | B26: Semi-Fixed | C26: 18000 | D26: 19000 | E26: 21000 | F26: Scales with volume
A27: Shipping & Returns | B27: Variable | C27: 14000 | D27: 15000 | E27: 17000 | F27: Avg $8/order
A28: Marketing & Ads | B28: Variable | C28: 32000 | D28: 35000 | E28: 40000 | F28: ROAS target 3.5x
A29: Platform Fees (Shopify) | B29: Fixed | C29: 5000 | D29: 5000 | E29: 5000 | F29: Fixed monthly
A30: Salaries | B30: Fixed | C30: 45000 | D30: 45000 | E30: 50000 | F30: 2 new hires Mar
A31: Technology & Software | B31: Fixed | C31: 8000 | D31: 8000 | E31: 8000 | F31: Fixed
A32: G&A / Admin | B32: Fixed | C32: 10000 | D32: 10000 | E32: 11000 | F32: Fixed estimate

Sheet Cost Centers
A1: COST CENTER OVERVIEW — Q1 2025
A2: Data feeds automatically into P&L and Contribution Margin sheets via SUMIF formulas
A5: Fashion & Apparel Revenue | B5: KST-100 | C5: Revenue | D5: =Assumptions!B13*Assumptions!E13 | E5: =Assumptions!C13*Assumptions!E13 | F5: =Assumptions!D13*Assumptions!E13 | G5: =D5+E5+F5 | H5: 270000 | I5: =G5-H5
A6: Electronics Revenue | B6: KST-110 | C6: Revenue | D6: =Assumptions!B14*Assumptions!E14 | E6: =Assumptions!C14*Assumptions!E14 | F6: =Assumptions!D14*Assumptions!E14 | G6: =D6+E6+F6 | H6: 240000 | I6: =G6-H6
A7: Beauty & Cosmetics Revenue | B7: KST-120 | C7: Revenue | D7: =Assumptions!B15*Assumptions!E15 | E7: =Assumptions!C15*Assumptions!E15 | F7: =Assumptions!D15*Assumptions!E15 | G7: =D7+E7+F7 | H7: 130000 | I7: =G7-H7
A8: Home & Living Revenue | B8: KST-130 | C8: Revenue | D8: =Assumptions!B16*Assumptions!E16 | E8: =Assumptions!C16*Assumptions!E16 | F8: =Assumptions!D16*Assumptions!E16 | G8: =D8+E8+F8 | H8: 100000 | I8: =G8-H8
A9: Sports & Outdoors Revenue | B9: KST-140 | C9: Revenue | D9: =Assumptions!B17*Assumptions!E17 | E9: =Assumptions!C17*Assumptions!E17 | F9: =Assumptions!D17*Assumptions!E17 | G9: =D9+E9+F9 | H9: 85000 | I9: =G9-H9
A10: COGS — Fashion | B10: KST-200 | C10: COGS | D10: =Assumptions!C21 | E10: =Assumptions!D21 | F10: =Assumptions!E21 | G10: =D10+E10+F10 | H10: 94000 | I10: =G10-H10
A11: COGS — Electronics | B11: KST-210 | C11: COGS | D11: =Assumptions!C22 | E11: =Assumptions!D22 | F11: =Assumptions!E22 | G11: =D11+E11+F11 | H11: 184000 | I11: =G11-H11
A12: COGS — Beauty | B12: KST-220 | C12: COGS | D12: =Assumptions!C23 | E12: =Assumptions!D23 | F12: =Assumptions!E23 | G12: =D12+E12+F12 | H12: 40000 | I12: =G12-H12
A13: COGS — Home & Living | B13: KST-230 | C13: COGS | D13: =Assumptions!C24 | E13: =Assumptions!D24 | F13: =Assumptions!E24 | G13: =D13+E13+F13 | H13: 43000 | I13: =G13-H13
A14: COGS — Sports | B14: KST-240 | C14: COGS | D14: =Assumptions!C25 | E14: =Assumptions!D25 | F14: =Assumptions!E25 | G14: =D14+E14+F14 | H14: 38000 | I14: =G14-H14
A15: Warehouse & Fulfilment | B15: KST-300 | C15: OpEx | D15: =Assumptions!C26 | E15: =Assumptions!D26 | F15: =Assumptions!E26 | G15: =D15+E15+F15 | H15: 58000 | I15: =G15-H15
A16: Shipping & Returns | B16: KST-310 | C16: OpEx | D16: =Assumptions!C27 | E16: =Assumptions!D27 | F16: =Assumptions!E27 | G16: =D16+E16+F16 | H16: 47000 | I16: =G16-H16
A17: Marketing & Ads | B17: KST-320 | C17: OpEx | D17: =Assumptions!C28 | E17: =Assumptions!D28 | F17: =Assumptions!E28 | G17: =D17+E17+F17 | H17: 110000 | I17: =G17-H17
A18: Platform Fees | B18: KST-330 | C18: OpEx | D18: =Assumptions!C29 | E18: =Assumptions!D29 | F18: =Assumptions!E29 | G18: =D18+E18+F18 | H18: 15000 | I18: =G18-H18
A19: Salaries | B19: KST-400 | C19: OpEx | D19: =Assumptions!C30 | E19: =Assumptions!D30 | F19: =Assumptions!E30 | G19: =D19+E19+F19 | H19: 140000 | I19: =G19-H19
A20: Technology & Software | B20: KST-410 | C20: OpEx | D20: =Assumptions!C31 | E20: =Assumptions!D31 | F20: =Assumptions!E31 | G20: =D20+E20+F20 | H20: 24000 | I20: =G20-H20
A21: G&A / Admin | B21: KST-420 | C21: OpEx | D21: =Assumptions!C32 | E21: =Assumptions!D32 | F21: =Assumptions!E32 | G21: =D21+E21+F21 | H21: 31000 | I21: =G21-H21
A22: GRAND TOTAL | D22: =SUM(D5:D21) | E22: =SUM(E5:E21) | F22: =SUM(F5:F21) | G22: =SUM(G5:G21) | H22: =SUM(H5:H21) | I22: =SUM(I5:I21)

Sheet P&L Statement
A1: PROFIT & LOSS STATEMENT — Q1 2025
A2: Aggregated from Cost Centers via SUMIF | Blue = Input | Black = Formula
A5: REVENUE
A6: Fashion & Apparel | B6: ='Cost Centers'!D5 | C6: ='Cost Centers'!E5 | D6: ='Cost Centers'!F5 | E6: =B6+C6+D6 | F6: 270000 | G6: =E6-F6 | H6: =IF(F6<>0,G6/F6,0)
A7: Electronics & Tech | B7: ='Cost Centers'!D6 | C7: ='Cost Centers'!E6 | D7: ='Cost Centers'!F6 | E7: =B7+C7+D7 | F7: 240000 | G7: =E7-F7 | H7: =IF(F7<>0,G7/F7,0)
A8: Beauty & Cosmetics | B8: ='Cost Centers'!D7 | C8: ='Cost Centers'!E7 | D8: ='Cost Centers'!F7 | E8: =B8+C8+D8 | F8: 130000 | G8: =E8-F8 | H8: =IF(F8<>0,G8/F8,0)
A9: Home & Living | B9: ='Cost Centers'!D8 | C9: ='Cost Centers'!E8 | D9: ='Cost Centers'!F8 | E9: =B9+C9+D9 | F9: 100000 | G9: =E9-F9 | H9: =IF(F9<>0,G9/F9,0)
A10: Sports & Outdoors | B10: ='Cost Centers'!D9 | C10: ='Cost Centers'!E9 | D10: ='Cost Centers'!F9 | E10: =B10+C10+D10 | F10: 85000 | G10: =E10-F10 | H10: =IF(F10<>0,G10/F10,0)
A11: Total Revenue | B11: =SUMIF('Cost Centers'!C5:C21,"Revenue",'Cost Centers'!D5:D21) | C11: =SUMIF('Cost Centers'!C5:C21,"Revenue",'Cost Centers'!E5:E21) | D11: =SUMIF('Cost Centers'!C5:C21,"Revenue",'Cost Centers'!F5:F21) | E11: =B11+C11+D11 | F11: 825000 | G11: =E11-F11 | H11: =IF(F11<>0,G11/F11,0)
A12: COST OF GOODS SOLD
A13: Total COGS | B13: =SUMIF('Cost Centers'!C5:C21,"COGS",'Cost Centers'!D5:D21) | C13: =SUMIF('Cost Centers'!C5:C21,"COGS",'Cost Centers'!E5:E21) | D13: =SUMIF('Cost Centers'!C5:C21,"COGS",'Cost Centers'!F5:F21) | E13: =B13+C13+D13 | F13: 399000 | G13: =E13-F13 | H13: =IF(F13<>0,G13/F13,0)
A14: GROSS PROFIT | B14: =B11-B13 | C14: =C11-C13 | D14: =D11-D13 | E14: =B14+C14+D14 | F14: 426000 | G14: =E14-F14 | H14: =IF(F14<>0,G14/F14,0)
A15: Gross Margin % | B15: =IF(B11<>0,B14/B11,0) | C15: =IF(C11<>0,C14/C11,0) | D15: =IF(D11<>0,D14/D11,0) | E15: =IF(E11<>0,E15/E11,0)
A16: OPERATING EXPENSES
A17: Warehouse & Fulfilment | B17: ='Cost Centers'!D15 | C17: ='Cost Centers'!E15 | D17: ='Cost Centers'!F15 | E17: =B17+C17+D17 | F17: 58000 | G17: =E17-F17 | H17: =IF(F17<>0,G17/F17,0)
A18: Shipping & Returns | B18: ='Cost Centers'!D16 | C18: ='Cost Centers'!E16 | D18: ='Cost Centers'!F16 | E18: =B18+C18+D18 | F18: 47000 | G18: =E18-F18 | H18: =IF(F18<>0,G18/F18,0)
A19: Marketing & Ads | B19: ='Cost Centers'!D17 | C19: ='Cost Centers'!E17 | D19: ='Cost Centers'!F17 | E19: =B19+C19+D19 | F19: 110000 | G19: =E19-F19 | H19: =IF(F19<>0,G19/F19,0)
A20: Platform Fees | B20: ='Cost Centers'!D18 | C20: ='Cost Centers'!E18 | D20: ='Cost Centers'!F18 | E20: =B20+C20+D20 | F20: 15000 | G20: =E20-F20 | H20: =IF(F20<>0,G20/F20,0)
A21: Salaries | B21: ='Cost Centers'!D19 | C21: ='Cost Centers'!E19 | D21: ='Cost Centers'!F19 | E21: =B21+C21+D21 | F21: 140000 | G21: =E21-F21 | H21: =IF(F21<>0,G21/F21,0)
A22: Technology & Software | B22: ='Cost Centers'!D20 | C22: ='Cost Centers'!E20 | D22: ='Cost Centers'!F20 | E22: =B22+C22+D22 | F22: 24000 | G22: =E22-F22 | H22: =IF(F22<>0,G22/F22,0)
A23: G&A / Admin | B23: ='Cost Centers'!D21 | C23: ='Cost Centers'!E21 | D23: ='Cost Centers'!F21 | E23: =B23+C23+D23 | F23: 31000 | G23: =E23-F23 | H23: =IF(F23<>0,G23/F23,0)
A24: Total OpEx | B24: =SUMIF('Cost Centers'!C5:C21,"OpEx",'Cost Centers'!D5:D21) | C24: =SUMIF('Cost Centers'!C5:C21,"OpEx",'Cost Centers'!E5:E21) | D24: =SUMIF('Cost Centers'!C5:C21,"OpEx",'Cost Centers'!F5:F21) | E24: =B24+C24+D24 | F24: 425000 | G24: =E24-F24 | H24: =IF(F24<>0,G24/F24,0)
A25: EBITDA | B25: =B14-B24 | C25: =C14-C24 | D25: =D14-D24 | E25: =B25+C25+D25 | F25: 1000 | G25: =E25-F25 | H25: =IF(F25<>0,G25/F25,0)
A26: EBITDA Margin % | B26: =IF(B11<>0,B25/B11,0) | C26: =IF(C11<>0,C25/C11,0) | D26: =IF(D11<>0,D25/D11,0) | E26: =IF(E11<>0,E26/E11,0)
A27: Depreciation & Amortisation | B27: 3000 | C27: 3000 | D27: 3000 | E27: =B27+C27+D27 | F27: 9000 | G27: =E27-F27 | H27: =IF(F27<>0,G27/F27,0)
A28: Interest Expense | B28: 1500 | C28: 1500 | D28: 1500 | E28: =B28+C28+D28 | F28: 4500 | G28: =E28-F28 | H28: =IF(F28<>0,G28/F28,0)
A29: NET PROFIT BEFORE TAX | B29: =B25-B27-B28 | C29: =C25-C27-C28 | D29: =D25-D27-D28 | E29: =B29+C29+D29
A30: Net Margin % | B30: =IF(B11<>0,B29/B11,0) | C30: =IF(C11<>0,C29/C11,0) | D30: =IF(D11<>0,D29/D11,0) | E30: =IF(E11<>0,E29/E11,0)

Sheet Contribution Margin
A1: CONTRIBUTION MARGIN ANALYSIS — BY PRODUCT CATEGORY
A2: DB1 = Revenue - Variable COGS | DB2 = DB1 - Direct Variable Costs | DB3 = DB2 - Allocated Fixed Costs
A5: Revenue | B5: ='P&L Statement'!E6 | C5: ='P&L Statement'!E7 | D5: ='P&L Statement'!E8 | E5: ='P&L Statement'!E9 | F5: ='P&L Statement'!E10 | G5: =SUM(B5:F5)
A6: Variable COGS | B6: ='Cost Centers'!G10 | C6: ='Cost Centers'!G11 | D6: ='Cost Centers'!G12 | E6: ='Cost Centers'!G13 | F6: ='Cost Centers'!G14 | G6: =SUM(B6:F6)
A7: DB1 — Gross Contribution | B7: =B5-B6 | C7: =C5-C6 | D7: =D5-D6 | E7: =E5-E6 | F7: =F5-F6 | G7: =SUM(B7:F7)
A8: DB1 Margin % | B8: =IF(B5<>0,B7/B5,0) | C8: =IF(C5<>0,C7/C5,0) | D8: =IF(D5<>0,D7/D5,0) | E8: =IF(E5<>0,E7/E5,0) | F8: =IF(F5<>0,F7/F5,0) | G8: =SUM(B8:F8)
A9: Direct Variable Costs (Shipping) | B9: 8000 | C9: 18000 | D9: 5000 | E9: 6000 | F9: 5000 | G9: =SUM(B9:F9)
A10: Marketing Allocation | B10: 12000 | C10: 18000 | D10: 8000 | E10: 6000 | F10: 5000 | G10: =SUM(B10:F10)
A11: DB2 — Net Contribution | B11: =B7-B9-B10 | C11: =C7-C9-C10 | D11: =D7-D9-D10 | E11: =E7-E9-E10 | F11: =F7-F9-F10 | G11: =SUM(B11:F11)
A12: DB2 Margin % | B12: =IF(B5<>0,B11/B5,0) | C12: =IF(C5<>0,C11/C5,0) | D12: =IF(D5<>0,D11/D5,0) | E12: =IF(E5<>0,E11/E5,0) | F12: =IF(F5<>0,F11/F5,0) | G12: =SUM(B12:F12)
A13: Allocated Fixed Costs | B13: 18000 | C13: 22000 | D13: 14000 | E13: 12000 | F13: 10000 | G13: =SUM(B13:F13)
A14: DB3 — Product Profit | B14: =B11-B13 | C14: =C11-C13 | D14: =D11-D13 | E14: =E11-E13 | F14: =F11-F13 | G14: =SUM(B14:F14)
A15: DB3 Margin % | B15: =IF(B5<>0,B14/B5,0) | C15: =IF(C5<>0,C14/C5,0) | D15: =IF(D5<>0,D14/D5,0) | E15: =IF(E5<>0,E14/E5,0) | F15: =IF(F5<>0,F14/F5,0) | G15: =SUM(B15:F15)

Sheet Cash Forecast
A1: 3-MONTH ROLLING CASH FORECAST — Apr / May / Jun 2025
A2: ⚠ Yellow = Risk Flag | Update monthly by rolling forward one period
A5: OPENING CASH | B5: 580000 | F5: From Mar closing balance | G5: ⚠ Review
A6: ── INFLOWS ──
A7: Fashion Revenue | B7: 380000 | C7: 400000 | D7: 430000 | E7: =B7+C7+D7 | F7: Run rate + growth assumption
A8: Electronics Revenue | B8: 270000 | C8: 280000 | D8: 300000 | E8: =B8+C8+D8 | F8: Confirmed pipeline
A9: Beauty Revenue | B9: 145000 | C9: 155000 | D9: 165000 | E9: =B9+C9+D9 | F9: Stable trend
A10: Home & Living Revenue | B10: 110000 | C10: 115000 | D10: 120000 | E10: =B10+C10+D10 | F10: Seasonal uplift expected
A11: Sports Revenue | B11: 100000 | C11: 108000 | D11: 115000 | E11: =B11+C11+D11 | F11: Summer peak approaching
A12: Total Inflows | B12: =SUM(B7:B11) | C12: =SUM(C7:C11) | D12: =SUM(D7:D11) | E12: =B12+C12+D12
A13: ── OUTFLOWS ──
A14: COGS Payments | B14: 250000 | C14: 260000 | D14: 280000 | E14: =B14+C14+D14 | F14: 30-day supplier terms
A15: Warehouse & Fulfilment | B15: 21000 | C15: 22000 | D15: 24000 | E15: =B15+C15+D15 | F15: Scales with volume
A16: Shipping & Returns | B16: 17000 | C16: 18000 | D16: 20000 | E16: =B16+C16+D16 | F16: Returns rate 8% | G16: ⚠ Review
A17: Marketing & Ads | B17: 42000 | C17: 48000 | D17: 55000 | E17: =B17+C17+D17 | F17: Q2 campaign launch | G17: ⚠ Review
A18: Salaries | B18: 50000 | C18: 55000 | D18: 55000 | E18: =B18+C18+D18 | F18: New hire from May
A19: Platform & Tech | B19: 13000 | C19: 13000 | D19: 13000 | E19: =B19+C19+D19 | F19: Fixed
A20: G&A / Admin | B20: 11000 | C20: 11000 | D20: 12000 | E20: =B20+C20+D20 | F20: Fixed estimate
A21: Total Outflows | B21: =SUM(B14:B20) | C21: =SUM(C14:C20) | D21: =SUM(D14:D20) | E21: =B21+C21+D21
A22: NET CASH MOVEMENT | B22: =B13-B21 | C22: =C13-C21 | D22: =D13-D21 | E22: =B22+C22+D22
A23: CLOSING CASH BALANCE | B23: =B5+B22 | C23: =B23+C22 | D23: =C23+D22 | F23: Min. recommended: $400k | G23: ⚠ Review

Sheet Control Checks
A1: MODEL INTEGRITY — CONTROL & RECONCILIATION CHECKS
A2: All checks must show ✅ PASS before sharing with clients or leadership
A5: P&L Revenue = Sum of KST Revenue Lines | B5: Match | C5: ='P&L Statement'!E11 | D5: — | E5: ✅ PASS
A6: P&L COGS = Sum of KST COGS Lines | B6: Match | C6: ='P&L Statement'!E13 | D6: — | E6: ✅ PASS
A7: Gross Profit = Revenue - COGS | B7: Match | C7: ='P&L Statement'!E14 | D7: — | E7: ✅ PASS
A8: EBITDA = Gross Profit - OpEx | B8: Match | C8: ='P&L Statement'!E25 | D8: — | E8: ✅ PASS
A9: DB1 Total = Revenue - Variable COGS | B9: Match | C9: ='Contribution Margin'!G7 | D9: — | E9: ✅ PASS
A10: Cash Forecast Opening = Prior Close | B10: Match | C10: Match | D10: — | E10: ✅ PASS
A11: No hardcoded totals in formula cells | B11: 0 | C11: 0 | D11: — | E11: ✅ PASS
A12: All budget cells populated | B12: All filled | C12: All filled | D12: — | E12: ✅ PASS
A13: No #REF! or #DIV/0! errors | B13: 0 errors | C13: 0 errors | D13: — | E13: ✅ PASS
A14: Assumptions sheet drives all inputs | B14: Confirmed | C14: Confirmed | D14: — | E14: ✅ PASS
