Workbook

Sheet R_STUDIO EINGABE
A1: Number | B1: NAME | C1: Code | D1: YEAR | E1: ESGC | F1: NET INCOM | G1: EBITD | H1: EQUITY | I1: DEBT | J1: REVENUE | K1: RoA | L1: RoE | M1: ASSET | N1: MCCAP | O1: MB
A2: =VLOOKUP(C2,'PORTFOLIO RAW'!C:D,2,FALSE) -> 323 | B2: VRTX.O | C2: 545310 | D2: 2007 | E2: 46.309199 | F2: -391279 | G2: -361535 | H2: 271295 | I2: 19997 | J2: 199012 | K2: -51.19 | L2: -100.69 | M2: 601477 | N2: 3086699 | O2: 18.81
A3: =VLOOKUP(C3,'PORTFOLIO RAW'!C:D,2,FALSE) -> 7 | B3: AMD.O | C3: 936365 | D3: 2007 | E3: 66.492963 | F3: -3379000 | G3: -1494000 | H3: 2990000 | I3: 5269000 | J3: 6013000 | K3: -25.46 | L3: -77.01 | M3: 11523000 | N3: 4545000 | O3: 2.47
A4: =VLOOKUP(C4,'PORTFOLIO RAW'!C:D,2,FALSE) -> 232 | B4: MYL.O | C4: 906931 | D4: 2007 | E4: 39.734872 | F4: -1538695 | G4: -991803 | H4: 3402356 | I4: 5256449 | J4: 2905007 | K4: -20.63 | L4: -73.45 | M4: 11334473 | N4: 4279515 | O4: 1.12
A5: =VLOOKUP(C5,'PORTFOLIO RAW'!C:D,2,FALSE) -> 270 | B5: PHM | C5: 912518 | D5: 2007 | E5: 28.390501 | F5: -2274417 | G5: -1908031 | H5: 4320193 | I5: 4104542 | J5: 9263094 | K5: -17.74 | L5: -41.4 | M5: 10119797 | N5: 2709821 | O5: 0.95
A6: =VLOOKUP(C6,'PORTFOLIO RAW'!C:D,2,FALSE) -> 201 | B6: LEN | C6: 912219 | D6: 2007 | E6: 32.451224 | F6: -1941081 | G6: -2439945 | H6: 3822119 | I6: 2836873 | J6: 10186781 | K6: -17.67 | L6: -40.76 | M6: 8361149 | N6: 2860378 | O6: 1.07
A7: =VLOOKUP(C7,'PORTFOLIO RAW'!C:D,2,FALSE) -> 236 | B7: NEM | C7: 912160 | D7: 2007 | E7: 40.131477 | F7: -963000 | G7: 448000 | H7: 7548000 | I7: 2938000 | J7: 5526000 | K7: -12.38 | L7: -22.34 | M7: 14571000 | N7: 22105146 | O7: 2.81
A8: =VLOOKUP(C8,'PORTFOLIO RAW'!C:D,2,FALSE) -> 156 | B8: HRB | C8: 905596 | D8: 2007 | E8: 52.247727 | F8: -433653 | G8: 832933 | H8: 1414499 | I8: 2197293 | J8: 4021274 | K8: -5.98 | L8: -24.35 | M8: 7499493 | N8: 6002173 | O8: 6.84
A9: =VLOOKUP(C9,'PORTFOLIO RAW'!C:D,2,FALSE) -> 101 | B9: DHI | C9: 325922 | D9: 2007 | E9: 44.898601 | F9: -712500 | G9: -863200 | H9: 5586900 | I9: 4376800 | J9: 11296500 | K9: -5.55 | L9: -11.84 | M9: 10692500 | N9: 4147423 | O9: 0.79
A10: =VLOOKUP(C10,'PORTFOLIO RAW'!C:D,2,FALSE) -> 321 | B10: VRSN.O | C10: 674693 | D10: 2007 | E10: 32.069426 | F10: -140859 | G10: 121127 | H10: 1527865 | I10: 1265296 | J10: 1496289 | K10: -3.36 | L10: -7.15 | M10: 3792418 | N10: 8381364 | O10: 5.44
A11: =VLOOKUP(C11,'PORTFOLIO RAW'!C:D,2,FALSE) -> 187 | B11: JCI | C11: 545615 | D11: 2007 | E11: 77.544271 | F11: -2519000 | G11: -717000 | H11: 15624000 | I11: 4456000 | J11: 18781000 | K11: -3.3 | L11: -6.83 | M11: 31706000 | N11: 19678368 | O11: 1.42
A12: =VLOOKUP(C12,'PORTFOLIO RAW'!C:D,2,FALSE) -> 117 | B12: ETFC.O | C12: 883488 | D12: 2007 | E12: 49.936486 | F12: -1441754 | G12: -1887044 | H12: 2829065 | I12: 19401895 | J12: 2427286 | K12: -2.43 | L12: -41.04 | M12: 56295703 | N12: 1636187 | O12: 2.06
A13: =VLOOKUP(C13,'PORTFOLIO RAW'!C:D,2,FALSE) -> 223 | B13: MU.O | C13: 999506 | D13: 2007 | E13: 30.696688 | F13: -320000 | G13: 1590000 | H13: 7752000 | I13: 2544000 | J13: 5688000 | K13: -2.18 | L13: -4.03 | M13: 14753000 | N13: 5494775 | O13: 1.32
... A18: =VLOOKUP(C18,'PORTFOLIO RAW'!C:D,2,FALSE) -> 172 | B18: HBAN.O | C18: 951068 | D18: 2007 | E18: 36.710451 | F18: 75169 | G18: 427006 | H18: 5949140 | I18: 9798547 | J18: 3419566 | K18: 0.63 | L18: 1.68 | M18: 54697468 | N18: 5406022 | O18: 1.09
A19: =VLOOKUP(C19,'PORTFOLIO RAW'!C:D,2,FALSE) -> 263 | B19: PFG.O | C19: 14698C | D19: 2007 | E19: 34.242672 | F19: 807100 | G19: 1187600 | H19: 6854600 | I19: 1689600 | J19: 10800400 | K19: 0.63 | L19: 12.16 | M19: 154513700 | N19: 17836444 | O19: 2.32
A20: =VLOOKUP(C20,'PORTFOLIO RAW'!C:D,2,FALSE) -> 200 | B20: LEG | C20: 906487 | D20: 2007 | E20: 31.697727 | F20: 51000 | G20: 370400 | H20: 2132700 | I20: 1159300 | J20: 4306400 | K20: 0.65 | L20: -0.5 | M20: 4072500 | N20: 2942128 | O20: 1.59
A21: =VLOOKUP(C21,'PORTFOLIO RAW'!C:D,2,FALSE) -> 94 | B21: COO | C21: 938928 | D21: 2007 | E21: 42.179545 | F21: -11192 | G21: 126966 | H21: 1423589 | I21: 876630 | J21: 950641 | K21: 0.66 | L21: -0.8 | M21: 2540256 | N21: 1694116 | O21: 1.64
A22: =VLOOKUP(C22,'PORTFOLIO RAW'!C:D,2,FALSE) -> 81 | B22: C | C22: 741344 | D22: 2007 | E22: 42.623932 | F22: 3581000 | G22: 19813000 | H22: 113598000 | I22: 810759000 | J22: 159229000 | K22: 0.72 | L22: 3.08 | M22: 2187631000 | N22: 147041024 | O22: 2.07
A23: =VLOOKUP(C23,'PORTFOLIO RAW'!C:D,2,FALSE) -> 202 | B23: LNC | C23: 912402 | D23: 2007 | E23: 33.773253 | F23: 1321000 | G23: 2168000 | H23: 11579000 | I23: 5168000 | J23: 10594000 | K23: 0.81 | L23: 11.35 | M23: 191435000 | N23: 15383663 | O23: 1.52
A24: =VLOOKUP(C24,'PORTFOLIO RAW'!C:D,2,FALSE) -> 160 | B24: HIG | C24: 867871 | D24: 2007 | E24: 34.491325 | F24: 2949000 | G24: 5062000 | H24: 19563000 | I24: 5316000 | J24: 26399000 | K24: 0.91 | L24: 15.78 | M24: 360053000 | N24: 27363905 | O24: 1.47
A25: =VLOOKUP(C25,'PORTFOLIO RAW'!C:D,2,FALSE) -> 220 | B25: MET | C25: 286738 | D25: 2007 | E25: 29.15109 | F25: 4180000 | G25: 6543000 | H25: 32108000 | I25: 20501000 | J25: 51890000 | K25: 0.93 | L25: 12.9 | M25: 558562000 | N25: 44934748 | O25: 1.58
A26: =VLOOKUP(C26,'PORTFOLIO RAW'!C:D,2,FALSE) -> 25 | B26: AMP | C26: 31604H | D26: 2007 | E26: 54.302887 | F26: 814000 | G26: 2110000 | H26: 7810000 | I26: 2018000 | J26: 8909000 | K26: 0.99 | L26: 10.35 | M26: 109110000 | N26: 12551184 | O26: 1.85
A27: =VLOOKUP(C27,'PORTFOLIO RAW'!C:D,2,FALSE) -> 267 | B27: PRU | C27: 14861V | D27: 2007 | E27: 38.867331 | F27: 3704000 | G27: 6591000 | H27: 23057000 | I27: 47511000 | J27: 36034000 | K27: 1.02 | L27: 16.62 | M27: 485814000 | N27: 41809092 | O27: 1.86
A28: =VLOOKUP(C28,'PORTFOLIO RAW'!C:D,2,FALSE) -> 276 | B28: RF | C28: 951051 | D28: 2007 | E28: 41.784759 | F28: 1393163 | G28: 2620943 | H28: 19823029 | I28: 22444912 | J28: 10930498 | K28: 1.13 | L28: 6.17 | M28: 141041717 | N28: 16404491 | O28: 1.11
A29: =VLOOKUP(C29,'PORTFOLIO RAW'!C:D,2,FALSE) -> 296 | B29: STT | C29: 951052 | D29: 2007 | E29: 42.121227 | F29: 1261000 | G29: 2447000 | H29: 11299000 | I29: 24264000 | J29: 11818000 | K29: 1.13 | L29: 13.59 | M29: 142543000 | N29: 31366261 | O29: 2.29
A30: =VLOOKUP(C30,'PORTFOLIO RAW'!C:D,2,FALSE) -> 348 | B30: ZION.O | C30: 951584 | D30: 2007 | E30: 44.106225 | F30: 479422 | G30: 935352 | H30: 5052800 | I30: 10056547 | J30: 3775878 | K30: 1.19 | L30: 9.78 | M30: 52736159 | N30: 5001270 | O30: 1.51
A31: =VLOOKUP(C31,'PORTFOLIO RAW'!C:D,2,FALSE) -> 23 | B31: AIG | C31: 916305 | D31: 2007 | E31: 29.592648 | F31: 6200000 | G31: 21460000 | H31: 91513000 | I31: 176049000 | J31: 126251000 | K31: 1.23 | L31: 6.77 | M31: 1060505000 | N31: 147474750 | O31: 1.88
A32: =VLOOKUP(C32,'PORTFOLIO RAW'!C:D,2,FALSE) -> 254 | B32: PBCT.O | C32: 517465 | D32: 2007 | E32: 38.545229 | F32: 150700 | G32: 249900 | H32: 4445400 | I32: 65400 | J32: 892400 | K32: 1.28 | L32: 5.21 | M32: 13554800 | N32: 5309740 | O32: 1.18
A33: =VLOOKUP(C33,'PORTFOLIO RAW'!C:D,2,FALSE) -> 298 | B33: STI | C33: 922725 | D33: 2007 | E33: 44.531371 | F33: 1603740 | G33: 4033944 | H33: 17552518 | I33: 35157328 | J33: 13394224 | K33: 1.29 | L33: 9.2 | M33: 179573933 | N33: 21772214 | O33: 1.56
A34: =VLOOKUP(C34,'PORTFOLIO RAW'!C:D,2,FALSE) -> 47 | B34: BAC | C34: 923937 | D34: 2007 | E34: 44.270765 | F34: 14800000 | G34: 31451000 | H34: 142394000 | I34: 610032000 | J34: 119190000 | K34: 1.33 | L34: 10.77 | M34: 1715746000 | N34: 183107152 | O34: 1.58
A35: =VLOOKUP(C35,'PORTFOLIO RAW'!C:D,2,FALSE) -> 243 | B35: NTRS.O | C35: 905861 | D35: 2007 | E35: 62.034574 | F35: 726900 | G35: 1351800 | H35: 4509100 | I35: 8950800 | J35: 5393000 | K35: 1.34 | L35: 17.2 | M35: 67611200 | N35: 16894237 | O35: 3.19
A36: =VLOOKUP(C36,'PORTFOLIO RAW'!C:D,2,FALSE) -> 188 | B36: JPM | C36: 902242 | D36: 2007 | E36: 56.935394 | F36: 15365000 | G36: 31838000 | H36: 123221000 | I36: 431839000 | J36: 116353000 | K36: 1.35 | L36: 12.86 | M36: 1562147000 | N36: 146987010 | O36: 1.29
A37: =VLOOKUP(C37,'PORTFOLIO RAW'!C:D,2,FALSE) -> 140 | B37: FITB.O | C37: 997198 | D37: 2007 | E37: 26.93842 | F37: 1075000 | G37: 2429000 | H37: 9152000 | I37: 22031000 | J37: 8494000 | K37: 1.44 | L37: 11.22 | M37: 110962000 | N37: 13385532 | O37: 2.07
A38: =VLOOKUP(C38,'PORTFOLIO RAW'!C:D,2,FALSE) -> 191 | B38: KEY | C38: 916130 | D38: 2007 | E38: 28.776327 | F38: 941000 | G38: 2341000 | H38: 7746000 | I38: 22337000 | J38: 7609000 | K38: 1.44 | L38: 11.9 | M38: 99983000 | N38: 9117196 | O38: 1.72
A39: =VLOOKUP(C39,'PORTFOLIO RAW'!C:D,2,FALSE) -> 315 | B39: UPS | C39: 277487 | D39: 2007 | E39: 30.867602 | F39: 382000 | G39: 2422000 | H39: 12183000 | I39: 11018000 | J39: 49692000 | K39: 1.5 | L39: 2.76 | M39: 39042000 | N39: 73619520 | O39: 12.57
... A50: =VLOOKUP(C50,'PORTFOLIO RAW'!C:D,2,FALSE) -> 24 | B50: AMT | C50: 680902 | D50: 2007 | E50: 33.311468 | F50: 56316 | G50: 911592 | H50: 3022092 | I50: 4285284 | J50: 1456594 | K50: 2.66 | L50: 1.52 | M50: 7650603 | N50: 17018700 | O50: 5.68
A51: =VLOOKUP(C51,'PORTFOLIO RAW'!C:D,2,FALSE) -> 38 | B51: AIZ | C51: 28341F | D51: 2007 | E51: 30.024258 | F51: 653746 | G51: 1106527 | H51: 4065519 | I51: 993023 | J51: 8441701 | K51: 2.67 | L51: 16.82 | M51: 26750316 | N51: 7881356 | O51: 1.51
A52: =VLOOKUP(C52,'PORTFOLIO RAW'!C:D,2,FALSE) -> 180 | B52: IPG | C52: 923465 | D52: 2007 | E52: 39.540937 | F52: 131300 | G52: 649600 | H52: 1807200 | I52: 2349200 | J52: 6554200 | K52: 2.75 | L52: 8.15 | M52: 11978200 | N52: 3821432 | O52: 2.74
A53: =VLOOKUP(C53,'PORTFOLIO RAW'!C:D,2,FALSE) -> 33 | B53: AIV | C53: 132808 | D53: 2007 | E53: 48.750242 | F53: -114070 | G53: 894607 | H53: 1031645 | I53: 7531782 | J53: 1721184 | K53: 2.91 | L53: -2.83 | M53: 10597547 | N53: 3338615 | O53: 4.22
A54: =VLOOKUP(C54,'PORTFOLIO RAW'!C:D,2,FALSE) -> 76 | B54: CI | C54: 912278 | D54: 2007 | E54: 23.944604 | F54: 1115000 | G54: 1926000 | H54: 4620000 | I54: 1793000 | J54: 17663000 | K54: 2.92 | L54: 25.47 | M54: 39271000 | N54: 15022263 | O54: 3.18
A55: =VLOOKUP(C55,'PORTFOLIO RAW'!C:D,2,FALSE) -> 16 | B55: ALL | C55: 322677 | D55: 2007 | E55: 43.513543 | F55: 4636000 | G55: 6917000 | H55: 20963000 | I55: 5640000 | J55: 36639000 | K55: 3.1 | L55: 22.76 | M55: 155941000 | N55: 29405490 | O55: 1.56
A56: =VLOOKUP(C56,'PORTFOLIO RAW'!C:D,2,FALSE) -> 239 | B56: NI | C56: 906176 | D56: 2007 | E56: 49.03307 | F56: 312000 | G56: 1434600 | H56: 5076600 | I56: 6689300 | J56: 7939800 | K56: 3.22 | L56: 6.37 | M56: 18004800 | N56: 5179104 | O56: 1.05
A57: =VLOOKUP(C57,'PORTFOLIO RAW'!C:D,2,FALSE) -> 114 | B57: DUK | C57: 904383 | D57: 2007 | E57: 62.591863 | F57: 1522000 | G57: 4456000 | H57: 21199000 | I57: 11766000 | J57: 12720000 | K57: 3.23 | L57: 6.34 | M57: 49704000 | N57: 25454540 | O57: 1.11
A58: =VLOOKUP(C58,'PORTFOLIO RAW'!C:D,2,FALSE) -> 8 | B58: AES | C58: 545101 | D58: 2007 | E58: 50.503558 | F58: 495000 | G58: 4268000 | H58: 3164000 | I58: 17994000 | J58: 13588000 | K58: 3.32 | L58: -3.06 | M58: 33806000 | N58: 14338569 | O58: 4.08
A59: =VLOOKUP(C59,'PORTFOLIO RAW'!C:D,2,FALSE) -> 208 | B59: MAC | C59: 357366 | D59: 2007 | E59: 47.910953 | F59: 73266 | G59: 539443 | H59: 1312634 | I59: 5762958 | J59: 896368 | K59: 3.42 | L59: 5.02 | M59: 8121134 | N59: 5138491 | O59: 4.64
A60: =VLOOKUP(C60,'PORTFOLIO RAW'!C:D,2,FALSE) -> 341 | B60: WLTW.O | C60: 13967H | D60: 2007 | E60: 59.819356 | F60: 409000 | G60: 686000 | H60: 1347000 | I60: 1250000 | J60: 2578000 | K60: 3.44 | L60: 29.2 | M60: 12948000 | N60: 5433261 | O60: 4.22
A61: =VLOOKUP(C61,'PORTFOLIO RAW'!C:D,2,FALSE) -> 322 | B61: VZ | C61: 945384 | D61: 2007 | E61: 34.060005 | F61: 5510000 | G61: 30166000 | H61: 50581000 | I61: 31157000 | J61: 93469000 | K61: 3.57 | L61: 11.14 | M61: 186959000 | N61: 125688446 | O61: 2.51
A62: =VLOOKUP(C62,'PORTFOLIO RAW'!C:D,2,FALSE) -> 88 | B62: CMCSA.O | C62: 981550 | D62: 2007 | E62: 36.318622 | F62: 2587000 | G62: 12909000 | H62: 41340000 | I62: 31323000 | J62: 30895000 | K62: 3.64 | L62: 6.27 | M62: 113417000 | N62: 54981499 | O62: 1.74
A63: =VLOOKUP(C63,'PORTFOLIO RAW'!C:D,2,FALSE) -> 258 | B63: PNW | C63: 902607 | D63: 2007 | E63: 53.769161 | F63: 298780 | G63: 1021958 | H63: 3531611 | I63: 3631559 | J63: 3523620 | K63: 3.67 | L63: 8.8 | M63: 11243712 | N63: 4261610 | O63: 1.14
A64: =VLOOKUP(C64,'PORTFOLIO RAW'!C:D,2,FALSE) -> 116 | B64: DXC | C64: 916091 | D64: 2007 | E64: 33.630282 | F64: 388800 | G64: 1944200 | H64: 5885500 | I64: 1505900 | J64: 14856600 | K64: 3.76 | L64: 6.28 | M64: 13730500 | N64: 8574041 | O64: 1.77
A65: =VLOOKUP(C65,'PORTFOLIO RAW'!C:D,2,FALSE) -> 154 | B65: GL | C65: 993394 | D65: 2007 | E65: 36.168975 | F65: 527535 | G65: 868669 | H65: 3324627 | I65: 924491 | J65: 3486697 | K65: 3.78 | L65: 15.55 | M65: 15241428 | N65: 5579574 | O65: 1.72
A66: =VLOOKUP(C66,'PORTFOLIO RAW'!C:D,2,FALSE) -> 69 | B66: CBS | C66: 32480Q | D66: 2007 | E66: 49.025617 | F66: 1230800 | G66: 3159600 | H66: 21472400 | I66: 7087700 | J66: 14072900 | K66: 3.86 | L66: 5.54 | M66: 40430200 | N66: 18309275 | O66: 1.08
A67: =VLOOKUP(C67,'PORTFOLIO RAW'!C:D,2,FALSE) -> 334 | B67: WEC | C67: 902335 | D67: 2007 | E67: 76.42645 | F67: 336500 | G67: 1015400 | H67: 3099200 | I67: 4426000 | J67: 4237800 | K67: 3.89 | L67: 11.21 | M67: 11720300 | N67: 5696297 | O67: 1.69
A68: =VLOOKUP(C68,'PORTFOLIO RAW'!C:D,2,FALSE) -> 343 | B68: XEL.O | C68: 905010 | D68: 2007 | E68: 55.295053 | F68: 573107 | G68: 2245460 | H68: 6301002 | I68: 8068255 | J68: 10034170 | K68: 3.91 | L68: 9.46 | M68: 23184727 | N68: 9677626 | O68: 1.46
A69: =VLOOKUP(C69,'PORTFOLIO RAW'!C:D,2,FALSE) -> 311 | B69: TSN | C69: 906643 | D69: 2007 | E69: 54.259199 | F69: 268000 | G69: 1156000 | H69: 4731000 | I69: 2779000 | J69: 26900000 | K69: 3.92 | L69: 5.84 | M69: 10227000 | N69: 5788608 | O69: 1.37
A70: =VLOOKUP(C70,'PORTFOLIO RAW'!C:D,2,FALSE) -> 31 | B70: AON | C70: 922817 | D70: 2007 | E70: 37.492183 | F70: 864000 | G70: 1356000 | H70: 6121000 | I70: 2145000 | J70: 7473000 | K70: 3.96 | L70: 15.36 | M70: 24418000 | N70: 14512067 | O70: 2.09
A71: =VLOOKUP(C71,'PORTFOLIO RAW'!C:D,2,FALSE) -> 133 | B71: EXPE.O | C71: 31412T | D71: 2007 | E71: 27.230846 | F71: 295864 | G71: 689589 | H71: 4818081 | I71: 1085000 | J71: 2665332 | K71: 3.99 | L71: 5.52 | M71: 8295422 | N71: 9014517 | O71: 1.8
A72: =VLOOKUP(C72,'PORTFOLIO RAW'!C:D,2,FALSE) -> 155 | B72: GS | C72: 696738 | D72: 2007 | E72: 46.4836 | F72: 11407000 | G72: 60752000 | H72: 39700000 | I72: 553911000 | J72: 87968000 | K72: 3.99 | L72: 31.52 | M72: 1115619000 | N72: 84016167 | O72: 2.08
A73: =VLOOKUP(C73,'PORTFOLIO RAW'!C:D,2,FALSE) -> 306 | B73: TMO | C73: 906394 | D73: 2007 | E73: 35.64776 | F73: 779600 | G73: 1775300 | H73: 14488300 | I73: 2195200 | J73: 9746400 | K73: 4.01 | L73: 5.36 | M73: 21207400 | N73: 23950926 | O73: 1.69
A74: =VLOOKUP(C74,'PORTFOLIO RAW'!C:D,2,FALSE) -> 21 | B74: AEP | C74: 905425 | D74: 2007 | E74: 39.4155 | F74: 1144000 | G74: 3981000 | H74: 10079000 | I74: 16025000 | J74: 13380000 | K74: 4.12 | L74: 11.17 | M74: 40366000 | N74: 18643867 | O74: 1.81
A75: =VLOOKUP(C75,'PORTFOLIO RAW'!C:D,2,FALSE) -> 26 | B75: ABC | C75: 154680 | D75: 2007 | E75: 33.994805 | F75: 493768 | G75: 965100 | H75: 3099720 | I75: 1227774 | J75: 66074312 | K75: 4.13 | L75: 12.96 | M75: 12310064 | N75: 7604394 | O75: 2.65
A76: =VLOOKUP(C76,'PORTFOLIO RAW'!C:D,2,FALSE) -> 310 | B76: TRV | C76: 933974 | D76: 2007 | E76: 32.693476 | F76: 4597000 | G76: 7373000 | H76: 25885000 | I76: 6242000 | J76: 26087000 | K76: 4.24 | L76: 18.07 | M76: 114017000 | N76: 33775640 | O76: 1.3
A77: =VLOOKUP(C77,'PORTFOLIO RAW'!C:D,2,FALSE) -> 338 | B77: WY | C77: 905818 | D77: 2007 | E77: 69.279611 | F77: 51000 | G77: 1462000 | H77: 7981000 | I77: 7395000 | J77: 16308000 | K77: 4.29 | L77: 9.26 | M77: 23806000 | N77: 15451957 | O77: 1.92
A78: =VLOOKUP(C78,'PORTFOLIO RAW'!C:D,2,FALSE) -> 287 | B78: SRE | C78: 902103 | D78: 2007 | E78: 26.263702 | F78: 1125000 | G78: 2517000 | H78: 8339000 | I78: 5638000 | J78: 11438000 | K78: 4.32 | L78: 13.87 | M78: 30091000 | N78: 16150680 | O78: 1.87
A79: =VLOOKUP(C79,'PORTFOLIO RAW'!C:D,2,FALSE) -> 217 | B79: MCK | C79: 134784 | D79: 2007 | E79: 62.667532 | F79: 963000 | G79: 1668000 | H79: 6298000 | I79: 1958000 | J79: 92977000 | K79: 4.35 | L79: 14.91 | M79: 23968000 | N79: 19325450 | O79: 2.72
A80: =VLOOKUP(C80,'PORTFOLIO RAW'!C:D,2,FALSE) -> 41 | B80: ADP.O | C80: 912669 | D80: 2007 | E80: 37.687438 | F80: 1021200 | G80: 2007200 | H80: 5147900 | I80: 43700 | J80: 7800000 | K80: 4.43 | L80: 20.41 | M80: 26647100 | N80: 23859174 | O80: 4.82
A81: =VLOOKUP(C81,'PORTFOLIO RAW'!C:D,2,FALSE) -> 209 | B81: M | C81: 546814 | D81: 2007 | E81: 49.370286 | F81: 909000 | G81: 3203000 | H81: 9907000 | I81: 9753000 | J81: 26313000 | K81: 4.43 | L81: 8.06 | M81: 27789000 | N81: 10857639 | O81: 1.49
A82: =VLOOKUP(C82,'PORTFOLIO RAW'!C:D,2,FALSE) -> 20 | B82: AEE | C82: 670942 | D82: 2007 | E82: 53.852774 | F82: 618000 | G82: 2176000 | H82: 6752000 | I82: 7400000 | J82: 7546000 | K82: 4.47 | L82: 9.27 | M82: 20728000 | N82: 11291943 | O82: 1.63
A83: =VLOOKUP(C83,'PORTFOLIO RAW'!C:D,2,FALSE) -> 122 | B83: EIX | C83: 902324 | D83: 2007 | E83: 47.190505 | F83: 1100000 | G83: 3847000 | H83: 8444000 | I83: 9746000 | J83: 13113000 | K83: 4.5 | L83: 13.62 | M83: 37562000 | N83: 17388544 | O83: 2.19
... A94: =VLOOKUP(C94,'PORTFOLIO RAW'!C:D,2,FALSE) -> 289 | B94: SPG | C94: 357834 | D94: 2007 | E94: 57.831471 | F94: 464229 | G94: 2385640 | H94: 2833974 | I94: 17218674 | J94: 3650799 | K94: 4.84 | L94: 14.72 | M94: 23603061 | N94: 19372758 | O94: 7.85
A95: =VLOOKUP(C95,'PORTFOLIO RAW'!C:D,2,FALSE) -> 227 | B95: MDLZ.O | C95: 13967E | D95: 2007 | E95: 45.843293 | F95: 2590000 | G95: 5237000 | H95: 27295000 | I95: 21009000 | J95: 37241000 | K95: 4.85 | L95: 9.27 | M95: 67993000 | N95: 50047164 | O95: 2
A96: =VLOOKUP(C96,'PORTFOLIO RAW'!C:D,2,FALSE) -> 326 | B96: VNO | C96: 912146 | D96: 2007 | E96: 28.920828 | F96: 453013 | G96: 1663602 | H96: 5266849 | I96: 13022166 | J96: 3270629 | K96: 4.86 | L96: 9.69 | M96: 22474426 | N96: 13463087 | O96: 3.09
A97: =VLOOKUP(C97,'PORTFOLIO RAW'!C:D,2,FALSE) -> 150 | B97: GE | C97: 906150 | D97: 2007 | E97: 40.822573 | F97: 22468000 | G97: 62949000 | H97: 115559000 | I97: 514116000 | J97: 169719000 | K97: 5.05 | L97: 19.49 | M97: 795337000 | N97: 370240295 | O97: 3.66
A98: =VLOOKUP(C98,'PORTFOLIO RAW'!C:D,2,FALSE) -> 256 | B98: PKI | C98: 912157 | D98: 2007 | E98: 57.782716 | F98: 133834 | G98: 244611 | H98: 1575277 | I98: 516640 | J98: 1787331 | K98: 5.2 | L98: 8.35 | M98: 2942137 | N98: 3059562 | O98: 2.2
A99: =VLOOKUP(C99,'PORTFOLIO RAW'!C:D,2,FALSE) -> 39 | B99: T | C99: 945388 | D99: 2007 | E99: 37.742947 | F99: 11951000 | G99: 42596000 | H99: 115367000 | I99: 64115000 | J99: 118928000 | K99: 5.21 | L99: 10.35 | M99: 275644000 | N99: 251169741 | O99: 2.22
A100: =VLOOKUP(C100,'PORTFOLIO RAW'!C:D,2,FALSE) -> 115 | B100: DRE | C100: 513260 | D100: 2007 | E100: 56.707332 | F100: 97421 | G100: 579590 | H100: 2006033 | I100: 4316460 | J100: 893846 | K100: 5.22 | L100: 11.98 | M100: 7661981 | N100: 3812244 | O100: 2.28
A101: =VLOOKUP(C101,'PORTFOLIO RAW'!C:D,2,FALSE) -> 183 | B101: IRM | C101: 894720 | D101: 2007 | E101: 40.133552 | F101: 153094 | G101: 700911 | H101: 1795455 | I101: 3266288 | J101: 2730035 | K101: 5.24 | L101: 9.14 | M101: 6307921 | N101: 7371037 | O101: 3.19
A102: =VLOOKUP(C102,'PORTFOLIO RAW'!C:D,2,FALSE) -> 78 | B102: CINF.O | C102: 951545 | D102: 2007 | E102: 40.827675 | F102: 855000 | G102: 1280000 | H102: 3778000 | I102: 860000 | J102: 4273000 | K102: 5.25 | L102: 23.73 | M102: 16637000 | N102: 6563597 | O102: 1.98
A103: =VLOOKUP(C103,'PORTFOLIO RAW'!C:D,2,FALSE) -> 292 | B103: SO | C103: 902325 | D103: 2007 | E103: 40.551953 | F103: 1734000 | G103: 4907000 | H103: 12385000 | I103: 16593000 | J103: 15353000 | K103: 5.27 | L103: 14.6 | M103: 44879000 | N103: 29589500 | O103: 2.26
A104: =VLOOKUP(C104,'PORTFOLIO RAW'!C:D,2,FALSE) -> 73 | B104: SCHW.K | C104: 755741 | D104: 2007 | E104: 48.507494 | F104: 1120000 | G104: 2065000 | H104: 3732000 | I104: 899000 | J104: 5617000 | K104: 5.39 | L104: 55.08 | M104: 42032000 | N104: 29658865 | O104: 7.07
A105: =VLOOKUP(C105,'PORTFOLIO RAW'!C:D,2,FALSE) -> 142 | B105: FISV.O | C105: 741123 | D105: 2007 | E105: 30.45664 | F105: 439000 | G105: 930000 | H105: 2467000 | I105: 5405000 | J105: 3922000 | K105: 5.4 | L105: 17.94 | M105: 11846000 | N105: 9161399 | O105: 3.3
A106: =VLOOKUP(C106,'PORTFOLIO RAW'!C:D,2,FALSE) -> 229 | B106: MS | C106: 327998 | D106: 2007 | E106: 37.300942 | F106: 2495000 | G106: 61218000 | H106: 30169000 | I106: 415731000 | J106: 85405000 | K106: 5.47 | L106: 9.75 | M106: 1045409000 | N106: 56099544 | O106: 2.28
A107: =VLOOKUP(C107,'PORTFOLIO RAW'!C:D,2,FALSE) -> 52 | B107: BRKb | C107: 874227 | D107: 2007 | E107: 27.944171 | F107: 13213000 | G107: 24478000 | H107: 120733000 | I107: 33826000 | J107: 118245000 | K107: 5.54 | L107: 11.53 | M107: 273342000 | N107: 219153329 | O107: 1.48
... A117: =VLOOKUP(C117,'PORTFOLIO RAW'!C:D,2,FALSE) -> 230 | B117: MOS | C117: 771767 | D117: 2007 | E117: 16.143386 | F117: 419700 | G117: 1075600 | H117: 4183900 | I117: 2360500 | J117: 5773700 | K117: 5.94 | L117: 10.88 | M117: 9163600 | N117: 41586513 | O117: 3.11
A118: =VLOOKUP(C118,'PORTFOLIO RAW'!C:D,2,FALSE) -> 84 | B118: CME.O | C118: 26393N | D118: 2007 | E118: 34.450369 | F118: 658533 | G118: 1367410 | H118: 12305637 | I118: 3026461 | J118: 1756101 | K118: 5.98 | L118: 9.53 | M118: 20306197 | N118: 36550766 | O118: 2.41
A119: =VLOOKUP(C119,'PORTFOLIO RAW'!C:D,2,FALSE) -> 300 | B119: SNPS.O | C119: 325059 | D119: 2007 | E119: 37.878247 | F119: 130491 | G119: 271166 | H119: 1436393 | I119: 0 | J119: 1212469 | K119: 6 | L119: 10.04 | M119: 2400695 | N119: 3795244 | O119: 2.66
A120: =VLOOKUP(C120,'PORTFOLIO RAW'!C:D,2,FALSE) -> 96 | B120: COST.O | C120: 312385 | D120: 2007 | E120: 42.723698 | F120: 1082772 | G120: 2303334 | H120: 8623341 | I120: 2221715 | J120: 64908891 | K120: 6.06 | L120: 12.19 | M120: 19596523 | N120: 30486027 | O120: 2.91
A121: =VLOOKUP(C121,'PORTFOLIO RAW'!C:D,2,FALSE) -> 179 | B121: IP | C121: 904069 | D121: 2007 | E121: 76.503504 | F121: 1204000 | G121: 3191000 | H121: 8672000 | I121: 6620000 | J121: 21890000 | K121: 6.06 | L121: 14.04 | M121: 24159000 | N121: 13767976 | O121: 1.77
A122: =VLOOKUP(C122,'PORTFOLIO RAW'!C:D,2,FALSE) -> 93 | B122: STZ | C122: 937083 | D122: 2007 | E122: 26.191086 | F122: 327000 | G122: 898800 | H122: 3417500 | I122: 4185500 | J122: 5216400 | K122: 6.08 | L122: 10.51 | M122: 9381600 | N122: 5552310 | O122: 15.03
A123: =VLOOKUP(C123,'PORTFOLIO RAW'!C:D,2,FALSE) -> 118 | B123: EMN | C123: 357922 | D123: 2007 | E123: 41.201224 | F123: 311000 | G123: 889000 | H123: 2082000 | I123: 1613000 | J123: 6830000 | K123: 6.09 | L123: 14.59 | M123: 5964000 | N123: 4867061 | O123: 2.7
A124: =VLOOKUP(C124,'PORTFOLIO RAW'!C:D,2,FALSE) -> 244 | B124: NOC | C124: 905809 | D124: 2007 | E124: 31.790186 | F124: 1766000 | G124: 3752000 | H124: 17687000 | I124: 4405000 | J124: 32018000 | K124: 6.17 | L124: 10.3 | M124: 33308000 | N124: 26567310 | O124: 1.56
A125: =VLOOKUP(C125,'PORTFOLIO RAW'!C:D,2,FALSE) -> 98 | B125: CSX.O | C125: 993189 | D125: 2007 | E125: 35.90315 | F125: 1336000 | G125: 3239000 | H125: 8685000 | I125: 7257000 | J125: 10030000 | K125: 6.34 | L125: 15.16 | M125: 25534000 | N125: 17937859 | O125: 2.04
A126: =VLOOKUP(C126,'PORTFOLIO RAW'!C:D,2,FALSE) -> 46 | B126: BLL | C126: 932060 | D126: 2007 | E126: 47.663731 | F126: 281300 | G126: 794900 | H126: 1342500 | I126: 2358600 | J126: 7475300 | K126: 6.4 | L126: 22.43 | M126: 6016300 | N126: 4510100 | O126: 4.17
A127: =VLOOKUP(C127,'PORTFOLIO RAW'!C:D,2,FALSE) -> 268 | B127: PEG | C127: 902321 | D127: 2007 | E127: 57.904598 | F127: 1319000 | G127: 3796000 | H127: 7299000 | I127: 9850000 | J127: 12853000 | K127: 6.41 | L127: 19.01 | M127: 28392000 | N127: 24978650 | O127: 3.06
A128: =VLOOKUP(C128,'PORTFOLIO RAW'!C:D,2,FALSE) -> 143 | B128: FMC | C128: 905082 | D128: 2007 | E128: 76.673543 | F128: 132400 | G128: 363700 | H128: 1064300 | I128: 545200 | J128: 2632900 | K128: 6.42 | L128: 12.76 | M128: 2474400 | N128: 4098309 | O128: 3.63
A129: =VLOOKUP(C129,'PORTFOLIO RAW'!C:D,2,FALSE) -> 342 | B129: WYNN.O | C129: 26406N | D129: 2007 | E129: 40.226266 | F129: 258148 | G129: 689212 | H129: 1948159 | I129: 3548379 | J129: 2687519 | K129: 6.42 | L129: 14.37 | M129: 6299282 | N129: 12824318 | O129: 8.18
A130: =VLOOKUP(C130,'PORTFOLIO RAW'!C:D,2,FALSE) -> 272 | B130: DGX | C130: 877181 | D130: 2007 | E130: 37.635992 | F130: 339939 | G130: 1336151 | H130: 3324242 | I130: 3540800 | J130: 6704907 | K130: 6.49 | L130: 10.72 | M130: 8565693 | N130: 10264716 | O130: 3.25
A131: =VLOOKUP(C131,'PORTFOLIO RAW'!C:D,2,FALSE) -> 265 | B131: PGR | C131: 936324 | D131: 2007 | E131: 48.339796 | F131: 1182500 | G131: 1908500 | H131: 4442700 | I131: 2173900 | J131: 14696100 | K131: 6.54 | L131: 22.13 | M131: 18843100 | N131: 13032632 | O131: 3.17
A132: =VLOOKUP(C132,'PORTFOLIO RAW'!C:D,2,FALSE) -> 275 | B132: REG.O | C132: 312451 | D132: 2007 | E132: 41.056459 | F132: 156744 | G132: 343546 | H132: 1595386 | I132: 2007975 | J132: 451508 | K132: 6.64 | L132: 11.59 | M132: 4143012 | N132: 4490996 | O132: 3.21
A133: =VLOOKUP(C133,'PORTFOLIO RAW'!C:D,2,FALSE) -> 43 | B133: AVB | C133: 130502 | D133: 2007 | E133: 39.143901 | F133: 238968 | G133: 467178 | H133: 2926654 | I133: 3208202 | J133: 812741 | K133: 6.7 | L133: 12.94 | M133: 6736484 | N133: 7278774 | O133: 3.16
...

Sheet PORTFOLIO RAW
A1: Number | B1: NAME | C1: Code
A2: 1 | B2: MMM | C2: 902172 | D2: =A2 -> 1
A3: 2 | B3: ABT | C3: 916328 | D3: =A3 -> 2
A4: 3 | B4: ACN | C4: 14352P | D4: =A4 -> 3
A5: 4 | B5: ATVI.O | C5: 312367 | D5: =A5 -> 4
A6: 5 | B6: ADBE.O | C6: 749382 | D6: =A6 -> 5
A7: 6 | B7: AAP | C7: 14806F | D7: =A7 -> 6
A8: 7 | B8: AMD.O | C8: 936365 | D8: =A8 -> 7
A9: 8 | B9: AES | C9: 545101 | D9: =A9 -> 8
A10: 9 | B10: AFL | C10: 933185 | D10: =A10 -> 9
A11: 10 | B11: A | C11: 277642 | D11: =A11 -> 10
A12: 11 | B12: APD | C12: 905271 | D12: =A12 -> 11
A13: 12 | B13: AKAM.O | C13: 277355 | D13: =A13 -> 12
A14: 13 | B14: ALB | C14: 130298 | D14: =A14 -> 13
A15: 14 | B15: AGN | C15: 325596 | D15: =A15 -> 14
A16: 15 | B16: LNT.O | C16: 906979 | D16: =A16 -> 15
A17: 16 | B17: ALL | C17: 322677 | D17: =A17 -> 16
A18: 17 | B18: GOOG.O | C18: 29026M | D18: =A18 -> 17
A19: 18 | B19: MO | C19: 904853 | D19: =A19 -> 18
A20: 19 | B20: AMZN.O | C20: 891399 | D20: =A20 -> 19
A21: 20 | B21: AEE | C21: 670942 | D21: =A21 -> 20
A22: 21 | B22: AEP | C22: 905425 | D22: =A22 -> 21
A23: 22 | B23: AXP | C23: 906156 | D23: =A23 -> 22
A24: 23 | B24: AIG | C24: 916305 | D24: =A24 -> 23
A25: 24 | B25: AMT | C25: 680902 | D25: =A25 -> 24
A26: 25 | B26: AMP | C26: 31604H | D26: =A26 -> 25
A27: 26 | B27: ABC | C27: 154680 | D27: =A27 -> 26
A28: 27 | B28: AMGN.O | C28: 938692 | D28: =A28 -> 27
A29: 28 | B29: APH | C29: 546075 | D29: =A29 -> 28
A30: 29 | B30: ADI.O | C30: 905276 | D30: =A30 -> 29
A31: 30 | B31: ANTM.K | C31: 14737P | D31: =A31 -> 30
A32: 31 | B32: AON | C32: 922817 | D32: =A32 -> 31
A33: 32 | B33: APA | C33: 921983 | D33: =A33 -> 32
A34: 33 | B34: AIV | C34: 132808 | D34: =A34 -> 33
A35: 34 | B35: AAPL.O | C35: 992816 | D35: =A35 -> 34
A36: 35 | B36: AMAT.O | C36: 905296 | D36: =A36 -> 35
A37: 36 | B37: ADM | C37: 921093 | D37: =A37 -> 36
A38: 37 | B38: ARNC.K | C38: 905113 | D38: =A38 -> 37
A39: 38 | B39: AIZ | C39: 28341F | D39: =A39 -> 38
A40: 39 | B40: T | C40: 945388 | D40: =A40 -> 39
A41: 40 | B41: ADSK.O | C41: 702259 | D41: =A41 -> 40
A42: 41 | B42: ADP.O | C42: 912669 | D42: =A42 -> 41
A43: 42 | B43: AZO | C43: 544616 | D43: =A43 -> 42
A44: 43 | B44: AVB | C44: 130502 | D44: =A44 -> 43
A45: 44 | B45: AVY | C45: 921161 | D45: =A45 -> 44
A46: 45 | B46: BHGE.K | C46: 921431 | D46: =A46 -> 45
A47: 46 | B47: BLL | C47: 932060 | D47: =A47 -> 46
A48: 47 | B48: BAC | C48: 923937 | D48: =A48 -> 47
A49: 48 | B49: BK | C49: 905840 | D49: =A49 -> 48
A50: 49 | B50: BAX | C50: 916365 | D50: =A50 -> 49
A51: 50 | B51: BBT | C51: 992305 | D51: =A51 -> 50
... A68: 67 | B68: CAT | C68: 902224 | D68: =A68 -> 67
A69: 68 | B69: CBRE.K | C69: 28513N | D69: =A69 -> 68
A70: 69 | B70: CBS | C70: 32480Q | D70: =A70 -> 69
A71: 70 | B71: CE | C71: 29756N | D71: =A71 -> 70
A72: 71 | B72: CELG.O | C72: 755790 | D72: =A72 -> 71
A73: 72 | B73: CNP | C73: 904842 | D73: =A73 -> 72
A74: 73 | B74: SCHW.K | C74: 755741 | D74: =A74 -> 73
A75: 74 | B75: CVX | C75: 905024 | D75: =A75 -> 74
A76: 75 | B76: CB | C76: 328314 | D76: =A76 -> 75
A77: 76 | B77: CI | C77: 912278 | D77: =A77 -> 76
A78: 77 | B78: XEC | C78: 26276P | D78: =A78 -> 77
A79: 78 | B79: CINF.O | C79: 951545 | D79: =A79 -> 78
A80: 79 | B80: CTAS.O | C80: 944777 | D80: =A80 -> 79
A81: 80 | B81: CSCO.O | C81: 542868 | D81: =A81 -> 80
A82: 81 | B82: C | C82: 741344 | D82: =A82 -> 81
A83: 82 | B83: CTXS.O | C83: 867705 | D83: =A83 -> 82
A84: 83 | B84: CLX | C84: 916125 | D84: =A84 -> 83
A85: 84 | B85: CME.O | C85: 26393N | D85: =A85 -> 84
A86: 85 | B86: CMS | C86: 901686 | D86: =A86 -> 85
A87: 86 | B87: KO | C87: 904282 | D87: =A87 -> 86
A88: 87 | B88: CL | C88: 906148 | D88: =A88 -> 87
A89: 88 | B89: CMCSA.O | C89: 981550 | D89: =A89 -> 88
A90: 89 | B90: CMA | C90: 922964 | D90: =A90 -> 89
A91: 90 | B91: CAG | C91: 929814 | D91: =A91 -> 90
A92: 91 | B92: COP | C92: 901666 | D92: =A92 -> 91
A93: 92 | B93: ED | C93: 902288 | D93: =A93 -> 92
A94: 93 | B94: STZ | C94: 937083 | D94: =A94 -> 93
A95: 94 | B95: COO | C95: 938928 | D95: =A95 -> 94
A96: 95 | B96: GLW | C96: 912273 | D96: =A96 -> 95
A97: 96 | B97: COST.O | C97: 312385 | D97: =A97 -> 96
... A108: 107 | B108: DVN | C108: 271980 | D108: =A108 -> 107
A109: 108 | B109: DISCK.O | C109: 31196R | D109: =A109 -> 108
A110: 109 | B110: DISH.O | C110: 135448 | D110: =A110 -> 109
A111: 110 | B111: DLTR.O | C111: 154259 | D111: =A111 -> 110
A112: 111 | B112: D | C112: 944314 | D112: =A112 -> 111
A113: 112 | B113: DOV | C113: 904830 | D113: =A113 -> 112
A114: 113 | B114: DTE | C114: 905214 | D114: =A114 -> 113
A115: 114 | B115: DUK | C115: 904383 | D115: =A115 -> 114
A116: 115 | B116: DRE | C116: 513260 | D116: =A116 -> 115
A117: 116 | B117: DXC | C117: 916091 | D117: =A117 -> 116
A118: 117 | B118: ETFC.O | C118: 883488 | D118: =A118 -> 117
A119: 118 | B119: EMN | C119: 357922 | D119: =A119 -> 118
A120: 119 | B120: ETN | C120: 903749 | D120: =A120 -> 119
A121: 120 | B121: EBAY.O | C121: 687609 | D121: =A121 -> 120
... A133: 132 | B133: EXC | C133: 902317 | D133: =A133 -> 132
A134: 133 | B134: EXPE.O | C134: 31412T | D134: =A134 -> 133
A135: 134 | B135: EXPD.O | C135: 910722 | D135: =A135 -> 134
A136: 135 | B136: XOM | C136: 905039 | D136: =A136 -> 135
A137: 136 | B137: FAST.O | C137: 755980 | D137: =A137 -> 136
...

Sheet ESGC
A1: ESGC PORTFOLIO
C2: 3 | D2: 4 | E2: 5 | F2: 6 | G2: 7 | H2: 8 | I2: 9 | J2: 10 | K2: 11 | L2: 12 | M2: 13
A3: Code | B3: Name | C3: 2007 | D3: 2008 | E3: 2009 | F3: 2010 | G3: 2011 | H3: 2012 | I3: 2013 | J3: 2014 | K3: 2015 | L3: 2016 | M3: 2017
A4: =VLOOKUP(B4,'PORTFOLIO RAW'!B:C,2,FALSE) -> 902172 | B4: MMM | C4: 87.196853 | D4: 50.382743 | E4: 47.140342 | F4: 46.539558 | G4: 50.033837 | H4: 47.442829 | I4: 55.273448 | J4: 88.864444 | K4: 50.953109 | L4: 87.126519 | M4: 50.687716
A5: =VLOOKUP(B5,'PORTFOLIO RAW'!B:C,2,FALSE) -> 916328 | B5: ABT | C5: 34.369681 | D5: 74.108803 | E5: 40.291636 | F5: 40.793148 | G5: 39.468559 | H5: 40.011399 | I5: 44.822485 | J5: 41.422324 | K5: 42.586139 | L5: 45.821979 | M5: 43.056786
A6: =VLOOKUP(B6,'PORTFOLIO RAW'!B:C,2,FALSE) -> 14352P | B6: ACN | C6: 51.685846 | D6: 72.464911 | E6: 44.880139 | F6: 82.828882 | G6: 84.107278 | H6: 49.473394 | I6: 47.959104 | J6: 88.985526 | K6: 86.6825 | L6: 92.692745 | M6: 91.716033
A7: =VLOOKUP(B7,'PORTFOLIO RAW'!B:C,2,FALSE) -> 312367 | B7: ATVI.O | C7: 34.591234 | D7: 36.641828 | E7: 34.06525 | F7: 33.580174 | G7: 23.221913 | H7: 25.839549 | I7: 18.424289 | J7: 50.753359 | K7: 33.499076 | L7: 35.063434 | M7: 55.24599
A8: =VLOOKUP(B8,'PORTFOLIO RAW'!B:C,2,FALSE) -> 749382 | B8: ADBE.O | C8: 37.092577 | D8: 38.053702 | E8: 38.053702 | F8: 44.299029 | G8: 35.393899 | H8: 48.863832 | I8: 48.863832 | J8: 43.561088 | K8: 47.51067 | L8: 45.014435 | M8: 45.519894
A9: =VLOOKUP(B9,'PORTFOLIO RAW'!B:C,2,FALSE) -> 14806F | B9: AAP | C9: 37.296212 | D9: 37.730194 | E9: 37.730194 | F9: 46.130315 | G9: 49.030131 | H9: 33.668147 | I9: 46.424335 | J9: 46.259533 | K9: 46.259533 | L9: 42.812791 | M9: 27.92945
A10: =VLOOKUP(B10,'PORTFOLIO RAW'!B:C,2,FALSE) -> 936365 | B10: AMD.O | C10: 66.492963 | D10: 62.677185 | E10: 36.2718 | F10: 38.761892 | G10: 35.158859 | H10: 43.250636 | I10: 41.235471 | J10: 41.235471 | K10: 78.280174 | L10: 39.892114 | M10: 43.134463
A11: =VLOOKUP(B11,'PORTFOLIO RAW'!B:C,2,FALSE) -> 545101 | B11: AES | C11: 50.503558 | D11: 34.33064 | E11: 33.561278 | F11: 33.561278 | G11: 44.781638 | H11: 44.781638 | I11: 53.84665 | J11: 53.84665 | K11: 32.588884 | L11: 58.433747 | M11: 66.98827
A12: =VLOOKUP(B12,'PORTFOLIO RAW'!B:C,2,FALSE) -> 933185 | B12: AFL | C12: 52.782483 | D12: 35.970888 | E12: 35.970888 | F12: 58.328972 | G12: 42.440133 | H12: 69.337764 | I12: 38.73711 | J12: 38.73711 | K12: 69.659623 | L12: 69.118896 | M12: 69.731359
A13: =VLOOKUP(B13,'PORTFOLIO RAW'!B:C,2,FALSE) -> 277642 | B13: A | C13: 47.935211 | D13: 47.935211 | E13: 50.429171 | F13: 49.67811 | G13: 83.594284 | H13: 83.594284 | I13: 84.716912 | J13: 84.716912 | K13: 82.687352 | L13: 82.000545 | M13: 89.222975
A14: =VLOOKUP(B14,'PORTFOLIO RAW'!B:C,2,FALSE) -> 905271 | B14: APD | C14: 66.565326 | D14: 78.888183 | E14: 72.150888 | F14: 77.437421 | G14: 40.825982 | H14: 84.362445 | I14: 83.578389 | J14: 45.614554 | K14: 46.770641 | L14: 79.926533 | M14: 76.728144
A15: =VLOOKUP(B15,'PORTFOLIO RAW'!B:C,2,FALSE) -> 277355 | B15: AKAM.O | C15: 44.900541 | D15: 44.900541 | E15: 36.647063 | F15: 37.96387 | G15: 37.96387 | H15: 41.334767 | I15: 27.501162 | J15: 35.535379 | K15: 58.519486 | L15: 66.453929 | M15: 35.587406
... A350: =VLOOKUP(B350,'PORTFOLIO RAW'!B:C,2,FALSE) -> 951584 | B350: ZION.O | C350: 44.106225 | D350: 43.228866 | E350: 43.228965 | F350: 35.866759 | G350: 24.717636 | H350: 26.053497 | I350: 33.482903 | J350: 31.583338 | K350: 35.871449 | L350: 39.735018 | M350: 40.503275

Sheet MB
A1: MARKET-TO-BOOK RATIO
E2: 4 | F2: 5 | G2: 6 | H2: 7 | I2: 8 | J2: 9 | K2: 10 | L2: 11 | M2: 12 | N2: 13 | O2: 14
B3: Code | C3: Name | D3: Code | E3: 2007 | F3: 2008 | G3: 2009 | H3: 2010 | I3: 2011 | J3: 2012 | K3: 2013 | L3: 2014 | M3: 2015 | N3: 2016 | O3: 2017
A4: =VLOOKUP(B4,'PORTFOLIO RAW'!C:C,1,FALSE) -> 891399 | B4: 891399 | C4: AMAZON.COM - MRKT VALUE TO BOOK | D4: 891399(MTBV) | E4: 30.96 | F4: 12.91 | G4: 7.42 | H4: 9.87 | I4: 13.65 | J4: 14.39 | K4: 14.83 | L4: 14.25 | M4: 18.88 | N4: 19.18 | O4: 16.87
A5: =VLOOKUP(B5,'PORTFOLIO RAW'!C:C,1,FALSE) -> 916328 | B5: 916328 | C5: ABBOTT LABORATORIES - MRKT VALUE TO BOOK | D5: 916328(MTBV) | E5: 4.67 | F5: 5.18 | G5: 3.11 | H5: 3.6 | I5: 3.36 | J5: 4.1 | K5: 2.18 | L5: 3.04 | M5: 3.04 | N5: 2.98 | O5: 2.92
A6: =VLOOKUP(B6,'PORTFOLIO RAW'!C:C,1,FALSE) -> 545101 | B6: 545101 | C6: AES - MRKT VALUE TO BOOK | D6: 545101(MTBV) | E6: 4.08 | F6: 2.42 | G6: 2.05 | H6: 1.4 | I6: 1.41 | J6: 1.83 | K6: 2.29 | L6: 2.49 | M6: 2.37 | N6: 3.01 | O6: 3.02
A7: =VLOOKUP(B7,'PORTFOLIO RAW'!C:C,1,FALSE) -> 906187 | B7: 906187 | C7: INTERNATIONAL BUS.MCHS. - MRKT VALUE TO BOOK | D7: 906187(MTBV) | E7: 5.58 | F7: 11.96 | G7: 7.07 | H7: 7.21 | I7: 10.36 | J7: 12.49 | K7: 9.13 | L7: 16.31 | M7: 9.93 | N7: 8.09 | O7: 7.73
A8: =VLOOKUP(B8,'PORTFOLIO RAW'!C:C,1,FALSE) -> 936365 | B8: 936365 | C8: ADVANCED MICRO DEVICES - MRKT VALUE TO BOOK | D8: 936365(MTBV) | E8: 2.47 | F8: -40.13 | G8: 5.87 | H8: 4.06 | I8: 2.93 | J8: 4.72 | K8: 5.07 | L8: 15.65 | M8: -3.54 | N8: 13.27 | O8: 21.29
A9: =VLOOKUP(B9,'PORTFOLIO RAW'!C:C,1,FALSE) -> 749382 | B9: 749382 | C9: ADOBE (NAS) - MRKT VALUE TO BOOK | D9: 749382(MTBV) | E9: 5.42 | F9: 4.92 | G9: 3.54 | H9: 3.35 | I9: 2.1 | J9: 2.55 | K9: 3.91 | L9: 4.93 | M9: 5.79 | N9: 6.75 | O9: 8.75
A10: =VLOOKUP(B10,'PORTFOLIO RAW'!C:C,1,FALSE) -> 905271 | B10: 905271 | C10: AIR PRDS.& CHEMS. - MRKT VALUE TO BOOK | D10: 905271(MTBV) | E10: 3.65 | F10: 3.51 | G10: 3.52 | H10: 3.18 | I10: 3.02 | J10: 2.78 | K10: 3.23 | L10: 3.89 | M10: 3.99 | N10: 4.5 | O10: 3.26
A11: =VLOOKUP(B11,'PORTFOLIO RAW'!C:C,1,FALSE) -> 894371 | B11: 894371 | C11: BOSTON PROPERTIES - MRKT VALUE TO BOOK | D11: 894371(MTBV) | E11: 3.36 | F11: 3.23 | G11: 2.2 | H11: 2.83 | I11: 3.01 | J11: 3.33 | K11: 3.01 | L11: 3.15 | M11: 3.19 | N11: 3.72 | O11: 3.32
A12: =VLOOKUP(B12,'PORTFOLIO RAW'!C:C,1,FALSE) -> 322677 | B12: 322677 | C12: ALLSTATE ORD SHS - MRKT VALUE TO BOOK | D12: 322677(MTBV) | E12: 1.56 | F12: 1.57 | G12: 0.94 | H12: 0.94 | I12: 0.73 | J12: 1.09 | K12: 1.26 | L12: 1.45 | M12: 1.31 | N12: 1.42 | O12: 1.73
A13: =VLOOKUP(B13,'PORTFOLIO RAW'!C:C,1,FALSE) -> 906191 | B13: 906191 | C13: HONEYWELL INTL. - MRKT VALUE TO BOOK | D13: 906191(MTBV) | E13: 4.72 | F13: 4.69 | G13: 3.42 | H13: 3.21 | I13: 3.39 | J13: 3.64 | K13: 3.84 | L13: 4.28 | M13: 4.19 | N13: 4.51 | O13: 6.11
A14: =VLOOKUP(B14,'PORTFOLIO RAW'!C:C,1,FALSE) -> 938692 | B14: 938692 | C14: AMGEN - MRKT VALUE TO BOOK | D14: 938692(MTBV) | E14: 3.36 | F14: 3.11 | G14: 2.72 | H14: 2.24 | I14: 2.79 | J14: 3.33 | K14: 3.98 | L14: 4.24 | M14: 4.07 | N14: 4.34 | O14: 5.44
A15: =VLOOKUP(B15,'PORTFOLIO RAW'!C:C,1,FALSE) -> 905802 | B15: 905802 | C15: HESS - MRKT VALUE TO BOOK | D15: 905802(MTBV) | E15: 2.16 | F15: 2.51 | G15: 1.36 | H15: 1.12 | I15: 1.1 | J15: 0.9 | K15: 1.09 | L15: 1.35 | M15: 0.78 | N15: 1 | O15: 1.25
... A109: =VLOOKUP(B109,'PORTFOLIO RAW'!C:C,1,FALSE) -> 905016 | B109: 905016 | C109: NEXTERA ENERGY - MRKT VALUE TO BOOK | D109: 905016(MTBV) | E109: 2.37 | F109: 1.96 | G109: 1.75 | H109: 1.57 | I109: 1.57 | J109: 1.77 | K109: 1.9 | L109: 2.08 | M109: 1.98 | N109: 2.37 | O109: 2.44
A110: =VLOOKUP(B110,'PORTFOLIO RAW'!C:C,1,FALSE) -> 28341F | B110: 28341F | C110: ASSURANT - MRKT VALUE TO BOOK | D110: 28341F(MTBV) | E110: 1.51 | F110: 1.54 | G110: 0.81 | H110: 0.99 | I110: 0.77 | J110: 0.59 | K110: 0.94 | L110: 1.09 | M110: 1.26 | N110: 1.49 | O110: 1.37
A111: =VLOOKUP(B111,'PORTFOLIO RAW'!C:C,1,FALSE) -> 755980 | B111: 755980 | C111: FASTENAL - MRKT VALUE TO BOOK | D111: 755980(MTBV) | E111: 6.65 | F111: 6.97 | G111: 4.86 | H111: 6 | I111: 7.41 | J111: 8.33 | K111: 8.4 | L111: 7.16 | M111: 5.99 | N111: 5.97 | O111: 6.12
A112: =VLOOKUP(B112,'PORTFOLIO RAW'!C:C,1,FALSE) -> 905994 | B112: 905994 | C112: FEDERAL REALTY INV.TST. - MRKT VALUE TO BOOK | D112: 905994(MTBV) | E112: 4.41 | F112: 4.71 | G112: 3.32 | H112: 4.49 | I112: 4.42 | J112: 5.28 | K112: 4.69 | L112: 5.07 | M112: 5.63 | N112: 5.6 | O112: 4.27
A113: =VLOOKUP(B113,'PORTFOLIO RAW'!C:C,1,FALSE) -> 997198 | B113: 997198 | C113: FIFTH THIRD BANCORP - MRKT VALUE TO BOOK | D113: 997198(MTBV) | E113: 2.07 | F113: 1.39 | G113: 0.84 | H113: 0.96 | I113: 0.75 | J113: 1.08 | K113: 1.23 | L113: 1.22 | M113: 1.05 | N113: 1.06 | O113: 1.34
A114: =VLOOKUP(B114,'PORTFOLIO RAW'!C:C,1,FALSE) -> 951503 | B114: 951503 | C114: M&T BANK - MRKT VALUE TO BOOK | D114: 951503(MTBV) | E114: 1.79 | F114: 1.67 | G114: 1.12 | H114: 1.43 | I114: 1.07 | J114: 1.28 | K114: 1.39 | L114: 1.52 | M114: 1.06 | N114: 1.19 | O114: 1.56
A115: =VLOOKUP(B115,'PORTFOLIO RAW'!C:C,1,FALSE) -> 741123 | B115: 741123 | C115: FISERV - MRKT VALUE TO BOOK | D115: 741123(MTBV) | E115: 3.3 | F115: 3.26 | G115: 2.52 | H115: 2.52 | I115: 2.33 | J115: 2.92 | K115: 3.7 | L115: 4.97 | M115: 7.63 | N115: 8.59 | O115: 9.64
A116: =VLOOKUP(B116,'PORTFOLIO RAW'!C:C,1,FALSE) -> 546814 | B116: 546814 | C116: MACY'S - MRKT VALUE TO BOOK | D116: 546814(MTBV) | E116: 1.49 | F116: 1.81 | G116: 1.61 | H116: 1.69 | I116: 1.97 | J116: 2.57 | K116: 2.69 | L116: 3.95 | M116: 4.21 | N116: 2.49 | O116: 1.15
A117: =VLOOKUP(B117,'PORTFOLIO RAW'!C:C,1,FALSE) -> 938076 | B117: 938076 | C117: FRANKLIN RESOURCES - MRKT VALUE TO BOOK | D117: 938076(MTBV) | E117: 4.34 | F117: 3.58 | G117: 3.12 | H117: 3.15 | I117: 2.98 | J117: 2.9 | K117: 3.27 | L117: 3.01 | M117: 2 | N117: 1.69 | O117: 1.9
A118: =VLOOKUP(B118,'PORTFOLIO RAW'!C:C,1,FALSE) -> 152594 | B118: 152594 | C118: FREEPORT-MCMORAN - MRKT VALUE TO BOOK | D118: 152594(MTBV) | E118: 2.88 | F118: 13.66 | G118: 4.63 | H118: 3.14 | I118: 2.34 | J118: 2.21 | K118: 1.68 | L118: 1.94 | M118: 1.58 | N118: 2.18 | O118: 2.57
A119: =VLOOKUP(B119,'PORTFOLIO RAW'!C:C,1,FALSE) -> 951018 | B119: 951018 | C119: GAP - MRKT VALUE TO BOOK | D119: 951018(MTBV) | E119: 3.4 | F119: 3.09 | G119: 3.14 | H119: 2.91 | I119: 3.1 | J119: 6.01 | K119: 6.34 | L119: 6.4 | M119: 5.05 | N119: 3.1 | O119: 3.49
A120: =VLOOKUP(B120,'PORTFOLIO RAW'!C:C,1,FALSE) -> 907652 | B120: 907652 | C120: GENERAL DYNAMICS - MRKT VALUE TO BOOK | D120: 907652(MTBV) | E120: 2.87 | F120: 3.26 | G120: 2 | H120: 1.82 | I120: 1.63 | J120: 2.05 | K120: 2.13 | L120: 3.66 | M120: 4.18 | N120: 4.22 | O120: 5.35
A121: =VLOOKUP(B121,'PORTFOLIO RAW'!C:C,1,FALSE) -> 905801 | B121: 905801 | C121: GENERAL MILLS - MRKT VALUE TO BOOK | D121: 905801(MTBV) | E121: 3.07 | F121: 4.52 | G121: 3.65 | H121: 3.64 | I121: 3.76 | J121: 3.91 | K121: 4.72 | L121: 6.2 | M121: 6.86 | N121: 8.84 | O121: 4.83
A122: =VLOOKUP(B122,'PORTFOLIO RAW'!C:C,1,FALSE) -> 906511 | B122: 906511 | C122: GENUINE PARTS - MRKT VALUE TO BOOK | D122: 906511(MTBV) | E122: 3.18 | F122: 2.94 | G122: 2.29 | H122: 2.5 | I122: 2.94 | J122: 3.24 | K122: 3.76 | L122: 4.14 | M122: 4.01 | N122: 4.6 | O122: 3.73
... A235: =VLOOKUP(B235,'PORTFOLIO RAW'!C:C,1,FALSE) -> 933974 | B235: 933974 | C235: TRAVELERS COS. - MRKT VALUE TO BOOK | D235: 933974(MTBV) | E235: 1.3 | F235: 1.18 | G235: 1.06 | H235: 1.07 | I235: 0.98 | J235: 1.18 | K235: 1.37 | L235: 1.4 | M235: 1.39 | N235: 1.47 | O235: 1.48
A236: =VLOOKUP(B236,'PORTFOLIO RAW'!C:C,1,FALSE) -> 14015T | B236: 14015T | C236: FIDELITY NAT.INFO.SVS. - MRKT VALUE TO BOOK | D236: 14015T(MTBV) | E236: 2.35 | F236: 1.09 | G236: 0.58 | H236: 1.29 | I236: 1.22 | J236: 1.44 | K236: 2.08 | L236: 2.49 | M236: 2.06 | N236: 2.58 | O236: 2.85
A237: =VLOOKUP(B237,'PORTFOLIO RAW'!C:C,1,FALSE) -> 905019 | B237: 905019 | C237: MERCK & COMPANY - MRKT VALUE TO BOOK | D237: 905019(MTBV) | E237: 6.13 | F237: 3.64 | G237: 1.14 | H237: 2.07 | I237: 1.84 | J237: 2.58 | K237: 2.82 | L237: 3.59 | M237: 3.29 | N237: 4.27 | O237: 5.23
A238: =VLOOKUP(B238,'PORTFOLIO RAW'!C:C,1,FALSE) -> 912090 | B238: 912090 | C238: SCHLUMBERGER - MRKT VALUE TO BOOK | D238: 912090(MTBV) | E238: 8.6 | F238: 6.45 | G238: 3.87 | H238: 2.58 | I238: 2.99 | J238: 2.87 | K238: 2.93 | L238: 3.54 | M238: 2.58 | N238: 2.55 | O238: 2.54
A239: =VLOOKUP(B239,'PORTFOLIO RAW'!C:C,1,FALSE) -> 755741 | B239: 755741 | C239: CHARLES SCHWAB - MRKT VALUE TO BOOK | D239: 755741(MTBV) | E239: 7.07 | F239: 7.16 | G239: 4.03 | H239: 2.68 | I239: 1.86 | J239: 1.97 | K239: 2.88 | L239: 3.63 | M239: 3.14 | N239: 2.99 | O239: 3.55
A240: =VLOOKUP(B240,'PORTFOLIO RAW'!C:C,1,FALSE) -> 14361V | B240: 14361V | C240: ZIMMER BIOMET HDG. - MRKT VALUE TO BOOK | D240: 14361V(MTBV) | E240: 3.61 | F240: 2.71 | G240: 1.94 | H240: 1.8 | I240: 1.98 | J240: 1.99 | K240: 2.24 | L240: 2.69 | M240: 2.04 | N240: 2.58 | O240: 2
A241: =VLOOKUP(B241,'PORTFOLIO RAW'!C:C,1,FALSE) -> 154680 | B241: 154680 | C241: AMERISOURCEBERGEN - MRKT VALUE TO BOOK | D241: 154680(MTBV) | E241: 2.65 | F241: 2.31 | G241: 2.38 | H241: 2.89 | I241: 3.73 | J241: 3.93 | K241: 6.14 | L241: 8.87 | M241: 36.21 | N241: 9.17 | O241: 8.44
A242: =VLOOKUP(B242,'PORTFOLIO RAW'!C:C,1,FALSE) -> 14698C | B242: 14698C | C242: PRINCIPAL FINL.GP. - MRKT VALUE TO BOOK | D242: 14698C(MTBV) | E242: 2.32 | F242: 2.11 | G242: 1.09 | H242: 0.93 | I242: 0.88 | J242: 1.01 | K242: 1.35 | L242: 1.57 | M242: 1.52 | N242: 1.38 | O242: 1.61
A243: =VLOOKUP(B243,'PORTFOLIO RAW'!C:C,1,FALSE) -> 905361 | B243: 905361 | C243: SHERWIN-WILLIAMS - MRKT VALUE TO BOOK | D243: 905361(MTBV) | E243: 4.93 | F243: 4.64 | G243: 4.84 | H243: 5.05 | I243: 5.2 | J243: 8.99 | K243: 10.66 | L243: 21.64 | M243: 26.49 | N243: 13.51 | O243: 8.78
A244: =VLOOKUP(B244,'PORTFOLIO RAW'!C:C,1,FALSE) -> 357834 | B244: 357834 | C244: SIMON PROPERTY GROUP - MRKT VALUE TO BOOK | D244: 357834(MTBV) | E244: 7.85 | F244: 8.69 | G244: 4.71 | H244: 5.95 | I244: 7.63 | J244: 8.06 | K244: 8.07 | L244: 10.2 | M244: 12.86 | N244: 15.37 | O244: 13.64
A245: =VLOOKUP(B245,'PORTFOLIO RAW'!C:C,1,FALSE) -> 906400 | B245: 906400 | C245: SNAP-ON - MRKT VALUE TO BOOK | D245: 906400(MTBV) | E245: 2.22 | F245: 2.83 | G245: 1.65 | H245: 1.96 | I245: 1.9 | J245: 2.33 | K245: 2.78 | L245: 3.26 | M245: 3.75 | N245: 3.32 | O245: 2.91
A246: =VLOOKUP(B246,'PORTFOLIO RAW'!C:C,1,FALSE) -> 14861V | B246: 14861V | C246: PRUDENTIAL FINL. - MRKT VALUE TO BOOK | D246: 14861V(MTBV) | E246: 1.86 | F246: 1.83 | G246: 0.99 | H246: 0.9 | I246: 0.75 | J246: 0.98 | K246: 1.45 | L246: 1.89 | M246: 1.31 | N246: 1.26 | O246: 1.33
A247: =VLOOKUP(B247,'PORTFOLIO RAW'!C:C,1,FALSE) -> 14806F | B247: 14806F | C247: ADV.AUTO PARTS - MRKT VALUE TO BOOK | D247: 14806F(MTBV) | E247: 3.42 | F247: 3.48 | G247: 2.92 | H247: 4.8 | I247: 5.36 | J247: 4.19 | K247: 3.87 | L247: 4.8 | M247: 5.17 | N247: 3.68 | O247: 2.05
A248: =VLOOKUP(B248,'PORTFOLIO RAW'!C:C,1,FALSE) -> 902324 | B248: 902324 | C248: EDISON INTL. - MRKT VALUE TO BOOK | D248: 902324(MTBV) | E248: 2.19 | F248: 1.37 | G248: 1.16 | H248: 1.06 | I248: 1.23 | J248: 1.56 | K248: 1.51 | L248: 1.72 | M248: 1.76 | N248: 1.99 | O248: 2.21
A249: =VLOOKUP(B249,'PORTFOLIO RAW'!C:C,1,FALSE) -> 902325 | B249: 902325 | C249: SOUTHERN - MRKT VALUE TO BOOK | D249: 902325(MTBV) | E249: 2.26 | F249: 2.23 | G249: 1.71 | H249: 1.91 | I249: 2.09 | J249: 2.15 | K249: 1.92 | L249: 1.96 | M249: 1.92 | N249: 2.06 | O249: 2.05
A250: =VLOOKUP(B250,'PORTFOLIO RAW'!C:C,1,FALSE) -> 992305 | B250: 992305 | C250: BB&T - MRKT VALUE TO BOOK | D250: 992305(MTBV) | E250: 1.83 | F250: 1.74 | G250: 1.17 | H250: 1 | I250: 0.89 | J250: 1.23 | K250: 1.22 | L250: 1.28 | M250: 1.05 | N250: 1.16 | O250: 1.37
A251: =VLOOKUP(B251,'PORTFOLIO RAW'!C:C,1,FALSE) -> 905647 | B251: 905647 | C251: SOUTHWEST AIRLINES - MRKT VALUE TO BOOK | D251: 905647(MTBV) | E251: 1.63 | F251: 2.32 | G251: 1.31 | H251: 1.46 | I251: 0.99 | J251: 0.95 | K251: 1.39 | L251: 3.49 | M251: 3.54 | N251: 2.71 | O251: 3.11
A252: =VLOOKUP(B252,'PORTFOLIO RAW'!C:C,1,FALSE) -> 945388 | B252: 945388 | C252: AT&T - MRKT VALUE TO BOOK | D252: 945388(MTBV) | E252: 2.22 | F252: 1.86 | G252: 1.57 | H252: 1.51 | I252: 1.62 | J252: 2.37 | K252: 2 | L252: 2.13 | M252: 1.63 | N252: 2 | O252: 1.68
A253: =VLOOKUP(B253,'PORTFOLIO RAW'!C:C,1,FALSE) -> 905024 | B253: 905024 | C253: CHEVRON - MRKT VALUE TO BOOK | D253: 905024(MTBV) | E253: 2.6 | F253: 2.08 | G253: 1.58 | H253: 1.53 | I253: 1.61 | J253: 1.69 | K253: 1.62 | L253: 1.53 | M253: 0.96 | N253: 1.27 | O253: 1.49
A254: =VLOOKUP(B254,'PORTFOLIO RAW'!C:C,1,FALSE) -> 951052 | B254: 951052 | C254: STATE STREET - MRKT VALUE TO BOOK | D254: 951052(MTBV) | E254: 2.29 | F254: 2.4 | G254: 1.86 | H254: 1.12 | I254: 0.87 | J254: 1.02 | K254: 1.52 | L254: 1.62 | M254: 1.53 | N254: 1.51 | O254: 1.87
A255: =VLOOKUP(B255,'PORTFOLIO RAW'!C:C,1,FALSE) -> 326143 | B255: 326143 | C255: STARBUCKS - MRKT VALUE TO BOOK | D255: 326143(MTBV) | E255: 8.98 | F255: 4.73 | G255: 5.02 | H255: 5.29 | I255: 6.99 | J255: 7.61 | K255: 12.77 | L255: 10.84 | M255: 14.5 | N255: 13.29 | O255: 14.61
A256: =VLOOKUP(B256,'PORTFOLIO RAW'!C:C,1,FALSE) -> 905792 | B256: 905792 | C256: PUBLIC STORAGE - MRKT VALUE TO BOOK | D256: 905792(MTBV) | E256: 2.54 | F256: 3.22 | G256: 2.38 | H256: 3.34 | I256: 3.98 | J256: 4.64 | K256: 5.39 | L256: 5.52 | M256: 7 | N256: 7.45 | O256: 7.58
A257: =VLOOKUP(B257,'PORTFOLIO RAW'!C:C,1,FALSE) -> 981722 | B257: 981722 | C257: STRYKER - MRKT VALUE TO BOOK | D257: 981722(MTBV) | E257: 5.2 | F257: 4.87 | G257: 2.84 | H257: 2.7 | I257: 2.45 | J257: 2.47 | K257: 2.98 | L257: 3.65 | M257: 4.39 | N257: 4.49 | O257: 5.36
A258: =VLOOKUP(B258,'PORTFOLIO RAW'!C:C,1,FALSE) -> 922725 | B258: 922725 | C258: SUNTRUST BANKS - MRKT VALUE TO BOOK | D258: 922725(MTBV) | E258: 1.56 | F258: 1.22 | G258: 0.68 | H258: 0.72 | I258: 0.51 | J258: 0.76 | K258: 0.86 | L258: 0.97 | M258: 0.87 | N258: 0.97 | O258: 1.2
A259: =VLOOKUP(B259,'PORTFOLIO RAW'!C:C,1,FALSE) -> 541900 | B259: 541900 | C259: SYMANTEC - MRKT VALUE TO BOOK | D259: 541900(MTBV) | E259: 1.55 | F259: 4.23 | G259: 2.8 | H259: 2.63 | I259: 2.52 | J259: 2.45 | K259: 3.03 | L259: 2.84 | M259: 3.73 | N259: 4.41 | O259: 4.13
... A282: =VLOOKUP(B282,'PORTFOLIO RAW'!C:C,1,FALSE) -> 904869 | B282: 904869 | C282: WHIRLPOOL - MRKT VALUE TO BOOK | D282: 904869(MTBV) | E282: 1.87 | F282: 2.24 | G282: 1.48 | H282: 1.44 | I282: 0.94 | J282: 1.54 | K282: 2.38 | L282: 2.49 | M282: 2.71 | N282: 2.54 | O282: 2.96
A283: =VLOOKUP(B283,'PORTFOLIO RAW'!C:C,1,FALSE) -> 26406N | B283: 26406N | C283: WYNN RESORTS - MRKT VALUE TO BOOK | D283: 26406N(MTBV) | E283: 8.18 | F283: 6.19 | G283: 2.81 | H283: 5.23 | I283: 9.16 | J283: -44.59 | K283: -85.06 | L283: -652.48 | M283: -62.06 | N283: 66.69 | O283: 15.77
A284: =VLOOKUP(B284,'PORTFOLIO RAW'!C:C,1,FALSE) -> 26393N | B284: 26393N | C284: CME GROUP - MRKT VALUE TO BOOK | D284: 26393N(MTBV) | E284: 2.41 | F284: 1.18 | G284: 1.05 | H284: 0.95 | I284: 0.82 | J284: 0.9 | K284: 1.18 | L284: 1.33 | M284: 1.49 | N284: 1.81 | O284: 2.03
A285: =VLOOKUP(B285,'PORTFOLIO RAW'!C:C,1,FALSE) -> 922407 | B285: 922407 | C285: WILLIAMS - MRKT VALUE TO BOOK | D285: 922407(MTBV) | E285: 3.17 | F285: 1.84 | G285: 1.27 | H285: 1.51 | I285: 8.82 | J285: 4.53 | K285: 5.15 | L285: 4.8 | M285: 5.63 | N285: 4.81 | O285: 2.6
A286: =VLOOKUP(B286,'PORTFOLIO RAW'!C:C,1,FALSE) -> 906979 | B286: 906979 | C286: ALLIANT ENERGY (XSC) - MRKT VALUE TO BOOK | D286: 906979(MTBV) | E286: 1.59 | F286: 1.36 | G286: 1.12 | H286: 1.38 | I286: 1.48 | J286: 1.54 | K286: 1.67 | L286: 1.85 | M286: 1.73 | N286: 2.29 | O286: 2.33
A287: =VLOOKUP(B287,'PORTFOLIO RAW'!C:C,1,FALSE) -> 877723 | B287: 877723 | C287: CARMAX - MRKT VALUE TO BOOK | D287: 877723(MTBV) | E287: 3.23 | F287: 2.28 | G287: 2.17 | H287: 2.33 | I287: 2.38 | J287: 2.27 | K287: 3.45 | L287: 3.68 | M287: 4.25 | N287: 3.43 | O287: 3.77
A288: =VLOOKUP(B288,'PORTFOLIO RAW'!C:C,1,FALSE) -> 543542 | B288: 543542 | C288: XILINX - MRKT VALUE TO BOOK | D288: 543542(MTBV) | E288: 4.79 | F288: 3.83 | G288: 2.97 | H288: 2.81 | I288: 2.94 | J288: 3.09 | K288: 4.5 | L288: 4.49 | M288: 4.24 | N288: 5.35 | O288: 7.41
A289: =VLOOKUP(B289,'PORTFOLIO RAW'!C:C,1,FALSE) -> 26276P | B289: 26276P | C289: CIMAREX EN. - MRKT VALUE TO BOOK | D289: 26276P(MTBV) | E289: 0.97 | F289: 1.87 | G289: 1.74 | H289: 2.25 | I289: 1.77 | J289: 1.53 | K289: 1.97 | L289: 2.58 | M289: 3.51 | N289: 5.08 | O289: 4.06
A290: =VLOOKUP(B290,'PORTFOLIO RAW'!C:C,1,FALSE) -> 921855 | B290: 921855 | C290: TJX - MRKT VALUE TO BOOK | D290: 921855(MTBV) | E290: 6.35 | F290: 6.4 | G290: 5.58 | H290: 5.58 | I290: 6.91 | J290: 9.07 | K290: 9.57 | L290: 9.69 | M290: 11.17 | N290: 10.93 | O290: 8.95
A291: =VLOOKUP(B291,'PORTFOLIO RAW'!C:C,1,FALSE) -> 951584 | B291: 951584 | C291: ZIONS BANCORP. - MRKT VALUE TO BOOK | D291: 951584(MTBV) | E291: 1.51 | F291: 1.16 | G291: 0.56 | H291: 0.83 | I291: 0.66 | J291: 0.78 | K291: 0.95 | L291: 0.96 | M291: 0.84 | N291: 0.88 | O291: 1.28
A292: =VLOOKUP(B292,'PORTFOLIO RAW'!C:C,1,FALSE) -> 951051 | B292: 951051 | C292: REGIONS FINL.NEW - MRKT VALUE TO BOOK | D292: 951051(MTBV) | E292: 1.11 | F292: 1.03 | G292: 0.52 | H292: 0.67 | I292: 0.37 | J292: 0.71 | K292: 0.85 | L292: 0.9 | M292: 0.75 | N292: 0.77 | O292: 1.13
A293: =VLOOKUP(B293,'PORTFOLIO RAW'!C:C,1,FALSE) -> 905997 | B293: 905997 | C293: MOLSON COORS BREWING 'B' - MRKT VALUE TO BOOK | D293: 905997(MTBV) | E293: 0.91 | F293: 1.26 | G293: 1.1 | H293: 0.98 | I293: 0.93 | J293: 0.92 | K293: 0.96 | L293: 1.61 | M293: 2.01 | N293: 1.74 | O293: 1.23
A294: =VLOOKUP(B294,'PORTFOLIO RAW'!C:C,1,FALSE) -> 31604H | B294: 31604H | C294: AMERIPRISE FINL. - MRKT VALUE TO BOOK | D294: 31604H(MTBV) | E294: 1.85 | F294: 1.53 | G294: 0.9 | H294: 1.13 | I294: 1 | J294: 1.33 | K294: 2.23 | L294: 2.92 | M294: 2.65 | N294: 2.55 | O294: 3.54
A295: =VLOOKUP(B295,'PORTFOLIO RAW'!C:C,1,FALSE) -> 543487 | B295: 543487 | C295: VIACOM 'B' - MRKT VALUE TO BOOK | D295: 543487(MTBV) | E295: 3.76 | F295: 2.37 | G295: 1.95 | H295: 2.34 | I295: 3.11 | J295: 3.76 | K295: 7.69 | L295: 9.22 | M295: 5.13 | N295: 3.35 | O295: 1.85
A296: =VLOOKUP(B296,'PORTFOLIO RAW'!C:C,1,FALSE) -> 32480Q | B296: 32480Q | C296: CBS 'B' - MRKT VALUE TO BOOK | D296: 32480Q(MTBV) | E296: 1.08 | F296: 1.24 | G296: 0.94 | H296: 1.08 | I296: 1.61 | J296: 2.3 | K296: 3.41 | L296: 4.23 | M296: 3.72 | N296: 6.07 | O296: 12.07
A297: =VLOOKUP(B297,'PORTFOLIO RAW'!C:C,1,FALSE) -> 41071J | B297: 41071J | C297: HANESBRANDS - MRKT VALUE TO BOOK | D297: 41071J(MTBV) | E297: 9.23 | F297: 13.16 | G297: 6.33 | H297: 4.4 | I297: 3.87 | J297: 3.6 | K297: 5.12 | L297: 7.7 | M297: 9.47 | N297: 7.94 | O297: 13.09
A298: =VLOOKUP(B298,'PORTFOLIO RAW'!C:C,1,FALSE) -> 41195M | B298: 41195M | C298: WESTERN UNION - MRKT VALUE TO BOOK | D298: 41195M(MTBV) | E298: 299.31 | F298: -2315.23 | G298: 38.82 | H298: 19.8 | I298: 11.39 | J298: 11.97 | K298: 9.31 | L298: 6.81 | M298: 6.76 | N298: 10.72 | O298: -17.89
A299: =VLOOKUP(B299,'PORTFOLIO RAW'!C:C,1,FALSE) -> 517465 | B299: 517465 | C299: PEOPLES UNITED FINANCIAL - MRKT VALUE TO BOOK | D299: 517465(MTBV) | E299: 1.18 | F299: 1.46 | G299: 1.11 | H299: 0.93 | I299: 0.88 | J299: 0.84 | K299: 1.01 | L299: 1 | M299: 1 | N299: 1 | O299: 1.07
A300: =VLOOKUP(B300,'PORTFOLIO RAW'!C:C,1,FALSE) -> 905840 | B300: 905840 | C300: BANK OF NEW YORK MELLON - MRKT VALUE TO BOOK | D300: 905840(MTBV) | E300: 1.68 | F300: 1.63 | G300: 1.26 | H300: 0.97 | I300: 0.75 | J300: 0.77 | K300: 0.99 | L300: 1.25 | M300: 1.21 | N300: 1.22 | O300: 1.44
A301: =VLOOKUP(B301,'PORTFOLIO RAW'!C:C,1,FALSE) -> 51245V | B301: 51245V | C301: INVESCO - MRKT VALUE TO BOOK | D301: 51245V(MTBV) | E301: NA | F301: 1.84 | G301: 1.36 | H301: 1.22 | I301: 0.99 | J301: 1.36 | K301: 1.72 | L301: 2.13 | M301: 1.77 | N301: 1.67 | O301: 1.57
A302: =VLOOKUP(B302,'PORTFOLIO RAW'!C:C,1,FALSE) -> 328314 | B302: 328314 | C302: CHUBB - MRKT VALUE TO BOOK | D302: 328314(MTBV) | E302: 1.21 | F302: 1.36 | G302: 0.88 | H302: 0.92 | I302: 0.94 | J302: 1.04 | K302: 1.17 | L302: 1.3 | M302: 1.15 | N302: 1.23 | O302: 1.35
A303: =VLOOKUP(B303,'PORTFOLIO RAW'!C:C,1,FALSE) -> 31196R | B303: 31196R | C303: DISCOVERY SERIES A - MRKT VALUE TO BOOK | D303: 31196R(MTBV) | E303: 2.59 | F303: 1.76 | G303: 1.35 | H303: 1.95 | I303: 1.58 | J303: 2.34 | K303: 3.11 | L303: 2.67 | M303: 2.16 | N303: 1.82 | O303: 1.75
A304: =VLOOKUP(B304,'PORTFOLIO RAW'!C:C,1,FALSE) -> 771767 | B304: 771767 | C304: MOSAIC - MRKT VALUE TO BOOK | D304: 771767(MTBV) | E304: 3.11 | F304: 4.98 | G304: 2.77 | H304: 2.33 | I304: 2.18 | J304: 2.27 | K304: 1.69 | L304: 1.55 | M304: 1.31 | N304: 0.92 | O304: 0.76
A305: =VLOOKUP(B305,'PORTFOLIO RAW'!C:C,1,FALSE) -> 921503 | B305: 921503 | C305: STANLEY BLACK & DECKER - MRKT VALUE TO BOOK | D305: 921503(MTBV) | E305: 2.71 | F305: 2.2 | G305: 1.7 | H305: 1.43 | I305: 1.3 | J305: 1.92 | K305: 2.12 | L305: 2.27 | M305: 2.64 | N305: 2.88 | O305: 3.09
A306: =VLOOKUP(B306,'PORTFOLIO RAW'!C:C,1,FALSE) -> 255781 | B306: 255781 | C306: GARMIN - MRKT VALUE TO BOOK | D306: 255781(MTBV) | E306: 9.85 | F306: 3.53 | G306: 2.59 | H306: 1.97 | I306: 1.98 | J306: 2.31 | K306: 2.33 | L306: 2.95 | M306: 2.07 | N306: 2.63 | O306: 2.58
A307: =VLOOKUP(B307,'PORTFOLIO RAW'!C:C,1,FALSE) -> 670129 | B307: 670129 | C307: PROLOGIS - MRKT VALUE TO BOOK | D307: 670129(MTBV) | E307: 2.28 | F307: 2.02 | G307: 1.34 | H307: 1.45 | I307: 0.99 | J307: 1.3 | K307: 1.4 | L307: 1.39 | M307: 1.37 | N307: 1.85 | O307: 2.21
A308: =VLOOKUP(B308,'PORTFOLIO RAW'!C:C,1,FALSE) -> 14352P | B308: 14352P | C308: ACCENTURE CLASS A - MRKT VALUE TO BOOK | D308: 14352P(MTBV) | E308: 10.9 | F308: 9.24 | G308: 8.57 | H308: 7.35 | I308: 9.04 | J308: 8.79 | K308: 9.09 | L308: 8.53 | M308: 8.38 | N308: 7.96 | O308: 8.24
A309: =VLOOKUP(B309,'PORTFOLIO RAW'!C:C,1,FALSE) -> 749688 | B309: 749688 | C309: HCA HEALTHCARE - MRKT VALUE TO BOOK | D309: 749688(MTBV) | E309: NA | F309: NA | G309: NA | H309: NA | I309: -1.25 | J309: -1.48 | K309: -2.28 | L309: -4.02 | M309: -4.51 | N309: -3.89 | O309: -4.13
A310: =VLOOKUP(B310,'PORTFOLIO RAW'!C:C,1,FALSE) -> 894145 | B310: 894145 | C310: RALPH LAUREN CL.A - MRKT VALUE TO BOOK | D310: 894145(MTBV) | E310: 3.61 | F310: 2.62 | G310: 2.41 | H310: 2.62 | I310: 3.84 | J310: 3.69 | K310: 3.61 | L310: 3.86 | M310: 2.54 | N310: 2.48 | O310: 2.09
A311: =VLOOKUP(B311,'PORTFOLIO RAW'!C:C,1,FALSE) -> 26599V | B311: 26599V | C311: SEAGATE TECH. - MRKT VALUE TO BOOK | D311: 26599V(MTBV) | E311: 2.96 | F311: 4.11 | G311: 2.78 | H311: 2.16 | I311: 1.37 | J311: 3.37 | K311: 5.22 | L311: 6.3 | M311: 8.51 | N311: 7.81 | O311: 5.6
A312: =VLOOKUP(B312,'PORTFOLIO RAW'!C:C,1,FALSE) -> 904878 | B312: 904878 | C312: MOTOROLA SOLUTIONS - MRKT VALUE TO BOOK | D312: 904878(MTBV) | E312: 2.65 | F312: 1.79 | G312: 2.1 | H312: 1.81 | I312: 2.92 | J312: 4.37 | K312: 4.39 | L312: 5.68 | M312: -130.87 | N312: -13.01 | O312: -8
A313: =VLOOKUP(B313,'PORTFOLIO RAW'!C:C,1,FALSE) -> 922817 | B313: 922817 | C313: AON CLASS A - MRKT VALUE TO BOOK | D313: 922817(MTBV) | E313: 2.09 | F313: 2.44 | G313: 2.15 | H313: 1.27 | I313: 1.74 | J313: 2.19 | K313: 2.85 | L313: 3.84 | M313: 4.1 | N313: 5.35 | O313: 8.1
A314: =VLOOKUP(B314,'PORTFOLIO RAW'!C:C,1,FALSE) -> 905446 | B314: 905446 | C314: INGERSOLL-RAND - MRKT VALUE TO BOOK | D314: 905446(MTBV) | E314: 1.95 | F314: 1.75 | G314: 1.44 | H314: 1.42 | I314: 1.58 | J314: 2 | K314: 2.69 | L314: 2.65 | M314: 2.51 | N314: 2.49 | O314: 3.17
A315: =VLOOKUP(B315,'PORTFOLIO RAW'!C:C,1,FALSE) -> 28513N | B315: 28513N | C315: CBRE GROUP CLASS A - MRKT VALUE TO BOOK | D315: 28513N(MTBV) | E315: 6.53 | F315: 26.02 | G315: 5.67 | H315: 6.64 | I315: 3.96 | J315: 4.14 | K315: 4.16 | L315: 4.46 | M315: 4.08 | N315: 3.18 | O315: 3.12
A316: =VLOOKUP(B316,'PORTFOLIO RAW'!C:C,1,FALSE) -> 31412T | B316: 31412T | C316: EXPEDIA GROUP - MRKT VALUE TO BOOK | D316: 31412T(MTBV) | E316: 1.8 | F316: 2.06 | G316: 2.63 | H316: 3.08 | I316: 3.61 | J316: 3.3 | K316: 3.37 | L316: 6.07 | M316: 3.31 | N316: 3.9 | O316: 4.79
A317: =VLOOKUP(B317,'PORTFOLIO RAW'!C:C,1,FALSE) -> 680902 | B317: 680902 | C317: AMERICAN TOWER - MRKT VALUE TO BOOK | D317: 680902(MTBV) | E317: 5.68 | F317: 5.23 | G317: 4.48 | H317: 5.74 | I317: 6.64 | J317: 7.83 | K317: 8.26 | L317: 9.54 | M317: 8.19 | N317: 9.65 | O317: 9.66
A318: =VLOOKUP(B318,'PORTFOLIO RAW'!C:C,1,FALSE) -> 904383 | B318: 904383 | C318: DUKE ENERGY - MRKT VALUE TO BOOK | D318: 904383(MTBV) | E318: 1.11 | F318: 1.08 | G318: 0.95 | H318: 1.03 | I318: 1.15 | J318: 1.1 | K318: 1.15 | L318: 1.29 | M318: 1.2 | N318: 1.35 | O318: 1.43
A319: =VLOOKUP(B319,'PORTFOLIO RAW'!C:C,1,FALSE) -> 13967E | B319: 13967E | C319: MONDELEZ INTERNATIONAL CL.A - MRKT VALUE TO BOOK | D319: 13967E(MTBV) | E319: 2 | F319: 2.39 | G319: 1.52 | H319: 1.54 | I319: 1.73 | J319: 2.29 | K319: 1.78 | L319: 2.17 | M319: 2.46 | N319: 2.65 | O319: 2.33
A320: =VLOOKUP(B320,'PORTFOLIO RAW'!C:C,1,FALSE) -> 903749 | B320: 903749 | C320: EATON - MRKT VALUE TO BOOK | D320: 903749(MTBV) | E320: 2.77 | F320: 1.82 | G320: 1.46 | H320: 1.85 | I320: 1.76 | J320: 1.07 | K320: 1.99 | L320: 2 | M320: 1.63 | N320: 1.92 | O320: 2.02
A321: =VLOOKUP(B321,'PORTFOLIO RAW'!C:C,1,FALSE) -> 937343 | B321: 937343 | C321: L BRANDS - MRKT VALUE TO BOOK | D321: 937343(MTBV) | E321: 3.65 | F321: 3.53 | G321: 2.48 | H321: 5.99 | I321: 89.8 | J321: -14.65 | K321: -47.01 | L321: 1081.05 | M321: -103.07 | N321: -28.33 | O321: -14.03
A322: =VLOOKUP(B322,'PORTFOLIO RAW'!C:C,1,FALSE) -> 905113 | B322: 905113 | C322: ARCONIC - MRKT VALUE TO BOOK | D322: 905113(MTBV) | E322: 2.06 | F322: 1.87 | G322: 1.11 | H322: 0.86 | I322: 0.87 | J322: 0.75 | K322: 0.84 | L322: 1.56 | M322: 1.09 | N322: 2.46 | O322: 2.38
A323: =VLOOKUP(B323,'PORTFOLIO RAW'!C:C,1,FALSE) -> 13967H | B323: 13967H | C323: WILLIS TOWERS WATSON - MRKT VALUE TO BOOK | D323: 13967H(MTBV) | E323: 4.22 | F323: 2.44 | G323: 2.17 | H323: 2.06 | I323: 2.47 | J323: 4.05 | K323: 3.54 | L323: 3.83 | M323: 3.37 | N323: 1.72 | O323: 2.02
A324: =VLOOKUP(B324,'PORTFOLIO RAW'!C:C,1,FALSE) -> 921431 | B324: 921431 | C324: BAKER HUGHES A - MRKT VALUE TO BOOK | D324: 921431(MTBV) | E324: 4.51 | F324: 3.05 | G324: 1.87 | H324: 1.24 | I324: 1.6 | J324: 1.22 | K324: 1.25 | L324: 1.58 | M324: 1.43 | N324: 1.64 | O324: 1.1
A325: =VLOOKUP(B325,'PORTFOLIO RAW'!C:C,1,FALSE) -> 266220 | B325: 266220 | C325: TAPESTRY - MRKT VALUE TO BOOK | D325: 266220(MTBV) | E325: 11.99 | F325: 5.86 | G325: 7.11 | H325: 7.64 | I325: 8.64 | J325: 6.99 | K325: 6.39 | L325: 4.1 | M325: 3.01 | N325: 3.35 | O325: 3.46
A326: =VLOOKUP(B326,'PORTFOLIO RAW'!C:C,1,FALSE) -> 30730Q | B326: 30730Q | C326: INTERCONTINENTAL EX. - MRKT VALUE TO BOOK | D326: 30730Q(MTBV) | E326: 6.35 | F326: 3.05 | G326: 2.98 | H326: 2.8 | I326: 2.88 | J326: 2.75 | K326: 1.05 | L326: 1.87 | M326: 1.7 | N326: 2.12 | O326: 2.32
A327: =VLOOKUP(B327,'PORTFOLIO RAW'!C:C,1,FALSE) -> 921925 | B327: 921925 | C327: JEFFERIES FINANCIAL GROUP - MRKT VALUE TO BOOK | D327: 921925(MTBV) | E327: 1.78 | F327: 3.83 | G327: 1.42 | H327: 0.84 | I327: 1.09 | J327: 0.86 | K327: 0.98 | L327: 0.91 | M327: 0.72 | N327: 0.67 | O327: 0.87
...

Sheet MCAP
A1: Market Capitalization
B2: 1 | C2: 2 | D2: 3 | E2: 4 | F2: 5 | G2: 6 | H2: 7 | I2: 8 | J2: 9 | K2: 10 | L2: 11 | M2: 12 | N2: 13 | O2: 14
B3: Code | C3: Name | D3: Code | E3: 2007 | F3: 2008 | G3: 2009 | H3: 2010 | I3: 2011 | J3: 2012 | K3: 2013 | L3: 2014 | M3: 2015 | N3: 2016 | O3: 2017
A4: =VLOOKUP(B4,'PORTFOLIO RAW'!B:B,1,FALSE) -> #N/A | B4: 891399 | C4: AMAZON.COM INC - MARKET CAPITALIZATION | D4: 891399(WC08001) | E4: 38538240 | F4: 21947840 | G4: 59726880 | H4: 81180000 | I4: 78760500 | J4: 113894980 | K4: 183044610 | L4: 144312750 | M4: 318344190 | N4: 357687990 | O4: 566023480
A5: =VLOOKUP(B5,'[1]PORTFOLIO RAW'!B:B,1,FALSE) -> 916328 | B5: 916328 | C5: ABBOTT LABORATORIES - MARKET CAPITALIZATION | D5: 916328(WC08001) | E5: 87027454 | F5: 82853346 | G5: 83747538 | H5: 74116001 | I5: 88302401 | J5: 103271721 | K5: 59338607 | L5: 67891755 | M5: 66137387 | N5: 56572906 | O5: 99507393
A6: =VLOOKUP(B6,'[1]PORTFOLIO RAW'!B:B,1,FALSE) -> 545101 | B6: 545101 | C6: AES CORP - MARKET CAPITALIZATION | D6: 545101(WC08001) | E6: 14338569 | F6: 5461363 | G6: 8886820 | H6: 9593056 | I6: 9059806 | J6: 7963623 | K6: 10483596 | L6: 9692032 | M6: 6381360 | N6: 7659698 | O6: 7152003
A7: =VLOOKUP(B7,'[1]PORTFOLIO RAW'!B:B,1,FALSE) -> 906187 | B7: 906187 | C7: INT'L BUSINESS MACHS - MARKET CAPITALIZATION | D7: 906187(WC08001) | E7: 149743810 | F7: 112698313 | G7: 170868669 | H7: 180220333 | I7: 213886010 | J7: 214031778 | K7: 197772108 | L7: 158919632 | M7: 132903587 | N7: 157004530 | O7: 141480737
A8: =VLOOKUP(B8,'[1]PORTFOLIO RAW'!B:B,1,FALSE) -> 936365 | B8: 936365 | C8: ADVANCED MICRO - MARKET CAPITALIZATION | D8: 936365(WC08001) | E8: 4545000 | F8: 1315440 | G8: 6495280 | H8: 5586940 | I8: 3763800 | J8: 1711200 | K8: 2805750 | L8: 2071920 | M8: 2273040 | N8: 10602900 | O8: 9940760
A9: =VLOOKUP(B9,'[1]PORTFOLIO RAW'!B:B,1,FALSE) -> 749382 | B9: 749382 | C9: ADOBE INC - MARKET CAPITALIZATION | D9: 749382(WC08001) | E9: 24416307 | F9: 11200903 | G9: 19223324 | H9: 15448390 | I9: 13895836 | J9: 18618894 | K9: 29715612 | L9: 36167087 | M9: 46764177 | N9: 50883449 | O9: 86088753
A10: =VLOOKUP(B10,'[1]PORTFOLIO RAW'!B:B,1,FALSE) -> 905271 | B10: 905271 | C10: AIR PRODUCTS & CHEMS - MARKET CAPITALIZATION | D10: 905271(WC08001) | E10: 21240531 | F10: 10523252 | G10: 17124757 | H10: 19445371 | I10: 17905682 | J10: 17852223 | K10: 23605617 | L10: 30798607 | M10: 28020374 | N10: 31259396 | O10: 35826224
A11: =VLOOKUP(B11,'[1]PORTFOLIO RAW'!B:B,1,FALSE) -> 894371 | B11: 894371 | C11: BOSTON PROPERTIES - MARKET CAPITALIZATION | D11: 894371(WC08001) | E11: 10971523 | F11: 6664936 | G11: 9314682 | H11: 12071143 | I11: 14751518 | J11: 16040924 | K11: 15354914 | L11: 19704234 | M11: 19587589 | N11: 19343728 | O11: 20066917
A12: =VLOOKUP(B12,'[1]PORTFOLIO RAW'!B:B,1,FALSE) -> 322677 | B12: 322677 | C12: ALLSTATE CORP - MARKET CAPITALIZATION | D12: 322677(WC08001) | E12: 29405490 | F12: 17559360 | G12: 16131480 | H12: 16992040 | I12: 13732410 | J12: 19241430 | K12: 24488460 | L12: 29364500 | M12: 23656290 | N12: 27127920 | O12: 37172050
A13: =VLOOKUP(B13,'[1]PORTFOLIO RAW'!B:B,1,FALSE) -> 906191 | B13: 906191 | C13: HONEYWELL INTERNATNL - MARKET CAPITALIZATION | D13: 906191(WC08001) | E13: 45965321 | F13: 24116466 | G13: 29957004 | H13: 41624280 | I13: 42104945 | J13: 49684316 | K13: 71615806 | L13: 78157424 | M13: 79790328 | N13: 88138680 | O13: 115158024
A14: =VLOOKUP(B14,'[1]PORTFOLIO RAW'!B:B,1,FALSE) -> 938692 | B14: 938692 | C14: AMGEN INC - MARKET CAPITALIZATION | D14: 938692(WC08001) | E14: 50480280 | F14: 60464250 | G14: 56287150 | H14: 51166800 | I14: 51085476 | J14: 65193060 | K14: 86084768 | L14: 121124116 | M14: 122396820 | N14: 107932222 | O14: 125590580
A15: =VLOOKUP(B15,'[1]PORTFOLIO RAW'!B:B,1,FALSE) -> 905802 | B15: 905802 | C15: HESS CORPORATION - MARKET CAPITALIZATION | D15: 905802(WC08001) | E15: 32335674 | F15: 17493760 | G15: 19797384 | H15: 25846087 | I15: 19310615 | J15: 18087303 | K15: 27001077 | L15: 21100337 | M15: 13867490 | N15: 19716230 | O15: 14955595
A16: =VLOOKUP(B16,'[1]PORTFOLIO RAW'!B:B,1,FALSE) -> 906156 | B16: 906156 | C16: AMERICAN EXPRESS CO - MARKET CAPITALIZATION | D16: 906156(WC08001) | E16: 60239160 | F16: 21518000 | G16: 48299840 | H16: 51375240 | I16: 54905880 | J16: 63515400 | K16: 96536720 | L16: 95179920 | M16: 67393950 | N16: 66968320 | O16: 85307290
... A110: =VLOOKUP(B110,'[1]PORTFOLIO RAW'!B:B,1,FALSE) -> 905016 | B110: 905016 | C110: NEXTERA ENERGY - MARKET CAPITALIZATION | D110: 905016(WC08001) | E110: 27609842 | F110: 20580707 | G110: 21847537 | H110: 21880591 | I110: 25326080 | J110: 29336560 | K110: 37244700 | L110: 47086470 | M110: 47893290 | N110: 55907280 | O110: 73565490
A111: =VLOOKUP(B111,'[1]PORTFOLIO RAW'!B:B,1,FALSE) -> 28341F | B111: 28341F | C111: ASSURANT INC - MARKET CAPITALIZATION | D111: 28341F(WC08001) | E111: 7881356 | F111: 3521056 | G111: 3438804 | H111: 3929054 | I111: 3634811 | J111: 2729642 | K111: 4767238 | L111: 4742169 | M111: 5303590 | N111: 5194726 | O111: 5285812
A112: =VLOOKUP(B112,'[1]PORTFOLIO RAW'!B:B,1,FALSE) -> 755980 | B112: 755980 | C112: FASTENAL COMPANY - MARKET CAPITALIZATION | D112: 755980(WC08001) | E112: 6027459 | F112: 5176295 | G112: 6139015 | H112: 8832574 | I112: 12876231 | J112: 13834728 | K112: 14098761 | L112: 14071475 | M112: 11820724 | N112: 13584827 | O112: 15728381
A113: =VLOOKUP(B113,'[1]PORTFOLIO RAW'!B:B,1,FALSE) -> 905994 | B113: 905994 | C113: FEDERAL REALTY INVST - MARKET CAPITALIZATION | D113: 905994(WC08001) | E113: 4817741 | F113: 3661831 | G113: 4147312 | H113: 4794754 | I113: 5766632 | J113: 6742103 | K113: 6764191 | L113: 9156128 | M113: 10152985 | N113: 10231337 | O113: 9707199
A114: =VLOOKUP(B114,'[1]PORTFOLIO RAW'!B:B,1,FALSE) -> 997198 | B114: 997198 | C114: FIFTH THIRD BANCORP - MARKET CAPITALIZATION | D114: 997198(WC08001) | E114: 13385532 | F114: 4769217 | G114: 7751913 | H114: 11689281 | I114: 11699912 | J114: 13408711 | K114: 17987080 | L114: 16789957 | M114: 15780114 | N114: 20240427 | O114: 21050040
A115: =VLOOKUP(B115,'[1]PORTFOLIO RAW'!B:B,1,FALSE) -> 951503 | B115: 951503 | C115: M&T BANK CORPORATION - MARKET CAPITALIZATION | D115: 951503(WC08001) | E115: 8960656 | F115: 6336072 | G115: 7907916 | H115: 10420115 | I115: 9594671 | J115: 12621581 | K115: 15194715 | L115: 16621150 | M115: 19335906 | N115: 24431384 | O115: 25662932
A116: =VLOOKUP(B116,'[1]PORTFOLIO RAW'!B:B,1,FALSE) -> 741123 | B116: 741123 | C116: FISERV INC - MARKET CAPITALIZATION | D116: 741123(WC08001) | E116: 9161399 | F116: 5670083 | G116: 7427136 | H116: 8602464 | I116: 8229474 | J116: 10542602 | K116: 15158135 | L116: 17054091 | M116: 20605938 | N116: 22903340 | O116: 27222588
A117: =VLOOKUP(B117,'[1]PORTFOLIO RAW'!B:B,1,FALSE) -> 546814 | B117: 546814 | C117: MACY'S INC - MARKET CAPITALIZATION | D117: 546814(WC08001) | E117: 10857639 | F117: 4348035 | G117: 7052608 | H117: 10709490 | I117: 13328956 | J117: 15128054 | K117: 19487529 | L117: 22392721 | M117: 10852758 | N117: 10888489 | O117: 7677030
A118: =VLOOKUP(B118,'[1]PORTFOLIO RAW'!B:B,1,FALSE) -> 938076 | B118: 938076 | C118: FRANKLIN RESOURCES - MARKET CAPITALIZATION | D118: 938076(WC08001) | E118: 28089120 | F118: 14846580 | G118: 24159320 | H118: 24911893 | I118: 20911631 | J118: 26674666 | K118: 36422869 | L118: 34489590 | M118: 22221503 | N118: 22574261 | O118: 24042315
A119: =VLOOKUP(B119,'[1]PORTFOLIO RAW'!B:B,1,FALSE) -> 152594 | B119: 152594 | C119: FREEPORT-MCMORAN INC - MARKET CAPITALIZATION | D119: 152594(WC08001) | E119: 39234520 | F119: 9384960 | G119: 34524700 | H119: 56742525 | I119: 34876920 | J119: 32455800 | K119: 39174120 | L119: 24271040 | M119: 8435420 | N119: 19059550 | O119: 27454080
A120: =VLOOKUP(B120,'[1]PORTFOLIO RAW'!B:B,1,FALSE) -> 951018 | B120: 951018 | C120: GAP INC - MARKET CAPITALIZATION | D120: 951018(WC08001) | E120: 15619520 | F120: 9292660 | G120: 14162200 | H120: 13018320 | I120: 8996750 | J120: 14371520 | K120: 17429680 | L120: 17728310 | M120: 9805900 | N120: 8953560 | O120: 13249340
A121: =VLOOKUP(B121,'[1]PORTFOLIO RAW'!B:B,1,FALSE) -> 907652 | B121: 907652 | C121: GENERAL DYNAMICS - MARKET CAPITALIZATION | D121: 907652(WC08001) | E121: 42882558 | F121: 27751506 | G121: 26293489 | H121: 26400832 | I121: 23671040 | J121: 24499015 | K121: 33767637 | L121: 45712423 | M121: 42991932 | N121: 52215583 | O121: 60403411
A122: =VLOOKUP(B122,'[1]PORTFOLIO RAW'!B:B,1,FALSE) -> 905801 | B122: 905801 | C122: GENERAL MILLS, INC. - MARKET CAPITALIZATION | D122: 905801(WC08001) | E122: 19380000 | F122: 20503125 | G122: 23225680 | H122: 23364835 | I122: 26056368 | J122: 26212370 | K122: 31982328 | L122: 32653959 | M122: 34521042 | N122: 36864336 | O122: 34204401
A123: =VLOOKUP(B123,'[1]PORTFOLIO RAW'!B:B,1,FALSE) -> 906511 | B123: 906511 | C123: GENUINE PARTS CO - MARKET CAPITALIZATION | D123: 906511(WC08001) | E123: 7688821 | F123: 6036244 | G123: 6032521 | H123: 8093046 | I123: 9525848 | J123: 9844819 | K123: 12792384 | L123: 16317257 | M123: 12890498 | N123: 14179132 | O123: 13933465
... A182: =VLOOKUP(B182,'[1]PORTFOLIO RAW'!B:B,1,FALSE) -> 771830 | B182: 771830 | C182: MAXIM INTEGRATED PRD - MARKET CAPITALIZATION | D182: 771830(WC08001) | E182: 8488256 | F182: 3660715 | G182: 6218306 | H182: 7106030 | I182: 7702111 | J182: 8606321 | K182: 8024598 | L182: 9065135 | M182: 10823274 | N182: 10950370 | O182: 14790639
A183: =VLOOKUP(B183,'[1]PORTFOLIO RAW'!B:B,1,FALSE) -> 312367 | B183: 312367 | C183: ACTIVISION BLIZZARD - MARKET CAPITALIZATION | D183: 312367(WC08001) | E183: NA | F183: 11225706 | G183: 13892290 | H183: 14720499 | I183: 13963382 | J183: 11805257 | K183: 12547131 | L183: 14546879 | M183: 28432598 | N183: 26919521 | O183: 47965229
A184: =VLOOKUP(B184,'[1]PORTFOLIO RAW'!B:B,1,FALSE) -> 912635 | B184: 912635 | C184: CVS HEALTH CORP - MARKET CAPITALIZATION | D184: 912635(WC08001) | E184: 57099166 | F184: 41350106 | G184: 44804110 | H184: 47391510 | I184: 52932440 | J184: 59518850 | K184: 84452600 | L184: 109793400 | M184: 107644770 | N184: 83723510 | O184: 73515000
A185: =VLOOKUP(B185,'[1]PORTFOLIO RAW'!B:B,1,FALSE) -> 152533 | B185: 152533 | C185: LAB CORP OF AMERICA - MARKET CAPITALIZATION | D185: 152533(WC08001) | E185: 8383830 | F185: 6969162 | G185: 7880652 | H185: 9003008 | I185: 8407866 | J185: 8098970 | K185: 7830409 | L185: 9128340 | M185: 12524732 | N185: 13184626 | O185: 16254069
A186: =VLOOKUP(B186,'[1]PORTFOLIO RAW'!B:B,1,FALSE) -> 719643 | B186: 719643 | C186: MICROSOFT CORP - MARKET CAPITALIZATION | D186: 719643(WC08001) | E186: 333928000 | F186: 177895440 | G186: 271515840 | H186: 241923880 | I186: 217440960 | J186: 223853996 | K186: 311550480 | L186: 382701550 | M186: 445337960 | N186: 485189120 | O186: 659342320
A187: =VLOOKUP(B187,'[1]PORTFOLIO RAW'!B:B,1,FALSE) -> 999506 | B187: 999506 | C187: MICRON TECHNOLOGY - MARKET CAPITALIZATION | D187: 999506(WC08001) | E187: 5494775 | F187: 2009304 | G187: 8962272 | H187: 7975890 | I187: 6191247 | J187: 6452218 | K187: 22715700 | L187: 37565730 | M187: 14712240 | N187: 22796800 | O187: 45725440
A188: =VLOOKUP(B188,'[1]PORTFOLIO RAW'!B:B,1,FALSE) -> 328228 | B188: 328228 | C188: MICROCHIP TECHNOLOGY - MARKET CAPITALIZATION | D188: 328228(WC08001) | E188: 6831964 | F188: 3600136 | G188: 5309443 | H188: 6340110 | I188: 6942913 | J188: 6294776 | K188: 8792160 | L188: 9022123 | M188: 9404817 | N188: 13091843 | O188: 20132751
A189: =VLOOKUP(B189,'[1]PORTFOLIO RAW'!B:B,1,FALSE) -> 902172 | B189: 902172 | C189: 3M COMPANY - MARKET CAPITALIZATION | D189: 902172(WC08001) | E189: 59796037 | F189: 39906481 | G189: 58745229 | H189: 61443668 | I189: 56799901 | J189: 63796460 | K189: 93027298 | L189: 104365316 | M189: 91789490 | N189: 106557411 | O189: 140017903
A190: =VLOOKUP(B190,'[1]PORTFOLIO RAW'!B:B,1,FALSE) -> 325475 | B190: 325475 | C190: MOHAWK INDUSTRIES - MARKET CAPITALIZATION | D190: 325475(WC08001) | E190: 5085835 | F190: 2940050 | G190: 3259838 | H190: 3895382 | I190: 4116543 | J190: 6256272 | K190: 10822945 | L190: 11327764 | M190: 14001413 | N190: 14809866 | O190: 20532754
A191: =VLOOKUP(B191,'[1]PORTFOLIO RAW'!B:B,1,FALSE) -> 905010 | B191: 905010 | C191: XCEL ENERGY INC - MARKET CAPITALIZATION | D191: 905010(WC08001) | E191: 9677626 | F191: 8417837 | G191: 9708347 | H191: 11358960 | I191: 13446692 | J191: 13033399 | K191: 13913324 | L191: 18165939 | M191: 18225601 | N191: 20643968 | O191: 24428472
A192: =VLOOKUP(B192,'[1]PORTFOLIO RAW'!B:B,1,FALSE) -> 902230 | B192: 902230 | C192: FORD MOTOR COMPANY - MARKET CAPITALIZATION | D192: 902230(WC08001) | E192: 14772350 | F192: 5523480 | G192: 33370000 | H192: 63511717 | I192: 40896036 | J192: 50793107 | K192: 61473120 | L192: 62139500 | M192: 56796790 | N192: 49090110 | O192: 50684420
A193: =VLOOKUP(B193,'[1]PORTFOLIO RAW'!B:B,1,FALSE) -> 884383 | B193: 884383 | C193: NATL OILWELL VARCO - MARKET CAPITALIZATION | D193: 884383(WC08001) | E193: 25794989 | F193: 10200057 | G193: 18449537 | H193: 28321783 | I193: 28821002 | J193: 29180551 | K193: 34073332 | L193: 27455603 | M193: 12584363 | N193: 14176184 | O193: 13691381
A194: =VLOOKUP(B194,'[1]PORTFOLIO RAW'!B:B,1,FALSE) -> 867422 | B194: 867422 | C194: NETAPP INC. - MARKET CAPITALIZATION | D194: 867422(WC08001) | E194: 9161069 | F194: 4773759 | G194: 11415766 | H194: 19087608 | I194: 13383630 | J194: 12232330 | K194: 14670524 | L194: 13450525 | M194: 8120833 | N194: 9910870 | O194: 14881080
A195: =VLOOKUP(B195,'[1]PORTFOLIO RAW'!B:B,1,FALSE) -> 906933 | B195: 906933 | C195: NEWELL BRANDS INC - MARKET CAPITALIZATION | D195: 906933(WC08001) | E195: 7160996 | F195: 2710038 | G195: 4169778 | H195: 5281290 | I195: 4656045 | J195: 6389263 | K195: 9029426 | L195: 10253828 | M195: 11778176 | N195: 21543625 | O195: 14992680
... A237: =VLOOKUP(B237,'[1]PORTFOLIO RAW'!B:B,1,FALSE) -> 933974 | B237: 933974 | C237: TRAVELERS COS - MARKET CAPITALIZATION | D237: 933974(WC08001) | E237: 33775640 | F237: 26446520 | G237: 25942158 | H237: 24211566 | I237: 23241976 | J237: 27104868 | K237: 32005890 | L237: 34104870 | M237: 33395274 | N237: 34228632 | O237: 36812696
A238: =VLOOKUP(B238,'[1]PORTFOLIO RAW'!B:B,1,FALSE) -> 14015T | B238: 14015T | C238: FIDELITY NATNL INF - MARKET CAPITALIZATION | D238: 14015T(WC08001) | E238: 8097573 | F238: 3105943 | G238: 8778280 | H238: 8269041 | I238: 7788211 | J238: 10237621 | K238: 15599408 | L238: 17720780 | M238: 19664700 | N238: 24809920 | O238: 31331970
A239: =VLOOKUP(B239,'[1]PORTFOLIO RAW'!B:B,1,FALSE) -> 905019 | B239: 905019 | C239: MERCK & CO INC - MARKET CAPITALIZATION | D239: 905019(WC08001) | E239: 126244143 | F239: 64073786 | G239: 113574452 | H239: 111079130 | I239: 114639617 | J239: 123910449 | K239: 146522712 | L239: 161177982 | M239: 146899185 | N239: 161817813 | O239: 151738335
A240: =VLOOKUP(B240,'[1]PORTFOLIO RAW'!B:B,1,FALSE) -> 912090 | B240: 912090 | C240: SCHLUMBERGER LIMITED - MARKET CAPITALIZATION | D240: 912090(WC08001) | E240: 117612778 | F240: 50546289 | G240: 77770372 | H240: 113657814 | I240: 91110198 | J240: 92046266 | K240: 117803540 | L240: 108924432 | M240: 87606000 | N240: 116774450 | O240: 93267760
A241: =VLOOKUP(B241,'[1]PORTFOLIO RAW'!B:B,1,FALSE) -> 755741 | B241: 755741 | C241: CHARLES SCHWAB CORP - MARKET CAPITALIZATION | D241: 755741(WC08001) | E241: 29658865 | F241: 18710307 | G241: 21871309 | H241: 20572760 | I241: 14313316 | J241: 18345318 | K241: 33719041 | L241: 39570705 | M241: 43478716 | N241: 52603638 | O241: 69109733
A242: =VLOOKUP(B242,'[1]PORTFOLIO RAW'!B:B,1,FALSE) -> 14361V | B242: 14361V | C242: ZIMMER BIOMET - MARKET CAPITALIZATION | D242: 14361V(WC08001) | E242: 15406335 | F242: 9037912 | G242: 12070262 | H242: 10499808 | I242: 9508760 | J242: 11438856 | K242: 15823662 | L242: 19247374 | M242: 20794993 | N242: 20701920 | O242: 24447742
A243: =VLOOKUP(B243,'[1]PORTFOLIO RAW'!B:B,1,FALSE) -> 154680 | B243: 154680 | C243: AMERISOURCEBERGEN - MARKET CAPITALIZATION | D243: 154680(WC08001) | E243: 7604394 | F243: 5570643 | G243: 7506133 | H243: 9469023 | I243: 9706272 | J243: 10164325 | K243: 16170893 | L243: 20007284 | M243: 21456756 | N243: 17205749 | O243: 20016172
A244: =VLOOKUP(B244,'[1]PORTFOLIO RAW'!B:B,1,FALSE) -> 14698C | B244: 14698C | C244: PRINCIPAL FINL GROUP - MARKET CAPITALIZATION | D244: 14698C(WC08001) | E244: 17836444 | F244: 5852401 | G244: 7668760 | H244: 10432224 | I244: 7407060 | J244: 8379176 | K244: 14556312 | L244: 15265166 | M244: 13107172 | N244: 16646322 | O244: 20391840
A245: =VLOOKUP(B245,'[1]PORTFOLIO RAW'!B:B,1,FALSE) -> 905361 | B245: 905361 | C245: SHERWIN-WILLIAMS CO - MARKET CAPITALIZATION | D245: 905361(WC08001) | E245: 7128139 | F245: 6992848 | G245: 6746783 | H245: 8962986 | I245: 9271067 | J245: 15885002 | K245: 18373741 | L245: 24910986 | M245: 23947198 | N245: 24996322 | O245: 38496050
A246: =VLOOKUP(B246,'[1]PORTFOLIO RAW'!B:B,1,FALSE) -> 357834 | B246: 357834 | C246: SIMON PROPERTY GROUP - MARKET CAPITALIZATION | D246: 357834(WC08001) | E246: 19372758 | F246: 12290225 | G246: 22802712 | H246: 29545084 | I246: 37888793 | J246: 48991431 | K246: 47262199 | L246: 56597586 | M246: 60163735 | N246: 55623960 | O246: 53439796
A247: =VLOOKUP(B247,'[1]PORTFOLIO RAW'!B:B,1,FALSE) -> 906400 | B247: 906400 | C247: SNAP-ON INC - MARKET CAPITALIZATION | D247: 906400(WC08001) | E247: 2770382 | F247: 2262064 | G247: 2440306 | H247: 3291912 | I247: 2947347 | J247: 4601546 | K247: 6364840 | L247: 7946433 | M247: 9957691 | N247: 9925072 | O247: 9881110
A248: =VLOOKUP(B248,'[1]PORTFOLIO RAW'!B:B,1,FALSE) -> 14861V | B248: 14861V | C248: PRUDENTIAL FINANCIAL - MARKET CAPITALIZATION | D248: 14861V(WC08001) | E248: 41809092 | F248: 12809660 | G248: 23094171 | H248: 28521245 | I248: 23558337 | J248: 24800229 | K248: 42702955 | L248: 41325156 | M248: 36398522 | N248: 44701488 | O248: 48585054
A249: =VLOOKUP(B249,'[1]PORTFOLIO RAW'!B:B,1,FALSE) -> 14806F | B249: 14806F | C249: ADVANCE AUTO PARTS - MARKET CAPITALIZATION | D249: 14806F(WC08001) | E249: 3763289 | F249: 3191770 | G249: 3789859 | H249: 5421389 | I249: 5068994 | J249: 5309260 | K249: 8061931 | L249: 11639227 | M249: 11034490 | N249: 12472431 | O249: 7370680
A250: =VLOOKUP(B250,'[1]PORTFOLIO RAW'!B:B,1,FALSE) -> 902324 | B250: 902324 | C250: EDISON INTERNATIONAL - MARKET CAPITALIZATION | D250: 902324(WC08001) | E250: 17388544 | F250: 10465056 | G250: 11331714 | H250: 12576313 | I250: 13488584 | J250: 14723408 | K250: 15085059 | L250: 21334118 | M250: 19291282 | N250: 23455149 | O250: 20604301
A251: =VLOOKUP(B251,'[1]PORTFOLIO RAW'!B:B,1,FALSE) -> 902325 | B251: 902325 | C251: SOUTHERN CO - MARKET CAPITALIZATION | D251: 902325(WC08001) | E251: 29589500 | F251: 28771200 | G251: 27305740 | H251: 32247005 | I251: 40046636 | J251: 37149148 | K251: 36476903 | L251: 44606613 | M251: 42373024 | N251: 48707938 | O251: 48046719
A252: =VLOOKUP(B252,'[1]PORTFOLIO RAW'!B:B,1,FALSE) -> 992305 | B252: 992305 | C252: BB&T CORPORATION - MARKET CAPITALIZATION | D252: 992305(WC08001) | E252: 16744440 | F252: 15356950 | G252: 17498958 | H252: 18255276 | I252: 17547089 | J252: 20369082 | K252: 26371058 | L252: 28027945 | M252: 29504542 | N252: 38061515 | O252: 38881338
A253: =VLOOKUP(B253,'[1]PORTFOLIO RAW'!B:B,1,FALSE) -> 905647 | B253: 905647 | C253: SOUTHWEST AIRLINES - MARKET CAPITALIZATION | D253: 905647(WC08001) | E253: 8964530 | F253: 6378736 | G253: 8490100 | H253: 9701697 | I253: 6613119 | J253: 7478472 | K253: 13196943 | L253: 28591142 | M253: 29091081 | N253: 32276465 | O253: 38520648
A254: =VLOOKUP(B254,'[1]PORTFOLIO RAW'!B:B,1,FALSE) -> 945388 | B254: 945388 | C254: AT&T INC - MARKET CAPITALIZATION | D254: 945388(WC08001) | E254: 251169741 | F254: 167950500 | G254: 165431123 | H254: 173667732 | I254: 179217719 | J254: 188148817 | K254: 183757277 | L254: 174228406 | M254: 211447380 | N254: 261091413 | O254: 238700826
A255: =VLOOKUP(B255,'[1]PORTFOLIO RAW'!B:B,1,FALSE) -> 905024 | B255: 905024 | C255: CHEVRON CORPORATION - MARKET CAPITALIZATION | D255: 905024(WC08001) | E255: 195100202 | F255: 148253025 | G255: 154574502 | H255: 183182621 | I255: 210796161 | J255: 210515910 | K255: 239028159 | L255: 210859003 | M255: 169377947 | N255: 222630306 | O255: 238449629
A256: =VLOOKUP(B256,'[1]PORTFOLIO RAW'!B:B,1,FALSE) -> 951052 | B256: 951052 | C256: STATE STREET CORP - MARKET CAPITALIZATION | D256: 951052(WC08001) | E256: 31366261 | F256: 16973163 | G256: 21549415 | H256: 23246203 | I256: 19648056 | J256: 21561703 | K256: 31860697 | L256: 32592819 | M256: 26520906 | N256: 29684310 | O256: 35886303
A257: =VLOOKUP(B257,'[1]PORTFOLIO RAW'!B:B,1,FALSE) -> 326143 | B257: 326143 | C257: STARBUCKS CORP - MARKET CAPITALIZATION | D257: 326143(WC08001) | E257: 15112700 | F257: 6957830 | G257: 17131274 | H257: 23859738 | I257: 34268248 | J257: 40184959 | K257: 59043348 | L257: 61496475 | M257: 89150553 | N257: 81086960 | O257: 82216788
A258: =VLOOKUP(B258,'[1]PORTFOLIO RAW'!B:B,1,FALSE) -> 905792 | B258: 905792 | C258: PUBLIC STORAGE, INC - MARKET CAPITALIZATION | D258: 905792(WC08001) | E258: 12437304 | F258: 13378239 | G258: 13716631 | H258: 17165621 | I258: 22890310 | J258: 24844446 | K258: 25855767 | L258: 31876561 | M258: 42832591 | N258: 38730044 | O258: 36335354
A259: =VLOOKUP(B259,'[1]PORTFOLIO RAW'!B:B,1,FALSE) -> 981722 | B259: 981722 | C259: STRYKER CORPORATION - MARKET CAPITALIZATION | D259: 981722(WC08001) | E259: 30709920 | F259: 15836180 | G259: 20042223 | H259: 21002070 | I259: 18939510 | J259: 20831600 | K259: 28402920 | L259: 35656740 | M259: 34666620 | N259: 44928750 | O259: 57972096
A260: =VLOOKUP(B260,'[1]PORTFOLIO RAW'!B:B,1,FALSE) -> 922725 | B260: 922725 | C260: SUNTRUST BANKS INC - MARKET CAPITALIZATION | D260: 922725(WC08001) | E260: 21772214 | F260: 10472373 | G260: 10127763 | H260: 14767866 | I260: 9504316 | J260: 15279488 | K260: 19733731 | L260: 21978226 | M260: 21793222 | N260: 26941662 | O260: 30417433
A261: =VLOOKUP(B261,'[1]PORTFOLIO RAW'!B:B,1,FALSE) -> 541900 | B261: 541900 | C261: SYMANTEC CORP - MARKET CAPITALIZATION | D261: 541900(WC08001) | E261: 14516590 | F261: 11348512 | G261: 14615683 | H261: 13358520 | I261: 11862700 | J261: 13625680 | K261: 16458840 | L261: 17830225 | M261: 14364000 | N261: 14620680 | O261: 17061013
... A284: =VLOOKUP(B284,'[1]PORTFOLIO RAW'!B:B,1,FALSE) -> 904869 | B284: 904869 | C284: WHIRLPOOL CORP - MARKET CAPITALIZATION | D284: 904869(WC08001) | E284: 6203880 | F284: 3018550 | G284: 6049500 | H284: 6751080 | I284: 3606200 | J284: 8038250 | K284: 12078220 | L284: 15111720 | M284: 11308990 | N284: 13450980 | O284: 11973440
A285: =VLOOKUP(B285,'[1]PORTFOLIO RAW'!B:B,1,FALSE) -> 26406N | B285: 26406N | C285: WYNN RESORTS, LTD - MARKET CAPITALIZATION | D285: 26406N(WC08001) | E285: 12824318 | F285: 4733671 | G285: 7179378 | H285: 12938413 | I285: 13820199 | J285: 11346496 | K285: 19652578 | L285: 15090110 | M285: 7027760 | N285: 8806672 | O285: 17365759
A286: =VLOOKUP(B286,'[1]PORTFOLIO RAW'!B:B,1,FALSE) -> 26393N | B286: 26393N | C286: CME GROUP INC - MARKET CAPITALIZATION | D286: 26393N(WC08001) | E286: 36550766 | F286: 13822666 | G286: 22346077 | H286: 21509032 | I286: 16114174 | J286: 16814085 | K286: 26194271 | L286: 29738095 | M286: 30526867 | N286: 39016346 | O286: 49545730
A287: =VLOOKUP(B287,'[1]PORTFOLIO RAW'!B:B,1,FALSE) -> 922407 | B287: 922407 | C287: WILLIAMS COMPANIES - MARKET CAPITALIZATION | D287: 922407(WC08001) | E287: 20967080 | F287: 8369440 | G287: 12289640 | H287: 14461200 | I287: 19514820 | J287: 22295940 | K287: 26343310 | L287: 33570180 | M287: 19249300 | N287: 23355000 | O287: 25184740
A288: =VLOOKUP(B288,'[1]PORTFOLIO RAW'!B:B,1,FALSE) -> 906979 | B288: 906979 | C288: ALLIANT ENERGY CORP - MARKET CAPITALIZATION | D288: 906979(WC08001) | E288: 4490520 | F288: 3222905 | G288: 3348466 | H288: 4077569 | I288: 4897040 | J288: 4873457 | K288: 5724693 | L288: 7368348 | M288: 7085528 | N288: 8626555 | O288: 9857766
A289: =VLOOKUP(B289,'[1]PORTFOLIO RAW'!B:B,1,FALSE) -> 877723 | B289: 877723 | C289: CARMAX INC - MARKET CAPITALIZATION | D289: 877723(WC08001) | E289: 4266556 | F289: 1722695 | G289: 5344506 | H289: 7111329 | I289: 6884996 | J289: 8526035 | K289: 10622105 | L289: 14759853 | M289: 11272697 | N289: 12537521 | O289: 11963362
A290: =VLOOKUP(B290,'[1]PORTFOLIO RAW'!B:B,1,FALSE) -> 543542 | B290: 543542 | C290: XILINX INC - MARKET CAPITALIZATION | D290: 543542(WC08001) | E290: 6471377 | F290: 4998849 | G290: 6904205 | H290: 7925653 | I290: 8483140 | J290: 9453390 | K290: 12106762 | L290: 11629296 | M290: 12134230 | N290: 15315084 | O290: 16721980
A291: =VLOOKUP(B291,'[1]PORTFOLIO RAW'!B:B,1,FALSE) -> 26276P | B291: 26276P | C291: CIMAREX ENERGY CO - MARKET CAPITALIZATION | D291: 26276P(WC08001) | E291: 3510497 | F291: 2229666 | G291: 4378320 | H291: 7545830 | I291: 5309416 | J291: 4999186 | K291: 9143137 | L291: 9284809 | M291: 8475063 | N291: 12927287 | O291: 11644321
A292: =VLOOKUP(B292,'[1]PORTFOLIO RAW'!B:B,1,FALSE) -> 921855 | B292: 921855 | C292: TJX COMPANIES INC - MARKET CAPITALIZATION | D292: 921855(WC08001) | E292: 12294990 | F292: 8491740 | G292: 14963063 | H292: 17296889 | I292: 24099808 | J292: 30729640 | K292: 44930723 | L292: 46959003 | M292: 47048481 | N292: 48557950 | O292: 48017570
A293: =VLOOKUP(B293,'[1]PORTFOLIO RAW'!B:B,1,FALSE) -> 951584 | B293: 951584 | C293: ZIONS BANCORP - MARKET CAPITALIZATION | D293: 951584(WC08001) | E293: 5001270 | F293: 2827070 | G293: 1929954 | H293: 4428858 | I293: 2997724 | J293: 3941863 | K293: 5532944 | L293: 5787955 | M293: 5580587 | N293: 8740783 | O293: 10040552
A294: =VLOOKUP(B294,'[1]PORTFOLIO RAW'!B:B,1,FALSE) -> 951051 | B294: 951051 | C294: REGIONS FINANCIAL - MARKET CAPITALIZATION | D294: 951051(WC08001) | E294: 16404491 | F294: 5503273 | G294: 6308905 | H294: 8793655 | I294: 5412910 | J294: 10077111 | K294: 13625658 | L294: 14297627 | M294: 12454375 | N294: 17441377 | O294: 19596699
A295: =VLOOKUP(B295,'[1]PORTFOLIO RAW'!B:B,1,FALSE) -> 29756N | B295: 29756N | C295: CELANESE CORPORATION - MARKET CAPITALIZATION | D295: 29756N(WC08001) | E295: 6436991 | F295: 1783776 | G295: 4635050 | H295: 6412610 | I295: 6926653 | J295: 8177010 | K295: 8680342 | L295: 9168046 | M295: 9882852 | N295: 11075604 | O295: 14538172
A296: =VLOOKUP(B296,'[1]PORTFOLIO RAW'!B:B,1,FALSE) -> 905997 | B296: 905997 | C296: MOLSON COORS BREW - MARKET CAPITALIZATION | D296: 905997(WC08001) | E296: 9330443 | F296: 8864304 | G296: 8372664 | H296: 9375492 | I296: 7837200 | J296: 7766385 | K296: 10342830 | L296: 13823460 | M296: 17328240 | N296: 20911919 | O296: 17677878
A297: =VLOOKUP(B297,'[1]PORTFOLIO RAW'!B:B,1,FALSE) -> 31604H | B297: 31604H | C297: AMERIPRISE FIN - MARKET CAPITALIZATION | D297: 31604H(WC08001) | E297: 12551184 | F297: 5057440 | G297: 9902982 | H297: 14197464 | I297: 11017250 | J297: 12772950 | K297: 22103211 | L297: 24216233 | M297: 18201360 | N297: 17169064 | O297: 24850177
A298: =VLOOKUP(B298,'[1]PORTFOLIO RAW'!B:B,1,FALSE) -> 543487 | B298: 543487 | C298: VIACOM, INC. - MARKET CAPITALIZATION | D298: 543487(WC08001) | E298: 28319616 | F298: 11565608 | G298: 18058002 | H298: 24102685 | I298: 25352403 | J298: 26739180 | K298: 39241862 | L298: 31168550 | M298: 16385796 | N298: 13934700 | O298: 12397944
A299: =VLOOKUP(B299,'[1]PORTFOLIO RAW'!B:B,1,FALSE) -> 32480Q | B299: 32480Q | C299: CBS CORPORATION - MARKET CAPITALIZATION | D299: 32480Q(WC08001) | E299: 18309275 | F299: 5493852 | G299: 9480940 | H299: 12957810 | I299: 17668140 | J299: 23971500 | K299: 37989040 | L299: 28057380 | M299: 21821190 | N299: 26211440 | O299: 22597000
A300: =VLOOKUP(B300,'[1]PORTFOLIO RAW'!B:B,1,FALSE) -> 41071J | B300: 41071J | C300: HANESBRANDS, INC. - MARKET CAPITALIZATION | D300: 41071J(WC08001) | E300: 2587466 | F300: 1192382 | G300: 2300021 | H300: 2443658 | I300: 2131729 | J300: 3520027 | K300: 6988736 | L300: 11184020 | M300: 11526342 | N300: 8168280 | O300: 7530232
A301: =VLOOKUP(B301,'[1]PORTFOLIO RAW'!B:B,1,FALSE) -> 41195M | B301: 41195M | C301: WESTERN UNION COMP - MARKET CAPITALIZATION | D301: 41195M(WC08001) | E301: 18205144 | F301: 10175664 | G301: 12940525 | H301: 12144780 | I301: 11310244 | J301: 7786281 | K301: 9466800 | L301: 9340065 | M301: 8997984 | N301: 10458180 | O301: 8725590
A302: =VLOOKUP(B302,'[1]PORTFOLIO RAW'!B:B,1,FALSE) -> 517465 | B302: 517465 | C302: PEOPLE'S UNITED - MARKET CAPITALIZATION | D302: 517465(WC08001) | E302: 5309740 | F302: 6146001 | G302: 5761500 | H302: 5030991 | I302: 4593875 | J302: 4105764 | K302: 4641840 | L302: 4672404 | M302: 5008115 | N302: 6115824 | O302: 6481420
A303: =VLOOKUP(B303,'[1]PORTFOLIO RAW'!B:B,1,FALSE) -> 905840 | B303: 905840 | C303: BANK OF NEW YORK - MARKET CAPITALIZATION | D303: 905840(WC08001) | E303: 55878145 | F303: 32536079 | G303: 33783137 | H303: 37494212 | I303: 24084621 | J303: 29901702 | K303: 39910208 | L303: 45366492 | M303: 44737838 | N303: 49629996 | O303: 54584010
A304: =VLOOKUP(B304,'[1]PORTFOLIO RAW'!B:B,1,FALSE) -> 328314 | B304: 328314 | C304: CHUBB - MARKET CAPITALIZATION | D304: 328314(WC08001) | E304: 20369146 | F304: 17656518 | G304: 16960843 | H304: 20850193 | I304: 23625341 | J304: 27157658 | K304: 35178866 | L304: 37756425 | M304: 37925238 | N304: 61563787 | O304: 67779942
A305: =VLOOKUP(B305,'[1]PORTFOLIO RAW'!B:B,1,FALSE) -> 31196R | B305: 31196R | C305: DISCOVERY INC - MARKET CAPITALIZATION | D305: 31196R(WC08001) | E305: NA | F305: 3993120 | G305: 8710280 | H305: 11842800 | I305: 10693170 | J305: 15571644 | K305: 21266784 | L305: 15120105 | M305: 11152240 | N305: 10689900 | O305: 8504400
A306: =VLOOKUP(B306,'[1]PORTFOLIO RAW'!B:B,1,FALSE) -> 771767 | B306: 771767 | C306: MOSAIC CO - MARKET CAPITALIZATION | D306: 771767(WC08001) | E306: 41586513 | F306: 15359805 | G306: 26550779 | H306: 34013798 | I306: 22520663 | J306: 24094387 | K306: 20137301 | L306: 16778214 | M306: 9725896 | N306: 10272497 | O306: 9007934
A307: =VLOOKUP(B307,'[1]PORTFOLIO RAW'!B:B,1,FALSE) -> 921503 | B307: 921503 | C307: STANLEY BLACK - MARKET CAPITALIZATION | D307: 921503(WC08001) | E307: 3896764 | F307: 2689673 | G307: 4145454 | H307: 11123653 | I307: 11427575 | J307: 11831651 | K307: 12545619 | L307: 15096613 | M307: 16430474 | N307: 17497080 | O307: 26138713
A308: =VLOOKUP(B308,'[1]PORTFOLIO RAW'!B:B,1,FALSE) -> 255781 | B308: 255781 | C308: GARMIN LTD. - MARKET CAPITALIZATION | D308: 255781(WC08001) | E308: 21047060 | F308: 3840959 | G308: 6148412 | H308: 6023156 | I308: 7749519 | J308: 7970368 | K308: 9013983 | L308: 10133586 | M308: 7051967 | N308: 9143517 | O308: 11210419
A309: =VLOOKUP(B309,'[1]PORTFOLIO RAW'!B:B,1,FALSE) -> 670129 | B309: 670129 | C309: PROLOGIS - MARKET CAPITALIZATION | D309: 670129(WC08001) | E309: 5710557 | F309: 2306164 | G309: 3813552 | H309: 5350621 | I309: 13111288 | J309: 16849987 | K309: 18430623 | L309: 21923699 | M309: 22512055 | N309: 27908542 | O309: 34331319
A310: =VLOOKUP(B310,'[1]PORTFOLIO RAW'!B:B,1,FALSE) -> 14352P | B310: 14352P | C310: ACCENTURE PLC - MARKET CAPITALIZATION | D310: 14352P(WC08001) | E310: 27330590 | F310: 23976484 | G310: 29584317 | H310: 33459247 | I310: 36771251 | J310: 45003917 | K310: 54787741 | L310: 58637023 | M310: 67928811 | N310: 75266594 | O310: 97378767
A311: =VLOOKUP(B311,'[1]PORTFOLIO RAW'!B:B,1,FALSE) -> 894145 | B311: 894145 | C311: RALPH LAUREN - MARKET CAPITALIZATION | D311: 894145(WC08001) | E311: 6426160 | F311: 4518295 | G311: 8033216 | H311: 10892344 | I311: 13048560 | J311: 13897584 | K311: 16050213 | L311: 16423692 | M311: 9620724 | N311: 7487528 | O311: 8398890
A312: =VLOOKUP(B312,'[1]PORTFOLIO RAW'!B:B,1,FALSE) -> 26599V | B312: 26599V | C312: SEAGATE TECHNOLOGY - MARKET CAPITALIZATION | D312: 26599V(WC08001) | E312: 13642027 | F312: 2149115 | G312: 8967830 | H312: 7067719 | I312: 6963630 | J312: 12047321 | K312: 20185984 | L312: 21714865 | M312: 11564233 | N312: 11396502 | O312: 12208894
A313: =VLOOKUP(B313,'[1]PORTFOLIO RAW'!B:B,1,FALSE) -> 904878 | B313: 904878 | C313: MOTOROLA SOLUTIONS - MARKET CAPITALIZATION | D313: 904878(WC08001) | E313: 36300124 | F313: 10084895 | G313: 17941896 | H313: 21351260 | I313: 14757252 | J313: 15373248 | K313: 17178750 | L313: 14744184 | M313: 11930835 | N313: 13651983 | O313: 14562808
A314: =VLOOKUP(B314,'[1]PORTFOLIO RAW'!B:B,1,FALSE) -> 922817 | B314: 922817 | C314: AON PLC - MARKET CAPITALIZATION | D314: 922817(WC08001) | E314: 14512067 | F314: 12429528 | G314: 10209942 | H314: 15289123 | I314: 15200640 | J314: 17289149 | K314: 25225723 | L314: 26552400 | M314: 24878258 | N314: 29220860 | O314: 33178400
...

Sheet NI
A1: NET INCOME
B2: 1 | C2: 2 | D2: 3 | E2: 4 | F2: 5 | G2: 6 | H2: 7 | I2: 8 | J2: 9 | K2: 10 | L2: 11 | M2: 12 | N2: 13 | O2: 14
B3: Code | C3: Name | D3: Code | E3: 2007 | F3: 2008 | G3: 2009 | H3: 2010 | I3: 2011 | J3: 2012 | K3: 2013 | L3: 2014 | M3: 2015 | N3: 2016 | O3: 2017
A4: 902172 | B4: 902172 | C4: 3M COMPANY - NET INCOME - BASIC | D4: 902172(WC01706) | E4: 4096000 | F4: 3460000 | G4: 3193000 | H4: 4085000 | I4: 4283000 | J4: 4444000 | K4: 4659000 | L4: 4956000 | M4: 4833000 | N4: 5050000 | O4: 5620000
A5: 916328 | B5: 916328 | C5: ABBOTT LABORATORIES - NET INCOME - BASIC | D5: 916328(WC01706) | E5: 3606314 | F5: 4734216 | G5: 5745838 | H5: 4626172 | I5: 4728449 | J5: 5962920 | K5: 2576000 | L5: 2284000 | M5: 2671000 | N5: 1384000 | O5: 1937000
A6: 14352P | B6: 14352P | C6: ACCENTURE PLC - NET INCOME - BASIC | D6: 14352P(WC01706) | E6: 1243148 | F6: 1691751 | G6: 1589963 | H6: 1780656 | I6: 2277677 | J6: 2553510 | K6: 3281878 | L6: 2941498 | M6: 3053581 | N6: 4111892 | O6: 3445149
A7: 312367 | B7: 312367 | C7: ACTIVISION BLIZZARD - NET INCOME - BASIC | D7: 312367(WC01706) | E7: 227000 | F7: -107000 | G7: 113000 | H7: 414000 | I7: 1069000 | J7: 1125000 | K7: 998000 | L7: 847000 | M7: 881000 | N7: 962000 | O7: 909000
A8: 749382 | B8: 749382 | C8: ADOBE INC - NET INCOME - BASIC | D8: 749382(WC01706) | E8: 723807 | F8: 871814 | G8: 386508 | H8: 774680 | I8: 832847 | J8: 832775 | K8: 289985 | L8: 268395 | M8: 629551 | N8: 1168782 | O8: 1693954
A9: 14806F | B9: 14806F | C9: ADVANCE AUTO PARTS - NET INCOME - BASIC | D9: 14806F(WC01706) | E9: 238317 | F9: 238038 | G9: 270373 | H9: 344501 | I9: 393627 | J9: 386800 | K9: 390863 | L9: 492270 | M9: 471745 | N9: 457677 | O9: 331705
A10: 936365 | B10: 936365 | C10: ADVANCED MICRO - NET INCOME - BASIC | D10: 936365(WC01706) | E10: -3379000 | F10: -3098000 | G10: 304000 | H10: 471000 | I10: 491000 | J10: -1183000 | K10: -83000 | L10: -403000 | M10: -660000 | N10: -497000 | O10: -1087000
A11: 545101 | B11: 545101 | C11: AES CORP - NET INCOME - BASIC | D11: 545101(WC01706) | E11: 495000 | F11: 1228000 | G11: 808000 | H11: -55000 | I11: -28000 | J11: -928000 | K11: 266000 | L11: 825000 | M11: 306000 | N11: -11000 | O11: -511000
A12: 933185 | B12: 933185 | C12: AFLAC INCORPORATED - NET INCOME - BASIC | D12: 933185(WC01706) | E12: 1634000 | F12: 1254000 | G12: 1497000 | H12: 2344000 | I12: 1964000 | J12: 2866000 | K12: 3158000 | L12: 2951000 | M12: 2533000 | N12: 2659000 | O12: 2671000
A13: 277642 | B13: 277642 | C13: AGILENT TECHNOLOGIES - NET INCOME - BASIC | D13: 277642(WC01706) | E13: 638000 | F13: 693000 | G13: -31000 | H13: 684000 | I13: 1012000 | J13: 1153000 | K13: 724000 | L13: 504000 | M13: 401000 | N13: 462000 | O13: 684000
A14: 905271 | B14: 905271 | C14: AIR PRODUCTS & CHEMS - NET INCOME - BASIC | D14: 905271(WC01706) | E14: 1042700 | F14: 1090500 | G14: 631400 | H14: 1029100 | I14: 1224200 | J14: 1046500 | K14: 994200 | L14: 991700 | M14: 1277900 | N14: 631100 | O14: 1219900
A15: 277355 | B15: 277355 | C15: AKAMAI TECHNOLOGIES - NET INCOME - BASIC | D15: 277355(WC01706) | E15: 100967 | F15: 145138 | G15: 145913 | H15: 171220 | I15: 200904 | J15: 203989 | K15: 293487 | L15: 333948 | M15: 321406 | N15: 316132 | O15: 244321
A16: 130298 | B16: 130298 | C16: ALBEMARLE CORP - NET INCOME - BASIC | D16: 130298(WC01706) | E16: 229690 | F16: 194202 | G16: 178368 | H16: 323720 | I16: 436280 | J16: 311536 | K16: 413171 | L16: 133316 | M16: 334906 | N16: 643675 | O16: 474350
A17: 325596 | B17: 325596 | C17: ALLERGAN PLC - NET INCOME - BASIC | D17: 325596(WC01706) | E17: 141030 | F17: 238379 | G17: 222000 | H17: 184400 | I17: 260900 | J17: 97300 | K17: -750400 | L17: -1630500 | M17: 3683200 | N17: 14695000 | O17: -7203900
A18: 906979 | B18: 906979 | C18: ALLIANT ENERGY CORP - NET INCOME - BASIC | D18: 906979(WC01706) | E18: 424700 | F18: 288000 | G18: 111000 | H18: 287600 | I18: 303600 | J18: 319800 | K18: 358300 | L18: 383100 | M18: 378200 | N18: 371500 | O18: 439200
A19: 322677 | B19: 322677 | C19: ALLSTATE CORP - NET INCOME - BASIC | D19: 322677(WC01706) | E19: 4636000 | F19: -1679000 | G19: 854000 | H19: 928000 | I19: 788000 | J19: 2306000 | K19: 2263000 | L19: 2746000 | M19: 2055000 | N19: 1761000 | O19: 2567000
A20: 29026M | B20: 29026M | C20: ALPHABET INC - NET INCOME - BASIC | D20: 29026M(WC01706) | E20: 4203720 | F20: 4226858 | G20: 6520448 | H20: 8505000 | I20: 9737000 | J20: 10737000 | K20: 12920000 | L20: 14444000 | M20: 15826000 | N20: 19478000 | O20: 22486000
A21: 904853 | B21: 904853 | C21: ALTRIA GROUP INC - NET INCOME - BASIC | D21: 904853(WC01706) | E21: 9786000 | F21: 3090000 | G21: 3206000 | H21: 3890000 | I21: 3377000 | J21: 4167000 | K21: 4523000 | L21: 5058000 | M21: 5231000 | N21: 14215000 | O21: 6841000
A22: 891399 | B22: 891399 | C22: AMAZON.COM INC - NET INCOME - BASIC | D22: 891399(WC01706) | E22: 476000 | F22: 645000 | G22: 902000 | H22: 1152000 | I22: 631000 | J22: -39000 | K22: 274000 | L22: -241000 | M22: 596000 | N22: 2371000 | O22: 2244000
A23: 670942 | B23: 670942 | C23: AMEREN CORPORATION - NET INCOME - BASIC | D23: 670942(WC01706) | E23: 618000 | F23: 607000 | G23: 612000 | H23: 139000 | I23: 519000 | J23: -974000 | K23: 289000 | L23: 586000 | M23: 630000 | N23: 653000 | O23: 677000
A24: 905425 | B24: 905425 | C24: AMERICAN ELECTRIC - NET INCOME - BASIC | D24: 905425(WC01706) | E24: 1144000 | F24: 1380000 | G24: 1362000 | H24: 1211000 | I24: 1568000 | J24: 1259000 | K24: 1480000 | L24: 1634000 | M24: 2047100 | N24: 610900 | O24: 1885900
A25: 906156 | B25: 906156 | C25: AMERICAN EXPRESS CO - NET INCOME - BASIC | D25: 906156(WC01706) | E25: 4012000 | F25: 2688000 | G25: 1802000 | H25: 4006000 | I25: 4877000 | J25: 4433000 | K25: 5312000 | L25: 5839000 | M25: 5063000 | N25: 5285000 | O25: 5234000
A26: 916305 | B26: 916305 | C26: AMERICAN INT'L GROUP - NET INCOME - BASIC | D26: 916305(WC01706) | E26: 6200000 | F26: -99689000 | G26: -12244000 | H26: 1583000 | I26: 16986000 | J26: 3438000 | K26: 9085000 | L26: 7529000 | M26: 2196000 | N26: -849000 | O26: 616000
A27: 680902 | B27: 680902 | C27: AMERICAN TOWER CORP - NET INCOME - BASIC | D27: 680902(WC01706) | E27: 56316 | F27: 347246 | G27: 246595 | H27: 372936 | I27: 396462 | J27: 637283 | K27: 551333 | L27: 801022 | M27: 594911 | N27: 849300 | O27: 1151500
A28: 31604H | B28: 31604H | C28: AMERIPRISE FIN - NET INCOME - BASIC | D28: 31604H(WC01706) | E28: 814000 | F28: -38000 | G28: 722000 | H28: 1097000 | I28: 1050000 | J28: 1036000 | K28: 1334000 | L28: 1619000 | M28: 1562000 | N28: 1314000 | O28: 1766000
A29: 154680 | B29: 154680 | C29: AMERISOURCEBERGEN - NET INCOME - BASIC | D29: 154680(WC01706) | E29: 493768 | F29: 469064 | G29: 511852 | H29: 636748 | I29: 706624 | J29: 718986 | K29: 433707 | L29: 276484 | M29: -134887 | N29: 1427929 | O29: 364484
A30: 938692 | B30: 938692 | C30: AMGEN INC - NET INCOME - BASIC | D30: 938692(WC01706) | E30: 3166000 | F30: 4196000 | G30: 4605000 | H30: 4627000 | I30: 3683000 | J30: 4345000 | K30: 5081000 | L30: 5158000 | M30: 6939000 | N30: 7722000 | O30: 8079000
A31: 546075 | B31: 546075 | C31: AMPHENOL CORP - NET INCOME - BASIC | D31: 546075(WC01706) | E31: 353194 | F31: 419151 | G31: 317834 | H31: 496405 | I31: 524191 | J31: 555317 | K31: 635672 | L31: 709100 | M31: 763500 | N31: 822900 | O31: 1049000
A32: 905276 | B32: 905276 | C32: ANALOG DEVICES, INC. - NET INCOME - BASIC | D32: 905276(WC01706) | E32: 496907 | F32: 525177 | G32: 247772 | H32: 711225 | I32: 860894 | J32: 651236 | K32: 673487 | L32: 629320 | M32: 696878 | N32: 861664 | O32: 725016
A33: 14737P | B33: 14737P | C33: ANTHEM INC - NET INCOME - BASIC | D33: 14737P(WC01706) | E33: 3345400 | F33: 2490700 | G33: 4745900 | H33: 2887100 | I33: 2646700 | J33: 2655500 | K33: 2489700 | L33: 2569700 | M33: 2560000 | N33: 2469800 | O33: 2734500
A34: 922817 | B34: 922817 | C34: AON PLC - NET INCOME - BASIC | D34: 922817(WC01706) | E34: 864000 | F34: 651000 | G34: 639000 | H34: 733000 | I34: 975000 | J34: 993000 | K34: 1113000 | L34: 1397000 | M34: 1385000 | N34: 1396000 | O34: 1576000
A35: 921983 | B35: 921983 | C35: APACHE CORPORATION - NET INCOME - BASIC | D35: 921983(WC01706) | E35: 2806678 | F35: 706274 | G35: -291692 | H35: 3000000 | I35: 4508000 | J35: 1925000 | K35: 2188000 | L35: -5403000 | M35: -23119000 | N35: -1405000 | O35: 1417000
A36: 992816 | B36: 992816 | C36: APPLE INC - NET INCOME - BASIC | D36: 992816(WC01706) | E36: 3496000 | F36: 4834000 | G36: 8235000 | H36: 14013000 | I36: 25922000 | J36: 41733000 | K36: 37037000 | L36: 39510000 | M36: 53394000 | N36: 45687000 | O36: 48351000
A37: 905296 | B37: 905296 | C37: APPLIED MATERIALS - NET INCOME - BASIC | D37: 905296(WC01706) | E37: 1710196 | F37: 960746 | G37: -305327 | H37: 937866 | I37: 1926000 | J37: 109000 | K37: 256000 | L37: 1072000 | M37: 1377000 | N37: 1721000 | O37: 3434000
A38: 132808 | B38: 132808 | C38: APT INVESTMENT & MGT - NET INCOME - BASIC | D38: 132808(WC01706) | E38: -114070 | F38: 361755 | G38: -114840 | H38: -125318 | I38: -103161 | J38: 82146 | K38: 203673 | L38: 11584 | M38: 55373 | N38: 23991 | O38: -8592
A39: 921093 | B39: 921093 | C39: ARCHER DANIELS MIDL. - NET INCOME - BASIC | D39: 921093(WC01706) | E39: 2162000 | F39: 1802000 | G39: 1707000 | H39: 1930000 | I39: 2036000 | J39: 1146000 | K39: 1342000 | L39: 2248000 | M39: 1849000 | N39: 1279000 | O39: 1216000
A40: 905113 | B40: 905113 | C40: ARCONIC INC - NET INCOME - BASIC | D40: 905113(WC01706) | E40: 2569000 | F40: -76000 | G40: -1153000 | H40: 253000 | I40: 608000 | J40: 189000 | K40: -2287000 | L40: 247000 | M40: -391000 | N40: -1010000 | O40: 145000
A41: 28341F | B41: 28341F | C41: ASSURANT INC - NET INCOME - BASIC | D41: 28341F(WC01706) | E41: 653746 | F41: 447796 | G41: 430574 | H41: 279177 | I41: 545839 | J41: 483705 | K41: 488907 | L41: 470907 | M41: 141555 | N41: 565350 | O41: 342600
A42: 945388 | B42: 945388 | C42: AT&T INC - NET INCOME - BASIC | D42: 945388(WC01706) | E42: 11951000 | F42: 12867000 | G42: 12535000 | H42: 19095000 | I42: 3944000 | J42: 7264000 | K42: 18249000 | L42: 6224000 | M42: 13345000 | N42: 12976000 | O42: 9179000
A43: 702259 | B43: 702259 | C43: AUTODESK INC - NET INCOME - BASIC | D43: 702259(WC01706) | E43: 356200 | F43: 183600 | G43: 58000 | H43: 212000 | I43: 285300 | J43: 247400 | K43: 228800 | L43: 81800 | M43: -330500 | N43: -582100 | O43: -158500
A44: 912669 | B44: 912669 | C44: AUTOMATIC DATA PROC - NET INCOME - BASIC | D44: 912669(WC01706) | E44: 1021200 | F44: 1161700 | G44: 1328200 | H44: 1210900 | I44: 1254200 | J44: 1388500 | K44: 1405800 | L44: 1515900 | M44: 1374100 | N44: 1492500 | O44: 1733400
A45: 544616 | B45: 544616 | C45: AUTOZONE INC - NET INCOME - BASIC | D45: 544616(WC01706) | E45: 595672 | F45: 641606 | G45: 657049 | H45: 738311 | I45: 848974 | J45: 930373 | K45: 1016480 | L45: 1069744 | M45: 1160241 | N45: 1241007 | O45: 1280869
A46: 130502 | B46: 130502 | C46: AVALONBAY COMMUNITIE - NET INCOME - BASIC | D46: 130502(WC01706) | E46: 238968 | F46: 116132 | G46: 91760 | H46: 100759 | I46: 158901 | J46: 276294 | K46: 74347 | L46: 644175 | M46: 740264 | N46: 1031392 | O46: 874458
A47: 921161 | B47: 921161 | C47: AVERY DENNISON CORP - NET INCOME - BASIC | D47: 921161(WC01706) | E47: 303500 | F47: 266100 | G47: -746700 | H47: 316900 | I47: 190100 | J47: 215400 | K47: 215800 | L47: 251100 | M47: 274400 | N47: 320700 | O47: 453800
A48: 921431 | B48: 921431 | C48: BAKER HUGHES A GE CO - NET INCOME - BASIC | D48: 921431(WC01706) | E48: 1513900 | F48: 1635000 | G48: 421000 | H48: 812000 | I48: 1739000 | J48: 1311000 | K48: 1096000 | L48: 1719000 | M48: -1967000 | N48: -2738000 | O48: -205000
A49: 932060 | B49: 932060 | C49: BALL CORPORATION - NET INCOME - BASIC | D49: 932060(WC01706) | E49: 281300 | F49: 319500 | G49: 387900 | H49: 468000 | I49: 444000 | J49: 403500 | K49: 406800 | L49: 470000 | M49: 280900 | N49: 263000 | O49: 457000
A50: 923937 | B50: 923937 | C50: BANK OF AMERICA CORP - NET INCOME - BASIC | D50: 923937(WC01706) | E50: 14800000 | F50: 2556000 | G50: -2210000 | H50: -3599000 | I50: 84000 | J50: 2758000 | K50: 10080000 | L50: 3789000 | M50: 14405000 | N50: 16224000 | O50: 18571000
A51: 905840 | B51: 905840 | C51: BANK OF NEW YORK - NET INCOME - BASIC | D51: 905840(WC01706) | E51: 2227000 | F51: 1412000 | G51: -1367000 | H51: 2518000 | I51: 2480000 | J51: 2397000 | K51: 2009000 | L51: 2451000 | M51: 3010000 | N51: 3373000 | O51: 3162000
A52: 916365 | B52: 916365 | C52: BAXTER INTERNATIONAL - NET INCOME - BASIC | D52: 916365(WC01706) | E52: 1707000 | F52: 2014000 | G52: 2205000 | H52: 1420000 | I52: 2224000 | J52: 2326000 | K52: 2012000 | L52: 2497000 | M52: 968000 | N52: 4965000 | O52: 1302000
A53: 992305 | B53: 992305 | C53: BB&T CORPORATION - NET INCOME - BASIC | D53: 992305(WC01706) | E53: 1734000 | F53: 1498000 | G53: 729000 | H53: 816000 | I53: 1289000 | J53: 1916000 | K53: 1562000 | L53: 2003000 | M53: 1936000 | N53: 2259000 | O53: 2177000
... A70: 902224 | B70: 902224 | C70: CATERPILLAR INC - NET INCOME - BASIC | D70: 902224(WC01706) | E70: 3541000 | F70: 3557000 | G70: 895000 | H70: 2700000 | I70: 4928000 | J70: 5681000 | K70: 3789000 | L70: 3695000 | M70: 2102000 | N70: -67000 | O70: 3125000
A71: 28513N | B71: 28513N | C71: CBRE GROUP - NET INCOME - BASIC | D71: 28513N(WC01706) | E71: 390505 | F71: -1012066 | G71: 33341 | H71: 200345 | I71: 239162 | J71: 315555 | K71: 316538 | L71: 484503 | M71: 547132 | N71: 571973 | O71: 834879
A72: 32480Q | B72: 32480Q | C72: CBS CORPORATION - NET INCOME - BASIC | D72: 32480Q(WC01706) | E72: 1230800 | F72: -11673400 | G72: 226500 | H72: 724200 | I72: 1305000 | J72: 1574000 | K72: 1879000 | L72: 2959000 | M72: 1413000 | N72: 1261000 | O72: 486000
A73: 29756N | B73: 29756N | C73: CELANESE CORPORATION - NET INCOME - BASIC | D73: 29756N(WC01706) | E73: 326000 | F73: 362000 | G73: 478000 | H73: 374000 | I73: 607000 | J73: 605000 | K73: 1101000 | L73: 624000 | M73: 304000 | N73: 900000 | O73: 933000
A74: 755790 | B74: 755790 | C74: CELGENE CORPORATION - NET INCOME - BASIC | D74: 755790(WC01706) | E74: 226433 | F74: -1533653 | G74: 776747 | H74: 880512 | I74: 1318150 | J74: 1456180 | K74: 1449900 | L74: 1999900 | M74: 1602000 | N74: 1999200 | O74: 4209000
A75: 904842 | B75: 904842 | C75: CENTERPOINT ENERGY - NET INCOME - BASIC | D75: 904842(WC01706) | E75: 399000 | F75: 447000 | G75: 372000 | H75: 442000 | I75: 770000 | J75: 417000 | K75: 311000 | L75: 611000 | M75: -692000 | N75: 432000 | O75: 679000
A76: 755741 | B76: 755741 | C76: CHARLES SCHWAB CORP - NET INCOME - BASIC | D76: 755741(WC01706) | E76: 1120000 | F76: 1212000 | G76: 787000 | H76: 454000 | I76: 864000 | J76: 883000 | K76: 1010000 | L76: 1261000 | M76: 1364000 | N76: 1746000 | O76: 2226000
A77: 905024 | B77: 905024 | C77: CHEVRON CORPORATION - NET INCOME - BASIC | D77: 905024(WC01706) | E77: 18688000 | F77: 23931000 | G77: 10483000 | H77: 19024000 | I77: 26895000 | J77: 26179000 | K77: 21423000 | L77: 19241000 | M77: 4587000 | N77: -497000 | O77: 7175000
A78: 328314 | B78: 328314 | C78: CHUBB - NET INCOME - BASIC | D78: 328314(WC01706) | E78: 2533000 | F78: 1173000 | G78: 2549000 | H78: 3108000 | I78: 1585000 | J78: 2706000 | K78: 3758000 | L78: 2853000 | M78: 2834000 | N78: 4135000 | O78: 3411000
A79: 912278 | B79: 912278 | C79: CIGNA CORP - NET INCOME - BASIC | D79: 912278(WC01706) | E79: 1115000 | F79: 292000 | G79: 1302000 | H79: 1345000 | I79: 1327000 | J79: 1623000 | K79: 1476000 | L79: 2102000 | M79: 2094000 | N79: 1867000 | O79: 2469000
A80: 26276P | B80: 26276P | C80: CIMAREX ENERGY CO - NET INCOME - BASIC | D80: 26276P(WC01706) | E80: 346469 | F80: -901685 | G80: -311943 | H80: 574782 | I80: 529932 | J80: 347070 | K80: 553598 | L80: 497298 | M80: -2408948 | N80: -431049 | O80: 424632
A81: 951545 | B81: 951545 | C81: CINCINNATI FINL CORP - NET INCOME - BASIC | D81: 951545(WC01706) | E81: 855000 | F81: 429000 | G81: 432000 | H81: 377000 | I81: 166000 | J81: 421000 | K81: 517000 | L81: 525000 | M81: 634000 | N81: 591000 | O81: 550000
A82: 944777 | B82: 944777 | C82: CINTAS CORPORATION - NET INCOME - BASIC | D82: 944777(WC01706) | E82: 334538 | F82: 335405 | G82: 226357 | H82: 214959 | I82: 245892 | J82: 295757 | K82: 313546 | L82: 370990 | M82: 426741 | N82: 686115 | O82: 459740
A83: 542868 | B83: 542868 | C83: CISCO SYSTEMS, INC. - NET INCOME - BASIC | D83: 542868(WC01706) | E83: 7333000 | F83: 8052000 | G83: 6134000 | H83: 7767000 | I83: 6490000 | J83: 8041000 | K83: 9983000 | L83: 7853000 | M83: 8981000 | N83: 10739000 | O83: 9609000
A84: 741344 | B84: 741344 | C84: CITIGROUP INC - NET INCOME - BASIC | D84: 741344(WC01706) | E84: 3581000 | F84: -29416000 | G84: -9246000 | H84: 10503000 | I84: 10760000 | J84: 7350000 | K84: 13216000 | L84: 6691000 | M84: 16249000 | N84: 13640000 | O84: 14552000
A85: 867705 | B85: 867705 | C85: CITRIX SYSTEMS INC - NET INCOME - BASIC | D85: 867705(WC01706) | E85: 214483 | F85: 178276 | G85: 191017 | H85: 277065 | I85: 356322 | J85: 352547 | K85: 339523 | L85: 251723 | M85: 319361 | N85: 536112 | O85: 408681
A86: 916125 | B86: 916125 | C86: CLOROX CO - NET INCOME - BASIC | D86: 916125(WC01706) | E86: 496000 | F86: 461000 | G86: 537000 | H86: 600000 | I86: 308000 | J86: 543000 | K86: 572000 | L86: 558000 | M86: 580000 | N86: 648000 | O86: 701000
A87: 26393N | B87: 26393N | C87: CME GROUP INC - NET INCOME - BASIC | D87: 26393N(WC01706) | E87: 658533 | F87: 715486 | G87: 825800 | H87: 951400 | I87: 1812300 | J87: 896300 | K87: 976800 | L87: 1127100 | M87: 1247000 | N87: 1534100 | O87: 1463400
A88: 901686 | B88: 901686 | C88: CMS ENERGY CORP - NET INCOME - BASIC | D88: 901686(WC01706) | E88: -227000 | F88: 289000 | G88: 218000 | H88: 324000 | I88: 415000 | J88: 382000 | K88: 452000 | L88: 477000 | M88: 523000 | N88: 551000 | O88: 608000
A89: 904282 | B89: 904282 | C89: COCA-COLA - NET INCOME - BASIC | D89: 904282(WC01706) | E89: 5981000 | F89: 5807000 | G89: 6824000 | H89: 11809000 | I89: 8572000 | J89: 9019000 | K89: 8584000 | L89: 7098000 | M89: 7351000 | N89: 6527000 | O89: 4858000
A90: 906148 | B90: 906148 | C90: COLGATE-PALMOLIVE CO - NET INCOME - BASIC | D90: 906148(WC01706) | E90: 1709400 | F90: 1928700 | G90: 2261000 | H90: 2169000 | I90: 2431000 | J90: 2472000 | K90: 2241000 | L90: 2180000 | M90: 1384000 | N90: 2441000 | O90: 2299000
A91: 981550 | B91: 981550 | C91: COMCAST CORPORATION - NET INCOME - BASIC | D91: 981550(WC01706) | E91: 2587000 | F91: 2547000 | G91: 3638000 | H91: 3635000 | I91: 4160000 | J91: 6203000 | K91: 6816000 | L91: 8380000 | M91: 8163000 | N91: 8695000 | O91: 10035000
A92: 922964 | B92: 922964 | C92: COMERICA INC. - NET INCOME - BASIC | D92: 922964(WC01706) | E92: 682000 | F92: 196000 | G92: -118000 | H92: 136000 | I92: 389000 | J92: 515000 | K92: 533000 | L92: 586000 | M92: 515000 | N92: 473000 | O92: 845000
A93: 929814 | B93: 929814 | C93: CONAGRA BRANDS INC - NET INCOME - BASIC | D93: 929814(WC01706) | E93: 683800 | F93: 518700 | G93: 978400 | H93: 724300 | I93: 815100 | J93: 466400 | K93: 772300 | L93: 301400 | M93: -254300 | N93: -681800 | O93: 638500
A94: 901666 | B94: 901666 | C94: CONOCOPHILLIPS - NET INCOME - BASIC | D94: 901666(WC01706) | E94: 11891000 | F94: -16998000 | G94: 4858000 | H94: 11358000 | I94: 12436000 | J94: 8428000 | K94: 9156000 | L94: 6869000 | M94: -4428000 | N94: -3615000 | O94: -1707000
A95: 902288 | B95: 902288 | C95: CONSOLIDATED EDISON - NET INCOME - BASIC | D95: 902288(WC01706) | E95: 929000 | F95: 1196000 | G95: 868000 | H95: 992000 | I95: 1051000 | J95: 1138000 | K95: 1062000 | L95: 1092000 | M95: 1193000 | N95: 1245000 | O95: 6837000
A96: 937083 | B96: 937083 | C96: CONSTELLATION BRANDS - NET INCOME - BASIC | D96: 937083(WC01706) | E96: 327000 | F96: -613300 | G96: -301400 | H96: 99300 | I96: 559500 | J96: 445000 | K96: 387800 | L96: 1943100 | M96: 839300 | N96: 1054900 | O96: 1535100
A97: 938928 | B97: 938928 | C97: COOPER COMPANIES INC - NET INCOME - BASIC | D97: 938928(WC01706) | E97: -11192 | F97: 65476 | G97: 100548 | H97: 112803 | I97: 175430 | J97: 248339 | K97: 296151 | L97: 269856 | M97: 203523 | N97: 273917 | O97: 372900
A98: 912273 | B98: 912273 | C98: CORNING INCORPORATED - NET INCOME - BASIC | D98: 912273(WC01706) | E98: 2150000 | F98: 5257000 | G98: 2008000 | H98: 3558000 | I98: 2805000 | J98: 1728000 | K98: 1961000 | L98: 2378000 | M98: 1241000 | N98: 3597000 | O98: -506600
A99: 312385 | B99: 312385 | C99: COSTCO WHOLESALE - NET INCOME - BASIC | D99: 312385(WC01706) | E99: 1082772 | F99: 1282725 | G99: 1086000 | H99: 1304000 | I99: 1463000 | J99: 1710000 | K99: 2039000 | L99: 2058000 | M99: 2377000 | N99: 2350000 | O99: 2679000
... A110: 271980 | B110: 271980 | C110: DEVON ENERGY CORP - NET INCOME - BASIC | D110: 271980(WC01706) | E110: 3596000 | F110: -2922000 | G110: -2479000 | H110: 4550000 | I110: 4681000 | J110: -209000 | K110: -22000 | L110: 1590000 | M110: -14459000 | N110: -3304000 | O110: 952000
A111: 31196R | B111: 31196R | C111: DISCOVERY INC - NET INCOME - BASIC | D111: 31196R(WC01706) | E111: 108338 | F111: 317000 | G111: 552000 | H111: 652000 | I111: 1132000 | J111: 943000 | K111: 1075000 | L111: 758000 | M111: 686000 | N111: 789000 | O111: -269000
A112: 135448 | B112: 135448 | C112: DISH NETWORK - NET INCOME - BASIC | D112: 135448(WC01706) | E112: 756054 | F112: 902947 | G112: 635545 | H112: 984729 | I112: 1515907 | J112: 636687 | K112: 807492 | L112: 944693 | M112: 747092 | N112: 1449853 | O112: 898689
A113: 154259 | B113: 154259 | C113: DOLLAR TREE, INC - NET INCOME - BASIC | D113: 154259(WC01706) | E113: 201300 | F113: 229500 | G113: 320500 | H113: 397300 | I113: 488300 | J113: 619300 | K113: 596700 | L113: 599200 | M113: 282400 | N113: 896200 | O113: 1152300
A114: 944314 | B114: 944314 | C114: DOMINION ENERGY INC - NET INCOME - BASIC | D114: 944314(WC01706) | E114: 2705000 | F114: 1834000 | G114: 1287000 | H114: 2808000 | I114: 1408000 | J114: 318000 | K114: 1697000 | L114: 1310000 | M114: 1899000 | N114: 2123000 | O114: 2148000
A115: 904830 | B115: 904830 | C115: DOVER CORP - NET INCOME - BASIC | D115: 904830(WC01706) | E115: 661080 | F115: 590831 | G115: 367608 | H115: 714307 | I115: 899986 | J115: 861888 | K115: 1003129 | L115: 775235 | M115: 604279 | N115: 508892 | O115: 760765
A116: 905214 | B116: 905214 | C116: DTE ENERGY CO - NET INCOME - BASIC | D116: 905214(WC01706) | E116: 787000 | F116: 546000 | G116: 532000 | H116: 630000 | I116: 711000 | J116: 610000 | K116: 661000 | L116: 905000 | M116: 727000 | N116: 868000 | O116: 1027000
A117: 904383 | B117: 904383 | C117: DUKE ENERGY CORP - NET INCOME - BASIC | D117: 904383(WC01706) | E117: 1522000 | F117: 1295000 | G117: 1075000 | H117: 1320000 | I117: 1706000 | J117: 1768000 | K117: 2665000 | L117: 1883000 | M117: 2816000 | N117: 2152000 | O117: 2947000
A118: 513260 | B118: 513260 | C118: DUKE REALTY CORP - NET INCOME - BASIC | D118: 513260(WC01706) | E118: 97421 | F118: 40491 | G118: -340387 | H118: -47162 | I118: -72709 | J118: -142687 | K118: 17124 | L118: 182511 | M118: 190512 | N118: 308771 | O118: 272672
A119: 916091 | B119: 916091 | C119: DXC TECHNO - NET INCOME - BASIC | D119: 916091(WC01706) | E119: 388800 | F119: 544600 | G119: 1115200 | H119: 817000 | I119: 740000 | J119: -4243000 | K119: 544000 | L119: 947000 | M119: -8000 | N119: 251000 | O119: -123000
A120: 883488 | B120: 883488 | C120: E*TRADE FINANCIAL - NET INCOME - BASIC | D120: 883488(WC01706) | E120: -1441754 | F120: -780588 | G120: -1297762 | H120: -28472 | I120: 156701 | J120: -112583 | K120: 86012 | L120: 293000 | M120: 268000 | N120: 552000 | O120: 647000
A121: 357922 | B121: 357922 | C121: EASTMAN CHEMICAL CO - NET INCOME - BASIC | D121: 357922(WC01706) | E121: 311000 | F121: 328000 | G121: 136000 | H121: 438000 | I121: 665000 | J121: 436000 | K121: 1165000 | L121: 751000 | M121: 848000 | N121: 854000 | O121: 1045000
A122: 903749 | B122: 903749 | C122: EATON CORP PLC - NET INCOME - BASIC | D122: 903749(WC01706) | E122: 959000 | F122: 1058000 | G122: 383000 | H122: 929000 | I122: 1350000 | J122: 1217000 | K122: 1861000 | L122: 1793000 | M122: 1979000 | N122: 1922000 | O122: 2923000
A123: 687609 | B123: 687609 | C123: EBAY INC. - NET INCOME - BASIC | D123: 687609(WC01706) | E123: 348251 | F123: 1779474 | G123: 2389097 | H123: 1800961 | I123: 3229387 | J123: 2609000 | K123: 2856000 | L123: 46000 | M123: 1725000 | N123: 7266000 | O123: 2084000
... A134: 902317 | B134: 902317 | C134: EXELON CORPORATION - NET INCOME - BASIC | D134: 902317(WC01706) | E134: 2726000 | F134: 2716000 | G134: 2707000 | H134: 2563000 | I134: 2495000 | J134: 1160000 | K134: 1719000 | L134: 1623000 | M134: 2269000 | N134: 1134000 | O134: 3770000
A135: 31412T | B135: 31412T | C135: EXPEDIA GROUP INC - NET INCOME - BASIC | D135: 31412T(WC01706) | E135: 295864 | F135: -2517763 | G135: 299526 | H135: 421500 | I135: 472294 | J135: 280171 | K135: 232850 | L135: 398097 | M135: 764465 | N135: 281848 | O135: 363845
A136: 910722 | B136: 910722 | C136: EXPEDITORS INTL WASH - NET INCOME - BASIC | D136: 910722(WC01706) | E136: 269154 | F136: 301014 | G136: 240217 | H136: 344172 | I136: 385679 | J136: 333360 | K136: 348526 | L136: 376888 | M136: 457223 | N136: 430807 | O136: 450077
...

Sheet EBITDA
A1: EBITDA
B2: 1 | C2: 2 | D2: 3 | E2: 4 | F2: 5 | G2: 6 | H2: 7 | I2: 8 | J2: 9 | K2: 10 | L2: 11 | M2: 12 | N2: 13 | O2: 14
B3: Code | C3: Name | D3: Code | E3: 2007 | F3: 2008 | G3: 2009 | H3: 2010 | I3: 2011 | J3: 2012 | K3: 2013 | L3: 2014 | M3: 2015 | N3: 2016 | O3: 2017
A4: =VLOOKUP(B4,'PORTFOLIO RAW'!C:C,1,FALSE) -> 891399 | B4: 891399 | C4: AMAZON.COM INC - EBIT & DEPRECIATION | D4: 891399(WC18198) | E4: 1008000 | F4: 1312000 | G4: 1627000 | H4: 2193000 | I4: 2148000 | J4: 2795000 | K4: 3900000 | L4: 4845000 | M4: 8308000 | N4: 12492000 | O4: 16132000
A5: =VLOOKUP(B5,'PORTFOLIO RAW'!C:C,1,FALSE) -> 916328 | B5: 916328 | C5: ABBOTT LABORATORIES - EBIT & DEPRECIATION | D5: 916328(WC18198) | E5: 6419660 | F5: 8104592 | G5: 9493940 | H5: 9138274 | I5: 9260677 | J5: 9638224 | K5: 4299000 | L5: 4216000 | M5: 4818000 | N5: 3197000 | O5: 6156000
A6: =VLOOKUP(B6,'PORTFOLIO RAW'!C:C,1,FALSE) -> 545101 | B6: 545101 | C6: AES CORP - EBIT & DEPRECIATION | D6: 545101(WC18198) | E6: 4268000 | F6: 5596000 | G6: 4790000 | H6: 3622000 | I6: 5044000 | J6: 3280000 | K6: 3783000 | L6: 4294000 | M6: 3705000 | N6: 2744000 | O6: 3110000
A7: =VLOOKUP(B7,'PORTFOLIO RAW'!C:C,1,FALSE) -> 906187 | B7: 906187 | C7: INT'L BUSINESS MACHS - EBIT & DEPRECIATION | D7: 906187(WC18198) | E7: 20301000 | F7: 22838000 | G7: 23630000 | H7: 25025000 | I7: 26328000 | J7: 27048000 | K7: 24533000 | L7: 25168000 | M7: 20375000 | N7: 17449000 | O7: 16590000
A8: =VLOOKUP(B8,'PORTFOLIO RAW'!C:C,1,FALSE) -> 936365 | B8: 936365 | C8: ADVANCED MICRO - EBIT & DEPRECIATION | D8: 936365(WC18198) | E8: -1494000 | F8: -671000 | G8: 1974000 | H8: 1553000 | I8: 496000 | J8: -782000 | K8: 339000 | L8: -18000 | M8: -319000 | N8: -159000 | O8: 339000
A9: =VLOOKUP(B9,'PORTFOLIO RAW'!C:C,1,FALSE) -> 749382 | B9: 749382 | C9: ADOBE INC - EBIT & DEPRECIATION | D9: 749382(WC18198) | E9: 1262907 | F9: 1358796 | G9: 987350 | H9: 1264303 | I9: 1372387 | J9: 1486047 | K9: 744876 | L9: 734698 | M9: 1277438 | N9: 1837115 | O9: 2538040
A10: =VLOOKUP(B10,'PORTFOLIO RAW'!C:C,1,FALSE) -> 905271 | B10: 905271 | C10: AIR PRODUCTS & CHEMS - EBIT & DEPRECIATION | D10: 905271(WC18198) | E10: 2247700 | F10: 2364800 | G10: 1686600 | H10: 2252400 | I10: 2504300 | J10: 2129000 | K10: 2231400 | L10: 2280100 | M10: 2610900 | N10: 3016200 | O10: 2307700
A11: =VLOOKUP(B11,'PORTFOLIO RAW'!C:C,1,FALSE) -> 894371 | B11: 894371 | C11: BOSTON PROPERTIES - EBIT & DEPRECIATION | D11: 894371(WC18198) | E11: 1717571 | F11: 907372 | G11: 906955 | H11: 870003 | I11: 1061245 | J11: 1111776 | K11: 1640851 | L11: 1597604 | M11: 1848886 | N11: 1669155 | O11: 1543277
A12: =VLOOKUP(B12,'PORTFOLIO RAW'!C:C,1,FALSE) -> 322677 | B12: 322677 | C12: ALLSTATE CORP - EBIT & DEPRECIATION | D12: 322677(WC18198) | E12: 6917000 | F12: -2496000 | G12: 1879000 | H12: 1692000 | I12: 1491000 | J12: 3719000 | K12: 4131000 | L12: 4924000 | M12: 3945000 | N12: 3431000 | O12: 4809000
A13: =VLOOKUP(B13,'PORTFOLIO RAW'!C:C,1,FALSE) -> 906191 | B13: 906191 | C13: HONEYWELL INTERNATNL - EBIT & DEPRECIATION | D13: 906191(WC18198) | E13: 4604000 | F13: 5097000 | G13: 4368000 | H13: 4211000 | I13: 3676000 | J13: 5119000 | K13: 6711000 | L13: 7045000 | M13: 7779000 | N13: 7806000 | O13: 8294000
A14: =VLOOKUP(B14,'PORTFOLIO RAW'!C:C,1,FALSE) -> 938692 | B14: 938692 | C14: AMGEN INC - EBIT & DEPRECIATION | D14: 938692(WC18198) | E14: 5437000 | F14: 6567000 | G14: 6830000 | H14: 6937000 | I14: 5819000 | J14: 7150000 | K14: 8595000 | L14: 9809000 | M14: 11184000 | N14: 12542000 | O14: 12856000
A15: =VLOOKUP(B15,'PORTFOLIO RAW'!C:C,1,FALSE) -> 905802 | B15: 905802 | C15: HESS CORPORATION - EBIT & DEPRECIATION | D15: 905802(WC18198) | E15: 5360000 | F15: 6952000 | G15: 4313000 | H15: 6511000 | I15: 6323000 | J15: 7106000 | K15: 7669000 | L15: 5983000 | M15: 38000 | N15: -272000 | O15: -2570000
... A29: =VLOOKUP(B29,'PORTFOLIO RAW'!C:C,1,FALSE) -> 670942 | B29: 670942 | C29: AMEREN CORPORATION - EBIT & DEPRECIATION | D29: 670942(WC18198) | E29: 2176000 | F29: 2125000 | G29: 2229000 | H29: 1758000 | I29: 2061000 | J29: -424000 | K29: 1933000 | L29: 2056000 | M29: 2099000 | N29: 2268000 | O29: 2392000
A30: =VLOOKUP(B30,'PORTFOLIO RAW'!C:C,1,FALSE) -> 702259 | B30: 702259 | C30: AUTODESK INC - EBIT & DEPRECIATION | D30: 702259(WC18198) | E30: 534700 | F30: 344300 | G30: 196200 | H30: 377400 | I30: 478400 | J30: NA | K30: 418600 | L30: 242100 | M30: 159400 | N30: -337400 | O30: -395100
A31: =VLOOKUP(B31,'PORTFOLIO RAW'!C:C,1,FALSE) -> 912669 | B31: 912669 | C31: AUTOMATIC DATA PROC - EBIT & DEPRECIATION | D31: 912669(WC18198) | E31: 2007200 | F31: 2211600 | G31: 2246100 | H31: 2181000 | I31: 2259500 | J31: 2453100 | K31: 2410400 | L31: 2616900 | M31: 2355100 | N31: 2579500 | O31: 2927200
A32: =VLOOKUP(B32,'PORTFOLIO RAW'!C:C,1,FALSE) -> 544616 | B32: 544616 | C32: AUTOZONE INC - EBIT & DEPRECIATION | D32: 544616(WC18198) | E32: 1217496 | F32: 1297428 | G32: 1360382 | H32: 1514124 | I32: 1693070 | J32: 1842119 | K32: 2001955 | L32: 2083340 | M32: 2224575 | N32: 2360163 | O32: 2406622
A33: =VLOOKUP(B33,'PORTFOLIO RAW'!C:C,1,FALSE) -> 921161 | B33: 921161 | C33: AVERY DENNISON CORP - EBIT & DEPRECIATION | D33: 921161(WC18198) | E33: 715100 | F33: 664900 | G33: -445200 | H33: 670700 | I33: 546200 | J33: 548900 | K33: 626800 | L33: 629400 | M33: 657800 | N33: 713500 | O33: 826300
A34: =VLOOKUP(B34,'PORTFOLIO RAW'!C:C,1,FALSE) -> 932060 | B34: 932060 | C34: BALL CORPORATION - EBIT & DEPRECIATION | D34: 932060(WC18198) | E34: 794900 | F34: 887900 | G34: 931700 | H34: 1016400 | I34: 1138000 | J34: 1073400 | K34: 1067300 | L34: 1086400 | M34: 774200 | N34: 807000 | O34: 1528000
A35: =VLOOKUP(B35,'PORTFOLIO RAW'!C:C,1,FALSE) -> 874227 | B35: 874227 | C35: BERKSHIRE HATHAWAY - EBIT & DEPRECIATION | D35: 874227(WC18198) | E35: 24478000 | F35: 12347000 | G35: 16671000 | H35: 25888000 | I35: 22661000 | J35: 30126000 | K35: 38105000 | L35: 38728000 | M35: 46240000 | N35: 45142000 | O35: 35482000
A36: =VLOOKUP(B36,'PORTFOLIO RAW'!C:C,1,FALSE) -> 916365 | B36: 916365 | C36: BAXTER INTERNATIONAL - EBIT & DEPRECIATION | D36: 916365(WC18198) | E36: 2846000 | F36: 3255000 | G36: 3418000 | H36: 2779000 | I36: 3637000 | J36: 3698000 | K36: 3503000 | L36: 3611000 | M36: 1333000 | N36: 5843000 | O36: 2063000
A37: =VLOOKUP(B37,'PORTFOLIO RAW'!C:C,1,FALSE) -> 905876 | B37: 905876 | C37: BECTON, DICKINSON - EBIT & DEPRECIATION | D37: 905876(WC18198) | E37: 1691706 | F37: 2067372 | G37: 2143456 | H37: 2207692 | I37: 2299698 | J37: 2105920 | K37: 1850000 | L37: 2219000 | M37: 2001000 | N37: 2576000 | O37: 2588000
A38: =VLOOKUP(B38,'PORTFOLIO RAW'!C:C,1,FALSE) -> 945384 | B38: 945384 | C38: VERIZON COMMUNICATNS - EBIT & DEPRECIATION | D38: 945384(WC18198) | E38: 30166000 | F38: 31731000 | G38: 30649000 | H38: 31002000 | I38: 29362000 | J38: 28604000 | K38: 48408000 | L38: 34938000 | M38: 49263000 | N38: 41388000 | O38: 42134000
A39: =VLOOKUP(B39,'PORTFOLIO RAW'!C:C,1,FALSE) -> 929302 | B39: 929302 | C39: BEST BUY CO INC - EBIT & DEPRECIATION | D39: 929302(WC18198) | E39: 2670000 | F39: 2870000 | G39: 2587000 | H39: 3215000 | I39: 3143000 | J39: 940820 | K39: 1903000 | L39: 2133000 | M39: 2047000 | N39: 2542000 | O39: 2575000
A40: =VLOOKUP(B40,'PORTFOLIO RAW'!C:C,1,FALSE) -> 895784 | B40: 895784 | C40: SL GREEN REALTY CORP - EBIT & DEPRECIATION | D40: 895784(WC18198) | E40: 598725 | F40: 547709 | G40: 500310 | H40: 724810 | I40: 1218024 | J40: 783663 | K40: 816231 | L40: 933469 | M40: 1216001 | N40: 1417949 | O40: 758011
A41: =VLOOKUP(B41,'PORTFOLIO RAW'!C:C,1,FALSE) -> 878574 | B41: 878574 | C41: YUM! BRANDS INC - EBIT & DEPRECIATION | D41: 878574(WC18198) | E41: 1881000 | F41: 2119000 | G41: 2084000 | H41: 2369000 | I41: 2448000 | J41: 2932000 | K41: 2516000 | L41: 2288000 | M41: 2648000 | N41: 1960000 | O41: 3000000
A42: =VLOOKUP(B42,'PORTFOLIO RAW'!C:C,1,FALSE) -> 905159 | B42: 905159 | C42: FIRSTENERGY CORP - EBIT & DEPRECIATION | D42: 905159(WC18198) | E42: 3573000 | F42: 3498000 | G42: 2819000 | H42: 2657000 | I42: 3502000 | J42: 3377000 | K42: 2813000 | L42: 2426000 | M42: 3884000 | N42: -6751000 | O42: 1423000
... A44: =VLOOKUP(B44,'PORTFOLIO RAW'!C:C,1,FALSE) -> 904818 | B44: 904818 | C44: BOEING CO - EBIT & DEPRECIATION | D44: 904818(WC18198) | E44: 7908000 | F44: 5670000 | G44: 3662000 | H44: 6643000 | I44: 7401000 | J44: 8004000 | K44: 8462000 | L44: 9376000 | M44: 9263000 | N44: 7784000 | O44: 12476000
A45: =VLOOKUP(B45,'PORTFOLIO RAW'!C:C,1,FALSE) -> 923649 | B45: 923649 | C45: ROBERT HALF INTL INC - EBIT & DEPRECIATION | D45: 923649(WC18198) | E45: 565945 | F45: 497786 | G45: 132529 | H45: 171726 | I45: 301631 | J45: 392969 | K45: NA | L45: NA | M45: NA | N45: NA | O45: NA
A46: =VLOOKUP(B46,'PORTFOLIO RAW'!C:C,1,FALSE) -> 325824 | B46: 325824 | C46: BOSTON SCIENTIFIC - EBIT & DEPRECIATION | D46: 325824(WC18198) | E46: 940000 | F46: -699000 | G46: -61000 | H46: 146000 | I46: 1641000 | J46: -3161000 | K46: 790000 | L46: 432000 | M46: 403000 | N46: 1225000 | O46: 2006000
A47: =VLOOKUP(B47,'PORTFOLIO RAW'!C:C,1,FALSE) -> 879628 | B47: 879628 | C47: C.H. ROBINSON - EBIT & DEPRECIATION | D47: 879628(WC18198) | E47: 550880 | F47: 609551 | G47: 617575 | H47: 653471 | I47: 727202 | J47: NA | K47: 741343 | L47: 805427 | M47: 931919 | N47: 912200 | O47: 868096
A48: =VLOOKUP(B48,'PORTFOLIO RAW'!C:C,1,FALSE) -> 905080 | B48: 905080 | C48: BRISTOL-MYERS SQUIBB - EBIT & DEPRECIATION | D48: 905080(WC18198) | E48: 4324000 | F48: 5980000 | G48: 6086000 | H48: 6808000 | I48: 7646000 | J48: 3328000 | K48: 4235000 | L48: 3306000 | M48: 2861000 | N48: 6675000 | O48: 6109000
A49: =VLOOKUP(B49,'PORTFOLIO RAW'!C:C,1,FALSE) -> 130502 | B49: 130502 | C49: AVALONBAY COMMUNITIE - EBIT & DEPRECIATION | D49: 130502(WC18198) | E49: 467178 | F49: 418099 | G49: 435041 | H49: 505086 | I49: 575663 | J49: 636788 | K49: 801598 | L49: 1143050 | M49: 1327114 | N49: 1687995 | O49: 1589868
A50: =VLOOKUP(B50,'PORTFOLIO RAW'!C:C,1,FALSE) -> 902103 | B50: 902103 | C50: SEMPRA ENERGY - EBIT & DEPRECIATION | D50: 902103(WC18198) | E50: 2517000 | F50: 2018000 | G50: 2618000 | H50: 2381000 | I50: 3155000 | J50: 2845000 | K50: 3063000 | L50: 3161000 | M50: 3421000 | N50: 3072000 | O50: 3699000
A51: =VLOOKUP(B51,'PORTFOLIO RAW'!C:C,1,FALSE) -> 951849 | B51: 951849 | C51: FEDEX CORP - EBIT & DEPRECIATION | D51: 951849(WC18198) | E51: 5093000 | F51: 4060000 | G51: 2737000 | H51: 3931000 | I51: 4324000 | J51: 5306000 | K51: 4923000 | L51: 6072000 | M51: 4473000 | N51: 5707000 | O51: 8086000
A52: =VLOOKUP(B52,'PORTFOLIO RAW'!C:C,1,FALSE) -> 674693 | B52: 674693 | C52: VERISIGN, INC. - EBIT & DEPRECIATION | D52: 674693(WC18198) | E52: 121127 | F52: 292344 | G52: 414907 | H52: 320676 | I52: 396625 | J52: 517710 | K52: 609988 | L52: 632995 | M52: 670902 | N52: 754904 | O52: 786119
A53: =VLOOKUP(B53,'PORTFOLIO RAW'!C:C,1,FALSE) -> 546075 | B53: 546075 | C53: AMPHENOL CORP - EBIT & DEPRECIATION | D53: 546075(WC18198) | E53: 630726 | F53: 723509 | G53: 581637 | H53: 807275 | I53: 879220 | J53: 960233 | K53: 1046680 | L53: 1221000 | M53: 1292700 | N53: 1430700 | O53: 1671500
A54: =VLOOKUP(B54,'PORTFOLIO RAW'!C:C,1,FALSE) -> 912216 | B54: 912216 | C54: BROWN FORMAN CORP - EBIT & DEPRECIATION | D54: 912216(WC18198) | E54: 664000 | F54: 745000 | G54: 722000 | H54: 772000 | I54: 917000 | J54: 843000 | K54: 952000 | L54: 1023000 | M54: 1080000 | N54: 1591000 | O54: 1050000
A55: =VLOOKUP(B55,'PORTFOLIO RAW'!C:C,1,FALSE) -> 993189 | B55: 993189 | C55: CSX CORPORATION - EBIT & DEPRECIATION | D55: 993189(WC18198) | E55: 3239000 | F55: 3583000 | G55: 3226000 | H55: 4050000 | I55: 4416000 | J55: 4589000 | K55: 4588000 | L55: 4740000 | M55: 4890000 | N55: 4621000 | O55: 4784000
A56: =VLOOKUP(B56,'PORTFOLIO RAW'!C:C,1,FALSE) -> 905075 | B56: 905075 | C56: CAMPBELL SOUP CO - EBIT & DEPRECIATION | D56: 905075(WC18198) | E56: 1595000 | F56: 1379000 | G56: 1452000 | H56: 1604000 | I56: 1542000 | J56: 1459000 | K56: 1485000 | L56: 1500000 | M56: 1397000 | N56: 1275000 | O56: 1723000
A57: =VLOOKUP(B57,'PORTFOLIO RAW'!C:C,1,FALSE) -> 937083 | B57: 937083 | C57: CONSTELLATION BRANDS - EBIT & DEPRECIATION | D57: 937083(WC18198) | E57: 898800 | F57: -185100 | G57: 183800 | H57: 449000 | I57: 639800 | J57: 603400 | K57: 632600 | L57: 2593200 | M57: 1697900 | N57: 1985100 | O57: 2693300
A58: =VLOOKUP(B58,'PORTFOLIO RAW'!C:C,1,FALSE) -> 944704 | B58: 944704 | C58: CARDINAL HEALTH, INC - EBIT & DEPRECIATION | D58: 944704(WC18198) | E58: 1695800 | F58: 2502500 | G58: 2277500 | H58: 1577400 | I58: 1924400 | J58: 2118000 | K58: 1408000 | L58: 2390000 | M58: 2559000 | N58: 3095000 | O58: 2842000
A59: =VLOOKUP(B59,'PORTFOLIO RAW'!C:C,1,FALSE) -> 902224 | B59: 902224 | C59: CATERPILLAR INC - EBIT & DEPRECIATION | D59: 902224(WC18198) | E59: 8170000 | F59: 7880000 | G59: 4339000 | H59: 7245000 | I59: 10474000 | J59: 12312000 | K59: 9408000 | L59: 9354000 | M59: 6995000 | N59: 4274000 | O59: 8136000
... A110: =VLOOKUP(B110,'PORTFOLIO RAW'!C:C,1,FALSE) -> 905016 | B110: 905016 | C110: NEXTERA ENERGY - EBIT & DEPRECIATION | D110: 905016(WC18198) | E110: 3779000 | F110: 4388000 | G110: 4466000 | H110: 5433000 | I110: 5157000 | J110: 5333000 | K110: 6151000 | L110: 7660000 | M110: 8305000 | N110: 8905000 | O110: 8456000
A111: =VLOOKUP(B111,'PORTFOLIO RAW'!C:C,1,FALSE) -> 28341F | B111: 28341F | C111: ASSURANT INC - EBIT & DEPRECIATION | D111: 28341F(WC18198) | E111: 1106527 | F111: 688445 | G111: 866621 | H111: 774673 | I111: 883380 | J111: 887863 | K111: 992285 | L111: 934749 | M111: 393402 | N111: 1031350 | O111: 609700
A112: =VLOOKUP(B112,'PORTFOLIO RAW'!C:C,1,FALSE) -> 755980 | B112: 755980 | C112: FASTENAL COMPANY - EBIT & DEPRECIATION | D112: 755980(WC18198) | E112: 415231 | F112: 490435 | G112: 337577 | H112: 471395 | I112: 619787 | J112: 728207 | K112: 777772 | L112: 861021 | M112: 915726 | N112: 900285 | O112: 1009600
A113: =VLOOKUP(B113,'PORTFOLIO RAW'!C:C,1,FALSE) -> 905994 | B113: 905994 | C113: FEDERAL REALTY INVST - EBIT & DEPRECIATION | D113: 905994(WC18198) | E113: 313615 | F113: 329277 | G113: 324908 | H113: 347746 | I113: 354419 | J113: 397990 | K113: 402389 | L113: 431400 | M113: 456027 | N113: 514954 | O113: 536540
A114: =VLOOKUP(B114,'PORTFOLIO RAW'!C:C,1,FALSE) -> 997198 | B114: 997198 | C114: FIFTH THIRD BANCORP - EBIT & DEPRECIATION | D114: 997198(WC18198) | E114: 2429000 | F114: -1889000 | G114: 1312000 | H114: 1455000 | I114: 2360000 | J114: 2670000 | K114: 3230000 | L114: 2639000 | M114: 3034000 | N114: 2823000 | O114: 3473000
A115: =VLOOKUP(B115,'PORTFOLIO RAW'!C:C,1,FALSE) -> 951503 | B115: 951503 | C115: M&T BANK CORPORATION - EBIT & DEPRECIATION | D115: 951503(WC18198) | E115: 1464522 | F115: 1359973 | G115: 949624 | H115: 1457812 | I115: 1573001 | J115: 1883709 | K115: 2025557 | L115: 1972761 | M115: 2042421 | N115: 2400036 | O115: 2624332
A116: =VLOOKUP(B116,'PORTFOLIO RAW'!C:C,1,FALSE) -> 741123 | B116: 741123 | C116: FISERV INC - EBIT & DEPRECIATION | D116: 741123(WC18198) | E116: 930000 | F116: 1241000 | G116: 1287000 | H116: 1330000 | I116: 1266000 | J116: 1417000 | K116: 1465000 | L116: 1615000 | M116: 1643000 | N116: 1866000 | O116: 1978000
A117: =VLOOKUP(B117,'PORTFOLIO RAW'!C:C,1,FALSE) -> 546814 | B117: 546814 | C117: MACY'S INC - EBIT & DEPRECIATION | D117: 546814(WC18198) | E117: 3203000 | F117: -3072000 | G117: 2279000 | H117: 2983000 | I117: 3500000 | J117: 3576000 | K117: 3700000 | L117: 3821000 | M117: 3102000 | N117: 2377000 | O117: 2819000
A118: =VLOOKUP(B118,'PORTFOLIO RAW'!C:C,1,FALSE) -> 938076 | B118: 938076 | C118: FRANKLIN RESOURCES - EBIT & DEPRECIATION | D118: 938076(WC18198) | E118: 2623574 | F118: 2439216 | G118: 1455487 | H118: 2522542 | I118: 2906287 | J118: 2858300 | K118: 3096400 | L118: 3492300 | M118: 3232900 | N118: 2584400 | O118: 2578100
A119: =VLOOKUP(B119,'PORTFOLIO RAW'!C:C,1,FALSE) -> 152594 | B119: 152594 | C119: FREEPORT-MCMORAN INC - EBIT & DEPRECIATION | D119: 152594(WC18198) | E119: 7870000 | F119: -10826000 | G119: 7539000 | H119: 10102000 | I119: 10152000 | J119: 6852000 | K119: 8100000 | L119: 4069000 | M119: -9879000 | N119: -107000 | O119: 5417000
A120: =VLOOKUP(B120,'PORTFOLIO RAW'!C:C,1,FALSE) -> 951018 | B120: 951018 | C120: GAP INC - EBIT & DEPRECIATION | D120: 951018(WC18198) | E120: 1979000 | F120: 2153000 | G120: 2471000 | H120: 2637000 | I120: 2035000 | J120: 2507000 | K120: 2690000 | L120: 2652000 | M120: 2122000 | N120: 1792000 | O120: 2057000
A121: =VLOOKUP(B121,'PORTFOLIO RAW'!C:C,1,FALSE) -> 907652 | B121: 907652 | C121: GENERAL DYNAMICS - EBIT & DEPRECIATION | D121: 907652(WC18198) | E121: 3601000 | F121: 4184000 | G121: 4246000 | H121: 4526000 | I121: 4465000 | J121: 1329000 | K121: 4266000 | L121: 4401000 | M121: 4682000 | N121: 4784000 | O121: 4635000
A122: =VLOOKUP(B122,'PORTFOLIO RAW'!C:C,1,FALSE) -> 905801 | B122: 905801 | C122: GENERAL MILLS, INC. - EBIT & DEPRECIATION | D122: 905801(WC18198) | E122: 2507000 | F122: 2714300 | G122: 2798100 | H122: 3012100 | I122: 3242700 | J122: 3104800 | K122: 3452400 | L122: 3558900 | M122: 2678800 | N122: 3323600 | O122: 3177000
A123: =VLOOKUP(B123,'PORTFOLIO RAW'!C:C,1,FALSE) -> 906511 | B123: 906511 | C123: GENUINE PARTS CO - EBIT & DEPRECIATION | D123: 906511(WC18198) | E123: 940713 | F123: 888887 | G123: 762461 | H123: 879176 | I123: 1006778 | J123: 1137797 | K123: 1205232 | L123: 1291140 | M123: 1287018 | N123: 1242911 | O123: 1218445
... A134: =VLOOKUP(B134,'PORTFOLIO RAW'!C:C,1,FALSE) -> 905077 | B134: 905077 | C134: HERSHEY CO - EBIT & DEPRECIATION | D134: 905077(WC18198) | E134: 772233 | F134: 841191 | G134: 944878 | H134: 1103684 | I134: 1272392 | J134: 1324125 | K134: 1543866 | L134: 1605173 | M134: 1227758 | N134: 1493266 | O134: 1472587
A135: =VLOOKUP(B135,'PORTFOLIO RAW'!C:C,1,FALSE) -> 699943 | B135: 699943 | C135: JUNIPER NETWORKS INC - EBIT & DEPRECIATION | D135: 699943(WC18198) | E135: NA | F135: 896365 | G135: 460434 | H135: 924789 | I135: 791254 | J135: 531400 | K135: 773800 | L135: 166700 | M135: 1112000 | N135: 1131800 | O135: 1138600
A136: =VLOOKUP(B136,'PORTFOLIO RAW'!C:C,1,FALSE) -> 542983 | B136: 542983 | C136: HOLOGIC INC - EBIT & DEPRECIATION | D136: 542983(WC18198) | E136: 181729 | F136: -21279 | G136: -1745249 | H136: 366884 | I136: 646968 | J136: 424377 | K136: -395876 | L136: 791900 | M136: 874100 | N136: 1036000 | O136: 1832900
A137: =VLOOKUP(B137,'PORTFOLIO RAW'!C:C,1,FALSE) -> 741410 | B137: 741410 | C137: UNUM GROUP - EBIT & DEPRECIATION | D137: 741410(WC18198) | E137: 1246500 | F137: 1049500 | G137: 1492200 | H137: 1548500 | I137: 481600 | J137: 1479200 | K137: 1439400 | L137: 782600 | M137: 1490600 | N137: 1615400 | O137: 1667300
A138: =VLOOKUP(B138,'PORTFOLIO RAW'!C:C,1,FALSE) -> 998171 | B138: 998171 | C138: HOME DEPOT, INC. - EBIT & DEPRECIATION | D138: 998171(WC18198) | E138: 9018000 | F138: 6116000 | G138: 6464000 | H138: 7521000 | I138: 8356000 | J138: 9537000 | K138: 10935000 | L138: 12592000 | M138: 13803000 | N138: 15436000 | O138: 16817000
A139: =VLOOKUP(B139,'PORTFOLIO RAW'!C:C,1,FALSE) -> 904842 | B139: 904842 | C139: CENTERPOINT ENERGY - EBIT & DEPRECIATION | D139: 904842(WC18198) | E139: 1851000 | F139: 1984000 | G139: 1920000 | H139: 2161000 | I139: 2613000 | J139: 2345000 | K139: 2031000 | L139: 2061000 | M139: 1930000 | N139: 2033000 | O139: 2215000
A140: =VLOOKUP(B140,'PORTFOLIO RAW'!C:C,1,FALSE) -> 916860 | B140: 916860 | C140: HUMANA INC. - EBIT & DEPRECIATION | D140: 916860(WC18198) | E140: 1520578 | F140: 1256437 | G140: 1957877 | H140: 2079722 | I140: 2614000 | J140: 2311000 | K140: 2394000 | L140: 2811000 | M140: 3064000 | N140: 2206000 | O140: 4747000
A141: =VLOOKUP(B141,'PORTFOLIO RAW'!C:C,1,FALSE) -> 951068 | B141: 951068 | C141: HUNTINGTON BANCSHR - EBIT & DEPRECIATION | D141: 951068(WC18198) | E141: 427006 | F141: 164649 | G141: -3474706 | H141: 501775 | I141: 855151 | J141: 956811 | K141: 972944 | L141: 988149 | M141: 1081019 | N141: 1206408 | O141: 1768000
A142: =VLOOKUP(B142,'PORTFOLIO RAW'!C:C,1,FALSE) -> 545725 | B142: 545725 | C142: BIOGEN INC - EBIT & DEPRECIATION | D142: 545725(WC18198) | E142: 1273000 | F142: 1669900 | G142: 1787900 | H142: 1620100 | I142: 2103100 | J142: 2257200 | K142: 3129576 | L142: 4664294 | M142: 5463300 | N142: 5885900 | O142: 6662200
A143: =VLOOKUP(B143,'PORTFOLIO RAW'!C:C,1,FALSE) -> 905052 | B143: 905052 | C143: ILLINOIS TOOL WORKS - EBIT & DEPRECIATION | D143: 905052(WC18198) | E143: 3205660 | F143: 2895326 | G143: 1947986 | H143: 2934721 | I143: 3378856 | J143: 4460000 | K143: 3213000 | L143: 3465000 | M143: 3426000 | N143: 3554000 | O143: 3992000
A144: =VLOOKUP(B144,'PORTFOLIO RAW'!C:C,1,FALSE) -> 328184 | B144: 328184 | C144: INTUIT INC - EBIT & DEPRECIATION | D144: 328184(WC18198) | E144: 858208 | F144: 966738 | G144: 979288 | H144: 1132000 | I144: 1267000 | J144: 1443000 | K144: 1472000 | L144: 1542000 | M144: 970000 | N144: 1476000 | O144: 1634000
A145: =VLOOKUP(B145,'PORTFOLIO RAW'!C:C,1,FALSE) -> 922726 | B145: 922726 | C145: INTEL CORPORATION - EBIT & DEPRECIATION | D145: 922726(WC18198) | E145: 13979000 | F145: 14066000 | G145: 10927000 | H145: 20335000 | I145: 23774000 | J145: 22566000 | K145: 20564000 | L145: 24335000 | M145: 23395000 | N145: 21122000 | O145: 26709000
A146: =VLOOKUP(B146,'PORTFOLIO RAW'!C:C,1,FALSE) -> 905050 | B146: 905050 | C146: INTL FLAVORS&FRAGRAN - EBIT & DEPRECIATION | D146: 905050(WC18198) | E146: 453007 | F146: 430516 | G146: 412892 | H146: 487544 | I146: 493512 | J146: 561835 | K146: 615204 | L146: 684482 | M146: 674760 | N146: 679175 | O146: 720375
A147: =VLOOKUP(B147,'PORTFOLIO RAW'!C:C,1,FALSE) -> 904069 | B147: 904069 | C147: INTERNATIONAL PAPER - EBIT & DEPRECIATION | D147: 904069(WC18198) | E147: 3191000 | F147: 766000 | G147: 3325000 | H147: 2921000 | I147: 3386000 | J147: 3271000 | K147: 3065000 | L147: 2955000 | M147: 3204000 | N147: 2905000 | O147: 2949000
... A167: =VLOOKUP(B167,'PORTFOLIO RAW'!C:C,1,FALSE) -> 154423 | B167: 154423 | C167: LOCKHEED MARTIN CORP - EBIT & DEPRECIATION | D167: 154423(WC18198) | E167: 5336000 | F167: 5687000 | G167: 5038000 | H167: 4700000 | I167: 4661000 | J167: 5166000 | K167: 5174000 | L167: 6250000 | M167: 6149000 | N167: 6273000 | O167: 6908000
A168: =VLOOKUP(B168,'PORTFOLIO RAW'!C:C,1,FALSE) -> 922418 | B168: 922418 | C168: LOEWS CORPORATION - EBIT & DEPRECIATION | D168: 922418(WC18198) | E168: NA | F168: 1624000 | G168: 2962000 | H168: 4235000 | I168: 3587000 | J168: 2744000 | K168: 2742000 | L168: 3207000 | M168: 1719000 | N168: 2313000 | O168: 3065000
A169: =VLOOKUP(B169,'PORTFOLIO RAW'!C:C,1,FALSE) -> 755695 | B169: 755695 | C169: CARNIVAL CORP - EBIT & DEPRECIATION | D169: 755695(WC18198) | E169: 3892000 | F169: 4040000 | G169: 3495000 | H169: 3773000 | I169: 3799000 | J169: 3165000 | K169: 2979000 | L169: 3168000 | M169: 3642000 | N169: 4789000 | O169: 4710000
A170: =VLOOKUP(B170,'PORTFOLIO RAW'!C:C,1,FALSE) -> 905620 | B170: 905620 | C170: LOWE'S COMPANIES INC - EBIT & DEPRECIATION | D170: 905620(WC18198) | E170: 6214000 | F170: 5493000 | G170: 4871000 | H170: 5249000 | I170: 4860000 | J170: 5192000 | K170: 5709000 | L170: 6384000 | M170: 6550000 | N170: 7423000 | O170: 7662000
A171: =VLOOKUP(B171,'PORTFOLIO RAW'!C:C,1,FALSE) -> 944314 | B171: 944314 | C171: DOMINION ENERGY INC - EBIT & DEPRECIATION | D171: 944314(WC18198) | E171: 7167000 | F171: 4707000 | G171: 4129000 | H171: 7199000 | I171: 4315000 | J171: 2839000 | K171: 4971000 | L171: 4531000 | M171: 5401000 | N171: 5726000 | O171: 6247000
A172: =VLOOKUP(B172,'PORTFOLIO RAW'!C:C,1,FALSE) -> 357366 | B172: 357366 | C172: MACERICH CO - EBIT & DEPRECIATION | D172: 357366(WC18198) | E172: 539443 | F172: 594357 | G172: 646487 | H172: 412969 | I172: 386372 | J172: 713082 | K172: 570001 | L172: 2120510 | M172: 1157788 | N172: 1017653 | O172: 604772
A173: =VLOOKUP(B173,'PORTFOLIO RAW'!C:C,1,FALSE) -> 516007 | B173: 516007 | C173: MGM RESORTS - EBIT & DEPRECIATION | D173: 516007(WC18198) | E173: 3404888 | F173: 677782 | G173: -359711 | H173: -278363 | I173: 4763528 | J173: 446244 | K173: 1908615 | L173: 2067670 | M173: 389798 | N173: 2329000 | O173: 2514742
A174: =VLOOKUP(B174,'PORTFOLIO RAW'!C:C,1,FALSE) -> 510493 | B174: 510493 | C174: MCCORMICK & CO INC - EBIT & DEPRECIATION | D174: 510493(WC18198) | E174: 445600 | F174: 480100 | G174: 566300 | H174: 610600 | I174: 644400 | J174: 688200 | K174: 658700 | L174: 711800 | M174: 660500 | N174: 755500 | O174: 816600
A175: =VLOOKUP(B175,'PORTFOLIO RAW'!C:C,1,FALSE) -> 921910 | B175: 921910 | C175: MCDONALD'S CORP - EBIT & DEPRECIATION | D175: 921910(WC18198) | E175: 5080700 | F175: 7777700 | G175: 8010700 | H175: 8564600 | I175: 9739800 | J175: 9940600 | K175: 10233300 | L175: 9595900 | M175: 8896500 | N175: 9212500 | O175: 10674500
A176: =VLOOKUP(B176,'PORTFOLIO RAW'!C:C,1,FALSE) -> 311759 | B176: 311759 | C176: EVEREST RE GROUP - EBIT & DEPRECIATION | D176: 311759(WC18198) | E176: NA | F176: NA | G176: NA | H176: NA | I176: NA | J176: NA | K176: 1601084 | L176: 1484648 | M176: 1244700 | N176: 1136072 | O176: 436787
A177: =VLOOKUP(B177,'PORTFOLIO RAW'!C:C,1,FALSE) -> 912588 | B177: 912588 | C177: HOST HOTELS - EBIT & DEPRECIATION | D177: 912588(WC18198) | E177: 1468000 | F177: 1371000 | G177: 786000 | H177: 818000 | I177: 1002000 | J177: 1076000 | K177: 1249000 | L177: 1650000 | M177: 1460000 | N177: 1668000 | O177: 1538000
A178: =VLOOKUP(B178,'PORTFOLIO RAW'!C:C,1,FALSE) -> 904780 | B178: 904780 | C178: MARSH & MCLENNAN CO. - EBIT & DEPRECIATION | D178: 904780(WC18198) | E178: 1556000 | F178: 703000 | G178: 891000 | H178: 1316000 | I178: 1926000 | J178: 2226000 | K178: 2498000 | L178: 2610000 | M178: 2893000 | N178: 3107000 | O178: 3361000
A179: =VLOOKUP(B179,'PORTFOLIO RAW'!C:C,1,FALSE) -> 905624 | B179: 905624 | C179: MASCO CORP - EBIT & DEPRECIATION | D179: 905624(WC18198) | E179: 1276000 | F179: 255000 | G179: 338000 | H179: -247000 | I179: 45000 | J179: 510000 | K179: 855000 | L179: 967000 | M179: 1061000 | N179: 1218000 | O179: 1314000
A180: =VLOOKUP(B180,'PORTFOLIO RAW'!C:C,1,FALSE) -> 130062 | B180: 130062 | C180: MARTIN MARIETTA MAT - EBIT & DEPRECIATION | D180: 130062(WC18198) | E180: 591853 | F180: 488727 | G180: 368113 | H180: 377700 | I180: 332600 | J180: 333463 | K180: 391454 | L180: 538000 | M180: 753700 | N180: 974000 | O180: 1007600
A181: =VLOOKUP(B181,'PORTFOLIO RAW'!C:C,1,FALSE) -> 286738 | B181: 286738 | C181: METLIFE INC - EBIT & DEPRECIATION | D181: 286738(WC18198) | E181: 6543000 | F181: 6655000 | G181: -2789000 | H181: 5144000 | I181: 11650000 | J181: 2530000 | K181: 6048000 | L181: 10733000 | M181: 9371000 | N181: 1658000 | O181: 5460000
A182: =VLOOKUP(B182,'PORTFOLIO RAW'!C:C,1,FALSE) -> 771830 | B182: 771830 | C182: MAXIM INTEGRATED PRD - EBIT & DEPRECIATION | D182: 771830(WC18198) | E182: 518323 | F182: 644687 | G182: 240042 | H182: NA | I182: 876208 | J182: 747546 | K182: 792515 | L182: 678519 | M182: 578113 | N182: 562391 | O182: 878181
A183: =VLOOKUP(B183,'PORTFOLIO RAW'!C:C,1,FALSE) -> 312367 | B183: 312367 | C183: ACTIVISION BLIZZARD - EBIT & DEPRECIATION | D183: 312367(WC18198) | E183: 241000 | F183: 201000 | G183: 343000 | H183: 695000 | I183: 1483000 | J183: 1579000 | K183: 1675000 | L183: 1342000 | M183: 1825000 | N183: 2487000 | O183: 2516000
A184: =VLOOKUP(B184,'PORTFOLIO RAW'!C:C,1,FALSE) -> 912635 | B184: 912635 | C184: CVS HEALTH CORP - EBIT & DEPRECIATION | D184: 912635(WC18198) | E184: 5921600 | F184: 7340700 | G184: 7832000 | H184: 7637000 | I184: 7902000 | J184: 9156000 | K184: 9939000 | L184: 10224000 | M184: 11586000 | N184: 12210000 | O184: 11847000
A185: =VLOOKUP(B185,'PORTFOLIO RAW'!C:C,1,FALSE) -> 152533 | B185: 152533 | C185: LAB CORP OF AMERICA - EBIT & DEPRECIATION | D185: 152533(WC18198) | E185: 943800 | F185: 1023000 | G185: 1128800 | H185: 1178600 | I185: 1175500 | J185: 1247100 | K185: 1225300 | L185: 1167400 | M185: 1454800 | N185: 1815900 | O185: 1891900
A186: =VLOOKUP(B186,'PORTFOLIO RAW'!C:C,1,FALSE) -> 719643 | B186: 719643 | C186: MICROSOFT CORP - EBIT & DEPRECIATION | D186: 719643(WC18198) | E186: 21575000 | F186: 25870000 | G186: 22421000 | H186: 27671000 | I186: 30903000 | J186: 25405000 | K186: 31236000 | L186: 33629000 | M186: 25245000 | N186: 27616000 | O186: 34149000
A187: =VLOOKUP(B187,'PORTFOLIO RAW'!C:C,1,FALSE) -> 999506 | B187: 999506 | C187: MICRON TECHNOLOGY - EBIT & DEPRECIATION | D187: 999506(WC18198) | E187: 1590000 | F187: 531000 | G187: 470000 | H187: 4103000 | I187: 2780000 | J187: 1531000 | K187: 3320000 | L187: 5188000 | M187: 5647000 | N187: 3136000 | O187: 9663000
A188: =VLOOKUP(B188,'PORTFOLIO RAW'!C:C,1,FALSE) -> 328228 | B188: 328228 | C188: MICROCHIP TECHNOLOGY - EBIT & DEPRECIATION | D188: 328228(WC18198) | E188: 522677 | F188: 459027 | G188: 357565 | H188: 359020 | I188: 598674 | J188: 513580 | K188: 397809 | L188: 670386 | M188: 686558 | N188: 668856 | O188: 705563
A189: =VLOOKUP(B189,'PORTFOLIO RAW'!C:C,1,FALSE) -> 902172 | B189: 902172 | C189: 3M COMPANY - EBIT & DEPRECIATION | D189: 902172(WC18198) | E189: 7397000 | F189: 6476000 | G189: 5946000 | H189: 7057000 | I189: 7452000 | J189: 7832000 | K189: 8035000 | L189: 8536000 | M189: 8377000 | N189: 8726000 | O189: 9510000
A190: =VLOOKUP(B190,'PORTFOLIO RAW'!C:C,1,FALSE) -> 325475 | B190: 325475 | C190: MOHAWK INDUSTRIES - EBIT & DEPRECIATION | D190: 325475(WC18198) | E190: 1065023 | F190: -856062 | G190: 352322 | H190: 615072 | I190: 599225 | J190: 711524 | K190: 846688 | L190: 1107668 | M190: 1182594 | N190: 1691139 | O190: 1795640
A191: =VLOOKUP(B191,'PORTFOLIO RAW'!C:C,1,FALSE) -> 905010 | B191: 905010 | C191: XCEL ENERGY INC - EBIT & DEPRECIATION | D191: 905010(WC18198) | E191: 2245460 | F191: 2378197 | G191: 2394044 | H191: 2544998 | I191: 2778017 | J191: 2851124 | K191: 3047186 | L191: 3209649 | M191: 3308796 | N191: 3719944 | O191: 3873000
A192: =VLOOKUP(B192,'PORTFOLIO RAW'!C:C,1,FALSE) -> 902230 | B192: 902230 | C192: FORD MOTOR COMPANY - EBIT & DEPRECIATION | D192: 902230(WC18198) | E192: 19950000 | F192: 8040000 | G192: 17862000 | H192: 18920000 | I192: 18205000 | J192: 17332000 | K192: 16107000 | L192: 13986000 | M192: 19654000 | N192: 17741000 | O192: 20398000
A193: =VLOOKUP(B193,'PORTFOLIO RAW'!C:C,1,FALSE) -> 884383 | B193: 884383 | C193: NATL OILWELL VARCO - EBIT & DEPRECIATION | D193: 884383(WC18198) | E193: 2293300 | F193: 3387800 | G193: 2704000 | H193: 2918000 | I193: 3471000 | J193: 4124000 | K193: 4149000 | L193: 4320000 | M193: 248000 | N193: -1794000 | O193: 413000
...

Sheet EQIT
A1: EQUITY
B2: 1 | C2: 2 | D2: 3 | E2: 4 | F2: 5 | G2: 6 | H2: 7 | I2: 8 | J2: 9 | K2: 10 | L2: 11 | M2: 12 | N2: 13 | O2: 14
B3: Code | C3: Name | D3: Code | E3: 2007 | F3: 2008 | G3: 2009 | H3: 2010 | I3: 2011 | J3: 2012 | K3: 2013 | L3: 2014 | M3: 2015 | N3: 2016 | O3: 2017
A4: =VLOOKUP(B4,'[1]PORTFOLIO RAW'!B:B,1,FALSE) -> 891399 | B4: 891399 | C4: AMAZON.COM INC - COMMON SHAREHOLDERS' EQUITY | D4: 891399(WC03501) | E4: 1197000 | F4: 2672000 | G4: 5257000 | H4: 6864000 | I4: 7757000 | J4: 8192000 | K4: 9746000 | L4: 10741000 | M4: 13384000 | N4: 19285000 | O4: 27709000
A5: =VLOOKUP(B5,'[1]PORTFOLIO RAW'!B:B,1,FALSE) -> 916328 | B5: 916328 | C5: ABBOTT LABORATORIES - COMMON SHAREHOLDERS' EQUITY | D5: 916328(WC03501) | E5: 17778540 | F5: 17479551 | G5: 22855627 | H5: 22388135 | I5: 24439833 | J5: 26720961 | K5: 25171000 | L5: 21526000 | M5: 21211000 | N5: 20538000 | O5: 30897000
A6: =VLOOKUP(B6,'[1]PORTFOLIO RAW'!B:B,1,FALSE) -> 545101 | B6: 545101 | C6: AES CORP - COMMON SHAREHOLDERS' EQUITY | D6: 545101(WC03501) | E6: 3164000 | F6: 3669000 | G6: 4675000 | H6: 6473000 | I6: 5946000 | J6: 4569000 | K6: 4330000 | L6: 4272000 | M6: 3149000 | N6: 2794000 | O6: 2465000
A7: =VLOOKUP(B7,'[1]PORTFOLIO RAW'!B:B,1,FALSE) -> 906187 | B7: 906187 | C7: INT'L BUSINESS MACHS - COMMON SHAREHOLDERS' EQUITY | D7: 906187(WC03501) | E7: 28469000 | F7: 13465000 | G7: 22637000 | H7: 23046000 | I7: 20139000 | J7: 18860000 | K7: 22792000 | L7: 11869000 | M7: 14262000 | N7: 18246000 | O7: 17594000
A8: =VLOOKUP(B8,'[1]PORTFOLIO RAW'!B:B,1,FALSE) -> 936365 | B8: 936365 | C8: ADVANCED MICRO - COMMON SHAREHOLDERS' EQUITY | D8: 936365(WC03501) | E8: 2990000 | F8: -82000 | G8: 648000 | H8: 1013000 | I8: 1590000 | J8: 538000 | K8: 544000 | L8: 187000 | M8: -412000 | N8: 416000 | O8: 611000
A9: =VLOOKUP(B9,'[1]PORTFOLIO RAW'!B:B,1,FALSE) -> 749382 | B9: 749382 | C9: ADOBE INC - COMMON SHAREHOLDERS' EQUITY | D9: 749382(WC03501) | E9: 4649982 | F9: 4410354 | G9: 4890568 | H9: 5192387 | I9: 5783113 | J9: 6665182 | K9: 6724634 | L9: 6775905 | M9: 7001580 | N9: 7424835 | O9: 8459869
A10: =VLOOKUP(B10,'[1]PORTFOLIO RAW'!B:B,1,FALSE) -> 905271 | B10: 905271 | C10: AIR PRODUCTS & CHEMS - COMMON SHAREHOLDERS' EQUITY | D10: 905271(WC03501) | E10: 5495600 | F10: 5030700 | G10: 4791900 | H10: 5546900 | I10: 5795800 | J10: 6477200 | K10: 7042100 | L10: 7365800 | M10: 7249000 | N10: 7079600 | O10: 10086200
A11: =VLOOKUP(B11,'[1]PORTFOLIO RAW'!B:B,1,FALSE) -> 894371 | B11: 894371 | C11: BOSTON PROPERTIES - COMMON SHAREHOLDERS' EQUITY | D11: 894371(WC03501) | E11: 3668825 | F11: 3531267 | G11: 4446002 | H11: 4372643 | I11: 4865998 | J11: 5097065 | K11: 5541153 | L11: 5697298 | M11: 5709435 | N11: 5586295 | O11: 5613957
A12: =VLOOKUP(B12,'[1]PORTFOLIO RAW'!B:B,1,FALSE) -> 322677 | B12: 322677 | C12: ALLSTATE CORP - COMMON SHAREHOLDERS' EQUITY | D12: 322677(WC03501) | E12: 20963000 | F12: 16379000 | G12: 17562000 | H12: 18081000 | I12: 17311000 | J12: 17746000 | K12: 19054000 | L12: 18632000 | M12: 17600000 | N12: 17715000 | O12: 19084000
A13: =VLOOKUP(B13,'[1]PORTFOLIO RAW'!B:B,1,FALSE) -> 906191 | B13: 906191 | C13: HONEYWELL INTERNATNL - COMMON SHAREHOLDERS' EQUITY | D13: 906191(WC03501) | E13: 9222000 | F13: 7187000 | G13: 8844000 | H13: 10666000 | I13: 10806000 | J13: 12975000 | K13: 17467000 | L13: 17657000 | M13: 18283000 | N13: 19369000 | O13: 17276000
A14: =VLOOKUP(B14,'[1]PORTFOLIO RAW'!B:B,1,FALSE) -> 938692 | B14: 938692 | C14: AMGEN INC - COMMON SHAREHOLDERS' EQUITY | D14: 938692(WC03501) | E14: 17869000 | F14: 20386000 | G14: 22667000 | H14: 23944000 | I14: 19029000 | J14: 19060000 | K14: 22096000 | L14: 25778000 | M14: 28083000 | N14: 29875000 | O14: 25241000
A15: =VLOOKUP(B15,'[1]PORTFOLIO RAW'!B:B,1,FALSE) -> 905802 | B15: 905802 | C15: HESS CORPORATION - COMMON SHAREHOLDERS' EQUITY | D15: 905802(WC03501) | E15: 9760000 | F15: 12307000 | G15: 13384000 | H15: 16689000 | I15: 18516000 | J15: 21090000 | K15: 24720000 | L15: 22205000 | M15: 19386000 | N15: 14533000 | O15: 11050000
... A110: =VLOOKUP(B110,'[1]PORTFOLIO RAW'!B:B,1,FALSE) -> 905016 | B110: 905016 | C110: NEXTERA ENERGY - COMMON SHAREHOLDERS' EQUITY | D110: 905016(WC03501) | E110: 10735000 | F110: 11681000 | G110: 12967000 | H110: 14461000 | I110: 14943000 | J110: 16068000 | K110: 18040000 | L110: 19916000 | M110: 22574000 | N110: 24341000 | O110: 28208000
A111: =VLOOKUP(B111,'[1]PORTFOLIO RAW'!B:B,1,FALSE) -> 28341F | B111: 28341F | C111: ASSURANT INC - COMMON SHAREHOLDERS' EQUITY | D111: 28341F(WC03501) | E111: 4065519 | F111: 4187905 | G111: 4658699 | H111: 4367282 | I111: 4313163 | J111: 5185366 | K111: 4280981 | L111: 4361631 | M111: 4006090 | N111: 3618201 | O111: 3671500
A112: =VLOOKUP(B112,'[1]PORTFOLIO RAW'!B:B,1,FALSE) -> 755980 | B112: 755980 | C112: FASTENAL COMPANY - COMMON SHAREHOLDERS' EQUITY | D112: 755980(WC03501) | E112: 1010161 | F112: 1142259 | G112: 1190843 | H112: 1282512 | I112: 1458976 | J112: 1560360 | K112: 1772697 | L112: 1915217 | M112: 1801289 | N112: 1933094 | O112: 2096900
A113: =VLOOKUP(B113,'[1]PORTFOLIO RAW'!B:B,1,FALSE) -> 905994 | B113: 905994 | C113: FEDERAL REALTY INVST - COMMON SHAREHOLDERS' EQUITY | D113: 905994(WC03501) | E113: 1105438 | F113: 1104605 | G113: 1167340 | H113: 1139836 | I113: 1206095 | J113: 1276815 | K113: 1438163 | L113: 1594404 | M113: 1653752 | N113: 1966736 | O113: 2106709
A114: =VLOOKUP(B114,'[1]PORTFOLIO RAW'!B:B,1,FALSE) -> 997198 | B114: 997198 | C114: FIFTH THIRD BANCORP - COMMON SHAREHOLDERS' EQUITY | D114: 997198(WC03501) | E114: 9152000 | F114: 7836000 | G114: 9678000 | H114: 10232000 | I114: 12790000 | J114: 13305000 | K114: 13555000 | L114: 14295000 | M114: 14508000 | N114: 14874000 | O114: 15034000
A115: =VLOOKUP(B115,'[1]PORTFOLIO RAW'!B:B,1,FALSE) -> 951503 | B115: 951503 | C115: M&T BANK CORPORATION - COMMON SHAREHOLDERS' EQUITY | D115: 951503(WC03501) | E115: 6485256 | F115: 6184731 | G115: 6974907 | H115: 7579695 | I115: 8406624 | J115: 9321093 | K115: 10424032 | L115: 11104396 | M115: 14941789 | N115: 15255122 | O115: 15019319
A116: =VLOOKUP(B116,'[1]PORTFOLIO RAW'!B:B,1,FALSE) -> 741123 | B116: 741123 | C116: FISERV INC - COMMON SHAREHOLDERS' EQUITY | D116: 741123(WC03501) | E116: 2467000 | F116: 2594000 | G116: 3026000 | H116: 3229000 | I116: 3258000 | J116: 3417000 | K116: 3585000 | L116: 3295000 | M116: 2660000 | N116: 2541000 | O116: 2731000
A117: =VLOOKUP(B117,'[1]PORTFOLIO RAW'!B:B,1,FALSE) -> 546814 | B117: 546814 | C117: MACY'S INC - COMMON SHAREHOLDERS' EQUITY | D117: 546814(WC03501) | E117: 9907000 | F117: 4646000 | G117: 4701000 | H117: 5530000 | I117: 5933000 | J117: 6051000 | K117: 6249000 | L117: 5378000 | M117: 4250000 | N117: 4323000 | O117: 5673000
A118: =VLOOKUP(B118,'[1]PORTFOLIO RAW'!B:B,1,FALSE) -> 938076 | B118: 938076 | C118: FRANKLIN RESOURCES - COMMON SHAREHOLDERS' EQUITY | D118: 938076(WC03501) | E118: 7332275 | F118: 7074364 | G118: 7632173 | H118: 7726994 | I118: 8524731 | J118: 9201300 | K118: 10073100 | L118: 11584100 | M118: 11841000 | N118: 11935800 | O118: 12620000
A119: =VLOOKUP(B119,'[1]PORTFOLIO RAW'!B:B,1,FALSE) -> 152594 | B119: 152594 | C119: FREEPORT-MCMORAN INC - COMMON SHAREHOLDERS' EQUITY | D119: 152594(WC03501) | E119: 14259000 | F119: 2066000 | G119: 6244000 | H119: 12504000 | I119: 15642000 | J119: 17543000 | K119: 20934000 | L119: 18287000 | M119: 7828000 | N119: 6051000 | O119: 7977000
A120: =VLOOKUP(B120,'[1]PORTFOLIO RAW'!B:B,1,FALSE) -> 951018 | B120: 951018 | C120: GAP INC - COMMON SHAREHOLDERS' EQUITY | D120: 951018(WC03501) | E120: 4274000 | F120: 4387000 | G120: 4891000 | H120: 4080000 | I120: 2755000 | J120: 2894000 | K120: 3062000 | L120: 2983000 | M120: 2545000 | N120: 2904000 | O120: 3144000
A121: =VLOOKUP(B121,'[1]PORTFOLIO RAW'!B:B,1,FALSE) -> 907652 | B121: 907652 | C121: GENERAL DYNAMICS - COMMON SHAREHOLDERS' EQUITY | D121: 907652(WC03501) | E121: 11768000 | F121: 10053000 | G121: 12423000 | H121: 13316000 | I121: 13232000 | J121: 11390000 | K121: 14501000 | L121: 11829000 | M121: 10738000 | N121: 10976000 | O121: 11435000
A122: =VLOOKUP(B122,'[1]PORTFOLIO RAW'!B:B,1,FALSE) -> 905801 | B122: 905801 | C122: GENERAL MILLS, INC. - COMMON SHAREHOLDERS' EQUITY | D122: 905801(WC03501) | E122: 5319000 | F122: 6215800 | G122: 5174700 | H122: 5402900 | I122: 6365500 | J122: 6421700 | K122: 6672200 | L122: 6534800 | M122: 4996700 | N122: 4930200 | O122: 4327900
A123: =VLOOKUP(B123,'[1]PORTFOLIO RAW'!B:B,1,FALSE) -> 906511 | B123: 906511 | C123: GENUINE PARTS CO - COMMON SHAREHOLDERS' EQUITY | D123: 906511(WC03501) | E123: 2716716 | F123: 2324332 | G123: 2621330 | H123: 2793819 | I123: 2783235 | J123: 2997887 | K123: 3349074 | L123: 3301248 | M123: 3146567 | N123: 3193728 | O123: 3412152
... A237: =VLOOKUP(B237,'[1]PORTFOLIO RAW'!B:B,1,FALSE) -> 933974 | B237: 933974 | C237: TRAVELERS COS - COMMON SHAREHOLDERS' EQUITY | D237: 933974(WC03501) | E237: 25885000 | F237: 25374000 | G237: 25475000 | H237: 23549000 | I237: 21606000 | J237: 22302000 | K237: 23474000 | L237: 22870000 | M237: 22309000 | N237: 22491000 | O237: 22777000
A238: =VLOOKUP(B238,'[1]PORTFOLIO RAW'!B:B,1,FALSE) -> 14015T | B238: 14015T | C238: FIDELITY NATNL INF - COMMON SHAREHOLDERS' EQUITY | D238: 14015T(WC03501) | E238: 3781179 | F238: 3532800 | G238: 8308900 | H238: 6403200 | I238: 6503000 | J238: 6640900 | K238: 6580500 | L238: 6556700 | M238: 9321000 | N238: 9741000 | O238: 10835000
A239: =VLOOKUP(B239,'[1]PORTFOLIO RAW'!B:B,1,FALSE) -> 905019 | B239: 905019 | C239: MERCK & CO INC - COMMON SHAREHOLDERS' EQUITY | D239: 905019(WC03501) | E239: 18184700 | F239: 18758300 | G239: 59058000 | H239: 54376000 | I239: 54517000 | J239: 53020000 | K239: 49765000 | L239: 48647000 | M239: 44676000 | N239: 40088000 | O239: 34336000
A240: =VLOOKUP(B240,'[1]PORTFOLIO RAW'!B:B,1,FALSE) -> 912090 | B240: 912090 | C240: SCHLUMBERGER LIMITED - COMMON SHAREHOLDERS' EQUITY | D240: 912090(WC03501) | E240: 14876000 | F240: 16863000 | G240: 19120000 | H240: 31226000 | I240: 31263000 | J240: 34751000 | K240: 39469000 | L240: 37850000 | M240: 35633000 | N240: 41078000 | O240: 36842000
A241: =VLOOKUP(B241,'[1]PORTFOLIO RAW'!B:B,1,FALSE) -> 755741 | B241: 755741 | C241: CHARLES SCHWAB CORP - COMMON SHAREHOLDERS' EQUITY | D241: 755741(WC03501) | E241: 3732000 | F241: 4061000 | G241: 5073000 | H241: 6226000 | I241: 7714000 | J241: 8704000 | K241: 9496000 | L241: 10918000 | M241: 11917000 | N241: 13586000 | O241: 15675000
A242: =VLOOKUP(B242,'[1]PORTFOLIO RAW'!B:B,1,FALSE) -> 14361V | B242: 14361V | C242: ZIMMER BIOMET - COMMON SHAREHOLDERS' EQUITY | D242: 14361V(WC03501) | E242: 5449600 | F242: 5650300 | G242: 5638700 | H242: 5771300 | I242: 5507200 | J242: 5860900 | K242: 6297300 | L242: 6520800 | M242: 9887900 | N242: 9668900 | O242: 11735800
A243: =VLOOKUP(B243,'[1]PORTFOLIO RAW'!B:B,1,FALSE) -> 154680 | B243: 154680 | C243: AMERISOURCEBERGEN - COMMON SHAREHOLDERS' EQUITY | D243: 154680(WC03501) | E243: 3099720 | F243: 2710045 | G243: 2716469 | H243: 2954297 | I243: 2866858 | J243: 2456712 | K243: 2319745 | L243: 1956899 | M243: 633520 | N243: 2129404 | O243: 2064461
A244: =VLOOKUP(B244,'[1]PORTFOLIO RAW'!B:B,1,FALSE) -> 14698C | B244: 14698C | C244: PRINCIPAL FINL GROUP - COMMON SHAREHOLDERS' EQUITY | D244: 14698C(WC03501) | E244: 6854600 | F244: 6393600 | G244: 8284000 | H244: 9045100 | I244: 8709200 | J244: 8267500 | K244: 9434200 | L244: 10183900 | M244: 9311600 | N244: 10227300 | O244: 11335900
A245: =VLOOKUP(B245,'[1]PORTFOLIO RAW'!B:B,1,FALSE) -> 905361 | B245: 905361 | C245: SHERWIN-WILLIAMS CO - COMMON SHAREHOLDERS' EQUITY | D245: 905361(WC03501) | E245: 1785727 | F245: 1605648 | G245: 1490950 | H245: 1609440 | I245: 1516919 | J245: 1690718 | K245: 1734129 | L245: 996470 | M245: 867910 | N245: 1878441 | O245: 3692188
A246: =VLOOKUP(B246,'[1]PORTFOLIO RAW'!B:B,1,FALSE) -> 357834 | B246: 357834 | C246: SIMON PROPERTY GROUP - COMMON SHAREHOLDERS' EQUITY | D246: 357834(WC03501) | E246: 2833974 | F246: 2614638 | G246: 4412433 | H246: 4785405 | I246: 4604619 | J246: 5865884 | K246: 5805016 | L246: 5049115 | M246: 4427731 | N246: 4267043 | O246: 3643091
A247: =VLOOKUP(B247,'[1]PORTFOLIO RAW'!B:B,1,FALSE) -> 906400 | B247: 906400 | C247: SNAP-ON INC - COMMON SHAREHOLDERS' EQUITY | D247: 906400(WC03501) | E247: 1280100 | F247: 1186500 | G247: 1290000 | H247: 1388500 | I247: 1530900 | J247: 1802100 | K247: 2113200 | L247: 2207800 | M247: 2412700 | N247: 2617200 | O247: 2953900
A248: =VLOOKUP(B248,'[1]PORTFOLIO RAW'!B:B,1,FALSE) -> 14861V | B248: 14861V | C248: PRUDENTIAL FINANCIAL - COMMON SHAREHOLDERS' EQUITY | D248: 14861V(WC03501) | E248: 23057000 | F248: 20157000 | G248: 24684000 | H248: 29270000 | I248: 31588000 | J248: 27173000 | K248: 24934000 | L248: 22519000 | M248: 26117000 | N248: 27692000 | O248: 34101000
A249: =VLOOKUP(B249,'[1]PORTFOLIO RAW'!B:B,1,FALSE) -> 14806F | B249: 14806F | C249: ADVANCE AUTO PARTS - COMMON SHAREHOLDERS' EQUITY | D249: 14806F(WC03501) | E249: 1023795 | F249: 1075166 | G249: 1282365 | H249: 1039374 | I249: 847914 | J249: 1210694 | K249: 1516205 | L249: 2002912 | M249: 2460648 | N249: 2916192 | O249: 3415196
A250: =VLOOKUP(B250,'[1]PORTFOLIO RAW'!B:B,1,FALSE) -> 902324 | B250: 902324 | C250: EDISON INTERNATIONAL - COMMON SHAREHOLDERS' EQUITY | D250: 902324(WC03501) | E250: 8444000 | F250: 9517000 | G250: 9841000 | H250: 10583000 | I250: 10055000 | J250: 9432000 | K250: 9925000 | L250: 10960000 | M250: 11368000 | N250: 11996000 | O250: 11671000
A251: =VLOOKUP(B251,'[1]PORTFOLIO RAW'!B:B,1,FALSE) -> 902325 | B251: 902325 | C251: SOUTHERN CO - COMMON SHAREHOLDERS' EQUITY | D251: 902325(WC03501) | E251: 12385000 | F251: 13276000 | G251: 14878000 | H251: 16202000 | I251: 17578000 | J251: 18297000 | K251: 19008000 | L251: 19949000 | M251: 20592000 | N251: 24758000 | O251: 24167000
A252: =VLOOKUP(B252,'[1]PORTFOLIO RAW'!B:B,1,FALSE) -> 992305 | B252: 992305 | C252: BB&T CORPORATION - COMMON SHAREHOLDERS' EQUITY | D252: 992305(WC03501) | E252: 12632000 | F252: 12955000 | G252: 16191000 | H252: 16436000 | I252: 17418000 | J252: 18983000 | K252: 20156000 | L252: 21663000 | M252: 24631000 | N252: 26741000 | O252: 26508000
A253: =VLOOKUP(B253,'[1]PORTFOLIO RAW'!B:B,1,FALSE) -> 905647 | B253: 905647 | C253: SOUTHWEST AIRLINES - COMMON SHAREHOLDERS' EQUITY | D253: 905647(WC03501) | E253: 6941000 | F253: 4953000 | G253: 5466000 | H253: 6237000 | I253: 6877000 | J253: 6992000 | K253: 7336000 | L253: 6775000 | M253: 7358000 | N253: 8441000 | O253: 10430000
A254: =VLOOKUP(B254,'[1]PORTFOLIO RAW'!B:B,1,FALSE) -> 945388 | B254: 945388 | C254: AT&T INC - COMMON SHAREHOLDERS' EQUITY | D254: 945388(WC03501) | E254: 115367000 | F254: 96347000 | G254: 101900000 | H254: 111647000 | I254: 105534000 | J254: 92362000 | K254: 90988000 | L254: 86370000 | M254: 122671000 | N254: 123135000 | O254: 140861000
A255: =VLOOKUP(B255,'[1]PORTFOLIO RAW'!B:B,1,FALSE) -> 905024 | B255: 905024 | C255: CHEVRON CORPORATION - COMMON SHAREHOLDERS' EQUITY | D255: 905024(WC03501) | E255: 77089000 | F255: 86648000 | G255: 91914000 | H255: 105081000 | I255: 121382000 | J255: 136524000 | K255: 149113000 | L255: 155028000 | M255: 152716000 | N255: 145556000 | O255: 148124000
A256: =VLOOKUP(B256,'[1]PORTFOLIO RAW'!B:B,1,FALSE) -> 951052 | B256: 951052 | C256: STATE STREET CORP - COMMON SHAREHOLDERS' EQUITY | D256: 951052(WC03501) | E256: 11299000 | F256: 10891000 | G256: 14491000 | H256: 17787000 | I256: 18898000 | J256: 20380000 | K256: 19887000 | L256: 19512000 | M256: 18400000 | N256: 18023000 | O256: 19121000
A257: =VLOOKUP(B257,'[1]PORTFOLIO RAW'!B:B,1,FALSE) -> 326143 | B257: 326143 | C257: STARBUCKS CORP - COMMON SHAREHOLDERS' EQUITY | D257: 326143(WC03501) | E257: 2284117 | F257: 2490900 | G257: 3045700 | H257: 3674700 | I257: 4384900 | J257: 5109000 | K257: 4480200 | L257: 5272000 | M257: 5818000 | N257: 5884000 | O257: 5450100
A258: =VLOOKUP(B258,'[1]PORTFOLIO RAW'!B:B,1,FALSE) -> 905792 | B258: 905792 | C258: PUBLIC STORAGE, INC - COMMON SHAREHOLDERS' EQUITY | D258: 905792(WC03501) | E258: 5235629 | F258: 5291137 | G258: 5528630 | H258: 5280571 | I258: 5176938 | J258: 5256256 | K258: 5229230 | L258: 5155796 | M258: 5115641 | N258: 5044410 | O258: 4915009
A259: =VLOOKUP(B259,'[1]PORTFOLIO RAW'!B:B,1,FALSE) -> 981722 | B259: 981722 | C259: STRYKER CORPORATION - COMMON SHAREHOLDERS' EQUITY | D259: 981722(WC03501) | E259: 5378500 | F259: 5406700 | G259: 6595100 | H259: 7173600 | I259: 7683000 | J259: 8597000 | K259: 9047000 | L259: 8595000 | M259: 8511000 | N259: 9550000 | O259: 9966000
A260: =VLOOKUP(B260,'[1]PORTFOLIO RAW'!B:B,1,FALSE) -> 922725 | B260: 922725 | C260: SUNTRUST BANKS INC - COMMON SHAREHOLDERS' EQUITY | D260: 922725(WC03501) | E260: 17552518 | F260: 17166406 | G260: 17495055 | H260: 18188000 | I260: 19791000 | J260: 20260000 | K260: 20697000 | L260: 21780000 | M260: 22212000 | N260: 22393000 | O260: 22679000
A261: =VLOOKUP(B261,'[1]PORTFOLIO RAW'!B:B,1,FALSE) -> 541900 | B261: 541900 | C261: SYMANTEC CORP - COMMON SHAREHOLDERS' EQUITY | D261: 541900(WC03501) | E261: 11601513 | F261: 10973183 | G261: 3947988 | H261: 4548000 | I261: 4528000 | J261: 5094000 | K261: 5421000 | L261: 5797000 | M261: 5935000 | N261: 3676000 | O261: 3487000
... A284: =VLOOKUP(B284,'[1]PORTFOLIO RAW'!B:B,1,FALSE) -> 904869 | B284: 904869 | C284: WHIRLPOOL CORP - COMMON SHAREHOLDERS' EQUITY | D284: 904869(WC03501) | E284: 3911000 | F284: 3006000 | G284: 3664000 | H284: 4226000 | I284: 4181000 | J284: 4260000 | K284: 4924000 | L284: 4885000 | M284: 4743000 | N284: 4773000 | O284: 4198000
A285: =VLOOKUP(B285,'[1]PORTFOLIO RAW'!B:B,1,FALSE) -> 26406N | B285: 26406N | C285: WYNN RESORTS, LTD - COMMON SHAREHOLDERS' EQUITY | D285: 26406N(WC03501) | E285: 1948159 | F285: 1592522 | G285: 3034338 | H285: 2237948 | I285: 2089022 | J285: -259037 | K285: -184507 | L285: -28779 | M285: -111979 | N285: 157949 | O285: 947846
A286: =VLOOKUP(B286,'[1]PORTFOLIO RAW'!B:B,1,FALSE) -> 26393N | B286: 26393N | C286: CME GROUP INC - COMMON SHAREHOLDERS' EQUITY | D286: 26393N(WC03501) | E286: 12305637 | F286: 18688569 | G286: 19301000 | H286: 20060100 | I286: 21552000 | J286: 21419100 | K286: 21154800 | L286: 20923500 | M286: 20551800 | N286: 20340700 | O286: 22411800
A287: =VLOOKUP(B287,'[1]PORTFOLIO RAW'!B:B,1,FALSE) -> 922407 | B287: 922407 | C287: WILLIAMS COMPANIES - COMMON SHAREHOLDERS' EQUITY | D287: 922407(WC03501) | E287: 6375000 | F287: 8440000 | G287: 8447000 | H287: 7288000 | I287: 1793000 | J287: 4752000 | K287: 4864000 | L287: 8777000 | M287: 6148000 | N287: 4643000 | O287: 9656000
A288: =VLOOKUP(B288,'[1]PORTFOLIO RAW'!B:B,1,FALSE) -> 906979 | B288: 906979 | C288: ALLIANT ENERGY CORP - COMMON SHAREHOLDERS' EQUITY | D288: 906979(WC03501) | E288: 2681200 | F288: 2823500 | G288: 2772600 | H288: 2893600 | I288: 3013000 | J288: 3134900 | K288: 3281400 | L288: 3438700 | M288: 3724100 | N288: 3862000 | O288: 4182200
A289: =VLOOKUP(B289,'[1]PORTFOLIO RAW'!B:B,1,FALSE) -> 877723 | B289: 877723 | C289: CARMAX INC - COMMON SHAREHOLDERS' EQUITY | D289: 877723(WC03501) | E289: 1247375 | F289: 1488926 | G289: 1593067 | H289: 1933582 | I289: 2291630 | J289: 2673112 | K289: 3019167 | L289: 3316997 | M289: 3156785 | N289: 2904786 | O289: 3108580
A290: =VLOOKUP(B290,'[1]PORTFOLIO RAW'!B:B,1,FALSE) -> 543542 | B290: 543542 | C290: XILINX INC - COMMON SHAREHOLDERS' EQUITY | D290: 543542(WC03501) | E290: 1772740 | F290: 1671823 | G290: 1737900 | H290: 2120470 | I290: 2414617 | J290: 2707685 | K290: 2963296 | L290: 2787681 | M290: 2635541 | N290: 2602787 | O290: 2509039
A291: =VLOOKUP(B291,'[1]PORTFOLIO RAW'!B:B,1,FALSE) -> 26276P | B291: 26276P | C291: CIMAREX ENERGY CO - COMMON SHAREHOLDERS' EQUITY | D291: 26276P(WC03501) | E291: 3259287 | F291: 2349365 | G291: 2038106 | H291: 2609832 | I291: 3130613 | J291: 3474736 | K291: 4022208 | L291: 4500632 | M291: 2797678 | N291: 2360064 | O291: 2568278
A292: =VLOOKUP(B292,'[1]PORTFOLIO RAW'!B:B,1,FALSE) -> 921855 | B292: 921855 | C292: TJX COMPANIES INC - COMMON SHAREHOLDERS' EQUITY | D292: 921855(WC03501) | E292: 2131245 | F292: 2134557 | G292: 2889276 | H292: 3099899 | I292: 3209290 | J292: 3665937 | K292: 4229893 | L292: 4264230 | M292: 4307075 | N292: 4510599 | O292: 5148309
A293: =VLOOKUP(B293,'[1]PORTFOLIO RAW'!B:B,1,FALSE) -> 951584 | B293: 951584 | C293: ZIONS BANCORP - COMMON SHAREHOLDERS' EQUITY | D293: 951584(WC03501) | E293: 5052800 | F293: 4919862 | G293: 4189874 | H293: 4591607 | I293: 4607748 | J293: 4923767 | K293: 5460593 | L293: 6365519 | M293: 6679029 | N293: 6924705 | O293: 7113000
A294: =VLOOKUP(B294,'[1]PORTFOLIO RAW'!B:B,1,FALSE) -> 951051 | B294: 951051 | C294: REGIONS FINANCIAL - COMMON SHAREHOLDERS' EQUITY | D294: 951051(WC03501) | E294: 19823029 | F294: 13312837 | G294: 14113000 | H294: 13234000 | I294: 12999000 | J294: 14999000 | K294: 15268000 | L294: 15989000 | M294: 15844000 | N294: 15664000 | O294: 15192000
A295: =VLOOKUP(B295,'[1]PORTFOLIO RAW'!B:B,1,FALSE) -> 29756N | B295: 29756N | C295: CELANESE CORPORATION - COMMON SHAREHOLDERS' EQUITY | D295: 29756N(WC03501) | E295: 1062000 | F295: 182000 | G295: 584000 | H295: 926000 | I295: 1341000 | J295: 1730000 | K295: 2699000 | L295: 2818000 | M295: 2378000 | N295: 2588000 | O295: 2887000
A296: =VLOOKUP(B296,'[1]PORTFOLIO RAW'!B:B,1,FALSE) -> 905997 | B296: 905997 | C296: MOLSON COORS BREW - COMMON SHAREHOLDERS' EQUITY | D296: 905997(WC03501) | E296: 7149391 | F296: 5980300 | G296: 7079600 | H296: 7798800 | I296: 7647900 | J296: 7966900 | K296: 8638900 | L296: 7863300 | M296: 7043000 | N296: 11418700 | O296: 13226100
A297: =VLOOKUP(B297,'[1]PORTFOLIO RAW'!B:B,1,FALSE) -> 31604H | B297: 31604H | C297: AMERIPRISE FIN - COMMON SHAREHOLDERS' EQUITY | D297: 31604H(WC03501) | E297: 7810000 | F297: 6178000 | G297: 9273000 | H297: 10725000 | I297: 10255000 | J297: 9092000 | K297: 8192000 | L297: 8124000 | M297: 7217000 | N297: 6292000 | O297: 5998000
A298: =VLOOKUP(B298,'[1]PORTFOLIO RAW'!B:B,1,FALSE) -> 543487 | B298: 543487 | C298: VIACOM, INC. - COMMON SHAREHOLDERS' EQUITY | D298: 543487(WC03501) | E298: 7111200 | F298: 7033000 | G298: 8704000 | H298: 9283000 | I298: 8644000 | J298: 7448000 | K298: 5193000 | L298: 3719000 | M298: 3538000 | N298: 4277000 | O298: 6035000
A299: =VLOOKUP(B299,'[1]PORTFOLIO RAW'!B:B,1,FALSE) -> 32480Q | B299: 32480Q | C299: CBS CORPORATION - COMMON SHAREHOLDERS' EQUITY | D299: 32480Q(WC03501) | E299: 21472400 | F299: 8597300 | G299: 9019400 | H299: 9820600 | I299: 9908000 | J299: 10213000 | K299: 9966000 | L299: 6970000 | M299: 5563000 | N299: 3689000 | O299: 1978000
A300: =VLOOKUP(B300,'[1]PORTFOLIO RAW'!B:B,1,FALSE) -> 41071J | B300: 41071J | C300: HANESBRANDS, INC. - COMMON SHAREHOLDERS' EQUITY | D300: 41071J(WC03501) | E300: 288904 | F300: 185155 | G300: 334719 | H300: 562674 | I300: 681061 | J300: 886866 | K300: 1230623 | L300: 1386772 | M300: 1275891 | N300: 1223914 | O300: 686202
A301: =VLOOKUP(B301,'[1]PORTFOLIO RAW'!B:B,1,FALSE) -> 41195M | B301: 41195M | C301: WESTERN UNION COMP - COMMON SHAREHOLDERS' EQUITY | D301: 41195M(WC03501) | E301: 50700 | F301: -8100 | G301: 353500 | H301: 582700 | I301: 894800 | J301: 940600 | K301: 1104700 | L301: 1300400 | M301: 1404900 | N301: 902200 | O301: -491400
A302: =VLOOKUP(B302,'[1]PORTFOLIO RAW'!B:B,1,FALSE) -> 517465 | B302: 517465 | C302: PEOPLE'S UNITED - COMMON SHAREHOLDERS' EQUITY | D302: 517465(WC03501) | E302: 4445400 | F302: 5175500 | G302: 5100700 | H302: 5219300 | I302: 5225000 | J302: 5038800 | K302: 4568400 | L302: 4633100 | M302: 4731600 | N302: 4897800 | O302: 5575800
A303: =VLOOKUP(B303,'[1]PORTFOLIO RAW'!B:B,1,FALSE) -> 905840 | B303: 905840 | C303: BANK OF NEW YORK - COMMON SHAREHOLDERS' EQUITY | D303: 905840(WC03501) | E303: 29403000 | F303: 25050000 | G303: 28977000 | H303: 32354000 | I303: 33417000 | J303: 35363000 | K303: 35959000 | L303: 35879000 | M303: 35485000 | N303: 35269000 | O303: 37709000
A304: =VLOOKUP(B304,'[1]PORTFOLIO RAW'!B:B,1,FALSE) -> 328314 | B304: 328314 | C304: CHUBB - COMMON SHAREHOLDERS' EQUITY | D304: 328314(WC03501) | E304: 16079000 | F304: 16158000 | G304: 19010000 | H304: 21575000 | I304: 22801000 | J304: 24898000 | K304: 27651000 | L304: 27736000 | M304: 28261000 | N304: 47217000 | O304: 49722000
A305: =VLOOKUP(B305,'[1]PORTFOLIO RAW'!B:B,1,FALSE) -> 31196R | B305: 31196R | C305: DISCOVERY INC - COMMON SHAREHOLDERS' EQUITY | D305: 31196R(WC03501) | E305: 2708262 | F305: 5534000 | G305: 6206000 | H305: 6223000 | I305: 6515000 | J305: 6289000 | K305: 6194000 | L305: 5600000 | M305: 5449000 | N305: 5165000 | O305: 4610000
A306: =VLOOKUP(B306,'[1]PORTFOLIO RAW'!B:B,1,FALSE) -> 771767 | B306: 771767 | C306: MOSAIC CO - COMMON SHAREHOLDERS' EQUITY | D306: 771767(WC03501) | E306: 4183900 | F306: 6731200 | G306: 8493000 | H306: 8722200 | I306: 11641600 | J306: 11983100 | K306: 11302300 | L306: 10703100 | M306: 9531800 | N306: 9584600 | O306: 9617500
A307: =VLOOKUP(B307,'[1]PORTFOLIO RAW'!B:B,1,FALSE) -> 921503 | B307: 921503 | C307: STANLEY BLACK - COMMON SHAREHOLDERS' EQUITY | D307: 921503(WC03501) | E307: 1728500 | F307: 1688000 | G307: 1986100 | H307: 7017000 | I307: 7003600 | J307: 6667100 | K307: 6799200 | L307: 6429100 | M307: 5811600 | N307: 6367000 | O307: 7547100
A308: =VLOOKUP(B308,'[1]PORTFOLIO RAW'!B:B,1,FALSE) -> 255781 | B308: 255781 | C308: GARMIN LTD. - COMMON SHAREHOLDERS' EQUITY | D308: 255781(WC03501) | E308: 2350614 | F308: 2225854 | G308: 2836447 | H308: 3049562 | I308: 3256581 | J308: 3531796 | K308: 3659706 | L308: 3403367 | M308: 3345126 | N308: 3418003 | O308: 3802466
A309: =VLOOKUP(B309,'[1]PORTFOLIO RAW'!B:B,1,FALSE) -> 670129 | B309: 670129 | C309: PROLOGIS - COMMON SHAREHOLDERS' EQUITY | D309: 670129(WC03501) | E309: 2531452 | F309: 2282607 | G309: 2707516 | H309: 3088223 | I309: 13079439 | J309: 12486817 | K309: 13611158 | L309: 13897274 | M309: 14589700 | N309: 14912846 | O309: 15562208
A310: =VLOOKUP(B310,'[1]PORTFOLIO RAW'!B:B,1,FALSE) -> 14352P | B310: 14352P | C310: ACCENTURE PLC - COMMON SHAREHOLDERS' EQUITY | D310: 14352P(WC03501) | E310: 2063332 | F310: 2540506 | G310: 2886593 | H310: 2835746 | I310: 3878951 | J310: 4145833 | K310: 4960186 | L310: 5732035 | M310: 6133725 | N310: 7555262 | O310: 8949477
A311: =VLOOKUP(B311,'[1]PORTFOLIO RAW'!B:B,1,FALSE) -> 894145 | B311: 894145 | C311: RALPH LAUREN - COMMON SHAREHOLDERS' EQUITY | D311: 894145(WC03501) | E311: 2334900 | F311: 2389700 | G311: 2735100 | H311: 3116600 | I311: 3304700 | J311: 3652500 | K311: 3784600 | L311: 4034000 | M311: 3891000 | N311: 3744000 | O311: 3299600
A312: =VLOOKUP(B312,'[1]PORTFOLIO RAW'!B:B,1,FALSE) -> 26599V | B312: 26599V | C312: SEAGATE TECHNOLOGY - COMMON SHAREHOLDERS' EQUITY | D312: 26599V(WC03501) | E312: 4737000 | F312: 4586000 | G312: 1524000 | H312: 2724000 | I312: 2463000 | J312: 3497000 | K312: 3495000 | L312: 2832000 | M312: 3018000 | N312: 1593000 | O312: 1364000
A313: =VLOOKUP(B313,'[1]PORTFOLIO RAW'!B:B,1,FALSE) -> 904878 | B313: 904878 | C313: MOTOROLA SOLUTIONS - COMMON SHAREHOLDERS' EQUITY | D313: 904878(WC03501) | E313: 15447000 | F313: 9507000 | G313: 9775000 | H313: 10885000 | I313: 5214000 | J313: 3265000 | K313: 3659000 | L313: 2735000 | M313: -106000 | N313: -964000 | O313: -1742000
A314: =VLOOKUP(B314,'[1]PORTFOLIO RAW'!B:B,1,FALSE) -> 922817 | B314: 922817 | C314: AON PLC - COMMON SHAREHOLDERS' EQUITY | D314: 922817(WC03501) | E314: 6121000 | F314: 5267000 | G314: 5335000 | H314: 8251000 | I314: 8078000 | J314: 7762000 | K314: 8145000 | L314: 6571000 | M314: 6106000 | N314: 5475000 | O314: 4583000
A315: =VLOOKUP(B315,'[1]PORTFOLIO RAW'!B:B,1,FALSE) -> 905446 | B315: 905446 | C315: INGERSOLL-RAND - COMMON SHAREHOLDERS' EQUITY | D315: 905446(WC03501) | E315: 5416912 | F315: 4782885 | G315: 4957056 | H315: 6033435 | I315: 5345560 | J315: 5418032 | K315: 5146159 | L315: 4951580 | M315: 5357181 | N315: 6298322 | O315: 5955010
A316: =VLOOKUP(B316,'[1]PORTFOLIO RAW'!B:B,1,FALSE) -> 28513N | B316: 28513N | C316: CBRE GROUP - COMMON SHAREHOLDERS' EQUITY | D316: 28513N(WC03501) | E316: 988603 | F316: 114686 | G316: 629122 | H316: 908215 | I316: 1151481 | J316: 1539211 | K316: 1895785 | L316: 2259830 | M316: 2712652 | N316: 3014487 | O316: 4019430
A317: =VLOOKUP(B317,'[1]PORTFOLIO RAW'!B:B,1,FALSE) -> 31412T | B317: 31412T | C317: EXPEDIA GROUP INC - COMMON SHAREHOLDERS' EQUITY | D317: 31412T(WC03501) | E317: 4818081 | F317: 2328394 | G317: 2682681 | H317: 2672544 | I317: 2199864 | J317: 2280259 | K317: 2145464 | L317: 1784267 | M317: 4864394 | N317: 4132301 | O317: 4522335
A318: =VLOOKUP(B318,'[1]PORTFOLIO RAW'!B:B,1,FALSE) -> 680902 | B318: 680902 | C318: AMERICAN TOWER CORP - COMMON SHAREHOLDERS' EQUITY | D318: 680902(WC03501) | E318: 3022092 | F318: 2991322 | G318: 3315082 | H318: 3501444 | I318: 3287220 | J318: 3573101 | K318: 3534165 | L318: 3953500 | M318: 4676679 | N318: 4788895 | O318: 6240100
A319: =VLOOKUP(B319,'[1]PORTFOLIO RAW'!B:B,1,FALSE) -> 904383 | B319: 904383 | C319: DUKE ENERGY CORP - COMMON SHAREHOLDERS' EQUITY | D319: 904383(WC03501) | E319: 21199000 | F319: 20988000 | G319: 21750000 | H319: 22522000 | I319: 22772000 | J319: 40863000 | K319: 41330000 | L319: 40875000 | M319: 39727000 | N319: 41033000 | O319: 41739000
A320: =VLOOKUP(B320,'[1]PORTFOLIO RAW'!B:B,1,FALSE) -> 13967E | B320: 13967E | C320: MONDELEZ - COMMON SHAREHOLDERS' EQUITY | D320: 13967E(WC03501) | E320: 27295000 | F320: 22200000 | G320: 25876000 | H320: 35834000 | I320: 35217000 | J320: 32215000 | K320: 32373000 | L320: 27750000 | M320: 28012000 | N320: 25161000 | O320: 26111000
A321: =VLOOKUP(B321,'[1]PORTFOLIO RAW'!B:B,1,FALSE) -> 903749 | B321: 903749 | C321: EATON CORP PLC - COMMON SHAREHOLDERS' EQUITY | D321: 903749(WC03501) | E321: 5172000 | F321: 6317000 | G321: 6777000 | H321: 7362000 | I321: 7469000 | J321: 15086000 | K321: 16791000 | L321: 15786000 | M321: 15186000 | N321: 14897000 | O321: 17253000
A322: =VLOOKUP(B322,'[1]PORTFOLIO RAW'!B:B,1,FALSE) -> 937343 | B322: 937343 | C322: L BRANDS INC - COMMON SHAREHOLDERS' EQUITY | D322: 937343(WC03501) | E322: 2219000 | F322: 1874000 | G322: 2183000 | H322: 1476000 | I322: 137000 | J322: -1015000 | K322: -370000 | L322: 18000 | M322: -259000 | N322: -729000 | O322: -753000
A323: =VLOOKUP(B323,'[1]PORTFOLIO RAW'!B:B,1,FALSE) -> 905113 | B323: 905113 | C323: ARCONIC INC - COMMON SHAREHOLDERS' EQUITY | D323: 905113(WC03501) | E323: 15961000 | F323: 11680000 | G323: 12365000 | H323: 13556000 | I323: 13789000 | J323: 13144000 | K323: 10538000 | L323: 12248000 | M323: 11988000 | N323: 5057000 | O323: 4855000
A324: =VLOOKUP(B324,'[1]PORTFOLIO RAW'!B:B,1,FALSE) -> 13967H | B324: 13967H | C324: WILLIS TOWERS WAT - COMMON SHAREHOLDERS' EQUITY | D324: 13967H(WC03501) | E324: 1347000 | F324: 1845000 | G324: 2180000 | H324: 2577000 | I324: 2486000 | J324: 1699000 | K324: 2215000 | L324: 1985000 | M324: 2229000 | N324: 10065000 | O324: 10126000
A325: =VLOOKUP(B325,'[1]PORTFOLIO RAW'!B:B,1,FALSE) -> 921431 | B325: 921431 | C325: BAKER HUGHES A GE CO - COMMON SHAREHOLDERS' EQUITY | D325: 921431(WC03501) | E325: 6305600 | F325: 6807000 | G325: 7284000 | H325: 14100000 | I325: 15746000 | J325: 17069000 | K325: 17713000 | L325: 18625000 | M325: 16298000 | N325: 12656000 | O325: 39033000
A326: =VLOOKUP(B326,'[1]PORTFOLIO RAW'!B:B,1,FALSE) -> 266220 | B326: 266220 | C326: TAPESTRY INC - COMMON SHAREHOLDERS' EQUITY | D326: 266220(WC03501) | E326: 1910354 | F326: 1515820 | G326: 1696042 | H326: 1505293 | I326: 1612569 | J326: 1992931 | K326: 2409158 | L326: 2420653 | M326: 2489900 | N326: 2682900 | O326: 3001900
A327: =VLOOKUP(B327,'[1]PORTFOLIO RAW'!B:B,1,FALSE) -> 30730Q | B327: 30730Q | C327: INTERCONTINENTAL - COMMON SHAREHOLDERS' EQUITY | D327: 30730Q(WC03501) | E327: 1476856 | F327: 2006231 | G327: 2399732 | H327: 2777550 | I327: 3121525 | J327: 3643377 | K327: 12583000 | L327: 12360000 | M327: 14808000 | N327: 15717000 | O327: 16924000
A328: =VLOOKUP(B328,'[1]PORTFOLIO RAW'!B:B,1,FALSE) -> 921925 | B328: 921925 | C328: JEFFERIES FINANCIAL - COMMON SHAREHOLDERS' EQUITY | D328: 921925(WC03501) | E328: 5570492 | F328: 2676797 | G328: 4361647 | H328: 6956758 | I328: 6174396 | J328: 6767268 | K328: 10102462 | L328: 10302158 | M328: 10401211 | N328: 10128100 | O328: 10105957
A329: =VLOOKUP(B329,'[1]PORTFOLIO RAW'!B:B,1,FALSE) -> 912278 | B329: 912278 | C329: CIGNA CORP - COMMON SHAREHOLDERS' EQUITY | D329: 912278(WC03501) | E329: 4620000 | F329: 3745000 | G329: 5065000 | H329: 6137000 | I329: 7627000 | J329: 8910000 | K329: 10113000 | L329: 10774000 | M329: 12035000 | N329: 13361000 | O329: 13407000
...

Sheet DEBT
A1: DEBT
B2: 1 | C2: 2 | D2: 3 | E2: 4 | F2: 5 | G2: 6 | H2: 7 | I2: 8 | J2: 9 | K2: 10 | L2: 11 | M2: 12 | N2: 13 | O2: 14
B3: Code | C3: Name | D3: Code | E3: 2007 | F3: 2008 | G3: 2009 | H3: 2010 | I3: 2011 | J3: 2012 | K3: 2013 | L3: 2014 | M3: 2015 | N3: 2016 | O3: 2017
A4: =VLOOKUP(B4,'[1]PORTFOLIO RAW'!B:B,1,FALSE) -> 891399 | B4: 891399 | C4: AMAZON.COM INC - TOTAL DEBT | D4: 891399(WC03255) | E4: 1361000 | F4: 592000 | G4: 393000 | H4: 865000 | I4: 1939000 | J4: 4964000 | K4: 6917000 | L4: 16089000 | M4: 17547000 | N4: 20410000 | O4: 44147000
A5: =VLOOKUP(B5,'[1]PORTFOLIO RAW'!B:B,1,FALSE) -> 916328 | B5: 916328 | C5: ABBOTT LABORATORIES - TOTAL DEBT | D5: 916328(WC03255) | E5: 12213704 | F5: 11445302 | G5: 15880914 | H5: 18268283 | I5: 14734577 | J5: 19860964 | K5: 6056000 | L5: 7400000 | M5: 8562000 | N5: 21552000 | O5: 27924000
A6: =VLOOKUP(B6,'[1]PORTFOLIO RAW'!B:B,1,FALSE) -> 545101 | B6: 545101 | C6: AES CORP - TOTAL DEBT | D6: 545101(WC03255) | E6: 17994000 | F6: 18091000 | G6: 19916000 | H6: 19733000 | I6: 22573000 | J6: 21373000 | K6: 21049000 | L6: 20858000 | M6: 20807000 | N6: 20463000 | O6: 19965000
A7: =VLOOKUP(B7,'[1]PORTFOLIO RAW'!B:B,1,FALSE) -> 906187 | B7: 906187 | C7: INT'L BUSINESS MACHS - TOTAL DEBT | D7: 906187(WC03255) | E7: 35274000 | F7: 33925000 | G7: 26100000 | H7: 28624000 | I7: 31320000 | J7: 33269000 | K7: 39718000 | L7: 40804000 | M7: 39889000 | N7: 42168000 | O7: 46824000
A8: =VLOOKUP(B8,'[1]PORTFOLIO RAW'!B:B,1,FALSE) -> 936365 | B8: 936365 | C8: ADVANCED MICRO - TOTAL DEBT | D8: 936365(WC03255) | E8: 5269000 | F8: 5074000 | G8: 4731000 | H8: 2421000 | I8: 2016000 | J8: 2042000 | K8: 2058000 | L8: 2212000 | M8: 2262000 | N8: 1435000 | O8: 1395000
A9: =VLOOKUP(B9,'[1]PORTFOLIO RAW'!B:B,1,FALSE) -> 749382 | B9: 749382 | C9: ADOBE INC - TOTAL DEBT | D9: 749382(WC03255) | E9: 0 | F9: 350000 | G9: 1000000 | H9: 1522461 | I9: 1514308 | J9: 1508155 | K9: 1513973 | L9: 1514315 | M9: 1907231 | N9: 1902068 | O9: 1881421
A10: =VLOOKUP(B10,'[1]PORTFOLIO RAW'!B:B,1,FALSE) -> 905271 | B10: 905271 | C10: AIR PRODUCTS & CHEMS - TOTAL DEBT | D10: 905271(WC03255) | E10: 3677200 | F10: 3966800 | G10: 4501500 | H10: 4159700 | I10: 4562200 | J10: 5291900 | K10: 6273600 | L10: 6118500 | M10: 5879000 | N10: 6225200 | O10: 3962800
A11: =VLOOKUP(B11,'[1]PORTFOLIO RAW'!B:B,1,FALSE) -> 894371 | B11: 894371 | C11: BOSTON PROPERTIES - TOTAL DEBT | D11: 894371(WC03255) | E11: 5492166 | F11: 6271916 | G11: 6719771 | H11: 7786001 | I11: 8704138 | J11: 8912369 | K11: 11521509 | L11: 10086984 | M11: 9216513 | N11: 9796133 | O11: 10271611
A12: =VLOOKUP(B12,'[1]PORTFOLIO RAW'!B:B,1,FALSE) -> 322677 | B12: 322677 | C12: ALLSTATE CORP - TOTAL DEBT | D12: 322677(WC03255) | E12: 5640000 | F12: 5659000 | G12: 5910000 | H12: 5908000 | I12: 5908000 | J12: 6057000 | K12: 6245000 | L12: 5205000 | M12: 5129000 | N12: 6347000 | O12: 6350000
A13: =VLOOKUP(B13,'[1]PORTFOLIO RAW'!B:B,1,FALSE) -> 906191 | B13: 906191 | C13: HONEYWELL INTERNATNL - TOTAL DEBT | D13: 906191(WC03255) | E13: 7657000 | F13: 8375000 | G13: 7607000 | H13: 6644000 | I13: 7555000 | J13: 7496000 | K13: 8829000 | L13: 8683000 | M13: 12068000 | N13: 15775000 | O13: 17882000
A14: =VLOOKUP(B14,'[1]PORTFOLIO RAW'!B:B,1,FALSE) -> 938692 | B14: 938692 | C14: AMGEN INC - TOTAL DEBT | D14: 938692(WC03255) | E14: 11177000 | F14: 10176000 | G14: 10601000 | H14: 13362000 | I14: 21428000 | J14: 26529000 | K14: 32128000 | L14: 30715000 | M14: 31556000 | N14: 34596000 | O14: 35342000
A15: =VLOOKUP(B15,'[1]PORTFOLIO RAW'!B:B,1,FALSE) -> 905802 | B15: 905802 | C15: HESS CORPORATION - TOTAL DEBT | D15: 905802(WC03255) | E15: 3980000 | F15: 3955000 | G15: 4467000 | H15: 5583000 | I15: 6057000 | J15: 8111000 | K15: 5798000 | L15: 5987000 | M15: 6630000 | N15: 6806000 | O15: 6977000
... A110: =VLOOKUP(B110,'[1]PORTFOLIO RAW'!B:B,1,FALSE) -> 905016 | B110: 905016 | C110: NEXTERA ENERGY - TOTAL DEBT | D110: 905016(WC03255) | E110: 13698000 | F110: 17086000 | G110: 18889000 | H110: 20822000 | I110: 22967000 | J110: 27359000 | K110: 28426000 | L110: 29024000 | M110: 29687000 | N110: 30840000 | O110: 35081000
A111: =VLOOKUP(B111,'[1]PORTFOLIO RAW'!B:B,1,FALSE) -> 28341F | B111: 28341F | C111: ASSURANT INC - TOTAL DEBT | D111: 28341F(WC03255) | E111: 993023 | F111: 983117 | G111: 980218 | H111: 977164 | I111: 972278 | J111: 972399 | K111: 1638118 | L111: 1171079 | M111: 1171382 | N111: 1067020 | O111: 1068200
A112: =VLOOKUP(B112,'[1]PORTFOLIO RAW'!B:B,1,FALSE) -> 755980 | B112: 755980 | C112: FASTENAL COMPANY - TOTAL DEBT | D112: 755980(WC03255) | E112: 0 | F112: 0 | G112: 0 | H112: 0 | I112: 0 | J112: 0 | K112: 0 | L112: 90000 | M112: 365000 | N112: 390000 | O112: 415000
A113: =VLOOKUP(B113,'[1]PORTFOLIO RAW'!B:B,1,FALSE) -> 905994 | B113: 905994 | C113: FEDERAL REALTY INVST - TOTAL DEBT | D113: 905994(WC03255) | E113: 1638460 | F113: 1745785 | G113: 1793848 | H113: 1767149 | I113: 2110410 | J113: 2208602 | K113: 2321862 | L113: 2409677 | M113: 2642366 | N113: 2798452 | O113: 3284766
A114: =VLOOKUP(B114,'[1]PORTFOLIO RAW'!B:B,1,FALSE) -> 997198 | B114: 997198 | C114: FIFTH THIRD BANCORP - TOTAL DEBT | D114: 997198(WC03255) | E114: 22031000 | F114: 23831000 | G114: 12104000 | H114: 11411000 | I114: 13267000 | J114: 14266000 | K114: 11297000 | L114: 16667000 | M114: 16920000 | N114: 17681000 | O114: 18749000
A115: =VLOOKUP(B115,'[1]PORTFOLIO RAW'!B:B,1,FALSE) -> 951503 | B115: 951503 | C115: M&T BANK CORPORATION - TOTAL DEBT | D115: 951503(WC03255) | E115: 16139842 | F115: 15084884 | G115: 12682598 | H115: 8787583 | I115: 7468308 | J115: 5682240 | K115: 5369325 | L115: 9199635 | M115: 12786040 | N115: 9657277 | O115: 8316529
A116: =VLOOKUP(B116,'[1]PORTFOLIO RAW'!B:B,1,FALSE) -> 741123 | B116: 741123 | C116: FISERV INC - TOTAL DEBT | D116: 741123(WC03255) | E116: 5405000 | F116: 4105000 | G116: 3641000 | H116: 3356000 | I116: 3395000 | J116: 3230000 | K116: 3848000 | L116: 3803000 | M116: 4293000 | N116: 4562000 | O116: 4900000
A117: =VLOOKUP(B117,'[1]PORTFOLIO RAW'!B:B,1,FALSE) -> 546814 | B117: 546814 | C117: MACY'S INC - TOTAL DEBT | D117: 546814(WC03255) | E117: 9753000 | F117: 9699000 | G117: 8698000 | H117: 7425000 | I117: 7758000 | J117: 6930000 | K117: 7672000 | L117: 7341000 | M117: 7637000 | N117: 6871000 | O117: 5883000
A118: =VLOOKUP(B118,'[1]PORTFOLIO RAW'!B:B,1,FALSE) -> 938076 | B118: 938076 | C118: FRANKLIN RESOURCES - TOTAL DEBT | D118: 938076(WC03255) | E118: 822898 | F118: 269271 | G118: 121156 | H118: 979900 | I118: 2168437 | J118: 2777200 | K118: 2295100 | L118: 2149000 | M118: 2155300 | N118: 2083400 | O118: 1097600
A119: =VLOOKUP(B119,'[1]PORTFOLIO RAW'!B:B,1,FALSE) -> 152594 | B119: 152594 | C119: FREEPORT-MCMORAN INC - TOTAL DEBT | D119: 152594(WC03255) | E119: 7211000 | F119: 7351000 | G119: 6346000 | H119: 4755000 | I119: 3537000 | J119: 3527000 | K119: 20706000 | L119: 18970000 | M119: 20428000 | N119: 16027000 | O119: 13117000
A120: =VLOOKUP(B120,'[1]PORTFOLIO RAW'!B:B,1,FALSE) -> 951018 | B120: 951018 | C120: GAP INC - TOTAL DEBT | D120: 951018(WC03255) | E120: 188000 | F120: 50000 | G120: 0 | H120: 0 | I120: 1665000 | J120: 1246000 | K120: 1394000 | L120: 1353000 | M120: 1731000 | N120: 1313000 | O120: 1249000
A121: =VLOOKUP(B121,'[1]PORTFOLIO RAW'!B:B,1,FALSE) -> 907652 | B121: 907652 | C121: GENERAL DYNAMICS - TOTAL DEBT | D121: 907652(WC03255) | E121: 2791000 | F121: 4024000 | G121: 3864000 | H121: 3203000 | I121: 3930000 | J121: 3909000 | K121: 3943000 | L121: 3942000 | M121: 3431000 | N121: 3918000 | O121: 4009000
A122: =VLOOKUP(B122,'[1]PORTFOLIO RAW'!B:B,1,FALSE) -> 905801 | B122: 905801 | C122: GENERAL MILLS, INC. - TOTAL DEBT | D122: 905801(WC03255) | E122: 6206000 | F122: 6999500 | G122: 7075500 | H122: 6425900 | I122: 6885100 | J122: 7429600 | K122: 7969100 | L122: 8785800 | M122: 9223900 | N122: 8430900 | O122: 9481700
A123: =VLOOKUP(B123,'[1]PORTFOLIO RAW'!B:B,1,FALSE) -> 906511 | B123: 906511 | C123: GENUINE PARTS CO - TOTAL DEBT | D123: 906511(WC03255) | E123: 513707 | F123: 512708 | G123: 513504 | H123: 512622 | I123: 500000 | J123: 500000 | K123: 792473 | L123: 805506 | M123: 662642 | N123: 914221 | O123: 3300702
... A237: =VLOOKUP(B237,'[1]PORTFOLIO RAW'!B:B,1,FALSE) -> 933974 | B237: 933974 | C237: TRAVELERS COS - TOTAL DEBT | D237: 933974(WC03255) | E237: 6242000 | F237: 6181000 | G237: 6527000 | H237: 6611000 | I237: 6605000 | J237: 6350000 | K237: 6346000 | L237: 6349000 | M237: 6344000 | N237: 6437000 | O237: 6571000
A238: =VLOOKUP(B238,'[1]PORTFOLIO RAW'!B:B,1,FALSE) -> 14015T | B238: 14015T | C238: FIDELITY NATNL INF - TOTAL DEBT | D238: 14015T(WC03255) | E238: 4275397 | F238: 2514500 | G238: 3253300 | H238: 5240000 | I238: 4809800 | J238: 4385500 | K238: 4468600 | L238: 5067700 | M238: 11513100 | N238: 10478000 | O238: 8763000
A239: =VLOOKUP(B239,'[1]PORTFOLIO RAW'!B:B,1,FALSE) -> 905019 | B239: 905019 | C239: MERCK & CO INC - TOTAL DEBT | D239: 905019(WC03255) | E239: 5739400 | F239: 6240400 | G239: 17660700 | H239: 17882000 | I239: 17515000 | J239: 20569000 | K239: 25060000 | L239: 21403000 | M239: 26514000 | N239: 24842000 | O239: 24410000
A240: =VLOOKUP(B240,'[1]PORTFOLIO RAW'!B:B,1,FALSE) -> 912090 | B240: 912090 | C240: SCHLUMBERGER LIMITED - TOTAL DEBT | D240: 912090(WC03255) | E240: 5466101 | F240: 5290888 | G240: 5480000 | H240: 8099000 | I240: 9925000 | J240: 11630000 | K240: 13176000 | L240: 13330000 | M240: 18999000 | N240: 19616000 | O240: 18199000
A241: =VLOOKUP(B241,'[1]PORTFOLIO RAW'!B:B,1,FALSE) -> 755741 | B241: 755741 | C241: CHARLES SCHWAB CORP - TOTAL DEBT | D241: 755741(WC03255) | E241: 899000 | F241: 883000 | G241: 1512000 | H241: 2006000 | I241: 2001000 | J241: 1632000 | K241: 1903000 | L241: 1899000 | M241: 2890000 | N241: 2876000 | O241: 19753000
A242: =VLOOKUP(B242,'[1]PORTFOLIO RAW'!B:B,1,FALSE) -> 14361V | B242: 14361V | C242: ZIMMER BIOMET - TOTAL DEBT | D242: 14361V(WC03255) | E242: 104300 | F242: 460100 | G242: 1127600 | H242: 1142100 | I242: 1719300 | J242: 1820900 | K242: 1672800 | L242: 1425500 | M242: 11556300 | N242: 11241400 | O242: 10142500
A243: =VLOOKUP(B243,'[1]PORTFOLIO RAW'!B:B,1,FALSE) -> 154680 | B243: 154680 | C243: AMERISOURCEBERGEN - TOTAL DEBT | D243: 154680(WC03255) | E243: 1227774 | F243: 1189131 | G243: 1178001 | H243: 1343580 | I243: 1364952 | J243: 1446770 | K243: 1462981 | L243: 2056532 | M243: 3597774 | N243: 4481393 | O243: 3822396
A244: =VLOOKUP(B244,'[1]PORTFOLIO RAW'!B:B,1,FALSE) -> 14698C | B244: 14698C | C244: PRINCIPAL FINL GROUP - TOTAL DEBT | D244: 14698C(WC03255) | E244: 1689600 | F244: 1791400 | G244: 1686200 | H244: 1691600 | I244: 1670000 | J244: 2712100 | K244: 2752300 | L244: 2559200 | M244: 3514700 | N244: 3177100 | O244: 3217900
A245: =VLOOKUP(B245,'[1]PORTFOLIO RAW'!B:B,1,FALSE) -> 905361 | B245: 905361 | C245: SHERWIN-WILLIAMS CO - TOTAL DEBT | D245: 905361(WC03255) | E245: 965448 | F245: 833735 | G245: 817611 | H245: 1044793 | I245: 993367 | J245: 1704889 | K245: 1721872 | L245: 1805416 | M245: 1962812 | N245: 1952540 | O245: 10520655
A246: =VLOOKUP(B246,'[1]PORTFOLIO RAW'!B:B,1,FALSE) -> 357834 | B246: 357834 | C246: SIMON PROPERTY GROUP - TOTAL DEBT | D246: 357834(WC03255) | E246: 17218674 | F246: 18042532 | G246: 18630302 | H246: 17473760 | I246: 18446440 | J246: 23113007 | K246: 23588531 | L246: 20852993 | M246: 22502173 | N246: 22977104 | O246: 24632463
A247: =VLOOKUP(B247,'[1]PORTFOLIO RAW'!B:B,1,FALSE) -> 906400 | B247: 906400 | C247: SNAP-ON INC - TOTAL DEBT | D247: 906400(WC03255) | E247: 517900 | F247: 539200 | G247: 1091500 | H247: 1193800 | I247: 1006600 | J247: 1015200 | K247: 972000 | L247: 919300 | M247: 880100 | N247: 1010200 | O247: 1186800
A248: =VLOOKUP(B248,'[1]PORTFOLIO RAW'!B:B,1,FALSE) -> 14861V | B248: 14861V | C248: PRUDENTIAL FINANCIAL - TOTAL DEBT | D248: 14861V(WC03255) | E248: 47511000 | F248: 42913000 | G248: 33355000 | H248: 33691000 | I248: 36149000 | J248: 33031000 | K248: 37422000 | L248: 39135000 | M248: 37422000 | N248: 28930000 | O248: 28470000
A249: =VLOOKUP(B249,'[1]PORTFOLIO RAW'!B:B,1,FALSE) -> 14806F | B249: 14806F | C249: ADVANCE AUTO PARTS - TOTAL DEBT | D249: 14806F(WC03255) | E249: 535672 | F249: 476752 | G249: 213799 | H249: 311380 | I249: 432165 | J249: 613810 | K249: 1053584 | L249: 1636893 | M249: 1213759 | N249: 1043255 | O249: 1044677
A250: =VLOOKUP(B250,'[1]PORTFOLIO RAW'!B:B,1,FALSE) -> 902324 | B250: 902324 | C250: EDISON INTERNATIONAL - TOTAL DEBT | D250: 902324(WC03255) | E250: 9746000 | F250: 13491000 | G250: 11123000 | H250: 12534000 | I250: 14397000 | J250: 9622000 | K250: 10635000 | L250: 12029000 | M250: 11954000 | N250: 12463000 | O250: 14516000
A251: =VLOOKUP(B251,'[1]PORTFOLIO RAW'!B:B,1,FALSE) -> 902325 | B251: 902325 | C251: SOUTHERN CO - TOTAL DEBT | D251: 902325(WC03255) | E251: 16593000 | F251: 18386000 | G251: 19883000 | H251: 20752000 | I251: 21223000 | J251: 22584000 | K251: 23295000 | L251: 24977000 | M251: 28738000 | N251: 47324000 | O251: 50793000
A252: =VLOOKUP(B252,'[1]PORTFOLIO RAW'!B:B,1,FALSE) -> 992305 | B252: 992305 | C252: BB&T CORPORATION - TOTAL DEBT | D252: 992305(WC03255) | E252: 29327000 | F252: 28820000 | G252: 29482000 | H252: 27403000 | I252: 25369000 | J252: 21978000 | K252: 27774000 | L252: 28144000 | M252: 32686000 | N252: 23371000 | O252: 28586000
A253: =VLOOKUP(B253,'[1]PORTFOLIO RAW'!B:B,1,FALSE) -> 905647 | B253: 905647 | C253: SOUTHWEST AIRLINES - TOTAL DEBT | D253: 905647(WC03255) | E253: 2091000 | F253: 3661000 | G253: 3515000 | H253: 3380000 | I253: 3751000 | J253: 3154000 | K253: 3110000 | L253: 2885000 | M253: 3343000 | N253: 3512000 | O253: 3753000
A254: =VLOOKUP(B254,'[1]PORTFOLIO RAW'!B:B,1,FALSE) -> 945388 | B254: 945388 | C254: AT&T INC - TOTAL DEBT | D254: 945388(WC03255) | E254: 64115000 | F254: 74991000 | G254: 72081000 | H254: 66167000 | I254: 64753000 | J254: 69844000 | K254: 74788000 | L254: 82067000 | M254: 126151000 | N254: 123513000 | O254: 164346000
A255: =VLOOKUP(B255,'[1]PORTFOLIO RAW'!B:B,1,FALSE) -> 905024 | B255: 905024 | C255: CHEVRON CORPORATION - TOTAL DEBT | D255: 905024(WC03255) | E255: 7232000 | F255: 8901000 | G255: 10514000 | H255: 11476000 | I255: 10152000 | J255: 12192000 | K255: 20431000 | L255: 27818000 | M255: 38592000 | N255: 46126000 | O255: 38763000
A256: =VLOOKUP(B256,'[1]PORTFOLIO RAW'!B:B,1,FALSE) -> 951052 | B256: 951052 | C256: STATE STREET CORP - TOTAL DEBT | D256: 951052(WC03255) | E256: 24264000 | F256: 34252000 | G256: 44112000 | H256: 32591000 | I256: 22125000 | J256: 20336000 | K256: 21451000 | L256: 23369000 | M256: 17787000 | N256: 17415000 | O256: 15606000
A257: =VLOOKUP(B257,'[1]PORTFOLIO RAW'!B:B,1,FALSE) -> 326143 | B257: 326143 | C257: STARBUCKS CORP - TOTAL DEBT | D257: 326143(WC03255) | E257: 1264244 | F257: 1270000 | G257: 557300 | H257: 552000 | I257: 550900 | J257: 549600 | K257: 1348200 | L257: 2048300 | M257: 2347500 | N257: 3602200 | O257: 3991700
A258: =VLOOKUP(B258,'[1]PORTFOLIO RAW'!B:B,1,FALSE) -> 905792 | B258: 905792 | C258: PUBLIC STORAGE, INC - TOTAL DEBT | D258: 905792(WC03255) | E258: 1069928 | F258: 643811 | G258: 518889 | H258: 568417 | I258: 398314 | J258: 468828 | K258: 839053 | L258: 64364 | M258: 319016 | N258: 390749 | O258: 1431322
A259: =VLOOKUP(B259,'[1]PORTFOLIO RAW'!B:B,1,FALSE) -> 981722 | B259: 981722 | C259: STRYKER CORPORATION - TOTAL DEBT | D259: 981722(WC03255) | E259: 16800 | F259: 20500 | G259: 18000 | H259: 1021800 | I259: 1768000 | J259: 1762000 | K259: 2764000 | L259: 3973000 | M259: 4022000 | N259: 6914000 | O259: 7222000
A260: =VLOOKUP(B260,'[1]PORTFOLIO RAW'!B:B,1,FALSE) -> 922725 | B260: 922725 | C260: SUNTRUST BANKS INC - TOTAL DEBT | D260: 922725(WC03255) | E260: 35157328 | F260: 36292131 | G260: 22854884 | H260: 19469000 | I260: 22374000 | J260: 14851000 | K260: 19439000 | L260: 22208000 | M260: 13089000 | N260: 18299000 | O260: 15801000
A261: =VLOOKUP(B261,'[1]PORTFOLIO RAW'!B:B,1,FALSE) -> 541900 | B261: 541900 | C261: SYMANTEC CORP - TOTAL DEBT | D261: 541900(WC03255) | E261: 2100000 | F261: 2300000 | G261: 2100000 | H261: 1871000 | I261: 2583000 | J261: 2039000 | K261: 3091000 | L261: 2095000 | M261: 2096000 | N261: 2207000 | O261: 8186000
... A284: =VLOOKUP(B284,'[1]PORTFOLIO RAW'!B:B,1,FALSE) -> 904869 | B284: 904869 | C284: WHIRLPOOL CORP - TOTAL DEBT | D284: 904869(WC03255) | E284: 2093000 | F284: 2597000 | G284: 2903000 | H284: 2509000 | I284: 2491000 | J284: 2461000 | K284: 2463000 | L284: 4347000 | M284: 3998000 | N284: 4470000 | O284: 5218000
A285: =VLOOKUP(B285,'[1]PORTFOLIO RAW'!B:B,1,FALSE) -> 26406N | B285: 26406N | C285: WYNN RESORTS, LTD - TOTAL DEBT | D285: 26406N(WC03255) | E285: 3548379 | F285: 4299177 | G285: 3569103 | H285: 3267529 | I285: 3334998 | J285: 5782820 | K285: 6587568 | L285: 7345262 | M285: 9212765 | N285: 10125352 | O285: 9645226
A286: =VLOOKUP(B286,'[1]PORTFOLIO RAW'!B:B,1,FALSE) -> 26393N | B286: 26393N | C286: CME GROUP INC - TOTAL DEBT | D286: 26393N(WC03255) | E286: 3026461 | F286: 3672762 | G286: 2314500 | H286: 2525300 | I286: 2106800 | J286: 2856500 | K286: 2857100 | L286: 2107900 | M286: 2241400 | N286: 2231200 | O286: 2233100
A287: =VLOOKUP(B287,'[1]PORTFOLIO RAW'!B:B,1,FALSE) -> 922407 | B287: 922407 | C287: WILLIAMS COMPANIES - TOTAL DEBT | D287: 922407(WC03255) | E287: 7900000 | F287: 7879000 | G287: 8276000 | H287: 9108000 | I287: 8722000 | J287: 10736000 | K287: 11579000 | L287: 21690000 | M287: 24487000 | N287: 23502000 | O287: 20935000
A288: =VLOOKUP(B288,'[1]PORTFOLIO RAW'!B:B,1,FALSE) -> 906979 | B288: 906979 | C288: ALLIANT ENERGY CORP - TOTAL DEBT | D288: 906979(WC03255) | E288: 1655900 | F288: 1970800 | G288: 2696000 | H288: 2752100 | I288: 2807300 | J288: 3355600 | K288: 3617700 | L288: 3933000 | M288: 3997400 | N288: 4570300 | O288: 5286500
A289: =VLOOKUP(B289,'[1]PORTFOLIO RAW'!B:B,1,FALSE) -> 877723 | B289: 877723 | C289: CARMAX INC - TOTAL DEBT | D289: 877723(WC03255) | E289: 185477 | F289: 327831 | G289: 337047 | H289: 150571 | I289: 4043785 | J289: 5052706 | K289: 6209036 | L289: 7583410 | M289: 9109252 | N289: 10657832 | O289: 12169704
