Workbook

Sheet PORTFOLIO RAW
A2: NAME | B2: Code
A3: MMM | B3: 902172
A4: ABT | B4: 916328
A5: ACN | B5: 14352P
A6: ATVI.O | B6: 312367
A7: ADBE.O | B7: 749382
A8: AAP | B8: 14806F
A9: AMD.O | B9: 936365
A10: AES | B10: 545101
A11: AFL | B11: 933185
A12: A | B12: 277642
A13: APD | B13: 905271
A14: AKAM.O | B14: 277355
A15: ALB | B15: 130298
A16: AGN | B16: 325596
A17: LNT.O | B17: 906979
A18: ALL | B18: 322677
A19: GOOG.O | B19: 29026M
A20: MO | B20: 904853
A21: AMZN.O | B21: 891399
A22: AEE | B22: 670942
A23: AEP | B23: 905425
A24: AXP | B24: 906156
A25: AIG | B25: 916305
A26: AMT | B26: 680902
A27: AMP | B27: 31604H
A28: ABC | B28: 154680
A29: AMGN.O | B29: 938692
A30: APH | B30: 546075
A31: ADI.O | B31: 905276
A32: ANTM.K | B32: 14737P
A33: AON | B33: 922817
A34: APA | B34: 921983
A35: AIV | B35: 132808
A36: AAPL.O | B36: 992816
A37: AMAT.O | B37: 905296
A38: ADM | B38: 921093
A39: ARNC.K | B39: 905113
A40: AIZ | B40: 28341F
A41: T | B41: 945388
A42: ADSK.O | B42: 702259
A43: ADP.O | B43: 912669
A44: AZO | B44: 544616
A45: AVB | B45: 130502
A46: AVY | B46: 921161
A47: BHGE.K | B47: 921431
A48: BLL | B48: 932060
A49: BAC | B49: 923937
A50: BK | B50: 905840
A51: BAX | B51: 916365
A52: BBT | B52: 992305
... A69: CAT | B69: 902224
A70: CBRE.K | B70: 28513N
A71: CBS | B71: 32480Q
A72: CE | B72: 29756N
A73: CELG.O | B73: 755790
A74: CNP | B74: 904842
A75: SCHW.K | B75: 755741
A76: CVX | B76: 905024
A77: CB | B77: 328314
A78: CI | B78: 912278
A79: XEC | B79: 26276P
A80: CINF.O | B80: 951545
A81: CTAS.O | B81: 944777
A82: CSCO.O | B82: 542868
A83: C | B83: 741344
A84: CTXS.O | B84: 867705
A85: CLX | B85: 916125
A86: CME.O | B86: 26393N
A87: CMS | B87: 901686
A88: KO | B88: 904282
A89: CL | B89: 906148
A90: CMCSA.O | B90: 981550
A91: CMA | B91: 922964
A92: CAG | B92: 929814
A93: COP | B93: 901666
A94: ED | B94: 902288
A95: STZ | B95: 937083
A96: COO | B96: 938928
A97: GLW | B97: 912273
A98: COST.O | B98: 312385
... A109: DVN | B109: 271980
A110: DISCK.O | B110: 31196R
A111: DISH.O | B111: 135448
A112: DLTR.O | B112: 154259
A113: D | B113: 944314
A114: DOV | B114: 904830
A115: DTE | B115: 905214
A116: DUK | B116: 904383
A117: DRE | B117: 513260
A118: DXC | B118: 916091
A119: ETFC.O | B119: 883488
A120: EMN | B120: 357922
A121: ETN | B121: 903749
A122: EBAY.O | B122: 687609
... A134: EXC | B134: 902317
A135: EXPE.O | B135: 31412T
A136: EXPD.O | B136: 910722
A137: XOM | B137: 905039
A138: FAST.O | B138: 755980
...

Sheet MB
A1: Market to Book Ratio
A2: Code | B2: Code | C2: Name | D2: Code | E2: 2007 | F2: 2008 | G2: 2009 | H2: 2010 | I2: 2011 | J2: 2012 | K2: 2013 | L2: 2014 | M2: 2015 | N2: 2016 | O2: 2017
A3: =VLOOKUP(B3,'[1]PORTFOLIO RAW'!B:B,1,FALSE) -> 891399 | B3: 891399 | C3: AMAZON.COM - MRKT VALUE TO BOOK | D3: 891399(MTBV) | E3: 30.96 | F3: 12.91 | G3: 7.42 | H3: 9.87 | I3: 13.65 | J3: 14.39 | K3: 14.83 | L3: 14.25 | M3: 18.88 | N3: 19.18 | O3: 16.87
A4: =VLOOKUP(B4,'[1]PORTFOLIO RAW'!B:B,1,FALSE) -> 916328 | B4: 916328 | C4: ABBOTT LABORATORIES - MRKT VALUE TO BOOK | D4: 916328(MTBV) | E4: 4.67 | F4: 5.18 | G4: 3.11 | H4: 3.6 | I4: 3.36 | J4: 4.1 | K4: 2.18 | L4: 3.04 | M4: 3.04 | N4: 2.98 | O4: 2.92
A5: =VLOOKUP(B5,'[1]PORTFOLIO RAW'!B:B,1,FALSE) -> 545101 | B5: 545101 | C5: AES - MRKT VALUE TO BOOK | D5: 545101(MTBV) | E5: 4.08 | F5: 2.42 | G5: 2.05 | H5: 1.4 | I5: 1.41 | J5: 1.83 | K5: 2.29 | L5: 2.49 | M5: 2.37 | N5: 3.01 | O5: 3.02
A6: =VLOOKUP(B6,'[1]PORTFOLIO RAW'!B:B,1,FALSE) -> 906187 | B6: 906187 | C6: INTERNATIONAL BUS.MCHS. - MRKT VALUE TO BOOK | D6: 906187(MTBV) | E6: 5.58 | F6: 11.96 | G6: 7.07 | H6: 7.21 | I6: 10.36 | J6: 12.49 | K6: 9.13 | L6: 16.31 | M6: 9.93 | N6: 8.09 | O6: 7.73
A7: =VLOOKUP(B7,'[1]PORTFOLIO RAW'!B:B,1,FALSE) -> 936365 | B7: 936365 | C7: ADVANCED MICRO DEVICES - MRKT VALUE TO BOOK | D7: 936365(MTBV) | E7: 2.47 | F7: -40.13 | G7: 5.87 | H7: 4.06 | I7: 2.93 | J7: 4.72 | K7: 5.07 | L7: 15.65 | M7: -3.54 | N7: 13.27 | O7: 21.29
A8: =VLOOKUP(B8,'[1]PORTFOLIO RAW'!B:B,1,FALSE) -> 749382 | B8: 749382 | C8: ADOBE (NAS) - MRKT VALUE TO BOOK | D8: 749382(MTBV) | E8: 5.42 | F8: 4.92 | G8: 3.54 | H8: 3.35 | I8: 2.1 | J8: 2.55 | K8: 3.91 | L8: 4.93 | M8: 5.79 | N8: 6.75 | O8: 8.75
A9: =VLOOKUP(B9,'[1]PORTFOLIO RAW'!B:B,1,FALSE) -> 905271 | B9: 905271 | C9: AIR PRDS.& CHEMS. - MRKT VALUE TO BOOK | D9: 905271(MTBV) | E9: 3.65 | F9: 3.51 | G9: 3.52 | H9: 3.18 | I9: 3.02 | J9: 2.78 | K9: 3.23 | L9: 3.89 | M9: 3.99 | N9: 4.5 | O9: 3.26
A10: =VLOOKUP(B10,'[1]PORTFOLIO RAW'!B:B,1,FALSE) -> 894371 | B10: 894371 | C10: BOSTON PROPERTIES - MRKT VALUE TO BOOK | D10: 894371(MTBV) | E10: 3.36 | F10: 3.23 | G10: 2.2 | H10: 2.83 | I10: 3.01 | J10: 3.33 | K10: 3.01 | L10: 3.15 | M10: 3.19 | N10: 3.72 | O10: 3.32
A11: =VLOOKUP(B11,'[1]PORTFOLIO RAW'!B:B,1,FALSE) -> 322677 | B11: 322677 | C11: ALLSTATE ORD SHS - MRKT VALUE TO BOOK | D11: 322677(MTBV) | E11: 1.56 | F11: 1.57 | G11: 0.94 | H11: 0.94 | I11: 0.73 | J11: 1.09 | K11: 1.26 | L11: 1.45 | M11: 1.31 | N11: 1.42 | O11: 1.73
A12: =VLOOKUP(B12,'[1]PORTFOLIO RAW'!B:B,1,FALSE) -> 906191 | B12: 906191 | C12: HONEYWELL INTL. - MRKT VALUE TO BOOK | D12: 906191(MTBV) | E12: 4.72 | F12: 4.69 | G12: 3.42 | H12: 3.21 | I12: 3.39 | J12: 3.64 | K12: 3.84 | L12: 4.28 | M12: 4.19 | N12: 4.51 | O12: 6.11
A13: =VLOOKUP(B13,'[1]PORTFOLIO RAW'!B:B,1,FALSE) -> 938692 | B13: 938692 | C13: AMGEN - MRKT VALUE TO BOOK | D13: 938692(MTBV) | E13: 3.36 | F13: 3.11 | G13: 2.72 | H13: 2.24 | I13: 2.79 | J13: 3.33 | K13: 3.98 | L13: 4.24 | M13: 4.07 | N13: 4.34 | O13: 5.44
A14: =VLOOKUP(B14,'[1]PORTFOLIO RAW'!B:B,1,FALSE) -> 905802 | B14: 905802 | C14: HESS - MRKT VALUE TO BOOK | D14: 905802(MTBV) | E14: 2.16 | F14: 2.51 | G14: 1.36 | H14: 1.12 | I14: 1.1 | J14: 0.9 | K14: 1.09 | L14: 1.35 | M14: 0.78 | N14: 1 | O14: 1.25
... A108: =VLOOKUP(B108,'[1]PORTFOLIO RAW'!B:B,1,FALSE) -> 905016 | B108: 905016 | C108: NEXTERA ENERGY - MRKT VALUE TO BOOK | D108: 905016(MTBV) | E108: 2.37 | F108: 1.96 | G108: 1.75 | H108: 1.57 | I108: 1.57 | J108: 1.77 | K108: 1.9 | L108: 2.08 | M108: 1.98 | N108: 2.37 | O108: 2.44
A109: =VLOOKUP(B109,'[1]PORTFOLIO RAW'!B:B,1,FALSE) -> 28341F | B109: 28341F | C109: ASSURANT - MRKT VALUE TO BOOK | D109: 28341F(MTBV) | E109: 1.51 | F109: 1.54 | G109: 0.81 | H109: 0.99 | I109: 0.77 | J109: 0.59 | K109: 0.94 | L109: 1.09 | M109: 1.26 | N109: 1.49 | O109: 1.37
A110: =VLOOKUP(B110,'[1]PORTFOLIO RAW'!B:B,1,FALSE) -> 755980 | B110: 755980 | C110: FASTENAL - MRKT VALUE TO BOOK | D110: 755980(MTBV) | E110: 6.65 | F110: 6.97 | G110: 4.86 | H110: 6 | I110: 7.41 | J110: 8.33 | K110: 8.4 | L110: 7.16 | M110: 5.99 | N110: 5.97 | O110: 6.12
A111: =VLOOKUP(B111,'[1]PORTFOLIO RAW'!B:B,1,FALSE) -> 905994 | B111: 905994 | C111: FEDERAL REALTY INV.TST. - MRKT VALUE TO BOOK | D111: 905994(MTBV) | E111: 4.41 | F111: 4.71 | G111: 3.32 | H111: 4.49 | I111: 4.42 | J111: 5.28 | K111: 4.69 | L111: 5.07 | M111: 5.63 | N111: 5.6 | O111: 4.27
A112: =VLOOKUP(B112,'[1]PORTFOLIO RAW'!B:B,1,FALSE) -> 997198 | B112: 997198 | C112: FIFTH THIRD BANCORP - MRKT VALUE TO BOOK | D112: 997198(MTBV) | E112: 2.07 | F112: 1.39 | G112: 0.84 | H112: 0.96 | I112: 0.75 | J112: 1.08 | K112: 1.23 | L112: 1.22 | M112: 1.05 | N112: 1.06 | O112: 1.34
A113: =VLOOKUP(B113,'[1]PORTFOLIO RAW'!B:B,1,FALSE) -> 951503 | B113: 951503 | C113: M&T BANK - MRKT VALUE TO BOOK | D113: 951503(MTBV) | E113: 1.79 | F113: 1.67 | G113: 1.12 | H113: 1.43 | I113: 1.07 | J113: 1.28 | K113: 1.39 | L113: 1.52 | M113: 1.06 | N113: 1.19 | O113: 1.56
A114: =VLOOKUP(B114,'[1]PORTFOLIO RAW'!B:B,1,FALSE) -> 741123 | B114: 741123 | C114: FISERV - MRKT VALUE TO BOOK | D114: 741123(MTBV) | E114: 3.3 | F114: 3.26 | G114: 2.52 | H114: 2.52 | I114: 2.33 | J114: 2.92 | K114: 3.7 | L114: 4.97 | M114: 7.63 | N114: 8.59 | O114: 9.64
A115: =VLOOKUP(B115,'[1]PORTFOLIO RAW'!B:B,1,FALSE) -> 546814 | B115: 546814 | C115: MACY'S - MRKT VALUE TO BOOK | D115: 546814(MTBV) | E115: 1.49 | F115: 1.81 | G115: 1.61 | H115: 1.69 | I115: 1.97 | J115: 2.57 | K115: 2.69 | L115: 3.95 | M115: 4.21 | N115: 2.49 | O115: 1.15
A116: =VLOOKUP(B116,'[1]PORTFOLIO RAW'!B:B,1,FALSE) -> 938076 | B116: 938076 | C116: FRANKLIN RESOURCES - MRKT VALUE TO BOOK | D116: 938076(MTBV) | E116: 4.34 | F116: 3.58 | G116: 3.12 | H116: 3.15 | I116: 2.98 | J116: 2.9 | K116: 3.27 | L116: 3.01 | M116: 2 | N116: 1.69 | O116: 1.9
A117: =VLOOKUP(B117,'[1]PORTFOLIO RAW'!B:B,1,FALSE) -> 152594 | B117: 152594 | C117: FREEPORT-MCMORAN - MRKT VALUE TO BOOK | D117: 152594(MTBV) | E117: 2.88 | F117: 13.66 | G117: 4.63 | H117: 3.14 | I117: 2.34 | J117: 2.21 | K117: 1.68 | L117: 1.94 | M117: 1.58 | N117: 2.18 | O117: 2.57
A118: =VLOOKUP(B118,'[1]PORTFOLIO RAW'!B:B,1,FALSE) -> 951018 | B118: 951018 | C118: GAP - MRKT VALUE TO BOOK | D118: 951018(MTBV) | E118: 3.4 | F118: 3.09 | G118: 3.14 | H118: 2.91 | I118: 3.1 | J118: 6.01 | K118: 6.34 | L118: 6.4 | M118: 5.05 | N118: 3.1 | O118: 3.49
A119: =VLOOKUP(B119,'[1]PORTFOLIO RAW'!B:B,1,FALSE) -> 907652 | B119: 907652 | C119: GENERAL DYNAMICS - MRKT VALUE TO BOOK | D119: 907652(MTBV) | E119: 2.87 | F119: 3.26 | G119: 2 | H119: 1.82 | I119: 1.63 | J119: 2.05 | K119: 2.13 | L119: 3.66 | M119: 4.18 | N119: 4.22 | O119: 5.35
A120: =VLOOKUP(B120,'[1]PORTFOLIO RAW'!B:B,1,FALSE) -> 905801 | B120: 905801 | C120: GENERAL MILLS - MRKT VALUE TO BOOK | D120: 905801(MTBV) | E120: 3.07 | F120: 4.52 | G120: 3.65 | H120: 3.64 | I120: 3.76 | J120: 3.91 | K120: 4.72 | L120: 6.2 | M120: 6.86 | N120: 8.84 | O120: 4.83
A121: =VLOOKUP(B121,'[1]PORTFOLIO RAW'!B:B,1,FALSE) -> 906511 | B121: 906511 | C121: GENUINE PARTS - MRKT VALUE TO BOOK | D121: 906511(MTBV) | E121: 3.18 | F121: 2.94 | G121: 2.29 | H121: 2.5 | I121: 2.94 | J121: 3.24 | K121: 3.76 | L121: 4.14 | M121: 4.01 | N121: 4.6 | O121: 3.73
... A234: =VLOOKUP(B234,'[1]PORTFOLIO RAW'!B:B,1,FALSE) -> 933974 | B234: 933974 | C234: TRAVELERS COS. - MRKT VALUE TO BOOK | D234: 933974(MTBV) | E234: 1.3 | F234: 1.18 | G234: 1.06 | H234: 1.07 | I234: 0.98 | J234: 1.18 | K234: 1.37 | L234: 1.4 | M234: 1.39 | N234: 1.47 | O234: 1.48
A235: =VLOOKUP(B235,'[1]PORTFOLIO RAW'!B:B,1,FALSE) -> 14015T | B235: 14015T | C235: FIDELITY NAT.INFO.SVS. - MRKT VALUE TO BOOK | D235: 14015T(MTBV) | E235: 2.35 | F235: 1.09 | G235: 0.58 | H235: 1.29 | I235: 1.22 | J235: 1.44 | K235: 2.08 | L235: 2.49 | M235: 2.06 | N235: 2.58 | O235: 2.85
A236: =VLOOKUP(B236,'[1]PORTFOLIO RAW'!B:B,1,FALSE) -> 905019 | B236: 905019 | C236: MERCK & COMPANY - MRKT VALUE TO BOOK | D236: 905019(MTBV) | E236: 6.13 | F236: 3.64 | G236: 1.14 | H236: 2.07 | I236: 1.84 | J236: 2.58 | K236: 2.82 | L236: 3.59 | M236: 3.29 | N236: 4.27 | O236: 5.23
A237: =VLOOKUP(B237,'[1]PORTFOLIO RAW'!B:B,1,FALSE) -> 912090 | B237: 912090 | C237: SCHLUMBERGER - MRKT VALUE TO BOOK | D237: 912090(MTBV) | E237: 8.6 | F237: 6.45 | G237: 3.87 | H237: 2.58 | I237: 2.99 | J237: 2.87 | K237: 2.93 | L237: 3.54 | M237: 2.58 | N237: 2.55 | O237: 2.54
A238: =VLOOKUP(B238,'[1]PORTFOLIO RAW'!B:B,1,FALSE) -> 755741 | B238: 755741 | C238: CHARLES SCHWAB - MRKT VALUE TO BOOK | D238: 755741(MTBV) | E238: 7.07 | F238: 7.16 | G238: 4.03 | H238: 2.68 | I238: 1.86 | J238: 1.97 | K238: 2.88 | L238: 3.63 | M238: 3.14 | N238: 2.99 | O238: 3.55
A239: =VLOOKUP(B239,'[1]PORTFOLIO RAW'!B:B,1,FALSE) -> 14361V | B239: 14361V | C239: ZIMMER BIOMET HDG. - MRKT VALUE TO BOOK | D239: 14361V(MTBV) | E239: 3.61 | F239: 2.71 | G239: 1.94 | H239: 1.8 | I239: 1.98 | J239: 1.99 | K239: 2.24 | L239: 2.69 | M239: 2.04 | N239: 2.58 | O239: 2
A240: =VLOOKUP(B240,'[1]PORTFOLIO RAW'!B:B,1,FALSE) -> 154680 | B240: 154680 | C240: AMERISOURCEBERGEN - MRKT VALUE TO BOOK | D240: 154680(MTBV) | E240: 2.65 | F240: 2.31 | G240: 2.38 | H240: 2.89 | I240: 3.73 | J240: 3.93 | K240: 6.14 | L240: 8.87 | M240: 36.21 | N240: 9.17 | O240: 8.44
A241: =VLOOKUP(B241,'[1]PORTFOLIO RAW'!B:B,1,FALSE) -> 14698C | B241: 14698C | C241: PRINCIPAL FINL.GP. - MRKT VALUE TO BOOK | D241: 14698C(MTBV) | E241: 2.32 | F241: 2.11 | G241: 1.09 | H241: 0.93 | I241: 0.88 | J241: 1.01 | K241: 1.35 | L241: 1.57 | M241: 1.52 | N241: 1.38 | O241: 1.61
A242: =VLOOKUP(B242,'[1]PORTFOLIO RAW'!B:B,1,FALSE) -> 905361 | B242: 905361 | C242: SHERWIN-WILLIAMS - MRKT VALUE TO BOOK | D242: 905361(MTBV) | E242: 4.93 | F242: 4.64 | G242: 4.84 | H242: 5.05 | I242: 5.2 | J242: 8.99 | K242: 10.66 | L242: 21.64 | M242: 26.49 | N242: 13.51 | O242: 8.78
A243: =VLOOKUP(B243,'[1]PORTFOLIO RAW'!B:B,1,FALSE) -> 357834 | B243: 357834 | C243: SIMON PROPERTY GROUP - MRKT VALUE TO BOOK | D243: 357834(MTBV) | E243: 7.85 | F243: 8.69 | G243: 4.71 | H243: 5.95 | I243: 7.63 | J243: 8.06 | K243: 8.07 | L243: 10.2 | M243: 12.86 | N243: 15.37 | O243: 13.64
A244: =VLOOKUP(B244,'[1]PORTFOLIO RAW'!B:B,1,FALSE) -> 906400 | B244: 906400 | C244: SNAP-ON - MRKT VALUE TO BOOK | D244: 906400(MTBV) | E244: 2.22 | F244: 2.83 | G244: 1.65 | H244: 1.96 | I244: 1.9 | J244: 2.33 | K244: 2.78 | L244: 3.26 | M244: 3.75 | N244: 3.32 | O244: 2.91
A245: =VLOOKUP(B245,'[1]PORTFOLIO RAW'!B:B,1,FALSE) -> 14861V | B245: 14861V | C245: PRUDENTIAL FINL. - MRKT VALUE TO BOOK | D245: 14861V(MTBV) | E245: 1.86 | F245: 1.83 | G245: 0.99 | H245: 0.9 | I245: 0.75 | J245: 0.98 | K245: 1.45 | L245: 1.89 | M245: 1.31 | N245: 1.26 | O245: 1.33
A246: =VLOOKUP(B246,'[1]PORTFOLIO RAW'!B:B,1,FALSE) -> 14806F | B246: 14806F | C246: ADV.AUTO PARTS - MRKT VALUE TO BOOK | D246: 14806F(MTBV) | E246: 3.42 | F246: 3.48 | G246: 2.92 | H246: 4.8 | I246: 5.36 | J246: 4.19 | K246: 3.87 | L246: 4.8 | M246: 5.17 | N246: 3.68 | O246: 2.05
A247: =VLOOKUP(B247,'[1]PORTFOLIO RAW'!B:B,1,FALSE) -> 902324 | B247: 902324 | C247: EDISON INTL. - MRKT VALUE TO BOOK | D247: 902324(MTBV) | E247: 2.19 | F247: 1.37 | G247: 1.16 | H247: 1.06 | I247: 1.23 | J247: 1.56 | K247: 1.51 | L247: 1.72 | M247: 1.76 | N247: 1.99 | O247: 2.21
A248: =VLOOKUP(B248,'[1]PORTFOLIO RAW'!B:B,1,FALSE) -> 902325 | B248: 902325 | C248: SOUTHERN - MRKT VALUE TO BOOK | D248: 902325(MTBV) | E248: 2.26 | F248: 2.23 | G248: 1.71 | H248: 1.91 | I248: 2.09 | J248: 2.15 | K248: 1.92 | L248: 1.96 | M248: 1.92 | N248: 2.06 | O248: 2.05
A249: =VLOOKUP(B249,'[1]PORTFOLIO RAW'!B:B,1,FALSE) -> 992305 | B249: 992305 | C249: BB&T - MRKT VALUE TO BOOK | D249: 992305(MTBV) | E249: 1.83 | F249: 1.74 | G249: 1.17 | H249: 1 | I249: 0.89 | J249: 1.23 | K249: 1.22 | L249: 1.28 | M249: 1.05 | N249: 1.16 | O249: 1.37
A250: =VLOOKUP(B250,'[1]PORTFOLIO RAW'!B:B,1,FALSE) -> 905647 | B250: 905647 | C250: SOUTHWEST AIRLINES - MRKT VALUE TO BOOK | D250: 905647(MTBV) | E250: 1.63 | F250: 2.32 | G250: 1.31 | H250: 1.46 | I250: 0.99 | J250: 0.95 | K250: 1.39 | L250: 3.49 | M250: 3.54 | N250: 2.71 | O250: 3.11
A251: =VLOOKUP(B251,'[1]PORTFOLIO RAW'!B:B,1,FALSE) -> 945388 | B251: 945388 | C251: AT&T - MRKT VALUE TO BOOK | D251: 945388(MTBV) | E251: 2.22 | F251: 1.86 | G251: 1.57 | H251: 1.51 | I251: 1.62 | J251: 2.37 | K251: 2 | L251: 2.13 | M251: 1.63 | N251: 2 | O251: 1.68
A252: =VLOOKUP(B252,'[1]PORTFOLIO RAW'!B:B,1,FALSE) -> 905024 | B252: 905024 | C252: CHEVRON - MRKT VALUE TO BOOK | D252: 905024(MTBV) | E252: 2.6 | F252: 2.08 | G252: 1.58 | H252: 1.53 | I252: 1.61 | J252: 1.69 | K252: 1.62 | L252: 1.53 | M252: 0.96 | N252: 1.27 | O252: 1.49
A253: =VLOOKUP(B253,'[1]PORTFOLIO RAW'!B:B,1,FALSE) -> 951052 | B253: 951052 | C253: STATE STREET - MRKT VALUE TO BOOK | D253: 951052(MTBV) | E253: 2.29 | F253: 2.4 | G253: 1.86 | H253: 1.12 | I253: 0.87 | J253: 1.02 | K253: 1.52 | L253: 1.62 | M253: 1.53 | N253: 1.51 | O253: 1.87
A254: =VLOOKUP(B254,'[1]PORTFOLIO RAW'!B:B,1,FALSE) -> 326143 | B254: 326143 | C254: STARBUCKS - MRKT VALUE TO BOOK | D254: 326143(MTBV) | E254: 8.98 | F254: 4.73 | G254: 5.02 | H254: 5.29 | I254: 6.99 | J254: 7.61 | K254: 12.77 | L254: 10.84 | M254: 14.5 | N254: 13.29 | O254: 14.61
A255: =VLOOKUP(B255,'[1]PORTFOLIO RAW'!B:B,1,FALSE) -> 905792 | B255: 905792 | C255: PUBLIC STORAGE - MRKT VALUE TO BOOK | D255: 905792(MTBV) | E255: 2.54 | F255: 3.22 | G255: 2.38 | H255: 3.34 | I255: 3.98 | J255: 4.64 | K255: 5.39 | L255: 5.52 | M255: 7 | N255: 7.45 | O255: 7.58
A256: =VLOOKUP(B256,'[1]PORTFOLIO RAW'!B:B,1,FALSE) -> 981722 | B256: 981722 | C256: STRYKER - MRKT VALUE TO BOOK | D256: 981722(MTBV) | E256: 5.2 | F256: 4.87 | G256: 2.84 | H256: 2.7 | I256: 2.45 | J256: 2.47 | K256: 2.98 | L256: 3.65 | M256: 4.39 | N256: 4.49 | O256: 5.36
A257: =VLOOKUP(B257,'[1]PORTFOLIO RAW'!B:B,1,FALSE) -> 922725 | B257: 922725 | C257: SUNTRUST BANKS - MRKT VALUE TO BOOK | D257: 922725(MTBV) | E257: 1.56 | F257: 1.22 | G257: 0.68 | H257: 0.72 | I257: 0.51 | J257: 0.76 | K257: 0.86 | L257: 0.97 | M257: 0.87 | N257: 0.97 | O257: 1.2
A258: =VLOOKUP(B258,'[1]PORTFOLIO RAW'!B:B,1,FALSE) -> 541900 | B258: 541900 | C258: SYMANTEC - MRKT VALUE TO BOOK | D258: 541900(MTBV) | E258: 1.55 | F258: 4.23 | G258: 2.8 | H258: 2.63 | I258: 2.52 | J258: 2.45 | K258: 3.03 | L258: 2.84 | M258: 3.73 | N258: 4.41 | O258: 4.13
... A281: =VLOOKUP(B281,'[1]PORTFOLIO RAW'!B:B,1,FALSE) -> 904869 | B281: 904869 | C281: WHIRLPOOL - MRKT VALUE TO BOOK | D281: 904869(MTBV) | E281: 1.87 | F281: 2.24 | G281: 1.48 | H281: 1.44 | I281: 0.94 | J281: 1.54 | K281: 2.38 | L281: 2.49 | M281: 2.71 | N281: 2.54 | O281: 2.96
A282: =VLOOKUP(B282,'[1]PORTFOLIO RAW'!B:B,1,FALSE) -> 26406N | B282: 26406N | C282: WYNN RESORTS - MRKT VALUE TO BOOK | D282: 26406N(MTBV) | E282: 8.18 | F282: 6.19 | G282: 2.81 | H282: 5.23 | I282: 9.16 | J282: -44.59 | K282: -85.06 | L282: -652.48 | M282: -62.06 | N282: 66.69 | O282: 15.77
A283: =VLOOKUP(B283,'[1]PORTFOLIO RAW'!B:B,1,FALSE) -> 26393N | B283: 26393N | C283: CME GROUP - MRKT VALUE TO BOOK | D283: 26393N(MTBV) | E283: 2.41 | F283: 1.18 | G283: 1.05 | H283: 0.95 | I283: 0.82 | J283: 0.9 | K283: 1.18 | L283: 1.33 | M283: 1.49 | N283: 1.81 | O283: 2.03
A284: =VLOOKUP(B284,'[1]PORTFOLIO RAW'!B:B,1,FALSE) -> 922407 | B284: 922407 | C284: WILLIAMS - MRKT VALUE TO BOOK | D284: 922407(MTBV) | E284: 3.17 | F284: 1.84 | G284: 1.27 | H284: 1.51 | I284: 8.82 | J284: 4.53 | K284: 5.15 | L284: 4.8 | M284: 5.63 | N284: 4.81 | O284: 2.6
A285: =VLOOKUP(B285,'[1]PORTFOLIO RAW'!B:B,1,FALSE) -> 906979 | B285: 906979 | C285: ALLIANT ENERGY (XSC) - MRKT VALUE TO BOOK | D285: 906979(MTBV) | E285: 1.59 | F285: 1.36 | G285: 1.12 | H285: 1.38 | I285: 1.48 | J285: 1.54 | K285: 1.67 | L285: 1.85 | M285: 1.73 | N285: 2.29 | O285: 2.33
A286: =VLOOKUP(B286,'[1]PORTFOLIO RAW'!B:B,1,FALSE) -> 877723 | B286: 877723 | C286: CARMAX - MRKT VALUE TO BOOK | D286: 877723(MTBV) | E286: 3.23 | F286: 2.28 | G286: 2.17 | H286: 2.33 | I286: 2.38 | J286: 2.27 | K286: 3.45 | L286: 3.68 | M286: 4.25 | N286: 3.43 | O286: 3.77
A287: =VLOOKUP(B287,'[1]PORTFOLIO RAW'!B:B,1,FALSE) -> 543542 | B287: 543542 | C287: XILINX - MRKT VALUE TO BOOK | D287: 543542(MTBV) | E287: 4.79 | F287: 3.83 | G287: 2.97 | H287: 2.81 | I287: 2.94 | J287: 3.09 | K287: 4.5 | L287: 4.49 | M287: 4.24 | N287: 5.35 | O287: 7.41
A288: =VLOOKUP(B288,'[1]PORTFOLIO RAW'!B:B,1,FALSE) -> 26276P | B288: 26276P | C288: CIMAREX EN. - MRKT VALUE TO BOOK | D288: 26276P(MTBV) | E288: 0.97 | F288: 1.87 | G288: 1.74 | H288: 2.25 | I288: 1.77 | J288: 1.53 | K288: 1.97 | L288: 2.58 | M288: 3.51 | N288: 5.08 | O288: 4.06
A289: =VLOOKUP(B289,'[1]PORTFOLIO RAW'!B:B,1,FALSE) -> 921855 | B289: 921855 | C289: TJX - MRKT VALUE TO BOOK | D289: 921855(MTBV) | E289: 6.35 | F289: 6.4 | G289: 5.58 | H289: 5.58 | I289: 6.91 | J289: 9.07 | K289: 9.57 | L289: 9.69 | M289: 11.17 | N289: 10.93 | O289: 8.95
A290: =VLOOKUP(B290,'[1]PORTFOLIO RAW'!B:B,1,FALSE) -> 951584 | B290: 951584 | C290: ZIONS BANCORP. - MRKT VALUE TO BOOK | D290: 951584(MTBV) | E290: 1.51 | F290: 1.16 | G290: 0.56 | H290: 0.83 | I290: 0.66 | J290: 0.78 | K290: 0.95 | L290: 0.96 | M290: 0.84 | N290: 0.88 | O290: 1.28
A291: =VLOOKUP(B291,'[1]PORTFOLIO RAW'!B:B,1,FALSE) -> 951051 | B291: 951051 | C291: REGIONS FINL.NEW - MRKT VALUE TO BOOK | D291: 951051(MTBV) | E291: 1.11 | F291: 1.03 | G291: 0.52 | H291: 0.67 | I291: 0.37 | J291: 0.71 | K291: 0.85 | L291: 0.9 | M291: 0.75 | N291: 0.77 | O291: 1.13
A292: =VLOOKUP(B292,'[1]PORTFOLIO RAW'!B:B,1,FALSE) -> 905997 | B292: 905997 | C292: MOLSON COORS BREWING 'B' - MRKT VALUE TO BOOK | D292: 905997(MTBV) | E292: 0.91 | F292: 1.26 | G292: 1.1 | H292: 0.98 | I292: 0.93 | J292: 0.92 | K292: 0.96 | L292: 1.61 | M292: 2.01 | N292: 1.74 | O292: 1.23
A293: =VLOOKUP(B293,'[1]PORTFOLIO RAW'!B:B,1,FALSE) -> 31604H | B293: 31604H | C293: AMERIPRISE FINL. - MRKT VALUE TO BOOK | D293: 31604H(MTBV) | E293: 1.85 | F293: 1.53 | G293: 0.9 | H293: 1.13 | I293: 1 | J293: 1.33 | K293: 2.23 | L293: 2.92 | M293: 2.65 | N293: 2.55 | O293: 3.54
A294: =VLOOKUP(B294,'[1]PORTFOLIO RAW'!B:B,1,FALSE) -> 543487 | B294: 543487 | C294: VIACOM 'B' - MRKT VALUE TO BOOK | D294: 543487(MTBV) | E294: 3.76 | F294: 2.37 | G294: 1.95 | H294: 2.34 | I294: 3.11 | J294: 3.76 | K294: 7.69 | L294: 9.22 | M294: 5.13 | N294: 3.35 | O294: 1.85
A295: =VLOOKUP(B295,'[1]PORTFOLIO RAW'!B:B,1,FALSE) -> 32480Q | B295: 32480Q | C295: CBS 'B' - MRKT VALUE TO BOOK | D295: 32480Q(MTBV) | E295: 1.08 | F295: 1.24 | G295: 0.94 | H295: 1.08 | I295: 1.61 | J295: 2.3 | K295: 3.41 | L295: 4.23 | M295: 3.72 | N295: 6.07 | O295: 12.07
A296: =VLOOKUP(B296,'[1]PORTFOLIO RAW'!B:B,1,FALSE) -> 41071J | B296: 41071J | C296: HANESBRANDS - MRKT VALUE TO BOOK | D296: 41071J(MTBV) | E296: 9.23 | F296: 13.16 | G296: 6.33 | H296: 4.4 | I296: 3.87 | J296: 3.6 | K296: 5.12 | L296: 7.7 | M296: 9.47 | N296: 7.94 | O296: 13.09
A297: =VLOOKUP(B297,'[1]PORTFOLIO RAW'!B:B,1,FALSE) -> 41195M | B297: 41195M | C297: WESTERN UNION - MRKT VALUE TO BOOK | D297: 41195M(MTBV) | E297: 299.31 | F297: -2315.23 | G297: 38.82 | H297: 19.8 | I297: 11.39 | J297: 11.97 | K297: 9.31 | L297: 6.81 | M297: 6.76 | N297: 10.72 | O297: -17.89
A298: =VLOOKUP(B298,'[1]PORTFOLIO RAW'!B:B,1,FALSE) -> 517465 | B298: 517465 | C298: PEOPLES UNITED FINANCIAL - MRKT VALUE TO BOOK | D298: 517465(MTBV) | E298: 1.18 | F298: 1.46 | G298: 1.11 | H298: 0.93 | I298: 0.88 | J298: 0.84 | K298: 1.01 | L298: 1 | M298: 1 | N298: 1 | O298: 1.07
A299: =VLOOKUP(B299,'[1]PORTFOLIO RAW'!B:B,1,FALSE) -> 905840 | B299: 905840 | C299: BANK OF NEW YORK MELLON - MRKT VALUE TO BOOK | D299: 905840(MTBV) | E299: 1.68 | F299: 1.63 | G299: 1.26 | H299: 0.97 | I299: 0.75 | J299: 0.77 | K299: 0.99 | L299: 1.25 | M299: 1.21 | N299: 1.22 | O299: 1.44
A300: =VLOOKUP(B300,'[1]PORTFOLIO RAW'!B:B,1,FALSE) -> 51245V | B300: 51245V | C300: INVESCO - MRKT VALUE TO BOOK | D300: 51245V(MTBV) | E300: NA | F300: 1.84 | G300: 1.36 | H300: 1.22 | I300: 0.99 | J300: 1.36 | K300: 1.72 | L300: 2.13 | M300: 1.77 | N300: 1.67 | O300: 1.57
A301: =VLOOKUP(B301,'[1]PORTFOLIO RAW'!B:B,1,FALSE) -> 328314 | B301: 328314 | C301: CHUBB - MRKT VALUE TO BOOK | D301: 328314(MTBV) | E301: 1.21 | F301: 1.36 | G301: 0.88 | H301: 0.92 | I301: 0.94 | J301: 1.04 | K301: 1.17 | L301: 1.3 | M301: 1.15 | N301: 1.23 | O301: 1.35
A302: =VLOOKUP(B302,'[1]PORTFOLIO RAW'!B:B,1,FALSE) -> 31196R | B302: 31196R | C302: DISCOVERY SERIES A - MRKT VALUE TO BOOK | D302: 31196R(MTBV) | E302: 2.59 | F302: 1.76 | G302: 1.35 | H302: 1.95 | I302: 1.58 | J302: 2.34 | K302: 3.11 | L302: 2.67 | M302: 2.16 | N302: 1.82 | O302: 1.75
A303: =VLOOKUP(B303,'[1]PORTFOLIO RAW'!B:B,1,FALSE) -> 771767 | B303: 771767 | C303: MOSAIC - MRKT VALUE TO BOOK | D303: 771767(MTBV) | E303: 3.11 | F303: 4.98 | G303: 2.77 | H303: 2.33 | I303: 2.18 | J303: 2.27 | K303: 1.69 | L303: 1.55 | M303: 1.31 | N303: 0.92 | O303: 0.76
A304: =VLOOKUP(B304,'[1]PORTFOLIO RAW'!B:B,1,FALSE) -> 921503 | B304: 921503 | C304: STANLEY BLACK & DECKER - MRKT VALUE TO BOOK | D304: 921503(MTBV) | E304: 2.71 | F304: 2.2 | G304: 1.7 | H304: 1.43 | I304: 1.3 | J304: 1.92 | K304: 2.12 | L304: 2.27 | M304: 2.64 | N304: 2.88 | O304: 3.09
A305: =VLOOKUP(B305,'[1]PORTFOLIO RAW'!B:B,1,FALSE) -> 255781 | B305: 255781 | C305: GARMIN - MRKT VALUE TO BOOK | D305: 255781(MTBV) | E305: 9.85 | F305: 3.53 | G305: 2.59 | H305: 1.97 | I305: 1.98 | J305: 2.31 | K305: 2.33 | L305: 2.95 | M305: 2.07 | N305: 2.63 | O305: 2.58
A306: =VLOOKUP(B306,'[1]PORTFOLIO RAW'!B:B,1,FALSE) -> 670129 | B306: 670129 | C306: PROLOGIS - MRKT VALUE TO BOOK | D306: 670129(MTBV) | E306: 2.28 | F306: 2.02 | G306: 1.34 | H306: 1.45 | I306: 0.99 | J306: 1.3 | K306: 1.4 | L306: 1.39 | M306: 1.37 | N306: 1.85 | O306: 2.21
A307: =VLOOKUP(B307,'[1]PORTFOLIO RAW'!B:B,1,FALSE) -> 14352P | B307: 14352P | C307: ACCENTURE CLASS A - MRKT VALUE TO BOOK | D307: 14352P(MTBV) | E307: 10.9 | F307: 9.24 | G307: 8.57 | H307: 7.35 | I307: 9.04 | J307: 8.79 | K307: 9.09 | L307: 8.53 | M307: 8.38 | N307: 7.96 | O307: 8.24
A308: =VLOOKUP(B308,'[1]PORTFOLIO RAW'!B:B,1,FALSE) -> 749688 | B308: 749688 | C308: HCA HEALTHCARE - MRKT VALUE TO BOOK | D308: 749688(MTBV) | E308: NA | F308: NA | G308: NA | H308: NA | I308: -1.25 | J308: -1.48 | K308: -2.28 | L308: -4.02 | M308: -4.51 | N308: -3.89 | O308: -4.13
A309: =VLOOKUP(B309,'[1]PORTFOLIO RAW'!B:B,1,FALSE) -> 894145 | B309: 894145 | C309: RALPH LAUREN CL.A - MRKT VALUE TO BOOK | D309: 894145(MTBV) | E309: 3.61 | F309: 2.62 | G309: 2.41 | H309: 2.62 | I309: 3.84 | J309: 3.69 | K309: 3.61 | L309: 3.86 | M309: 2.54 | N309: 2.48 | O309: 2.09
A310: =VLOOKUP(B310,'[1]PORTFOLIO RAW'!B:B,1,FALSE) -> 26599V | B310: 26599V | C310: SEAGATE TECH. - MRKT VALUE TO BOOK | D310: 26599V(MTBV) | E310: 2.96 | F310: 4.11 | G310: 2.78 | H310: 2.16 | I310: 1.37 | J310: 3.37 | K310: 5.22 | L310: 6.3 | M310: 8.51 | N310: 7.81 | O310: 5.6
A311: =VLOOKUP(B311,'[1]PORTFOLIO RAW'!B:B,1,FALSE) -> 904878 | B311: 904878 | C311: MOTOROLA SOLUTIONS - MRKT VALUE TO BOOK | D311: 904878(MTBV) | E311: 2.65 | F311: 1.79 | G311: 2.1 | H311: 1.81 | I311: 2.92 | J311: 4.37 | K311: 4.39 | L311: 5.68 | M311: -130.87 | N311: -13.01 | O311: -8
A312: =VLOOKUP(B312,'[1]PORTFOLIO RAW'!B:B,1,FALSE) -> 922817 | B312: 922817 | C312: AON CLASS A - MRKT VALUE TO BOOK | D312: 922817(MTBV) | E312: 2.09 | F312: 2.44 | G312: 2.15 | H312: 1.27 | I312: 1.74 | J312: 2.19 | K312: 2.85 | L312: 3.84 | M312: 4.1 | N312: 5.35 | O312: 8.1
A313: =VLOOKUP(B313,'[1]PORTFOLIO RAW'!B:B,1,FALSE) -> 905446 | B313: 905446 | C313: INGERSOLL-RAND - MRKT VALUE TO BOOK | D313: 905446(MTBV) | E313: 1.95 | F313: 1.75 | G313: 1.44 | H313: 1.42 | I313: 1.58 | J313: 2 | K313: 2.69 | L313: 2.65 | M313: 2.51 | N313: 2.49 | O313: 3.17
A314: =VLOOKUP(B314,'[1]PORTFOLIO RAW'!B:B,1,FALSE) -> 28513N | B314: 28513N | C314: CBRE GROUP CLASS A - MRKT VALUE TO BOOK | D314: 28513N(MTBV) | E314: 6.53 | F314: 26.02 | G314: 5.67 | H314: 6.64 | I314: 3.96 | J314: 4.14 | K314: 4.16 | L314: 4.46 | M314: 4.08 | N314: 3.18 | O314: 3.12
A315: =VLOOKUP(B315,'[1]PORTFOLIO RAW'!B:B,1,FALSE) -> 31412T | B315: 31412T | C315: EXPEDIA GROUP - MRKT VALUE TO BOOK | D315: 31412T(MTBV) | E315: 1.8 | F315: 2.06 | G315: 2.63 | H315: 3.08 | I315: 3.61 | J315: 3.3 | K315: 3.37 | L315: 6.07 | M315: 3.31 | N315: 3.9 | O315: 4.79
A316: =VLOOKUP(B316,'[1]PORTFOLIO RAW'!B:B,1,FALSE) -> 680902 | B316: 680902 | C316: AMERICAN TOWER - MRKT VALUE TO BOOK | D316: 680902(MTBV) | E316: 5.68 | F316: 5.23 | G316: 4.48 | H316: 5.74 | I316: 6.64 | J316: 7.83 | K316: 8.26 | L316: 9.54 | M316: 8.19 | N316: 9.65 | O316: 9.66
A317: =VLOOKUP(B317,'[1]PORTFOLIO RAW'!B:B,1,FALSE) -> 904383 | B317: 904383 | C317: DUKE ENERGY - MRKT VALUE TO BOOK | D317: 904383(MTBV) | E317: 1.11 | F317: 1.08 | G317: 0.95 | H317: 1.03 | I317: 1.15 | J317: 1.1 | K317: 1.15 | L317: 1.29 | M317: 1.2 | N317: 1.35 | O317: 1.43
A318: =VLOOKUP(B318,'[1]PORTFOLIO RAW'!B:B,1,FALSE) -> 13967E | B318: 13967E | C318: MONDELEZ INTERNATIONAL CL.A - MRKT VALUE TO BOOK | D318: 13967E(MTBV) | E318: 2 | F318: 2.39 | G318: 1.52 | H318: 1.54 | I318: 1.73 | J318: 2.29 | K318: 1.78 | L318: 2.17 | M318: 2.46 | N318: 2.65 | O318: 2.33
A319: =VLOOKUP(B319,'[1]PORTFOLIO RAW'!B:B,1,FALSE) -> 903749 | B319: 903749 | C319: EATON - MRKT VALUE TO BOOK | D319: 903749(MTBV) | E319: 2.77 | F319: 1.82 | G319: 1.46 | H319: 1.85 | I319: 1.76 | J319: 1.07 | K319: 1.99 | L319: 2 | M319: 1.63 | N319: 1.92 | O319: 2.02
A320: =VLOOKUP(B320,'[1]PORTFOLIO RAW'!B:B,1,FALSE) -> 937343 | B320: 937343 | C320: L BRANDS - MRKT VALUE TO BOOK | D320: 937343(MTBV) | E320: 3.65 | F320: 3.53 | G320: 2.48 | H320: 5.99 | I320: 89.8 | J320: -14.65 | K320: -47.01 | L320: 1081.05 | M320: -103.07 | N320: -28.33 | O320: -14.03
A321: =VLOOKUP(B321,'[1]PORTFOLIO RAW'!B:B,1,FALSE) -> 905113 | B321: 905113 | C321: ARCONIC - MRKT VALUE TO BOOK | D321: 905113(MTBV) | E321: 2.06 | F321: 1.87 | G321: 1.11 | H321: 0.86 | I321: 0.87 | J321: 0.75 | K321: 0.84 | L321: 1.56 | M321: 1.09 | N321: 2.46 | O321: 2.38
A322: =VLOOKUP(B322,'[1]PORTFOLIO RAW'!B:B,1,FALSE) -> 13967H | B322: 13967H | C322: WILLIS TOWERS WATSON - MRKT VALUE TO BOOK | D322: 13967H(MTBV) | E322: 4.22 | F322: 2.44 | G322: 2.17 | H322: 2.06 | I322: 2.47 | J322: 4.05 | K322: 3.54 | L322: 3.83 | M322: 3.37 | N322: 1.72 | O322: 2.02
A323: =VLOOKUP(B323,'[1]PORTFOLIO RAW'!B:B,1,FALSE) -> 921431 | B323: 921431 | C323: BAKER HUGHES A - MRKT VALUE TO BOOK | D323: 921431(MTBV) | E323: 4.51 | F323: 3.05 | G323: 1.87 | H323: 1.24 | I323: 1.6 | J323: 1.22 | K323: 1.25 | L323: 1.58 | M323: 1.43 | N323: 1.64 | O323: 1.1
A324: =VLOOKUP(B324,'[1]PORTFOLIO RAW'!B:B,1,FALSE) -> 266220 | B324: 266220 | C324: TAPESTRY - MRKT VALUE TO BOOK | D324: 266220(MTBV) | E324: 11.99 | F324: 5.86 | G324: 7.11 | H324: 7.64 | I324: 8.64 | J324: 6.99 | K324: 6.39 | L324: 4.1 | M324: 3.01 | N324: 3.35 | O324: 3.46
A325: =VLOOKUP(B325,'[1]PORTFOLIO RAW'!B:B,1,FALSE) -> 30730Q | B325: 30730Q | C325: INTERCONTINENTAL EX. - MRKT VALUE TO BOOK | D325: 30730Q(MTBV) | E325: 6.35 | F325: 3.05 | G325: 2.98 | H325: 2.8 | I325: 2.88 | J325: 2.75 | K325: 1.05 | L325: 1.87 | M325: 1.7 | N325: 2.12 | O325: 2.32
A326: =VLOOKUP(B326,'[1]PORTFOLIO RAW'!B:B,1,FALSE) -> 921925 | B326: 921925 | C326: JEFFERIES FINANCIAL GROUP - MRKT VALUE TO BOOK | D326: 921925(MTBV) | E326: 1.78 | F326: 3.83 | G326: 1.42 | H326: 0.84 | I326: 1.09 | J326: 0.86 | K326: 0.98 | L326: 0.91 | M326: 0.72 | N326: 0.67 | O326: 0.87
A327: =VLOOKUP(B327,'[1]PORTFOLIO RAW'!B:B,1,FALSE) -> 912278 | B327: 912278 | C327: CIGNA - MRKT VALUE TO BOOK | D327: 912278(MTBV) | E327: 3.18 | F327: 2.7 | G327: 1.71 | H327: 1.55 | I327: 1.62 | J327: 1.52 | K327: 2.2 | L327: 2.33 | M327: 3.03 | N327: 2.53 | O327: 3.41
...

Sheet MCAP
A1: Market Capitalization
E2: 4 | F2: 5 | G2: 6 | H2: 7 | I2: 8 | J2: 9 | K2: 10 | L2: 11 | M2: 12 | N2: 13 | O2: 14 | P2: 15
B3: Code | C3: Name | D3: Code | E3: 2007 | F3: 2008 | G3: 2009 | H3: 2010 | I3: 2011 | J3: 2012 | K3: 2013 | L3: 2014 | M3: 2015 | N3: 2016 | O3: 2017 | P3: 2018
A4: =VLOOKUP(B4,'[1]PORTFOLIO RAW'!B:B,1,FALSE) -> 891399 | B4: 891399 | C4: AMAZON.COM INC - MARKET CAPITALIZATION | D4: 891399(WC08001) | E4: 38538240 | F4: 21947840 | G4: 59726880 | H4: 81180000 | I4: 78760500 | J4: 113894980 | K4: 183044610 | L4: 144312750 | M4: 318344190 | N4: 357687990 | O4: 566023480 | P4: 737467270
A5: =VLOOKUP(B5,'[1]PORTFOLIO RAW'!B:B,1,FALSE) -> 916328 | B5: 916328 | C5: ABBOTT LABORATORIES - MARKET CAPITALIZATION | D5: 916328(WC08001) | E5: 87027454 | F5: 82853346 | G5: 83747538 | H5: 74116001 | I5: 88302401 | J5: 103271721 | K5: 59338607 | L5: 67891755 | M5: 66137387 | N5: 56572906 | O5: 99507393 | P5: 126983953
A6: =VLOOKUP(B6,'[1]PORTFOLIO RAW'!B:B,1,FALSE) -> 545101 | B6: 545101 | C6: AES CORP - MARKET CAPITALIZATION | D6: 545101(WC08001) | E6: 14338569 | F6: 5461363 | G6: 8886820 | H6: 9593056 | I6: 9059806 | J6: 7963623 | K6: 10483596 | L6: 9692032 | M6: 6381360 | N6: 7659698 | O6: 7152003 | P6: 9576830
A7: =VLOOKUP(B7,'[1]PORTFOLIO RAW'!B:B,1,FALSE) -> 906187 | B7: 906187 | C7: INT'L BUSINESS MACHS - MARKET CAPITALIZATION | D7: 906187(WC08001) | E7: 149743810 | F7: 112698313 | G7: 170868669 | H7: 180220333 | I7: 213886010 | J7: 214031778 | K7: 197772108 | L7: 158919632 | M7: 132903587 | N7: 157004530 | O7: 141480737 | P7: 101448135
A8: =VLOOKUP(B8,'[1]PORTFOLIO RAW'!B:B,1,FALSE) -> 936365 | B8: 936365 | C8: ADVANCED MICRO - MARKET CAPITALIZATION | D8: 936365(WC08001) | E8: 4545000 | F8: 1315440 | G8: 6495280 | H8: 5586940 | I8: 3763800 | J8: 1711200 | K8: 2805750 | L8: 2071920 | M8: 2273040 | N8: 10602900 | O8: 9940760 | P8: 18552300
A9: =VLOOKUP(B9,'[1]PORTFOLIO RAW'!B:B,1,FALSE) -> 749382 | B9: 749382 | C9: ADOBE INC - MARKET CAPITALIZATION | D9: 749382(WC08001) | E9: 24416307 | F9: 11200903 | G9: 19223324 | H9: 15448390 | I9: 13895836 | J9: 18618894 | K9: 29715612 | L9: 36167087 | M9: 46764177 | N9: 50883449 | O9: 86088753 | P9: 110328877
A10: =VLOOKUP(B10,'[1]PORTFOLIO RAW'!B:B,1,FALSE) -> 905271 | B10: 905271 | C10: AIR PRODUCTS & CHEMS - MARKET CAPITALIZATION | D10: 905271(WC08001) | E10: 21240531 | F10: 10523252 | G10: 17124757 | H10: 19445371 | I10: 17905682 | J10: 17852223 | K10: 23605617 | L10: 30798607 | M10: 28020374 | N10: 31259396 | O10: 35826224 | P10: 35133415
A11: =VLOOKUP(B11,'[1]PORTFOLIO RAW'!B:B,1,FALSE) -> 894371 | B11: 894371 | C11: BOSTON PROPERTIES - MARKET CAPITALIZATION | D11: 894371(WC08001) | E11: 10971523 | F11: 6664936 | G11: 9314682 | H11: 12071143 | I11: 14751518 | J11: 16040924 | K11: 15354914 | L11: 19704234 | M11: 19587589 | N11: 19343728 | O11: 20066917 | P11: 17384302
A12: =VLOOKUP(B12,'[1]PORTFOLIO RAW'!B:B,1,FALSE) -> 322677 | B12: 322677 | C12: ALLSTATE CORP - MARKET CAPITALIZATION | D12: 322677(WC08001) | E12: 29405490 | F12: 17559360 | G12: 16131480 | H12: 16992040 | I12: 13732410 | J12: 19241430 | K12: 24488460 | L12: 29364500 | M12: 23656290 | N12: 27127920 | O12: 37172050 | P12: 27433160
A13: =VLOOKUP(B13,'[1]PORTFOLIO RAW'!B:B,1,FALSE) -> 906191 | B13: 906191 | C13: HONEYWELL INTERNATNL - MARKET CAPITALIZATION | D13: 906191(WC08001) | E13: 45965321 | F13: 24116466 | G13: 29957004 | H13: 41624280 | I13: 42104945 | J13: 49684316 | K13: 71615806 | L13: 78157424 | M13: 79790328 | N13: 88138680 | O13: 115158024 | P13: 96394752
A14: =VLOOKUP(B14,'[1]PORTFOLIO RAW'!B:B,1,FALSE) -> 938692 | B14: 938692 | C14: AMGEN INC - MARKET CAPITALIZATION | D14: 938692(WC08001) | E14: 50480280 | F14: 60464250 | G14: 56287150 | H14: 51166800 | I14: 51085476 | J14: 65193060 | K14: 86084768 | L14: 121124116 | M14: 122396820 | N14: 107932222 | O14: 125590580 | P14: 122564232
A15: =VLOOKUP(B15,'[1]PORTFOLIO RAW'!B:B,1,FALSE) -> 905802 | B15: 905802 | C15: HESS CORPORATION - MARKET CAPITALIZATION | D15: 905802(WC08001) | E15: 32335674 | F15: 17493760 | G15: 19797384 | H15: 25846087 | I15: 19310615 | J15: 18087303 | K15: 27001077 | L15: 21100337 | M15: 13867490 | N15: 19716230 | O15: 14955595 | P15: 11803099
... A109: =VLOOKUP(B109,'[1]PORTFOLIO RAW'!B:B,1,FALSE) -> 905016 | B109: 905016 | C109: NEXTERA ENERGY - MARKET CAPITALIZATION | D109: 905016(WC08001) | E109: 27609842 | F109: 20580707 | G109: 21847537 | H109: 21880591 | I109: 25326080 | J109: 29336560 | K109: 37244700 | L109: 47086470 | M109: 47893290 | N109: 55907280 | O109: 73565490 | P109: 83085960
A110: =VLOOKUP(B110,'[1]PORTFOLIO RAW'!B:B,1,FALSE) -> 28341F | B110: 28341F | C110: ASSURANT INC - MARKET CAPITALIZATION | D110: 28341F(WC08001) | E110: 7881356 | F110: 3521056 | G110: 3438804 | H110: 3929054 | I110: 3634811 | J110: 2729642 | K110: 4767238 | L110: 4742169 | M110: 5303590 | N110: 5194726 | O110: 5285812 | P110: 5537139
A111: =VLOOKUP(B111,'[1]PORTFOLIO RAW'!B:B,1,FALSE) -> 755980 | B111: 755980 | C111: FASTENAL COMPANY - MARKET CAPITALIZATION | D111: 755980(WC08001) | E111: 6027459 | F111: 5176295 | G111: 6139015 | H111: 8832574 | I111: 12876231 | J111: 13834728 | K111: 14098761 | L111: 14071475 | M111: 11820724 | N111: 13584827 | O111: 15728381 | P111: 14949811
A112: =VLOOKUP(B112,'[1]PORTFOLIO RAW'!B:B,1,FALSE) -> 905994 | B112: 905994 | C112: FEDERAL REALTY INVST - MARKET CAPITALIZATION | D112: 905994(WC08001) | E112: 4817741 | F112: 3661831 | G112: 4147312 | H112: 4794754 | I112: 5766632 | J112: 6742103 | K112: 6764191 | L112: 9156128 | M112: 10152985 | N112: 10231337 | O112: 9707199 | P112: 8764427
A113: =VLOOKUP(B113,'[1]PORTFOLIO RAW'!B:B,1,FALSE) -> 997198 | B113: 997198 | C113: FIFTH THIRD BANCORP - MARKET CAPITALIZATION | D113: 997198(WC08001) | E113: 13385532 | F113: 4769217 | G113: 7751913 | H113: 11689281 | I113: 11699912 | J113: 13408711 | K113: 17987080 | L113: 16789957 | M113: 15780114 | N113: 20240427 | O113: 21050040 | P113: 15215224
A114: =VLOOKUP(B114,'[1]PORTFOLIO RAW'!B:B,1,FALSE) -> 951503 | B114: 951503 | C114: M&T BANK CORPORATION - MARKET CAPITALIZATION | D114: 951503(WC08001) | E114: 8960656 | F114: 6336072 | G114: 7907916 | H114: 10420115 | I114: 9594671 | J114: 12621581 | K114: 15194715 | L114: 16621150 | M114: 19335906 | N114: 24431384 | O114: 25662932 | P114: 19824903
A115: =VLOOKUP(B115,'[1]PORTFOLIO RAW'!B:B,1,FALSE) -> 741123 | B115: 741123 | C115: FISERV INC - MARKET CAPITALIZATION | D115: 741123(WC08001) | E115: 9161399 | F115: 5670083 | G115: 7427136 | H115: 8602464 | I115: 8229474 | J115: 10542602 | K115: 15158135 | L115: 17054091 | M115: 20605938 | N115: 22903340 | O115: 27222588 | P115: 28844825
A116: =VLOOKUP(B116,'[1]PORTFOLIO RAW'!B:B,1,FALSE) -> 546814 | B116: 546814 | C116: MACY'S INC - MARKET CAPITALIZATION | D116: 546814(WC08001) | E116: 10857639 | F116: 4348035 | G116: 7052608 | H116: 10709490 | I116: 13328956 | J116: 15128054 | K116: 19487529 | L116: 22392721 | M116: 10852758 | N116: 10888489 | O116: 7677030 | P116: 9157350
A117: =VLOOKUP(B117,'[1]PORTFOLIO RAW'!B:B,1,FALSE) -> 938076 | B117: 938076 | C117: FRANKLIN RESOURCES - MARKET CAPITALIZATION | D117: 938076(WC08001) | E117: 28089120 | F117: 14846580 | G117: 24159320 | H117: 24911893 | I117: 20911631 | J117: 26674666 | K117: 36422869 | L117: 34489590 | M117: 22221503 | N117: 22574261 | O117: 24042315 | P117: 15397176
A118: =VLOOKUP(B118,'[1]PORTFOLIO RAW'!B:B,1,FALSE) -> 152594 | B118: 152594 | C118: FREEPORT-MCMORAN INC - MARKET CAPITALIZATION | D118: 152594(WC08001) | E118: 39234520 | F118: 9384960 | G118: 34524700 | H118: 56742525 | I118: 34876920 | J118: 32455800 | K118: 39174120 | L118: 24271040 | M118: 8435420 | N118: 19059550 | O118: 27454080 | P118: 14939190
A119: =VLOOKUP(B119,'[1]PORTFOLIO RAW'!B:B,1,FALSE) -> 951018 | B119: 951018 | C119: GAP INC - MARKET CAPITALIZATION | D119: 951018(WC08001) | E119: 15619520 | F119: 9292660 | G119: 14162200 | H119: 13018320 | I119: 8996750 | J119: 14371520 | K119: 17429680 | L119: 17728310 | M119: 9805900 | N119: 8953560 | O119: 13249340 | P119: 9737280
A120: =VLOOKUP(B120,'[1]PORTFOLIO RAW'!B:B,1,FALSE) -> 907652 | B120: 907652 | C120: GENERAL DYNAMICS - MARKET CAPITALIZATION | D120: 907652(WC08001) | E120: 42882558 | F120: 27751506 | G120: 26293489 | H120: 26400832 | I120: 23671040 | J120: 24499015 | K120: 33767637 | L120: 45712423 | M120: 42991932 | N120: 52215583 | O120: 60403411 | P120: 45386236
A121: =VLOOKUP(B121,'[1]PORTFOLIO RAW'!B:B,1,FALSE) -> 905801 | B121: 905801 | C121: GENERAL MILLS, INC. - MARKET CAPITALIZATION | D121: 905801(WC08001) | E121: 19380000 | F121: 20503125 | G121: 23225680 | H121: 23364835 | I121: 26056368 | J121: 26212370 | K121: 31982328 | L121: 32653959 | M121: 34521042 | N121: 36864336 | O121: 34204401 | P121: 23095314
A122: =VLOOKUP(B122,'[1]PORTFOLIO RAW'!B:B,1,FALSE) -> 906511 | B122: 906511 | C122: GENUINE PARTS CO - MARKET CAPITALIZATION | D122: 906511(WC08001) | E122: 7688821 | F122: 6036244 | G122: 6032521 | H122: 8093046 | I122: 9525848 | J122: 9844819 | K122: 12792384 | L122: 16317257 | M122: 12890498 | N122: 14179132 | O122: 13933465 | P122: 14012834
... A181: =VLOOKUP(B181,'[1]PORTFOLIO RAW'!B:B,1,FALSE) -> 771830 | B181: 771830 | C181: MAXIM INTEGRATED PRD - MARKET CAPITALIZATION | D181: 771830(WC08001) | E181: 8488256 | F181: 3660715 | G181: 6218306 | H181: 7106030 | I181: 7702111 | J181: 8606321 | K181: 8024598 | L181: 9065135 | M181: 10823274 | N181: 10950370 | O181: 14790639 | P181: 14170064
A182: =VLOOKUP(B182,'[1]PORTFOLIO RAW'!B:B,1,FALSE) -> 312367 | B182: 312367 | C182: ACTIVISION BLIZZARD - MARKET CAPITALIZATION | D182: 312367(WC08001) | E182: NA | F182: 11225706 | G182: 13892290 | H182: 14720499 | I182: 13963382 | J182: 11805257 | K182: 12547131 | L182: 14546879 | M182: 28432598 | N182: 26919521 | O182: 47965229 | P182: 35552354
A183: =VLOOKUP(B183,'[1]PORTFOLIO RAW'!B:B,1,FALSE) -> 912635 | B183: 912635 | C183: CVS HEALTH CORP - MARKET CAPITALIZATION | D183: 912635(WC08001) | E183: 57099166 | F183: 41350106 | G183: 44804110 | H183: 47391510 | I183: 52932440 | J183: 59518850 | K183: 84452600 | L183: 109793400 | M183: 107644770 | N183: 83723510 | O183: 73515000 | P183: 84848400
A184: =VLOOKUP(B184,'[1]PORTFOLIO RAW'!B:B,1,FALSE) -> 152533 | B184: 152533 | C184: LAB CORP OF AMERICA - MARKET CAPITALIZATION | D184: 152533(WC08001) | E184: 8383830 | F184: 6969162 | G184: 7880652 | H184: 9003008 | I184: 8407866 | J184: 8098970 | K184: 7830409 | L184: 9128340 | M184: 12524732 | N184: 13184626 | O184: 16254069 | P184: 12497004
A185: =VLOOKUP(B185,'[1]PORTFOLIO RAW'!B:B,1,FALSE) -> 719643 | B185: 719643 | C185: MICROSOFT CORP - MARKET CAPITALIZATION | D185: 719643(WC08001) | E185: 333928000 | F185: 177895440 | G185: 271515840 | H185: 241923880 | I185: 217440960 | J185: 223853996 | K185: 311550480 | L185: 382701550 | M185: 445337960 | N185: 485189120 | O185: 659342320 | P185: 779752890
A186: =VLOOKUP(B186,'[1]PORTFOLIO RAW'!B:B,1,FALSE) -> 999506 | B186: 999506 | C186: MICRON TECHNOLOGY - MARKET CAPITALIZATION | D186: 999506(WC08001) | E186: 5494775 | F186: 2009304 | G186: 8962272 | H186: 7975890 | I186: 6191247 | J186: 6452218 | K186: 22715700 | L186: 37565730 | M186: 14712240 | N186: 22796800 | O186: 45725440 | P186: 36838530
A187: =VLOOKUP(B187,'[1]PORTFOLIO RAW'!B:B,1,FALSE) -> 328228 | B187: 328228 | C187: MICROCHIP TECHNOLOGY - MARKET CAPITALIZATION | D187: 328228(WC08001) | E187: 6831964 | F187: 3600136 | G187: 5309443 | H187: 6340110 | I187: 6942913 | J187: 6294776 | K187: 8792160 | L187: 9022123 | M187: 9404817 | N187: 13091843 | O187: 20132751 | P187: 16903197
A188: =VLOOKUP(B188,'[1]PORTFOLIO RAW'!B:B,1,FALSE) -> 902172 | B188: 902172 | C188: 3M COMPANY - MARKET CAPITALIZATION | D188: 902172(WC08001) | E188: 59796037 | F188: 39906481 | G188: 58745229 | H188: 61443668 | I188: 56799901 | J188: 63796460 | K188: 93027298 | L188: 104365316 | M188: 91789490 | N188: 106557411 | O188: 140017903 | P188: 109860633
A189: =VLOOKUP(B189,'[1]PORTFOLIO RAW'!B:B,1,FALSE) -> 325475 | B189: 325475 | C189: MOHAWK INDUSTRIES - MARKET CAPITALIZATION | D189: 325475(WC08001) | E189: 5085835 | F189: 2940050 | G189: 3259838 | H189: 3895382 | I189: 4116543 | J189: 6256272 | K189: 10822945 | L189: 11327764 | M189: 14001413 | N189: 14809866 | O189: 20532754 | P189: 8457027
A190: =VLOOKUP(B190,'[1]PORTFOLIO RAW'!B:B,1,FALSE) -> 905010 | B190: 905010 | C190: XCEL ENERGY INC - MARKET CAPITALIZATION | D190: 905010(WC08001) | E190: 9677626 | F190: 8417837 | G190: 9708347 | H190: 11358960 | I190: 13446692 | J190: 13033399 | K190: 13913324 | L190: 18165939 | M190: 18225601 | N190: 20643968 | O190: 24428472 | P190: 25326592
A191: =VLOOKUP(B191,'[1]PORTFOLIO RAW'!B:B,1,FALSE) -> 902230 | B191: 902230 | C191: FORD MOTOR COMPANY - MARKET CAPITALIZATION | D191: 902230(WC08001) | E191: 14772350 | F191: 5523480 | G191: 33370000 | H191: 63511717 | I191: 40896036 | J191: 50793107 | K191: 61473120 | L191: 62139500 | M191: 56796790 | N191: 49090110 | O191: 50684420 | P191: 31143150
A192: =VLOOKUP(B192,'[1]PORTFOLIO RAW'!B:B,1,FALSE) -> 884383 | B192: 884383 | C192: NATL OILWELL VARCO - MARKET CAPITALIZATION | D192: 884383(WC08001) | E192: 25794989 | F192: 10200057 | G192: 18449537 | H192: 28321783 | I192: 28821002 | J192: 29180551 | K192: 34073332 | L192: 27455603 | M192: 12584363 | N192: 14176184 | O192: 13691381 | P192: 9854065
A193: =VLOOKUP(B193,'[1]PORTFOLIO RAW'!B:B,1,FALSE) -> 867422 | B193: 867422 | C193: NETAPP INC. - MARKET CAPITALIZATION | D193: 867422(WC08001) | E193: 9161069 | F193: 4773759 | G193: 11415766 | H193: 19087608 | I193: 13383630 | J193: 12232330 | K193: 14670524 | L193: 13450525 | M193: 8120833 | N193: 9910870 | O193: 14881080 | P193: 15693210
A194: =VLOOKUP(B194,'[1]PORTFOLIO RAW'!B:B,1,FALSE) -> 906933 | B194: 906933 | C194: NEWELL BRANDS INC - MARKET CAPITALIZATION | D194: 906933(WC08001) | E194: 7160996 | F194: 2710038 | G194: 4169778 | H194: 5281290 | I194: 4656045 | J194: 6389263 | K194: 9029426 | L194: 10253828 | M194: 11778176 | N194: 21543625 | O194: 14992680 | P194: 7859852
... A236: =VLOOKUP(B236,'[1]PORTFOLIO RAW'!B:B,1,FALSE) -> 933974 | B236: 933974 | C236: TRAVELERS COS - MARKET CAPITALIZATION | D236: 933974(WC08001) | E236: 33775640 | F236: 26446520 | G236: 25942158 | H236: 24211566 | I236: 23241976 | J236: 27104868 | K236: 32005890 | L236: 34104870 | M236: 33395274 | N236: 34228632 | O236: 36812696 | P236: 31578075
A237: =VLOOKUP(B237,'[1]PORTFOLIO RAW'!B:B,1,FALSE) -> 14015T | B237: 14015T | C237: FIDELITY NATNL INF - MARKET CAPITALIZATION | D237: 14015T(WC08001) | E237: 8097573 | F237: 3105943 | G237: 8778280 | H237: 8269041 | I237: 7788211 | J237: 10237621 | K237: 15599408 | L237: 17720780 | M237: 19664700 | N237: 24809920 | O237: 31331970 | P237: 33533850
A238: =VLOOKUP(B238,'[1]PORTFOLIO RAW'!B:B,1,FALSE) -> 905019 | B238: 905019 | C238: MERCK & CO INC - MARKET CAPITALIZATION | D238: 905019(WC08001) | E238: 126244143 | F238: 64073786 | G238: 113574452 | H238: 111079130 | I238: 114639617 | J238: 123910449 | K238: 146522712 | L238: 161177982 | M238: 146899185 | N238: 161817813 | O238: 151738335 | P238: 198097475
A239: =VLOOKUP(B239,'[1]PORTFOLIO RAW'!B:B,1,FALSE) -> 912090 | B239: 912090 | C239: SCHLUMBERGER LIMITED - MARKET CAPITALIZATION | D239: 912090(WC08001) | E239: 117612778 | F239: 50546289 | G239: 77770372 | H239: 113657814 | I239: 91110198 | J239: 92046266 | K239: 117803540 | L239: 108924432 | M239: 87606000 | N239: 116774450 | O239: 93267760 | P239: 49898640
A240: =VLOOKUP(B240,'[1]PORTFOLIO RAW'!B:B,1,FALSE) -> 755741 | B240: 755741 | C240: CHARLES SCHWAB CORP - MARKET CAPITALIZATION | D240: 755741(WC08001) | E240: 29658865 | F240: 18710307 | G240: 21871309 | H240: 20572760 | I240: 14313316 | J240: 18345318 | K240: 33719041 | L240: 39570705 | M240: 43478716 | N240: 52603638 | O240: 69109733 | P240: 55335683
A241: =VLOOKUP(B241,'[1]PORTFOLIO RAW'!B:B,1,FALSE) -> 14361V | B241: 14361V | C241: ZIMMER BIOMET - MARKET CAPITALIZATION | D241: 14361V(WC08001) | E241: 15406335 | F241: 9037912 | G241: 12070262 | H241: 10499808 | I241: 9508760 | J241: 11438856 | K241: 15823662 | L241: 19247374 | M241: 20794993 | N241: 20701920 | O241: 24447742 | P241: 21158880
A242: =VLOOKUP(B242,'[1]PORTFOLIO RAW'!B:B,1,FALSE) -> 154680 | B242: 154680 | C242: AMERISOURCEBERGEN - MARKET CAPITALIZATION | D242: 154680(WC08001) | E242: 7604394 | F242: 5570643 | G242: 7506133 | H242: 9469023 | I242: 9706272 | J242: 10164325 | K242: 16170893 | L242: 20007284 | M242: 21456756 | N242: 17205749 | O242: 20016172 | P242: 15863410
A243: =VLOOKUP(B243,'[1]PORTFOLIO RAW'!B:B,1,FALSE) -> 14698C | B243: 14698C | C243: PRINCIPAL FINL GROUP - MARKET CAPITALIZATION | D243: 14698C(WC08001) | E243: 17836444 | F243: 5852401 | G243: 7668760 | H243: 10432224 | I243: 7407060 | J243: 8379176 | K243: 14556312 | L243: 15265166 | M243: 13107172 | N243: 16646322 | O243: 20391840 | P243: 12345515
A244: =VLOOKUP(B244,'[1]PORTFOLIO RAW'!B:B,1,FALSE) -> 905361 | B244: 905361 | C244: SHERWIN-WILLIAMS CO - MARKET CAPITALIZATION | D244: 905361(WC08001) | E244: 7128139 | F244: 6992848 | G244: 6746783 | H244: 8962986 | I244: 9271067 | J244: 15885002 | K244: 18373741 | L244: 24910986 | M244: 23947198 | N244: 24996322 | O244: 38496050 | P244: 36637721
A245: =VLOOKUP(B245,'[1]PORTFOLIO RAW'!B:B,1,FALSE) -> 357834 | B245: 357834 | C245: SIMON PROPERTY GROUP - MARKET CAPITALIZATION | D245: 357834(WC08001) | E245: 19372758 | F245: 12290225 | G245: 22802712 | H245: 29545084 | I245: 37888793 | J245: 48991431 | K245: 47262199 | L245: 56597586 | M245: 60163735 | N245: 55623960 | O245: 53439796 | P245: 51911844
A246: =VLOOKUP(B246,'[1]PORTFOLIO RAW'!B:B,1,FALSE) -> 906400 | B246: 906400 | C246: SNAP-ON INC - MARKET CAPITALIZATION | D246: 906400(WC08001) | E246: 2770382 | F246: 2262064 | G246: 2440306 | H246: 3291912 | I246: 2947347 | J246: 4601546 | K246: 6364840 | L246: 7946433 | M246: 9957691 | N246: 9925072 | O246: 9881110 | P246: 8079690
A247: =VLOOKUP(B247,'[1]PORTFOLIO RAW'!B:B,1,FALSE) -> 14861V | B247: 14861V | C247: PRUDENTIAL FINANCIAL - MARKET CAPITALIZATION | D247: 14861V(WC08001) | E247: 41809092 | F247: 12809660 | G247: 23094171 | H247: 28521245 | I247: 23558337 | J247: 24800229 | K247: 42702955 | L247: 41325156 | M247: 36398522 | N247: 44701488 | O247: 48585054 | P247: 33493600
A248: =VLOOKUP(B248,'[1]PORTFOLIO RAW'!B:B,1,FALSE) -> 14806F | B248: 14806F | C248: ADVANCE AUTO PARTS - MARKET CAPITALIZATION | D248: 14806F(WC08001) | E248: 3763289 | F248: 3191770 | G248: 3789859 | H248: 5421389 | I248: 5068994 | J248: 5309260 | K248: 8061931 | L248: 11639227 | M248: 11034490 | N248: 12472431 | O248: 7370680 | P248: 11409552
A249: =VLOOKUP(B249,'[1]PORTFOLIO RAW'!B:B,1,FALSE) -> 902324 | B249: 902324 | C249: EDISON INTERNATIONAL - MARKET CAPITALIZATION | D249: 902324(WC08001) | E249: 17388544 | F249: 10465056 | G249: 11331714 | H249: 12576313 | I249: 13488584 | J249: 14723408 | K249: 15085059 | L249: 21334118 | M249: 19291282 | N249: 23455149 | O249: 20604301 | P249: 18496302
A250: =VLOOKUP(B250,'[1]PORTFOLIO RAW'!B:B,1,FALSE) -> 902325 | B250: 902325 | C250: SOUTHERN CO - MARKET CAPITALIZATION | D250: 902325(WC08001) | E250: 29589500 | F250: 28771200 | G250: 27305740 | H250: 32247005 | I250: 40046636 | J250: 37149148 | K250: 36476903 | L250: 44606613 | M250: 42373024 | N250: 48707938 | O250: 48046719 | P250: 43876080
A251: =VLOOKUP(B251,'[1]PORTFOLIO RAW'!B:B,1,FALSE) -> 992305 | B251: 992305 | C251: BB&T CORPORATION - MARKET CAPITALIZATION | D251: 992305(WC08001) | E251: 16744440 | F251: 15356950 | G251: 17498958 | H251: 18255276 | I251: 17547089 | J251: 20369082 | K251: 26371058 | L251: 28027945 | M251: 29504542 | N251: 38061515 | O251: 38881338 | P251: 33067282
A252: =VLOOKUP(B252,'[1]PORTFOLIO RAW'!B:B,1,FALSE) -> 905647 | B252: 905647 | C252: SOUTHWEST AIRLINES - MARKET CAPITALIZATION | D252: 905647(WC08001) | E252: 8964530 | F252: 6378736 | G252: 8490100 | H252: 9701697 | I252: 6613119 | J252: 7478472 | K252: 13196943 | L252: 28591142 | M252: 29091081 | N252: 32276465 | O252: 38520648 | P252: 25685004
A253: =VLOOKUP(B253,'[1]PORTFOLIO RAW'!B:B,1,FALSE) -> 945388 | B253: 945388 | C253: AT&T INC - MARKET CAPITALIZATION | D253: 945388(WC08001) | E253: 251169741 | F253: 167950500 | G253: 165431123 | H253: 173667732 | I253: 179217719 | J253: 188148817 | K253: 183757277 | L253: 174228406 | M253: 211447380 | N253: 261091413 | O253: 238700826 | P253: 207817678
A254: =VLOOKUP(B254,'[1]PORTFOLIO RAW'!B:B,1,FALSE) -> 905024 | B254: 905024 | C254: CHEVRON CORPORATION - MARKET CAPITALIZATION | D254: 905024(WC08001) | E254: 195100202 | F254: 148253025 | G254: 154574502 | H254: 183182621 | I254: 210796161 | J254: 210515910 | K254: 239028159 | L254: 210859003 | M254: 169377947 | N254: 222630306 | O254: 238449629 | P254: 207009712
A255: =VLOOKUP(B255,'[1]PORTFOLIO RAW'!B:B,1,FALSE) -> 951052 | B255: 951052 | C255: STATE STREET CORP - MARKET CAPITALIZATION | D255: 951052(WC08001) | E255: 31366261 | F255: 16973163 | G255: 21549415 | H255: 23246203 | I255: 19648056 | J255: 21561703 | K255: 31860697 | L255: 32592819 | M255: 26520906 | N255: 29684310 | O255: 35886303 | P255: 23963240
A256: =VLOOKUP(B256,'[1]PORTFOLIO RAW'!B:B,1,FALSE) -> 326143 | B256: 326143 | C256: STARBUCKS CORP - MARKET CAPITALIZATION | D256: 326143(WC08001) | E256: 15112700 | F256: 6957830 | G256: 17131274 | H256: 23859738 | I256: 34268248 | J256: 40184959 | K256: 59043348 | L256: 61496475 | M256: 89150553 | N256: 81086960 | O256: 82216788 | P256: 84306040
A257: =VLOOKUP(B257,'[1]PORTFOLIO RAW'!B:B,1,FALSE) -> 905792 | B257: 905792 | C257: PUBLIC STORAGE, INC - MARKET CAPITALIZATION | D257: 905792(WC08001) | E257: 12437304 | F257: 13378239 | G257: 13716631 | H257: 17165621 | I257: 22890310 | J257: 24844446 | K257: 25855767 | L257: 31876561 | M257: 42832591 | N257: 38730044 | O257: 36335354 | P257: 35245832
A258: =VLOOKUP(B258,'[1]PORTFOLIO RAW'!B:B,1,FALSE) -> 981722 | B258: 981722 | C258: STRYKER CORPORATION - MARKET CAPITALIZATION | D258: 981722(WC08001) | E258: 30709920 | F258: 15836180 | G258: 20042223 | H258: 21002070 | I258: 18939510 | J258: 20831600 | K258: 28402920 | L258: 35656740 | M258: 34666620 | N258: 44928750 | O258: 57972096 | P258: 58687200
A259: =VLOOKUP(B259,'[1]PORTFOLIO RAW'!B:B,1,FALSE) -> 922725 | B259: 922725 | C259: SUNTRUST BANKS INC - MARKET CAPITALIZATION | D259: 922725(WC08001) | E259: 21772214 | F259: 10472373 | G259: 10127763 | H259: 14767866 | I259: 9504316 | J259: 15279488 | K259: 19733731 | L259: 21978226 | M259: 21793222 | N259: 26941662 | O259: 30417433 | P259: 22541031
A260: =VLOOKUP(B260,'[1]PORTFOLIO RAW'!B:B,1,FALSE) -> 541900 | B260: 541900 | C260: SYMANTEC CORP - MARKET CAPITALIZATION | D260: 541900(WC08001) | E260: 14516590 | F260: 11348512 | G260: 14615683 | H260: 13358520 | I260: 11862700 | J260: 13625680 | K260: 16458840 | L260: 17830225 | M260: 14364000 | N260: 14620680 | O260: 17061013 | P260: 11790480
... A283: =VLOOKUP(B283,'[1]PORTFOLIO RAW'!B:B,1,FALSE) -> 904869 | B283: 904869 | C283: WHIRLPOOL CORP - MARKET CAPITALIZATION | D283: 904869(WC08001) | E283: 6203880 | F283: 3018550 | G283: 6049500 | H283: 6751080 | I283: 3606200 | J283: 8038250 | K283: 12078220 | L283: 15111720 | M283: 11308990 | N283: 13450980 | O283: 11973440 | P283: 6839680
A284: =VLOOKUP(B284,'[1]PORTFOLIO RAW'!B:B,1,FALSE) -> 26406N | B284: 26406N | C284: WYNN RESORTS, LTD - MARKET CAPITALIZATION | D284: 26406N(WC08001) | E284: 12824318 | F284: 4733671 | G284: 7179378 | H284: 12938413 | I284: 13820199 | J284: 11346496 | K284: 19652578 | L284: 15090110 | M284: 7027760 | N284: 8806672 | O284: 17365759 | P284: 10606320
A285: =VLOOKUP(B285,'[1]PORTFOLIO RAW'!B:B,1,FALSE) -> 26393N | B285: 26393N | C285: CME GROUP INC - MARKET CAPITALIZATION | D285: 26393N(WC08001) | E285: 36550766 | F285: 13822666 | G285: 22346077 | H285: 21509032 | I285: 16114174 | J285: 16814085 | K285: 26194271 | L285: 29738095 | M285: 30526867 | N285: 39016346 | O285: 49545730 | P285: 67126321
A286: =VLOOKUP(B286,'[1]PORTFOLIO RAW'!B:B,1,FALSE) -> 922407 | B286: 922407 | C286: WILLIAMS COMPANIES - MARKET CAPITALIZATION | D286: 922407(WC08001) | E286: 20967080 | F286: 8369440 | G286: 12289640 | H286: 14461200 | I286: 19514820 | J286: 22295940 | K286: 26343310 | L286: 33570180 | M286: 19249300 | N286: 23355000 | O286: 25184740 | P286: 26680500
A287: =VLOOKUP(B287,'[1]PORTFOLIO RAW'!B:B,1,FALSE) -> 906979 | B287: 906979 | C287: ALLIANT ENERGY CORP - MARKET CAPITALIZATION | D287: 906979(WC08001) | E287: 4490520 | F287: 3222905 | G287: 3348466 | H287: 4077569 | I287: 4897040 | J287: 4873457 | K287: 5724693 | L287: 7368348 | M287: 7085528 | N287: 8626555 | O287: 9857766 | P287: 9973674
A288: =VLOOKUP(B288,'[1]PORTFOLIO RAW'!B:B,1,FALSE) -> 877723 | B288: 877723 | C288: CARMAX INC - MARKET CAPITALIZATION | D288: 877723(WC08001) | E288: 4266556 | F288: 1722695 | G288: 5344506 | H288: 7111329 | I288: 6884996 | J288: 8526035 | K288: 10622105 | L288: 14759853 | M288: 11272697 | N288: 12537521 | O288: 11963362 | P288: 11275585
A289: =VLOOKUP(B289,'[1]PORTFOLIO RAW'!B:B,1,FALSE) -> 543542 | B289: 543542 | C289: XILINX INC - MARKET CAPITALIZATION | D289: 543542(WC08001) | E289: 6471377 | F289: 4998849 | G289: 6904205 | H289: 7925653 | I289: 8483140 | J289: 9453390 | K289: 12106762 | L289: 11629296 | M289: 12134230 | N289: 15315084 | O289: 16721980 | P289: 21580119
A290: =VLOOKUP(B290,'[1]PORTFOLIO RAW'!B:B,1,FALSE) -> 26276P | B290: 26276P | C290: CIMAREX ENERGY CO - MARKET CAPITALIZATION | D290: 26276P(WC08001) | E290: 3510497 | F290: 2229666 | G290: 4378320 | H290: 7545830 | I290: 5309416 | J290: 4999186 | K290: 9143137 | L290: 9284809 | M290: 8475063 | N290: 12927287 | O290: 11644321 | P290: 5903345
A291: =VLOOKUP(B291,'[1]PORTFOLIO RAW'!B:B,1,FALSE) -> 921855 | B291: 921855 | C291: TJX COMPANIES INC - MARKET CAPITALIZATION | D291: 921855(WC08001) | E291: 12294990 | F291: 8491740 | G291: 14963063 | H291: 17296889 | I291: 24099808 | J291: 30729640 | K291: 44930723 | L291: 46959003 | M291: 47048481 | N291: 48557950 | O291: 48017570 | P291: 54456745
A292: =VLOOKUP(B292,'[1]PORTFOLIO RAW'!B:B,1,FALSE) -> 951584 | B292: 951584 | C292: ZIONS BANCORP - MARKET CAPITALIZATION | D292: 951584(WC08001) | E292: 5001270 | F292: 2827070 | G292: 1929954 | H292: 4428858 | I292: 2997724 | J292: 3941863 | K292: 5532944 | L292: 5787955 | M292: 5580587 | N292: 8740783 | O292: 10040552 | P292: 7640950
A293: =VLOOKUP(B293,'[1]PORTFOLIO RAW'!B:B,1,FALSE) -> 951051 | B293: 951051 | C293: REGIONS FINANCIAL - MARKET CAPITALIZATION | D293: 951051(WC08001) | E293: 16404491 | F293: 5503273 | G293: 6308905 | H293: 8793655 | I293: 5412910 | J293: 10077111 | K293: 13625658 | L293: 14297627 | M293: 12454375 | N293: 17441377 | O293: 19596699 | P293: 13712175
A294: =VLOOKUP(B294,'[1]PORTFOLIO RAW'!B:B,1,FALSE) -> 29756N | B294: 29756N | C294: CELANESE CORPORATION - MARKET CAPITALIZATION | D294: 29756N(WC08001) | E294: 6436991 | F294: 1783776 | G294: 4635050 | H294: 6412610 | I294: 6926653 | J294: 8177010 | K294: 8680342 | L294: 9168046 | M294: 9882852 | N294: 11075604 | O294: 14538172 | P294: 11524784
A295: =VLOOKUP(B295,'[1]PORTFOLIO RAW'!B:B,1,FALSE) -> 905997 | B295: 905997 | C295: MOLSON COORS BREW - MARKET CAPITALIZATION | D295: 905997(WC08001) | E295: 9330443 | F295: 8864304 | G295: 8372664 | H295: 9375492 | I295: 7837200 | J295: 7766385 | K295: 10342830 | L295: 13823460 | M295: 17328240 | N295: 20911919 | O295: 17677878 | P295: 12136176
A296: =VLOOKUP(B296,'[1]PORTFOLIO RAW'!B:B,1,FALSE) -> 31604H | B296: 31604H | C296: AMERIPRISE FIN - MARKET CAPITALIZATION | D296: 31604H(WC08001) | E296: 12551184 | F296: 5057440 | G296: 9902982 | H296: 14197464 | I296: 11017250 | J296: 12772950 | K296: 22103211 | L296: 24216233 | M296: 18201360 | N296: 17169064 | O296: 24850177 | P296: 14228840
A297: =VLOOKUP(B297,'[1]PORTFOLIO RAW'!B:B,1,FALSE) -> 543487 | B297: 543487 | C297: VIACOM, INC. - MARKET CAPITALIZATION | D297: 543487(WC08001) | E297: 28319616 | F297: 11565608 | G297: 18058002 | H297: 24102685 | I297: 25352403 | J297: 26739180 | K297: 39241862 | L297: 31168550 | M297: 16385796 | N297: 13934700 | O297: 12397944 | P297: 10359670
A298: =VLOOKUP(B298,'[1]PORTFOLIO RAW'!B:B,1,FALSE) -> 32480Q | B298: 32480Q | C298: CBS CORPORATION - MARKET CAPITALIZATION | D298: 32480Q(WC08001) | E298: 18309275 | F298: 5493852 | G298: 9480940 | H298: 12957810 | I298: 17668140 | J298: 23971500 | K298: 37989040 | L298: 28057380 | M298: 21821190 | N298: 26211440 | O298: 22597000 | P298: 16307560
A299: =VLOOKUP(B299,'[1]PORTFOLIO RAW'!B:B,1,FALSE) -> 41071J | B299: 41071J | C299: HANESBRANDS, INC. - MARKET CAPITALIZATION | D299: 41071J(WC08001) | E299: 2587466 | F299: 1192382 | G299: 2300021 | H299: 2443658 | I299: 2131729 | J299: 3520027 | K299: 6988736 | L299: 11184020 | M299: 11526342 | N299: 8168280 | O299: 7530232 | P299: 4527467
A300: =VLOOKUP(B300,'[1]PORTFOLIO RAW'!B:B,1,FALSE) -> 41195M | B300: 41195M | C300: WESTERN UNION COMP - MARKET CAPITALIZATION | D300: 41195M(WC08001) | E300: 18205144 | F300: 10175664 | G300: 12940525 | H300: 12144780 | I300: 11310244 | J300: 7786281 | K300: 9466800 | L300: 9340065 | M300: 8997984 | N300: 10458180 | O300: 8725590 | P300: 7526872
A301: =VLOOKUP(B301,'[1]PORTFOLIO RAW'!B:B,1,FALSE) -> 517465 | B301: 517465 | C301: PEOPLE'S UNITED - MARKET CAPITALIZATION | D301: 517465(WC08001) | E301: 5309740 | F301: 6146001 | G301: 5761500 | H301: 5030991 | I301: 4593875 | J301: 4105764 | K301: 4641840 | L301: 4672404 | M301: 5008115 | N301: 6115824 | O301: 6481420 | P301: 5444439
A302: =VLOOKUP(B302,'[1]PORTFOLIO RAW'!B:B,1,FALSE) -> 905840 | B302: 905840 | C302: BANK OF NEW YORK - MARKET CAPITALIZATION | D302: 905840(WC08001) | E302: 55878145 | F302: 32536079 | G302: 33783137 | H302: 37494212 | I302: 24084621 | J302: 29901702 | K302: 39910208 | L302: 45366492 | M302: 44737838 | N302: 49629996 | O302: 54584010 | P302: 45207236
A303: =VLOOKUP(B303,'[1]PORTFOLIO RAW'!B:B,1,FALSE) -> 51245V | B303: 51245V | C303: INVESCO LTD. - MARKET CAPITALIZATION | D303: 51245V(WC08001) | E303: 13327086 | F303: 5409224 | G303: 10793655 | H303: 11070006 | I303: 8767276 | J303: 11250008 | K303: 15419040 | L303: 16637920 | M303: 13696668 | N303: 12252432 | O303: 14877175 | P303: 6646980
A304: =VLOOKUP(B304,'[1]PORTFOLIO RAW'!B:B,1,FALSE) -> 328314 | B304: 328314 | C304: CHUBB - MARKET CAPITALIZATION | D304: 328314(WC08001) | E304: 20369146 | F304: 17656518 | G304: 16960843 | H304: 20850193 | I304: 23625341 | J304: 27157658 | K304: 35178866 | L304: 37756425 | M304: 37925238 | N304: 61563787 | O304: 67779942 | P304: 59319892
A305: =VLOOKUP(B305,'[1]PORTFOLIO RAW'!B:B,1,FALSE) -> 31196R | B305: 31196R | C305: DISCOVERY INC - MARKET CAPITALIZATION | D305: 31196R(WC08001) | E305: NA | F305: 3993120 | G305: 8710280 | H305: 11842800 | I305: 10693170 | J305: 15571644 | K305: 21266784 | L305: 15120105 | M305: 11152240 | N305: 10689900 | O305: 8504400 | P305: 12889540
A306: =VLOOKUP(B306,'[1]PORTFOLIO RAW'!B:B,1,FALSE) -> 771767 | B306: 771767 | C306: MOSAIC CO - MARKET CAPITALIZATION | D306: 771767(WC08001) | E306: 41586513 | F306: 15359805 | G306: 26550779 | H306: 34013798 | I306: 22520663 | J306: 24094387 | K306: 20137301 | L306: 16778214 | M306: 9725896 | N306: 10272497 | O306: 9007934 | P306: 11259581
A307: =VLOOKUP(B307,'[1]PORTFOLIO RAW'!B:B,1,FALSE) -> 921503 | B307: 921503 | C307: STANLEY BLACK - MARKET CAPITALIZATION | D307: 921503(WC08001) | E307: 3896764 | F307: 2689673 | G307: 4145454 | H307: 11123653 | I307: 11427575 | J307: 11831651 | K307: 12545619 | L307: 15096613 | M307: 16430474 | N307: 17497080 | O307: 26138713 | P307: 18116955
A308: =VLOOKUP(B308,'[1]PORTFOLIO RAW'!B:B,1,FALSE) -> 255781 | B308: 255781 | C308: GARMIN LTD. - MARKET CAPITALIZATION | D308: 255781(WC08001) | E308: 21047060 | F308: 3840959 | G308: 6148412 | H308: 6023156 | I308: 7749519 | J308: 7970368 | K308: 9013983 | L308: 10133586 | M308: 7051967 | N308: 9143517 | O308: 11210419 | P308: 11996671
A309: =VLOOKUP(B309,'[1]PORTFOLIO RAW'!B:B,1,FALSE) -> 670129 | B309: 670129 | C309: PROLOGIS - MARKET CAPITALIZATION | D309: 670129(WC08001) | E309: 5710557 | F309: 2306164 | G309: 3813552 | H309: 5350621 | I309: 13111288 | J309: 16849987 | K309: 18430623 | L309: 21923699 | M309: 22512055 | N309: 27908542 | O309: 34331319 | P309: 36971052
A310: =VLOOKUP(B310,'[1]PORTFOLIO RAW'!B:B,1,FALSE) -> 14352P | B310: 14352P | C310: ACCENTURE PLC - MARKET CAPITALIZATION | D310: 14352P(WC08001) | E310: 27330590 | F310: 23976484 | G310: 29584317 | H310: 33459247 | I310: 36771251 | J310: 45003917 | K310: 54787741 | L310: 58637023 | M310: 67928811 | N310: 75266594 | O310: 97378767 | P310: 90202687
A311: =VLOOKUP(B311,'[1]PORTFOLIO RAW'!B:B,1,FALSE) -> 749688 | B311: 749688 | C311: HCA HEALTHCARE - MARKET CAPITALIZATION | D311: 749688(WC08001) | E311: NA | F311: NA | G311: NA | H311: NA | I311: 9637638 | J311: 13371350 | K311: 20973507 | L311: 30858873 | M311: 26966698 | N311: 27427067 | O311: 30752046 | P311: 42673308
A312: =VLOOKUP(B312,'[1]PORTFOLIO RAW'!B:B,1,FALSE) -> 894145 | B312: 894145 | C312: RALPH LAUREN - MARKET CAPITALIZATION | D312: 894145(WC08001) | E312: 6426160 | F312: 4518295 | G312: 8033216 | H312: 10892344 | I312: 13048560 | J312: 13897584 | K312: 16050213 | L312: 16423692 | M312: 9620724 | N312: 7487528 | O312: 8398890 | P312: 8411298
A313: =VLOOKUP(B313,'[1]PORTFOLIO RAW'!B:B,1,FALSE) -> 26599V | B313: 26599V | C313: SEAGATE TECHNOLOGY - MARKET CAPITALIZATION | D313: 26599V(WC08001) | E313: 13642027 | F313: 2149115 | G313: 8967830 | H313: 7067719 | I313: 6963630 | J313: 12047321 | K313: 20185984 | L313: 21714865 | M313: 11564233 | N313: 11396502 | O313: 12208894 | P313: 11081904
A314: =VLOOKUP(B314,'[1]PORTFOLIO RAW'!B:B,1,FALSE) -> 904878 | B314: 904878 | C314: MOTOROLA SOLUTIONS - MARKET CAPITALIZATION | D314: 904878(WC08001) | E314: 36300124 | F314: 10084895 | G314: 17941896 | H314: 21351260 | I314: 14757252 | J314: 15373248 | K314: 17178750 | L314: 14744184 | M314: 11930835 | N314: 13651983 | O314: 14562808 | P314: 18809040
...

Sheet NI
A1: Net Income
B2: Name | C2: Code | D2: Name | E2: Code | F2: 2007 | G2: 2008 | H2: 2009 | I2: 2010 | J2: 2011 | K2: 2012 | L2: 2013 | M2: 2014 | N2: 2015 | O2: 2016 | P2: 2017
A3: 902172 | B3: 3M COMPANY | C3: 902172 | D3: 3M COMPANY - NET INCOME - BASIC | E3: 902172(WC01706) | F3: 4096000 | G3: 3460000 | H3: 3193000 | I3: 4085000 | J3: 4283000 | K3: 4444000 | L3: 4659000 | M3: 4956000 | N3: 4833000 | O3: 5050000 | P3: 5620000
A4: 916328 | B4: ABBOTT LABORATORIES | C4: 916328 | D4: ABBOTT LABORATORIES - NET INCOME - BASIC | E4: 916328(WC01706) | F4: 3606314 | G4: 4734216 | H4: 5745838 | I4: 4626172 | J4: 4728449 | K4: 5962920 | L4: 2576000 | M4: 2284000 | N4: 2671000 | O4: 1384000 | P4: 1937000
A5: 14352P | B5: ACCENTURE PLC | C5: 14352P | D5: ACCENTURE PLC - NET INCOME - BASIC | E5: 14352P(WC01706) | F5: 1243148 | G5: 1691751 | H5: 1589963 | I5: 1780656 | J5: 2277677 | K5: 2553510 | L5: 3281878 | M5: 2941498 | N5: 3053581 | O5: 4111892 | P5: 3445149
A6: 312367 | B6: ACTIVISION BLIZZARD | C6: 312367 | D6: ACTIVISION BLIZZARD - NET INCOME - BASIC | E6: 312367(WC01706) | F6: 227000 | G6: -107000 | H6: 113000 | I6: 414000 | J6: 1069000 | K6: 1125000 | L6: 998000 | M6: 847000 | N6: 881000 | O6: 962000 | P6: 909000
A7: 749382 | B7: ADOBE INC | C7: 749382 | D7: ADOBE INC - NET INCOME - BASIC | E7: 749382(WC01706) | F7: 723807 | G7: 871814 | H7: 386508 | I7: 774680 | J7: 832847 | K7: 832775 | L7: 289985 | M7: 268395 | N7: 629551 | O7: 1168782 | P7: 1693954
A8: 14806F | B8: ADVANCE AUTO PARTS | C8: 14806F | D8: ADVANCE AUTO PARTS - NET INCOME - BASIC | E8: 14806F(WC01706) | F8: 238317 | G8: 238038 | H8: 270373 | I8: 344501 | J8: 393627 | K8: 386800 | L8: 390863 | M8: 492270 | N8: 471745 | O8: 457677 | P8: 331705
A9: 936365 | B9: ADVANCED MICRO | C9: 936365 | D9: ADVANCED MICRO - NET INCOME - BASIC | E9: 936365(WC01706) | F9: -3379000 | G9: -3098000 | H9: 304000 | I9: 471000 | J9: 491000 | K9: -1183000 | L9: -83000 | M9: -403000 | N9: -660000 | O9: -497000 | P9: -1087000
A10: 545101 | B10: AES CORP | C10: 545101 | D10: AES CORP - NET INCOME - BASIC | E10: 545101(WC01706) | F10: 495000 | G10: 1228000 | H10: 808000 | I10: -55000 | J10: -28000 | K10: -928000 | L10: 266000 | M10: 825000 | N10: 306000 | O10: -11000 | P10: -511000
A11: 933185 | B11: AFLAC INCORPORATED | C11: 933185 | D11: AFLAC INCORPORATED - NET INCOME - BASIC | E11: 933185(WC01706) | F11: 1634000 | G11: 1254000 | H11: 1497000 | I11: 2344000 | J11: 1964000 | K11: 2866000 | L11: 3158000 | M11: 2951000 | N11: 2533000 | O11: 2659000 | P11: 2671000
A12: 277642 | B12: AGILENT TECHNOLOGIES | C12: 277642 | D12: AGILENT TECHNOLOGIES - NET INCOME - BASIC | E12: 277642(WC01706) | F12: 638000 | G12: 693000 | H12: -31000 | I12: 684000 | J12: 1012000 | K12: 1153000 | L12: 724000 | M12: 504000 | N12: 401000 | O12: 462000 | P12: 684000
A13: 905271 | B13: AIR PRODUCTS & CHEMS | C13: 905271 | D13: AIR PRODUCTS & CHEMS - NET INCOME - BASIC | E13: 905271(WC01706) | F13: 1042700 | G13: 1090500 | H13: 631400 | I13: 1029100 | J13: 1224200 | K13: 1046500 | L13: 994200 | M13: 991700 | N13: 1277900 | O13: 631100 | P13: 1219900
A14: 277355 | B14: AKAMAI TECHNOLOGIES | C14: 277355 | D14: AKAMAI TECHNOLOGIES - NET INCOME - BASIC | E14: 277355(WC01706) | F14: 100967 | G14: 145138 | H14: 145913 | I14: 171220 | J14: 200904 | K14: 203989 | L14: 293487 | M14: 333948 | N14: 321406 | O14: 316132 | P14: 244321
A15: 130298 | B15: ALBEMARLE CORP | C15: 130298 | D15: ALBEMARLE CORP - NET INCOME - BASIC | E15: 130298(WC01706) | F15: 229690 | G15: 194202 | H15: 178368 | I15: 323720 | J15: 436280 | K15: 311536 | L15: 413171 | M15: 133316 | N15: 334906 | O15: 643675 | P15: 474350
A16: 325596 | B16: ALLERGAN PLC | C16: 325596 | D16: ALLERGAN PLC - NET INCOME - BASIC | E16: 325596(WC01706) | F16: 141030 | G16: 238379 | H16: 222000 | I16: 184400 | J16: 260900 | K16: 97300 | L16: -750400 | M16: -1630500 | N16: 3683200 | O16: 14695000 | P16: -7203900
A17: 906979 | B17: ALLIANT ENERGY CORP | C17: 906979 | D17: ALLIANT ENERGY CORP - NET INCOME - BASIC | E17: 906979(WC01706) | F17: 424700 | G17: 288000 | H17: 111000 | I17: 287600 | J17: 303600 | K17: 319800 | L17: 358300 | M17: 383100 | N17: 378200 | O17: 371500 | P17: 439200
A18: 322677 | B18: ALLSTATE CORP | C18: 322677 | D18: ALLSTATE CORP - NET INCOME - BASIC | E18: 322677(WC01706) | F18: 4636000 | G18: -1679000 | H18: 854000 | I18: 928000 | J18: 788000 | K18: 2306000 | L18: 2263000 | M18: 2746000 | N18: 2055000 | O18: 1761000 | P18: 2567000
A19: 29026M | B19: ALPHABET INC | C19: 29026M | D19: ALPHABET INC - NET INCOME - BASIC | E19: 29026M(WC01706) | F19: 4203720 | G19: 4226858 | H19: 6520448 | I19: 8505000 | J19: 9737000 | K19: 10737000 | L19: 12920000 | M19: 14444000 | N19: 15826000 | O19: 19478000 | P19: 22486000
A20: 904853 | B20: ALTRIA GROUP INC | C20: 904853 | D20: ALTRIA GROUP INC - NET INCOME - BASIC | E20: 904853(WC01706) | F20: 9786000 | G20: 3090000 | H20: 3206000 | I20: 3890000 | J20: 3377000 | K20: 4167000 | L20: 4523000 | M20: 5058000 | N20: 5231000 | O20: 14215000 | P20: 6841000
A21: 891399 | B21: AMAZON.COM INC | C21: 891399 | D21: AMAZON.COM INC - NET INCOME - BASIC | E21: 891399(WC01706) | F21: 476000 | G21: 645000 | H21: 902000 | I21: 1152000 | J21: 631000 | K21: -39000 | L21: 274000 | M21: -241000 | N21: 596000 | O21: 2371000 | P21: 2244000
A22: 670942 | B22: AMEREN CORPORATION | C22: 670942 | D22: AMEREN CORPORATION - NET INCOME - BASIC | E22: 670942(WC01706) | F22: 618000 | G22: 607000 | H22: 612000 | I22: 139000 | J22: 519000 | K22: -974000 | L22: 289000 | M22: 586000 | N22: 630000 | O22: 653000 | P22: 677000
A23: 905425 | B23: AMERICAN ELECTRIC | C23: 905425 | D23: AMERICAN ELECTRIC - NET INCOME - BASIC | E23: 905425(WC01706) | F23: 1144000 | G23: 1380000 | H23: 1362000 | I23: 1211000 | J23: 1568000 | K23: 1259000 | L23: 1480000 | M23: 1634000 | N23: 2047100 | O23: 610900 | P23: 1885900
A24: 906156 | B24: AMERICAN EXPRESS CO | C24: 906156 | D24: AMERICAN EXPRESS CO - NET INCOME - BASIC | E24: 906156(WC01706) | F24: 4012000 | G24: 2688000 | H24: 1802000 | I24: 4006000 | J24: 4877000 | K24: 4433000 | L24: 5312000 | M24: 5839000 | N24: 5063000 | O24: 5285000 | P24: 5234000
A25: 916305 | B25: AMERICAN INT'L GROUP | C25: 916305 | D25: AMERICAN INT'L GROUP - NET INCOME - BASIC | E25: 916305(WC01706) | F25: 6200000 | G25: -99689000 | H25: -12244000 | I25: 1583000 | J25: 16986000 | K25: 3438000 | L25: 9085000 | M25: 7529000 | N25: 2196000 | O25: -849000 | P25: 616000
A26: 680902 | B26: AMERICAN TOWER CORP | C26: 680902 | D26: AMERICAN TOWER CORP - NET INCOME - BASIC | E26: 680902(WC01706) | F26: 56316 | G26: 347246 | H26: 246595 | I26: 372936 | J26: 396462 | K26: 637283 | L26: 551333 | M26: 801022 | N26: 594911 | O26: 849300 | P26: 1151500
A27: 31604H | B27: AMERIPRISE FIN | C27: 31604H | D27: AMERIPRISE FIN - NET INCOME - BASIC | E27: 31604H(WC01706) | F27: 814000 | G27: -38000 | H27: 722000 | I27: 1097000 | J27: 1050000 | K27: 1036000 | L27: 1334000 | M27: 1619000 | N27: 1562000 | O27: 1314000 | P27: 1766000
A28: 154680 | B28: AMERISOURCEBERGEN | C28: 154680 | D28: AMERISOURCEBERGEN - NET INCOME - BASIC | E28: 154680(WC01706) | F28: 493768 | G28: 469064 | H28: 511852 | I28: 636748 | J28: 706624 | K28: 718986 | L28: 433707 | M28: 276484 | N28: -134887 | O28: 1427929 | P28: 364484
A29: 938692 | B29: AMGEN INC | C29: 938692 | D29: AMGEN INC - NET INCOME - BASIC | E29: 938692(WC01706) | F29: 3166000 | G29: 4196000 | H29: 4605000 | I29: 4627000 | J29: 3683000 | K29: 4345000 | L29: 5081000 | M29: 5158000 | N29: 6939000 | O29: 7722000 | P29: 8079000
A30: 546075 | B30: AMPHENOL CORP | C30: 546075 | D30: AMPHENOL CORP - NET INCOME - BASIC | E30: 546075(WC01706) | F30: 353194 | G30: 419151 | H30: 317834 | I30: 496405 | J30: 524191 | K30: 555317 | L30: 635672 | M30: 709100 | N30: 763500 | O30: 822900 | P30: 1049000
A31: 905276 | B31: ANALOG DEVICES, INC. | C31: 905276 | D31: ANALOG DEVICES, INC. - NET INCOME - BASIC | E31: 905276(WC01706) | F31: 496907 | G31: 525177 | H31: 247772 | I31: 711225 | J31: 860894 | K31: 651236 | L31: 673487 | M31: 629320 | N31: 696878 | O31: 861664 | P31: 725016
A32: 14737P | B32: ANTHEM INC | C32: 14737P | D32: ANTHEM INC - NET INCOME - BASIC | E32: 14737P(WC01706) | F32: 3345400 | G32: 2490700 | H32: 4745900 | I32: 2887100 | J32: 2646700 | K32: 2655500 | L32: 2489700 | M32: 2569700 | N32: 2560000 | O32: 2469800 | P32: 2734500
A33: 922817 | B33: AON PLC | C33: 922817 | D33: AON PLC - NET INCOME - BASIC | E33: 922817(WC01706) | F33: 864000 | G33: 651000 | H33: 639000 | I33: 733000 | J33: 975000 | K33: 993000 | L33: 1113000 | M33: 1397000 | N33: 1385000 | O33: 1396000 | P33: 1576000
A34: 921983 | B34: APACHE CORPORATION | C34: 921983 | D34: APACHE CORPORATION - NET INCOME - BASIC | E34: 921983(WC01706) | F34: 2806678 | G34: 706274 | H34: -291692 | I34: 3000000 | J34: 4508000 | K34: 1925000 | L34: 2188000 | M34: -5403000 | N34: -23119000 | O34: -1405000 | P34: 1417000
A35: 992816 | B35: APPLE INC | C35: 992816 | D35: APPLE INC - NET INCOME - BASIC | E35: 992816(WC01706) | F35: 3496000 | G35: 4834000 | H35: 8235000 | I35: 14013000 | J35: 25922000 | K35: 41733000 | L35: 37037000 | M35: 39510000 | N35: 53394000 | O35: 45687000 | P35: 48351000
A36: 905296 | B36: APPLIED MATERIALS | C36: 905296 | D36: APPLIED MATERIALS - NET INCOME - BASIC | E36: 905296(WC01706) | F36: 1710196 | G36: 960746 | H36: -305327 | I36: 937866 | J36: 1926000 | K36: 109000 | L36: 256000 | M36: 1072000 | N36: 1377000 | O36: 1721000 | P36: 3434000
A37: 132808 | B37: APT INVESTMENT & MGT | C37: 132808 | D37: APT INVESTMENT & MGT - NET INCOME - BASIC | E37: 132808(WC01706) | F37: -114070 | G37: 361755 | H37: -114840 | I37: -125318 | J37: -103161 | K37: 82146 | L37: 203673 | M37: 11584 | N37: 55373 | O37: 23991 | P37: -8592
A38: 921093 | B38: ARCHER DANIELS MIDL. | C38: 921093 | D38: ARCHER DANIELS MIDL. - NET INCOME - BASIC | E38: 921093(WC01706) | F38: 2162000 | G38: 1802000 | H38: 1707000 | I38: 1930000 | J38: 2036000 | K38: 1146000 | L38: 1342000 | M38: 2248000 | N38: 1849000 | O38: 1279000 | P38: 1216000
A39: 905113 | B39: ARCONIC INC | C39: 905113 | D39: ARCONIC INC - NET INCOME - BASIC | E39: 905113(WC01706) | F39: 2569000 | G39: -76000 | H39: -1153000 | I39: 253000 | J39: 608000 | K39: 189000 | L39: -2287000 | M39: 247000 | N39: -391000 | O39: -1010000 | P39: 145000
A40: 28341F | B40: ASSURANT INC | C40: 28341F | D40: ASSURANT INC - NET INCOME - BASIC | E40: 28341F(WC01706) | F40: 653746 | G40: 447796 | H40: 430574 | I40: 279177 | J40: 545839 | K40: 483705 | L40: 488907 | M40: 470907 | N40: 141555 | O40: 565350 | P40: 342600
A41: 945388 | B41: AT&T INC | C41: 945388 | D41: AT&T INC - NET INCOME - BASIC | E41: 945388(WC01706) | F41: 11951000 | G41: 12867000 | H41: 12535000 | I41: 19095000 | J41: 3944000 | K41: 7264000 | L41: 18249000 | M41: 6224000 | N41: 13345000 | O41: 12976000 | P41: 9179000
A42: 702259 | B42: AUTODESK INC | C42: 702259 | D42: AUTODESK INC - NET INCOME - BASIC | E42: 702259(WC01706) | F42: 356200 | G42: 183600 | H42: 58000 | I42: 212000 | J42: 285300 | K42: 247400 | L42: 228800 | M42: 81800 | N42: -330500 | O42: -582100 | P42: -158500
A43: 912669 | B43: AUTOMATIC DATA PROC | C43: 912669 | D43: AUTOMATIC DATA PROC - NET INCOME - BASIC | E43: 912669(WC01706) | F43: 1021200 | G43: 1161700 | H43: 1328200 | I43: 1210900 | J43: 1254200 | K43: 1388500 | L43: 1405800 | M43: 1515900 | N43: 1374100 | O43: 1492500 | P43: 1733400
A44: 544616 | B44: AUTOZONE INC | C44: 544616 | D44: AUTOZONE INC - NET INCOME - BASIC | E44: 544616(WC01706) | F44: 595672 | G44: 641606 | H44: 657049 | I44: 738311 | J44: 848974 | K44: 930373 | L44: 1016480 | M44: 1069744 | N44: 1160241 | O44: 1241007 | P44: 1280869
A45: 130502 | B45: AVALONBAY COMMUNITIE | C45: 130502 | D45: AVALONBAY COMMUNITIE - NET INCOME - BASIC | E45: 130502(WC01706) | F45: 238968 | G45: 116132 | H45: 91760 | I45: 100759 | J45: 158901 | K45: 276294 | L45: 74347 | M45: 644175 | N45: 740264 | O45: 1031392 | P45: 874458
A46: 921161 | B46: AVERY DENNISON CORP | C46: 921161 | D46: AVERY DENNISON CORP - NET INCOME - BASIC | E46: 921161(WC01706) | F46: 303500 | G46: 266100 | H46: -746700 | I46: 316900 | J46: 190100 | K46: 215400 | L46: 215800 | M46: 251100 | N46: 274400 | O46: 320700 | P46: 453800
A47: 921431 | B47: BAKER HUGHES A GE CO | C47: 921431 | D47: BAKER HUGHES A GE CO - NET INCOME - BASIC | E47: 921431(WC01706) | F47: 1513900 | G47: 1635000 | H47: 421000 | I47: 812000 | J47: 1739000 | K47: 1311000 | L47: 1096000 | M47: 1719000 | N47: -1967000 | O47: -2738000 | P47: -205000
A48: 932060 | B48: BALL CORPORATION | C48: 932060 | D48: BALL CORPORATION - NET INCOME - BASIC | E48: 932060(WC01706) | F48: 281300 | G48: 319500 | H48: 387900 | I48: 468000 | J48: 444000 | K48: 403500 | L48: 406800 | M48: 470000 | N48: 280900 | O48: 263000 | P48: 457000
A49: 923937 | B49: BANK OF AMERICA CORP | C49: 923937 | D49: BANK OF AMERICA CORP - NET INCOME - BASIC | E49: 923937(WC01706) | F49: 14800000 | G49: 2556000 | H49: -2210000 | I49: -3599000 | J49: 84000 | K49: 2758000 | L49: 10080000 | M49: 3789000 | N49: 14405000 | O49: 16224000 | P49: 18571000
A50: 905840 | B50: BANK OF NEW YORK | C50: 905840 | D50: BANK OF NEW YORK - NET INCOME - BASIC | E50: 905840(WC01706) | F50: 2227000 | G50: 1412000 | H50: -1367000 | I50: 2518000 | J50: 2480000 | K50: 2397000 | L50: 2009000 | M50: 2451000 | N50: 3010000 | O50: 3373000 | P50: 3162000
A51: 916365 | B51: BAXTER INTERNATIONAL | C51: 916365 | D51: BAXTER INTERNATIONAL - NET INCOME - BASIC | E51: 916365(WC01706) | F51: 1707000 | G51: 2014000 | H51: 2205000 | I51: 1420000 | J51: 2224000 | K51: 2326000 | L51: 2012000 | M51: 2497000 | N51: 968000 | O51: 4965000 | P51: 1302000
A52: 992305 | B52: BB&T CORPORATION | C52: 992305 | D52: BB&T CORPORATION - NET INCOME - BASIC | E52: 992305(WC01706) | F52: 1734000 | G52: 1498000 | H52: 729000 | I52: 816000 | J52: 1289000 | K52: 1916000 | L52: 1562000 | M52: 2003000 | N52: 1936000 | O52: 2259000 | P52: 2177000
... A69: 902224 | B69: CATERPILLAR INC | C69: 902224 | D69: CATERPILLAR INC - NET INCOME - BASIC | E69: 902224(WC01706) | F69: 3541000 | G69: 3557000 | H69: 895000 | I69: 2700000 | J69: 4928000 | K69: 5681000 | L69: 3789000 | M69: 3695000 | N69: 2102000 | O69: -67000 | P69: 3125000
A70: 28513N | B70: CBRE GROUP | C70: 28513N | D70: CBRE GROUP - NET INCOME - BASIC | E70: 28513N(WC01706) | F70: 390505 | G70: -1012066 | H70: 33341 | I70: 200345 | J70: 239162 | K70: 315555 | L70: 316538 | M70: 484503 | N70: 547132 | O70: 571973 | P70: 834879
A71: 32480Q | B71: CBS CORPORATION | C71: 32480Q | D71: CBS CORPORATION - NET INCOME - BASIC | E71: 32480Q(WC01706) | F71: 1230800 | G71: -11673400 | H71: 226500 | I71: 724200 | J71: 1305000 | K71: 1574000 | L71: 1879000 | M71: 2959000 | N71: 1413000 | O71: 1261000 | P71: 486000
A72: 29756N | B72: CELANESE CORPORATION | C72: 29756N | D72: CELANESE CORPORATION - NET INCOME - BASIC | E72: 29756N(WC01706) | F72: 326000 | G72: 362000 | H72: 478000 | I72: 374000 | J72: 607000 | K72: 605000 | L72: 1101000 | M72: 624000 | N72: 304000 | O72: 900000 | P72: 933000
A73: 755790 | B73: CELGENE CORPORATION | C73: 755790 | D73: CELGENE CORPORATION - NET INCOME - BASIC | E73: 755790(WC01706) | F73: 226433 | G73: -1533653 | H73: 776747 | I73: 880512 | J73: 1318150 | K73: 1456180 | L73: 1449900 | M73: 1999900 | N73: 1602000 | O73: 1999200 | P73: 4209000
A74: 904842 | B74: CENTERPOINT ENERGY | C74: 904842 | D74: CENTERPOINT ENERGY - NET INCOME - BASIC | E74: 904842(WC01706) | F74: 399000 | G74: 447000 | H74: 372000 | I74: 442000 | J74: 770000 | K74: 417000 | L74: 311000 | M74: 611000 | N74: -692000 | O74: 432000 | P74: 679000
A75: 755741 | B75: CHARLES SCHWAB CORP | C75: 755741 | D75: CHARLES SCHWAB CORP - NET INCOME - BASIC | E75: 755741(WC01706) | F75: 1120000 | G75: 1212000 | H75: 787000 | I75: 454000 | J75: 864000 | K75: 883000 | L75: 1010000 | M75: 1261000 | N75: 1364000 | O75: 1746000 | P75: 2226000
A76: 905024 | B76: CHEVRON CORPORATION | C76: 905024 | D76: CHEVRON CORPORATION - NET INCOME - BASIC | E76: 905024(WC01706) | F76: 18688000 | G76: 23931000 | H76: 10483000 | I76: 19024000 | J76: 26895000 | K76: 26179000 | L76: 21423000 | M76: 19241000 | N76: 4587000 | O76: -497000 | P76: 7175000
A77: 328314 | B77: CHUBB | C77: 328314 | D77: CHUBB - NET INCOME - BASIC | E77: 328314(WC01706) | F77: 2533000 | G77: 1173000 | H77: 2549000 | I77: 3108000 | J77: 1585000 | K77: 2706000 | L77: 3758000 | M77: 2853000 | N77: 2834000 | O77: 4135000 | P77: 3411000
A78: 912278 | B78: CIGNA CORP | C78: 912278 | D78: CIGNA CORP - NET INCOME - BASIC | E78: 912278(WC01706) | F78: 1115000 | G78: 292000 | H78: 1302000 | I78: 1345000 | J78: 1327000 | K78: 1623000 | L78: 1476000 | M78: 2102000 | N78: 2094000 | O78: 1867000 | P78: 2469000
A79: 26276P | B79: CIMAREX ENERGY CO | C79: 26276P | D79: CIMAREX ENERGY CO - NET INCOME - BASIC | E79: 26276P(WC01706) | F79: 346469 | G79: -901685 | H79: -311943 | I79: 574782 | J79: 529932 | K79: 347070 | L79: 553598 | M79: 497298 | N79: -2408948 | O79: -431049 | P79: 424632
A80: 944777 | B80: CINTAS CORPORATION | C80: 944777 | D80: CINTAS CORPORATION - NET INCOME - BASIC | E80: 944777(WC01706) | F80: 334538 | G80: 335405 | H80: 226357 | I80: 214959 | J80: 245892 | K80: 295757 | L80: 313546 | M80: 370990 | N80: 426741 | O80: 686115 | P80: 459740
A81: 542868 | B81: CISCO SYSTEMS, INC. | C81: 542868 | D81: CISCO SYSTEMS, INC. - NET INCOME - BASIC | E81: 542868(WC01706) | F81: 7333000 | G81: 8052000 | H81: 6134000 | I81: 7767000 | J81: 6490000 | K81: 8041000 | L81: 9983000 | M81: 7853000 | N81: 8981000 | O81: 10739000 | P81: 9609000
A82: 741344 | B82: CITIGROUP INC | C82: 741344 | D82: CITIGROUP INC - NET INCOME - BASIC | E82: 741344(WC01706) | F82: 3581000 | G82: -29416000 | H82: -9246000 | I82: 10503000 | J82: 10760000 | K82: 7350000 | L82: 13216000 | M82: 6691000 | N82: 16249000 | O82: 13640000 | P82: 14552000
A83: 867705 | B83: CITRIX SYSTEMS INC | C83: 867705 | D83: CITRIX SYSTEMS INC - NET INCOME - BASIC | E83: 867705(WC01706) | F83: 214483 | G83: 178276 | H83: 191017 | I83: 277065 | J83: 356322 | K83: 352547 | L83: 339523 | M83: 251723 | N83: 319361 | O83: 536112 | P83: 408681
A84: 916125 | B84: CLOROX CO | C84: 916125 | D84: CLOROX CO - NET INCOME - BASIC | E84: 916125(WC01706) | F84: 496000 | G84: 461000 | H84: 537000 | I84: 600000 | J84: 308000 | K84: 543000 | L84: 572000 | M84: 558000 | N84: 580000 | O84: 648000 | P84: 701000
A85: 26393N | B85: CME GROUP INC | C85: 26393N | D85: CME GROUP INC - NET INCOME - BASIC | E85: 26393N(WC01706) | F85: 658533 | G85: 715486 | H85: 825800 | I85: 951400 | J85: 1812300 | K85: 896300 | L85: 976800 | M85: 1127100 | N85: 1247000 | O85: 1534100 | P85: 1463400
A86: 901686 | B86: CMS ENERGY CORP | C86: 901686 | D86: CMS ENERGY CORP - NET INCOME - BASIC | E86: 901686(WC01706) | F86: -227000 | G86: 289000 | H86: 218000 | I86: 324000 | J86: 415000 | K86: 382000 | L86: 452000 | M86: 477000 | N86: 523000 | O86: 551000 | P86: 608000
A87: 904282 | B87: COCA-COLA | C87: 904282 | D87: COCA-COLA - NET INCOME - BASIC | E87: 904282(WC01706) | F87: 5981000 | G87: 5807000 | H87: 6824000 | I87: 11809000 | J87: 8572000 | K87: 9019000 | L87: 8584000 | M87: 7098000 | N87: 7351000 | O87: 6527000 | P87: 4858000
A88: 906148 | B88: COLGATE-PALMOLIVE CO | C88: 906148 | D88: COLGATE-PALMOLIVE CO - NET INCOME - BASIC | E88: 906148(WC01706) | F88: 1709400 | G88: 1928700 | H88: 2261000 | I88: 2169000 | J88: 2431000 | K88: 2472000 | L88: 2241000 | M88: 2180000 | N88: 1384000 | O88: 2441000 | P88: 2299000
A89: 981550 | B89: COMCAST CORPORATION | C89: 981550 | D89: COMCAST CORPORATION - NET INCOME - BASIC | E89: 981550(WC01706) | F89: 2587000 | G89: 2547000 | H89: 3638000 | I89: 3635000 | J89: 4160000 | K89: 6203000 | L89: 6816000 | M89: 8380000 | N89: 8163000 | O89: 8695000 | P89: 10035000
A90: 922964 | B90: COMERICA INC. | C90: 922964 | D90: COMERICA INC. - NET INCOME - BASIC | E90: 922964(WC01706) | F90: 682000 | G90: 196000 | H90: -118000 | I90: 136000 | J90: 389000 | K90: 515000 | L90: 533000 | M90: 586000 | N90: 515000 | O90: 473000 | P90: 845000
A91: 929814 | B91: CONAGRA BRANDS INC | C91: 929814 | D91: CONAGRA BRANDS INC - NET INCOME - BASIC | E91: 929814(WC01706) | F91: 683800 | G91: 518700 | H91: 978400 | I91: 724300 | J91: 815100 | K91: 466400 | L91: 772300 | M91: 301400 | N91: -254300 | O91: -681800 | P91: 638500
A92: 901666 | B92: CONOCOPHILLIPS | C92: 901666 | D92: CONOCOPHILLIPS - NET INCOME - BASIC | E92: 901666(WC01706) | F92: 11891000 | G92: -16998000 | H92: 4858000 | I92: 11358000 | J92: 12436000 | K92: 8428000 | L92: 9156000 | M92: 6869000 | N92: -4428000 | O92: -3615000 | P92: -1707000
A93: 902288 | B93: CONSOLIDATED EDISON | C93: 902288 | D93: CONSOLIDATED EDISON - NET INCOME - BASIC | E93: 902288(WC01706) | F93: 929000 | G93: 1196000 | H93: 868000 | I93: 992000 | J93: 1051000 | K93: 1138000 | L93: 1062000 | M93: 1092000 | N93: 1193000 | O93: 1245000 | P93: 6837000
A94: 937083 | B94: CONSTELLATION BRANDS | C94: 937083 | D94: CONSTELLATION BRANDS - NET INCOME - BASIC | E94: 937083(WC01706) | F94: 327000 | G94: -613300 | H94: -301400 | I94: 99300 | J94: 559500 | K94: 445000 | L94: 387800 | M94: 1943100 | N94: 839300 | O94: 1054900 | P94: 1535100
A95: 938928 | B95: COOPER COMPANIES INC | C95: 938928 | D95: COOPER COMPANIES INC - NET INCOME - BASIC | E95: 938928(WC01706) | F95: -11192 | G95: 65476 | H95: 100548 | I95: 112803 | J95: 175430 | K95: 248339 | L95: 296151 | M95: 269856 | N95: 203523 | O95: 273917 | P95: 372900
A96: 912273 | B96: CORNING INCORPORATED | C96: 912273 | D96: CORNING INCORPORATED - NET INCOME - BASIC | E96: 912273(WC01706) | F96: 2150000 | G96: 5257000 | H96: 2008000 | I96: 3558000 | J96: 2805000 | K96: 1728000 | L96: 1961000 | M96: 2378000 | N96: 1241000 | O96: 3597000 | P96: -506600
A97: 312385 | B97: COSTCO WHOLESALE | C97: 312385 | D97: COSTCO WHOLESALE - NET INCOME - BASIC | E97: 312385(WC01706) | F97: 1082772 | G97: 1282725 | H97: 1086000 | I97: 1304000 | J97: 1463000 | K97: 1710000 | L97: 2039000 | M97: 2058000 | N97: 2377000 | O97: 2350000 | P97: 2679000
... A108: 271980 | B108: DEVON ENERGY CORP | C108: 271980 | D108: DEVON ENERGY CORP - NET INCOME - BASIC | E108: 271980(WC01706) | F108: 3596000 | G108: -2922000 | H108: -2479000 | I108: 4550000 | J108: 4681000 | K108: -209000 | L108: -22000 | M108: 1590000 | N108: -14459000 | O108: -3304000 | P108: 952000
A109: 31196R | B109: DISCOVERY INC | C109: 31196R | D109: DISCOVERY INC - NET INCOME - BASIC | E109: 31196R(WC01706) | F109: 108338 | G109: 317000 | H109: 552000 | I109: 652000 | J109: 1132000 | K109: 943000 | L109: 1075000 | M109: 758000 | N109: 686000 | O109: 789000 | P109: -269000
A110: 135448 | B110: DISH NETWORK | C110: 135448 | D110: DISH NETWORK - NET INCOME - BASIC | E110: 135448(WC01706) | F110: 756054 | G110: 902947 | H110: 635545 | I110: 984729 | J110: 1515907 | K110: 636687 | L110: 807492 | M110: 944693 | N110: 747092 | O110: 1449853 | P110: 898689
A111: 154259 | B111: DOLLAR TREE, INC | C111: 154259 | D111: DOLLAR TREE, INC - NET INCOME - BASIC | E111: 154259(WC01706) | F111: 201300 | G111: 229500 | H111: 320500 | I111: 397300 | J111: 488300 | K111: 619300 | L111: 596700 | M111: 599200 | N111: 282400 | O111: 896200 | P111: 1152300
A112: 944314 | B112: DOMINION ENERGY INC | C112: 944314 | D112: DOMINION ENERGY INC - NET INCOME - BASIC | E112: 944314(WC01706) | F112: 2705000 | G112: 1834000 | H112: 1287000 | I112: 2808000 | J112: 1408000 | K112: 318000 | L112: 1697000 | M112: 1310000 | N112: 1899000 | O112: 2123000 | P112: 2148000
A113: 904830 | B113: DOVER CORP | C113: 904830 | D113: DOVER CORP - NET INCOME - BASIC | E113: 904830(WC01706) | F113: 661080 | G113: 590831 | H113: 367608 | I113: 714307 | J113: 899986 | K113: 861888 | L113: 1003129 | M113: 775235 | N113: 604279 | O113: 508892 | P113: 760765
A114: 905214 | B114: DTE ENERGY CO | C114: 905214 | D114: DTE ENERGY CO - NET INCOME - BASIC | E114: 905214(WC01706) | F114: 787000 | G114: 546000 | H114: 532000 | I114: 630000 | J114: 711000 | K114: 610000 | L114: 661000 | M114: 905000 | N114: 727000 | O114: 868000 | P114: 1027000
A115: 904383 | B115: DUKE ENERGY CORP | C115: 904383 | D115: DUKE ENERGY CORP - NET INCOME - BASIC | E115: 904383(WC01706) | F115: 1522000 | G115: 1295000 | H115: 1075000 | I115: 1320000 | J115: 1706000 | K115: 1768000 | L115: 2665000 | M115: 1883000 | N115: 2816000 | O115: 2152000 | P115: 2947000
A116: 513260 | B116: DUKE REALTY CORP | C116: 513260 | D116: DUKE REALTY CORP - NET INCOME - BASIC | E116: 513260(WC01706) | F116: 97421 | G116: 40491 | H116: -340387 | I116: -47162 | J116: -72709 | K116: -142687 | L116: 17124 | M116: 182511 | N116: 190512 | O116: 308771 | P116: 272672
A117: 916091 | B117: DXC TECHNO | C117: 916091 | D117: DXC TECHNO - NET INCOME - BASIC | E117: 916091(WC01706) | F117: 388800 | G117: 544600 | H117: 1115200 | I117: 817000 | J117: 740000 | K117: -4243000 | L117: 544000 | M117: 947000 | N117: -8000 | O117: 251000 | P117: -123000
A118: 883488 | B118: E*TRADE FINANCIAL | C118: 883488 | D118: E*TRADE FINANCIAL - NET INCOME - BASIC | E118: 883488(WC01706) | F118: -1441754 | G118: -780588 | H118: -1297762 | I118: -28472 | J118: 156701 | K118: -112583 | L118: 86012 | M118: 293000 | N118: 268000 | O118: 552000 | P118: 647000
A119: 357922 | B119: EASTMAN CHEMICAL CO | C119: 357922 | D119: EASTMAN CHEMICAL CO - NET INCOME - BASIC | E119: 357922(WC01706) | F119: 311000 | G119: 328000 | H119: 136000 | I119: 438000 | J119: 665000 | K119: 436000 | L119: 1165000 | M119: 751000 | N119: 848000 | O119: 854000 | P119: 1045000
A120: 903749 | B120: EATON CORP PLC | C120: 903749 | D120: EATON CORP PLC - NET INCOME - BASIC | E120: 903749(WC01706) | F120: 959000 | G120: 1058000 | H120: 383000 | I120: 929000 | J120: 1350000 | K120: 1217000 | L120: 1861000 | M120: 1793000 | N120: 1979000 | O120: 1922000 | P120: 2923000
A121: 687609 | B121: EBAY INC. | C121: 687609 | D121: EBAY INC. - NET INCOME - BASIC | E121: 687609(WC01706) | F121: 348251 | G121: 1779474 | H121: 2389097 | I121: 1800961 | J121: 3229387 | K121: 2609000 | L121: 2856000 | M121: 46000 | N121: 1725000 | O121: 7266000 | P121: 2084000
... A132: 902317 | B132: EXELON CORPORATION | C132: 902317 | D132: EXELON CORPORATION - NET INCOME - BASIC | E132: 902317(WC01706) | F132: 2726000 | G132: 2716000 | H132: 2707000 | I132: 2563000 | J132: 2495000 | K132: 1160000 | L132: 1719000 | M132: 1623000 | N132: 2269000 | O132: 1134000 | P132: 3770000
A133: 31412T | B133: EXPEDIA GROUP INC | C133: 31412T | D133: EXPEDIA GROUP INC - NET INCOME - BASIC | E133: 31412T(WC01706) | F133: 295864 | G133: -2517763 | H133: 299526 | I133: 421500 | J133: 472294 | K133: 280171 | L133: 232850 | M133: 398097 | N133: 764465 | O133: 281848 | P133: 363845
A134: 910722 | B134: EXPEDITORS INTL WASH | C134: 910722 | D134: EXPEDITORS INTL WASH - NET INCOME - BASIC | E134: 910722(WC01706) | F134: 269154 | G134: 301014 | H134: 240217 | I134: 344172 | J134: 385679 | K134: 333360 | L134: 348526 | M134: 376888 | N134: 457223 | O134: 430807 | P134: 450077
A135: 905039 | B135: EXXON MOBIL CORP | C135: 905039 | D135: EXXON MOBIL CORP - NET INCOME - BASIC | E135: 905039(WC01706) | F135: 40610000 | G135: 45220000 | H135: 19280000 | I135: 30460000 | J135: 41060000 | K135: 44880000 | L135: 32580000 | M135: 32520000 | N135: 16150000 | O135: 7840000 | P135: 13768000
A136: 755980 | B136: FASTENAL COMPANY | C136: 755980 | D136: FASTENAL COMPANY - NET INCOME - BASIC | E136: 755980(WC01706) | F136: 232622 | G136: 279705 | H136: 184357 | I136: 265356 | J136: 357929 | K136: 420536 | L136: 448636 | M136: 494150 | N136: 516361 | O136: 499478 | P136: 554300
...

Sheet EBITDA
A1: EBITDA
E2: 4 | F2: 5 | G2: 6 | H2: 7 | I2: 8 | J2: 9 | K2: 10 | L2: 11 | M2: 12 | N2: 13 | O2: 14
B3: Code | C3: Name | D3: Code | E3: 2007 | F3: 2008 | G3: 2009 | H3: 2010 | I3: 2011 | J3: 2012 | K3: 2013 | L3: 2014 | M3: 2015 | N3: 2016 | O3: 2017
A4: =VLOOKUP(B4,'[1]PORTFOLIO RAW'!B:B,1,FALSE) -> 891399 | B4: 891399 | C4: AMAZON.COM INC - EBIT & DEPRECIATION | D4: 891399(WC18198) | E4: 1008000 | F4: 1312000 | G4: 1627000 | H4: 2193000 | I4: 2148000 | J4: 2795000 | K4: 3900000 | L4: 4845000 | M4: 8308000 | N4: 12492000 | O4: 16132000
A5: =VLOOKUP(B5,'[1]PORTFOLIO RAW'!B:B,1,FALSE) -> 916328 | B5: 916328 | C5: ABBOTT LABORATORIES - EBIT & DEPRECIATION | D5: 916328(WC18198) | E5: 6419660 | F5: 8104592 | G5: 9493940 | H5: 9138274 | I5: 9260677 | J5: 9638224 | K5: 4299000 | L5: 4216000 | M5: 4818000 | N5: 3197000 | O5: 6156000
A6: =VLOOKUP(B6,'[1]PORTFOLIO RAW'!B:B,1,FALSE) -> 545101 | B6: 545101 | C6: AES CORP - EBIT & DEPRECIATION | D6: 545101(WC18198) | E6: 4268000 | F6: 5596000 | G6: 4790000 | H6: 3622000 | I6: 5044000 | J6: 3280000 | K6: 3783000 | L6: 4294000 | M6: 3705000 | N6: 2744000 | O6: 3110000
A7: =VLOOKUP(B7,'[1]PORTFOLIO RAW'!B:B,1,FALSE) -> 906187 | B7: 906187 | C7: INT'L BUSINESS MACHS - EBIT & DEPRECIATION | D7: 906187(WC18198) | E7: 20301000 | F7: 22838000 | G7: 23630000 | H7: 25025000 | I7: 26328000 | J7: 27048000 | K7: 24533000 | L7: 25168000 | M7: 20375000 | N7: 17449000 | O7: 16590000
A8: =VLOOKUP(B8,'[1]PORTFOLIO RAW'!B:B,1,FALSE) -> 936365 | B8: 936365 | C8: ADVANCED MICRO - EBIT & DEPRECIATION | D8: 936365(WC18198) | E8: -1494000 | F8: -671000 | G8: 1974000 | H8: 1553000 | I8: 496000 | J8: -782000 | K8: 339000 | L8: -18000 | M8: -319000 | N8: -159000 | O8: 339000
A9: =VLOOKUP(B9,'[1]PORTFOLIO RAW'!B:B,1,FALSE) -> 749382 | B9: 749382 | C9: ADOBE INC - EBIT & DEPRECIATION | D9: 749382(WC18198) | E9: 1262907 | F9: 1358796 | G9: 987350 | H9: 1264303 | I9: 1372387 | J9: 1486047 | K9: 744876 | L9: 734698 | M9: 1277438 | N9: 1837115 | O9: 2538040
A10: =VLOOKUP(B10,'[1]PORTFOLIO RAW'!B:B,1,FALSE) -> 905271 | B10: 905271 | C10: AIR PRODUCTS & CHEMS - EBIT & DEPRECIATION | D10: 905271(WC18198) | E10: 2247700 | F10: 2364800 | G10: 1686600 | H10: 2252400 | I10: 2504300 | J10: 2129000 | K10: 2231400 | L10: 2280100 | M10: 2610900 | N10: 3016200 | O10: 2307700
A11: =VLOOKUP(B11,'[1]PORTFOLIO RAW'!B:B,1,FALSE) -> 894371 | B11: 894371 | C11: BOSTON PROPERTIES - EBIT & DEPRECIATION | D11: 894371(WC18198) | E11: 1717571 | F11: 907372 | G11: 906955 | H11: 870003 | I11: 1061245 | J11: 1111776 | K11: 1640851 | L11: 1597604 | M11: 1848886 | N11: 1669155 | O11: 1543277
A12: =VLOOKUP(B12,'[1]PORTFOLIO RAW'!B:B,1,FALSE) -> 322677 | B12: 322677 | C12: ALLSTATE CORP - EBIT & DEPRECIATION | D12: 322677(WC18198) | E12: 6917000 | F12: -2496000 | G12: 1879000 | H12: 1692000 | I12: 1491000 | J12: 3719000 | K12: 4131000 | L12: 4924000 | M12: 3945000 | N12: 3431000 | O12: 4809000
A13: =VLOOKUP(B13,'[1]PORTFOLIO RAW'!B:B,1,FALSE) -> 906191 | B13: 906191 | C13: HONEYWELL INTERNATNL - EBIT & DEPRECIATION | D13: 906191(WC18198) | E13: 4604000 | F13: 5097000 | G13: 4368000 | H13: 4211000 | I13: 3676000 | J13: 5119000 | K13: 6711000 | L13: 7045000 | M13: 7779000 | N13: 7806000 | O13: 8294000
A14: =VLOOKUP(B14,'[1]PORTFOLIO RAW'!B:B,1,FALSE) -> 938692 | B14: 938692 | C14: AMGEN INC - EBIT & DEPRECIATION | D14: 938692(WC18198) | E14: 5437000 | F14: 6567000 | G14: 6830000 | H14: 6937000 | I14: 5819000 | J14: 7150000 | K14: 8595000 | L14: 9809000 | M14: 11184000 | N14: 12542000 | O14: 12856000
A15: =VLOOKUP(B15,'[1]PORTFOLIO RAW'!B:B,1,FALSE) -> 905802 | B15: 905802 | C15: HESS CORPORATION - EBIT & DEPRECIATION | D15: 905802(WC18198) | E15: 5360000 | F15: 6952000 | G15: 4313000 | H15: 6511000 | I15: 6323000 | J15: 7106000 | K15: 7669000 | L15: 5983000 | M15: 38000 | N15: -272000 | O15: -2570000
... A29: =VLOOKUP(B29,'[1]PORTFOLIO RAW'!B:B,1,FALSE) -> 670942 | B29: 670942 | C29: AMEREN CORPORATION - EBIT & DEPRECIATION | D29: 670942(WC18198) | E29: 2176000 | F29: 2125000 | G29: 2229000 | H29: 1758000 | I29: 2061000 | J29: -424000 | K29: 1933000 | L29: 2056000 | M29: 2099000 | N29: 2268000 | O29: 2392000
A30: =VLOOKUP(B30,'[1]PORTFOLIO RAW'!B:B,1,FALSE) -> 702259 | B30: 702259 | C30: AUTODESK INC - EBIT & DEPRECIATION | D30: 702259(WC18198) | E30: 534700 | F30: 344300 | G30: 196200 | H30: 377400 | I30: 478400 | J30: NA | K30: 418600 | L30: 242100 | M30: 159400 | N30: -337400 | O30: -395100
A31: =VLOOKUP(B31,'[1]PORTFOLIO RAW'!B:B,1,FALSE) -> 912669 | B31: 912669 | C31: AUTOMATIC DATA PROC - EBIT & DEPRECIATION | D31: 912669(WC18198) | E31: 2007200 | F31: 2211600 | G31: 2246100 | H31: 2181000 | I31: 2259500 | J31: 2453100 | K31: 2410400 | L31: 2616900 | M31: 2355100 | N31: 2579500 | O31: 2927200
A32: =VLOOKUP(B32,'[1]PORTFOLIO RAW'!B:B,1,FALSE) -> 544616 | B32: 544616 | C32: AUTOZONE INC - EBIT & DEPRECIATION | D32: 544616(WC18198) | E32: 1217496 | F32: 1297428 | G32: 1360382 | H32: 1514124 | I32: 1693070 | J32: 1842119 | K32: 2001955 | L32: 2083340 | M32: 2224575 | N32: 2360163 | O32: 2406622
A33: =VLOOKUP(B33,'[1]PORTFOLIO RAW'!B:B,1,FALSE) -> 921161 | B33: 921161 | C33: AVERY DENNISON CORP - EBIT & DEPRECIATION | D33: 921161(WC18198) | E33: 715100 | F33: 664900 | G33: -445200 | H33: 670700 | I33: 546200 | J33: 548900 | K33: 626800 | L33: 629400 | M33: 657800 | N33: 713500 | O33: 826300
A34: =VLOOKUP(B34,'[1]PORTFOLIO RAW'!B:B,1,FALSE) -> 932060 | B34: 932060 | C34: BALL CORPORATION - EBIT & DEPRECIATION | D34: 932060(WC18198) | E34: 794900 | F34: 887900 | G34: 931700 | H34: 1016400 | I34: 1138000 | J34: 1073400 | K34: 1067300 | L34: 1086400 | M34: 774200 | N34: 807000 | O34: 1528000
A35: =VLOOKUP(B35,'[1]PORTFOLIO RAW'!B:B,1,FALSE) -> 874227 | B35: 874227 | C35: BERKSHIRE HATHAWAY - EBIT & DEPRECIATION | D35: 874227(WC18198) | E35: 24478000 | F35: 12347000 | G35: 16671000 | H35: 25888000 | I35: 22661000 | J35: 30126000 | K35: 38105000 | L35: 38728000 | M35: 46240000 | N35: 45142000 | O35: 35482000
A36: =VLOOKUP(B36,'[1]PORTFOLIO RAW'!B:B,1,FALSE) -> 916365 | B36: 916365 | C36: BAXTER INTERNATIONAL - EBIT & DEPRECIATION | D36: 916365(WC18198) | E36: 2846000 | F36: 3255000 | G36: 3418000 | H36: 2779000 | I36: 3637000 | J36: 3698000 | K36: 3503000 | L36: 3611000 | M36: 1333000 | N36: 5843000 | O36: 2063000
A37: =VLOOKUP(B37,'[1]PORTFOLIO RAW'!B:B,1,FALSE) -> 905876 | B37: 905876 | C37: BECTON, DICKINSON - EBIT & DEPRECIATION | D37: 905876(WC18198) | E37: 1691706 | F37: 2067372 | G37: 2143456 | H37: 2207692 | I37: 2299698 | J37: 2105920 | K37: 1850000 | L37: 2219000 | M37: 2001000 | N37: 2576000 | O37: 2588000
A38: =VLOOKUP(B38,'[1]PORTFOLIO RAW'!B:B,1,FALSE) -> 945384 | B38: 945384 | C38: VERIZON COMMUNICATNS - EBIT & DEPRECIATION | D38: 945384(WC18198) | E38: 30166000 | F38: 31731000 | G38: 30649000 | H38: 31002000 | I38: 29362000 | J38: 28604000 | K38: 48408000 | L38: 34938000 | M38: 49263000 | N38: 41388000 | O38: 42134000
A39: =VLOOKUP(B39,'[1]PORTFOLIO RAW'!B:B,1,FALSE) -> 929302 | B39: 929302 | C39: BEST BUY CO INC - EBIT & DEPRECIATION | D39: 929302(WC18198) | E39: 2670000 | F39: 2870000 | G39: 2587000 | H39: 3215000 | I39: 3143000 | J39: 940820 | K39: 1903000 | L39: 2133000 | M39: 2047000 | N39: 2542000 | O39: 2575000
A40: =VLOOKUP(B40,'[1]PORTFOLIO RAW'!B:B,1,FALSE) -> 895784 | B40: 895784 | C40: SL GREEN REALTY CORP - EBIT & DEPRECIATION | D40: 895784(WC18198) | E40: 598725 | F40: 547709 | G40: 500310 | H40: 724810 | I40: 1218024 | J40: 783663 | K40: 816231 | L40: 933469 | M40: 1216001 | N40: 1417949 | O40: 758011
A41: =VLOOKUP(B41,'[1]PORTFOLIO RAW'!B:B,1,FALSE) -> 878574 | B41: 878574 | C41: YUM! BRANDS INC - EBIT & DEPRECIATION | D41: 878574(WC18198) | E41: 1881000 | F41: 2119000 | G41: 2084000 | H41: 2369000 | I41: 2448000 | J41: 2932000 | K41: 2516000 | L41: 2288000 | M41: 2648000 | N41: 1960000 | O41: 3000000
A42: =VLOOKUP(B42,'[1]PORTFOLIO RAW'!B:B,1,FALSE) -> 905159 | B42: 905159 | C42: FIRSTENERGY CORP - EBIT & DEPRECIATION | D42: 905159(WC18198) | E42: 3573000 | F42: 3498000 | G42: 2819000 | H42: 2657000 | I42: 3502000 | J42: 3377000 | K42: 2813000 | L42: 2426000 | M42: 3884000 | N42: -6751000 | O42: 1423000
... A44: =VLOOKUP(B44,'[1]PORTFOLIO RAW'!B:B,1,FALSE) -> 904818 | B44: 904818 | C44: BOEING CO - EBIT & DEPRECIATION | D44: 904818(WC18198) | E44: 7908000 | F44: 5670000 | G44: 3662000 | H44: 6643000 | I44: 7401000 | J44: 8004000 | K44: 8462000 | L44: 9376000 | M44: 9263000 | N44: 7784000 | O44: 12476000
A45: =VLOOKUP(B45,'[1]PORTFOLIO RAW'!B:B,1,FALSE) -> 923649 | B45: 923649 | C45: ROBERT HALF INTL INC - EBIT & DEPRECIATION | D45: 923649(WC18198) | E45: 565945 | F45: 497786 | G45: 132529 | H45: 171726 | I45: 301631 | J45: 392969 | K45: NA | L45: NA | M45: NA | N45: NA | O45: NA
A46: =VLOOKUP(B46,'[1]PORTFOLIO RAW'!B:B,1,FALSE) -> 325824 | B46: 325824 | C46: BOSTON SCIENTIFIC - EBIT & DEPRECIATION | D46: 325824(WC18198) | E46: 940000 | F46: -699000 | G46: -61000 | H46: 146000 | I46: 1641000 | J46: -3161000 | K46: 790000 | L46: 432000 | M46: 403000 | N46: 1225000 | O46: 2006000
A47: =VLOOKUP(B47,'[1]PORTFOLIO RAW'!B:B,1,FALSE) -> 879628 | B47: 879628 | C47: C.H. ROBINSON - EBIT & DEPRECIATION | D47: 879628(WC18198) | E47: 550880 | F47: 609551 | G47: 617575 | H47: 653471 | I47: 727202 | J47: NA | K47: 741343 | L47: 805427 | M47: 931919 | N47: 912200 | O47: 868096
A48: =VLOOKUP(B48,'[1]PORTFOLIO RAW'!B:B,1,FALSE) -> 905080 | B48: 905080 | C48: BRISTOL-MYERS SQUIBB - EBIT & DEPRECIATION | D48: 905080(WC18198) | E48: 4324000 | F48: 5980000 | G48: 6086000 | H48: 6808000 | I48: 7646000 | J48: 3328000 | K48: 4235000 | L48: 3306000 | M48: 2861000 | N48: 6675000 | O48: 6109000
A49: =VLOOKUP(B49,'[1]PORTFOLIO RAW'!B:B,1,FALSE) -> 130502 | B49: 130502 | C49: AVALONBAY COMMUNITIE - EBIT & DEPRECIATION | D49: 130502(WC18198) | E49: 467178 | F49: 418099 | G49: 435041 | H49: 505086 | I49: 575663 | J49: 636788 | K49: 801598 | L49: 1143050 | M49: 1327114 | N49: 1687995 | O49: 1589868
A50: =VLOOKUP(B50,'[1]PORTFOLIO RAW'!B:B,1,FALSE) -> 902103 | B50: 902103 | C50: SEMPRA ENERGY - EBIT & DEPRECIATION | D50: 902103(WC18198) | E50: 2517000 | F50: 2018000 | G50: 2618000 | H50: 2381000 | I50: 3155000 | J50: 2845000 | K50: 3063000 | L50: 3161000 | M50: 3421000 | N50: 3072000 | O50: 3699000
A51: =VLOOKUP(B51,'[1]PORTFOLIO RAW'!B:B,1,FALSE) -> 951849 | B51: 951849 | C51: FEDEX CORP - EBIT & DEPRECIATION | D51: 951849(WC18198) | E51: 5093000 | F51: 4060000 | G51: 2737000 | H51: 3931000 | I51: 4324000 | J51: 5306000 | K51: 4923000 | L51: 6072000 | M51: 4473000 | N51: 5707000 | O51: 8086000
A52: =VLOOKUP(B52,'[1]PORTFOLIO RAW'!B:B,1,FALSE) -> 674693 | B52: 674693 | C52: VERISIGN, INC. - EBIT & DEPRECIATION | D52: 674693(WC18198) | E52: 121127 | F52: 292344 | G52: 414907 | H52: 320676 | I52: 396625 | J52: 517710 | K52: 609988 | L52: 632995 | M52: 670902 | N52: 754904 | O52: 786119
A53: =VLOOKUP(B53,'[1]PORTFOLIO RAW'!B:B,1,FALSE) -> 546075 | B53: 546075 | C53: AMPHENOL CORP - EBIT & DEPRECIATION | D53: 546075(WC18198) | E53: 630726 | F53: 723509 | G53: 581637 | H53: 807275 | I53: 879220 | J53: 960233 | K53: 1046680 | L53: 1221000 | M53: 1292700 | N53: 1430700 | O53: 1671500
A54: =VLOOKUP(B54,'[1]PORTFOLIO RAW'!B:B,1,FALSE) -> 912216 | B54: 912216 | C54: BROWN FORMAN CORP - EBIT & DEPRECIATION | D54: 912216(WC18198) | E54: 664000 | F54: 745000 | G54: 722000 | H54: 772000 | I54: 917000 | J54: 843000 | K54: 952000 | L54: 1023000 | M54: 1080000 | N54: 1591000 | O54: 1050000
A55: =VLOOKUP(B55,'[1]PORTFOLIO RAW'!B:B,1,FALSE) -> 993189 | B55: 993189 | C55: CSX CORPORATION - EBIT & DEPRECIATION | D55: 993189(WC18198) | E55: 3239000 | F55: 3583000 | G55: 3226000 | H55: 4050000 | I55: 4416000 | J55: 4589000 | K55: 4588000 | L55: 4740000 | M55: 4890000 | N55: 4621000 | O55: 4784000
A56: =VLOOKUP(B56,'[1]PORTFOLIO RAW'!B:B,1,FALSE) -> 905075 | B56: 905075 | C56: CAMPBELL SOUP CO - EBIT & DEPRECIATION | D56: 905075(WC18198) | E56: 1595000 | F56: 1379000 | G56: 1452000 | H56: 1604000 | I56: 1542000 | J56: 1459000 | K56: 1485000 | L56: 1500000 | M56: 1397000 | N56: 1275000 | O56: 1723000
A57: =VLOOKUP(B57,'[1]PORTFOLIO RAW'!B:B,1,FALSE) -> 937083 | B57: 937083 | C57: CONSTELLATION BRANDS - EBIT & DEPRECIATION | D57: 937083(WC18198) | E57: 898800 | F57: -185100 | G57: 183800 | H57: 449000 | I57: 639800 | J57: 603400 | K57: 632600 | L57: 2593200 | M57: 1697900 | N57: 1985100 | O57: 2693300
A58: =VLOOKUP(B58,'[1]PORTFOLIO RAW'!B:B,1,FALSE) -> 944704 | B58: 944704 | C58: CARDINAL HEALTH, INC - EBIT & DEPRECIATION | D58: 944704(WC18198) | E58: 1695800 | F58: 2502500 | G58: 2277500 | H58: 1577400 | I58: 1924400 | J58: 2118000 | K58: 1408000 | L58: 2390000 | M58: 2559000 | N58: 3095000 | O58: 2842000
A59: =VLOOKUP(B59,'[1]PORTFOLIO RAW'!B:B,1,FALSE) -> 902224 | B59: 902224 | C59: CATERPILLAR INC - EBIT & DEPRECIATION | D59: 902224(WC18198) | E59: 8170000 | F59: 7880000 | G59: 4339000 | H59: 7245000 | I59: 10474000 | J59: 12312000 | K59: 9408000 | L59: 9354000 | M59: 6995000 | N59: 4274000 | O59: 8136000
... A109: =VLOOKUP(B109,'[1]PORTFOLIO RAW'!B:B,1,FALSE) -> 905016 | B109: 905016 | C109: NEXTERA ENERGY - EBIT & DEPRECIATION | D109: 905016(WC18198) | E109: 3779000 | F109: 4388000 | G109: 4466000 | H109: 5433000 | I109: 5157000 | J109: 5333000 | K109: 6151000 | L109: 7660000 | M109: 8305000 | N109: 8905000 | O109: 8456000
A110: =VLOOKUP(B110,'[1]PORTFOLIO RAW'!B:B,1,FALSE) -> 28341F | B110: 28341F | C110: ASSURANT INC - EBIT & DEPRECIATION | D110: 28341F(WC18198) | E110: 1106527 | F110: 688445 | G110: 866621 | H110: 774673 | I110: 883380 | J110: 887863 | K110: 992285 | L110: 934749 | M110: 393402 | N110: 1031350 | O110: 609700
A111: =VLOOKUP(B111,'[1]PORTFOLIO RAW'!B:B,1,FALSE) -> 755980 | B111: 755980 | C111: FASTENAL COMPANY - EBIT & DEPRECIATION | D111: 755980(WC18198) | E111: 415231 | F111: 490435 | G111: 337577 | H111: 471395 | I111: 619787 | J111: 728207 | K111: 777772 | L111: 861021 | M111: 915726 | N111: 900285 | O111: 1009600
A112: =VLOOKUP(B112,'[1]PORTFOLIO RAW'!B:B,1,FALSE) -> 905994 | B112: 905994 | C112: FEDERAL REALTY INVST - EBIT & DEPRECIATION | D112: 905994(WC18198) | E112: 313615 | F112: 329277 | G112: 324908 | H112: 347746 | I112: 354419 | J112: 397990 | K112: 402389 | L112: 431400 | M112: 456027 | N112: 514954 | O112: 536540
A113: =VLOOKUP(B113,'[1]PORTFOLIO RAW'!B:B,1,FALSE) -> 997198 | B113: 997198 | C113: FIFTH THIRD BANCORP - EBIT & DEPRECIATION | D113: 997198(WC18198) | E113: 2429000 | F113: -1889000 | G113: 1312000 | H113: 1455000 | I113: 2360000 | J113: 2670000 | K113: 3230000 | L113: 2639000 | M113: 3034000 | N113: 2823000 | O113: 3473000
A114: =VLOOKUP(B114,'[1]PORTFOLIO RAW'!B:B,1,FALSE) -> 951503 | B114: 951503 | C114: M&T BANK CORPORATION - EBIT & DEPRECIATION | D114: 951503(WC18198) | E114: 1464522 | F114: 1359973 | G114: 949624 | H114: 1457812 | I114: 1573001 | J114: 1883709 | K114: 2025557 | L114: 1972761 | M114: 2042421 | N114: 2400036 | O114: 2624332
A115: =VLOOKUP(B115,'[1]PORTFOLIO RAW'!B:B,1,FALSE) -> 741123 | B115: 741123 | C115: FISERV INC - EBIT & DEPRECIATION | D115: 741123(WC18198) | E115: 930000 | F115: 1241000 | G115: 1287000 | H115: 1330000 | I115: 1266000 | J115: 1417000 | K115: 1465000 | L115: 1615000 | M115: 1643000 | N115: 1866000 | O115: 1978000
A116: =VLOOKUP(B116,'[1]PORTFOLIO RAW'!B:B,1,FALSE) -> 546814 | B116: 546814 | C116: MACY'S INC - EBIT & DEPRECIATION | D116: 546814(WC18198) | E116: 3203000 | F116: -3072000 | G116: 2279000 | H116: 2983000 | I116: 3500000 | J116: 3576000 | K116: 3700000 | L116: 3821000 | M116: 3102000 | N116: 2377000 | O116: 2819000
A117: =VLOOKUP(B117,'[1]PORTFOLIO RAW'!B:B,1,FALSE) -> 938076 | B117: 938076 | C117: FRANKLIN RESOURCES - EBIT & DEPRECIATION | D117: 938076(WC18198) | E117: 2623574 | F117: 2439216 | G117: 1455487 | H117: 2522542 | I117: 2906287 | J117: 2858300 | K117: 3096400 | L117: 3492300 | M117: 3232900 | N117: 2584400 | O117: 2578100
A118: =VLOOKUP(B118,'[1]PORTFOLIO RAW'!B:B,1,FALSE) -> 152594 | B118: 152594 | C118: FREEPORT-MCMORAN INC - EBIT & DEPRECIATION | D118: 152594(WC18198) | E118: 7870000 | F118: -10826000 | G118: 7539000 | H118: 10102000 | I118: 10152000 | J118: 6852000 | K118: 8100000 | L118: 4069000 | M118: -9879000 | N118: -107000 | O118: 5417000
A119: =VLOOKUP(B119,'[1]PORTFOLIO RAW'!B:B,1,FALSE) -> 951018 | B119: 951018 | C119: GAP INC - EBIT & DEPRECIATION | D119: 951018(WC18198) | E119: 1979000 | F119: 2153000 | G119: 2471000 | H119: 2637000 | I119: 2035000 | J119: 2507000 | K119: 2690000 | L119: 2652000 | M119: 2122000 | N119: 1792000 | O119: 2057000
A120: =VLOOKUP(B120,'[1]PORTFOLIO RAW'!B:B,1,FALSE) -> 907652 | B120: 907652 | C120: GENERAL DYNAMICS - EBIT & DEPRECIATION | D120: 907652(WC18198) | E120: 3601000 | F120: 4184000 | G120: 4246000 | H120: 4526000 | I120: 4465000 | J120: 1329000 | K120: 4266000 | L120: 4401000 | M120: 4682000 | N120: 4784000 | O120: 4635000
A121: =VLOOKUP(B121,'[1]PORTFOLIO RAW'!B:B,1,FALSE) -> 905801 | B121: 905801 | C121: GENERAL MILLS, INC. - EBIT & DEPRECIATION | D121: 905801(WC18198) | E121: 2507000 | F121: 2714300 | G121: 2798100 | H121: 3012100 | I121: 3242700 | J121: 3104800 | K121: 3452400 | L121: 3558900 | M121: 2678800 | N121: 3323600 | O121: 3177000
A122: =VLOOKUP(B122,'[1]PORTFOLIO RAW'!B:B,1,FALSE) -> 906511 | B122: 906511 | C122: GENUINE PARTS CO - EBIT & DEPRECIATION | D122: 906511(WC18198) | E122: 940713 | F122: 888887 | G122: 762461 | H122: 879176 | I122: 1006778 | J122: 1137797 | K122: 1205232 | L122: 1291140 | M122: 1287018 | N122: 1242911 | O122: 1218445
... A133: =VLOOKUP(B133,'[1]PORTFOLIO RAW'!B:B,1,FALSE) -> 905077 | B133: 905077 | C133: HERSHEY CO - EBIT & DEPRECIATION | D133: 905077(WC18198) | E133: 772233 | F133: 841191 | G133: 944878 | H133: 1103684 | I133: 1272392 | J133: 1324125 | K133: 1543866 | L133: 1605173 | M133: 1227758 | N133: 1493266 | O133: 1472587
A134: =VLOOKUP(B134,'[1]PORTFOLIO RAW'!B:B,1,FALSE) -> 699943 | B134: 699943 | C134: JUNIPER NETWORKS INC - EBIT & DEPRECIATION | D134: 699943(WC18198) | E134: NA | F134: 896365 | G134: 460434 | H134: 924789 | I134: 791254 | J134: 531400 | K134: 773800 | L134: 166700 | M134: 1112000 | N134: 1131800 | O134: 1138600
A135: =VLOOKUP(B135,'[1]PORTFOLIO RAW'!B:B,1,FALSE) -> 542983 | B135: 542983 | C135: HOLOGIC INC - EBIT & DEPRECIATION | D135: 542983(WC18198) | E135: 181729 | F135: -21279 | G135: -1745249 | H135: 366884 | I135: 646968 | J135: 424377 | K135: -395876 | L135: 791900 | M135: 874100 | N135: 1036000 | O135: 1832900
A136: =VLOOKUP(B136,'[1]PORTFOLIO RAW'!B:B,1,FALSE) -> 741410 | B136: 741410 | C136: UNUM GROUP - EBIT & DEPRECIATION | D136: 741410(WC18198) | E136: 1246500 | F136: 1049500 | G136: 1492200 | H136: 1548500 | I136: 481600 | J136: 1479200 | K136: 1439400 | L136: 782600 | M136: 1490600 | N136: 1615400 | O136: 1667300
A137: =VLOOKUP(B137,'[1]PORTFOLIO RAW'!B:B,1,FALSE) -> 998171 | B137: 998171 | C137: HOME DEPOT, INC. - EBIT & DEPRECIATION | D137: 998171(WC18198) | E137: 9018000 | F137: 6116000 | G137: 6464000 | H137: 7521000 | I137: 8356000 | J137: 9537000 | K137: 10935000 | L137: 12592000 | M137: 13803000 | N137: 15436000 | O137: 16817000
A138: =VLOOKUP(B138,'[1]PORTFOLIO RAW'!B:B,1,FALSE) -> 904842 | B138: 904842 | C138: CENTERPOINT ENERGY - EBIT & DEPRECIATION | D138: 904842(WC18198) | E138: 1851000 | F138: 1984000 | G138: 1920000 | H138: 2161000 | I138: 2613000 | J138: 2345000 | K138: 2031000 | L138: 2061000 | M138: 1930000 | N138: 2033000 | O138: 2215000
A139: =VLOOKUP(B139,'[1]PORTFOLIO RAW'!B:B,1,FALSE) -> 916860 | B139: 916860 | C139: HUMANA INC. - EBIT & DEPRECIATION | D139: 916860(WC18198) | E139: 1520578 | F139: 1256437 | G139: 1957877 | H139: 2079722 | I139: 2614000 | J139: 2311000 | K139: 2394000 | L139: 2811000 | M139: 3064000 | N139: 2206000 | O139: 4747000
A140: =VLOOKUP(B140,'[1]PORTFOLIO RAW'!B:B,1,FALSE) -> 951068 | B140: 951068 | C140: HUNTINGTON BANCSHR - EBIT & DEPRECIATION | D140: 951068(WC18198) | E140: 427006 | F140: 164649 | G140: -3474706 | H140: 501775 | I140: 855151 | J140: 956811 | K140: 972944 | L140: 988149 | M140: 1081019 | N140: 1206408 | O140: 1768000
A141: =VLOOKUP(B141,'[1]PORTFOLIO RAW'!B:B,1,FALSE) -> 545725 | B141: 545725 | C141: BIOGEN INC - EBIT & DEPRECIATION | D141: 545725(WC18198) | E141: 1273000 | F141: 1669900 | G141: 1787900 | H141: 1620100 | I141: 2103100 | J141: 2257200 | K141: 3129576 | L141: 4664294 | M141: 5463300 | N141: 5885900 | O141: 6662200
A142: =VLOOKUP(B142,'[1]PORTFOLIO RAW'!B:B,1,FALSE) -> 905052 | B142: 905052 | C142: ILLINOIS TOOL WORKS - EBIT & DEPRECIATION | D142: 905052(WC18198) | E142: 3205660 | F142: 2895326 | G142: 1947986 | H142: 2934721 | I142: 3378856 | J142: 4460000 | K142: 3213000 | L142: 3465000 | M142: 3426000 | N142: 3554000 | O142: 3992000
A143: =VLOOKUP(B143,'[1]PORTFOLIO RAW'!B:B,1,FALSE) -> 328184 | B143: 328184 | C143: INTUIT INC - EBIT & DEPRECIATION | D143: 328184(WC18198) | E143: 858208 | F143: 966738 | G143: 979288 | H143: 1132000 | I143: 1267000 | J143: 1443000 | K143: 1472000 | L143: 1542000 | M143: 970000 | N143: 1476000 | O143: 1634000
A144: =VLOOKUP(B144,'[1]PORTFOLIO RAW'!B:B,1,FALSE) -> 922726 | B144: 922726 | C144: INTEL CORPORATION - EBIT & DEPRECIATION | D144: 922726(WC18198) | E144: 13979000 | F144: 14066000 | G144: 10927000 | H144: 20335000 | I144: 23774000 | J144: 22566000 | K144: 20564000 | L144: 24335000 | M144: 23395000 | N144: 21122000 | O144: 26709000
A145: =VLOOKUP(B145,'[1]PORTFOLIO RAW'!B:B,1,FALSE) -> 905050 | B145: 905050 | C145: INTL FLAVORS&FRAGRAN - EBIT & DEPRECIATION | D145: 905050(WC18198) | E145: 453007 | F145: 430516 | G145: 412892 | H145: 487544 | I145: 493512 | J145: 561835 | K145: 615204 | L145: 684482 | M145: 674760 | N145: 679175 | O145: 720375
A146: =VLOOKUP(B146,'[1]PORTFOLIO RAW'!B:B,1,FALSE) -> 904069 | B146: 904069 | C146: INTERNATIONAL PAPER - EBIT & DEPRECIATION | D146: 904069(WC18198) | E146: 3191000 | F146: 766000 | G146: 3325000 | H146: 2921000 | I146: 3386000 | J146: 3271000 | K146: 3065000 | L146: 2955000 | M146: 3204000 | N146: 2905000 | O146: 2949000
... A166: =VLOOKUP(B166,'[1]PORTFOLIO RAW'!B:B,1,FALSE) -> 154423 | B166: 154423 | C166: LOCKHEED MARTIN CORP - EBIT & DEPRECIATION | D166: 154423(WC18198) | E166: 5336000 | F166: 5687000 | G166: 5038000 | H166: 4700000 | I166: 4661000 | J166: 5166000 | K166: 5174000 | L166: 6250000 | M166: 6149000 | N166: 6273000 | O166: 6908000
A167: =VLOOKUP(B167,'[1]PORTFOLIO RAW'!B:B,1,FALSE) -> 922418 | B167: 922418 | C167: LOEWS CORPORATION - EBIT & DEPRECIATION | D167: 922418(WC18198) | E167: NA | F167: 1624000 | G167: 2962000 | H167: 4235000 | I167: 3587000 | J167: 2744000 | K167: 2742000 | L167: 3207000 | M167: 1719000 | N167: 2313000 | O167: 3065000
A168: =VLOOKUP(B168,'[1]PORTFOLIO RAW'!B:B,1,FALSE) -> 755695 | B168: 755695 | C168: CARNIVAL CORP - EBIT & DEPRECIATION | D168: 755695(WC18198) | E168: 3892000 | F168: 4040000 | G168: 3495000 | H168: 3773000 | I168: 3799000 | J168: 3165000 | K168: 2979000 | L168: 3168000 | M168: 3642000 | N168: 4789000 | O168: 4710000
A169: =VLOOKUP(B169,'[1]PORTFOLIO RAW'!B:B,1,FALSE) -> 905620 | B169: 905620 | C169: LOWE'S COMPANIES INC - EBIT & DEPRECIATION | D169: 905620(WC18198) | E169: 6214000 | F169: 5493000 | G169: 4871000 | H169: 5249000 | I169: 4860000 | J169: 5192000 | K169: 5709000 | L169: 6384000 | M169: 6550000 | N169: 7423000 | O169: 7662000
A170: =VLOOKUP(B170,'[1]PORTFOLIO RAW'!B:B,1,FALSE) -> 944314 | B170: 944314 | C170: DOMINION ENERGY INC - EBIT & DEPRECIATION | D170: 944314(WC18198) | E170: 7167000 | F170: 4707000 | G170: 4129000 | H170: 7199000 | I170: 4315000 | J170: 2839000 | K170: 4971000 | L170: 4531000 | M170: 5401000 | N170: 5726000 | O170: 6247000
A171: =VLOOKUP(B171,'[1]PORTFOLIO RAW'!B:B,1,FALSE) -> 357366 | B171: 357366 | C171: MACERICH CO - EBIT & DEPRECIATION | D171: 357366(WC18198) | E171: 539443 | F171: 594357 | G171: 646487 | H171: 412969 | I171: 386372 | J171: 713082 | K171: 570001 | L171: 2120510 | M171: 1157788 | N171: 1017653 | O171: 604772
A172: =VLOOKUP(B172,'[1]PORTFOLIO RAW'!B:B,1,FALSE) -> 516007 | B172: 516007 | C172: MGM RESORTS - EBIT & DEPRECIATION | D172: 516007(WC18198) | E172: 3404888 | F172: 677782 | G172: -359711 | H172: -278363 | I172: 4763528 | J172: 446244 | K172: 1908615 | L172: 2067670 | M172: 389798 | N172: 2329000 | O172: 2514742
A173: =VLOOKUP(B173,'[1]PORTFOLIO RAW'!B:B,1,FALSE) -> 510493 | B173: 510493 | C173: MCCORMICK & CO INC - EBIT & DEPRECIATION | D173: 510493(WC18198) | E173: 445600 | F173: 480100 | G173: 566300 | H173: 610600 | I173: 644400 | J173: 688200 | K173: 658700 | L173: 711800 | M173: 660500 | N173: 755500 | O173: 816600
A174: =VLOOKUP(B174,'[1]PORTFOLIO RAW'!B:B,1,FALSE) -> 921910 | B174: 921910 | C174: MCDONALD'S CORP - EBIT & DEPRECIATION | D174: 921910(WC18198) | E174: 5080700 | F174: 7777700 | G174: 8010700 | H174: 8564600 | I174: 9739800 | J174: 9940600 | K174: 10233300 | L174: 9595900 | M174: 8896500 | N174: 9212500 | O174: 10674500
A175: =VLOOKUP(B175,'[1]PORTFOLIO RAW'!B:B,1,FALSE) -> 311759 | B175: 311759 | C175: EVEREST RE GROUP - EBIT & DEPRECIATION | D175: 311759(WC18198) | E175: NA | F175: NA | G175: NA | H175: NA | I175: NA | J175: NA | K175: 1601084 | L175: 1484648 | M175: 1244700 | N175: 1136072 | O175: 436787
A176: =VLOOKUP(B176,'[1]PORTFOLIO RAW'!B:B,1,FALSE) -> 912588 | B176: 912588 | C176: HOST HOTELS - EBIT & DEPRECIATION | D176: 912588(WC18198) | E176: 1468000 | F176: 1371000 | G176: 786000 | H176: 818000 | I176: 1002000 | J176: 1076000 | K176: 1249000 | L176: 1650000 | M176: 1460000 | N176: 1668000 | O176: 1538000
A177: =VLOOKUP(B177,'[1]PORTFOLIO RAW'!B:B,1,FALSE) -> 904780 | B177: 904780 | C177: MARSH & MCLENNAN CO. - EBIT & DEPRECIATION | D177: 904780(WC18198) | E177: 1556000 | F177: 703000 | G177: 891000 | H177: 1316000 | I177: 1926000 | J177: 2226000 | K177: 2498000 | L177: 2610000 | M177: 2893000 | N177: 3107000 | O177: 3361000
A178: =VLOOKUP(B178,'[1]PORTFOLIO RAW'!B:B,1,FALSE) -> 905624 | B178: 905624 | C178: MASCO CORP - EBIT & DEPRECIATION | D178: 905624(WC18198) | E178: 1276000 | F178: 255000 | G178: 338000 | H178: -247000 | I178: 45000 | J178: 510000 | K178: 855000 | L178: 967000 | M178: 1061000 | N178: 1218000 | O178: 1314000
A179: =VLOOKUP(B179,'[1]PORTFOLIO RAW'!B:B,1,FALSE) -> 130062 | B179: 130062 | C179: MARTIN MARIETTA MAT - EBIT & DEPRECIATION | D179: 130062(WC18198) | E179: 591853 | F179: 488727 | G179: 368113 | H179: 377700 | I179: 332600 | J179: 333463 | K179: 391454 | L179: 538000 | M179: 753700 | N179: 974000 | O179: 1007600
A180: =VLOOKUP(B180,'[1]PORTFOLIO RAW'!B:B,1,FALSE) -> 286738 | B180: 286738 | C180: METLIFE INC - EBIT & DEPRECIATION | D180: 286738(WC18198) | E180: 6543000 | F180: 6655000 | G180: -2789000 | H180: 5144000 | I180: 11650000 | J180: 2530000 | K180: 6048000 | L180: 10733000 | M180: 9371000 | N180: 1658000 | O180: 5460000
A181: =VLOOKUP(B181,'[1]PORTFOLIO RAW'!B:B,1,FALSE) -> 771830 | B181: 771830 | C181: MAXIM INTEGRATED PRD - EBIT & DEPRECIATION | D181: 771830(WC18198) | E181: 518323 | F181: 644687 | G181: 240042 | H181: NA | I181: 876208 | J181: 747546 | K181: 792515 | L181: 678519 | M181: 578113 | N181: 562391 | O181: 878181
A182: =VLOOKUP(B182,'[1]PORTFOLIO RAW'!B:B,1,FALSE) -> 312367 | B182: 312367 | C182: ACTIVISION BLIZZARD - EBIT & DEPRECIATION | D182: 312367(WC18198) | E182: 241000 | F182: 201000 | G182: 343000 | H182: 695000 | I182: 1483000 | J182: 1579000 | K182: 1675000 | L182: 1342000 | M182: 1825000 | N182: 2487000 | O182: 2516000
A183: =VLOOKUP(B183,'[1]PORTFOLIO RAW'!B:B,1,FALSE) -> 912635 | B183: 912635 | C183: CVS HEALTH CORP - EBIT & DEPRECIATION | D183: 912635(WC18198) | E183: 5921600 | F183: 7340700 | G183: 7832000 | H183: 7637000 | I183: 7902000 | J183: 9156000 | K183: 9939000 | L183: 10224000 | M183: 11586000 | N183: 12210000 | O183: 11847000
A184: =VLOOKUP(B184,'[1]PORTFOLIO RAW'!B:B,1,FALSE) -> 152533 | B184: 152533 | C184: LAB CORP OF AMERICA - EBIT & DEPRECIATION | D184: 152533(WC18198) | E184: 943800 | F184: 1023000 | G184: 1128800 | H184: 1178600 | I184: 1175500 | J184: 1247100 | K184: 1225300 | L184: 1167400 | M184: 1454800 | N184: 1815900 | O184: 1891900
A185: =VLOOKUP(B185,'[1]PORTFOLIO RAW'!B:B,1,FALSE) -> 719643 | B185: 719643 | C185: MICROSOFT CORP - EBIT & DEPRECIATION | D185: 719643(WC18198) | E185: 21575000 | F185: 25870000 | G185: 22421000 | H185: 27671000 | I185: 30903000 | J185: 25405000 | K185: 31236000 | L185: 33629000 | M185: 25245000 | N185: 27616000 | O185: 34149000
A186: =VLOOKUP(B186,'[1]PORTFOLIO RAW'!B:B,1,FALSE) -> 999506 | B186: 999506 | C186: MICRON TECHNOLOGY - EBIT & DEPRECIATION | D186: 999506(WC18198) | E186: 1590000 | F186: 531000 | G186: 470000 | H186: 4103000 | I186: 2780000 | J186: 1531000 | K186: 3320000 | L186: 5188000 | M186: 5647000 | N186: 3136000 | O186: 9663000
A187: =VLOOKUP(B187,'[1]PORTFOLIO RAW'!B:B,1,FALSE) -> 328228 | B187: 328228 | C187: MICROCHIP TECHNOLOGY - EBIT & DEPRECIATION | D187: 328228(WC18198) | E187: 522677 | F187: 459027 | G187: 357565 | H187: 359020 | I187: 598674 | J187: 513580 | K187: 397809 | L187: 670386 | M187: 686558 | N187: 668856 | O187: 705563
A188: =VLOOKUP(B188,'[1]PORTFOLIO RAW'!B:B,1,FALSE) -> 902172 | B188: 902172 | C188: 3M COMPANY - EBIT & DEPRECIATION | D188: 902172(WC18198) | E188: 7397000 | F188: 6476000 | G188: 5946000 | H188: 7057000 | I188: 7452000 | J188: 7832000 | K188: 8035000 | L188: 8536000 | M188: 8377000 | N188: 8726000 | O188: 9510000
A189: =VLOOKUP(B189,'[1]PORTFOLIO RAW'!B:B,1,FALSE) -> 325475 | B189: 325475 | C189: MOHAWK INDUSTRIES - EBIT & DEPRECIATION | D189: 325475(WC18198) | E189: 1065023 | F189: -856062 | G189: 352322 | H189: 615072 | I189: 599225 | J189: 711524 | K189: 846688 | L189: 1107668 | M189: 1182594 | N189: 1691139 | O189: 1795640
A190: =VLOOKUP(B190,'[1]PORTFOLIO RAW'!B:B,1,FALSE) -> 905010 | B190: 905010 | C190: XCEL ENERGY INC - EBIT & DEPRECIATION | D190: 905010(WC18198) | E190: 2245460 | F190: 2378197 | G190: 2394044 | H190: 2544998 | I190: 2778017 | J190: 2851124 | K190: 3047186 | L190: 3209649 | M190: 3308796 | N190: 3719944 | O190: 3873000
A191: =VLOOKUP(B191,'[1]PORTFOLIO RAW'!B:B,1,FALSE) -> 902230 | B191: 902230 | C191: FORD MOTOR COMPANY - EBIT & DEPRECIATION | D191: 902230(WC18198) | E191: 19950000 | F191: 8040000 | G191: 17862000 | H191: 18920000 | I191: 18205000 | J191: 17332000 | K191: 16107000 | L191: 13986000 | M191: 19654000 | N191: 17741000 | O191: 20398000
A192: =VLOOKUP(B192,'[1]PORTFOLIO RAW'!B:B,1,FALSE) -> 884383 | B192: 884383 | C192: NATL OILWELL VARCO - EBIT & DEPRECIATION | D192: 884383(WC18198) | E192: 2293300 | F192: 3387800 | G192: 2704000 | H192: 2918000 | I192: 3471000 | J192: 4124000 | K192: 4149000 | L192: 4320000 | M192: 248000 | N192: -1794000 | O192: 413000
...

Sheet EQIT
A1: EQUITY
B2: Code | C2: Name | D2: Code | E2: 2007 | F2: 2008 | G2: 2009 | H2: 2010 | I2: 2011 | J2: 2012 | K2: 2013 | L2: 2014 | M2: 2015 | N2: 2016 | O2: 2017
A3: =VLOOKUP(B3,'[1]PORTFOLIO RAW'!B:B,1,FALSE) -> 891399 | B3: 891399 | C3: AMAZON.COM INC - COMMON SHAREHOLDERS' EQUITY | D3: 891399(WC03501) | E3: 1197000 | F3: 2672000 | G3: 5257000 | H3: 6864000 | I3: 7757000 | J3: 8192000 | K3: 9746000 | L3: 10741000 | M3: 13384000 | N3: 19285000 | O3: 27709000
A4: =VLOOKUP(B4,'[1]PORTFOLIO RAW'!B:B,1,FALSE) -> 916328 | B4: 916328 | C4: ABBOTT LABORATORIES - COMMON SHAREHOLDERS' EQUITY | D4: 916328(WC03501) | E4: 17778540 | F4: 17479551 | G4: 22855627 | H4: 22388135 | I4: 24439833 | J4: 26720961 | K4: 25171000 | L4: 21526000 | M4: 21211000 | N4: 20538000 | O4: 30897000
A5: =VLOOKUP(B5,'[1]PORTFOLIO RAW'!B:B,1,FALSE) -> 545101 | B5: 545101 | C5: AES CORP - COMMON SHAREHOLDERS' EQUITY | D5: 545101(WC03501) | E5: 3164000 | F5: 3669000 | G5: 4675000 | H5: 6473000 | I5: 5946000 | J5: 4569000 | K5: 4330000 | L5: 4272000 | M5: 3149000 | N5: 2794000 | O5: 2465000
A6: =VLOOKUP(B6,'[1]PORTFOLIO RAW'!B:B,1,FALSE) -> 906187 | B6: 906187 | C6: INT'L BUSINESS MACHS - COMMON SHAREHOLDERS' EQUITY | D6: 906187(WC03501) | E6: 28469000 | F6: 13465000 | G6: 22637000 | H6: 23046000 | I6: 20139000 | J6: 18860000 | K6: 22792000 | L6: 11869000 | M6: 14262000 | N6: 18246000 | O6: 17594000
A7: =VLOOKUP(B7,'[1]PORTFOLIO RAW'!B:B,1,FALSE) -> 936365 | B7: 936365 | C7: ADVANCED MICRO - COMMON SHAREHOLDERS' EQUITY | D7: 936365(WC03501) | E7: 2990000 | F7: -82000 | G7: 648000 | H7: 1013000 | I7: 1590000 | J7: 538000 | K7: 544000 | L7: 187000 | M7: -412000 | N7: 416000 | O7: 611000
A8: =VLOOKUP(B8,'[1]PORTFOLIO RAW'!B:B,1,FALSE) -> 749382 | B8: 749382 | C8: ADOBE INC - COMMON SHAREHOLDERS' EQUITY | D8: 749382(WC03501) | E8: 4649982 | F8: 4410354 | G8: 4890568 | H8: 5192387 | I8: 5783113 | J8: 6665182 | K8: 6724634 | L8: 6775905 | M8: 7001580 | N8: 7424835 | O8: 8459869
A9: =VLOOKUP(B9,'[1]PORTFOLIO RAW'!B:B,1,FALSE) -> 905271 | B9: 905271 | C9: AIR PRODUCTS & CHEMS - COMMON SHAREHOLDERS' EQUITY | D9: 905271(WC03501) | E9: 5495600 | F9: 5030700 | G9: 4791900 | H9: 5546900 | I9: 5795800 | J9: 6477200 | K9: 7042100 | L9: 7365800 | M9: 7249000 | N9: 7079600 | O9: 10086200
A10: =VLOOKUP(B10,'[1]PORTFOLIO RAW'!B:B,1,FALSE) -> 894371 | B10: 894371 | C10: BOSTON PROPERTIES - COMMON SHAREHOLDERS' EQUITY | D10: 894371(WC03501) | E10: 3668825 | F10: 3531267 | G10: 4446002 | H10: 4372643 | I10: 4865998 | J10: 5097065 | K10: 5541153 | L10: 5697298 | M10: 5709435 | N10: 5586295 | O10: 5613957
A11: =VLOOKUP(B11,'[1]PORTFOLIO RAW'!B:B,1,FALSE) -> 322677 | B11: 322677 | C11: ALLSTATE CORP - COMMON SHAREHOLDERS' EQUITY | D11: 322677(WC03501) | E11: 20963000 | F11: 16379000 | G11: 17562000 | H11: 18081000 | I11: 17311000 | J11: 17746000 | K11: 19054000 | L11: 18632000 | M11: 17600000 | N11: 17715000 | O11: 19084000
A12: =VLOOKUP(B12,'[1]PORTFOLIO RAW'!B:B,1,FALSE) -> 906191 | B12: 906191 | C12: HONEYWELL INTERNATNL - COMMON SHAREHOLDERS' EQUITY | D12: 906191(WC03501) | E12: 9222000 | F12: 7187000 | G12: 8844000 | H12: 10666000 | I12: 10806000 | J12: 12975000 | K12: 17467000 | L12: 17657000 | M12: 18283000 | N12: 19369000 | O12: 17276000
A13: =VLOOKUP(B13,'[1]PORTFOLIO RAW'!B:B,1,FALSE) -> 938692 | B13: 938692 | C13: AMGEN INC - COMMON SHAREHOLDERS' EQUITY | D13: 938692(WC03501) | E13: 17869000 | F13: 20386000 | G13: 22667000 | H13: 23944000 | I13: 19029000 | J13: 19060000 | K13: 22096000 | L13: 25778000 | M13: 28083000 | N13: 29875000 | O13: 25241000
A14: =VLOOKUP(B14,'[1]PORTFOLIO RAW'!B:B,1,FALSE) -> 905802 | B14: 905802 | C14: HESS CORPORATION - COMMON SHAREHOLDERS' EQUITY | D14: 905802(WC03501) | E14: 9760000 | F14: 12307000 | G14: 13384000 | H14: 16689000 | I14: 18516000 | J14: 21090000 | K14: 24720000 | L14: 22205000 | M14: 19386000 | N14: 14533000 | O14: 11050000
... A108: =VLOOKUP(B108,'[1]PORTFOLIO RAW'!B:B,1,FALSE) -> 905016 | B108: 905016 | C108: NEXTERA ENERGY - COMMON SHAREHOLDERS' EQUITY | D108: 905016(WC03501) | E108: 10735000 | F108: 11681000 | G108: 12967000 | H108: 14461000 | I108: 14943000 | J108: 16068000 | K108: 18040000 | L108: 19916000 | M108: 22574000 | N108: 24341000 | O108: 28208000
A109: =VLOOKUP(B109,'[1]PORTFOLIO RAW'!B:B,1,FALSE) -> 28341F | B109: 28341F | C109: ASSURANT INC - COMMON SHAREHOLDERS' EQUITY | D109: 28341F(WC03501) | E109: 4065519 | F109: 4187905 | G109: 4658699 | H109: 4367282 | I109: 4313163 | J109: 5185366 | K109: 4280981 | L109: 4361631 | M109: 4006090 | N109: 3618201 | O109: 3671500
A110: =VLOOKUP(B110,'[1]PORTFOLIO RAW'!B:B,1,FALSE) -> 755980 | B110: 755980 | C110: FASTENAL COMPANY - COMMON SHAREHOLDERS' EQUITY | D110: 755980(WC03501) | E110: 1010161 | F110: 1142259 | G110: 1190843 | H110: 1282512 | I110: 1458976 | J110: 1560360 | K110: 1772697 | L110: 1915217 | M110: 1801289 | N110: 1933094 | O110: 2096900
A111: =VLOOKUP(B111,'[1]PORTFOLIO RAW'!B:B,1,FALSE) -> 905994 | B111: 905994 | C111: FEDERAL REALTY INVST - COMMON SHAREHOLDERS' EQUITY | D111: 905994(WC03501) | E111: 1105438 | F111: 1104605 | G111: 1167340 | H111: 1139836 | I111: 1206095 | J111: 1276815 | K111: 1438163 | L111: 1594404 | M111: 1653752 | N111: 1966736 | O111: 2106709
A112: =VLOOKUP(B112,'[1]PORTFOLIO RAW'!B:B,1,FALSE) -> 997198 | B112: 997198 | C112: FIFTH THIRD BANCORP - COMMON SHAREHOLDERS' EQUITY | D112: 997198(WC03501) | E112: 9152000 | F112: 7836000 | G112: 9678000 | H112: 10232000 | I112: 12790000 | J112: 13305000 | K112: 13555000 | L112: 14295000 | M112: 14508000 | N112: 14874000 | O112: 15034000
A113: =VLOOKUP(B113,'[1]PORTFOLIO RAW'!B:B,1,FALSE) -> 951503 | B113: 951503 | C113: M&T BANK CORPORATION - COMMON SHAREHOLDERS' EQUITY | D113: 951503(WC03501) | E113: 6485256 | F113: 6184731 | G113: 6974907 | H113: 7579695 | I113: 8406624 | J113: 9321093 | K113: 10424032 | L113: 11104396 | M113: 14941789 | N113: 15255122 | O113: 15019319
A114: =VLOOKUP(B114,'[1]PORTFOLIO RAW'!B:B,1,FALSE) -> 741123 | B114: 741123 | C114: FISERV INC - COMMON SHAREHOLDERS' EQUITY | D114: 741123(WC03501) | E114: 2467000 | F114: 2594000 | G114: 3026000 | H114: 3229000 | I114: 3258000 | J114: 3417000 | K114: 3585000 | L114: 3295000 | M114: 2660000 | N114: 2541000 | O114: 2731000
A115: =VLOOKUP(B115,'[1]PORTFOLIO RAW'!B:B,1,FALSE) -> 546814 | B115: 546814 | C115: MACY'S INC - COMMON SHAREHOLDERS' EQUITY | D115: 546814(WC03501) | E115: 9907000 | F115: 4646000 | G115: 4701000 | H115: 5530000 | I115: 5933000 | J115: 6051000 | K115: 6249000 | L115: 5378000 | M115: 4250000 | N115: 4323000 | O115: 5673000
A116: =VLOOKUP(B116,'[1]PORTFOLIO RAW'!B:B,1,FALSE) -> 938076 | B116: 938076 | C116: FRANKLIN RESOURCES - COMMON SHAREHOLDERS' EQUITY | D116: 938076(WC03501) | E116: 7332275 | F116: 7074364 | G116: 7632173 | H116: 7726994 | I116: 8524731 | J116: 9201300 | K116: 10073100 | L116: 11584100 | M116: 11841000 | N116: 11935800 | O116: 12620000
A117: =VLOOKUP(B117,'[1]PORTFOLIO RAW'!B:B,1,FALSE) -> 152594 | B117: 152594 | C117: FREEPORT-MCMORAN INC - COMMON SHAREHOLDERS' EQUITY | D117: 152594(WC03501) | E117: 14259000 | F117: 2066000 | G117: 6244000 | H117: 12504000 | I117: 15642000 | J117: 17543000 | K117: 20934000 | L117: 18287000 | M117: 7828000 | N117: 6051000 | O117: 7977000
A118: =VLOOKUP(B118,'[1]PORTFOLIO RAW'!B:B,1,FALSE) -> 951018 | B118: 951018 | C118: GAP INC - COMMON SHAREHOLDERS' EQUITY | D118: 951018(WC03501) | E118: 4274000 | F118: 4387000 | G118: 4891000 | H118: 4080000 | I118: 2755000 | J118: 2894000 | K118: 3062000 | L118: 2983000 | M118: 2545000 | N118: 2904000 | O118: 3144000
A119: =VLOOKUP(B119,'[1]PORTFOLIO RAW'!B:B,1,FALSE) -> 907652 | B119: 907652 | C119: GENERAL DYNAMICS - COMMON SHAREHOLDERS' EQUITY | D119: 907652(WC03501) | E119: 11768000 | F119: 10053000 | G119: 12423000 | H119: 13316000 | I119: 13232000 | J119: 11390000 | K119: 14501000 | L119: 11829000 | M119: 10738000 | N119: 10976000 | O119: 11435000
A120: =VLOOKUP(B120,'[1]PORTFOLIO RAW'!B:B,1,FALSE) -> 905801 | B120: 905801 | C120: GENERAL MILLS, INC. - COMMON SHAREHOLDERS' EQUITY | D120: 905801(WC03501) | E120: 5319000 | F120: 6215800 | G120: 5174700 | H120: 5402900 | I120: 6365500 | J120: 6421700 | K120: 6672200 | L120: 6534800 | M120: 4996700 | N120: 4930200 | O120: 4327900
A121: =VLOOKUP(B121,'[1]PORTFOLIO RAW'!B:B,1,FALSE) -> 906511 | B121: 906511 | C121: GENUINE PARTS CO - COMMON SHAREHOLDERS' EQUITY | D121: 906511(WC03501) | E121: 2716716 | F121: 2324332 | G121: 2621330 | H121: 2793819 | I121: 2783235 | J121: 2997887 | K121: 3349074 | L121: 3301248 | M121: 3146567 | N121: 3193728 | O121: 3412152
... A235: =VLOOKUP(B235,'[1]PORTFOLIO RAW'!B:B,1,FALSE) -> 933974 | B235: 933974 | C235: TRAVELERS COS - COMMON SHAREHOLDERS' EQUITY | D235: 933974(WC03501) | E235: 25885000 | F235: 25374000 | G235: 25475000 | H235: 23549000 | I235: 21606000 | J235: 22302000 | K235: 23474000 | L235: 22870000 | M235: 22309000 | N235: 22491000 | O235: 22777000
A236: =VLOOKUP(B236,'[1]PORTFOLIO RAW'!B:B,1,FALSE) -> 14015T | B236: 14015T | C236: FIDELITY NATNL INF - COMMON SHAREHOLDERS' EQUITY | D236: 14015T(WC03501) | E236: 3781179 | F236: 3532800 | G236: 8308900 | H236: 6403200 | I236: 6503000 | J236: 6640900 | K236: 6580500 | L236: 6556700 | M236: 9321000 | N236: 9741000 | O236: 10835000
A237: =VLOOKUP(B237,'[1]PORTFOLIO RAW'!B:B,1,FALSE) -> 905019 | B237: 905019 | C237: MERCK & CO INC - COMMON SHAREHOLDERS' EQUITY | D237: 905019(WC03501) | E237: 18184700 | F237: 18758300 | G237: 59058000 | H237: 54376000 | I237: 54517000 | J237: 53020000 | K237: 49765000 | L237: 48647000 | M237: 44676000 | N237: 40088000 | O237: 34336000
A238: =VLOOKUP(B238,'[1]PORTFOLIO RAW'!B:B,1,FALSE) -> 912090 | B238: 912090 | C238: SCHLUMBERGER LIMITED - COMMON SHAREHOLDERS' EQUITY | D238: 912090(WC03501) | E238: 14876000 | F238: 16863000 | G238: 19120000 | H238: 31226000 | I238: 31263000 | J238: 34751000 | K238: 39469000 | L238: 37850000 | M238: 35633000 | N238: 41078000 | O238: 36842000
A239: =VLOOKUP(B239,'[1]PORTFOLIO RAW'!B:B,1,FALSE) -> 755741 | B239: 755741 | C239: CHARLES SCHWAB CORP - COMMON SHAREHOLDERS' EQUITY | D239: 755741(WC03501) | E239: 3732000 | F239: 4061000 | G239: 5073000 | H239: 6226000 | I239: 7714000 | J239: 8704000 | K239: 9496000 | L239: 10918000 | M239: 11917000 | N239: 13586000 | O239: 15675000
A240: =VLOOKUP(B240,'[1]PORTFOLIO RAW'!B:B,1,FALSE) -> 14361V | B240: 14361V | C240: ZIMMER BIOMET - COMMON SHAREHOLDERS' EQUITY | D240: 14361V(WC03501) | E240: 5449600 | F240: 5650300 | G240: 5638700 | H240: 5771300 | I240: 5507200 | J240: 5860900 | K240: 6297300 | L240: 6520800 | M240: 9887900 | N240: 9668900 | O240: 11735800
A241: =VLOOKUP(B241,'[1]PORTFOLIO RAW'!B:B,1,FALSE) -> 154680 | B241: 154680 | C241: AMERISOURCEBERGEN - COMMON SHAREHOLDERS' EQUITY | D241: 154680(WC03501) | E241: 3099720 | F241: 2710045 | G241: 2716469 | H241: 2954297 | I241: 2866858 | J241: 2456712 | K241: 2319745 | L241: 1956899 | M241: 633520 | N241: 2129404 | O241: 2064461
A242: =VLOOKUP(B242,'[1]PORTFOLIO RAW'!B:B,1,FALSE) -> 14698C | B242: 14698C | C242: PRINCIPAL FINL GROUP - COMMON SHAREHOLDERS' EQUITY | D242: 14698C(WC03501) | E242: 6854600 | F242: 6393600 | G242: 8284000 | H242: 9045100 | I242: 8709200 | J242: 8267500 | K242: 9434200 | L242: 10183900 | M242: 9311600 | N242: 10227300 | O242: 11335900
A243: =VLOOKUP(B243,'[1]PORTFOLIO RAW'!B:B,1,FALSE) -> 905361 | B243: 905361 | C243: SHERWIN-WILLIAMS CO - COMMON SHAREHOLDERS' EQUITY | D243: 905361(WC03501) | E243: 1785727 | F243: 1605648 | G243: 1490950 | H243: 1609440 | I243: 1516919 | J243: 1690718 | K243: 1734129 | L243: 996470 | M243: 867910 | N243: 1878441 | O243: 3692188
A244: =VLOOKUP(B244,'[1]PORTFOLIO RAW'!B:B,1,FALSE) -> 357834 | B244: 357834 | C244: SIMON PROPERTY GROUP - COMMON SHAREHOLDERS' EQUITY | D244: 357834(WC03501) | E244: 2833974 | F244: 2614638 | G244: 4412433 | H244: 4785405 | I244: 4604619 | J244: 5865884 | K244: 5805016 | L244: 5049115 | M244: 4427731 | N244: 4267043 | O244: 3643091
A245: =VLOOKUP(B245,'[1]PORTFOLIO RAW'!B:B,1,FALSE) -> 906400 | B245: 906400 | C245: SNAP-ON INC - COMMON SHAREHOLDERS' EQUITY | D245: 906400(WC03501) | E245: 1280100 | F245: 1186500 | G245: 1290000 | H245: 1388500 | I245: 1530900 | J245: 1802100 | K245: 2113200 | L245: 2207800 | M245: 2412700 | N245: 2617200 | O245: 2953900
A246: =VLOOKUP(B246,'[1]PORTFOLIO RAW'!B:B,1,FALSE) -> 14861V | B246: 14861V | C246: PRUDENTIAL FINANCIAL - COMMON SHAREHOLDERS' EQUITY | D246: 14861V(WC03501) | E246: 23057000 | F246: 20157000 | G246: 24684000 | H246: 29270000 | I246: 31588000 | J246: 27173000 | K246: 24934000 | L246: 22519000 | M246: 26117000 | N246: 27692000 | O246: 34101000
A247: =VLOOKUP(B247,'[1]PORTFOLIO RAW'!B:B,1,FALSE) -> 14806F | B247: 14806F | C247: ADVANCE AUTO PARTS - COMMON SHAREHOLDERS' EQUITY | D247: 14806F(WC03501) | E247: 1023795 | F247: 1075166 | G247: 1282365 | H247: 1039374 | I247: 847914 | J247: 1210694 | K247: 1516205 | L247: 2002912 | M247: 2460648 | N247: 2916192 | O247: 3415196
A248: =VLOOKUP(B248,'[1]PORTFOLIO RAW'!B:B,1,FALSE) -> 902324 | B248: 902324 | C248: EDISON INTERNATIONAL - COMMON SHAREHOLDERS' EQUITY | D248: 902324(WC03501) | E248: 8444000 | F248: 9517000 | G248: 9841000 | H248: 10583000 | I248: 10055000 | J248: 9432000 | K248: 9925000 | L248: 10960000 | M248: 11368000 | N248: 11996000 | O248: 11671000
A249: =VLOOKUP(B249,'[1]PORTFOLIO RAW'!B:B,1,FALSE) -> 902325 | B249: 902325 | C249: SOUTHERN CO - COMMON SHAREHOLDERS' EQUITY | D249: 902325(WC03501) | E249: 12385000 | F249: 13276000 | G249: 14878000 | H249: 16202000 | I249: 17578000 | J249: 18297000 | K249: 19008000 | L249: 19949000 | M249: 20592000 | N249: 24758000 | O249: 24167000
A250: =VLOOKUP(B250,'[1]PORTFOLIO RAW'!B:B,1,FALSE) -> 992305 | B250: 992305 | C250: BB&T CORPORATION - COMMON SHAREHOLDERS' EQUITY | D250: 992305(WC03501) | E250: 12632000 | F250: 12955000 | G250: 16191000 | H250: 16436000 | I250: 17418000 | J250: 18983000 | K250: 20156000 | L250: 21663000 | M250: 24631000 | N250: 26741000 | O250: 26508000
A251: =VLOOKUP(B251,'[1]PORTFOLIO RAW'!B:B,1,FALSE) -> 905647 | B251: 905647 | C251: SOUTHWEST AIRLINES - COMMON SHAREHOLDERS' EQUITY | D251: 905647(WC03501) | E251: 6941000 | F251: 4953000 | G251: 5466000 | H251: 6237000 | I251: 6877000 | J251: 6992000 | K251: 7336000 | L251: 6775000 | M251: 7358000 | N251: 8441000 | O251: 10430000
A252: =VLOOKUP(B252,'[1]PORTFOLIO RAW'!B:B,1,FALSE) -> 945388 | B252: 945388 | C252: AT&T INC - COMMON SHAREHOLDERS' EQUITY | D252: 945388(WC03501) | E252: 115367000 | F252: 96347000 | G252: 101900000 | H252: 111647000 | I252: 105534000 | J252: 92362000 | K252: 90988000 | L252: 86370000 | M252: 122671000 | N252: 123135000 | O252: 140861000
A253: =VLOOKUP(B253,'[1]PORTFOLIO RAW'!B:B,1,FALSE) -> 905024 | B253: 905024 | C253: CHEVRON CORPORATION - COMMON SHAREHOLDERS' EQUITY | D253: 905024(WC03501) | E253: 77089000 | F253: 86648000 | G253: 91914000 | H253: 105081000 | I253: 121382000 | J253: 136524000 | K253: 149113000 | L253: 155028000 | M253: 152716000 | N253: 145556000 | O253: 148124000
A254: =VLOOKUP(B254,'[1]PORTFOLIO RAW'!B:B,1,FALSE) -> 951052 | B254: 951052 | C254: STATE STREET CORP - COMMON SHAREHOLDERS' EQUITY | D254: 951052(WC03501) | E254: 11299000 | F254: 10891000 | G254: 14491000 | H254: 17787000 | I254: 18898000 | J254: 20380000 | K254: 19887000 | L254: 19512000 | M254: 18400000 | N254: 18023000 | O254: 19121000
A255: =VLOOKUP(B255,'[1]PORTFOLIO RAW'!B:B,1,FALSE) -> 326143 | B255: 326143 | C255: STARBUCKS CORP - COMMON SHAREHOLDERS' EQUITY | D255: 326143(WC03501) | E255: 2284117 | F255: 2490900 | G255: 3045700 | H255: 3674700 | I255: 4384900 | J255: 5109000 | K255: 4480200 | L255: 5272000 | M255: 5818000 | N255: 5884000 | O255: 5450100
A256: =VLOOKUP(B256,'[1]PORTFOLIO RAW'!B:B,1,FALSE) -> 905792 | B256: 905792 | C256: PUBLIC STORAGE, INC - COMMON SHAREHOLDERS' EQUITY | D256: 905792(WC03501) | E256: 5235629 | F256: 5291137 | G256: 5528630 | H256: 5280571 | I256: 5176938 | J256: 5256256 | K256: 5229230 | L256: 5155796 | M256: 5115641 | N256: 5044410 | O256: 4915009
A257: =VLOOKUP(B257,'[1]PORTFOLIO RAW'!B:B,1,FALSE) -> 981722 | B257: 981722 | C257: STRYKER CORPORATION - COMMON SHAREHOLDERS' EQUITY | D257: 981722(WC03501) | E257: 5378500 | F257: 5406700 | G257: 6595100 | H257: 7173600 | I257: 7683000 | J257: 8597000 | K257: 9047000 | L257: 8595000 | M257: 8511000 | N257: 9550000 | O257: 9966000
A258: =VLOOKUP(B258,'[1]PORTFOLIO RAW'!B:B,1,FALSE) -> 922725 | B258: 922725 | C258: SUNTRUST BANKS INC - COMMON SHAREHOLDERS' EQUITY | D258: 922725(WC03501) | E258: 17552518 | F258: 17166406 | G258: 17495055 | H258: 18188000 | I258: 19791000 | J258: 20260000 | K258: 20697000 | L258: 21780000 | M258: 22212000 | N258: 22393000 | O258: 22679000
A259: =VLOOKUP(B259,'[1]PORTFOLIO RAW'!B:B,1,FALSE) -> 541900 | B259: 541900 | C259: SYMANTEC CORP - COMMON SHAREHOLDERS' EQUITY | D259: 541900(WC03501) | E259: 11601513 | F259: 10973183 | G259: 3947988 | H259: 4548000 | I259: 4528000 | J259: 5094000 | K259: 5421000 | L259: 5797000 | M259: 5935000 | N259: 3676000 | O259: 3487000
... A282: =VLOOKUP(B282,'[1]PORTFOLIO RAW'!B:B,1,FALSE) -> 904869 | B282: 904869 | C282: WHIRLPOOL CORP - COMMON SHAREHOLDERS' EQUITY | D282: 904869(WC03501) | E282: 3911000 | F282: 3006000 | G282: 3664000 | H282: 4226000 | I282: 4181000 | J282: 4260000 | K282: 4924000 | L282: 4885000 | M282: 4743000 | N282: 4773000 | O282: 4198000
A283: =VLOOKUP(B283,'[1]PORTFOLIO RAW'!B:B,1,FALSE) -> 26406N | B283: 26406N | C283: WYNN RESORTS, LTD - COMMON SHAREHOLDERS' EQUITY | D283: 26406N(WC03501) | E283: 1948159 | F283: 1592522 | G283: 3034338 | H283: 2237948 | I283: 2089022 | J283: -259037 | K283: -184507 | L283: -28779 | M283: -111979 | N283: 157949 | O283: 947846
A284: =VLOOKUP(B284,'[1]PORTFOLIO RAW'!B:B,1,FALSE) -> 26393N | B284: 26393N | C284: CME GROUP INC - COMMON SHAREHOLDERS' EQUITY | D284: 26393N(WC03501) | E284: 12305637 | F284: 18688569 | G284: 19301000 | H284: 20060100 | I284: 21552000 | J284: 21419100 | K284: 21154800 | L284: 20923500 | M284: 20551800 | N284: 20340700 | O284: 22411800
A285: =VLOOKUP(B285,'[1]PORTFOLIO RAW'!B:B,1,FALSE) -> 922407 | B285: 922407 | C285: WILLIAMS COMPANIES - COMMON SHAREHOLDERS' EQUITY | D285: 922407(WC03501) | E285: 6375000 | F285: 8440000 | G285: 8447000 | H285: 7288000 | I285: 1793000 | J285: 4752000 | K285: 4864000 | L285: 8777000 | M285: 6148000 | N285: 4643000 | O285: 9656000
A286: =VLOOKUP(B286,'[1]PORTFOLIO RAW'!B:B,1,FALSE) -> 906979 | B286: 906979 | C286: ALLIANT ENERGY CORP - COMMON SHAREHOLDERS' EQUITY | D286: 906979(WC03501) | E286: 2681200 | F286: 2823500 | G286: 2772600 | H286: 2893600 | I286: 3013000 | J286: 3134900 | K286: 3281400 | L286: 3438700 | M286: 3724100 | N286: 3862000 | O286: 4182200
A287: =VLOOKUP(B287,'[1]PORTFOLIO RAW'!B:B,1,FALSE) -> 877723 | B287: 877723 | C287: CARMAX INC - COMMON SHAREHOLDERS' EQUITY | D287: 877723(WC03501) | E287: 1247375 | F287: 1488926 | G287: 1593067 | H287: 1933582 | I287: 2291630 | J287: 2673112 | K287: 3019167 | L287: 3316997 | M287: 3156785 | N287: 2904786 | O287: 3108580
A288: =VLOOKUP(B288,'[1]PORTFOLIO RAW'!B:B,1,FALSE) -> 543542 | B288: 543542 | C288: XILINX INC - COMMON SHAREHOLDERS' EQUITY | D288: 543542(WC03501) | E288: 1772740 | F288: 1671823 | G288: 1737900 | H288: 2120470 | I288: 2414617 | J288: 2707685 | K288: 2963296 | L288: 2787681 | M288: 2635541 | N288: 2602787 | O288: 2509039
A289: =VLOOKUP(B289,'[1]PORTFOLIO RAW'!B:B,1,FALSE) -> 26276P | B289: 26276P | C289: CIMAREX ENERGY CO - COMMON SHAREHOLDERS' EQUITY | D289: 26276P(WC03501) | E289: 3259287 | F289: 2349365 | G289: 2038106 | H289: 2609832 | I289: 3130613 | J289: 3474736 | K289: 4022208 | L289: 4500632 | M289: 2797678 | N289: 2360064 | O289: 2568278
A290: =VLOOKUP(B290,'[1]PORTFOLIO RAW'!B:B,1,FALSE) -> 921855 | B290: 921855 | C290: TJX COMPANIES INC - COMMON SHAREHOLDERS' EQUITY | D290: 921855(WC03501) | E290: 2131245 | F290: 2134557 | G290: 2889276 | H290: 3099899 | I290: 3209290 | J290: 3665937 | K290: 4229893 | L290: 4264230 | M290: 4307075 | N290: 4510599 | O290: 5148309
A291: =VLOOKUP(B291,'[1]PORTFOLIO RAW'!B:B,1,FALSE) -> 951584 | B291: 951584 | C291: ZIONS BANCORP - COMMON SHAREHOLDERS' EQUITY | D291: 951584(WC03501) | E291: 5052800 | F291: 4919862 | G291: 4189874 | H291: 4591607 | I291: 4607748 | J291: 4923767 | K291: 5460593 | L291: 6365519 | M291: 6679029 | N291: 6924705 | O291: 7113000
A292: =VLOOKUP(B292,'[1]PORTFOLIO RAW'!B:B,1,FALSE) -> 951051 | B292: 951051 | C292: REGIONS FINANCIAL - COMMON SHAREHOLDERS' EQUITY | D292: 951051(WC03501) | E292: 19823029 | F292: 13312837 | G292: 14113000 | H292: 13234000 | I292: 12999000 | J292: 14999000 | K292: 15268000 | L292: 15989000 | M292: 15844000 | N292: 15664000 | O292: 15192000
A293: =VLOOKUP(B293,'[1]PORTFOLIO RAW'!B:B,1,FALSE) -> 29756N | B293: 29756N | C293: CELANESE CORPORATION - COMMON SHAREHOLDERS' EQUITY | D293: 29756N(WC03501) | E293: 1062000 | F293: 182000 | G293: 584000 | H293: 926000 | I293: 1341000 | J293: 1730000 | K293: 2699000 | L293: 2818000 | M293: 2378000 | N293: 2588000 | O293: 2887000
A294: =VLOOKUP(B294,'[1]PORTFOLIO RAW'!B:B,1,FALSE) -> 905997 | B294: 905997 | C294: MOLSON COORS BREW - COMMON SHAREHOLDERS' EQUITY | D294: 905997(WC03501) | E294: 7149391 | F294: 5980300 | G294: 7079600 | H294: 7798800 | I294: 7647900 | J294: 7966900 | K294: 8638900 | L294: 7863300 | M294: 7043000 | N294: 11418700 | O294: 13226100
A295: =VLOOKUP(B295,'[1]PORTFOLIO RAW'!B:B,1,FALSE) -> 31604H | B295: 31604H | C295: AMERIPRISE FIN - COMMON SHAREHOLDERS' EQUITY | D295: 31604H(WC03501) | E295: 7810000 | F295: 6178000 | G295: 9273000 | H295: 10725000 | I295: 10255000 | J295: 9092000 | K295: 8192000 | L295: 8124000 | M295: 7217000 | N295: 6292000 | O295: 5998000
A296: =VLOOKUP(B296,'[1]PORTFOLIO RAW'!B:B,1,FALSE) -> 543487 | B296: 543487 | C296: VIACOM, INC. - COMMON SHAREHOLDERS' EQUITY | D296: 543487(WC03501) | E296: 7111200 | F296: 7033000 | G296: 8704000 | H296: 9283000 | I296: 8644000 | J296: 7448000 | K296: 5193000 | L296: 3719000 | M296: 3538000 | N296: 4277000 | O296: 6035000
A297: =VLOOKUP(B297,'[1]PORTFOLIO RAW'!B:B,1,FALSE) -> 32480Q | B297: 32480Q | C297: CBS CORPORATION - COMMON SHAREHOLDERS' EQUITY | D297: 32480Q(WC03501) | E297: 21472400 | F297: 8597300 | G297: 9019400 | H297: 9820600 | I297: 9908000 | J297: 10213000 | K297: 9966000 | L297: 6970000 | M297: 5563000 | N297: 3689000 | O297: 1978000
A298: =VLOOKUP(B298,'[1]PORTFOLIO RAW'!B:B,1,FALSE) -> 41071J | B298: 41071J | C298: HANESBRANDS, INC. - COMMON SHAREHOLDERS' EQUITY | D298: 41071J(WC03501) | E298: 288904 | F298: 185155 | G298: 334719 | H298: 562674 | I298: 681061 | J298: 886866 | K298: 1230623 | L298: 1386772 | M298: 1275891 | N298: 1223914 | O298: 686202
A299: =VLOOKUP(B299,'[1]PORTFOLIO RAW'!B:B,1,FALSE) -> 41195M | B299: 41195M | C299: WESTERN UNION COMP - COMMON SHAREHOLDERS' EQUITY | D299: 41195M(WC03501) | E299: 50700 | F299: -8100 | G299: 353500 | H299: 582700 | I299: 894800 | J299: 940600 | K299: 1104700 | L299: 1300400 | M299: 1404900 | N299: 902200 | O299: -491400
A300: =VLOOKUP(B300,'[1]PORTFOLIO RAW'!B:B,1,FALSE) -> 517465 | B300: 517465 | C300: PEOPLE'S UNITED - COMMON SHAREHOLDERS' EQUITY | D300: 517465(WC03501) | E300: 4445400 | F300: 5175500 | G300: 5100700 | H300: 5219300 | I300: 5225000 | J300: 5038800 | K300: 4568400 | L300: 4633100 | M300: 4731600 | N300: 4897800 | O300: 5575800
A301: =VLOOKUP(B301,'[1]PORTFOLIO RAW'!B:B,1,FALSE) -> 905840 | B301: 905840 | C301: BANK OF NEW YORK - COMMON SHAREHOLDERS' EQUITY | D301: 905840(WC03501) | E301: 29403000 | F301: 25050000 | G301: 28977000 | H301: 32354000 | I301: 33417000 | J301: 35363000 | K301: 35959000 | L301: 35879000 | M301: 35485000 | N301: 35269000 | O301: 37709000
A302: =VLOOKUP(B302,'[1]PORTFOLIO RAW'!B:B,1,FALSE) -> 51245V | B302: 51245V | C302: INVESCO LTD. - COMMON SHAREHOLDERS' EQUITY | D302: 51245V(WC03501) | E302: 6590600 | F302: 5689500 | G302: 6912900 | H302: 8264600 | I302: 8119100 | J302: 8316800 | K302: 8392600 | L302: 8326000 | M302: 7885300 | N302: 7503800 | O302: 8696100
A303: =VLOOKUP(B303,'[1]PORTFOLIO RAW'!B:B,1,FALSE) -> 328314 | B303: 328314 | C303: CHUBB - COMMON SHAREHOLDERS' EQUITY | D303: 328314(WC03501) | E303: 16079000 | F303: 16158000 | G303: 19010000 | H303: 21575000 | I303: 22801000 | J303: 24898000 | K303: 27651000 | L303: 27736000 | M303: 28261000 | N303: 47217000 | O303: 49722000
A304: =VLOOKUP(B304,'[1]PORTFOLIO RAW'!B:B,1,FALSE) -> 31196R | B304: 31196R | C304: DISCOVERY INC - COMMON SHAREHOLDERS' EQUITY | D304: 31196R(WC03501) | E304: 2708262 | F304: 5534000 | G304: 6206000 | H304: 6223000 | I304: 6515000 | J304: 6289000 | K304: 6194000 | L304: 5600000 | M304: 5449000 | N304: 5165000 | O304: 4610000
A305: =VLOOKUP(B305,'[1]PORTFOLIO RAW'!B:B,1,FALSE) -> 771767 | B305: 771767 | C305: MOSAIC CO - COMMON SHAREHOLDERS' EQUITY | D305: 771767(WC03501) | E305: 4183900 | F305: 6731200 | G305: 8493000 | H305: 8722200 | I305: 11641600 | J305: 11983100 | K305: 11302300 | L305: 10703100 | M305: 9531800 | N305: 9584600 | O305: 9617500
A306: =VLOOKUP(B306,'[1]PORTFOLIO RAW'!B:B,1,FALSE) -> 921503 | B306: 921503 | C306: STANLEY BLACK - COMMON SHAREHOLDERS' EQUITY | D306: 921503(WC03501) | E306: 1728500 | F306: 1688000 | G306: 1986100 | H306: 7017000 | I306: 7003600 | J306: 6667100 | K306: 6799200 | L306: 6429100 | M306: 5811600 | N306: 6367000 | O306: 7547100
A307: =VLOOKUP(B307,'[1]PORTFOLIO RAW'!B:B,1,FALSE) -> 255781 | B307: 255781 | C307: GARMIN LTD. - COMMON SHAREHOLDERS' EQUITY | D307: 255781(WC03501) | E307: 2350614 | F307: 2225854 | G307: 2836447 | H307: 3049562 | I307: 3256581 | J307: 3531796 | K307: 3659706 | L307: 3403367 | M307: 3345126 | N307: 3418003 | O307: 3802466
A308: =VLOOKUP(B308,'[1]PORTFOLIO RAW'!B:B,1,FALSE) -> 670129 | B308: 670129 | C308: PROLOGIS - COMMON SHAREHOLDERS' EQUITY | D308: 670129(WC03501) | E308: 2531452 | F308: 2282607 | G308: 2707516 | H308: 3088223 | I308: 13079439 | J308: 12486817 | K308: 13611158 | L308: 13897274 | M308: 14589700 | N308: 14912846 | O308: 15562208
A309: =VLOOKUP(B309,'[1]PORTFOLIO RAW'!B:B,1,FALSE) -> 14352P | B309: 14352P | C309: ACCENTURE PLC - COMMON SHAREHOLDERS' EQUITY | D309: 14352P(WC03501) | E309: 2063332 | F309: 2540506 | G309: 2886593 | H309: 2835746 | I309: 3878951 | J309: 4145833 | K309: 4960186 | L309: 5732035 | M309: 6133725 | N309: 7555262 | O309: 8949477
A310: =VLOOKUP(B310,'[1]PORTFOLIO RAW'!B:B,1,FALSE) -> 749688 | B310: 749688 | C310: HCA HEALTHCARE - COMMON SHAREHOLDERS' EQUITY | D310: 749688(WC03501) | E310: -10538000 | F310: -10255000 | G310: -8986000 | H310: -9702000 | I310: -8258000 | J310: -9660000 | K310: -8270000 | L310: -7894000 | M310: -7599000 | N310: -7302000 | O310: -6806000
A311: =VLOOKUP(B311,'[1]PORTFOLIO RAW'!B:B,1,FALSE) -> 894145 | B311: 894145 | C311: RALPH LAUREN - COMMON SHAREHOLDERS' EQUITY | D311: 894145(WC03501) | E311: 2334900 | F311: 2389700 | G311: 2735100 | H311: 3116600 | I311: 3304700 | J311: 3652500 | K311: 3784600 | L311: 4034000 | M311: 3891000 | N311: 3744000 | O311: 3299600
A312: =VLOOKUP(B312,'[1]PORTFOLIO RAW'!B:B,1,FALSE) -> 26599V | B312: 26599V | C312: SEAGATE TECHNOLOGY - COMMON SHAREHOLDERS' EQUITY | D312: 26599V(WC03501) | E312: 4737000 | F312: 4586000 | G312: 1524000 | H312: 2724000 | I312: 2463000 | J312: 3497000 | K312: 3495000 | L312: 2832000 | M312: 3018000 | N312: 1593000 | O312: 1364000
A313: =VLOOKUP(B313,'[1]PORTFOLIO RAW'!B:B,1,FALSE) -> 904878 | B313: 904878 | C313: MOTOROLA SOLUTIONS - COMMON SHAREHOLDERS' EQUITY | D313: 904878(WC03501) | E313: 15447000 | F313: 9507000 | G313: 9775000 | H313: 10885000 | I313: 5214000 | J313: 3265000 | K313: 3659000 | L313: 2735000 | M313: -106000 | N313: -964000 | O313: -1742000
A314: =VLOOKUP(B314,'[1]PORTFOLIO RAW'!B:B,1,FALSE) -> 922817 | B314: 922817 | C314: AON PLC - COMMON SHAREHOLDERS' EQUITY | D314: 922817(WC03501) | E314: 6121000 | F314: 5267000 | G314: 5335000 | H314: 8251000 | I314: 8078000 | J314: 7762000 | K314: 8145000 | L314: 6571000 | M314: 6106000 | N314: 5475000 | O314: 4583000
A315: =VLOOKUP(B315,'[1]PORTFOLIO RAW'!B:B,1,FALSE) -> 905446 | B315: 905446 | C315: INGERSOLL-RAND - COMMON SHAREHOLDERS' EQUITY | D315: 905446(WC03501) | E315: 5416912 | F315: 4782885 | G315: 4957056 | H315: 6033435 | I315: 5345560 | J315: 5418032 | K315: 5146159 | L315: 4951580 | M315: 5357181 | N315: 6298322 | O315: 5955010
A316: =VLOOKUP(B316,'[1]PORTFOLIO RAW'!B:B,1,FALSE) -> 28513N | B316: 28513N | C316: CBRE GROUP - COMMON SHAREHOLDERS' EQUITY | D316: 28513N(WC03501) | E316: 988603 | F316: 114686 | G316: 629122 | H316: 908215 | I316: 1151481 | J316: 1539211 | K316: 1895785 | L316: 2259830 | M316: 2712652 | N316: 3014487 | O316: 4019430
A317: =VLOOKUP(B317,'[1]PORTFOLIO RAW'!B:B,1,FALSE) -> 31412T | B317: 31412T | C317: EXPEDIA GROUP INC - COMMON SHAREHOLDERS' EQUITY | D317: 31412T(WC03501) | E317: 4818081 | F317: 2328394 | G317: 2682681 | H317: 2672544 | I317: 2199864 | J317: 2280259 | K317: 2145464 | L317: 1784267 | M317: 4864394 | N317: 4132301 | O317: 4522335
A318: =VLOOKUP(B318,'[1]PORTFOLIO RAW'!B:B,1,FALSE) -> 680902 | B318: 680902 | C318: AMERICAN TOWER CORP - COMMON SHAREHOLDERS' EQUITY | D318: 680902(WC03501) | E318: 3022092 | F318: 2991322 | G318: 3315082 | H318: 3501444 | I318: 3287220 | J318: 3573101 | K318: 3534165 | L318: 3953500 | M318: 4676679 | N318: 4788895 | O318: 6240100
A319: =VLOOKUP(B319,'[1]PORTFOLIO RAW'!B:B,1,FALSE) -> 904383 | B319: 904383 | C319: DUKE ENERGY CORP - COMMON SHAREHOLDERS' EQUITY | D319: 904383(WC03501) | E319: 21199000 | F319: 20988000 | G319: 21750000 | H319: 22522000 | I319: 22772000 | J319: 40863000 | K319: 41330000 | L319: 40875000 | M319: 39727000 | N319: 41033000 | O319: 41739000
A320: =VLOOKUP(B320,'[1]PORTFOLIO RAW'!B:B,1,FALSE) -> 13967E | B320: 13967E | C320: MONDELEZ - COMMON SHAREHOLDERS' EQUITY | D320: 13967E(WC03501) | E320: 27295000 | F320: 22200000 | G320: 25876000 | H320: 35834000 | I320: 35217000 | J320: 32215000 | K320: 32373000 | L320: 27750000 | M320: 28012000 | N320: 25161000 | O320: 26111000
A321: =VLOOKUP(B321,'[1]PORTFOLIO RAW'!B:B,1,FALSE) -> 903749 | B321: 903749 | C321: EATON CORP PLC - COMMON SHAREHOLDERS' EQUITY | D321: 903749(WC03501) | E321: 5172000 | F321: 6317000 | G321: 6777000 | H321: 7362000 | I321: 7469000 | J321: 15086000 | K321: 16791000 | L321: 15786000 | M321: 15186000 | N321: 14897000 | O321: 17253000
A322: =VLOOKUP(B322,'[1]PORTFOLIO RAW'!B:B,1,FALSE) -> 937343 | B322: 937343 | C322: L BRANDS INC - COMMON SHAREHOLDERS' EQUITY | D322: 937343(WC03501) | E322: 2219000 | F322: 1874000 | G322: 2183000 | H322: 1476000 | I322: 137000 | J322: -1015000 | K322: -370000 | L322: 18000 | M322: -259000 | N322: -729000 | O322: -753000
A323: =VLOOKUP(B323,'[1]PORTFOLIO RAW'!B:B,1,FALSE) -> 905113 | B323: 905113 | C323: ARCONIC INC - COMMON SHAREHOLDERS' EQUITY | D323: 905113(WC03501) | E323: 15961000 | F323: 11680000 | G323: 12365000 | H323: 13556000 | I323: 13789000 | J323: 13144000 | K323: 10538000 | L323: 12248000 | M323: 11988000 | N323: 5057000 | O323: 4855000
A324: =VLOOKUP(B324,'[1]PORTFOLIO RAW'!B:B,1,FALSE) -> 13967H | B324: 13967H | C324: WILLIS TOWERS WAT - COMMON SHAREHOLDERS' EQUITY | D324: 13967H(WC03501) | E324: 1347000 | F324: 1845000 | G324: 2180000 | H324: 2577000 | I324: 2486000 | J324: 1699000 | K324: 2215000 | L324: 1985000 | M324: 2229000 | N324: 10065000 | O324: 10126000
A325: =VLOOKUP(B325,'[1]PORTFOLIO RAW'!B:B,1,FALSE) -> 921431 | B325: 921431 | C325: BAKER HUGHES A GE CO - COMMON SHAREHOLDERS' EQUITY | D325: 921431(WC03501) | E325: 6305600 | F325: 6807000 | G325: 7284000 | H325: 14100000 | I325: 15746000 | J325: 17069000 | K325: 17713000 | L325: 18625000 | M325: 16298000 | N325: 12656000 | O325: 39033000
A326: =VLOOKUP(B326,'[1]PORTFOLIO RAW'!B:B,1,FALSE) -> 266220 | B326: 266220 | C326: TAPESTRY INC - COMMON SHAREHOLDERS' EQUITY | D326: 266220(WC03501) | E326: 1910354 | F326: 1515820 | G326: 1696042 | H326: 1505293 | I326: 1612569 | J326: 1992931 | K326: 2409158 | L326: 2420653 | M326: 2489900 | N326: 2682900 | O326: 3001900
A327: =VLOOKUP(B327,'[1]PORTFOLIO RAW'!B:B,1,FALSE) -> 30730Q | B327: 30730Q | C327: INTERCONTINENTAL - COMMON SHAREHOLDERS' EQUITY | D327: 30730Q(WC03501) | E327: 1476856 | F327: 2006231 | G327: 2399732 | H327: 2777550 | I327: 3121525 | J327: 3643377 | K327: 12583000 | L327: 12360000 | M327: 14808000 | N327: 15717000 | O327: 16924000
A328: =VLOOKUP(B328,'[1]PORTFOLIO RAW'!B:B,1,FALSE) -> 921925 | B328: 921925 | C328: JEFFERIES FINANCIAL - COMMON SHAREHOLDERS' EQUITY | D328: 921925(WC03501) | E328: 5570492 | F328: 2676797 | G328: 4361647 | H328: 6956758 | I328: 6174396 | J328: 6767268 | K328: 10102462 | L328: 10302158 | M328: 10401211 | N328: 10128100 | O328: 10105957
...

Sheet DEBT
A1: DEBT
B2: Code | C2: Name | D2: Code | E2: 2007 | F2: 2008 | G2: 2009 | H2: 2010 | I2: 2011 | J2: 2012 | K2: 2013 | L2: 2014 | M2: 2015 | N2: 2016 | O2: 2017
A3: =VLOOKUP(B3,'[1]PORTFOLIO RAW'!B:B,1,FALSE) -> 891399 | B3: 891399 | C3: AMAZON.COM INC - TOTAL DEBT | D3: 891399(WC03255) | E3: 1361000 | F3: 592000 | G3: 393000 | H3: 865000 | I3: 1939000 | J3: 4964000 | K3: 6917000 | L3: 16089000 | M3: 17547000 | N3: 20410000 | O3: 44147000
A4: =VLOOKUP(B4,'[1]PORTFOLIO RAW'!B:B,1,FALSE) -> 916328 | B4: 916328 | C4: ABBOTT LABORATORIES - TOTAL DEBT | D4: 916328(WC03255) | E4: 12213704 | F4: 11445302 | G4: 15880914 | H4: 18268283 | I4: 14734577 | J4: 19860964 | K4: 6056000 | L4: 7400000 | M4: 8562000 | N4: 21552000 | O4: 27924000
A5: =VLOOKUP(B5,'[1]PORTFOLIO RAW'!B:B,1,FALSE) -> 545101 | B5: 545101 | C5: AES CORP - TOTAL DEBT | D5: 545101(WC03255) | E5: 17994000 | F5: 18091000 | G5: 19916000 | H5: 19733000 | I5: 22573000 | J5: 21373000 | K5: 21049000 | L5: 20858000 | M5: 20807000 | N5: 20463000 | O5: 19965000
A6: =VLOOKUP(B6,'[1]PORTFOLIO RAW'!B:B,1,FALSE) -> 906187 | B6: 906187 | C6: INT'L BUSINESS MACHS - TOTAL DEBT | D6: 906187(WC03255) | E6: 35274000 | F6: 33925000 | G6: 26100000 | H6: 28624000 | I6: 31320000 | J6: 33269000 | K6: 39718000 | L6: 40804000 | M6: 39889000 | N6: 42168000 | O6: 46824000
A7: =VLOOKUP(B7,'[1]PORTFOLIO RAW'!B:B,1,FALSE) -> 936365 | B7: 936365 | C7: ADVANCED MICRO - TOTAL DEBT | D7: 936365(WC03255) | E7: 5269000 | F7: 5074000 | G7: 4731000 | H7: 2421000 | I7: 2016000 | J7: 2042000 | K7: 2058000 | L7: 2212000 | M7: 2262000 | N7: 1435000 | O7: 1395000
A8: =VLOOKUP(B8,'[1]PORTFOLIO RAW'!B:B,1,FALSE) -> 749382 | B8: 749382 | C8: ADOBE INC - TOTAL DEBT | D8: 749382(WC03255) | E8: 0 | F8: 350000 | G8: 1000000 | H8: 1522461 | I8: 1514308 | J8: 1508155 | K8: 1513973 | L8: 1514315 | M8: 1907231 | N8: 1902068 | O8: 1881421
A9: =VLOOKUP(B9,'[1]PORTFOLIO RAW'!B:B,1,FALSE) -> 905271 | B9: 905271 | C9: AIR PRODUCTS & CHEMS - TOTAL DEBT | D9: 905271(WC03255) | E9: 3677200 | F9: 3966800 | G9: 4501500 | H9: 4159700 | I9: 4562200 | J9: 5291900 | K9: 6273600 | L9: 6118500 | M9: 5879000 | N9: 6225200 | O9: 3962800
A10: =VLOOKUP(B10,'[1]PORTFOLIO RAW'!B:B,1,FALSE) -> 894371 | B10: 894371 | C10: BOSTON PROPERTIES - TOTAL DEBT | D10: 894371(WC03255) | E10: 5492166 | F10: 6271916 | G10: 6719771 | H10: 7786001 | I10: 8704138 | J10: 8912369 | K10: 11521509 | L10: 10086984 | M10: 9216513 | N10: 9796133 | O10: 10271611
A11: =VLOOKUP(B11,'[1]PORTFOLIO RAW'!B:B,1,FALSE) -> 322677 | B11: 322677 | C11: ALLSTATE CORP - TOTAL DEBT | D11: 322677(WC03255) | E11: 5640000 | F11: 5659000 | G11: 5910000 | H11: 5908000 | I11: 5908000 | J11: 6057000 | K11: 6245000 | L11: 5205000 | M11: 5129000 | N11: 6347000 | O11: 6350000
A12: =VLOOKUP(B12,'[1]PORTFOLIO RAW'!B:B,1,FALSE) -> 906191 | B12: 906191 | C12: HONEYWELL INTERNATNL - TOTAL DEBT | D12: 906191(WC03255) | E12: 7657000 | F12: 8375000 | G12: 7607000 | H12: 6644000 | I12: 7555000 | J12: 7496000 | K12: 8829000 | L12: 8683000 | M12: 12068000 | N12: 15775000 | O12: 17882000
A13: =VLOOKUP(B13,'[1]PORTFOLIO RAW'!B:B,1,FALSE) -> 938692 | B13: 938692 | C13: AMGEN INC - TOTAL DEBT | D13: 938692(WC03255) | E13: 11177000 | F13: 10176000 | G13: 10601000 | H13: 13362000 | I13: 21428000 | J13: 26529000 | K13: 32128000 | L13: 30715000 | M13: 31556000 | N13: 34596000 | O13: 35342000
A14: =VLOOKUP(B14,'[1]PORTFOLIO RAW'!B:B,1,FALSE) -> 905802 | B14: 905802 | C14: HESS CORPORATION - TOTAL DEBT | D14: 905802(WC03255) | E14: 3980000 | F14: 3955000 | G14: 4467000 | H14: 5583000 | I14: 6057000 | J14: 8111000 | K14: 5798000 | L14: 5987000 | M14: 6630000 | N14: 6806000 | O14: 6977000
... A108: =VLOOKUP(B108,'[1]PORTFOLIO RAW'!B:B,1,FALSE) -> 905016 | B108: 905016 | C108: NEXTERA ENERGY - TOTAL DEBT | D108: 905016(WC03255) | E108: 13698000 | F108: 17086000 | G108: 18889000 | H108: 20822000 | I108: 22967000 | J108: 27359000 | K108: 28426000 | L108: 29024000 | M108: 29687000 | N108: 30840000 | O108: 35081000
A109: =VLOOKUP(B109,'[1]PORTFOLIO RAW'!B:B,1,FALSE) -> 28341F | B109: 28341F | C109: ASSURANT INC - TOTAL DEBT | D109: 28341F(WC03255) | E109: 993023 | F109: 983117 | G109: 980218 | H109: 977164 | I109: 972278 | J109: 972399 | K109: 1638118 | L109: 1171079 | M109: 1171382 | N109: 1067020 | O109: 1068200
A110: =VLOOKUP(B110,'[1]PORTFOLIO RAW'!B:B,1,FALSE) -> 755980 | B110: 755980 | C110: FASTENAL COMPANY - TOTAL DEBT | D110: 755980(WC03255) | E110: 0 | F110: 0 | G110: 0 | H110: 0 | I110: 0 | J110: 0 | K110: 0 | L110: 90000 | M110: 365000 | N110: 390000 | O110: 415000
A111: =VLOOKUP(B111,'[1]PORTFOLIO RAW'!B:B,1,FALSE) -> 905994 | B111: 905994 | C111: FEDERAL REALTY INVST - TOTAL DEBT | D111: 905994(WC03255) | E111: 1638460 | F111: 1745785 | G111: 1793848 | H111: 1767149 | I111: 2110410 | J111: 2208602 | K111: 2321862 | L111: 2409677 | M111: 2642366 | N111: 2798452 | O111: 3284766
A112: =VLOOKUP(B112,'[1]PORTFOLIO RAW'!B:B,1,FALSE) -> 997198 | B112: 997198 | C112: FIFTH THIRD BANCORP - TOTAL DEBT | D112: 997198(WC03255) | E112: 22031000 | F112: 23831000 | G112: 12104000 | H112: 11411000 | I112: 13267000 | J112: 14266000 | K112: 11297000 | L112: 16667000 | M112: 16920000 | N112: 17681000 | O112: 18749000
A113: =VLOOKUP(B113,'[1]PORTFOLIO RAW'!B:B,1,FALSE) -> 951503 | B113: 951503 | C113: M&T BANK CORPORATION - TOTAL DEBT | D113: 951503(WC03255) | E113: 16139842 | F113: 15084884 | G113: 12682598 | H113: 8787583 | I113: 7468308 | J113: 5682240 | K113: 5369325 | L113: 9199635 | M113: 12786040 | N113: 9657277 | O113: 8316529
A114: =VLOOKUP(B114,'[1]PORTFOLIO RAW'!B:B,1,FALSE) -> 741123 | B114: 741123 | C114: FISERV INC - TOTAL DEBT | D114: 741123(WC03255) | E114: 5405000 | F114: 4105000 | G114: 3641000 | H114: 3356000 | I114: 3395000 | J114: 3230000 | K114: 3848000 | L114: 3803000 | M114: 4293000 | N114: 4562000 | O114: 4900000
A115: =VLOOKUP(B115,'[1]PORTFOLIO RAW'!B:B,1,FALSE) -> 546814 | B115: 546814 | C115: MACY'S INC - TOTAL DEBT | D115: 546814(WC03255) | E115: 9753000 | F115: 9699000 | G115: 8698000 | H115: 7425000 | I115: 7758000 | J115: 6930000 | K115: 7672000 | L115: 7341000 | M115: 7637000 | N115: 6871000 | O115: 5883000
A116: =VLOOKUP(B116,'[1]PORTFOLIO RAW'!B:B,1,FALSE) -> 938076 | B116: 938076 | C116: FRANKLIN RESOURCES - TOTAL DEBT | D116: 938076(WC03255) | E116: 822898 | F116: 269271 | G116: 121156 | H116: 979900 | I116: 2168437 | J116: 2777200 | K116: 2295100 | L116: 2149000 | M116: 2155300 | N116: 2083400 | O116: 1097600
A117: =VLOOKUP(B117,'[1]PORTFOLIO RAW'!B:B,1,FALSE) -> 152594 | B117: 152594 | C117: FREEPORT-MCMORAN INC - TOTAL DEBT | D117: 152594(WC03255) | E117: 7211000 | F117: 7351000 | G117: 6346000 | H117: 4755000 | I117: 3537000 | J117: 3527000 | K117: 20706000 | L117: 18970000 | M117: 20428000 | N117: 16027000 | O117: 13117000
A118: =VLOOKUP(B118,'[1]PORTFOLIO RAW'!B:B,1,FALSE) -> 951018 | B118: 951018 | C118: GAP INC - TOTAL DEBT | D118: 951018(WC03255) | E118: 188000 | F118: 50000 | G118: 0 | H118: 0 | I118: 1665000 | J118: 1246000 | K118: 1394000 | L118: 1353000 | M118: 1731000 | N118: 1313000 | O118: 1249000
A119: =VLOOKUP(B119,'[1]PORTFOLIO RAW'!B:B,1,FALSE) -> 907652 | B119: 907652 | C119: GENERAL DYNAMICS - TOTAL DEBT | D119: 907652(WC03255) | E119: 2791000 | F119: 4024000 | G119: 3864000 | H119: 3203000 | I119: 3930000 | J119: 3909000 | K119: 3943000 | L119: 3942000 | M119: 3431000 | N119: 3918000 | O119: 4009000
A120: =VLOOKUP(B120,'[1]PORTFOLIO RAW'!B:B,1,FALSE) -> 905801 | B120: 905801 | C120: GENERAL MILLS, INC. - TOTAL DEBT | D120: 905801(WC03255) | E120: 6206000 | F120: 6999500 | G120: 7075500 | H120: 6425900 | I120: 6885100 | J120: 7429600 | K120: 7969100 | L120: 8785800 | M120: 9223900 | N120: 8430900 | O120: 9481700
A121: =VLOOKUP(B121,'[1]PORTFOLIO RAW'!B:B,1,FALSE) -> 906511 | B121: 906511 | C121: GENUINE PARTS CO - TOTAL DEBT | D121: 906511(WC03255) | E121: 513707 | F121: 512708 | G121: 513504 | H121: 512622 | I121: 500000 | J121: 500000 | K121: 792473 | L121: 805506 | M121: 662642 | N121: 914221 | O121: 3300702
... A235: =VLOOKUP(B235,'[1]PORTFOLIO RAW'!B:B,1,FALSE) -> 933974 | B235: 933974 | C235: TRAVELERS COS - TOTAL DEBT | D235: 933974(WC03255) | E235: 6242000 | F235: 6181000 | G235: 6527000 | H235: 6611000 | I235: 6605000 | J235: 6350000 | K235: 6346000 | L235: 6349000 | M235: 6344000 | N235: 6437000 | O235: 6571000
A236: =VLOOKUP(B236,'[1]PORTFOLIO RAW'!B:B,1,FALSE) -> 14015T | B236: 14015T | C236: FIDELITY NATNL INF - TOTAL DEBT | D236: 14015T(WC03255) | E236: 4275397 | F236: 2514500 | G236: 3253300 | H236: 5240000 | I236: 4809800 | J236: 4385500 | K236: 4468600 | L236: 5067700 | M236: 11513100 | N236: 10478000 | O236: 8763000
A237: =VLOOKUP(B237,'[1]PORTFOLIO RAW'!B:B,1,FALSE) -> 905019 | B237: 905019 | C237: MERCK & CO INC - TOTAL DEBT | D237: 905019(WC03255) | E237: 5739400 | F237: 6240400 | G237: 17660700 | H237: 17882000 | I237: 17515000 | J237: 20569000 | K237: 25060000 | L237: 21403000 | M237: 26514000 | N237: 24842000 | O237: 24410000
A238: =VLOOKUP(B238,'[1]PORTFOLIO RAW'!B:B,1,FALSE) -> 912090 | B238: 912090 | C238: SCHLUMBERGER LIMITED - TOTAL DEBT | D238: 912090(WC03255) | E238: 5466101 | F238: 5290888 | G238: 5480000 | H238: 8099000 | I238: 9925000 | J238: 11630000 | K238: 13176000 | L238: 13330000 | M238: 18999000 | N238: 19616000 | O238: 18199000
A239: =VLOOKUP(B239,'[1]PORTFOLIO RAW'!B:B,1,FALSE) -> 755741 | B239: 755741 | C239: CHARLES SCHWAB CORP - TOTAL DEBT | D239: 755741(WC03255) | E239: 899000 | F239: 883000 | G239: 1512000 | H239: 2006000 | I239: 2001000 | J239: 1632000 | K239: 1903000 | L239: 1899000 | M239: 2890000 | N239: 2876000 | O239: 19753000
A240: =VLOOKUP(B240,'[1]PORTFOLIO RAW'!B:B,1,FALSE) -> 14361V | B240: 14361V | C240: ZIMMER BIOMET - TOTAL DEBT | D240: 14361V(WC03255) | E240: 104300 | F240: 460100 | G240: 1127600 | H240: 1142100 | I240: 1719300 | J240: 1820900 | K240: 1672800 | L240: 1425500 | M240: 11556300 | N240: 11241400 | O240: 10142500
A241: =VLOOKUP(B241,'[1]PORTFOLIO RAW'!B:B,1,FALSE) -> 154680 | B241: 154680 | C241: AMERISOURCEBERGEN - TOTAL DEBT | D241: 154680(WC03255) | E241: 1227774 | F241: 1189131 | G241: 1178001 | H241: 1343580 | I241: 1364952 | J241: 1446770 | K241: 1462981 | L241: 2056532 | M241: 3597774 | N241: 4481393 | O241: 3822396
A242: =VLOOKUP(B242,'[1]PORTFOLIO RAW'!B:B,1,FALSE) -> 14698C | B242: 14698C | C242: PRINCIPAL FINL GROUP - TOTAL DEBT | D242: 14698C(WC03255) | E242: 1689600 | F242: 1791400 | G242: 1686200 | H242: 1691600 | I242: 1670000 | J242: 2712100 | K242: 2752300 | L242: 2559200 | M242: 3514700 | N242: 3177100 | O242: 3217900
A243: =VLOOKUP(B243,'[1]PORTFOLIO RAW'!B:B,1,FALSE) -> 905361 | B243: 905361 | C243: SHERWIN-WILLIAMS CO - TOTAL DEBT | D243: 905361(WC03255) | E243: 965448 | F243: 833735 | G243: 817611 | H243: 1044793 | I243: 993367 | J243: 1704889 | K243: 1721872 | L243: 1805416 | M243: 1962812 | N243: 1952540 | O243: 10520655
A244: =VLOOKUP(B244,'[1]PORTFOLIO RAW'!B:B,1,FALSE) -> 357834 | B244: 357834 | C244: SIMON PROPERTY GROUP - TOTAL DEBT | D244: 357834(WC03255) | E244: 17218674 | F244: 18042532 | G244: 18630302 | H244: 17473760 | I244: 18446440 | J244: 23113007 | K244: 23588531 | L244: 20852993 | M244: 22502173 | N244: 22977104 | O244: 24632463
A245: =VLOOKUP(B245,'[1]PORTFOLIO RAW'!B:B,1,FALSE) -> 906400 | B245: 906400 | C245: SNAP-ON INC - TOTAL DEBT | D245: 906400(WC03255) | E245: 517900 | F245: 539200 | G245: 1091500 | H245: 1193800 | I245: 1006600 | J245: 1015200 | K245: 972000 | L245: 919300 | M245: 880100 | N245: 1010200 | O245: 1186800
A246: =VLOOKUP(B246,'[1]PORTFOLIO RAW'!B:B,1,FALSE) -> 14861V | B246: 14861V | C246: PRUDENTIAL FINANCIAL - TOTAL DEBT | D246: 14861V(WC03255) | E246: 47511000 | F246: 42913000 | G246: 33355000 | H246: 33691000 | I246: 36149000 | J246: 33031000 | K246: 37422000 | L246: 39135000 | M246: 37422000 | N246: 28930000 | O246: 28470000
A247: =VLOOKUP(B247,'[1]PORTFOLIO RAW'!B:B,1,FALSE) -> 14806F | B247: 14806F | C247: ADVANCE AUTO PARTS - TOTAL DEBT | D247: 14806F(WC03255) | E247: 535672 | F247: 476752 | G247: 213799 | H247: 311380 | I247: 432165 | J247: 613810 | K247: 1053584 | L247: 1636893 | M247: 1213759 | N247: 1043255 | O247: 1044677
A248: =VLOOKUP(B248,'[1]PORTFOLIO RAW'!B:B,1,FALSE) -> 902324 | B248: 902324 | C248: EDISON INTERNATIONAL - TOTAL DEBT | D248: 902324(WC03255) | E248: 9746000 | F248: 13491000 | G248: 11123000 | H248: 12534000 | I248: 14397000 | J248: 9622000 | K248: 10635000 | L248: 12029000 | M248: 11954000 | N248: 12463000 | O248: 14516000
A249: =VLOOKUP(B249,'[1]PORTFOLIO RAW'!B:B,1,FALSE) -> 902325 | B249: 902325 | C249: SOUTHERN CO - TOTAL DEBT | D249: 902325(WC03255) | E249: 16593000 | F249: 18386000 | G249: 19883000 | H249: 20752000 | I249: 21223000 | J249: 22584000 | K249: 23295000 | L249: 24977000 | M249: 28738000 | N249: 47324000 | O249: 50793000
A250: =VLOOKUP(B250,'[1]PORTFOLIO RAW'!B:B,1,FALSE) -> 992305 | B250: 992305 | C250: BB&T CORPORATION - TOTAL DEBT | D250: 992305(WC03255) | E250: 29327000 | F250: 28820000 | G250: 29482000 | H250: 27403000 | I250: 25369000 | J250: 21978000 | K250: 27774000 | L250: 28144000 | M250: 32686000 | N250: 23371000 | O250: 28586000
A251: =VLOOKUP(B251,'[1]PORTFOLIO RAW'!B:B,1,FALSE) -> 905647 | B251: 905647 | C251: SOUTHWEST AIRLINES - TOTAL DEBT | D251: 905647(WC03255) | E251: 2091000 | F251: 3661000 | G251: 3515000 | H251: 3380000 | I251: 3751000 | J251: 3154000 | K251: 3110000 | L251: 2885000 | M251: 3343000 | N251: 3512000 | O251: 3753000
A252: =VLOOKUP(B252,'[1]PORTFOLIO RAW'!B:B,1,FALSE) -> 945388 | B252: 945388 | C252: AT&T INC - TOTAL DEBT | D252: 945388(WC03255) | E252: 64115000 | F252: 74991000 | G252: 72081000 | H252: 66167000 | I252: 64753000 | J252: 69844000 | K252: 74788000 | L252: 82067000 | M252: 126151000 | N252: 123513000 | O252: 164346000
A253: =VLOOKUP(B253,'[1]PORTFOLIO RAW'!B:B,1,FALSE) -> 905024 | B253: 905024 | C253: CHEVRON CORPORATION - TOTAL DEBT | D253: 905024(WC03255) | E253: 7232000 | F253: 8901000 | G253: 10514000 | H253: 11476000 | I253: 10152000 | J253: 12192000 | K253: 20431000 | L253: 27818000 | M253: 38592000 | N253: 46126000 | O253: 38763000
A254: =VLOOKUP(B254,'[1]PORTFOLIO RAW'!B:B,1,FALSE) -> 951052 | B254: 951052 | C254: STATE STREET CORP - TOTAL DEBT | D254: 951052(WC03255) | E254: 24264000 | F254: 34252000 | G254: 44112000 | H254: 32591000 | I254: 22125000 | J254: 20336000 | K254: 21451000 | L254: 23369000 | M254: 17787000 | N254: 17415000 | O254: 15606000
A255: =VLOOKUP(B255,'[1]PORTFOLIO RAW'!B:B,1,FALSE) -> 326143 | B255: 326143 | C255: STARBUCKS CORP - TOTAL DEBT | D255: 326143(WC03255) | E255: 1264244 | F255: 1270000 | G255: 557300 | H255: 552000 | I255: 550900 | J255: 549600 | K255: 1348200 | L255: 2048300 | M255: 2347500 | N255: 3602200 | O255: 3991700
A256: =VLOOKUP(B256,'[1]PORTFOLIO RAW'!B:B,1,FALSE) -> 905792 | B256: 905792 | C256: PUBLIC STORAGE, INC - TOTAL DEBT | D256: 905792(WC03255) | E256: 1069928 | F256: 643811 | G256: 518889 | H256: 568417 | I256: 398314 | J256: 468828 | K256: 839053 | L256: 64364 | M256: 319016 | N256: 390749 | O256: 1431322
A257: =VLOOKUP(B257,'[1]PORTFOLIO RAW'!B:B,1,FALSE) -> 981722 | B257: 981722 | C257: STRYKER CORPORATION - TOTAL DEBT | D257: 981722(WC03255) | E257: 16800 | F257: 20500 | G257: 18000 | H257: 1021800 | I257: 1768000 | J257: 1762000 | K257: 2764000 | L257: 3973000 | M257: 4022000 | N257: 6914000 | O257: 7222000
A258: =VLOOKUP(B258,'[1]PORTFOLIO RAW'!B:B,1,FALSE) -> 922725 | B258: 922725 | C258: SUNTRUST BANKS INC - TOTAL DEBT | D258: 922725(WC03255) | E258: 35157328 | F258: 36292131 | G258: 22854884 | H258: 19469000 | I258: 22374000 | J258: 14851000 | K258: 19439000 | L258: 22208000 | M258: 13089000 | N258: 18299000 | O258: 15801000
A259: =VLOOKUP(B259,'[1]PORTFOLIO RAW'!B:B,1,FALSE) -> 541900 | B259: 541900 | C259: SYMANTEC CORP - TOTAL DEBT | D259: 541900(WC03255) | E259: 2100000 | F259: 2300000 | G259: 2100000 | H259: 1871000 | I259: 2583000 | J259: 2039000 | K259: 3091000 | L259: 2095000 | M259: 2096000 | N259: 2207000 | O259: 8186000
... A282: =VLOOKUP(B282,'[1]PORTFOLIO RAW'!B:B,1,FALSE) -> 904869 | B282: 904869 | C282: WHIRLPOOL CORP - TOTAL DEBT | D282: 904869(WC03255) | E282: 2093000 | F282: 2597000 | G282: 2903000 | H282: 2509000 | I282: 2491000 | J282: 2461000 | K282: 2463000 | L282: 4347000 | M282: 3998000 | N282: 4470000 | O282: 5218000
A283: =VLOOKUP(B283,'[1]PORTFOLIO RAW'!B:B,1,FALSE) -> 26406N | B283: 26406N | C283: WYNN RESORTS, LTD - TOTAL DEBT | D283: 26406N(WC03255) | E283: 3548379 | F283: 4299177 | G283: 3569103 | H283: 3267529 | I283: 3334998 | J283: 5782820 | K283: 6587568 | L283: 7345262 | M283: 9212765 | N283: 10125352 | O283: 9645226
A284: =VLOOKUP(B284,'[1]PORTFOLIO RAW'!B:B,1,FALSE) -> 26393N | B284: 26393N | C284: CME GROUP INC - TOTAL DEBT | D284: 26393N(WC03255) | E284: 3026461 | F284: 3672762 | G284: 2314500 | H284: 2525300 | I284: 2106800 | J284: 2856500 | K284: 2857100 | L284: 2107900 | M284: 2241400 | N284: 2231200 | O284: 2233100
A285: =VLOOKUP(B285,'[1]PORTFOLIO RAW'!B:B,1,FALSE) -> 922407 | B285: 922407 | C285: WILLIAMS COMPANIES - TOTAL DEBT | D285: 922407(WC03255) | E285: 7900000 | F285: 7879000 | G285: 8276000 | H285: 9108000 | I285: 8722000 | J285: 10736000 | K285: 11579000 | L285: 21690000 | M285: 24487000 | N285: 23502000 | O285: 20935000
A286: =VLOOKUP(B286,'[1]PORTFOLIO RAW'!B:B,1,FALSE) -> 906979 | B286: 906979 | C286: ALLIANT ENERGY CORP - TOTAL DEBT | D286: 906979(WC03255) | E286: 1655900 | F286: 1970800 | G286: 2696000 | H286: 2752100 | I286: 2807300 | J286: 3355600 | K286: 3617700 | L286: 3933000 | M286: 3997400 | N286: 4570300 | O286: 5286500
A287: =VLOOKUP(B287,'[1]PORTFOLIO RAW'!B:B,1,FALSE) -> 877723 | B287: 877723 | C287: CARMAX INC - TOTAL DEBT | D287: 877723(WC03255) | E287: 185477 | F287: 327831 | G287: 337047 | H287: 150571 | I287: 4043785 | J287: 5052706 | K287: 6209036 | L287: 7583410 | M287: 9109252 | N287: 10657832 | O287: 12169704
A288: =VLOOKUP(B288,'[1]PORTFOLIO RAW'!B:B,1,FALSE) -> 543542 | B288: 543542 | C288: XILINX INC - TOTAL DEBT | D288: 543542(WC03255) | E288: 999597 | F288: 999851 | G288: 690125 | H288: 354798 | I288: 890980 | J288: 906569 | K288: 960066 | L288: 1558871 | M288: 1570892 | N288: 1582941 | O288: 1451575
A289: =VLOOKUP(B289,'[1]PORTFOLIO RAW'!B:B,1,FALSE) -> 26276P | B289: 26276P | C289: CIMAREX ENERGY CO - TOTAL DEBT | D289: 26276P(WC03255) | E289: 487159 | F289: 591223 | G289: 392793 | H289: 350000 | I289: 405000 | J289: 750000 | K289: 924000 | L289: 1500000 | M289: 1485620 | N289: 1487939 | O289: 1486920
A290: =VLOOKUP(B290,'[1]PORTFOLIO RAW'!B:B,1,FALSE) -> 921855 | B290: 921855 | C290: TJX COMPANIES INC - TOTAL DEBT | D290: 921855(WC03255) | E290: 855468 | F290: 778809 | G290: 792524 | H290: 790244 | I290: 787593 | J290: 774552 | K290: 1274200 | L290: 1623900 | M290: 1709268 | N290: 2403831 | O290: 2452524
A291: =VLOOKUP(B291,'[1]PORTFOLIO RAW'!B:B,1,FALSE) -> 951584 | B291: 951584 | C291: ZIONS BANCORP - TOTAL DEBT | D291: 951584(WC03255) | E291: 10056547 | F291: 6578168 | G291: 2983634 | H291: 2873822 | I291: 2677319 | J291: 2689735 | K291: 2613923 | L291: 1336505 | M291: 1164335 | N291: 1362119 | O291: 5359000
A292: =VLOOKUP(B292,'[1]PORTFOLIO RAW'!B:B,1,FALSE) -> 951051 | B292: 951051 | C292: REGIONS FINANCIAL - TOTAL DEBT | D292: 951051(WC03255) | E292: 22444912 | F292: 35053239 | G292: 22132000 | H292: 17127000 | I292: 11177000 | J292: 7435000 | K292: 8371000 | L292: 5715000 | M292: 8359000 | N292: 12015000 | O292: 13632000
A293: =VLOOKUP(B293,'[1]PORTFOLIO RAW'!B:B,1,FALSE) -> 29756N | B293: 29756N | C293: CELANESE CORPORATION - TOTAL DEBT | D293: 29756N(WC03255) | E293: 3556000 | F293: 3533000 | G293: 3501000 | H293: 3218000 | I293: 3017000 | J293: 3098000 | K293: 3064000 | L293: 2745000 | M293: 2981000 | N293: 3008000 | O293: 3641000
A294: =VLOOKUP(B294,'[1]PORTFOLIO RAW'!B:B,1,FALSE) -> 905997 | B294: 905997 | C294: MOLSON COORS BREW - TOTAL DEBT | D294: 905997(WC03255) | E294: 2264877 | F294: 1831800 | G294: 1713000 | H294: 1960700 | I294: 1961800 | J294: 4668100 | K294: 3799900 | L294: 3186500 | M294: 2937400 | N294: 12072500 | O294: 11313500
A295: =VLOOKUP(B295,'[1]PORTFOLIO RAW'!B:B,1,FALSE) -> 31604H | B295: 31604H | C295: AMERIPRISE FIN - TOTAL DEBT | D295: 31604H(WC03255) | E295: 2018000 | F295: 2027000 | G295: 2249000 | H295: 8249000 | I295: 8075000 | J295: 7885000 | K295: 8956000 | L295: 10129000 | M295: 10446000 | N295: 5436000 | O295: 5299000
A296: =VLOOKUP(B296,'[1]PORTFOLIO RAW'!B:B,1,FALSE) -> 543487 | B296: 543487 | C296: VIACOM, INC. - TOTAL DEBT | D296: 543487(WC03255) | E296: 8246100 | F296: 8002000 | G296: 6773000 | H296: 6752000 | I296: 7365000 | J296: 8149000 | K296: 11885000 | L296: 12769000 | M296: 12285000 | N296: 11913000 | O296: 11119000
A297: =VLOOKUP(B297,'[1]PORTFOLIO RAW'!B:B,1,FALSE) -> 32480Q | B297: 32480Q | C297: CBS CORPORATION - TOTAL DEBT | D297: 32480Q(WC03255) | E297: 7087700 | F297: 6996100 | G297: 6996900 | H297: 6000800 | I297: 5982000 | J297: 5922000 | K297: 6436000 | L297: 7146000 | M297: 8448000 | N297: 9375000 | O297: 10162000
A298: =VLOOKUP(B298,'[1]PORTFOLIO RAW'!B:B,1,FALSE) -> 41071J | B298: 41071J | C298: HANESBRANDS, INC. - TOTAL DEBT | D298: 41071J(WC03255) | E298: 2334827 | F298: 2238281 | G298: 1980781 | H298: 2131413 | I298: 2037785 | J298: 1517552 | K298: 1684982 | L298: 1983752 | M298: 2624766 | N298: 3742445 | O298: 3963516
A299: =VLOOKUP(B299,'[1]PORTFOLIO RAW'!B:B,1,FALSE) -> 41195M | B299: 41195M | C299: WESTERN UNION COMP - TOTAL DEBT | D299: 41195M(WC03255) | E299: 3338000 | F299: 3143500 | G299: 3048500 | H299: 3289900 | I299: 3583200 | J299: 4029200 | K299: 4213000 | L299: 3720400 | M299: 3225600 | N299: 2786100 | O299: 3033600
A300: =VLOOKUP(B300,'[1]PORTFOLIO RAW'!B:B,1,FALSE) -> 517465 | B300: 517465 | C300: PEOPLE'S UNITED - TOTAL DEBT | D300: 517465(WC03255) | E300: 65400 | F300: 368400 | G300: 340700 | H300: 1192800 | I300: 1016300 | J300: 3045500 | K300: 5696100 | L300: 4725200 | M300: 5346000 | N300: 5086900 | O300: 5005400
A301: =VLOOKUP(B301,'[1]PORTFOLIO RAW'!B:B,1,FALSE) -> 905840 | B301: 905840 | C301: BANK OF NEW YORK - TOTAL DEBT | D301: 905840(WC03255) | E301: 24985000 | F301: 23721000 | G301: 21071000 | H301: 24987000 | I301: 28384000 | J301: 27675000 | K301: 30271000 | L301: 32519000 | M301: 37072000 | N301: 35206000 | O301: 49245000
A302: =VLOOKUP(B302,'[1]PORTFOLIO RAW'!B:B,1,FALSE) -> 51245V | B302: 51245V | C302: INVESCO LTD. - TOTAL DEBT | D302: 51245V(WC03255) | E302: 1393000 | F302: 1159200 | G302: 745700 | H302: 7181100 | I302: 6797600 | J302: 5085400 | K302: 5770300 | L302: 6738900 | M302: 7509800 | N302: 6505500 | O302: 6875600
A303: =VLOOKUP(B303,'[1]PORTFOLIO RAW'!B:B,1,FALSE) -> 328314 | B303: 328314 | C303: CHUBB - TOTAL DEBT | D303: 328314(WC03255) | E303: 2492000 | F303: 3586000 | G303: 3628000 | H303: 4967000 | I303: 4920000 | J303: 5070000 | K303: 6017000 | L303: 6218000 | M303: 11160000 | N303: 14821000 | O303: 14285000
A304: =VLOOKUP(B304,'[1]PORTFOLIO RAW'!B:B,1,FALSE) -> 31196R | B304: 31196R | C304: DISCOVERY INC - TOTAL DEBT | D304: 31196R(WC03255) | E304: 4141091 | F304: 3789000 | G304: 3495000 | H304: 3618000 | I304: 4245000 | J304: 5243000 | K304: 6499000 | L304: 7153000 | M304: 7735000 | N304: 7923000 | O304: 14785000
A305: =VLOOKUP(B305,'[1]PORTFOLIO RAW'!B:B,1,FALSE) -> 771767 | B305: 771767 | C305: MOSAIC CO - TOTAL DEBT | D305: 771767(WC03255) | E305: 2360500 | F305: 1551400 | G305: 1392500 | H305: 1343900 | I305: 832900 | J305: 1053000 | K305: 3031900 | L305: 3832500 | M305: 3859600 | N305: 3818200 | O305: 5227700
A306: =VLOOKUP(B306,'[1]PORTFOLIO RAW'!B:B,1,FALSE) -> 921503 | B306: 921503 | C306: STANLEY BLACK - TOTAL DEBT | D306: 921503(WC03255) | E306: 1504900 | F306: 1647200 | G306: 1383100 | H306: 3435800 | I306: 3452400 | J306: 3538000 | K306: 4202000 | L306: 3847300 | M306: 3844200 | N306: 3827400 | O306: 3831700
A307: =VLOOKUP(B307,'[1]PORTFOLIO RAW'!B:B,1,FALSE) -> 255781 | B307: 255781 | C307: GARMIN LTD. - TOTAL DEBT | D307: 255781(WC03255) | E307: 0 | F307: 0 | G307: 0 | H307: 0 | I307: 0 | J307: 0 | K307: 0 | L307: 0 | M307: 0 | N307: 0 | O307: 0
A308: =VLOOKUP(B308,'[1]PORTFOLIO RAW'!B:B,1,FALSE) -> 670129 | B308: 670129 | C308: PROLOGIS - TOTAL DEBT | D308: 670129(WC03255) | E308: 3494844 | F308: 3990185 | G308: 3212596 | H308: 3331299 | I308: 11382408 | J308: 11790794 | K308: 9011216 | L308: 9380199 | M308: 11626831 | N308: 10608294 | O308: 9412631
A309: =VLOOKUP(B309,'[1]PORTFOLIO RAW'!B:B,1,FALSE) -> 14352P | B309: 14352P | C309: ACCENTURE PLC - TOTAL DEBT | D309: 14352P(WC03255) | E309: 26360 | F309: 8278 | G309: 955 | H309: 1588 | I309: 4419 | J309: 33 | K309: 25600 | L309: 26733 | M309: 27435 | N309: 27230 | O309: 25070
A310: =VLOOKUP(B310,'[1]PORTFOLIO RAW'!B:B,1,FALSE) -> 749688 | B310: 749688 | C310: HCA HEALTHCARE - TOTAL DEBT | D310: 749688(WC03255) | E310: 27308000 | F310: 26989000 | G310: 25670000 | H310: 26033000 | I310: 27052000 | J310: 28930000 | K310: 28376000 | L310: 29645000 | M310: 30488000 | N310: 31376000 | O310: 33058000
A311: =VLOOKUP(B311,'[1]PORTFOLIO RAW'!B:B,1,FALSE) -> 894145 | B311: 894145 | C311: RALPH LAUREN - TOTAL DEBT | D311: 894145(WC03255) | E311: 447500 | F311: 752400 | G311: 483000 | H311: 320300 | I311: 332300 | J311: 312700 | K311: 305000 | L311: 571000 | M311: 789000 | N311: 1000000 | O311: 861700
A312: =VLOOKUP(B312,'[1]PORTFOLIO RAW'!B:B,1,FALSE) -> 26599V | B312: 26599V | C312: SEAGATE TECHNOLOGY - TOTAL DEBT | D312: 26599V(WC03255) | E312: 2063000 | F312: 2030000 | G312: 2727000 | H312: 2502000 | I312: 3512000 | J312: 2863000 | K312: 2777000 | L312: 3920000 | M312: 4155000 | N312: 4130000 | O312: 5021000
A313: =VLOOKUP(B313,'[1]PORTFOLIO RAW'!B:B,1,FALSE) -> 904878 | B313: 904878 | C313: MOTOROLA SOLUTIONS - TOTAL DEBT | D313: 904878(WC03255) | E313: 4285000 | F313: 4033000 | G313: 3791000 | H313: 2729000 | I313: 1535000 | J313: 1863000 | K313: 2444000 | L313: 3400000 | M313: 4390000 | N313: 4396000 | O313: 4471000
A314: =VLOOKUP(B314,'[1]PORTFOLIO RAW'!B:B,1,FALSE) -> 922817 | B314: 922817 | C314: AON PLC - TOTAL DEBT | D314: 922817(WC03255) | E314: 2145000 | F314: 1977000 | G314: 2008000 | H314: 4506000 | I314: 4492000 | J314: 4165000 | K314: 4593000 | L314: 5766000 | M314: 5903000 | N314: 6374000 | O314: 6119000
A315: =VLOOKUP(B315,'[1]PORTFOLIO RAW'!B:B,1,FALSE) -> 905446 | B315: 905446 | C315: INGERSOLL-RAND - TOTAL DEBT | D315: 905446(WC03255) | E315: 995785 | F315: 3679104 | G315: 2859427 | H315: 2790775 | I315: 2812087 | J315: 2450614 | K315: 2563434 | L315: 3493579 | M315: 3904119 | N315: 3858550 | O315: 3389376
A316: =VLOOKUP(B316,'[1]PORTFOLIO RAW'!B:B,1,FALSE) -> 28513N | B316: 28513N | C316: CBRE GROUP - TOTAL DEBT | D316: 28513N(WC03255) | E316: 2698614 | F316: 2920100 | G316: 3010677 | H316: 2515567 | I316: 3583348 | J316: 3751436 | K316: 2488249 | L316: 2424102 | M316: 4430336 | N316: 3802806 | O316: 2910393
A317: =VLOOKUP(B317,'[1]PORTFOLIO RAW'!B:B,1,FALSE) -> 31412T | B317: 31412T | C317: EXPEDIA GROUP INC - TOTAL DEBT | D317: 31412T(WC03255) | E317: 1085000 | F317: 1544548 | G317: 895086 | H317: 1644894 | I317: 1249281 | J317: 1249345 | K317: 1331412 | L317: 1850787 | M317: 3201277 | N317: 3160336 | O317: 4249054
A318: =VLOOKUP(B318,'[1]PORTFOLIO RAW'!B:B,1,FALSE) -> 680902 | B318: 680902 | C318: AMERICAN TOWER CORP - TOTAL DEBT | D318: 680902(WC03255) | E318: 4285284 | F318: 4333146 | G318: 4211581 | H318: 5587388 | I318: 7236308 | J318: 8753376 | K318: 14478278 | L318: 14608708 | M318: 17119009 | N318: 18533465 | O318: 20205100
A319: =VLOOKUP(B319,'[1]PORTFOLIO RAW'!B:B,1,FALSE) -> 904383 | B319: 904383 | C319: DUKE ENERGY CORP - TOTAL DEBT | D319: 904383(WC03255) | E319: 11766000 | F319: 14439000 | G319: 17015000 | H319: 18426000 | I319: 21000000 | J319: 40518000 | K319: 41095000 | L319: 42534000 | M319: 43202000 | N319: 50382000 | O319: 54442000
A320: =VLOOKUP(B320,'[1]PORTFOLIO RAW'!B:B,1,FALSE) -> 13967E | B320: 13967E | C320: MONDELEZ - TOTAL DEBT | D320: 13967E(WC03255) | E320: 21009000 | F320: 20251000 | G320: 18990000 | H320: 28724000 | I320: 26931000 | J320: 19425000 | K320: 17121000 | L320: 16700000 | M320: 15398000 | N320: 17199000 | O320: 17652000
A321: =VLOOKUP(B321,'[1]PORTFOLIO RAW'!B:B,1,FALSE) -> 903749 | B321: 903749 | C321: EATON CORP PLC - TOTAL DEBT | D321: 903749(WC03255) | E321: 3417000 | F321: 4271000 | G321: 3467000 | H321: 3458000 | I321: 3773000 | J321: 10833000 | K321: 9549000 | L321: 9034000 | M321: 8449000 | N321: 8277000 | O321: 7751000
A322: =VLOOKUP(B322,'[1]PORTFOLIO RAW'!B:B,1,FALSE) -> 937343 | B322: 937343 | C322: L BRANDS INC - TOTAL DEBT | D322: 937343(WC03255) | E322: 2912000 | F322: 2897000 | G322: 2725000 | H322: 2507000 | I322: 3538000 | J322: 4477000 | K322: 4976000 | L322: 4765000 | M322: 5721000 | N322: 5736000 | O322: 5794000
A323: =VLOOKUP(B323,'[1]PORTFOLIO RAW'!B:B,1,FALSE) -> 905113 | B323: 905113 | C323: ARCONIC INC - TOTAL DEBT | D323: 905113(WC03255) | E323: 7998000 | F323: 10578000 | G323: 9859000 | H323: 9165000 | I323: 9371000 | J323: 8829000 | K323: 8319000 | L323: 8852000 | M323: 9103000 | N323: 8084000 | O323: 6844000
A324: =VLOOKUP(B324,'[1]PORTFOLIO RAW'!B:B,1,FALSE) -> 13967H | B324: 13967H | C324: WILLIS TOWERS WAT - TOTAL DEBT | D324: 13967H(WC03255) | E324: 1250000 | F324: 2650000 | G324: 2374000 | H324: 2290000 | I324: 2395000 | J324: 2381000 | K324: 2326000 | L324: 2309000 | M324: 3266000 | N324: 3865000 | O324: 4535000
A325: =VLOOKUP(B325,'[1]PORTFOLIO RAW'!B:B,1,FALSE) -> 921431 | B325: 921431 | C325: BAKER HUGHES A GE CO - TOTAL DEBT | D325: 921431(WC03255) | E325: 1084800 | F325: 2333000 | G325: 1800000 | H325: 3885000 | I325: 4069000 | J325: 4916000 | K325: 4381000 | L325: 4133000 | M325: 4041000 | N325: 3018000 | O325: 8349000
A326: =VLOOKUP(B326,'[1]PORTFOLIO RAW'!B:B,1,FALSE) -> 266220 | B326: 266220 | C326: TAPESTRY INC - TOTAL DEBT | D326: 266220(WC03255) | E326: 3100 | F326: 2865 | G326: 33076 | H326: 24901 | I326: 24155 | J326: 23360 | K326: 985 | L326: 140485 | M326: 890400 | N326: 876200 | O326: 1579500
A327: =VLOOKUP(B327,'[1]PORTFOLIO RAW'!B:B,1,FALSE) -> 30730Q | B327: 30730Q | C327: INTERCONTINENTAL - TOTAL DEBT | D327: 30730Q(WC03255) | E327: 221875 | F327: 379375 | G327: 307500 | H327: 578500 | I327: 887500 | J327: 1132500 | K327: 5058000 | L327: 4289000 | M327: 7308000 | N327: 6364000 | O327: 6100000
A328: =VLOOKUP(B328,'[1]PORTFOLIO RAW'!B:B,1,FALSE) -> 921925 | B328: 921925 | C328: JEFFERIES FINANCIAL - TOTAL DEBT | D328: 921925(WC03255) | E328: 2136550 | F328: 2081456 | G328: 1970371 | H328: 1691128 | I328: 1997958 | J328: 1474054 | K328: 13564820 | L328: 14567029 | M328: 14782210 | N328: 14695978 | O328: 15164305
...

Sheet REV
A1: Revenue
B2: Code | C2: Name | D2: Code | E2: 2007 | F2: 2008 | G2: 2009 | H2: 2010 | I2: 2011 | J2: 2012 | K2: 2013 | L2: 2014 | M2: 2015 | N2: 2016 | O2: 2017
A3: =VLOOKUP(B3,'[1]PORTFOLIO RAW'!B:B,1,FALSE) -> 891399 | B3: 891399 | C3: AMAZON.COM INC - NET SALES OR REVENUES | D3: 891399(WC01001) | E3: 14835000 | F3: 19166000 | G3: 24509000 | H3: 34204000 | I3: 48077000 | J3: 61093000 | K3: 74452000 | L3: 88988000 | M3: 107006000 | N3: 135987000 | O3: 177866000
A4: =VLOOKUP(B4,'[1]PORTFOLIO RAW'!B:B,1,FALSE) -> 916328 | B4: 916328 | C4: ABBOTT LABORATORIES - NET SALES OR REVENUES | D4: 916328(WC01001) | E4: 25914238 | F4: 29527552 | G4: 30764707 | H4: 35166721 | I4: 38851259 | J4: 39873910 | K4: 21848000 | L4: 20247000 | M4: 20405000 | N4: 20853000 | O4: 27390000
A5: =VLOOKUP(B5,'[1]PORTFOLIO RAW'!B:B,1,FALSE) -> 545101 | B5: 545101 | C5: AES CORP - NET SALES OR REVENUES | D5: 545101(WC01001) | E5: 13588000 | F5: 16070000 | G5: 13933000 | H5: 16568000 | I5: 17344000 | J5: 18141000 | K5: 15880000 | L5: 17141000 | M5: 14971000 | N5: 13586000 | O5: 10530000
A6: =VLOOKUP(B6,'[1]PORTFOLIO RAW'!B:B,1,FALSE) -> 906187 | B6: 906187 | C6: INT'L BUSINESS MACHS - NET SALES OR REVENUES | D6: 906187(WC01001) | E6: 98786000 | F6: 103630000 | G6: 95758000 | H6: 99870000 | I6: 106916000 | J6: 104507000 | K6: 99751000 | L6: 92793000 | M6: 81741000 | N6: 79919000 | O6: 79139000
A7: =VLOOKUP(B7,'[1]PORTFOLIO RAW'!B:B,1,FALSE) -> 936365 | B7: 936365 | C7: ADVANCED MICRO - NET SALES OR REVENUES | D7: 936365(WC01001) | E7: 6013000 | F7: 5808000 | G7: 5403000 | H7: 6494000 | I7: 6568000 | J7: 5422000 | K7: 5299000 | L7: 5506000 | M7: 3991000 | N7: 4272000 | O7: 5329000
A8: =VLOOKUP(B8,'[1]PORTFOLIO RAW'!B:B,1,FALSE) -> 749382 | B8: 749382 | C8: ADOBE INC - NET SALES OR REVENUES | D8: 749382(WC01001) | E8: 3157881 | F8: 3579889 | G8: 2945853 | H8: 3779831 | I8: 4212509 | J8: 4403677 | K8: 4055240 | L8: 4147065 | M8: 4795511 | N8: 5854430 | O8: 7301505
A9: =VLOOKUP(B9,'[1]PORTFOLIO RAW'!B:B,1,FALSE) -> 905271 | B9: 905271 | C9: AIR PRODUCTS & CHEMS - NET SALES OR REVENUES | D9: 905271(WC01001) | E9: 10037800 | F9: 10414500 | G9: 8256200 | H9: 9026000 | I9: 10082000 | J9: 9611700 | K9: 10180400 | L9: 10439000 | M9: 9894900 | N9: 9524400 | O9: 8187600
A10: =VLOOKUP(B10,'[1]PORTFOLIO RAW'!B:B,1,FALSE) -> 894371 | B10: 894371 | C10: BOSTON PROPERTIES - NET SALES OR REVENUES | D10: 894371(WC01001) | E10: 1482289 | F10: 1488400 | G10: 1522249 | H10: 1558136 | I10: 1759526 | J10: 1876267 | K10: 2135539 | L10: 2565037 | M10: 2866716 | N10: 2631426 | O10: 2609739
A11: =VLOOKUP(B11,'[1]PORTFOLIO RAW'!B:B,1,FALSE) -> 322677 | B11: 322677 | C11: ALLSTATE CORP - NET SALES OR REVENUES | D11: 322677(WC01001) | E11: 36639000 | F11: 31315000 | G11: 33915000 | H11: 32361000 | I11: 33162000 | J11: 33200000 | K11: 34714000 | L11: 35481000 | M11: 36105000 | N11: 36847000 | O11: 38670000
A12: =VLOOKUP(B12,'[1]PORTFOLIO RAW'!B:B,1,FALSE) -> 906191 | B12: 906191 | C12: HONEYWELL INTERNATNL - NET SALES OR REVENUES | D12: 906191(WC01001) | E12: 34589000 | F12: 36556000 | G12: 30854000 | H12: 33389000 | I12: 36500000 | J12: 37665000 | K12: 39062000 | L12: 40306000 | M12: 38581000 | N12: 39302000 | O12: 40534000
A13: =VLOOKUP(B13,'[1]PORTFOLIO RAW'!B:B,1,FALSE) -> 938692 | B13: 938692 | C13: AMGEN INC - NET SALES OR REVENUES | D13: 938692(WC01001) | E13: 14771000 | F13: 15003000 | G13: 14642000 | H13: 15006000 | I13: 15582000 | J13: 17265000 | K13: 18676000 | L13: 20063000 | M13: 21662000 | N13: 22991000 | O13: 22849000
A14: =VLOOKUP(B14,'[1]PORTFOLIO RAW'!B:B,1,FALSE) -> 905802 | B14: 905802 | C14: HESS CORPORATION - NET SALES OR REVENUES | D14: 905802(WC01001) | E14: 31647000 | F14: 41165000 | G14: 29378000 | H14: 33862000 | I14: 38466000 | J14: 37691000 | K14: 22284000 | L14: 10737000 | M14: 6636000 | N14: 4762000 | O14: 5466000
... A109: =VLOOKUP(B109,'[1]PORTFOLIO RAW'!B:B,1,FALSE) -> 905016 | B109: 905016 | C109: NEXTERA ENERGY - NET SALES OR REVENUES | D109: 905016(WC01001) | E109: 15263000 | F109: 16410000 | G109: 15479000 | H109: 14667000 | I109: 14827000 | J109: 14085000 | K109: 15136000 | L109: 16601000 | M109: 16554000 | N109: 15696000 | O109: 16741000
A110: =VLOOKUP(B110,'[1]PORTFOLIO RAW'!B:B,1,FALSE) -> 28341F | B110: 28341F | C110: ASSURANT INC - NET SALES OR REVENUES | D110: 28341F(WC01001) | E110: 8441701 | F110: 8913986 | G110: 8721708 | H110: 8519870 | I110: 8259314 | J110: 8455532 | K110: 9052044 | L110: 10381683 | M110: 10330518 | N110: 7538654 | O110: 6415900
A111: =VLOOKUP(B111,'[1]PORTFOLIO RAW'!B:B,1,FALSE) -> 755980 | B111: 755980 | C111: FASTENAL COMPANY - NET SALES OR REVENUES | D111: 755980(WC01001) | E111: 2061819 | F111: 2340425 | G111: 1930330 | H111: 2269471 | I111: 2766859 | J111: 3133577 | K111: 3326106 | L111: 3733507 | M111: 3869187 | N111: 3962036 | O111: 4390500
A112: =VLOOKUP(B112,'[1]PORTFOLIO RAW'!B:B,1,FALSE) -> 905994 | B112: 905994 | C112: FEDERAL REALTY INVST - NET SALES OR REVENUES | D112: 905994(WC01001) | E112: 485892 | F112: 520525 | G112: 531019 | H112: 544674 | I112: 553059 | J112: 608018 | K112: 637413 | L112: 686090 | M112: 744012 | N112: 801591 | O112: 857348
A113: =VLOOKUP(B113,'[1]PORTFOLIO RAW'!B:B,1,FALSE) -> 997198 | B113: 997198 | C113: FIFTH THIRD BANCORP - NET SALES OR REVENUES | D113: 997198(WC01001) | E113: 8494000 | F113: 8205000 | G113: 7298000 | H113: 6645000 | I113: 6204000 | J113: 6130000 | K113: 6813000 | L113: 6321000 | M113: 6637000 | N113: 6823000 | O113: 7666000
A114: =VLOOKUP(B114,'[1]PORTFOLIO RAW'!B:B,1,FALSE) -> 951503 | B114: 951503 | C114: M&T BANK CORPORATION - NET SALES OR REVENUES | D114: 951503(WC01001) | E114: 4596167 | F114: 4403023 | G114: 3942920 | H114: 3920118 | I114: 4350105 | J114: 4674653 | K114: 4838665 | L114: 4752822 | M114: 5010148 | N114: 5721867 | O114: 6018938
A115: =VLOOKUP(B115,'[1]PORTFOLIO RAW'!B:B,1,FALSE) -> 741123 | B115: 741123 | C115: FISERV INC - NET SALES OR REVENUES | D115: 741123(WC01001) | E115: 3922000 | F115: 4739000 | G115: 4077000 | H115: 4133000 | I115: 4337000 | J115: 4482000 | K115: 4814000 | L115: 5066000 | M115: 5254000 | N115: 5505000 | O115: 5696000
A116: =VLOOKUP(B116,'[1]PORTFOLIO RAW'!B:B,1,FALSE) -> 546814 | B116: 546814 | C116: MACY'S INC - NET SALES OR REVENUES | D116: 546814(WC01001) | E116: 26313000 | F116: 24892000 | G116: 23489000 | H116: 25003000 | I116: 26405000 | J116: 27686000 | K116: 27931000 | L116: 28105000 | M116: 27079000 | N116: 25778000 | O116: 24837000
A117: =VLOOKUP(B117,'[1]PORTFOLIO RAW'!B:B,1,FALSE) -> 938076 | B117: 938076 | C117: FRANKLIN RESOURCES - NET SALES OR REVENUES | D117: 938076(WC01001) | E117: 6205769 | F117: 6032386 | G117: 4159565 | H117: 5914140 | I117: 7209754 | J117: 7174500 | K117: 8086100 | L117: 8592500 | M117: 7968500 | N117: 6683500 | O117: 6526600
A118: =VLOOKUP(B118,'[1]PORTFOLIO RAW'!B:B,1,FALSE) -> 152594 | B118: 152594 | C118: FREEPORT-MCMORAN INC - NET SALES OR REVENUES | D118: 152594(WC01001) | E118: 16939000 | F118: 17796000 | G118: 15040000 | H118: 18395000 | I118: 21427000 | J118: 18010000 | K118: 21391000 | L118: 21222000 | M118: 16229000 | N118: 14599000 | O118: 15888000
A119: =VLOOKUP(B119,'[1]PORTFOLIO RAW'!B:B,1,FALSE) -> 951018 | B119: 951018 | C119: GAP INC - NET SALES OR REVENUES | D119: 951018(WC01001) | E119: 15763000 | F119: 14526000 | G119: 14197000 | H119: 14664000 | I119: 14549000 | J119: 15651000 | K119: 16148000 | L119: 16435000 | M119: 15797000 | N119: 15516000 | O119: 15855000
A120: =VLOOKUP(B120,'[1]PORTFOLIO RAW'!B:B,1,FALSE) -> 907652 | B120: 907652 | C120: GENERAL DYNAMICS - NET SALES OR REVENUES | D120: 907652(WC01001) | E120: 27240000 | F120: 29300000 | G120: 31981000 | H120: 32466000 | I120: 32677000 | J120: 31513000 | K120: 31218000 | L120: 30852000 | M120: 31469000 | N120: 31353000 | O120: 30973000
A121: =VLOOKUP(B121,'[1]PORTFOLIO RAW'!B:B,1,FALSE) -> 905801 | B121: 905801 | C121: GENERAL MILLS, INC. - NET SALES OR REVENUES | D121: 905801(WC01001) | E121: 12442000 | F121: 13652100 | G121: 14691300 | H121: 14796500 | I121: 14880200 | J121: 16657900 | K121: 17774100 | L121: 17909600 | M121: 17630300 | N121: 16563100 | O121: 15619800
A122: =VLOOKUP(B122,'[1]PORTFOLIO RAW'!B:B,1,FALSE) -> 906511 | B122: 906511 | C122: GENUINE PARTS CO - NET SALES OR REVENUES | D122: 906511(WC01001) | E122: 10843195 | F122: 11015263 | G122: 10057512 | H122: 11207589 | I122: 12458877 | J122: 13013868 | K122: 14077843 | L122: 15341647 | M122: 15280044 | N122: 15339713 | O122: 16308801
... A236: =VLOOKUP(B236,'[1]PORTFOLIO RAW'!B:B,1,FALSE) -> 933974 | B236: 933974 | C236: TRAVELERS COS - NET SALES OR REVENUES | D236: 933974(WC01001) | E236: 26087000 | F236: 24897000 | G236: 24938000 | H236: 25138000 | I236: 25471000 | J236: 25755000 | K236: 26206000 | L236: 27162000 | M236: 26852000 | N236: 27654000 | O236: 28916000
A237: =VLOOKUP(B237,'[1]PORTFOLIO RAW'!B:B,1,FALSE) -> 14015T | B237: 14015T | C237: FIDELITY NATNL INF - NET SALES OR REVENUES | D237: 14015T(WC01001) | E237: 4758016 | F237: 3446000 | G237: 3769500 | H237: 5269500 | I237: 5745700 | J237: 5807600 | K237: 6070700 | L237: 6413800 | M237: 6595200 | N237: 9241000 | O237: 9123000
A238: =VLOOKUP(B238,'[1]PORTFOLIO RAW'!B:B,1,FALSE) -> 905019 | B238: 905019 | C238: MERCK & CO INC - NET SALES OR REVENUES | D238: 905019(WC01001) | E238: 24197700 | F238: 23850300 | G238: 27428300 | H238: 45913000 | I238: 48132000 | J238: 47347000 | K238: 44033000 | L238: 42237000 | M238: 39498000 | N238: 39807000 | O238: 40122000
A239: =VLOOKUP(B239,'[1]PORTFOLIO RAW'!B:B,1,FALSE) -> 912090 | B239: 912090 | C239: SCHLUMBERGER LIMITED - NET SALES OR REVENUES | D239: 912090(WC01001) | E239: 23277000 | F239: 27163000 | G239: 22702000 | H239: 27447000 | I239: 39540000 | J239: 42149000 | K239: 46294000 | L239: 48580000 | M239: 35475000 | N239: 27810000 | O239: 30440000
A240: =VLOOKUP(B240,'[1]PORTFOLIO RAW'!B:B,1,FALSE) -> 755741 | B240: 755741 | C240: CHARLES SCHWAB CORP - NET SALES OR REVENUES | D240: 755741(WC01001) | E240: 5617000 | F240: 5393000 | G240: 4474000 | H240: 4510000 | I240: 4915000 | J240: 5081000 | K240: 5549000 | L240: 6157000 | M240: 6501000 | N240: 7644000 | O240: 8960000
A241: =VLOOKUP(B241,'[1]PORTFOLIO RAW'!B:B,1,FALSE) -> 14361V | B241: 14361V | C241: ZIMMER BIOMET - NET SALES OR REVENUES | D241: 14361V(WC01001) | E241: 3897500 | F241: 4121100 | G241: 4095400 | H241: 4220200 | I241: 4451800 | J241: 4471700 | K241: 4623400 | L241: 4673300 | M241: 5997800 | N241: 7683900 | O241: 7824100
A242: =VLOOKUP(B242,'[1]PORTFOLIO RAW'!B:B,1,FALSE) -> 154680 | B242: 154680 | C242: AMERISOURCEBERGEN - NET SALES OR REVENUES | D242: 154680(WC01001) | E242: 66074312 | F242: 70189733 | G242: 71759990 | H242: 77953979 | I242: 80217558 | J242: 79489596 | K242: 87959167 | L242: 119569127 | M242: 135961803 | N242: 146849686 | O242: 153143826
A243: =VLOOKUP(B243,'[1]PORTFOLIO RAW'!B:B,1,FALSE) -> 14698C | B243: 14698C | C243: PRINCIPAL FINL GROUP - NET SALES OR REVENUES | D243: 14698C(WC01001) | E243: 10800400 | F243: 9921700 | G243: 9223300 | H243: 9298900 | I243: 8790400 | J243: 9213600 | K243: 9405500 | L243: 10555600 | M243: 11994600 | N243: 12492500 | O243: 14175000
A244: =VLOOKUP(B244,'[1]PORTFOLIO RAW'!B:B,1,FALSE) -> 905361 | B244: 905361 | C244: SHERWIN-WILLIAMS CO - NET SALES OR REVENUES | D244: 905361(WC01001) | E244: 8005292 | F244: 7979727 | G244: 7094249 | H244: 7776424 | I244: 8765699 | J244: 9534462 | K244: 10185532 | L244: 11129533 | M244: 11339304 | N244: 11855602 | O244: 14983788
A245: =VLOOKUP(B245,'[1]PORTFOLIO RAW'!B:B,1,FALSE) -> 357834 | B245: 357834 | C245: SIMON PROPERTY GROUP - NET SALES OR REVENUES | D245: 357834(WC01001) | E245: 3650799 | F245: 3783155 | G245: 3775216 | H245: 3957630 | I245: 4306432 | J245: 4880084 | K245: 5170138 | L245: 4870818 | M245: 5266103 | N245: 5435229 | O245: 5538640
A246: =VLOOKUP(B246,'[1]PORTFOLIO RAW'!B:B,1,FALSE) -> 906400 | B246: 906400 | C246: SNAP-ON INC - NET SALES OR REVENUES | D246: 906400(WC01001) | E246: 2904200 | F246: 2934700 | G246: 2417500 | H246: 2681400 | I246: 2978500 | J246: 3099200 | K246: 3237500 | L246: 3492600 | M246: 3593100 | N246: 3711800 | O246: 4000300
A247: =VLOOKUP(B247,'[1]PORTFOLIO RAW'!B:B,1,FALSE) -> 14861V | B247: 14861V | C247: PRUDENTIAL FINANCIAL - NET SALES OR REVENUES | D247: 14861V(WC01001) | E247: 36034000 | F247: 33295000 | G247: 35643000 | H247: 40370000 | I247: 50895000 | J247: 86541000 | K247: 41660000 | L247: 54161000 | M247: 57260000 | N247: 59001000 | O247: 59956000
A248: =VLOOKUP(B248,'[1]PORTFOLIO RAW'!B:B,1,FALSE) -> 14806F | B248: 14806F | C248: ADVANCE AUTO PARTS - NET SALES OR REVENUES | D248: 14806F(WC01001) | E248: 4844404 | F248: 5142255 | G248: 5412623 | H248: 5925203 | I248: 6170462 | J248: 6205003 | K248: 6493814 | L248: 9843861 | M248: 9737018 | N248: 9567679 | O248: 9373784
A249: =VLOOKUP(B249,'[1]PORTFOLIO RAW'!B:B,1,FALSE) -> 902324 | B249: 902324 | C249: EDISON INTERNATIONAL - NET SALES OR REVENUES | D249: 902324(WC01001) | E249: 13113000 | F249: 14112000 | G249: 12256000 | H249: 12531000 | I249: 12715000 | J249: 11862000 | K249: 12581000 | L249: 13413000 | M249: 11524000 | N249: 11869000 | O249: 12320000
A250: =VLOOKUP(B250,'[1]PORTFOLIO RAW'!B:B,1,FALSE) -> 902325 | B250: 902325 | C250: SOUTHERN CO - NET SALES OR REVENUES | D250: 902325(WC01001) | E250: 15353000 | F250: 17127000 | G250: 15738000 | H250: 17458000 | I250: 17655000 | J250: 16537000 | K250: 17087000 | L250: 18467000 | M250: 17489000 | N250: 19896000 | O250: 23031000
A251: =VLOOKUP(B251,'[1]PORTFOLIO RAW'!B:B,1,FALSE) -> 992305 | B251: 992305 | C251: BB&T CORPORATION - NET SALES OR REVENUES | D251: 992305(WC01001) | E251: 10668000 | F251: 10404000 | G251: 10824000 | H251: 11707000 | I251: 9770000 | J251: 10515000 | K251: 10737000 | L251: 10275000 | M251: 10603000 | N251: 11680000 | O251: 12156000
A252: =VLOOKUP(B252,'[1]PORTFOLIO RAW'!B:B,1,FALSE) -> 905647 | B252: 905647 | C252: SOUTHWEST AIRLINES - NET SALES OR REVENUES | D252: 905647(WC01001) | E252: 9861000 | F252: 11023000 | G252: 10350000 | H252: 12104000 | I252: 15658000 | J252: 17088000 | K252: 17699000 | L252: 18605000 | M252: 19820000 | N252: 20425000 | O252: 21171000
