Workbook

Sheet PORTFOLIO RAW
A2: NAME | B2: Code | C2: Industry
A3: MMM | B3: 902172 | C3: Industrials
A4: ABT | B4: 916328 | C4: Healthcare
A5: ACN | B5: 14352P | C5: Technology
A6: ATVI.O | B6: 312367 | C6: Technology
A7: ADBE.O | B7: 749382 | C7: Technology
A8: AAP | B8: 14806F | C8: Consumer Cyclicals
A9: AMD.O | B9: 936365 | C9: Technology
A10: AES | B10: 545101 | C10: Utilities
A11: AFL | B11: 933185 | C11: Financials
A12: A | B12: 277642 | C12: Healthcare
A13: APD | B13: 905271 | C13: Basic Materials
A14: AKAM.O | B14: 277355 | C14: Technology
A15: ALB | B15: 130298 | C15: Basic Materials
A16: AGN | B16: 325596 | C16: Healthcare
A17: LNT.O | B17: 906979 | C17: Utilities
A18: ALL | B18: 322677 | C18: Financials
A19: GOOG.O | B19: 29026M | C19: Technology
A20: MO | B20: 904853 | C20: Consumer Non-Cyclicals
A21: AMZN.O | B21: 891399 | C21: Consumer Cyclicals
A22: AEE | B22: 670942 | C22: Utilities
A23: AEP | B23: 905425 | C23: Utilities
A24: AXP | B24: 906156 | C24: Financials
A25: AIG | B25: 916305 | C25: Financials
A26: AMT | B26: 680902 | C26: Financials
A27: AMP | B27: 31604H | C27: Financials
A28: ABC | B28: 154680 | C28: Consumer Non-Cyclicals
A29: AMGN.O | B29: 938692 | C29: Healthcare
A30: APH | B30: 546075 | C30: Technology
A31: ADI.O | B31: 905276 | C31: Technology
A32: ANTM.K | B32: 14737P | C32: Healthcare
A33: AON | B33: 922817 | C33: Financials
A34: APA | B34: 921983 | C34: Energy
A35: AIV | B35: 132808 | C35: Financials
A36: AAPL.O | B36: 992816 | C36: Technology
A37: AMAT.O | B37: 905296 | C37: Technology
A38: ADM | B38: 921093 | C38: Consumer Non-Cyclicals
A39: ARNC.K | B39: 905113 | C39: Basic Materials
A40: AIZ | B40: 28341F | C40: Financials
A41: T | B41: 945388 | C41: Telecommunications Services
A42: ADSK.O | B42: 702259 | C42: Technology
A43: ADP.O | B43: 912669 | C43: Technology
A44: AZO | B44: 544616 | C44: Consumer Cyclicals
A45: AVB | B45: 130502 | C45: Financials
A46: AVY | B46: 921161 | C46: Basic Materials
A47: BHGE.K | B47: 921431 | C47: Energy
A48: BLL | B48: 932060 | C48: Basic Materials
A49: BAC | B49: 923937 | C49: Financials
A50: BK | B50: 905840 | C50: Financials
A51: BAX | B51: 916365 | C51: Healthcare
A52: BBT | B52: 992305 | C52: Financials
... A69: CAT | B69: 902224 | C69: Industrials
A70: CBRE.K | B70: 28513N | C70: Financials
A71: CBS | B71: 32480Q | C71: Consumer Cyclicals
A72: CE | B72: 29756N | C72: Basic Materials
A73: CELG.O | B73: 755790 | C73: Healthcare
A74: CNP | B74: 904842 | C74: Utilities
A75: SCHW.K | B75: 755741 | C75: Financials
A76: CVX | B76: 905024 | C76: Energy
A77: CB | B77: 328314 | C77: Financials
A78: CI | B78: 912278 | C78: Healthcare
A79: XEC | B79: 26276P | C79: Energy
A80: CINF.O | B80: 951545 | C80: Financials
A81: CTAS.O | B81: 944777 | C81: Industrials
A82: CSCO.O | B82: 542868 | C82: Technology
A83: C | B83: 741344 | C83: Financials
A84: CTXS.O | B84: 867705 | C84: Technology
A85: CLX | B85: 916125 | C85: Consumer Non-Cyclicals
A86: CME.O | B86: 26393N | C86: Financials
A87: CMS | B87: 901686 | C87: Utilities
A88: KO | B88: 904282 | C88: Consumer Non-Cyclicals
A89: CL | B89: 906148 | C89: Consumer Non-Cyclicals
A90: CMCSA.O | B90: 981550 | C90: Consumer Cyclicals
A91: CMA | B91: 922964 | C91: Financials
A92: CAG | B92: 929814 | C92: Consumer Non-Cyclicals
A93: COP | B93: 901666 | C93: Energy
A94: ED | B94: 902288 | C94: Utilities
A95: STZ | B95: 937083 | C95: Consumer Non-Cyclicals
A96: COO | B96: 938928 | C96: Healthcare
A97: GLW | B97: 912273 | C97: Technology
A98: COST.O | B98: 312385 | C98: Consumer Cyclicals
... A109: DVN | B109: 271980 | C109: Energy
A110: DISCK.O | B110: 31196R | C110: Consumer Cyclicals
A111: DISH.O | B111: 135448 | C111: Consumer Cyclicals
A112: DLTR.O | B112: 154259 | C112: Consumer Cyclicals
A113: D | B113: 944314 | C113: Utilities
A114: DOV | B114: 904830 | C114: Industrials
A115: DTE | B115: 905214 | C115: Utilities
A116: DUK | B116: 904383 | C116: Utilities
A117: DRE | B117: 513260 | C117: Financials
A118: DXC | B118: 916091 | C118: Technology
A119: ETFC.O | B119: 883488 | C119: Financials
A120: EMN | B120: 357922 | C120: Basic Materials
A121: ETN | B121: 903749 | C121: Industrials
A122: EBAY.O | B122: 687609 | C122: Technology
... A134: EXC | B134: 902317 | C134: Utilities
A135: EXPE.O | B135: 31412T | C135: Consumer Cyclicals
A136: EXPD.O | B136: 910722 | C136: Industrials
A137: XOM | B137: 905039 | C137: Energy
A138: FAST.O | B138: 755980 | C138: Industrials
...

Sheet MB
A1: Market to Book Ratio
A2: Code | B2: Code | C2: Name | D2: Code | E2: 2007 | F2: 2008 | G2: 2009 | H2: 2010 | I2: 2011 | J2: 2012 | K2: 2013 | L2: 2014 | M2: 2015 | N2: 2016 | O2: 2017
A3: =VLOOKUP(B3,'PORTFOLIO RAW'!B:B,1,FALSE) -> 891399 | B3: 891399 | C3: AMAZON.COM - MRKT VALUE TO BOOK | D3: 891399(MTBV) | E3: 30.96 | F3: 12.91 | G3: 7.42 | H3: 9.87 | I3: 13.65 | J3: 14.39 | K3: 14.83 | L3: 14.25 | M3: 18.88 | N3: 19.18 | O3: 16.87
A4: =VLOOKUP(B4,'PORTFOLIO RAW'!B:B,1,FALSE) -> 916328 | B4: 916328 | C4: ABBOTT LABORATORIES - MRKT VALUE TO BOOK | D4: 916328(MTBV) | E4: 4.67 | F4: 5.18 | G4: 3.11 | H4: 3.6 | I4: 3.36 | J4: 4.1 | K4: 2.18 | L4: 3.04 | M4: 3.04 | N4: 2.98 | O4: 2.92
A5: =VLOOKUP(B5,'PORTFOLIO RAW'!B:B,1,FALSE) -> 545101 | B5: 545101 | C5: AES - MRKT VALUE TO BOOK | D5: 545101(MTBV) | E5: 4.08 | F5: 2.42 | G5: 2.05 | H5: 1.4 | I5: 1.41 | J5: 1.83 | K5: 2.29 | L5: 2.49 | M5: 2.37 | N5: 3.01 | O5: 3.02
A6: =VLOOKUP(B6,'PORTFOLIO RAW'!B:B,1,FALSE) -> 906187 | B6: 906187 | C6: INTERNATIONAL BUS.MCHS. - MRKT VALUE TO BOOK | D6: 906187(MTBV) | E6: 5.58 | F6: 11.96 | G6: 7.07 | H6: 7.21 | I6: 10.36 | J6: 12.49 | K6: 9.13 | L6: 16.31 | M6: 9.93 | N6: 8.09 | O6: 7.73
A7: =VLOOKUP(B7,'PORTFOLIO RAW'!B:B,1,FALSE) -> 936365 | B7: 936365 | C7: ADVANCED MICRO DEVICES - MRKT VALUE TO BOOK | D7: 936365(MTBV) | E7: 2.47 | F7: -40.13 | G7: 5.87 | H7: 4.06 | I7: 2.93 | J7: 4.72 | K7: 5.07 | L7: 15.65 | M7: -3.54 | N7: 13.27 | O7: 21.29
A8: =VLOOKUP(B8,'PORTFOLIO RAW'!B:B,1,FALSE) -> 749382 | B8: 749382 | C8: ADOBE (NAS) - MRKT VALUE TO BOOK | D8: 749382(MTBV) | E8: 5.42 | F8: 4.92 | G8: 3.54 | H8: 3.35 | I8: 2.1 | J8: 2.55 | K8: 3.91 | L8: 4.93 | M8: 5.79 | N8: 6.75 | O8: 8.75
A9: =VLOOKUP(B9,'PORTFOLIO RAW'!B:B,1,FALSE) -> 905271 | B9: 905271 | C9: AIR PRDS.& CHEMS. - MRKT VALUE TO BOOK | D9: 905271(MTBV) | E9: 3.65 | F9: 3.51 | G9: 3.52 | H9: 3.18 | I9: 3.02 | J9: 2.78 | K9: 3.23 | L9: 3.89 | M9: 3.99 | N9: 4.5 | O9: 3.26
A10: =VLOOKUP(B10,'PORTFOLIO RAW'!B:B,1,FALSE) -> 894371 | B10: 894371 | C10: BOSTON PROPERTIES - MRKT VALUE TO BOOK | D10: 894371(MTBV) | E10: 3.36 | F10: 3.23 | G10: 2.2 | H10: 2.83 | I10: 3.01 | J10: 3.33 | K10: 3.01 | L10: 3.15 | M10: 3.19 | N10: 3.72 | O10: 3.32
A11: =VLOOKUP(B11,'PORTFOLIO RAW'!B:B,1,FALSE) -> 322677 | B11: 322677 | C11: ALLSTATE ORD SHS - MRKT VALUE TO BOOK | D11: 322677(MTBV) | E11: 1.56 | F11: 1.57 | G11: 0.94 | H11: 0.94 | I11: 0.73 | J11: 1.09 | K11: 1.26 | L11: 1.45 | M11: 1.31 | N11: 1.42 | O11: 1.73
A12: =VLOOKUP(B12,'PORTFOLIO RAW'!B:B,1,FALSE) -> 906191 | B12: 906191 | C12: HONEYWELL INTL. - MRKT VALUE TO BOOK | D12: 906191(MTBV) | E12: 4.72 | F12: 4.69 | G12: 3.42 | H12: 3.21 | I12: 3.39 | J12: 3.64 | K12: 3.84 | L12: 4.28 | M12: 4.19 | N12: 4.51 | O12: 6.11
A13: =VLOOKUP(B13,'PORTFOLIO RAW'!B:B,1,FALSE) -> 938692 | B13: 938692 | C13: AMGEN - MRKT VALUE TO BOOK | D13: 938692(MTBV) | E13: 3.36 | F13: 3.11 | G13: 2.72 | H13: 2.24 | I13: 2.79 | J13: 3.33 | K13: 3.98 | L13: 4.24 | M13: 4.07 | N13: 4.34 | O13: 5.44
A14: =VLOOKUP(B14,'PORTFOLIO RAW'!B:B,1,FALSE) -> 905802 | B14: 905802 | C14: HESS - MRKT VALUE TO BOOK | D14: 905802(MTBV) | E14: 2.16 | F14: 2.51 | G14: 1.36 | H14: 1.12 | I14: 1.1 | J14: 0.9 | K14: 1.09 | L14: 1.35 | M14: 0.78 | N14: 1 | O14: 1.25
... A109: =VLOOKUP(B109,'PORTFOLIO RAW'!B:B,1,FALSE) -> 905016 | B109: 905016 | C109: NEXTERA ENERGY - MRKT VALUE TO BOOK | D109: 905016(MTBV) | E109: 2.37 | F109: 1.96 | G109: 1.75 | H109: 1.57 | I109: 1.57 | J109: 1.77 | K109: 1.9 | L109: 2.08 | M109: 1.98 | N109: 2.37 | O109: 2.44
A110: =VLOOKUP(B110,'PORTFOLIO RAW'!B:B,1,FALSE) -> 28341F | B110: 28341F | C110: ASSURANT - MRKT VALUE TO BOOK | D110: 28341F(MTBV) | E110: 1.51 | F110: 1.54 | G110: 0.81 | H110: 0.99 | I110: 0.77 | J110: 0.59 | K110: 0.94 | L110: 1.09 | M110: 1.26 | N110: 1.49 | O110: 1.37
A111: =VLOOKUP(B111,'PORTFOLIO RAW'!B:B,1,FALSE) -> 755980 | B111: 755980 | C111: FASTENAL - MRKT VALUE TO BOOK | D111: 755980(MTBV) | E111: 6.65 | F111: 6.97 | G111: 4.86 | H111: 6 | I111: 7.41 | J111: 8.33 | K111: 8.4 | L111: 7.16 | M111: 5.99 | N111: 5.97 | O111: 6.12
A112: =VLOOKUP(B112,'PORTFOLIO RAW'!B:B,1,FALSE) -> 905994 | B112: 905994 | C112: FEDERAL REALTY INV.TST. - MRKT VALUE TO BOOK | D112: 905994(MTBV) | E112: 4.41 | F112: 4.71 | G112: 3.32 | H112: 4.49 | I112: 4.42 | J112: 5.28 | K112: 4.69 | L112: 5.07 | M112: 5.63 | N112: 5.6 | O112: 4.27
A113: =VLOOKUP(B113,'PORTFOLIO RAW'!B:B,1,FALSE) -> 997198 | B113: 997198 | C113: FIFTH THIRD BANCORP - MRKT VALUE TO BOOK | D113: 997198(MTBV) | E113: 2.07 | F113: 1.39 | G113: 0.84 | H113: 0.96 | I113: 0.75 | J113: 1.08 | K113: 1.23 | L113: 1.22 | M113: 1.05 | N113: 1.06 | O113: 1.34
A114: =VLOOKUP(B114,'PORTFOLIO RAW'!B:B,1,FALSE) -> 951503 | B114: 951503 | C114: M&T BANK - MRKT VALUE TO BOOK | D114: 951503(MTBV) | E114: 1.79 | F114: 1.67 | G114: 1.12 | H114: 1.43 | I114: 1.07 | J114: 1.28 | K114: 1.39 | L114: 1.52 | M114: 1.06 | N114: 1.19 | O114: 1.56
A115: =VLOOKUP(B115,'PORTFOLIO RAW'!B:B,1,FALSE) -> 741123 | B115: 741123 | C115: FISERV - MRKT VALUE TO BOOK | D115: 741123(MTBV) | E115: 3.3 | F115: 3.26 | G115: 2.52 | H115: 2.52 | I115: 2.33 | J115: 2.92 | K115: 3.7 | L115: 4.97 | M115: 7.63 | N115: 8.59 | O115: 9.64
A116: =VLOOKUP(B116,'PORTFOLIO RAW'!B:B,1,FALSE) -> 546814 | B116: 546814 | C116: MACY'S - MRKT VALUE TO BOOK | D116: 546814(MTBV) | E116: 1.49 | F116: 1.81 | G116: 1.61 | H116: 1.69 | I116: 1.97 | J116: 2.57 | K116: 2.69 | L116: 3.95 | M116: 4.21 | N116: 2.49 | O116: 1.15
A117: =VLOOKUP(B117,'PORTFOLIO RAW'!B:B,1,FALSE) -> 938076 | B117: 938076 | C117: FRANKLIN RESOURCES - MRKT VALUE TO BOOK | D117: 938076(MTBV) | E117: 4.34 | F117: 3.58 | G117: 3.12 | H117: 3.15 | I117: 2.98 | J117: 2.9 | K117: 3.27 | L117: 3.01 | M117: 2 | N117: 1.69 | O117: 1.9
A118: =VLOOKUP(B118,'PORTFOLIO RAW'!B:B,1,FALSE) -> 152594 | B118: 152594 | C118: FREEPORT-MCMORAN - MRKT VALUE TO BOOK | D118: 152594(MTBV) | E118: 2.88 | F118: 13.66 | G118: 4.63 | H118: 3.14 | I118: 2.34 | J118: 2.21 | K118: 1.68 | L118: 1.94 | M118: 1.58 | N118: 2.18 | O118: 2.57
A119: =VLOOKUP(B119,'PORTFOLIO RAW'!B:B,1,FALSE) -> 951018 | B119: 951018 | C119: GAP - MRKT VALUE TO BOOK | D119: 951018(MTBV) | E119: 3.4 | F119: 3.09 | G119: 3.14 | H119: 2.91 | I119: 3.1 | J119: 6.01 | K119: 6.34 | L119: 6.4 | M119: 5.05 | N119: 3.1 | O119: 3.49
A120: =VLOOKUP(B120,'PORTFOLIO RAW'!B:B,1,FALSE) -> 907652 | B120: 907652 | C120: GENERAL DYNAMICS - MRKT VALUE TO BOOK | D120: 907652(MTBV) | E120: 2.87 | F120: 3.26 | G120: 2 | H120: 1.82 | I120: 1.63 | J120: 2.05 | K120: 2.13 | L120: 3.66 | M120: 4.18 | N120: 4.22 | O120: 5.35
A121: =VLOOKUP(B121,'PORTFOLIO RAW'!B:B,1,FALSE) -> 905801 | B121: 905801 | C121: GENERAL MILLS - MRKT VALUE TO BOOK | D121: 905801(MTBV) | E121: 3.07 | F121: 4.52 | G121: 3.65 | H121: 3.64 | I121: 3.76 | J121: 3.91 | K121: 4.72 | L121: 6.2 | M121: 6.86 | N121: 8.84 | O121: 4.83
A122: =VLOOKUP(B122,'PORTFOLIO RAW'!B:B,1,FALSE) -> 906511 | B122: 906511 | C122: GENUINE PARTS - MRKT VALUE TO BOOK | D122: 906511(MTBV) | E122: 3.18 | F122: 2.94 | G122: 2.29 | H122: 2.5 | I122: 2.94 | J122: 3.24 | K122: 3.76 | L122: 4.14 | M122: 4.01 | N122: 4.6 | O122: 3.73
... A235: =VLOOKUP(B235,'PORTFOLIO RAW'!B:B,1,FALSE) -> 933974 | B235: 933974 | C235: TRAVELERS COS. - MRKT VALUE TO BOOK | D235: 933974(MTBV) | E235: 1.3 | F235: 1.18 | G235: 1.06 | H235: 1.07 | I235: 0.98 | J235: 1.18 | K235: 1.37 | L235: 1.4 | M235: 1.39 | N235: 1.47 | O235: 1.48
A236: =VLOOKUP(B236,'PORTFOLIO RAW'!B:B,1,FALSE) -> 14015T | B236: 14015T | C236: FIDELITY NAT.INFO.SVS. - MRKT VALUE TO BOOK | D236: 14015T(MTBV) | E236: 2.35 | F236: 1.09 | G236: 0.58 | H236: 1.29 | I236: 1.22 | J236: 1.44 | K236: 2.08 | L236: 2.49 | M236: 2.06 | N236: 2.58 | O236: 2.85
A237: =VLOOKUP(B237,'PORTFOLIO RAW'!B:B,1,FALSE) -> 905019 | B237: 905019 | C237: MERCK & COMPANY - MRKT VALUE TO BOOK | D237: 905019(MTBV) | E237: 6.13 | F237: 3.64 | G237: 1.14 | H237: 2.07 | I237: 1.84 | J237: 2.58 | K237: 2.82 | L237: 3.59 | M237: 3.29 | N237: 4.27 | O237: 5.23
A238: =VLOOKUP(B238,'PORTFOLIO RAW'!B:B,1,FALSE) -> 912090 | B238: 912090 | C238: SCHLUMBERGER - MRKT VALUE TO BOOK | D238: 912090(MTBV) | E238: 8.6 | F238: 6.45 | G238: 3.87 | H238: 2.58 | I238: 2.99 | J238: 2.87 | K238: 2.93 | L238: 3.54 | M238: 2.58 | N238: 2.55 | O238: 2.54
A239: =VLOOKUP(B239,'PORTFOLIO RAW'!B:B,1,FALSE) -> 755741 | B239: 755741 | C239: CHARLES SCHWAB - MRKT VALUE TO BOOK | D239: 755741(MTBV) | E239: 7.07 | F239: 7.16 | G239: 4.03 | H239: 2.68 | I239: 1.86 | J239: 1.97 | K239: 2.88 | L239: 3.63 | M239: 3.14 | N239: 2.99 | O239: 3.55
A240: =VLOOKUP(B240,'PORTFOLIO RAW'!B:B,1,FALSE) -> 14361V | B240: 14361V | C240: ZIMMER BIOMET HDG. - MRKT VALUE TO BOOK | D240: 14361V(MTBV) | E240: 3.61 | F240: 2.71 | G240: 1.94 | H240: 1.8 | I240: 1.98 | J240: 1.99 | K240: 2.24 | L240: 2.69 | M240: 2.04 | N240: 2.58 | O240: 2
A241: =VLOOKUP(B241,'PORTFOLIO RAW'!B:B,1,FALSE) -> 154680 | B241: 154680 | C241: AMERISOURCEBERGEN - MRKT VALUE TO BOOK | D241: 154680(MTBV) | E241: 2.65 | F241: 2.31 | G241: 2.38 | H241: 2.89 | I241: 3.73 | J241: 3.93 | K241: 6.14 | L241: 8.87 | M241: 36.21 | N241: 9.17 | O241: 8.44
A242: =VLOOKUP(B242,'PORTFOLIO RAW'!B:B,1,FALSE) -> 14698C | B242: 14698C | C242: PRINCIPAL FINL.GP. - MRKT VALUE TO BOOK | D242: 14698C(MTBV) | E242: 2.32 | F242: 2.11 | G242: 1.09 | H242: 0.93 | I242: 0.88 | J242: 1.01 | K242: 1.35 | L242: 1.57 | M242: 1.52 | N242: 1.38 | O242: 1.61
A243: =VLOOKUP(B243,'PORTFOLIO RAW'!B:B,1,FALSE) -> 905361 | B243: 905361 | C243: SHERWIN-WILLIAMS - MRKT VALUE TO BOOK | D243: 905361(MTBV) | E243: 4.93 | F243: 4.64 | G243: 4.84 | H243: 5.05 | I243: 5.2 | J243: 8.99 | K243: 10.66 | L243: 21.64 | M243: 26.49 | N243: 13.51 | O243: 8.78
A244: =VLOOKUP(B244,'PORTFOLIO RAW'!B:B,1,FALSE) -> 357834 | B244: 357834 | C244: SIMON PROPERTY GROUP - MRKT VALUE TO BOOK | D244: 357834(MTBV) | E244: 7.85 | F244: 8.69 | G244: 4.71 | H244: 5.95 | I244: 7.63 | J244: 8.06 | K244: 8.07 | L244: 10.2 | M244: 12.86 | N244: 15.37 | O244: 13.64
A245: =VLOOKUP(B245,'PORTFOLIO RAW'!B:B,1,FALSE) -> 906400 | B245: 906400 | C245: SNAP-ON - MRKT VALUE TO BOOK | D245: 906400(MTBV) | E245: 2.22 | F245: 2.83 | G245: 1.65 | H245: 1.96 | I245: 1.9 | J245: 2.33 | K245: 2.78 | L245: 3.26 | M245: 3.75 | N245: 3.32 | O245: 2.91
A246: =VLOOKUP(B246,'PORTFOLIO RAW'!B:B,1,FALSE) -> 14861V | B246: 14861V | C246: PRUDENTIAL FINL. - MRKT VALUE TO BOOK | D246: 14861V(MTBV) | E246: 1.86 | F246: 1.83 | G246: 0.99 | H246: 0.9 | I246: 0.75 | J246: 0.98 | K246: 1.45 | L246: 1.89 | M246: 1.31 | N246: 1.26 | O246: 1.33
A247: =VLOOKUP(B247,'PORTFOLIO RAW'!B:B,1,FALSE) -> 14806F | B247: 14806F | C247: ADV.AUTO PARTS - MRKT VALUE TO BOOK | D247: 14806F(MTBV) | E247: 3.42 | F247: 3.48 | G247: 2.92 | H247: 4.8 | I247: 5.36 | J247: 4.19 | K247: 3.87 | L247: 4.8 | M247: 5.17 | N247: 3.68 | O247: 2.05
A248: =VLOOKUP(B248,'PORTFOLIO RAW'!B:B,1,FALSE) -> 902324 | B248: 902324 | C248: EDISON INTL. - MRKT VALUE TO BOOK | D248: 902324(MTBV) | E248: 2.19 | F248: 1.37 | G248: 1.16 | H248: 1.06 | I248: 1.23 | J248: 1.56 | K248: 1.51 | L248: 1.72 | M248: 1.76 | N248: 1.99 | O248: 2.21
A249: =VLOOKUP(B249,'PORTFOLIO RAW'!B:B,1,FALSE) -> 902325 | B249: 902325 | C249: SOUTHERN - MRKT VALUE TO BOOK | D249: 902325(MTBV) | E249: 2.26 | F249: 2.23 | G249: 1.71 | H249: 1.91 | I249: 2.09 | J249: 2.15 | K249: 1.92 | L249: 1.96 | M249: 1.92 | N249: 2.06 | O249: 2.05
A250: =VLOOKUP(B250,'PORTFOLIO RAW'!B:B,1,FALSE) -> 992305 | B250: 992305 | C250: BB&T - MRKT VALUE TO BOOK | D250: 992305(MTBV) | E250: 1.83 | F250: 1.74 | G250: 1.17 | H250: 1 | I250: 0.89 | J250: 1.23 | K250: 1.22 | L250: 1.28 | M250: 1.05 | N250: 1.16 | O250: 1.37
A251: =VLOOKUP(B251,'PORTFOLIO RAW'!B:B,1,FALSE) -> 905647 | B251: 905647 | C251: SOUTHWEST AIRLINES - MRKT VALUE TO BOOK | D251: 905647(MTBV) | E251: 1.63 | F251: 2.32 | G251: 1.31 | H251: 1.46 | I251: 0.99 | J251: 0.95 | K251: 1.39 | L251: 3.49 | M251: 3.54 | N251: 2.71 | O251: 3.11
A252: =VLOOKUP(B252,'PORTFOLIO RAW'!B:B,1,FALSE) -> 945388 | B252: 945388 | C252: AT&T - MRKT VALUE TO BOOK | D252: 945388(MTBV) | E252: 2.22 | F252: 1.86 | G252: 1.57 | H252: 1.51 | I252: 1.62 | J252: 2.37 | K252: 2 | L252: 2.13 | M252: 1.63 | N252: 2 | O252: 1.68
A253: =VLOOKUP(B253,'PORTFOLIO RAW'!B:B,1,FALSE) -> 905024 | B253: 905024 | C253: CHEVRON - MRKT VALUE TO BOOK | D253: 905024(MTBV) | E253: 2.6 | F253: 2.08 | G253: 1.58 | H253: 1.53 | I253: 1.61 | J253: 1.69 | K253: 1.62 | L253: 1.53 | M253: 0.96 | N253: 1.27 | O253: 1.49
A254: =VLOOKUP(B254,'PORTFOLIO RAW'!B:B,1,FALSE) -> 951052 | B254: 951052 | C254: STATE STREET - MRKT VALUE TO BOOK | D254: 951052(MTBV) | E254: 2.29 | F254: 2.4 | G254: 1.86 | H254: 1.12 | I254: 0.87 | J254: 1.02 | K254: 1.52 | L254: 1.62 | M254: 1.53 | N254: 1.51 | O254: 1.87
A255: =VLOOKUP(B255,'PORTFOLIO RAW'!B:B,1,FALSE) -> 326143 | B255: 326143 | C255: STARBUCKS - MRKT VALUE TO BOOK | D255: 326143(MTBV) | E255: 8.98 | F255: 4.73 | G255: 5.02 | H255: 5.29 | I255: 6.99 | J255: 7.61 | K255: 12.77 | L255: 10.84 | M255: 14.5 | N255: 13.29 | O255: 14.61
A256: =VLOOKUP(B256,'PORTFOLIO RAW'!B:B,1,FALSE) -> 905792 | B256: 905792 | C256: PUBLIC STORAGE - MRKT VALUE TO BOOK | D256: 905792(MTBV) | E256: 2.54 | F256: 3.22 | G256: 2.38 | H256: 3.34 | I256: 3.98 | J256: 4.64 | K256: 5.39 | L256: 5.52 | M256: 7 | N256: 7.45 | O256: 7.58
A257: =VLOOKUP(B257,'PORTFOLIO RAW'!B:B,1,FALSE) -> 981722 | B257: 981722 | C257: STRYKER - MRKT VALUE TO BOOK | D257: 981722(MTBV) | E257: 5.2 | F257: 4.87 | G257: 2.84 | H257: 2.7 | I257: 2.45 | J257: 2.47 | K257: 2.98 | L257: 3.65 | M257: 4.39 | N257: 4.49 | O257: 5.36
A258: =VLOOKUP(B258,'PORTFOLIO RAW'!B:B,1,FALSE) -> 922725 | B258: 922725 | C258: SUNTRUST BANKS - MRKT VALUE TO BOOK | D258: 922725(MTBV) | E258: 1.56 | F258: 1.22 | G258: 0.68 | H258: 0.72 | I258: 0.51 | J258: 0.76 | K258: 0.86 | L258: 0.97 | M258: 0.87 | N258: 0.97 | O258: 1.2
A259: =VLOOKUP(B259,'PORTFOLIO RAW'!B:B,1,FALSE) -> 541900 | B259: 541900 | C259: SYMANTEC - MRKT VALUE TO BOOK | D259: 541900(MTBV) | E259: 1.55 | F259: 4.23 | G259: 2.8 | H259: 2.63 | I259: 2.52 | J259: 2.45 | K259: 3.03 | L259: 2.84 | M259: 3.73 | N259: 4.41 | O259: 4.13
... A282: =VLOOKUP(B282,'PORTFOLIO RAW'!B:B,1,FALSE) -> 904869 | B282: 904869 | C282: WHIRLPOOL - MRKT VALUE TO BOOK | D282: 904869(MTBV) | E282: 1.87 | F282: 2.24 | G282: 1.48 | H282: 1.44 | I282: 0.94 | J282: 1.54 | K282: 2.38 | L282: 2.49 | M282: 2.71 | N282: 2.54 | O282: 2.96
A283: =VLOOKUP(B283,'PORTFOLIO RAW'!B:B,1,FALSE) -> 26406N | B283: 26406N | C283: WYNN RESORTS - MRKT VALUE TO BOOK | D283: 26406N(MTBV) | E283: 8.18 | F283: 6.19 | G283: 2.81 | H283: 5.23 | I283: 9.16 | J283: -44.59 | K283: -85.06 | L283: -652.48 | M283: -62.06 | N283: 66.69 | O283: 15.77
A284: =VLOOKUP(B284,'PORTFOLIO RAW'!B:B,1,FALSE) -> 26393N | B284: 26393N | C284: CME GROUP - MRKT VALUE TO BOOK | D284: 26393N(MTBV) | E284: 2.41 | F284: 1.18 | G284: 1.05 | H284: 0.95 | I284: 0.82 | J284: 0.9 | K284: 1.18 | L284: 1.33 | M284: 1.49 | N284: 1.81 | O284: 2.03
A285: =VLOOKUP(B285,'PORTFOLIO RAW'!B:B,1,FALSE) -> 922407 | B285: 922407 | C285: WILLIAMS - MRKT VALUE TO BOOK | D285: 922407(MTBV) | E285: 3.17 | F285: 1.84 | G285: 1.27 | H285: 1.51 | I285: 8.82 | J285: 4.53 | K285: 5.15 | L285: 4.8 | M285: 5.63 | N285: 4.81 | O285: 2.6
A286: =VLOOKUP(B286,'PORTFOLIO RAW'!B:B,1,FALSE) -> 906979 | B286: 906979 | C286: ALLIANT ENERGY (XSC) - MRKT VALUE TO BOOK | D286: 906979(MTBV) | E286: 1.59 | F286: 1.36 | G286: 1.12 | H286: 1.38 | I286: 1.48 | J286: 1.54 | K286: 1.67 | L286: 1.85 | M286: 1.73 | N286: 2.29 | O286: 2.33
A287: =VLOOKUP(B287,'PORTFOLIO RAW'!B:B,1,FALSE) -> 877723 | B287: 877723 | C287: CARMAX - MRKT VALUE TO BOOK | D287: 877723(MTBV) | E287: 3.23 | F287: 2.28 | G287: 2.17 | H287: 2.33 | I287: 2.38 | J287: 2.27 | K287: 3.45 | L287: 3.68 | M287: 4.25 | N287: 3.43 | O287: 3.77
A288: =VLOOKUP(B288,'PORTFOLIO RAW'!B:B,1,FALSE) -> 543542 | B288: 543542 | C288: XILINX - MRKT VALUE TO BOOK | D288: 543542(MTBV) | E288: 4.79 | F288: 3.83 | G288: 2.97 | H288: 2.81 | I288: 2.94 | J288: 3.09 | K288: 4.5 | L288: 4.49 | M288: 4.24 | N288: 5.35 | O288: 7.41
A289: =VLOOKUP(B289,'PORTFOLIO RAW'!B:B,1,FALSE) -> 26276P | B289: 26276P | C289: CIMAREX EN. - MRKT VALUE TO BOOK | D289: 26276P(MTBV) | E289: 0.97 | F289: 1.87 | G289: 1.74 | H289: 2.25 | I289: 1.77 | J289: 1.53 | K289: 1.97 | L289: 2.58 | M289: 3.51 | N289: 5.08 | O289: 4.06
A290: =VLOOKUP(B290,'PORTFOLIO RAW'!B:B,1,FALSE) -> 921855 | B290: 921855 | C290: TJX - MRKT VALUE TO BOOK | D290: 921855(MTBV) | E290: 6.35 | F290: 6.4 | G290: 5.58 | H290: 5.58 | I290: 6.91 | J290: 9.07 | K290: 9.57 | L290: 9.69 | M290: 11.17 | N290: 10.93 | O290: 8.95
A291: =VLOOKUP(B291,'PORTFOLIO RAW'!B:B,1,FALSE) -> 951584 | B291: 951584 | C291: ZIONS BANCORP. - MRKT VALUE TO BOOK | D291: 951584(MTBV) | E291: 1.51 | F291: 1.16 | G291: 0.56 | H291: 0.83 | I291: 0.66 | J291: 0.78 | K291: 0.95 | L291: 0.96 | M291: 0.84 | N291: 0.88 | O291: 1.28
A292: =VLOOKUP(B292,'PORTFOLIO RAW'!B:B,1,FALSE) -> 951051 | B292: 951051 | C292: REGIONS FINL.NEW - MRKT VALUE TO BOOK | D292: 951051(MTBV) | E292: 1.11 | F292: 1.03 | G292: 0.52 | H292: 0.67 | I292: 0.37 | J292: 0.71 | K292: 0.85 | L292: 0.9 | M292: 0.75 | N292: 0.77 | O292: 1.13
A293: =VLOOKUP(B293,'PORTFOLIO RAW'!B:B,1,FALSE) -> 905997 | B293: 905997 | C293: MOLSON COORS BREWING 'B' - MRKT VALUE TO BOOK | D293: 905997(MTBV) | E293: 0.91 | F293: 1.26 | G293: 1.1 | H293: 0.98 | I293: 0.93 | J293: 0.92 | K293: 0.96 | L293: 1.61 | M293: 2.01 | N293: 1.74 | O293: 1.23
A294: =VLOOKUP(B294,'PORTFOLIO RAW'!B:B,1,FALSE) -> 31604H | B294: 31604H | C294: AMERIPRISE FINL. - MRKT VALUE TO BOOK | D294: 31604H(MTBV) | E294: 1.85 | F294: 1.53 | G294: 0.9 | H294: 1.13 | I294: 1 | J294: 1.33 | K294: 2.23 | L294: 2.92 | M294: 2.65 | N294: 2.55 | O294: 3.54
A295: =VLOOKUP(B295,'PORTFOLIO RAW'!B:B,1,FALSE) -> 543487 | B295: 543487 | C295: VIACOM 'B' - MRKT VALUE TO BOOK | D295: 543487(MTBV) | E295: 3.76 | F295: 2.37 | G295: 1.95 | H295: 2.34 | I295: 3.11 | J295: 3.76 | K295: 7.69 | L295: 9.22 | M295: 5.13 | N295: 3.35 | O295: 1.85
A296: =VLOOKUP(B296,'PORTFOLIO RAW'!B:B,1,FALSE) -> 32480Q | B296: 32480Q | C296: CBS 'B' - MRKT VALUE TO BOOK | D296: 32480Q(MTBV) | E296: 1.08 | F296: 1.24 | G296: 0.94 | H296: 1.08 | I296: 1.61 | J296: 2.3 | K296: 3.41 | L296: 4.23 | M296: 3.72 | N296: 6.07 | O296: 12.07
A297: =VLOOKUP(B297,'PORTFOLIO RAW'!B:B,1,FALSE) -> 41071J | B297: 41071J | C297: HANESBRANDS - MRKT VALUE TO BOOK | D297: 41071J(MTBV) | E297: 9.23 | F297: 13.16 | G297: 6.33 | H297: 4.4 | I297: 3.87 | J297: 3.6 | K297: 5.12 | L297: 7.7 | M297: 9.47 | N297: 7.94 | O297: 13.09
A298: =VLOOKUP(B298,'PORTFOLIO RAW'!B:B,1,FALSE) -> 41195M | B298: 41195M | C298: WESTERN UNION - MRKT VALUE TO BOOK | D298: 41195M(MTBV) | E298: 299.31 | F298: -2315.23 | G298: 38.82 | H298: 19.8 | I298: 11.39 | J298: 11.97 | K298: 9.31 | L298: 6.81 | M298: 6.76 | N298: 10.72 | O298: -17.89
A299: =VLOOKUP(B299,'PORTFOLIO RAW'!B:B,1,FALSE) -> 517465 | B299: 517465 | C299: PEOPLES UNITED FINANCIAL - MRKT VALUE TO BOOK | D299: 517465(MTBV) | E299: 1.18 | F299: 1.46 | G299: 1.11 | H299: 0.93 | I299: 0.88 | J299: 0.84 | K299: 1.01 | L299: 1 | M299: 1 | N299: 1 | O299: 1.07
A300: =VLOOKUP(B300,'PORTFOLIO RAW'!B:B,1,FALSE) -> 905840 | B300: 905840 | C300: BANK OF NEW YORK MELLON - MRKT VALUE TO BOOK | D300: 905840(MTBV) | E300: 1.68 | F300: 1.63 | G300: 1.26 | H300: 0.97 | I300: 0.75 | J300: 0.77 | K300: 0.99 | L300: 1.25 | M300: 1.21 | N300: 1.22 | O300: 1.44
A301: =VLOOKUP(B301,'PORTFOLIO RAW'!B:B,1,FALSE) -> 51245V | B301: 51245V | C301: INVESCO - MRKT VALUE TO BOOK | D301: 51245V(MTBV) | E301: NA | F301: 1.84 | G301: 1.36 | H301: 1.22 | I301: 0.99 | J301: 1.36 | K301: 1.72 | L301: 2.13 | M301: 1.77 | N301: 1.67 | O301: 1.57
A302: =VLOOKUP(B302,'PORTFOLIO RAW'!B:B,1,FALSE) -> 328314 | B302: 328314 | C302: CHUBB - MRKT VALUE TO BOOK | D302: 328314(MTBV) | E302: 1.21 | F302: 1.36 | G302: 0.88 | H302: 0.92 | I302: 0.94 | J302: 1.04 | K302: 1.17 | L302: 1.3 | M302: 1.15 | N302: 1.23 | O302: 1.35
A303: =VLOOKUP(B303,'PORTFOLIO RAW'!B:B,1,FALSE) -> 31196R | B303: 31196R | C303: DISCOVERY SERIES A - MRKT VALUE TO BOOK | D303: 31196R(MTBV) | E303: 2.59 | F303: 1.76 | G303: 1.35 | H303: 1.95 | I303: 1.58 | J303: 2.34 | K303: 3.11 | L303: 2.67 | M303: 2.16 | N303: 1.82 | O303: 1.75
A304: =VLOOKUP(B304,'PORTFOLIO RAW'!B:B,1,FALSE) -> 771767 | B304: 771767 | C304: MOSAIC - MRKT VALUE TO BOOK | D304: 771767(MTBV) | E304: 3.11 | F304: 4.98 | G304: 2.77 | H304: 2.33 | I304: 2.18 | J304: 2.27 | K304: 1.69 | L304: 1.55 | M304: 1.31 | N304: 0.92 | O304: 0.76
A305: =VLOOKUP(B305,'PORTFOLIO RAW'!B:B,1,FALSE) -> 921503 | B305: 921503 | C305: STANLEY BLACK & DECKER - MRKT VALUE TO BOOK | D305: 921503(MTBV) | E305: 2.71 | F305: 2.2 | G305: 1.7 | H305: 1.43 | I305: 1.3 | J305: 1.92 | K305: 2.12 | L305: 2.27 | M305: 2.64 | N305: 2.88 | O305: 3.09
A306: =VLOOKUP(B306,'PORTFOLIO RAW'!B:B,1,FALSE) -> 255781 | B306: 255781 | C306: GARMIN - MRKT VALUE TO BOOK | D306: 255781(MTBV) | E306: 9.85 | F306: 3.53 | G306: 2.59 | H306: 1.97 | I306: 1.98 | J306: 2.31 | K306: 2.33 | L306: 2.95 | M306: 2.07 | N306: 2.63 | O306: 2.58
A307: =VLOOKUP(B307,'PORTFOLIO RAW'!B:B,1,FALSE) -> 670129 | B307: 670129 | C307: PROLOGIS - MRKT VALUE TO BOOK | D307: 670129(MTBV) | E307: 2.28 | F307: 2.02 | G307: 1.34 | H307: 1.45 | I307: 0.99 | J307: 1.3 | K307: 1.4 | L307: 1.39 | M307: 1.37 | N307: 1.85 | O307: 2.21
A308: =VLOOKUP(B308,'PORTFOLIO RAW'!B:B,1,FALSE) -> 14352P | B308: 14352P | C308: ACCENTURE CLASS A - MRKT VALUE TO BOOK | D308: 14352P(MTBV) | E308: 10.9 | F308: 9.24 | G308: 8.57 | H308: 7.35 | I308: 9.04 | J308: 8.79 | K308: 9.09 | L308: 8.53 | M308: 8.38 | N308: 7.96 | O308: 8.24
A309: =VLOOKUP(B309,'PORTFOLIO RAW'!B:B,1,FALSE) -> 749688 | B309: 749688 | C309: HCA HEALTHCARE - MRKT VALUE TO BOOK | D309: 749688(MTBV) | E309: NA | F309: NA | G309: NA | H309: NA | I309: -1.25 | J309: -1.48 | K309: -2.28 | L309: -4.02 | M309: -4.51 | N309: -3.89 | O309: -4.13
A310: =VLOOKUP(B310,'PORTFOLIO RAW'!B:B,1,FALSE) -> 894145 | B310: 894145 | C310: RALPH LAUREN CL.A - MRKT VALUE TO BOOK | D310: 894145(MTBV) | E310: 3.61 | F310: 2.62 | G310: 2.41 | H310: 2.62 | I310: 3.84 | J310: 3.69 | K310: 3.61 | L310: 3.86 | M310: 2.54 | N310: 2.48 | O310: 2.09
A311: =VLOOKUP(B311,'PORTFOLIO RAW'!B:B,1,FALSE) -> 26599V | B311: 26599V | C311: SEAGATE TECH. - MRKT VALUE TO BOOK | D311: 26599V(MTBV) | E311: 2.96 | F311: 4.11 | G311: 2.78 | H311: 2.16 | I311: 1.37 | J311: 3.37 | K311: 5.22 | L311: 6.3 | M311: 8.51 | N311: 7.81 | O311: 5.6
A312: =VLOOKUP(B312,'PORTFOLIO RAW'!B:B,1,FALSE) -> 904878 | B312: 904878 | C312: MOTOROLA SOLUTIONS - MRKT VALUE TO BOOK | D312: 904878(MTBV) | E312: 2.65 | F312: 1.79 | G312: 2.1 | H312: 1.81 | I312: 2.92 | J312: 4.37 | K312: 4.39 | L312: 5.68 | M312: -130.87 | N312: -13.01 | O312: -8
A313: =VLOOKUP(B313,'PORTFOLIO RAW'!B:B,1,FALSE) -> 922817 | B313: 922817 | C313: AON CLASS A - MRKT VALUE TO BOOK | D313: 922817(MTBV) | E313: 2.09 | F313: 2.44 | G313: 2.15 | H313: 1.27 | I313: 1.74 | J313: 2.19 | K313: 2.85 | L313: 3.84 | M313: 4.1 | N313: 5.35 | O313: 8.1
A314: =VLOOKUP(B314,'PORTFOLIO RAW'!B:B,1,FALSE) -> 905446 | B314: 905446 | C314: INGERSOLL-RAND - MRKT VALUE TO BOOK | D314: 905446(MTBV) | E314: 1.95 | F314: 1.75 | G314: 1.44 | H314: 1.42 | I314: 1.58 | J314: 2 | K314: 2.69 | L314: 2.65 | M314: 2.51 | N314: 2.49 | O314: 3.17
A315: =VLOOKUP(B315,'PORTFOLIO RAW'!B:B,1,FALSE) -> 28513N | B315: 28513N | C315: CBRE GROUP CLASS A - MRKT VALUE TO BOOK | D315: 28513N(MTBV) | E315: 6.53 | F315: 26.02 | G315: 5.67 | H315: 6.64 | I315: 3.96 | J315: 4.14 | K315: 4.16 | L315: 4.46 | M315: 4.08 | N315: 3.18 | O315: 3.12
A316: =VLOOKUP(B316,'PORTFOLIO RAW'!B:B,1,FALSE) -> 31412T | B316: 31412T | C316: EXPEDIA GROUP - MRKT VALUE TO BOOK | D316: 31412T(MTBV) | E316: 1.8 | F316: 2.06 | G316: 2.63 | H316: 3.08 | I316: 3.61 | J316: 3.3 | K316: 3.37 | L316: 6.07 | M316: 3.31 | N316: 3.9 | O316: 4.79
A317: =VLOOKUP(B317,'PORTFOLIO RAW'!B:B,1,FALSE) -> 680902 | B317: 680902 | C317: AMERICAN TOWER - MRKT VALUE TO BOOK | D317: 680902(MTBV) | E317: 5.68 | F317: 5.23 | G317: 4.48 | H317: 5.74 | I317: 6.64 | J317: 7.83 | K317: 8.26 | L317: 9.54 | M317: 8.19 | N317: 9.65 | O317: 9.66
A318: =VLOOKUP(B318,'PORTFOLIO RAW'!B:B,1,FALSE) -> 904383 | B318: 904383 | C318: DUKE ENERGY - MRKT VALUE TO BOOK | D318: 904383(MTBV) | E318: 1.11 | F318: 1.08 | G318: 0.95 | H318: 1.03 | I318: 1.15 | J318: 1.1 | K318: 1.15 | L318: 1.29 | M318: 1.2 | N318: 1.35 | O318: 1.43
A319: =VLOOKUP(B319,'PORTFOLIO RAW'!B:B,1,FALSE) -> 13967E | B319: 13967E | C319: MONDELEZ INTERNATIONAL CL.A - MRKT VALUE TO BOOK | D319: 13967E(MTBV) | E319: 2 | F319: 2.39 | G319: 1.52 | H319: 1.54 | I319: 1.73 | J319: 2.29 | K319: 1.78 | L319: 2.17 | M319: 2.46 | N319: 2.65 | O319: 2.33
A320: =VLOOKUP(B320,'PORTFOLIO RAW'!B:B,1,FALSE) -> 903749 | B320: 903749 | C320: EATON - MRKT VALUE TO BOOK | D320: 903749(MTBV) | E320: 2.77 | F320: 1.82 | G320: 1.46 | H320: 1.85 | I320: 1.76 | J320: 1.07 | K320: 1.99 | L320: 2 | M320: 1.63 | N320: 1.92 | O320: 2.02
A321: =VLOOKUP(B321,'PORTFOLIO RAW'!B:B,1,FALSE) -> 937343 | B321: 937343 | C321: L BRANDS - MRKT VALUE TO BOOK | D321: 937343(MTBV) | E321: 3.65 | F321: 3.53 | G321: 2.48 | H321: 5.99 | I321: 89.8 | J321: -14.65 | K321: -47.01 | L321: 1081.05 | M321: -103.07 | N321: -28.33 | O321: -14.03
A322: =VLOOKUP(B322,'PORTFOLIO RAW'!B:B,1,FALSE) -> 905113 | B322: 905113 | C322: ARCONIC - MRKT VALUE TO BOOK | D322: 905113(MTBV) | E322: 2.06 | F322: 1.87 | G322: 1.11 | H322: 0.86 | I322: 0.87 | J322: 0.75 | K322: 0.84 | L322: 1.56 | M322: 1.09 | N322: 2.46 | O322: 2.38
A323: =VLOOKUP(B323,'PORTFOLIO RAW'!B:B,1,FALSE) -> 13967H | B323: 13967H | C323: WILLIS TOWERS WATSON - MRKT VALUE TO BOOK | D323: 13967H(MTBV) | E323: 4.22 | F323: 2.44 | G323: 2.17 | H323: 2.06 | I323: 2.47 | J323: 4.05 | K323: 3.54 | L323: 3.83 | M323: 3.37 | N323: 1.72 | O323: 2.02
A324: =VLOOKUP(B324,'PORTFOLIO RAW'!B:B,1,FALSE) -> 921431 | B324: 921431 | C324: BAKER HUGHES A - MRKT VALUE TO BOOK | D324: 921431(MTBV) | E324: 4.51 | F324: 3.05 | G324: 1.87 | H324: 1.24 | I324: 1.6 | J324: 1.22 | K324: 1.25 | L324: 1.58 | M324: 1.43 | N324: 1.64 | O324: 1.1
A325: =VLOOKUP(B325,'PORTFOLIO RAW'!B:B,1,FALSE) -> 266220 | B325: 266220 | C325: TAPESTRY - MRKT VALUE TO BOOK | D325: 266220(MTBV) | E325: 11.99 | F325: 5.86 | G325: 7.11 | H325: 7.64 | I325: 8.64 | J325: 6.99 | K325: 6.39 | L325: 4.1 | M325: 3.01 | N325: 3.35 | O325: 3.46
A326: =VLOOKUP(B326,'PORTFOLIO RAW'!B:B,1,FALSE) -> 30730Q | B326: 30730Q | C326: INTERCONTINENTAL EX. - MRKT VALUE TO BOOK | D326: 30730Q(MTBV) | E326: 6.35 | F326: 3.05 | G326: 2.98 | H326: 2.8 | I326: 2.88 | J326: 2.75 | K326: 1.05 | L326: 1.87 | M326: 1.7 | N326: 2.12 | O326: 2.32
A327: =VLOOKUP(B327,'PORTFOLIO RAW'!B:B,1,FALSE) -> 921925 | B327: 921925 | C327: JEFFERIES FINANCIAL GROUP - MRKT VALUE TO BOOK | D327: 921925(MTBV) | E327: 1.78 | F327: 3.83 | G327: 1.42 | H327: 0.84 | I327: 1.09 | J327: 0.86 | K327: 0.98 | L327: 0.91 | M327: 0.72 | N327: 0.67 | O327: 0.87
A328: =VLOOKUP(B328,'PORTFOLIO RAW'!B:B,1,FALSE) -> 912278 | B328: 912278 | C328: CIGNA - MRKT VALUE TO BOOK | D328: 912278(MTBV) | E328: 3.18 | F328: 2.7 | G328: 1.71 | H328: 1.55 | I328: 1.62 | J328: 1.52 | K328: 2.2 | L328: 2.33 | M328: 3.03 | N328: 2.53 | O328: 3.41
...

Sheet MCAP
A1: Market Capitalization
A2: Code | B2: Code | C2: Name | D2: Code | E2: 2007 | F2: 2008 | G2: 2009 | H2: 2010 | I2: 2011 | J2: 2012 | K2: 2013 | L2: 2014 | M2: 2015 | N2: 2016 | O2: 2017 | P2: 2018
A3: =VLOOKUP(B3,'PORTFOLIO RAW'!B:B,1,FALSE) -> 906187 | B3: 906187 | C3: INT'L BUSINESS MACHS - MARKET CAPITALIZATION | D3: 906187(WC08001) | E3: 149743810 | F3: 112698313 | G3: 170868669 | H3: 180220333 | I3: 213886010 | J3: 214031778 | K3: 197772108 | L3: 158919632 | M3: 132903587 | N3: 157004530 | O3: 141480737 | P3: 101448135
A4: =VLOOKUP(B4,'PORTFOLIO RAW'!B:B,1,FALSE) -> 902172 | B4: 902172 | C4: 3M COMPANY - MARKET CAPITALIZATION | D4: 902172(WC08001) | E4: 59796037 | F4: 39906481 | G4: 58745229 | H4: 61443668 | I4: 56799901 | J4: 63796460 | K4: 93027298 | L4: 104365316 | M4: 91789490 | N4: 106557411 | O4: 140017903 | P4: 109860633
A5: =VLOOKUP(B5,'PORTFOLIO RAW'!B:B,1,FALSE) -> 902317 | B5: 902317 | C5: EXELON CORPORATION - MARKET CAPITALIZATION | D5: 902317(WC08001) | E5: 53978980 | F5: 36591380 | G5: 32254200 | H5: 27565680 | I5: 28770312 | J5: 25421199 | K5: 23473230 | L5: 31888800 | M5: 25548400 | N5: 32792760 | O5: 37951830 | P5: 43656800
A6: =VLOOKUP(B6,'PORTFOLIO RAW'!B:B,1,FALSE) -> 998171 | B6: 998171 | C6: HOME DEPOT, INC. - MARKET CAPITALIZATION | D6: 998171(WC08001) | E6: 45528600 | F6: 39041920 | G6: 49123140 | H6: 56902380 | I6: 64615480 | J6: 91785400 | K6: 113629200 | L6: 137195790 | M6: 165577000 | N6: 161298240 | O6: 219475740 | P6: 189861100
A7: =VLOOKUP(B7,'PORTFOLIO RAW'!B:B,1,FALSE) -> 912273 | B7: 912273 | C7: CORNING INCORPORATED - MARKET CAPITALIZATION | D7: 912273(WC08001) | E7: 37616320 | F7: 14752440 | G7: 29988430 | H7: 30158520 | I7: 19664700 | J7: 18551400 | K7: 24930180 | L7: 29212820 | M7: 20656400 | N7: 22474020 | O7: 27447420 | P7: 23805480
A8: =VLOOKUP(B8,'PORTFOLIO RAW'!B:B,1,FALSE) -> 905113 | B8: 905113 | C8: ARCONIC INC - MARKET CAPITALIZATION | D8: 905113(WC08001) | E8: 30241536 | F8: 9011574 | G8: 15706955 | H8: 15728979 | I8: 9207164 | J8: 9263400 | K8: 11384849 | L8: 19211119 | M8: 12931280 | N8: 8130157 | O8: 13118601 | P8: 8147944
A9: =VLOOKUP(B9,'PORTFOLIO RAW'!B:B,1,FALSE) -> 902354 | B9: 902354 | C9: KIMBERLY-CLARK CORP - MARKET CAPITALIZATION | D9: 902354(WC08001) | E9: 29185206 | F9: 21813264 | G9: 26567070 | H9: 25650976 | I9: 29107692 | J9: 32868599 | K9: 39778264 | L9: 42206762 | M9: 45942570 | N9: 40695192 | O9: 42363726 | P9: 39309300
A10: =VLOOKUP(B10,'PORTFOLIO RAW'!B:B,1,FALSE) -> 9373MH | B10: 9373MH | C10: LINDE PLC - MARKET CAPITALIZATION | D10: 9373MH(WC08001) | E10: 27986954 | F10: 18215291 | G10: 24613216 | H10: 29022553 | I10: 31912859 | J10: 32422317 | K10: 38246226 | L10: 37476734 | M10: 29171618 | N10: 33387522 | O10: 44358665 | P10: 85391584
A11: =VLOOKUP(B11,'PORTFOLIO RAW'!B:B,1,FALSE) -> 905296 | B11: 905296 | C11: APPLIED MATERIALS - MARKET CAPITALIZATION | D11: 905296(WC08001) | E11: 24610227 | F11: 13480609 | G11: 18692383 | H11: 18658372 | I11: 13987260 | J11: 13693680 | K11: 21286720 | L11: 30427320 | M11: 21657200 | N11: 34787060 | O11: 54187200 | P11: 31659580
A12: =VLOOKUP(B12,'PORTFOLIO RAW'!B:B,1,FALSE) -> 545615 | B12: 545615 | C12: JOHNSON CONTROLS INT - MARKET CAPITALIZATION | D12: 545615(WC08001) | E12: 19678368 | F12: 10212172 | G12: 16918162 | H12: 20239527 | I12: 21702594 | J12: 13519020 | K12: 19020411 | L12: 18723948 | M12: 13467820 | N12: 38545430 | O12: 35365126 | P12: 28196259
A13: =VLOOKUP(B13,'PORTFOLIO RAW'!B:B,1,FALSE) -> 951018 | B13: 951018 | C13: GAP INC - MARKET CAPITALIZATION | D13: 951018(WC08001) | E13: 15619520 | F13: 9292660 | G13: 14162200 | H13: 13018320 | I13: 8996750 | J13: 14371520 | K13: 17429680 | L13: 17728310 | M13: 9805900 | N13: 8953560 | O13: 13249340 | P13: 9737280
A14: =VLOOKUP(B14,'PORTFOLIO RAW'!B:B,1,FALSE) -> 902230 | B14: 902230 | C14: FORD MOTOR COMPANY - MARKET CAPITALIZATION | D14: 902230(WC08001) | E14: 14772350 | F14: 5523480 | G14: 33370000 | H14: 63511717 | I14: 40896036 | J14: 50793107 | K14: 61473120 | L14: 62139500 | M14: 56796790 | N14: 49090110 | O14: 50684420 | P14: 31143150
A15: =VLOOKUP(B15,'PORTFOLIO RAW'!B:B,1,FALSE) -> 904069 | B15: 904069 | C15: INTERNATIONAL PAPER - MARKET CAPITALIZATION | D15: 904069(WC08001) | E15: 13767976 | F15: 5043981 | G15: 11600025 | H15: 11921232 | I15: 12933750 | J15: 17524859 | K15: 21393358 | L15: 22512494 | M15: 15537075 | N15: 21819811 | O15: 23924875 | P15: 16167812
A16: =VLOOKUP(B16,'PORTFOLIO RAW'!B:B,1,FALSE) -> 902335 | B16: 902335 | C16: WEC ENERGY GROUP INC - MARKET CAPITALIZATION | D16: 902335(WC08001) | E16: 5696297 | F16: 4908259 | G16: 5825676 | H16: 6879886 | I16: 8057819 | J16: 8440104 | K16: 9341309 | L16: 11893784 | M16: 16197720 | N16: 18510816 | O16: 20963622 | P16: 21853136
A17: =VLOOKUP(B17,'PORTFOLIO RAW'!B:B,1,FALSE) -> 905082 | B17: 905082 | C17: FMC CORPORATION - MARKET CAPITALIZATION | D17: 905082(WC08001) | E17: 4098309 | F17: 3243370 | G17: 4043653 | H17: 5711004 | I17: 6008789 | J17: 8056471 | K17: 10027554 | L17: 7603107 | M17: 5229951 | N17: 7561512 | O17: 12715730 | P17: 9783548
A18: =VLOOKUP(B18,'PORTFOLIO RAW'!B:B,1,FALSE) -> 912228 | B18: 912228 | C18: PROCTER & GAMBLE - MARKET CAPITALIZATION | D18: 912228(WC08001) | E18: 229944098 | F18: 187432058 | G18: 176857710 | H18: 182922355 | I18: 184499847 | J18: 186561720 | K18: 223250643 | L18: 246927319 | M18: 215558445 | N18: 224325440 | O18: 234597204 | P18: 229616160
A19: =VLOOKUP(B19,'PORTFOLIO RAW'!B:B,1,FALSE) -> 542868 | B19: 542868 | C19: CISCO SYSTEMS, INC. - MARKET CAPITALIZATION | D19: 542868(WC08001) | E19: 165126390 | F19: 96055900 | G19: 138492900 | H19: 114400650 | I19: 98264800 | J19: 104102521 | K19: 120875270 | L19: 142051205 | M19: 138083175 | N19: 151976380 | O19: 190848900 | P19: 199924620
A20: =VLOOKUP(B20,'PORTFOLIO RAW'!B:B,1,FALSE) -> 922726 | B20: 922726 | C20: INTEL CORPORATION - MARKET CAPITALIZATION | D20: 922726(WC08001) | E20: 155107880 | F20: 81538920 | G20: 112669200 | H20: 115896330 | I20: 121250000 | J20: 101945280 | K20: 128918485 | L20: 172304920 | M20: 162776250 | N20: 171557100 | O20: 216351920 | P20: 211935880
A21: =VLOOKUP(B21,'PORTFOLIO RAW'!B:B,1,FALSE) -> 902242 | B21: 902242 | C21: JPMORGAN CHASE & CO - MARKET CAPITALIZATION | D21: 902242(WC08001) | E21: 146987010 | F21: 117544026 | G21: 164263140 | H21: 165874676 | I21: 125441966 | J21: 167256355 | K21: 219657214 | L21: 232471512 | M21: 241899221 | N21: 307295076 | O21: 366301457 | P21: 319780298
A22: =VLOOKUP(B22,'PORTFOLIO RAW'!B:B,1,FALSE) -> 905019 | B22: 905019 | C22: MERCK & CO INC - MARKET CAPITALIZATION | D22: 905019(WC08001) | E22: 126244143 | F22: 64073786 | G22: 113574452 | H22: 111079130 | I22: 114639617 | J22: 123910449 | K22: 146522712 | L22: 161177982 | M22: 146899185 | N22: 161817813 | O22: 151738335 | P22: 198097475
... A46: =VLOOKUP(B46,'PORTFOLIO RAW'!B:B,1,FALSE) -> 905016 | B46: 905016 | C46: NEXTERA ENERGY - MARKET CAPITALIZATION | D46: 905016(WC08001) | E46: 27609842 | F46: 20580707 | G46: 21847537 | H46: 21880591 | I46: 25326080 | J46: 29336560 | K46: 37244700 | L46: 47086470 | M46: 47893290 | N46: 55907280 | O46: 73565490 | P46: 83085960
A47: =VLOOKUP(B47,'PORTFOLIO RAW'!B:B,1,FALSE) -> 14352P | B47: 14352P | C47: ACCENTURE PLC - MARKET CAPITALIZATION | D47: 14352P(WC08001) | E47: 27330590 | F47: 23976484 | G47: 29584317 | H47: 33459247 | I47: 36771251 | J47: 45003917 | K47: 54787741 | L47: 58637023 | M47: 67928811 | N47: 75266594 | O47: 97378767 | P47: 90202687
A48: =VLOOKUP(B48,'PORTFOLIO RAW'!B:B,1,FALSE) -> 912633 | B48: 912633 | C48: RAYTHEON COMPANY - MARKET CAPITALIZATION | D48: 912633(WC08001) | E48: 25870097 | F48: 20416000 | G48: 19474560 | H48: 16636060 | I48: 16400820 | J48: 18879680 | K48: 28570500 | L48: 33208190 | M48: 37234470 | N48: 41606000 | O48: 54100800 | P48: 43244700
A49: =VLOOKUP(B49,'PORTFOLIO RAW'!B:B,1,FALSE) -> 904383 | B49: 904383 | C49: DUKE ENERGY CORP - MARKET CAPITALIZATION | D49: 904383(WC08001) | E49: 25454540 | F49: 19092720 | G49: 22527890 | H49: 23669488 | I49: 29392000 | J49: 44915200 | K49: 48721060 | L49: 59062780 | M49: 49116320 | N49: 54334000 | O49: 58877000 | P49: 62740100
A50: =VLOOKUP(B50,'PORTFOLIO RAW'!B:B,1,FALSE) -> 902321 | B50: 902321 | C50: PUBLIC SVC ENTRPR GR - MARKET CAPITALIZATION | D50: 902321(WC08001) | E50: 24978650 | F50: 14760542 | G50: 16823849 | H50: 16095040 | I50: 16701254 | J50: 15480310 | K50: 16207667 | L50: 20946693 | M50: 19577140 | N50: 22159400 | O50: 26007500 | P50: 26233200
A51: =VLOOKUP(B51,'PORTFOLIO RAW'!B:B,1,FALSE) -> 516007 | B51: 516007 | C51: MGM RESORTS - MARKET CAPITALIZATION | D51: 516007(WC08001) | E51: 24682463 | F51: 3804676 | G51: 4023923 | H51: 7254423 | I51: 5098547 | J51: 5694688 | K51: 11533282 | L51: 10503825 | M51: 12833140 | N51: 16551986 | O51: 18907949 | P51: 12796653
A52: =VLOOKUP(B52,'PORTFOLIO RAW'!B:B,1,FALSE) -> 944704 | B52: 944704 | C52: CARDINAL HEALTH, INC - MARKET CAPITALIZATION | D52: 944704(WC08001) | E52: 21257775 | F52: 12309237 | G52: 11606400 | H52: 13653684 | I52: 14258171 | J52: 14124740 | K52: 22648590 | L52: 27206010 | M52: 29280560 | N52: 23174340 | O52: 19361320 | P52: 13781400
A53: =VLOOKUP(B53,'PORTFOLIO RAW'!B:B,1,FALSE) -> 905271 | B53: 905271 | C53: AIR PRODUCTS & CHEMS - MARKET CAPITALIZATION | D53: 905271(WC08001) | E53: 21240531 | F53: 10523252 | G53: 17124757 | H53: 19445371 | I53: 17905682 | J53: 17852223 | K53: 23605617 | L53: 30798607 | M53: 28020374 | N53: 31259396 | O53: 35826224 | P53: 35133415
A54: =VLOOKUP(B54,'PORTFOLIO RAW'!B:B,1,FALSE) -> 902107 | B54: 902107 | C54: PPL CORP - MARKET CAPITALIZATION | D54: 902107(WC08001) | E54: 19443686 | F54: 11495754 | G54: 12186783 | H54: 12722851 | I54: 17016675 | J54: 16661057 | K54: 18966359 | L54: 24190294 | M54: 22998739 | N54: 23144841 | O54: 21460668 | P54: 20406751
A55: =VLOOKUP(B55,'PORTFOLIO RAW'!B:B,1,FALSE) -> 357834 | B55: 357834 | C55: SIMON PROPERTY GROUP - MARKET CAPITALIZATION | D55: 357834(WC08001) | E55: 19372758 | F55: 12290225 | G55: 22802712 | H55: 29545084 | I55: 37888793 | J55: 48991431 | K55: 47262199 | L55: 56597586 | M55: 60163735 | N55: 55623960 | O55: 53439796 | P55: 51911844
A56: =VLOOKUP(B56,'PORTFOLIO RAW'!B:B,1,FALSE) -> 134784 | B56: 134784 | C56: MCKESSON CORPORATION - MARKET CAPITALIZATION | D56: 134784(WC08001) | E56: 19325450 | F56: 10728210 | G56: 16937500 | H56: 19072980 | I56: 19633320 | J56: 22785600 | K56: 36637800 | L56: 47950980 | M56: 45757360 | N56: 31601250 | O56: 32905450 | P56: 22314940
A57: =VLOOKUP(B57,'PORTFOLIO RAW'!B:B,1,FALSE) -> 878574 | B57: 878574 | C57: YUM! BRANDS INC - MARKET CAPITALIZATION | D57: 878574(WC08001) | E57: 19096730 | F57: 14458500 | G57: 16400930 | H57: 23004450 | I57: 27144600 | J57: 29946400 | K57: 33495230 | L57: 31616900 | M57: 30681000 | N57: 22482150 | O57: 27094520 | P57: 28127520
A58: =VLOOKUP(B58,'PORTFOLIO RAW'!B:B,1,FALSE) -> 905861 | B58: 905861 | C58: NORTHERN TRUST CORP - MARKET CAPITALIZATION | D58: 905861(WC08001) | E58: 16894237 | F58: 11640933 | G58: 12664032 | H58: 13424120 | I58: 9558397 | J58: 11983976 | K58: 14687861 | L58: 15730534 | M58: 16529789 | N58: 20357318 | O58: 22587793 | P58: 18307217
A59: =VLOOKUP(B59,'PORTFOLIO RAW'!B:B,1,FALSE) -> 905818 | B59: 905818 | C59: WEYERHAEUSER CO - MARKET CAPITALIZATION | D59: 905818(WC08001) | E59: 15451957 | F59: 6467561 | G59: 9117973 | H59: 10146017 | I59: 10015062 | J59: 15089363 | K59: 18422624 | L59: 18823383 | M59: 15304289 | N59: 22523211 | O59: 26629153 | P59: 16316107
A60: =VLOOKUP(B60,'PORTFOLIO RAW'!B:B,1,FALSE) -> 14361V | B60: 14361V | C60: ZIMMER BIOMET - MARKET CAPITALIZATION | D60: 14361V(WC08001) | E60: 15406335 | F60: 9037912 | G60: 12070262 | H60: 10499808 | I60: 9508760 | J60: 11438856 | K60: 15823662 | L60: 19247374 | M60: 20794993 | N60: 20701920 | O60: 24447742 | P60: 21158880
A61: =VLOOKUP(B61,'PORTFOLIO RAW'!B:B,1,FALSE) -> 545101 | B61: 545101 | C61: AES CORP - MARKET CAPITALIZATION | D61: 545101(WC08001) | E61: 14338569 | F61: 5461363 | G61: 8886820 | H61: 9593056 | I61: 9059806 | J61: 7963623 | K61: 10483596 | L61: 9692032 | M61: 6381360 | N61: 7659698 | O61: 7152003 | P61: 9576830
A62: =VLOOKUP(B62,'PORTFOLIO RAW'!B:B,1,FALSE) -> 903749 | B62: 903749 | C62: EATON CORP PLC - MARKET CAPITALIZATION | D62: 903749(WC08001) | E62: 14154700 | F62: 8202150 | G62: 10573644 | H62: 17251625 | I62: 14556432 | J62: 25502526 | K62: 36164612 | L62: 31798484 | M62: 23875952 | N62: 30150246 | O62: 34756499 | P62: 29084376
A63: =VLOOKUP(B63,'PORTFOLIO RAW'!B:B,1,FALSE) -> 26599V | B63: 26599V | C63: SEAGATE TECHNOLOGY - MARKET CAPITALIZATION | D63: 26599V(WC08001) | E63: 13642027 | F63: 2149115 | G63: 8967830 | H63: 7067719 | I63: 6963630 | J63: 12047321 | K63: 20185984 | L63: 21714865 | M63: 11564233 | N63: 11396502 | O63: 12208894 | P63: 11081904
A64: =VLOOKUP(B64,'PORTFOLIO RAW'!B:B,1,FALSE) -> 902288 | B64: 902288 | C64: CONSOLIDATED EDISON - MARKET CAPITALIZATION | D64: 902288(WC08001) | E64: 13288415 | F64: 10655985 | G64: 12771452 | H64: 14455422 | I64: 18167875 | J64: 16266105 | K64: 16189986 | L64: 19332758 | M64: 18831110 | N64: 22472400 | O64: 26334500 | P64: 24543660
A65: =VLOOKUP(B65,'PORTFOLIO RAW'!B:B,1,FALSE) -> 905966 | B65: 905966 | C65: CUMMINS INC. - MARKET CAPITALIZATION | D65: 905966(WC08001) | E65: 12877107 | F65: 5380749 | G65: 10043340 | H65: 21528957 | I65: 16741404 | J65: 20402305 | K65: 26319099 | L65: 26267774 | M65: 15419352 | N65: 22987894 | O65: 29269248 | P65: 21115120
A66: =VLOOKUP(B66,'PORTFOLIO RAW'!B:B,1,FALSE) -> 916860 | B66: 916860 | C66: HUMANA INC. - MARKET CAPITALIZATION | D66: 916860(WC08001) | E66: 12804082 | F66: 6293813 | G66: 7469202 | H66: 9220936 | I66: 14368418 | J66: 10866316 | K66: 15899019 | L66: 21487624 | M66: 26470894 | N66: 30462739 | O66: 34153954 | P66: 38837140
A67: =VLOOKUP(B67,'PORTFOLIO RAW'!B:B,1,FALSE) -> 921268 | B67: 921268 | C67: ECOLAB INC - MARKET CAPITALIZATION | D67: 921268(WC08001) | E67: 12639913 | F67: 8301711 | G67: 10547394 | H67: 11723293 | I67: 16879043 | J67: 21190514 | K67: 31395697 | L67: 31345548 | M67: 33856480 | N67: 34204796 | O67: 38818274 | P67: 42392595
A68: =VLOOKUP(B68,'PORTFOLIO RAW'!B:B,1,FALSE) -> 31604H | B68: 31604H | C68: AMERIPRISE FIN - MARKET CAPITALIZATION | D68: 31604H(WC08001) | E68: 12551184 | F68: 5057440 | G68: 9902982 | H68: 14197464 | I68: 11017250 | J68: 12772950 | K68: 22103211 | L68: 24216233 | M68: 18201360 | N68: 17169064 | O68: 24850177 | P68: 14228840
A69: =VLOOKUP(B69,'PORTFOLIO RAW'!B:B,1,FALSE) -> 905792 | B69: 905792 | C69: PUBLIC STORAGE, INC - MARKET CAPITALIZATION | D69: 905792(WC08001) | E69: 12437304 | F69: 13378239 | G69: 13716631 | H69: 17165621 | I69: 22890310 | J69: 24844446 | K69: 25855767 | L69: 31876561 | M69: 42832591 | N69: 38730044 | O69: 36335354 | P69: 35245832
A70: =VLOOKUP(B70,'PORTFOLIO RAW'!B:B,1,FALSE) -> 921855 | B70: 921855 | C70: TJX COMPANIES INC - MARKET CAPITALIZATION | D70: 921855(WC08001) | E70: 12294990 | F70: 8491740 | G70: 14963063 | H70: 17296889 | I70: 24099808 | J70: 30729640 | K70: 44930723 | L70: 46959003 | M70: 47048481 | N70: 48557950 | O70: 48017570 | P70: 54456745
A71: =VLOOKUP(B71,'PORTFOLIO RAW'!B:B,1,FALSE) -> 670942 | B71: 670942 | C71: AMEREN CORPORATION - MARKET CAPITALIZATION | D71: 670942(WC08001) | E71: 11291943 | F71: 7061098 | G71: 6635330 | H71: 6776876 | I71: 8037338 | J71: 7452672 | K71: 8772416 | L71: 11191138 | M71: 10487598 | N71: 12726796 | O71: 14310974 | P71: 15948735
A72: =VLOOKUP(B72,'PORTFOLIO RAW'!B:B,1,FALSE) -> 902233 | B72: 902233 | C72: ROCKWELL AUTOMATION - MARKET CAPITALIZATION | D72: 902233(WC08001) | E72: 10302624 | F72: 4616768 | G72: 6675858 | H72: 10161307 | I72: 10411203 | J72: 11741802 | K72: 16412424 | L72: 15201040 | M72: 13585564 | N72: 17270400 | O72: 25211340 | P72: 18223128
A73: =VLOOKUP(B73,'PORTFOLIO RAW'!B:B,1,FALSE) -> 916125 | B73: 916125 | C73: CLOROX CO - MARKET CAPITALIZATION | D73: 916125(WC08001) | E73: 9857383 | F73: 7669394 | G73: 8488637 | H73: 8781018 | I73: 8723810 | J73: 9486536 | K73: 12092835 | L73: 13421855 | M73: 16312153 | N73: 15525219 | O73: 19189568 | P73: 19727264
A74: =VLOOKUP(B74,'PORTFOLIO RAW'!B:B,1,FALSE) -> 329534 | B74: 329534 | C74: EQUITY RESIDENTIAL - MARKET CAPITALIZATION | D74: 329534(WC08001) | E74: 9830658 | F74: 8134501 | G74: 9457017 | H74: 15075747 | I74: 16966892 | J74: 18420847 | K74: 18698059 | L74: 26067536 | M74: 29760397 | N74: 23547453 | O74: 23468513 | P74: 24384435
A75: =VLOOKUP(B75,'PORTFOLIO RAW'!B:B,1,FALSE) -> 905010 | B75: 905010 | C75: XCEL ENERGY INC - MARKET CAPITALIZATION | D75: 905010(WC08001) | E75: 9677626 | F75: 8417837 | G75: 9708347 | H75: 11358960 | I75: 13446692 | J75: 13033399 | K75: 13913324 | L75: 18165939 | M75: 18225601 | N75: 20643968 | O75: 24428472 | P75: 25326592
A76: =VLOOKUP(B76,'PORTFOLIO RAW'!B:B,1,FALSE) -> 683118 | B76: 683118 | C76: MOODY'S CORP - MARKET CAPITALIZATION | D76: 683118(WC08001) | E76: 8974980 | F76: 4724058 | G76: 6347779 | H76: 6125052 | I76: 7491781 | J76: 11234042 | K76: 16789492 | L76: 19580033 | M76: 19674218 | N76: 17976727 | O76: 28189099 | P76: 26790153
A77: =VLOOKUP(B77,'PORTFOLIO RAW'!B:B,1,FALSE) -> 912588 | B77: 912588 | C77: HOST HOTELS - MARKET CAPITALIZATION | D77: 912588(WC08001) | E77: 8905104 | F77: 3976521 | G77: 7542321 | H77: 12072972 | I77: 10414327 | J77: 11354482 | K77: 14673312 | L77: 17965366 | M77: 11509602 | N77: 13900152 | O77: 14671135 | P77: 12342468
A78: =VLOOKUP(B78,'PORTFOLIO RAW'!B:B,1,FALSE) -> 152533 | B78: 152533 | C78: LAB CORP OF AMERICA - MARKET CAPITALIZATION | D78: 152533(WC08001) | E78: 8383830 | F78: 6969162 | G78: 7880652 | H78: 9003008 | I78: 8407866 | J78: 8098970 | K78: 7830409 | L78: 9128340 | M78: 12524732 | N78: 13184626 | O78: 16254069 | P78: 12497004
A79: =VLOOKUP(B79,'PORTFOLIO RAW'!B:B,1,FALSE) -> 906560 | B79: 906560 | C79: NORDSTROM, INC. - MARKET CAPITALIZATION | D79: 906560(WC08001) | E79: 8117330 | F79: 2866974 | G79: 8181166 | H79: 9238840 | I79: 10319796 | J79: 10539500 | K79: 11816160 | L79: 15092039 | M79: 8642035 | N79: 8148100 | O79: 7912460 | P79: 7345736
A80: =VLOOKUP(B80,'PORTFOLIO RAW'!B:B,1,FALSE) -> 905624 | B80: 905624 | C80: MASCO CORP - MARKET CAPITALIZATION | D80: 905624(WC08001) | E80: 7755829 | F80: 3911082 | G80: 4839024 | H80: 4413276 | I80: 3645992 | J80: 5814340 | K80: 7958115 | L80: 8694000 | M80: 9353150 | N80: 10055160 | O80: 13638976 | P80: 8593636
... A85: =VLOOKUP(B85,'PORTFOLIO RAW'!B:B,1,FALSE) -> 906643 | B85: 906643 | C85: TYSON FOODS, INC. - MARKET CAPITALIZATION | D85: 906643(WC08001) | E85: 5788608 | F85: 3302520 | G85: 4613520 | H85: 6491940 | I85: 7636800 | J85: 6964600 | K85: 11510240 | L85: 15073840 | M85: 19678770 | N85: 22266480 | O85: 29833760 | P85: 19544400
A86: =VLOOKUP(B86,'PORTFOLIO RAW'!B:B,1,FALSE) -> 13967H | B86: 13967H | C86: WILLIS TOWERS WAT - MARKET CAPITALIZATION | D86: 13967H(WC08001) | E86: 5433261 | F86: 4148930 | G86: 4447849 | H86: 5916101 | I86: 6742791 | J86: 5805342 | K86: 8012693 | L86: 8005534 | M86: 8827157 | N86: 16664227 | O86: 19909474 | P86: 19575363
A87: =VLOOKUP(B87,'PORTFOLIO RAW'!B:B,1,FALSE) -> 936365 | B87: 936365 | C87: ADVANCED MICRO - MARKET CAPITALIZATION | D87: 936365(WC08001) | E87: 4545000 | F87: 1315440 | G87: 6495280 | H87: 5586940 | I87: 3763800 | J87: 1711200 | K87: 2805750 | L87: 2071920 | M87: 2273040 | N87: 10602900 | O87: 9940760 | P87: 18552300
A88: =VLOOKUP(B88,'PORTFOLIO RAW'!B:B,1,FALSE) -> 906979 | B88: 906979 | C88: ALLIANT ENERGY CORP - MARKET CAPITALIZATION | D88: 906979(WC08001) | E88: 4490520 | F88: 3222905 | G88: 3348466 | H88: 4077569 | I88: 4897040 | J88: 4873457 | K88: 5724693 | L88: 7368348 | M88: 7085528 | N88: 8626555 | O88: 9857766 | P88: 9973674
A89: =VLOOKUP(B89,'PORTFOLIO RAW'!B:B,1,FALSE) -> 28513N | B89: 28513N | C89: CBRE GROUP - MARKET CAPITALIZATION | D89: 28513N(WC08001) | E89: 4344363 | F89: 1133292 | G89: 4366384 | H89: 6627224 | I89: 4991736 | J89: 6568636 | K89: 8729684 | L89: 11404943 | M89: 11557691 | N89: 10620930 | O89: 14701975 | P89: 13489988
A90: =VLOOKUP(B90,'PORTFOLIO RAW'!B:B,1,FALSE) -> 877723 | B90: 877723 | C90: CARMAX INC - MARKET CAPITALIZATION | D90: 877723(WC08001) | E90: 4266556 | F90: 1722695 | G90: 5344506 | H90: 7111329 | I90: 6884996 | J90: 8526035 | K90: 10622105 | L90: 14759853 | M90: 11272697 | N90: 12537521 | O90: 11963362 | P90: 11275585
A91: =VLOOKUP(B91,'PORTFOLIO RAW'!B:B,1,FALSE) -> 902607 | B91: 902607 | C91: PINNACLE WEST CAPTL - MARKET CAPITALIZATION | D91: 902607(WC08001) | E91: 4261610 | F91: 3241551 | G91: 3710492 | H91: 4508502 | I91: 5263463 | J91: 5594686 | K91: 5830819 | L91: 7553130 | M91: 7156014 | N91: 8687606 | O91: 9519010 | P91: 9551070
A92: =VLOOKUP(B92,'PORTFOLIO RAW'!B:B,1,FALSE) -> 755148 | B92: 755148 | C92: CADENCE DESIGN SYST - MARKET CAPITALIZATION | D92: 755148(WC08001) | E92: 4139060 | F92: 767418 | G92: 1609208 | H92: 2206378 | I92: 2835872 | J92: 3791500 | K92: 4039625 | L92: 5531348 | M92: 6067863 | N92: 7013657 | O92: 11796042 | P92: 12175052
A93: =VLOOKUP(B93,'PORTFOLIO RAW'!B:B,1,FALSE) -> 130298 | B93: 130298 | C93: ALBEMARLE CORP - MARKET CAPITALIZATION | D93: 130298(WC08001) | E93: 3907778 | F93: 2028854 | G93: 3328182 | H93: 5109112 | I93: 4576212 | J93: 5522406 | K93: 5074560 | L93: 4692004 | M93: 6285386 | N93: 9686066 | O93: 14137856 | P93: 8139825
A94: =VLOOKUP(B94,'PORTFOLIO RAW'!B:B,1,FALSE) -> 513260 | B94: 513260 | C94: DUKE REALTY CORP - MARKET CAPITALIZATION | D94: 513260(WC08001) | E94: 3812244 | F94: 1626683 | G94: 2726433 | H94: 3142350 | I94: 3047770 | J94: 3875597 | K94: 4909041 | L94: 6951062 | M94: 7257891 | N94: 9422319 | O94: 9696583 | P94: 9294241
A95: =VLOOKUP(B95,'PORTFOLIO RAW'!B:B,1,FALSE) -> 923036 | B95: 923036 | C95: SEALED AIR CORP - MARKET CAPITALIZATION | D95: 923036(WC08001) | E95: 3740049 | F95: 2358765 | G95: 3474388 | H95: 4054325 | I95: 3305390 | J95: 3406705 | K95: 6680565 | L95: 8932868 | M95: 8742193 | N95: 8772491 | O95: 8311759 | P95: 5422998
A96: =VLOOKUP(B96,'PORTFOLIO RAW'!B:B,1,FALSE) -> 912030 | B96: 912030 | C96: HASBRO INC - MARKET CAPITALIZATION | D96: 912030(WC08001) | E96: 3714395 | F96: 4061322 | G96: 4395346 | H96: 6483292 | I96: 4102115 | J96: 4628954 | K96: 7209303 | L96: 6847693 | M96: 8406220 | N96: 9683840 | O96: 11311234 | P96: 10247984
A97: =VLOOKUP(B97,'PORTFOLIO RAW'!B:B,1,FALSE) -> 912157 | B97: 912157 | C97: PERKINELMER INC - MARKET CAPITALIZATION | D97: 912157(WC08001) | E97: 3059562 | F97: 1629028 | G97: 2409504 | H97: 2987761 | I97: 2263140 | J97: 3651243 | K97: 4643570 | L97: 4918794 | M97: 6001661 | N97: 5716527 | O97: 8069596 | P97: 8687394
A98: =VLOOKUP(B98,'PORTFOLIO RAW'!B:B,1,FALSE) -> 312367 | B98: 312367 | C98: ACTIVISION BLIZZARD - MARKET CAPITALIZATION | D98: 312367(WC08001) | E98: NA | F98: 11225706 | G98: 13892290 | H98: 14720499 | I98: 13963382 | J98: 11805257 | K98: 12547131 | L98: 14546879 | M98: 28432598 | N98: 26919521 | O98: 47965229 | P98: 35552354
A99: =VLOOKUP(B99,'PORTFOLIO RAW'!B:B,1,FALSE) -> 31196R | B99: 31196R | C99: DISCOVERY INC - MARKET CAPITALIZATION | D99: 31196R(WC08001) | E99: NA | F99: 3993120 | G99: 8710280 | H99: 11842800 | I99: 10693170 | J99: 15571644 | K99: 21266784 | L99: 15120105 | M99: 11152240 | N99: 10689900 | O99: 8504400 | P99: 12889540
A100: =VLOOKUP(B100,'PORTFOLIO RAW'!B:B,1,FALSE) -> 749688 | B100: 749688 | C100: HCA HEALTHCARE - MARKET CAPITALIZATION | D100: 749688(WC08001) | E100: NA | F100: NA | G100: NA | H100: NA | I100: 9637638 | J100: 13371350 | K100: 20973507 | L100: 30858873 | M100: 26966698 | N100: 27427067 | O100: 30752046 | P100: 42673308
A101: =VLOOKUP(B101,'PORTFOLIO RAW'!B:B,1,FALSE) -> 905039 | B101: 905039 | C101: EXXON MOBIL CORP - MARKET CAPITALIZATION | D101: 905039(WC08001) | E101: 504239580 | F101: 397234080 | G101: 322334130 | H101: 364064480 | I101: 401253840 | J101: 389648100 | K101: 438702000 | L101: 388382450 | M101: 323960200 | N101: 374398480 | O101: 354549960 | P101: 288921030
A102: =VLOOKUP(B102,'PORTFOLIO RAW'!B:B,1,FALSE) -> 906150 | B102: 906150 | C102: GENERAL ELECTRIC CO. - MARKET CAPITALIZATION | D102: 906150(WC08001) | E102: 370240295 | F102: 170697731 | G102: 161332325 | H102: 194155227 | I102: 189362734 | J102: 218414069 | K102: 282006494 | L102: 254149993 | M102: 292164821 | N102: 276266602 | O102: 151475964 | P102: 65875858
A103: =VLOOKUP(B103,'PORTFOLIO RAW'!B:B,1,FALSE) -> 719643 | B103: 719643 | C103: MICROSOFT CORP - MARKET CAPITALIZATION | D103: 719643(WC08001) | E103: 333928000 | F103: 177895440 | G103: 271515840 | H103: 241923880 | I103: 217440960 | J103: 223853996 | K103: 311550480 | L103: 382701550 | M103: 445337960 | N103: 485189120 | O103: 659342320 | P103: 779752890
A104: =VLOOKUP(B104,'PORTFOLIO RAW'!B:B,1,FALSE) -> 945388 | B104: 945388 | C104: AT&T INC - MARKET CAPITALIZATION | D104: 945388(WC08001) | E104: 251169741 | F104: 167950500 | G104: 165431123 | H104: 173667732 | I104: 179217719 | J104: 188148817 | K104: 183757277 | L104: 174228406 | M104: 211447380 | N104: 261091413 | O104: 238700826 | P104: 207817678
A105: =VLOOKUP(B105,'PORTFOLIO RAW'!B:B,1,FALSE) -> 874227 | B105: 874227 | C105: BERKSHIRE HATHAWAY - MARKET CAPITALIZATION | D105: 874227(WC08001) | E105: 219153329 | F105: 149655232 | G105: 153933501 | H105: 198516054 | I105: 189438243 | J105: 220253207 | K105: 292459417 | L105: 371297434 | M105: 325063135 | N105: 401413287 | O105: 489506186 | P105: 502124274
A106: =VLOOKUP(B106,'PORTFOLIO RAW'!B:B,1,FALSE) -> 29026M | B106: 29026M | C106: ALPHABET INC - MARKET CAPITALIZATION | D106: 29026M(WC08001) | E106: 216624898 | F106: 96952970 | G106: 197012316 | H106: 190843426 | I106: 209849527 | J106: 233420372 | K106: 376370608 | L106: 360940074 | M106: 534763617 | N106: 547815138 | O106: 731884412 | P106: 726828198
A107: =VLOOKUP(B107,'PORTFOLIO RAW'!B:B,1,FALSE) -> 905024 | B107: 905024 | C107: CHEVRON CORPORATION - MARKET CAPITALIZATION | D107: 905024(WC08001) | E107: 195100202 | F107: 148253025 | G107: 154574502 | H107: 183182621 | I107: 210796161 | J107: 210515910 | K107: 239028159 | L107: 210859003 | M107: 169377947 | N107: 222630306 | O107: 238449629 | P107: 207009712
A108: =VLOOKUP(B108,'PORTFOLIO RAW'!B:B,1,FALSE) -> 912212 | B108: 912212 | C108: JOHNSON & JOHNSON - MARKET CAPITALIZATION | D108: 912212(WC08001) | E108: 189442874 | F108: 165679920 | G108: 177405816 | H108: 169351299 | I108: 178663726 | J108: 194772079 | K108: 258341319 | L108: 291041629 | M108: 283010241 | N108: 311817132 | O108: 374802393 | P108: 343572912
A109: =VLOOKUP(B109,'PORTFOLIO RAW'!B:B,1,FALSE) -> 916548 | B109: 916548 | C109: WALMART INC - MARKET CAPITALIZATION | D109: 916548(WC08001) | E109: 188836690 | F109: 220035500 | G109: 202361700 | H109: 189617880 | I109: 204259680 | J109: 226114220 | K109: 254404770 | L109: 277220640 | M109: 193830600 | N109: 210677760 | O109: 291510000 | P109: 268085700
A110: =VLOOKUP(B110,'PORTFOLIO RAW'!B:B,1,FALSE) -> 923937 | B110: 923937 | C110: BANK OF AMERICA CORP - MARKET CAPITALIZATION | D110: 923937(WC08001) | E110: 183107152 | F110: 70647517 | G110: 130272674 | H110: 134535965 | I110: 58579815 | J110: 125135641 | K110: 164914455 | L110: 188140945 | M110: 174699861 | N110: 222163026 | O110: 303681168 | P110: 238251216
A111: =VLOOKUP(B111,'PORTFOLIO RAW'!B:B,1,FALSE) -> 992816 | B111: 992816 | C111: APPLE INC - MARKET CAPITALIZATION | D111: 992816(WC08001) | E111: 172790923 | F111: 75818622 | G111: 189617813 | H111: 295455299 | I111: 376357166 | J111: 499821045 | K111: 504476450 | L111: 647506851 | M111: 587219541 | N111: 618034746 | O111: 867506995 | P111: 750051492
A112: =VLOOKUP(B112,'PORTFOLIO RAW'!B:B,1,FALSE) -> 904853 | B112: 904853 | C112: ALTRIA GROUP INC - MARKET CAPITALIZATION | D112: 904853(WC08001) | E112: 159298210 | F112: 31044256 | G112: 40752442 | H112: 51424771 | I112: 60617032 | J112: 63186235 | K112: 76529670 | L112: 97134550 | M112: 114095062 | N112: 131404068 | O112: 135768919 | P112: 92559705
A113: =VLOOKUP(B113,'PORTFOLIO RAW'!B:B,1,FALSE) -> 904030 | B113: 904030 | C113: PFIZER INC - MARKET CAPITALIZATION | D113: 904030(WC08001) | E113: 153677530 | F113: 119471660 | G113: 146793300 | H113: 140290120 | I113: 163923000 | J113: 182476987 | K113: 196001370 | L113: 195964650 | M113: 199329000 | N113: 197153600 | O113: 216559380 | P113: 249547050
A114: =VLOOKUP(B114,'PORTFOLIO RAW'!B:B,1,FALSE) -> 916305 | B114: 916305 | C114: AMERICAN INT'L GROUP - MARKET CAPITALIZATION | D114: 916305(WC08001) | E114: 147474750 | F114: 4222780 | G114: 4049426 | H114: 8093487 | I114: 44006258 | J114: 52114164 | K114: 74740433 | L114: 77065670 | M114: 73987013 | N114: 65005384 | O114: 53565081 | P114: 34153078
A115: =VLOOKUP(B115,'PORTFOLIO RAW'!B:B,1,FALSE) -> 741344 | B115: 741344 | C115: CITIGROUP INC - MARKET CAPITALIZATION | D115: 741344(WC08001) | E115: 147041024 | F115: 36569957 | G115: 94279723 | H115: 137446045 | I115: 76927236 | J115: 119822647 | K115: 157853848 | L115: 163624180 | M115: 152832174 | N115: 164763248 | O115: 191226895 | P115: 123302410
A116: =VLOOKUP(B116,'PORTFOLIO RAW'!B:B,1,FALSE) -> 901666 | B116: 901666 | C116: CONOCOPHILLIPS - MARKET CAPITALIZATION | D116: 901666(WC08001) | E116: 142502220 | F116: 78783555 | G116: 77881686 | H116: 99947356 | I116: 93686770 | J116: 70748802 | K116: 86612607 | L116: 85037217 | M116: 57708640 | N116: 62036685 | O116: 64611411 | P116: 70976074
A117: =VLOOKUP(B117,'PORTFOLIO RAW'!B:B,1,FALSE) -> 904282 | B117: 904282 | C117: COCA-COLA - MARKET CAPITALIZATION | D117: 904282(WC08001) | E117: 142255660 | F117: 104664240 | G117: 131271000 | H117: 150744840 | I117: 158342110 | J117: 162001250 | K117: 181846620 | L117: 184332520 | M117: 185759040 | N117: 177780480 | O117: 195402920 | P117: 202089800
A118: =VLOOKUP(B118,'PORTFOLIO RAW'!B:B,1,FALSE) -> 905277 | B118: 905277 | C118: HP INC - MARKET CAPITALIZATION | D118: 905277(WC08001) | E118: 130223963 | F118: 87651346 | G118: 121821150 | H118: 92784106 | I118: 51275435 | J118: 27970442 | K118: 53382566 | L118: 73810627 | M118: 21356033 | N118: 25407430 | O118: 34657676 | P118: 31923124
... A133: =VLOOKUP(B133,'PORTFOLIO RAW'!B:B,1,FALSE) -> 951046 | B133: 951046 | C133: U. S. BANCORP - MARKET CAPITALIZATION | D133: 951046(WC08001) | E133: 54842180 | F133: 43892550 | G133: 43061630 | H133: 51806765 | I133: 51660678 | J133: 59709643 | K133: 73719838 | L133: 80274709 | M133: 74467297 | N133: 87170378 | O133: 88709486 | P133: 73500897
A134: =VLOOKUP(B134,'PORTFOLIO RAW'!B:B,1,FALSE) -> 13967E | B134: 13967E | C134: MONDELEZ - MARKET CAPITALIZATION | D134: 13967E(WC08001) | E134: 50047164 | F134: 39450744 | G134: 40168912 | H134: 55081577 | I134: 66048620 | J134: 45255684 | K134: 60200500 | L134: 60431759 | M134: 70848687 | N134: 67752444 | O134: 63692224 | P134: 58083524
A135: =VLOOKUP(B135,'PORTFOLIO RAW'!B:B,1,FALSE) -> 14737P | B135: 14737P | C135: ANTHEM INC - MARKET CAPITALIZATION | D135: 14737P(WC08001) | E135: 48796482 | F135: 21201104 | G135: 26218240 | H135: 21478122 | I135: 22483440 | J135: 18563247 | K135: 27095569 | L135: 33693375 | M135: 36427053 | N135: 37918963 | O135: 57621666 | P135: 67599800
A136: =VLOOKUP(B136,'PORTFOLIO RAW'!B:B,1,FALSE) -> 906191 | B136: 906191 | C136: HONEYWELL INTERNATNL - MARKET CAPITALIZATION | D136: 906191(WC08001) | E136: 45965321 | F136: 24116466 | G136: 29957004 | H136: 41624280 | I136: 42104945 | J136: 49684316 | K136: 71615806 | L136: 78157424 | M136: 79790328 | N136: 88138680 | O136: 115158024 | P136: 96394752
A137: =VLOOKUP(B137,'PORTFOLIO RAW'!B:B,1,FALSE) -> 286738 | B137: 286738 | C137: METLIFE INC - MARKET CAPITALIZATION | D137: 286738(WC08001) | E137: 44934748 | F137: 27664594 | G137: 28945775 | H137: 43810633 | I137: 32987100 | J137: 35960161 | K137: 60499865 | L137: 61225980 | M137: 52935955 | N137: 59037519 | O137: 52763829 | P137: 39360672
A138: =VLOOKUP(B138,'PORTFOLIO RAW'!B:B,1,FALSE) -> 687609 | B138: 687609 | C138: EBAY INC. - MARKET CAPITALIZATION | D138: 687609(WC08001) | E138: 44813769 | F138: 17897069 | G138: 30537210 | H138: 36115269 | I138: 39019151 | J138: 65991024 | K138: 70995310 | L138: 68690880 | M138: 32536320 | N138: 32273030 | O138: 38834460 | P138: 25684050
A139: =VLOOKUP(B139,'PORTFOLIO RAW'!B:B,1,FALSE) -> 905115 | B139: 905115 | C139: EMERSON ELECTRIC CO. - MARKET CAPITALIZATION | D139: 905115(WC08001) | E139: 44672675 | F139: 28234219 | G139: 32029784 | H139: 43031333 | I139: 34424315 | J139: 38349040 | K139: 49593417 | L139: 43001440 | M139: 31309926 | N139: 35835904 | O139: 44719513 | P139: 37594700
A140: =VLOOKUP(B140,'PORTFOLIO RAW'!B:B,1,FALSE) -> 907652 | B140: 907652 | C140: GENERAL DYNAMICS - MARKET CAPITALIZATION | D140: 907652(WC08001) | E140: 42882558 | F140: 27751506 | G140: 26293489 | H140: 26400832 | I140: 23671040 | J140: 24499015 | K140: 33767637 | L140: 45712423 | M140: 42991932 | N140: 52215583 | O140: 60403411 | P140: 45386236
A141: =VLOOKUP(B141,'PORTFOLIO RAW'!B:B,1,FALSE) -> 14861V | B141: 14861V | C141: PRUDENTIAL FINANCIAL - MARKET CAPITALIZATION | D141: 14861V(WC08001) | E141: 41809092 | F141: 12809660 | G141: 23094171 | H141: 28521245 | I141: 23558337 | J141: 24800229 | K141: 42702955 | L141: 41325156 | M141: 36398522 | N141: 44701488 | O141: 48585054 | P141: 33493600
...

Sheet NI
A1: Net Income
B2: Code | C2: Name | D2: Code | E2: 2007 | F2: 2008 | G2: 2009 | H2: 2010 | I2: 2011 | J2: 2012 | K2: 2013 | L2: 2014 | M2: 2015 | N2: 2016 | O2: 2017
A3: =VLOOKUP(B3,'PORTFOLIO RAW'!B:B,1,FALSE) -> 902172 | B3: 902172 | C3: 3M COMPANY - NET INCOME - BASIC | D3: 902172(WC01706) | E3: 4096000 | F3: 3460000 | G3: 3193000 | H3: 4085000 | I3: 4283000 | J3: 4444000 | K3: 4659000 | L3: 4956000 | M3: 4833000 | N3: 5050000 | O3: 5620000
A4: =VLOOKUP(B4,'PORTFOLIO RAW'!B:B,1,FALSE) -> 916328 | B4: 916328 | C4: ABBOTT LABORATORIES - NET INCOME - BASIC | D4: 916328(WC01706) | E4: 3606314 | F4: 4734216 | G4: 5745838 | H4: 4626172 | I4: 4728449 | J4: 5962920 | K4: 2576000 | L4: 2284000 | M4: 2671000 | N4: 1384000 | O4: 1937000
A5: =VLOOKUP(B5,'PORTFOLIO RAW'!B:B,1,FALSE) -> 14352P | B5: 14352P | C5: ACCENTURE PLC - NET INCOME - BASIC | D5: 14352P(WC01706) | E5: 1243148 | F5: 1691751 | G5: 1589963 | H5: 1780656 | I5: 2277677 | J5: 2553510 | K5: 3281878 | L5: 2941498 | M5: 3053581 | N5: 4111892 | O5: 3445149
A6: =VLOOKUP(B6,'PORTFOLIO RAW'!B:B,1,FALSE) -> 312367 | B6: 312367 | C6: ACTIVISION BLIZZARD - NET INCOME - BASIC | D6: 312367(WC01706) | E6: 227000 | F6: -107000 | G6: 113000 | H6: 414000 | I6: 1069000 | J6: 1125000 | K6: 998000 | L6: 847000 | M6: 881000 | N6: 962000 | O6: 909000
A7: =VLOOKUP(B7,'PORTFOLIO RAW'!B:B,1,FALSE) -> 749382 | B7: 749382 | C7: ADOBE INC - NET INCOME - BASIC | D7: 749382(WC01706) | E7: 723807 | F7: 871814 | G7: 386508 | H7: 774680 | I7: 832847 | J7: 832775 | K7: 289985 | L7: 268395 | M7: 629551 | N7: 1168782 | O7: 1693954
A8: =VLOOKUP(B8,'PORTFOLIO RAW'!B:B,1,FALSE) -> 14806F | B8: 14806F | C8: ADVANCE AUTO PARTS - NET INCOME - BASIC | D8: 14806F(WC01706) | E8: 238317 | F8: 238038 | G8: 270373 | H8: 344501 | I8: 393627 | J8: 386800 | K8: 390863 | L8: 492270 | M8: 471745 | N8: 457677 | O8: 331705
A9: =VLOOKUP(B9,'PORTFOLIO RAW'!B:B,1,FALSE) -> 936365 | B9: 936365 | C9: ADVANCED MICRO - NET INCOME - BASIC | D9: 936365(WC01706) | E9: -3379000 | F9: -3098000 | G9: 304000 | H9: 471000 | I9: 491000 | J9: -1183000 | K9: -83000 | L9: -403000 | M9: -660000 | N9: -497000 | O9: -1087000
A10: =VLOOKUP(B10,'PORTFOLIO RAW'!B:B,1,FALSE) -> 545101 | B10: 545101 | C10: AES CORP - NET INCOME - BASIC | D10: 545101(WC01706) | E10: 495000 | F10: 1228000 | G10: 808000 | H10: -55000 | I10: -28000 | J10: -928000 | K10: 266000 | L10: 825000 | M10: 306000 | N10: -11000 | O10: -511000
A11: =VLOOKUP(B11,'PORTFOLIO RAW'!B:B,1,FALSE) -> 933185 | B11: 933185 | C11: AFLAC INCORPORATED - NET INCOME - BASIC | D11: 933185(WC01706) | E11: 1634000 | F11: 1254000 | G11: 1497000 | H11: 2344000 | I11: 1964000 | J11: 2866000 | K11: 3158000 | L11: 2951000 | M11: 2533000 | N11: 2659000 | O11: 2671000
A12: =VLOOKUP(B12,'PORTFOLIO RAW'!B:B,1,FALSE) -> 277642 | B12: 277642 | C12: AGILENT TECHNOLOGIES - NET INCOME - BASIC | D12: 277642(WC01706) | E12: 638000 | F12: 693000 | G12: -31000 | H12: 684000 | I12: 1012000 | J12: 1153000 | K12: 724000 | L12: 504000 | M12: 401000 | N12: 462000 | O12: 684000
A13: =VLOOKUP(B13,'PORTFOLIO RAW'!B:B,1,FALSE) -> 905271 | B13: 905271 | C13: AIR PRODUCTS & CHEMS - NET INCOME - BASIC | D13: 905271(WC01706) | E13: 1042700 | F13: 1090500 | G13: 631400 | H13: 1029100 | I13: 1224200 | J13: 1046500 | K13: 994200 | L13: 991700 | M13: 1277900 | N13: 631100 | O13: 1219900
A14: =VLOOKUP(B14,'PORTFOLIO RAW'!B:B,1,FALSE) -> 277355 | B14: 277355 | C14: AKAMAI TECHNOLOGIES - NET INCOME - BASIC | D14: 277355(WC01706) | E14: 100967 | F14: 145138 | G14: 145913 | H14: 171220 | I14: 200904 | J14: 203989 | K14: 293487 | L14: 333948 | M14: 321406 | N14: 316132 | O14: 244321
A15: =VLOOKUP(B15,'PORTFOLIO RAW'!B:B,1,FALSE) -> 130298 | B15: 130298 | C15: ALBEMARLE CORP - NET INCOME - BASIC | D15: 130298(WC01706) | E15: 229690 | F15: 194202 | G15: 178368 | H15: 323720 | I15: 436280 | J15: 311536 | K15: 413171 | L15: 133316 | M15: 334906 | N15: 643675 | O15: 474350
A16: =VLOOKUP(B16,'PORTFOLIO RAW'!B:B,1,FALSE) -> 325596 | B16: 325596 | C16: ALLERGAN PLC - NET INCOME - BASIC | D16: 325596(WC01706) | E16: 141030 | F16: 238379 | G16: 222000 | H16: 184400 | I16: 260900 | J16: 97300 | K16: -750400 | L16: -1630500 | M16: 3683200 | N16: 14695000 | O16: -7203900
A17: =VLOOKUP(B17,'PORTFOLIO RAW'!B:B,1,FALSE) -> 906979 | B17: 906979 | C17: ALLIANT ENERGY CORP - NET INCOME - BASIC | D17: 906979(WC01706) | E17: 424700 | F17: 288000 | G17: 111000 | H17: 287600 | I17: 303600 | J17: 319800 | K17: 358300 | L17: 383100 | M17: 378200 | N17: 371500 | O17: 439200
A18: =VLOOKUP(B18,'PORTFOLIO RAW'!B:B,1,FALSE) -> 322677 | B18: 322677 | C18: ALLSTATE CORP - NET INCOME - BASIC | D18: 322677(WC01706) | E18: 4636000 | F18: -1679000 | G18: 854000 | H18: 928000 | I18: 788000 | J18: 2306000 | K18: 2263000 | L18: 2746000 | M18: 2055000 | N18: 1761000 | O18: 2567000
A19: =VLOOKUP(B19,'PORTFOLIO RAW'!B:B,1,FALSE) -> 29026M | B19: 29026M | C19: ALPHABET INC - NET INCOME - BASIC | D19: 29026M(WC01706) | E19: 4203720 | F19: 4226858 | G19: 6520448 | H19: 8505000 | I19: 9737000 | J19: 10737000 | K19: 12920000 | L19: 14444000 | M19: 15826000 | N19: 19478000 | O19: 22486000
A20: =VLOOKUP(B20,'PORTFOLIO RAW'!B:B,1,FALSE) -> 904853 | B20: 904853 | C20: ALTRIA GROUP INC - NET INCOME - BASIC | D20: 904853(WC01706) | E20: 9786000 | F20: 3090000 | G20: 3206000 | H20: 3890000 | I20: 3377000 | J20: 4167000 | K20: 4523000 | L20: 5058000 | M20: 5231000 | N20: 14215000 | O20: 6841000
A21: =VLOOKUP(B21,'PORTFOLIO RAW'!B:B,1,FALSE) -> 891399 | B21: 891399 | C21: AMAZON.COM INC - NET INCOME - BASIC | D21: 891399(WC01706) | E21: 476000 | F21: 645000 | G21: 902000 | H21: 1152000 | I21: 631000 | J21: -39000 | K21: 274000 | L21: -241000 | M21: 596000 | N21: 2371000 | O21: 2244000
A22: =VLOOKUP(B22,'PORTFOLIO RAW'!B:B,1,FALSE) -> 670942 | B22: 670942 | C22: AMEREN CORPORATION - NET INCOME - BASIC | D22: 670942(WC01706) | E22: 618000 | F22: 607000 | G22: 612000 | H22: 139000 | I22: 519000 | J22: -974000 | K22: 289000 | L22: 586000 | M22: 630000 | N22: 653000 | O22: 677000
A23: =VLOOKUP(B23,'PORTFOLIO RAW'!B:B,1,FALSE) -> 905425 | B23: 905425 | C23: AMERICAN ELECTRIC - NET INCOME - BASIC | D23: 905425(WC01706) | E23: 1144000 | F23: 1380000 | G23: 1362000 | H23: 1211000 | I23: 1568000 | J23: 1259000 | K23: 1480000 | L23: 1634000 | M23: 2047100 | N23: 610900 | O23: 1885900
A24: =VLOOKUP(B24,'PORTFOLIO RAW'!B:B,1,FALSE) -> 906156 | B24: 906156 | C24: AMERICAN EXPRESS CO - NET INCOME - BASIC | D24: 906156(WC01706) | E24: 4012000 | F24: 2688000 | G24: 1802000 | H24: 4006000 | I24: 4877000 | J24: 4433000 | K24: 5312000 | L24: 5839000 | M24: 5063000 | N24: 5285000 | O24: 5234000
A25: =VLOOKUP(B25,'PORTFOLIO RAW'!B:B,1,FALSE) -> 916305 | B25: 916305 | C25: AMERICAN INT'L GROUP - NET INCOME - BASIC | D25: 916305(WC01706) | E25: 6200000 | F25: -99689000 | G25: -12244000 | H25: 1583000 | I25: 16986000 | J25: 3438000 | K25: 9085000 | L25: 7529000 | M25: 2196000 | N25: -849000 | O25: 616000
A26: =VLOOKUP(B26,'PORTFOLIO RAW'!B:B,1,FALSE) -> 680902 | B26: 680902 | C26: AMERICAN TOWER CORP - NET INCOME - BASIC | D26: 680902(WC01706) | E26: 56316 | F26: 347246 | G26: 246595 | H26: 372936 | I26: 396462 | J26: 637283 | K26: 551333 | L26: 801022 | M26: 594911 | N26: 849300 | O26: 1151500
A27: =VLOOKUP(B27,'PORTFOLIO RAW'!B:B,1,FALSE) -> 31604H | B27: 31604H | C27: AMERIPRISE FIN - NET INCOME - BASIC | D27: 31604H(WC01706) | E27: 814000 | F27: -38000 | G27: 722000 | H27: 1097000 | I27: 1050000 | J27: 1036000 | K27: 1334000 | L27: 1619000 | M27: 1562000 | N27: 1314000 | O27: 1766000
A28: =VLOOKUP(B28,'PORTFOLIO RAW'!B:B,1,FALSE) -> 154680 | B28: 154680 | C28: AMERISOURCEBERGEN - NET INCOME - BASIC | D28: 154680(WC01706) | E28: 493768 | F28: 469064 | G28: 511852 | H28: 636748 | I28: 706624 | J28: 718986 | K28: 433707 | L28: 276484 | M28: -134887 | N28: 1427929 | O28: 364484
A29: =VLOOKUP(B29,'PORTFOLIO RAW'!B:B,1,FALSE) -> 938692 | B29: 938692 | C29: AMGEN INC - NET INCOME - BASIC | D29: 938692(WC01706) | E29: 3166000 | F29: 4196000 | G29: 4605000 | H29: 4627000 | I29: 3683000 | J29: 4345000 | K29: 5081000 | L29: 5158000 | M29: 6939000 | N29: 7722000 | O29: 8079000
A30: =VLOOKUP(B30,'PORTFOLIO RAW'!B:B,1,FALSE) -> 546075 | B30: 546075 | C30: AMPHENOL CORP - NET INCOME - BASIC | D30: 546075(WC01706) | E30: 353194 | F30: 419151 | G30: 317834 | H30: 496405 | I30: 524191 | J30: 555317 | K30: 635672 | L30: 709100 | M30: 763500 | N30: 822900 | O30: 1049000
A31: =VLOOKUP(B31,'PORTFOLIO RAW'!B:B,1,FALSE) -> 905276 | B31: 905276 | C31: ANALOG DEVICES, INC. - NET INCOME - BASIC | D31: 905276(WC01706) | E31: 496907 | F31: 525177 | G31: 247772 | H31: 711225 | I31: 860894 | J31: 651236 | K31: 673487 | L31: 629320 | M31: 696878 | N31: 861664 | O31: 725016
A32: =VLOOKUP(B32,'PORTFOLIO RAW'!B:B,1,FALSE) -> 14737P | B32: 14737P | C32: ANTHEM INC - NET INCOME - BASIC | D32: 14737P(WC01706) | E32: 3345400 | F32: 2490700 | G32: 4745900 | H32: 2887100 | I32: 2646700 | J32: 2655500 | K32: 2489700 | L32: 2569700 | M32: 2560000 | N32: 2469800 | O32: 2734500
A33: =VLOOKUP(B33,'PORTFOLIO RAW'!B:B,1,FALSE) -> 922817 | B33: 922817 | C33: AON PLC - NET INCOME - BASIC | D33: 922817(WC01706) | E33: 864000 | F33: 651000 | G33: 639000 | H33: 733000 | I33: 975000 | J33: 993000 | K33: 1113000 | L33: 1397000 | M33: 1385000 | N33: 1396000 | O33: 1576000
A34: =VLOOKUP(B34,'PORTFOLIO RAW'!B:B,1,FALSE) -> 921983 | B34: 921983 | C34: APACHE CORPORATION - NET INCOME - BASIC | D34: 921983(WC01706) | E34: 2806678 | F34: 706274 | G34: -291692 | H34: 3000000 | I34: 4508000 | J34: 1925000 | K34: 2188000 | L34: -5403000 | M34: -23119000 | N34: -1405000 | O34: 1417000
A35: =VLOOKUP(B35,'PORTFOLIO RAW'!B:B,1,FALSE) -> 992816 | B35: 992816 | C35: APPLE INC - NET INCOME - BASIC | D35: 992816(WC01706) | E35: 3496000 | F35: 4834000 | G35: 8235000 | H35: 14013000 | I35: 25922000 | J35: 41733000 | K35: 37037000 | L35: 39510000 | M35: 53394000 | N35: 45687000 | O35: 48351000
A36: =VLOOKUP(B36,'PORTFOLIO RAW'!B:B,1,FALSE) -> 905296 | B36: 905296 | C36: APPLIED MATERIALS - NET INCOME - BASIC | D36: 905296(WC01706) | E36: 1710196 | F36: 960746 | G36: -305327 | H36: 937866 | I36: 1926000 | J36: 109000 | K36: 256000 | L36: 1072000 | M36: 1377000 | N36: 1721000 | O36: 3434000
A37: =VLOOKUP(B37,'PORTFOLIO RAW'!B:B,1,FALSE) -> 132808 | B37: 132808 | C37: APT INVESTMENT & MGT - NET INCOME - BASIC | D37: 132808(WC01706) | E37: -114070 | F37: 361755 | G37: -114840 | H37: -125318 | I37: -103161 | J37: 82146 | K37: 203673 | L37: 11584 | M37: 55373 | N37: 23991 | O37: -8592
A38: =VLOOKUP(B38,'PORTFOLIO RAW'!B:B,1,FALSE) -> 921093 | B38: 921093 | C38: ARCHER DANIELS MIDL. - NET INCOME - BASIC | D38: 921093(WC01706) | E38: 2162000 | F38: 1802000 | G38: 1707000 | H38: 1930000 | I38: 2036000 | J38: 1146000 | K38: 1342000 | L38: 2248000 | M38: 1849000 | N38: 1279000 | O38: 1216000
A39: =VLOOKUP(B39,'PORTFOLIO RAW'!B:B,1,FALSE) -> 905113 | B39: 905113 | C39: ARCONIC INC - NET INCOME - BASIC | D39: 905113(WC01706) | E39: 2569000 | F39: -76000 | G39: -1153000 | H39: 253000 | I39: 608000 | J39: 189000 | K39: -2287000 | L39: 247000 | M39: -391000 | N39: -1010000 | O39: 145000
A40: =VLOOKUP(B40,'PORTFOLIO RAW'!B:B,1,FALSE) -> 28341F | B40: 28341F | C40: ASSURANT INC - NET INCOME - BASIC | D40: 28341F(WC01706) | E40: 653746 | F40: 447796 | G40: 430574 | H40: 279177 | I40: 545839 | J40: 483705 | K40: 488907 | L40: 470907 | M40: 141555 | N40: 565350 | O40: 342600
A41: =VLOOKUP(B41,'PORTFOLIO RAW'!B:B,1,FALSE) -> 945388 | B41: 945388 | C41: AT&T INC - NET INCOME - BASIC | D41: 945388(WC01706) | E41: 11951000 | F41: 12867000 | G41: 12535000 | H41: 19095000 | I41: 3944000 | J41: 7264000 | K41: 18249000 | L41: 6224000 | M41: 13345000 | N41: 12976000 | O41: 9179000
A42: =VLOOKUP(B42,'PORTFOLIO RAW'!B:B,1,FALSE) -> 702259 | B42: 702259 | C42: AUTODESK INC - NET INCOME - BASIC | D42: 702259(WC01706) | E42: 356200 | F42: 183600 | G42: 58000 | H42: 212000 | I42: 285300 | J42: 247400 | K42: 228800 | L42: 81800 | M42: -330500 | N42: -582100 | O42: -158500
A43: =VLOOKUP(B43,'PORTFOLIO RAW'!B:B,1,FALSE) -> 912669 | B43: 912669 | C43: AUTOMATIC DATA PROC - NET INCOME - BASIC | D43: 912669(WC01706) | E43: 1021200 | F43: 1161700 | G43: 1328200 | H43: 1210900 | I43: 1254200 | J43: 1388500 | K43: 1405800 | L43: 1515900 | M43: 1374100 | N43: 1492500 | O43: 1733400
A44: =VLOOKUP(B44,'PORTFOLIO RAW'!B:B,1,FALSE) -> 544616 | B44: 544616 | C44: AUTOZONE INC - NET INCOME - BASIC | D44: 544616(WC01706) | E44: 595672 | F44: 641606 | G44: 657049 | H44: 738311 | I44: 848974 | J44: 930373 | K44: 1016480 | L44: 1069744 | M44: 1160241 | N44: 1241007 | O44: 1280869
A45: =VLOOKUP(B45,'PORTFOLIO RAW'!B:B,1,FALSE) -> 130502 | B45: 130502 | C45: AVALONBAY COMMUNITIE - NET INCOME - BASIC | D45: 130502(WC01706) | E45: 238968 | F45: 116132 | G45: 91760 | H45: 100759 | I45: 158901 | J45: 276294 | K45: 74347 | L45: 644175 | M45: 740264 | N45: 1031392 | O45: 874458
A46: =VLOOKUP(B46,'PORTFOLIO RAW'!B:B,1,FALSE) -> 921161 | B46: 921161 | C46: AVERY DENNISON CORP - NET INCOME - BASIC | D46: 921161(WC01706) | E46: 303500 | F46: 266100 | G46: -746700 | H46: 316900 | I46: 190100 | J46: 215400 | K46: 215800 | L46: 251100 | M46: 274400 | N46: 320700 | O46: 453800
A47: =VLOOKUP(B47,'PORTFOLIO RAW'!B:B,1,FALSE) -> 921431 | B47: 921431 | C47: BAKER HUGHES A GE CO - NET INCOME - BASIC | D47: 921431(WC01706) | E47: 1513900 | F47: 1635000 | G47: 421000 | H47: 812000 | I47: 1739000 | J47: 1311000 | K47: 1096000 | L47: 1719000 | M47: -1967000 | N47: -2738000 | O47: -205000
A48: =VLOOKUP(B48,'PORTFOLIO RAW'!B:B,1,FALSE) -> 932060 | B48: 932060 | C48: BALL CORPORATION - NET INCOME - BASIC | D48: 932060(WC01706) | E48: 281300 | F48: 319500 | G48: 387900 | H48: 468000 | I48: 444000 | J48: 403500 | K48: 406800 | L48: 470000 | M48: 280900 | N48: 263000 | O48: 457000
A49: =VLOOKUP(B49,'PORTFOLIO RAW'!B:B,1,FALSE) -> 923937 | B49: 923937 | C49: BANK OF AMERICA CORP - NET INCOME - BASIC | D49: 923937(WC01706) | E49: 14800000 | F49: 2556000 | G49: -2210000 | H49: -3599000 | I49: 84000 | J49: 2758000 | K49: 10080000 | L49: 3789000 | M49: 14405000 | N49: 16224000 | O49: 18571000
A50: =VLOOKUP(B50,'PORTFOLIO RAW'!B:B,1,FALSE) -> 905840 | B50: 905840 | C50: BANK OF NEW YORK - NET INCOME - BASIC | D50: 905840(WC01706) | E50: 2227000 | F50: 1412000 | G50: -1367000 | H50: 2518000 | I50: 2480000 | J50: 2397000 | K50: 2009000 | L50: 2451000 | M50: 3010000 | N50: 3373000 | O50: 3162000
A51: =VLOOKUP(B51,'PORTFOLIO RAW'!B:B,1,FALSE) -> 916365 | B51: 916365 | C51: BAXTER INTERNATIONAL - NET INCOME - BASIC | D51: 916365(WC01706) | E51: 1707000 | F51: 2014000 | G51: 2205000 | H51: 1420000 | I51: 2224000 | J51: 2326000 | K51: 2012000 | L51: 2497000 | M51: 968000 | N51: 4965000 | O51: 1302000
A52: =VLOOKUP(B52,'PORTFOLIO RAW'!B:B,1,FALSE) -> 992305 | B52: 992305 | C52: BB&T CORPORATION - NET INCOME - BASIC | D52: 992305(WC01706) | E52: 1734000 | F52: 1498000 | G52: 729000 | H52: 816000 | I52: 1289000 | J52: 1916000 | K52: 1562000 | L52: 2003000 | M52: 1936000 | N52: 2259000 | O52: 2177000
... A69: =VLOOKUP(B69,'PORTFOLIO RAW'!B:B,1,FALSE) -> 902224 | B69: 902224 | C69: CATERPILLAR INC - NET INCOME - BASIC | D69: 902224(WC01706) | E69: 3541000 | F69: 3557000 | G69: 895000 | H69: 2700000 | I69: 4928000 | J69: 5681000 | K69: 3789000 | L69: 3695000 | M69: 2102000 | N69: -67000 | O69: 3125000
A70: =VLOOKUP(B70,'PORTFOLIO RAW'!B:B,1,FALSE) -> 28513N | B70: 28513N | C70: CBRE GROUP - NET INCOME - BASIC | D70: 28513N(WC01706) | E70: 390505 | F70: -1012066 | G70: 33341 | H70: 200345 | I70: 239162 | J70: 315555 | K70: 316538 | L70: 484503 | M70: 547132 | N70: 571973 | O70: 834879
A71: =VLOOKUP(B71,'PORTFOLIO RAW'!B:B,1,FALSE) -> 32480Q | B71: 32480Q | C71: CBS CORPORATION - NET INCOME - BASIC | D71: 32480Q(WC01706) | E71: 1230800 | F71: -11673400 | G71: 226500 | H71: 724200 | I71: 1305000 | J71: 1574000 | K71: 1879000 | L71: 2959000 | M71: 1413000 | N71: 1261000 | O71: 486000
A72: =VLOOKUP(B72,'PORTFOLIO RAW'!B:B,1,FALSE) -> 29756N | B72: 29756N | C72: CELANESE CORPORATION - NET INCOME - BASIC | D72: 29756N(WC01706) | E72: 326000 | F72: 362000 | G72: 478000 | H72: 374000 | I72: 607000 | J72: 605000 | K72: 1101000 | L72: 624000 | M72: 304000 | N72: 900000 | O72: 933000
A73: =VLOOKUP(B73,'PORTFOLIO RAW'!B:B,1,FALSE) -> 755790 | B73: 755790 | C73: CELGENE CORPORATION - NET INCOME - BASIC | D73: 755790(WC01706) | E73: 226433 | F73: -1533653 | G73: 776747 | H73: 880512 | I73: 1318150 | J73: 1456180 | K73: 1449900 | L73: 1999900 | M73: 1602000 | N73: 1999200 | O73: 4209000
A74: =VLOOKUP(B74,'PORTFOLIO RAW'!B:B,1,FALSE) -> 904842 | B74: 904842 | C74: CENTERPOINT ENERGY - NET INCOME - BASIC | D74: 904842(WC01706) | E74: 399000 | F74: 447000 | G74: 372000 | H74: 442000 | I74: 770000 | J74: 417000 | K74: 311000 | L74: 611000 | M74: -692000 | N74: 432000 | O74: 679000
A75: =VLOOKUP(B75,'PORTFOLIO RAW'!B:B,1,FALSE) -> 755741 | B75: 755741 | C75: CHARLES SCHWAB CORP - NET INCOME - BASIC | D75: 755741(WC01706) | E75: 1120000 | F75: 1212000 | G75: 787000 | H75: 454000 | I75: 864000 | J75: 883000 | K75: 1010000 | L75: 1261000 | M75: 1364000 | N75: 1746000 | O75: 2226000
A76: =VLOOKUP(B76,'PORTFOLIO RAW'!B:B,1,FALSE) -> 905024 | B76: 905024 | C76: CHEVRON CORPORATION - NET INCOME - BASIC | D76: 905024(WC01706) | E76: 18688000 | F76: 23931000 | G76: 10483000 | H76: 19024000 | I76: 26895000 | J76: 26179000 | K76: 21423000 | L76: 19241000 | M76: 4587000 | N76: -497000 | O76: 7175000
A77: =VLOOKUP(B77,'PORTFOLIO RAW'!B:B,1,FALSE) -> 328314 | B77: 328314 | C77: CHUBB - NET INCOME - BASIC | D77: 328314(WC01706) | E77: 2533000 | F77: 1173000 | G77: 2549000 | H77: 3108000 | I77: 1585000 | J77: 2706000 | K77: 3758000 | L77: 2853000 | M77: 2834000 | N77: 4135000 | O77: 3411000
A78: =VLOOKUP(B78,'PORTFOLIO RAW'!B:B,1,FALSE) -> 912278 | B78: 912278 | C78: CIGNA CORP - NET INCOME - BASIC | D78: 912278(WC01706) | E78: 1115000 | F78: 292000 | G78: 1302000 | H78: 1345000 | I78: 1327000 | J78: 1623000 | K78: 1476000 | L78: 2102000 | M78: 2094000 | N78: 1867000 | O78: 2469000
A79: =VLOOKUP(B79,'PORTFOLIO RAW'!B:B,1,FALSE) -> 26276P | B79: 26276P | C79: CIMAREX ENERGY CO - NET INCOME - BASIC | D79: 26276P(WC01706) | E79: 346469 | F79: -901685 | G79: -311943 | H79: 574782 | I79: 529932 | J79: 347070 | K79: 553598 | L79: 497298 | M79: -2408948 | N79: -431049 | O79: 424632
A80: =VLOOKUP(B80,'PORTFOLIO RAW'!B:B,1,FALSE) -> 951545 | B80: 951545 | C80: CINCINNATI FINL CORP - NET INCOME - BASIC | D80: 951545(WC01706) | E80: 855000 | F80: 429000 | G80: 432000 | H80: 377000 | I80: 166000 | J80: 421000 | K80: 517000 | L80: 525000 | M80: 634000 | N80: 591000 | O80: 550000
A81: =VLOOKUP(B81,'PORTFOLIO RAW'!B:B,1,FALSE) -> 944777 | B81: 944777 | C81: CINTAS CORPORATION - NET INCOME - BASIC | D81: 944777(WC01706) | E81: 334538 | F81: 335405 | G81: 226357 | H81: 214959 | I81: 245892 | J81: 295757 | K81: 313546 | L81: 370990 | M81: 426741 | N81: 686115 | O81: 459740
A82: =VLOOKUP(B82,'PORTFOLIO RAW'!B:B,1,FALSE) -> 542868 | B82: 542868 | C82: CISCO SYSTEMS, INC. - NET INCOME - BASIC | D82: 542868(WC01706) | E82: 7333000 | F82: 8052000 | G82: 6134000 | H82: 7767000 | I82: 6490000 | J82: 8041000 | K82: 9983000 | L82: 7853000 | M82: 8981000 | N82: 10739000 | O82: 9609000
A83: =VLOOKUP(B83,'PORTFOLIO RAW'!B:B,1,FALSE) -> 741344 | B83: 741344 | C83: CITIGROUP INC - NET INCOME - BASIC | D83: 741344(WC01706) | E83: 3581000 | F83: -29416000 | G83: -9246000 | H83: 10503000 | I83: 10760000 | J83: 7350000 | K83: 13216000 | L83: 6691000 | M83: 16249000 | N83: 13640000 | O83: 14552000
A84: =VLOOKUP(B84,'PORTFOLIO RAW'!B:B,1,FALSE) -> 867705 | B84: 867705 | C84: CITRIX SYSTEMS INC - NET INCOME - BASIC | D84: 867705(WC01706) | E84: 214483 | F84: 178276 | G84: 191017 | H84: 277065 | I84: 356322 | J84: 352547 | K84: 339523 | L84: 251723 | M84: 319361 | N84: 536112 | O84: 408681
A85: =VLOOKUP(B85,'PORTFOLIO RAW'!B:B,1,FALSE) -> 916125 | B85: 916125 | C85: CLOROX CO - NET INCOME - BASIC | D85: 916125(WC01706) | E85: 496000 | F85: 461000 | G85: 537000 | H85: 600000 | I85: 308000 | J85: 543000 | K85: 572000 | L85: 558000 | M85: 580000 | N85: 648000 | O85: 701000
A86: =VLOOKUP(B86,'PORTFOLIO RAW'!B:B,1,FALSE) -> 26393N | B86: 26393N | C86: CME GROUP INC - NET INCOME - BASIC | D86: 26393N(WC01706) | E86: 658533 | F86: 715486 | G86: 825800 | H86: 951400 | I86: 1812300 | J86: 896300 | K86: 976800 | L86: 1127100 | M86: 1247000 | N86: 1534100 | O86: 1463400
A87: =VLOOKUP(B87,'PORTFOLIO RAW'!B:B,1,FALSE) -> 901686 | B87: 901686 | C87: CMS ENERGY CORP - NET INCOME - BASIC | D87: 901686(WC01706) | E87: -227000 | F87: 289000 | G87: 218000 | H87: 324000 | I87: 415000 | J87: 382000 | K87: 452000 | L87: 477000 | M87: 523000 | N87: 551000 | O87: 608000
A88: =VLOOKUP(B88,'PORTFOLIO RAW'!B:B,1,FALSE) -> 904282 | B88: 904282 | C88: COCA-COLA - NET INCOME - BASIC | D88: 904282(WC01706) | E88: 5981000 | F88: 5807000 | G88: 6824000 | H88: 11809000 | I88: 8572000 | J88: 9019000 | K88: 8584000 | L88: 7098000 | M88: 7351000 | N88: 6527000 | O88: 4858000
A89: =VLOOKUP(B89,'PORTFOLIO RAW'!B:B,1,FALSE) -> 906148 | B89: 906148 | C89: COLGATE-PALMOLIVE CO - NET INCOME - BASIC | D89: 906148(WC01706) | E89: 1709400 | F89: 1928700 | G89: 2261000 | H89: 2169000 | I89: 2431000 | J89: 2472000 | K89: 2241000 | L89: 2180000 | M89: 1384000 | N89: 2441000 | O89: 2299000
A90: =VLOOKUP(B90,'PORTFOLIO RAW'!B:B,1,FALSE) -> 981550 | B90: 981550 | C90: COMCAST CORPORATION - NET INCOME - BASIC | D90: 981550(WC01706) | E90: 2587000 | F90: 2547000 | G90: 3638000 | H90: 3635000 | I90: 4160000 | J90: 6203000 | K90: 6816000 | L90: 8380000 | M90: 8163000 | N90: 8695000 | O90: 10035000
A91: =VLOOKUP(B91,'PORTFOLIO RAW'!B:B,1,FALSE) -> 922964 | B91: 922964 | C91: COMERICA INC. - NET INCOME - BASIC | D91: 922964(WC01706) | E91: 682000 | F91: 196000 | G91: -118000 | H91: 136000 | I91: 389000 | J91: 515000 | K91: 533000 | L91: 586000 | M91: 515000 | N91: 473000 | O91: 845000
A92: =VLOOKUP(B92,'PORTFOLIO RAW'!B:B,1,FALSE) -> 929814 | B92: 929814 | C92: CONAGRA BRANDS INC - NET INCOME - BASIC | D92: 929814(WC01706) | E92: 683800 | F92: 518700 | G92: 978400 | H92: 724300 | I92: 815100 | J92: 466400 | K92: 772300 | L92: 301400 | M92: -254300 | N92: -681800 | O92: 638500
A93: =VLOOKUP(B93,'PORTFOLIO RAW'!B:B,1,FALSE) -> 901666 | B93: 901666 | C93: CONOCOPHILLIPS - NET INCOME - BASIC | D93: 901666(WC01706) | E93: 11891000 | F93: -16998000 | G93: 4858000 | H93: 11358000 | I93: 12436000 | J93: 8428000 | K93: 9156000 | L93: 6869000 | M93: -4428000 | N93: -3615000 | O93: -1707000
A94: =VLOOKUP(B94,'PORTFOLIO RAW'!B:B,1,FALSE) -> 902288 | B94: 902288 | C94: CONSOLIDATED EDISON - NET INCOME - BASIC | D94: 902288(WC01706) | E94: 929000 | F94: 1196000 | G94: 868000 | H94: 992000 | I94: 1051000 | J94: 1138000 | K94: 1062000 | L94: 1092000 | M94: 1193000 | N94: 1245000 | O94: 6837000
A95: =VLOOKUP(B95,'PORTFOLIO RAW'!B:B,1,FALSE) -> 937083 | B95: 937083 | C95: CONSTELLATION BRANDS - NET INCOME - BASIC | D95: 937083(WC01706) | E95: 327000 | F95: -613300 | G95: -301400 | H95: 99300 | I95: 559500 | J95: 445000 | K95: 387800 | L95: 1943100 | M95: 839300 | N95: 1054900 | O95: 1535100
A96: =VLOOKUP(B96,'PORTFOLIO RAW'!B:B,1,FALSE) -> 938928 | B96: 938928 | C96: COOPER COMPANIES INC - NET INCOME - BASIC | D96: 938928(WC01706) | E96: -11192 | F96: 65476 | G96: 100548 | H96: 112803 | I96: 175430 | J96: 248339 | K96: 296151 | L96: 269856 | M96: 203523 | N96: 273917 | O96: 372900
A97: =VLOOKUP(B97,'PORTFOLIO RAW'!B:B,1,FALSE) -> 912273 | B97: 912273 | C97: CORNING INCORPORATED - NET INCOME - BASIC | D97: 912273(WC01706) | E97: 2150000 | F97: 5257000 | G97: 2008000 | H97: 3558000 | I97: 2805000 | J97: 1728000 | K97: 1961000 | L97: 2378000 | M97: 1241000 | N97: 3597000 | O97: -506600
A98: =VLOOKUP(B98,'PORTFOLIO RAW'!B:B,1,FALSE) -> 312385 | B98: 312385 | C98: COSTCO WHOLESALE - NET INCOME - BASIC | D98: 312385(WC01706) | E98: 1082772 | F98: 1282725 | G98: 1086000 | H98: 1304000 | I98: 1463000 | J98: 1710000 | K98: 2039000 | L98: 2058000 | M98: 2377000 | N98: 2350000 | O98: 2679000
... A109: =VLOOKUP(B109,'PORTFOLIO RAW'!B:B,1,FALSE) -> 271980 | B109: 271980 | C109: DEVON ENERGY CORP - NET INCOME - BASIC | D109: 271980(WC01706) | E109: 3596000 | F109: -2922000 | G109: -2479000 | H109: 4550000 | I109: 4681000 | J109: -209000 | K109: -22000 | L109: 1590000 | M109: -14459000 | N109: -3304000 | O109: 952000
A110: =VLOOKUP(B110,'PORTFOLIO RAW'!B:B,1,FALSE) -> 31196R | B110: 31196R | C110: DISCOVERY INC - NET INCOME - BASIC | D110: 31196R(WC01706) | E110: 108338 | F110: 317000 | G110: 552000 | H110: 652000 | I110: 1132000 | J110: 943000 | K110: 1075000 | L110: 758000 | M110: 686000 | N110: 789000 | O110: -269000
A111: =VLOOKUP(B111,'PORTFOLIO RAW'!B:B,1,FALSE) -> 135448 | B111: 135448 | C111: DISH NETWORK - NET INCOME - BASIC | D111: 135448(WC01706) | E111: 756054 | F111: 902947 | G111: 635545 | H111: 984729 | I111: 1515907 | J111: 636687 | K111: 807492 | L111: 944693 | M111: 747092 | N111: 1449853 | O111: 898689
A112: =VLOOKUP(B112,'PORTFOLIO RAW'!B:B,1,FALSE) -> 154259 | B112: 154259 | C112: DOLLAR TREE, INC - NET INCOME - BASIC | D112: 154259(WC01706) | E112: 201300 | F112: 229500 | G112: 320500 | H112: 397300 | I112: 488300 | J112: 619300 | K112: 596700 | L112: 599200 | M112: 282400 | N112: 896200 | O112: 1152300
A113: =VLOOKUP(B113,'PORTFOLIO RAW'!B:B,1,FALSE) -> 944314 | B113: 944314 | C113: DOMINION ENERGY INC - NET INCOME - BASIC | D113: 944314(WC01706) | E113: 2705000 | F113: 1834000 | G113: 1287000 | H113: 2808000 | I113: 1408000 | J113: 318000 | K113: 1697000 | L113: 1310000 | M113: 1899000 | N113: 2123000 | O113: 2148000
A114: =VLOOKUP(B114,'PORTFOLIO RAW'!B:B,1,FALSE) -> 904830 | B114: 904830 | C114: DOVER CORP - NET INCOME - BASIC | D114: 904830(WC01706) | E114: 661080 | F114: 590831 | G114: 367608 | H114: 714307 | I114: 899986 | J114: 861888 | K114: 1003129 | L114: 775235 | M114: 604279 | N114: 508892 | O114: 760765
A115: =VLOOKUP(B115,'PORTFOLIO RAW'!B:B,1,FALSE) -> 905214 | B115: 905214 | C115: DTE ENERGY CO - NET INCOME - BASIC | D115: 905214(WC01706) | E115: 787000 | F115: 546000 | G115: 532000 | H115: 630000 | I115: 711000 | J115: 610000 | K115: 661000 | L115: 905000 | M115: 727000 | N115: 868000 | O115: 1027000
A116: =VLOOKUP(B116,'PORTFOLIO RAW'!B:B,1,FALSE) -> 904383 | B116: 904383 | C116: DUKE ENERGY CORP - NET INCOME - BASIC | D116: 904383(WC01706) | E116: 1522000 | F116: 1295000 | G116: 1075000 | H116: 1320000 | I116: 1706000 | J116: 1768000 | K116: 2665000 | L116: 1883000 | M116: 2816000 | N116: 2152000 | O116: 2947000
A117: =VLOOKUP(B117,'PORTFOLIO RAW'!B:B,1,FALSE) -> 513260 | B117: 513260 | C117: DUKE REALTY CORP - NET INCOME - BASIC | D117: 513260(WC01706) | E117: 97421 | F117: 40491 | G117: -340387 | H117: -47162 | I117: -72709 | J117: -142687 | K117: 17124 | L117: 182511 | M117: 190512 | N117: 308771 | O117: 272672
A118: =VLOOKUP(B118,'PORTFOLIO RAW'!B:B,1,FALSE) -> 916091 | B118: 916091 | C118: DXC TECHNO - NET INCOME - BASIC | D118: 916091(WC01706) | E118: 388800 | F118: 544600 | G118: 1115200 | H118: 817000 | I118: 740000 | J118: -4243000 | K118: 544000 | L118: 947000 | M118: -8000 | N118: 251000 | O118: -123000
A119: =VLOOKUP(B119,'PORTFOLIO RAW'!B:B,1,FALSE) -> 883488 | B119: 883488 | C119: E*TRADE FINANCIAL - NET INCOME - BASIC | D119: 883488(WC01706) | E119: -1441754 | F119: -780588 | G119: -1297762 | H119: -28472 | I119: 156701 | J119: -112583 | K119: 86012 | L119: 293000 | M119: 268000 | N119: 552000 | O119: 647000
A120: =VLOOKUP(B120,'PORTFOLIO RAW'!B:B,1,FALSE) -> 357922 | B120: 357922 | C120: EASTMAN CHEMICAL CO - NET INCOME - BASIC | D120: 357922(WC01706) | E120: 311000 | F120: 328000 | G120: 136000 | H120: 438000 | I120: 665000 | J120: 436000 | K120: 1165000 | L120: 751000 | M120: 848000 | N120: 854000 | O120: 1045000
A121: =VLOOKUP(B121,'PORTFOLIO RAW'!B:B,1,FALSE) -> 903749 | B121: 903749 | C121: EATON CORP PLC - NET INCOME - BASIC | D121: 903749(WC01706) | E121: 959000 | F121: 1058000 | G121: 383000 | H121: 929000 | I121: 1350000 | J121: 1217000 | K121: 1861000 | L121: 1793000 | M121: 1979000 | N121: 1922000 | O121: 2923000
A122: =VLOOKUP(B122,'PORTFOLIO RAW'!B:B,1,FALSE) -> 687609 | B122: 687609 | C122: EBAY INC. - NET INCOME - BASIC | D122: 687609(WC01706) | E122: 348251 | F122: 1779474 | G122: 2389097 | H122: 1800961 | I122: 3229387 | J122: 2609000 | K122: 2856000 | L122: 46000 | M122: 1725000 | N122: 7266000 | O122: 2084000
... A133: =VLOOKUP(B133,'PORTFOLIO RAW'!B:B,1,FALSE) -> 902317 | B133: 902317 | C133: EXELON CORPORATION - NET INCOME - BASIC | D133: 902317(WC01706) | E133: 2726000 | F133: 2716000 | G133: 2707000 | H133: 2563000 | I133: 2495000 | J133: 1160000 | K133: 1719000 | L133: 1623000 | M133: 2269000 | N133: 1134000 | O133: 3770000
A134: =VLOOKUP(B134,'PORTFOLIO RAW'!B:B,1,FALSE) -> 31412T | B134: 31412T | C134: EXPEDIA GROUP INC - NET INCOME - BASIC | D134: 31412T(WC01706) | E134: 295864 | F134: -2517763 | G134: 299526 | H134: 421500 | I134: 472294 | J134: 280171 | K134: 232850 | L134: 398097 | M134: 764465 | N134: 281848 | O134: 363845
A135: =VLOOKUP(B135,'PORTFOLIO RAW'!B:B,1,FALSE) -> 910722 | B135: 910722 | C135: EXPEDITORS INTL WASH - NET INCOME - BASIC | D135: 910722(WC01706) | E135: 269154 | F135: 301014 | G135: 240217 | H135: 344172 | I135: 385679 | J135: 333360 | K135: 348526 | L135: 376888 | M135: 457223 | N135: 430807 | O135: 450077
A136: =VLOOKUP(B136,'PORTFOLIO RAW'!B:B,1,FALSE) -> 905039 | B136: 905039 | C136: EXXON MOBIL CORP - NET INCOME - BASIC | D136: 905039(WC01706) | E136: 40610000 | F136: 45220000 | G136: 19280000 | H136: 30460000 | I136: 41060000 | J136: 44880000 | K136: 32580000 | L136: 32520000 | M136: 16150000 | N136: 7840000 | O136: 13768000
...

Sheet EBITDA
A1: EBITDA
B2: Code | C2: Name | D2: Code | E2: 2007 | F2: 2008 | G2: 2009 | H2: 2010 | I2: 2011 | J2: 2012 | K2: 2013 | L2: 2014 | M2: 2015 | N2: 2016 | O2: 2017
A3: =VLOOKUP(B3,'PORTFOLIO RAW'!B:B,1,FALSE) -> 891399 | B3: 891399 | C3: AMAZON.COM INC - EBIT & DEPRECIATION | D3: 891399(WC18198) | E3: 1008000 | F3: 1312000 | G3: 1627000 | H3: 2193000 | I3: 2148000 | J3: 2795000 | K3: 3900000 | L3: 4845000 | M3: 8308000 | N3: 12492000 | O3: 16132000
A4: =VLOOKUP(B4,'PORTFOLIO RAW'!B:B,1,FALSE) -> 916328 | B4: 916328 | C4: ABBOTT LABORATORIES - EBIT & DEPRECIATION | D4: 916328(WC18198) | E4: 6419660 | F4: 8104592 | G4: 9493940 | H4: 9138274 | I4: 9260677 | J4: 9638224 | K4: 4299000 | L4: 4216000 | M4: 4818000 | N4: 3197000 | O4: 6156000
A5: =VLOOKUP(B5,'PORTFOLIO RAW'!B:B,1,FALSE) -> 545101 | B5: 545101 | C5: AES CORP - EBIT & DEPRECIATION | D5: 545101(WC18198) | E5: 4268000 | F5: 5596000 | G5: 4790000 | H5: 3622000 | I5: 5044000 | J5: 3280000 | K5: 3783000 | L5: 4294000 | M5: 3705000 | N5: 2744000 | O5: 3110000
A6: =VLOOKUP(B6,'PORTFOLIO RAW'!B:B,1,FALSE) -> 906187 | B6: 906187 | C6: INT'L BUSINESS MACHS - EBIT & DEPRECIATION | D6: 906187(WC18198) | E6: 20301000 | F6: 22838000 | G6: 23630000 | H6: 25025000 | I6: 26328000 | J6: 27048000 | K6: 24533000 | L6: 25168000 | M6: 20375000 | N6: 17449000 | O6: 16590000
A7: =VLOOKUP(B7,'PORTFOLIO RAW'!B:B,1,FALSE) -> 936365 | B7: 936365 | C7: ADVANCED MICRO - EBIT & DEPRECIATION | D7: 936365(WC18198) | E7: -1494000 | F7: -671000 | G7: 1974000 | H7: 1553000 | I7: 496000 | J7: -782000 | K7: 339000 | L7: -18000 | M7: -319000 | N7: -159000 | O7: 339000
A8: =VLOOKUP(B8,'PORTFOLIO RAW'!B:B,1,FALSE) -> 749382 | B8: 749382 | C8: ADOBE INC - EBIT & DEPRECIATION | D8: 749382(WC18198) | E8: 1262907 | F8: 1358796 | G8: 987350 | H8: 1264303 | I8: 1372387 | J8: 1486047 | K8: 744876 | L8: 734698 | M8: 1277438 | N8: 1837115 | O8: 2538040
A9: =VLOOKUP(B9,'PORTFOLIO RAW'!B:B,1,FALSE) -> 905271 | B9: 905271 | C9: AIR PRODUCTS & CHEMS - EBIT & DEPRECIATION | D9: 905271(WC18198) | E9: 2247700 | F9: 2364800 | G9: 1686600 | H9: 2252400 | I9: 2504300 | J9: 2129000 | K9: 2231400 | L9: 2280100 | M9: 2610900 | N9: 3016200 | O9: 2307700
A10: =VLOOKUP(B10,'PORTFOLIO RAW'!B:B,1,FALSE) -> 894371 | B10: 894371 | C10: BOSTON PROPERTIES - EBIT & DEPRECIATION | D10: 894371(WC18198) | E10: 1717571 | F10: 907372 | G10: 906955 | H10: 870003 | I10: 1061245 | J10: 1111776 | K10: 1640851 | L10: 1597604 | M10: 1848886 | N10: 1669155 | O10: 1543277
A11: =VLOOKUP(B11,'PORTFOLIO RAW'!B:B,1,FALSE) -> 322677 | B11: 322677 | C11: ALLSTATE CORP - EBIT & DEPRECIATION | D11: 322677(WC18198) | E11: 6917000 | F11: -2496000 | G11: 1879000 | H11: 1692000 | I11: 1491000 | J11: 3719000 | K11: 4131000 | L11: 4924000 | M11: 3945000 | N11: 3431000 | O11: 4809000
A12: =VLOOKUP(B12,'PORTFOLIO RAW'!B:B,1,FALSE) -> 906191 | B12: 906191 | C12: HONEYWELL INTERNATNL - EBIT & DEPRECIATION | D12: 906191(WC18198) | E12: 4604000 | F12: 5097000 | G12: 4368000 | H12: 4211000 | I12: 3676000 | J12: 5119000 | K12: 6711000 | L12: 7045000 | M12: 7779000 | N12: 7806000 | O12: 8294000
A13: =VLOOKUP(B13,'PORTFOLIO RAW'!B:B,1,FALSE) -> 938692 | B13: 938692 | C13: AMGEN INC - EBIT & DEPRECIATION | D13: 938692(WC18198) | E13: 5437000 | F13: 6567000 | G13: 6830000 | H13: 6937000 | I13: 5819000 | J13: 7150000 | K13: 8595000 | L13: 9809000 | M13: 11184000 | N13: 12542000 | O13: 12856000
A14: =VLOOKUP(B14,'PORTFOLIO RAW'!B:B,1,FALSE) -> 905802 | B14: 905802 | C14: HESS CORPORATION - EBIT & DEPRECIATION | D14: 905802(WC18198) | E14: 5360000 | F14: 6952000 | G14: 4313000 | H14: 6511000 | I14: 6323000 | J14: 7106000 | K14: 7669000 | L14: 5983000 | M14: 38000 | N14: -272000 | O14: -2570000
... A28: =VLOOKUP(B28,'PORTFOLIO RAW'!B:B,1,FALSE) -> 670942 | B28: 670942 | C28: AMEREN CORPORATION - EBIT & DEPRECIATION | D28: 670942(WC18198) | E28: 2176000 | F28: 2125000 | G28: 2229000 | H28: 1758000 | I28: 2061000 | J28: -424000 | K28: 1933000 | L28: 2056000 | M28: 2099000 | N28: 2268000 | O28: 2392000
A29: =VLOOKUP(B29,'PORTFOLIO RAW'!B:B,1,FALSE) -> 702259 | B29: 702259 | C29: AUTODESK INC - EBIT & DEPRECIATION | D29: 702259(WC18198) | E29: 534700 | F29: 344300 | G29: 196200 | H29: 377400 | I29: 478400 | J29: NA | K29: 418600 | L29: 242100 | M29: 159400 | N29: -337400 | O29: -395100
A30: =VLOOKUP(B30,'PORTFOLIO RAW'!B:B,1,FALSE) -> 912669 | B30: 912669 | C30: AUTOMATIC DATA PROC - EBIT & DEPRECIATION | D30: 912669(WC18198) | E30: 2007200 | F30: 2211600 | G30: 2246100 | H30: 2181000 | I30: 2259500 | J30: 2453100 | K30: 2410400 | L30: 2616900 | M30: 2355100 | N30: 2579500 | O30: 2927200
A31: =VLOOKUP(B31,'PORTFOLIO RAW'!B:B,1,FALSE) -> 544616 | B31: 544616 | C31: AUTOZONE INC - EBIT & DEPRECIATION | D31: 544616(WC18198) | E31: 1217496 | F31: 1297428 | G31: 1360382 | H31: 1514124 | I31: 1693070 | J31: 1842119 | K31: 2001955 | L31: 2083340 | M31: 2224575 | N31: 2360163 | O31: 2406622
A32: =VLOOKUP(B32,'PORTFOLIO RAW'!B:B,1,FALSE) -> 921161 | B32: 921161 | C32: AVERY DENNISON CORP - EBIT & DEPRECIATION | D32: 921161(WC18198) | E32: 715100 | F32: 664900 | G32: -445200 | H32: 670700 | I32: 546200 | J32: 548900 | K32: 626800 | L32: 629400 | M32: 657800 | N32: 713500 | O32: 826300
A33: =VLOOKUP(B33,'PORTFOLIO RAW'!B:B,1,FALSE) -> 932060 | B33: 932060 | C33: BALL CORPORATION - EBIT & DEPRECIATION | D33: 932060(WC18198) | E33: 794900 | F33: 887900 | G33: 931700 | H33: 1016400 | I33: 1138000 | J33: 1073400 | K33: 1067300 | L33: 1086400 | M33: 774200 | N33: 807000 | O33: 1528000
A34: =VLOOKUP(B34,'PORTFOLIO RAW'!B:B,1,FALSE) -> 874227 | B34: 874227 | C34: BERKSHIRE HATHAWAY - EBIT & DEPRECIATION | D34: 874227(WC18198) | E34: 24478000 | F34: 12347000 | G34: 16671000 | H34: 25888000 | I34: 22661000 | J34: 30126000 | K34: 38105000 | L34: 38728000 | M34: 46240000 | N34: 45142000 | O34: 35482000
A35: =VLOOKUP(B35,'PORTFOLIO RAW'!B:B,1,FALSE) -> 916365 | B35: 916365 | C35: BAXTER INTERNATIONAL - EBIT & DEPRECIATION | D35: 916365(WC18198) | E35: 2846000 | F35: 3255000 | G35: 3418000 | H35: 2779000 | I35: 3637000 | J35: 3698000 | K35: 3503000 | L35: 3611000 | M35: 1333000 | N35: 5843000 | O35: 2063000
A36: =VLOOKUP(B36,'PORTFOLIO RAW'!B:B,1,FALSE) -> 905876 | B36: 905876 | C36: BECTON, DICKINSON - EBIT & DEPRECIATION | D36: 905876(WC18198) | E36: 1691706 | F36: 2067372 | G36: 2143456 | H36: 2207692 | I36: 2299698 | J36: 2105920 | K36: 1850000 | L36: 2219000 | M36: 2001000 | N36: 2576000 | O36: 2588000
A37: =VLOOKUP(B37,'PORTFOLIO RAW'!B:B,1,FALSE) -> 945384 | B37: 945384 | C37: VERIZON COMMUNICATNS - EBIT & DEPRECIATION | D37: 945384(WC18198) | E37: 30166000 | F37: 31731000 | G37: 30649000 | H37: 31002000 | I37: 29362000 | J37: 28604000 | K37: 48408000 | L37: 34938000 | M37: 49263000 | N37: 41388000 | O37: 42134000
A38: =VLOOKUP(B38,'PORTFOLIO RAW'!B:B,1,FALSE) -> 929302 | B38: 929302 | C38: BEST BUY CO INC - EBIT & DEPRECIATION | D38: 929302(WC18198) | E38: 2670000 | F38: 2870000 | G38: 2587000 | H38: 3215000 | I38: 3143000 | J38: 940820 | K38: 1903000 | L38: 2133000 | M38: 2047000 | N38: 2542000 | O38: 2575000
A39: =VLOOKUP(B39,'PORTFOLIO RAW'!B:B,1,FALSE) -> 895784 | B39: 895784 | C39: SL GREEN REALTY CORP - EBIT & DEPRECIATION | D39: 895784(WC18198) | E39: 598725 | F39: 547709 | G39: 500310 | H39: 724810 | I39: 1218024 | J39: 783663 | K39: 816231 | L39: 933469 | M39: 1216001 | N39: 1417949 | O39: 758011
A40: =VLOOKUP(B40,'PORTFOLIO RAW'!B:B,1,FALSE) -> 878574 | B40: 878574 | C40: YUM! BRANDS INC - EBIT & DEPRECIATION | D40: 878574(WC18198) | E40: 1881000 | F40: 2119000 | G40: 2084000 | H40: 2369000 | I40: 2448000 | J40: 2932000 | K40: 2516000 | L40: 2288000 | M40: 2648000 | N40: 1960000 | O40: 3000000
A41: =VLOOKUP(B41,'PORTFOLIO RAW'!B:B,1,FALSE) -> 905159 | B41: 905159 | C41: FIRSTENERGY CORP - EBIT & DEPRECIATION | D41: 905159(WC18198) | E41: 3573000 | F41: 3498000 | G41: 2819000 | H41: 2657000 | I41: 3502000 | J41: 3377000 | K41: 2813000 | L41: 2426000 | M41: 3884000 | N41: -6751000 | O41: 1423000
... A43: =VLOOKUP(B43,'PORTFOLIO RAW'!B:B,1,FALSE) -> 904818 | B43: 904818 | C43: BOEING CO - EBIT & DEPRECIATION | D43: 904818(WC18198) | E43: 7908000 | F43: 5670000 | G43: 3662000 | H43: 6643000 | I43: 7401000 | J43: 8004000 | K43: 8462000 | L43: 9376000 | M43: 9263000 | N43: 7784000 | O43: 12476000
A44: =VLOOKUP(B44,'PORTFOLIO RAW'!B:B,1,FALSE) -> 923649 | B44: 923649 | C44: ROBERT HALF INTL INC - EBIT & DEPRECIATION | D44: 923649(WC18198) | E44: 565945 | F44: 497786 | G44: 132529 | H44: 171726 | I44: 301631 | J44: 392969 | K44: NA | L44: NA | M44: NA | N44: NA | O44: NA
A45: =VLOOKUP(B45,'PORTFOLIO RAW'!B:B,1,FALSE) -> 325824 | B45: 325824 | C45: BOSTON SCIENTIFIC - EBIT & DEPRECIATION | D45: 325824(WC18198) | E45: 940000 | F45: -699000 | G45: -61000 | H45: 146000 | I45: 1641000 | J45: -3161000 | K45: 790000 | L45: 432000 | M45: 403000 | N45: 1225000 | O45: 2006000
A46: =VLOOKUP(B46,'PORTFOLIO RAW'!B:B,1,FALSE) -> 879628 | B46: 879628 | C46: C.H. ROBINSON - EBIT & DEPRECIATION | D46: 879628(WC18198) | E46: 550880 | F46: 609551 | G46: 617575 | H46: 653471 | I46: 727202 | J46: NA | K46: 741343 | L46: 805427 | M46: 931919 | N46: 912200 | O46: 868096
A47: =VLOOKUP(B47,'PORTFOLIO RAW'!B:B,1,FALSE) -> 905080 | B47: 905080 | C47: BRISTOL-MYERS SQUIBB - EBIT & DEPRECIATION | D47: 905080(WC18198) | E47: 4324000 | F47: 5980000 | G47: 6086000 | H47: 6808000 | I47: 7646000 | J47: 3328000 | K47: 4235000 | L47: 3306000 | M47: 2861000 | N47: 6675000 | O47: 6109000
A48: =VLOOKUP(B48,'PORTFOLIO RAW'!B:B,1,FALSE) -> 130502 | B48: 130502 | C48: AVALONBAY COMMUNITIE - EBIT & DEPRECIATION | D48: 130502(WC18198) | E48: 467178 | F48: 418099 | G48: 435041 | H48: 505086 | I48: 575663 | J48: 636788 | K48: 801598 | L48: 1143050 | M48: 1327114 | N48: 1687995 | O48: 1589868
A49: =VLOOKUP(B49,'PORTFOLIO RAW'!B:B,1,FALSE) -> 902103 | B49: 902103 | C49: SEMPRA ENERGY - EBIT & DEPRECIATION | D49: 902103(WC18198) | E49: 2517000 | F49: 2018000 | G49: 2618000 | H49: 2381000 | I49: 3155000 | J49: 2845000 | K49: 3063000 | L49: 3161000 | M49: 3421000 | N49: 3072000 | O49: 3699000
A50: =VLOOKUP(B50,'PORTFOLIO RAW'!B:B,1,FALSE) -> 951849 | B50: 951849 | C50: FEDEX CORP - EBIT & DEPRECIATION | D50: 951849(WC18198) | E50: 5093000 | F50: 4060000 | G50: 2737000 | H50: 3931000 | I50: 4324000 | J50: 5306000 | K50: 4923000 | L50: 6072000 | M50: 4473000 | N50: 5707000 | O50: 8086000
A51: =VLOOKUP(B51,'PORTFOLIO RAW'!B:B,1,FALSE) -> 674693 | B51: 674693 | C51: VERISIGN, INC. - EBIT & DEPRECIATION | D51: 674693(WC18198) | E51: 121127 | F51: 292344 | G51: 414907 | H51: 320676 | I51: 396625 | J51: 517710 | K51: 609988 | L51: 632995 | M51: 670902 | N51: 754904 | O51: 786119
A52: =VLOOKUP(B52,'PORTFOLIO RAW'!B:B,1,FALSE) -> 546075 | B52: 546075 | C52: AMPHENOL CORP - EBIT & DEPRECIATION | D52: 546075(WC18198) | E52: 630726 | F52: 723509 | G52: 581637 | H52: 807275 | I52: 879220 | J52: 960233 | K52: 1046680 | L52: 1221000 | M52: 1292700 | N52: 1430700 | O52: 1671500
A53: =VLOOKUP(B53,'PORTFOLIO RAW'!B:B,1,FALSE) -> 912216 | B53: 912216 | C53: BROWN FORMAN CORP - EBIT & DEPRECIATION | D53: 912216(WC18198) | E53: 664000 | F53: 745000 | G53: 722000 | H53: 772000 | I53: 917000 | J53: 843000 | K53: 952000 | L53: 1023000 | M53: 1080000 | N53: 1591000 | O53: 1050000
A54: =VLOOKUP(B54,'PORTFOLIO RAW'!B:B,1,FALSE) -> 993189 | B54: 993189 | C54: CSX CORPORATION - EBIT & DEPRECIATION | D54: 993189(WC18198) | E54: 3239000 | F54: 3583000 | G54: 3226000 | H54: 4050000 | I54: 4416000 | J54: 4589000 | K54: 4588000 | L54: 4740000 | M54: 4890000 | N54: 4621000 | O54: 4784000
A55: =VLOOKUP(B55,'PORTFOLIO RAW'!B:B,1,FALSE) -> 905075 | B55: 905075 | C55: CAMPBELL SOUP CO - EBIT & DEPRECIATION | D55: 905075(WC18198) | E55: 1595000 | F55: 1379000 | G55: 1452000 | H55: 1604000 | I55: 1542000 | J55: 1459000 | K55: 1485000 | L55: 1500000 | M55: 1397000 | N55: 1275000 | O55: 1723000
A56: =VLOOKUP(B56,'PORTFOLIO RAW'!B:B,1,FALSE) -> 937083 | B56: 937083 | C56: CONSTELLATION BRANDS - EBIT & DEPRECIATION | D56: 937083(WC18198) | E56: 898800 | F56: -185100 | G56: 183800 | H56: 449000 | I56: 639800 | J56: 603400 | K56: 632600 | L56: 2593200 | M56: 1697900 | N56: 1985100 | O56: 2693300
A57: =VLOOKUP(B57,'PORTFOLIO RAW'!B:B,1,FALSE) -> 944704 | B57: 944704 | C57: CARDINAL HEALTH, INC - EBIT & DEPRECIATION | D57: 944704(WC18198) | E57: 1695800 | F57: 2502500 | G57: 2277500 | H57: 1577400 | I57: 1924400 | J57: 2118000 | K57: 1408000 | L57: 2390000 | M57: 2559000 | N57: 3095000 | O57: 2842000
A58: =VLOOKUP(B58,'PORTFOLIO RAW'!B:B,1,FALSE) -> 902224 | B58: 902224 | C58: CATERPILLAR INC - EBIT & DEPRECIATION | D58: 902224(WC18198) | E58: 8170000 | F58: 7880000 | G58: 4339000 | H58: 7245000 | I58: 10474000 | J58: 12312000 | K58: 9408000 | L58: 9354000 | M58: 6995000 | N58: 4274000 | O58: 8136000
... A109: =VLOOKUP(B109,'PORTFOLIO RAW'!B:B,1,FALSE) -> 905016 | B109: 905016 | C109: NEXTERA ENERGY - EBIT & DEPRECIATION | D109: 905016(WC18198) | E109: 3779000 | F109: 4388000 | G109: 4466000 | H109: 5433000 | I109: 5157000 | J109: 5333000 | K109: 6151000 | L109: 7660000 | M109: 8305000 | N109: 8905000 | O109: 8456000
A110: =VLOOKUP(B110,'PORTFOLIO RAW'!B:B,1,FALSE) -> 28341F | B110: 28341F | C110: ASSURANT INC - EBIT & DEPRECIATION | D110: 28341F(WC18198) | E110: 1106527 | F110: 688445 | G110: 866621 | H110: 774673 | I110: 883380 | J110: 887863 | K110: 992285 | L110: 934749 | M110: 393402 | N110: 1031350 | O110: 609700
A111: =VLOOKUP(B111,'PORTFOLIO RAW'!B:B,1,FALSE) -> 755980 | B111: 755980 | C111: FASTENAL COMPANY - EBIT & DEPRECIATION | D111: 755980(WC18198) | E111: 415231 | F111: 490435 | G111: 337577 | H111: 471395 | I111: 619787 | J111: 728207 | K111: 777772 | L111: 861021 | M111: 915726 | N111: 900285 | O111: 1009600
A112: =VLOOKUP(B112,'PORTFOLIO RAW'!B:B,1,FALSE) -> 905994 | B112: 905994 | C112: FEDERAL REALTY INVST - EBIT & DEPRECIATION | D112: 905994(WC18198) | E112: 313615 | F112: 329277 | G112: 324908 | H112: 347746 | I112: 354419 | J112: 397990 | K112: 402389 | L112: 431400 | M112: 456027 | N112: 514954 | O112: 536540
A113: =VLOOKUP(B113,'PORTFOLIO RAW'!B:B,1,FALSE) -> 997198 | B113: 997198 | C113: FIFTH THIRD BANCORP - EBIT & DEPRECIATION | D113: 997198(WC18198) | E113: 2429000 | F113: -1889000 | G113: 1312000 | H113: 1455000 | I113: 2360000 | J113: 2670000 | K113: 3230000 | L113: 2639000 | M113: 3034000 | N113: 2823000 | O113: 3473000
A114: =VLOOKUP(B114,'PORTFOLIO RAW'!B:B,1,FALSE) -> 951503 | B114: 951503 | C114: M&T BANK CORPORATION - EBIT & DEPRECIATION | D114: 951503(WC18198) | E114: 1464522 | F114: 1359973 | G114: 949624 | H114: 1457812 | I114: 1573001 | J114: 1883709 | K114: 2025557 | L114: 1972761 | M114: 2042421 | N114: 2400036 | O114: 2624332
A115: =VLOOKUP(B115,'PORTFOLIO RAW'!B:B,1,FALSE) -> 741123 | B115: 741123 | C115: FISERV INC - EBIT & DEPRECIATION | D115: 741123(WC18198) | E115: 930000 | F115: 1241000 | G115: 1287000 | H115: 1330000 | I115: 1266000 | J115: 1417000 | K115: 1465000 | L115: 1615000 | M115: 1643000 | N115: 1866000 | O115: 1978000
A116: =VLOOKUP(B116,'PORTFOLIO RAW'!B:B,1,FALSE) -> 546814 | B116: 546814 | C116: MACY'S INC - EBIT & DEPRECIATION | D116: 546814(WC18198) | E116: 3203000 | F116: -3072000 | G116: 2279000 | H116: 2983000 | I116: 3500000 | J116: 3576000 | K116: 3700000 | L116: 3821000 | M116: 3102000 | N116: 2377000 | O116: 2819000
A117: =VLOOKUP(B117,'PORTFOLIO RAW'!B:B,1,FALSE) -> 938076 | B117: 938076 | C117: FRANKLIN RESOURCES - EBIT & DEPRECIATION | D117: 938076(WC18198) | E117: 2623574 | F117: 2439216 | G117: 1455487 | H117: 2522542 | I117: 2906287 | J117: 2858300 | K117: 3096400 | L117: 3492300 | M117: 3232900 | N117: 2584400 | O117: 2578100
A118: =VLOOKUP(B118,'PORTFOLIO RAW'!B:B,1,FALSE) -> 152594 | B118: 152594 | C118: FREEPORT-MCMORAN INC - EBIT & DEPRECIATION | D118: 152594(WC18198) | E118: 7870000 | F118: -10826000 | G118: 7539000 | H118: 10102000 | I118: 10152000 | J118: 6852000 | K118: 8100000 | L118: 4069000 | M118: -9879000 | N118: -107000 | O118: 5417000
A119: =VLOOKUP(B119,'PORTFOLIO RAW'!B:B,1,FALSE) -> 951018 | B119: 951018 | C119: GAP INC - EBIT & DEPRECIATION | D119: 951018(WC18198) | E119: 1979000 | F119: 2153000 | G119: 2471000 | H119: 2637000 | I119: 2035000 | J119: 2507000 | K119: 2690000 | L119: 2652000 | M119: 2122000 | N119: 1792000 | O119: 2057000
A120: =VLOOKUP(B120,'PORTFOLIO RAW'!B:B,1,FALSE) -> 907652 | B120: 907652 | C120: GENERAL DYNAMICS - EBIT & DEPRECIATION | D120: 907652(WC18198) | E120: 3601000 | F120: 4184000 | G120: 4246000 | H120: 4526000 | I120: 4465000 | J120: 1329000 | K120: 4266000 | L120: 4401000 | M120: 4682000 | N120: 4784000 | O120: 4635000
A121: =VLOOKUP(B121,'PORTFOLIO RAW'!B:B,1,FALSE) -> 905801 | B121: 905801 | C121: GENERAL MILLS, INC. - EBIT & DEPRECIATION | D121: 905801(WC18198) | E121: 2507000 | F121: 2714300 | G121: 2798100 | H121: 3012100 | I121: 3242700 | J121: 3104800 | K121: 3452400 | L121: 3558900 | M121: 2678800 | N121: 3323600 | O121: 3177000
A122: =VLOOKUP(B122,'PORTFOLIO RAW'!B:B,1,FALSE) -> 906511 | B122: 906511 | C122: GENUINE PARTS CO - EBIT & DEPRECIATION | D122: 906511(WC18198) | E122: 940713 | F122: 888887 | G122: 762461 | H122: 879176 | I122: 1006778 | J122: 1137797 | K122: 1205232 | L122: 1291140 | M122: 1287018 | N122: 1242911 | O122: 1218445
... A133: =VLOOKUP(B133,'PORTFOLIO RAW'!B:B,1,FALSE) -> 905077 | B133: 905077 | C133: HERSHEY CO - EBIT & DEPRECIATION | D133: 905077(WC18198) | E133: 772233 | F133: 841191 | G133: 944878 | H133: 1103684 | I133: 1272392 | J133: 1324125 | K133: 1543866 | L133: 1605173 | M133: 1227758 | N133: 1493266 | O133: 1472587
A134: =VLOOKUP(B134,'PORTFOLIO RAW'!B:B,1,FALSE) -> 699943 | B134: 699943 | C134: JUNIPER NETWORKS INC - EBIT & DEPRECIATION | D134: 699943(WC18198) | E134: NA | F134: 896365 | G134: 460434 | H134: 924789 | I134: 791254 | J134: 531400 | K134: 773800 | L134: 166700 | M134: 1112000 | N134: 1131800 | O134: 1138600
A135: =VLOOKUP(B135,'PORTFOLIO RAW'!B:B,1,FALSE) -> 542983 | B135: 542983 | C135: HOLOGIC INC - EBIT & DEPRECIATION | D135: 542983(WC18198) | E135: 181729 | F135: -21279 | G135: -1745249 | H135: 366884 | I135: 646968 | J135: 424377 | K135: -395876 | L135: 791900 | M135: 874100 | N135: 1036000 | O135: 1832900
A136: =VLOOKUP(B136,'PORTFOLIO RAW'!B:B,1,FALSE) -> 741410 | B136: 741410 | C136: UNUM GROUP - EBIT & DEPRECIATION | D136: 741410(WC18198) | E136: 1246500 | F136: 1049500 | G136: 1492200 | H136: 1548500 | I136: 481600 | J136: 1479200 | K136: 1439400 | L136: 782600 | M136: 1490600 | N136: 1615400 | O136: 1667300
A137: =VLOOKUP(B137,'PORTFOLIO RAW'!B:B,1,FALSE) -> 998171 | B137: 998171 | C137: HOME DEPOT, INC. - EBIT & DEPRECIATION | D137: 998171(WC18198) | E137: 9018000 | F137: 6116000 | G137: 6464000 | H137: 7521000 | I137: 8356000 | J137: 9537000 | K137: 10935000 | L137: 12592000 | M137: 13803000 | N137: 15436000 | O137: 16817000
A138: =VLOOKUP(B138,'PORTFOLIO RAW'!B:B,1,FALSE) -> 904842 | B138: 904842 | C138: CENTERPOINT ENERGY - EBIT & DEPRECIATION | D138: 904842(WC18198) | E138: 1851000 | F138: 1984000 | G138: 1920000 | H138: 2161000 | I138: 2613000 | J138: 2345000 | K138: 2031000 | L138: 2061000 | M138: 1930000 | N138: 2033000 | O138: 2215000
A139: =VLOOKUP(B139,'PORTFOLIO RAW'!B:B,1,FALSE) -> 916860 | B139: 916860 | C139: HUMANA INC. - EBIT & DEPRECIATION | D139: 916860(WC18198) | E139: 1520578 | F139: 1256437 | G139: 1957877 | H139: 2079722 | I139: 2614000 | J139: 2311000 | K139: 2394000 | L139: 2811000 | M139: 3064000 | N139: 2206000 | O139: 4747000
A140: =VLOOKUP(B140,'PORTFOLIO RAW'!B:B,1,FALSE) -> 951068 | B140: 951068 | C140: HUNTINGTON BANCSHR - EBIT & DEPRECIATION | D140: 951068(WC18198) | E140: 427006 | F140: 164649 | G140: -3474706 | H140: 501775 | I140: 855151 | J140: 956811 | K140: 972944 | L140: 988149 | M140: 1081019 | N140: 1206408 | O140: 1768000
A141: =VLOOKUP(B141,'PORTFOLIO RAW'!B:B,1,FALSE) -> 545725 | B141: 545725 | C141: BIOGEN INC - EBIT & DEPRECIATION | D141: 545725(WC18198) | E141: 1273000 | F141: 1669900 | G141: 1787900 | H141: 1620100 | I141: 2103100 | J141: 2257200 | K141: 3129576 | L141: 4664294 | M141: 5463300 | N141: 5885900 | O141: 6662200
A142: =VLOOKUP(B142,'PORTFOLIO RAW'!B:B,1,FALSE) -> 905052 | B142: 905052 | C142: ILLINOIS TOOL WORKS - EBIT & DEPRECIATION | D142: 905052(WC18198) | E142: 3205660 | F142: 2895326 | G142: 1947986 | H142: 2934721 | I142: 3378856 | J142: 4460000 | K142: 3213000 | L142: 3465000 | M142: 3426000 | N142: 3554000 | O142: 3992000
A143: =VLOOKUP(B143,'PORTFOLIO RAW'!B:B,1,FALSE) -> 328184 | B143: 328184 | C143: INTUIT INC - EBIT & DEPRECIATION | D143: 328184(WC18198) | E143: 858208 | F143: 966738 | G143: 979288 | H143: 1132000 | I143: 1267000 | J143: 1443000 | K143: 1472000 | L143: 1542000 | M143: 970000 | N143: 1476000 | O143: 1634000
A144: =VLOOKUP(B144,'PORTFOLIO RAW'!B:B,1,FALSE) -> 922726 | B144: 922726 | C144: INTEL CORPORATION - EBIT & DEPRECIATION | D144: 922726(WC18198) | E144: 13979000 | F144: 14066000 | G144: 10927000 | H144: 20335000 | I144: 23774000 | J144: 22566000 | K144: 20564000 | L144: 24335000 | M144: 23395000 | N144: 21122000 | O144: 26709000
A145: =VLOOKUP(B145,'PORTFOLIO RAW'!B:B,1,FALSE) -> 905050 | B145: 905050 | C145: INTL FLAVORS&FRAGRAN - EBIT & DEPRECIATION | D145: 905050(WC18198) | E145: 453007 | F145: 430516 | G145: 412892 | H145: 487544 | I145: 493512 | J145: 561835 | K145: 615204 | L145: 684482 | M145: 674760 | N145: 679175 | O145: 720375
A146: =VLOOKUP(B146,'PORTFOLIO RAW'!B:B,1,FALSE) -> 904069 | B146: 904069 | C146: INTERNATIONAL PAPER - EBIT & DEPRECIATION | D146: 904069(WC18198) | E146: 3191000 | F146: 766000 | G146: 3325000 | H146: 2921000 | I146: 3386000 | J146: 3271000 | K146: 3065000 | L146: 2955000 | M146: 3204000 | N146: 2905000 | O146: 2949000
... A166: =VLOOKUP(B166,'PORTFOLIO RAW'!B:B,1,FALSE) -> 154423 | B166: 154423 | C166: LOCKHEED MARTIN CORP - EBIT & DEPRECIATION | D166: 154423(WC18198) | E166: 5336000 | F166: 5687000 | G166: 5038000 | H166: 4700000 | I166: 4661000 | J166: 5166000 | K166: 5174000 | L166: 6250000 | M166: 6149000 | N166: 6273000 | O166: 6908000
A167: =VLOOKUP(B167,'PORTFOLIO RAW'!B:B,1,FALSE) -> 922418 | B167: 922418 | C167: LOEWS CORPORATION - EBIT & DEPRECIATION | D167: 922418(WC18198) | E167: NA | F167: 1624000 | G167: 2962000 | H167: 4235000 | I167: 3587000 | J167: 2744000 | K167: 2742000 | L167: 3207000 | M167: 1719000 | N167: 2313000 | O167: 3065000
A168: =VLOOKUP(B168,'PORTFOLIO RAW'!B:B,1,FALSE) -> 755695 | B168: 755695 | C168: CARNIVAL CORP - EBIT & DEPRECIATION | D168: 755695(WC18198) | E168: 3892000 | F168: 4040000 | G168: 3495000 | H168: 3773000 | I168: 3799000 | J168: 3165000 | K168: 2979000 | L168: 3168000 | M168: 3642000 | N168: 4789000 | O168: 4710000
A169: =VLOOKUP(B169,'PORTFOLIO RAW'!B:B,1,FALSE) -> 905620 | B169: 905620 | C169: LOWE'S COMPANIES INC - EBIT & DEPRECIATION | D169: 905620(WC18198) | E169: 6214000 | F169: 5493000 | G169: 4871000 | H169: 5249000 | I169: 4860000 | J169: 5192000 | K169: 5709000 | L169: 6384000 | M169: 6550000 | N169: 7423000 | O169: 7662000
A170: =VLOOKUP(B170,'PORTFOLIO RAW'!B:B,1,FALSE) -> 944314 | B170: 944314 | C170: DOMINION ENERGY INC - EBIT & DEPRECIATION | D170: 944314(WC18198) | E170: 7167000 | F170: 4707000 | G170: 4129000 | H170: 7199000 | I170: 4315000 | J170: 2839000 | K170: 4971000 | L170: 4531000 | M170: 5401000 | N170: 5726000 | O170: 6247000
A171: =VLOOKUP(B171,'PORTFOLIO RAW'!B:B,1,FALSE) -> 357366 | B171: 357366 | C171: MACERICH CO - EBIT & DEPRECIATION | D171: 357366(WC18198) | E171: 539443 | F171: 594357 | G171: 646487 | H171: 412969 | I171: 386372 | J171: 713082 | K171: 570001 | L171: 2120510 | M171: 1157788 | N171: 1017653 | O171: 604772
A172: =VLOOKUP(B172,'PORTFOLIO RAW'!B:B,1,FALSE) -> 516007 | B172: 516007 | C172: MGM RESORTS - EBIT & DEPRECIATION | D172: 516007(WC18198) | E172: 3404888 | F172: 677782 | G172: -359711 | H172: -278363 | I172: 4763528 | J172: 446244 | K172: 1908615 | L172: 2067670 | M172: 389798 | N172: 2329000 | O172: 2514742
A173: =VLOOKUP(B173,'PORTFOLIO RAW'!B:B,1,FALSE) -> 510493 | B173: 510493 | C173: MCCORMICK & CO INC - EBIT & DEPRECIATION | D173: 510493(WC18198) | E173: 445600 | F173: 480100 | G173: 566300 | H173: 610600 | I173: 644400 | J173: 688200 | K173: 658700 | L173: 711800 | M173: 660500 | N173: 755500 | O173: 816600
A174: =VLOOKUP(B174,'PORTFOLIO RAW'!B:B,1,FALSE) -> 921910 | B174: 921910 | C174: MCDONALD'S CORP - EBIT & DEPRECIATION | D174: 921910(WC18198) | E174: 5080700 | F174: 7777700 | G174: 8010700 | H174: 8564600 | I174: 9739800 | J174: 9940600 | K174: 10233300 | L174: 9595900 | M174: 8896500 | N174: 9212500 | O174: 10674500
A175: =VLOOKUP(B175,'PORTFOLIO RAW'!B:B,1,FALSE) -> 311759 | B175: 311759 | C175: EVEREST RE GROUP - EBIT & DEPRECIATION | D175: 311759(WC18198) | E175: NA | F175: NA | G175: NA | H175: NA | I175: NA | J175: NA | K175: 1601084 | L175: 1484648 | M175: 1244700 | N175: 1136072 | O175: 436787
A176: =VLOOKUP(B176,'PORTFOLIO RAW'!B:B,1,FALSE) -> 912588 | B176: 912588 | C176: HOST HOTELS - EBIT & DEPRECIATION | D176: 912588(WC18198) | E176: 1468000 | F176: 1371000 | G176: 786000 | H176: 818000 | I176: 1002000 | J176: 1076000 | K176: 1249000 | L176: 1650000 | M176: 1460000 | N176: 1668000 | O176: 1538000
A177: =VLOOKUP(B177,'PORTFOLIO RAW'!B:B,1,FALSE) -> 904780 | B177: 904780 | C177: MARSH & MCLENNAN CO. - EBIT & DEPRECIATION | D177: 904780(WC18198) | E177: 1556000 | F177: 703000 | G177: 891000 | H177: 1316000 | I177: 1926000 | J177: 2226000 | K177: 2498000 | L177: 2610000 | M177: 2893000 | N177: 3107000 | O177: 3361000
A178: =VLOOKUP(B178,'PORTFOLIO RAW'!B:B,1,FALSE) -> 905624 | B178: 905624 | C178: MASCO CORP - EBIT & DEPRECIATION | D178: 905624(WC18198) | E178: 1276000 | F178: 255000 | G178: 338000 | H178: -247000 | I178: 45000 | J178: 510000 | K178: 855000 | L178: 967000 | M178: 1061000 | N178: 1218000 | O178: 1314000
A179: =VLOOKUP(B179,'PORTFOLIO RAW'!B:B,1,FALSE) -> 130062 | B179: 130062 | C179: MARTIN MARIETTA MAT - EBIT & DEPRECIATION | D179: 130062(WC18198) | E179: 591853 | F179: 488727 | G179: 368113 | H179: 377700 | I179: 332600 | J179: 333463 | K179: 391454 | L179: 538000 | M179: 753700 | N179: 974000 | O179: 1007600
A180: =VLOOKUP(B180,'PORTFOLIO RAW'!B:B,1,FALSE) -> 286738 | B180: 286738 | C180: METLIFE INC - EBIT & DEPRECIATION | D180: 286738(WC18198) | E180: 6543000 | F180: 6655000 | G180: -2789000 | H180: 5144000 | I180: 11650000 | J180: 2530000 | K180: 6048000 | L180: 10733000 | M180: 9371000 | N180: 1658000 | O180: 5460000
A181: =VLOOKUP(B181,'PORTFOLIO RAW'!B:B,1,FALSE) -> 771830 | B181: 771830 | C181: MAXIM INTEGRATED PRD - EBIT & DEPRECIATION | D181: 771830(WC18198) | E181: 518323 | F181: 644687 | G181: 240042 | H181: NA | I181: 876208 | J181: 747546 | K181: 792515 | L181: 678519 | M181: 578113 | N181: 562391 | O181: 878181
A182: =VLOOKUP(B182,'PORTFOLIO RAW'!B:B,1,FALSE) -> 312367 | B182: 312367 | C182: ACTIVISION BLIZZARD - EBIT & DEPRECIATION | D182: 312367(WC18198) | E182: 241000 | F182: 201000 | G182: 343000 | H182: 695000 | I182: 1483000 | J182: 1579000 | K182: 1675000 | L182: 1342000 | M182: 1825000 | N182: 2487000 | O182: 2516000
A183: =VLOOKUP(B183,'PORTFOLIO RAW'!B:B,1,FALSE) -> 912635 | B183: 912635 | C183: CVS HEALTH CORP - EBIT & DEPRECIATION | D183: 912635(WC18198) | E183: 5921600 | F183: 7340700 | G183: 7832000 | H183: 7637000 | I183: 7902000 | J183: 9156000 | K183: 9939000 | L183: 10224000 | M183: 11586000 | N183: 12210000 | O183: 11847000
A184: =VLOOKUP(B184,'PORTFOLIO RAW'!B:B,1,FALSE) -> 152533 | B184: 152533 | C184: LAB CORP OF AMERICA - EBIT & DEPRECIATION | D184: 152533(WC18198) | E184: 943800 | F184: 1023000 | G184: 1128800 | H184: 1178600 | I184: 1175500 | J184: 1247100 | K184: 1225300 | L184: 1167400 | M184: 1454800 | N184: 1815900 | O184: 1891900
A185: =VLOOKUP(B185,'PORTFOLIO RAW'!B:B,1,FALSE) -> 719643 | B185: 719643 | C185: MICROSOFT CORP - EBIT & DEPRECIATION | D185: 719643(WC18198) | E185: 21575000 | F185: 25870000 | G185: 22421000 | H185: 27671000 | I185: 30903000 | J185: 25405000 | K185: 31236000 | L185: 33629000 | M185: 25245000 | N185: 27616000 | O185: 34149000
A186: =VLOOKUP(B186,'PORTFOLIO RAW'!B:B,1,FALSE) -> 999506 | B186: 999506 | C186: MICRON TECHNOLOGY - EBIT & DEPRECIATION | D186: 999506(WC18198) | E186: 1590000 | F186: 531000 | G186: 470000 | H186: 4103000 | I186: 2780000 | J186: 1531000 | K186: 3320000 | L186: 5188000 | M186: 5647000 | N186: 3136000 | O186: 9663000
A187: =VLOOKUP(B187,'PORTFOLIO RAW'!B:B,1,FALSE) -> 328228 | B187: 328228 | C187: MICROCHIP TECHNOLOGY - EBIT & DEPRECIATION | D187: 328228(WC18198) | E187: 522677 | F187: 459027 | G187: 357565 | H187: 359020 | I187: 598674 | J187: 513580 | K187: 397809 | L187: 670386 | M187: 686558 | N187: 668856 | O187: 705563
A188: =VLOOKUP(B188,'PORTFOLIO RAW'!B:B,1,FALSE) -> 902172 | B188: 902172 | C188: 3M COMPANY - EBIT & DEPRECIATION | D188: 902172(WC18198) | E188: 7397000 | F188: 6476000 | G188: 5946000 | H188: 7057000 | I188: 7452000 | J188: 7832000 | K188: 8035000 | L188: 8536000 | M188: 8377000 | N188: 8726000 | O188: 9510000
A189: =VLOOKUP(B189,'PORTFOLIO RAW'!B:B,1,FALSE) -> 325475 | B189: 325475 | C189: MOHAWK INDUSTRIES - EBIT & DEPRECIATION | D189: 325475(WC18198) | E189: 1065023 | F189: -856062 | G189: 352322 | H189: 615072 | I189: 599225 | J189: 711524 | K189: 846688 | L189: 1107668 | M189: 1182594 | N189: 1691139 | O189: 1795640
A190: =VLOOKUP(B190,'PORTFOLIO RAW'!B:B,1,FALSE) -> 905010 | B190: 905010 | C190: XCEL ENERGY INC - EBIT & DEPRECIATION | D190: 905010(WC18198) | E190: 2245460 | F190: 2378197 | G190: 2394044 | H190: 2544998 | I190: 2778017 | J190: 2851124 | K190: 3047186 | L190: 3209649 | M190: 3308796 | N190: 3719944 | O190: 3873000
A191: =VLOOKUP(B191,'PORTFOLIO RAW'!B:B,1,FALSE) -> 902230 | B191: 902230 | C191: FORD MOTOR COMPANY - EBIT & DEPRECIATION | D191: 902230(WC18198) | E191: 19950000 | F191: 8040000 | G191: 17862000 | H191: 18920000 | I191: 18205000 | J191: 17332000 | K191: 16107000 | L191: 13986000 | M191: 19654000 | N191: 17741000 | O191: 20398000
A192: =VLOOKUP(B192,'PORTFOLIO RAW'!B:B,1,FALSE) -> 884383 | B192: 884383 | C192: NATL OILWELL VARCO - EBIT & DEPRECIATION | D192: 884383(WC18198) | E192: 2293300 | F192: 3387800 | G192: 2704000 | H192: 2918000 | I192: 3471000 | J192: 4124000 | K192: 4149000 | L192: 4320000 | M192: 248000 | N192: -1794000 | O192: 413000
A193: =VLOOKUP(B193,'PORTFOLIO RAW'!B:B,1,FALSE) -> 867422 | B193: 867422 | C193: NETAPP INC. - EBIT & DEPRECIATION | D193: 867422(WC18198) | E193: 482203 | F193: 534873 | G193: 242232 | H193: 687100 | I193: 1035600 | J193: 1080200 | K193: 1002900 | L193: 1110900 | M193: 1062000 | N193: 673000 | O193: 943000
...

Sheet EQIT
A1: Equity
B2: Code | C2: Name | D2: Code | E2: 2007 | F2: 2008 | G2: 2009 | H2: 2010 | I2: 2011 | J2: 2012 | K2: 2013 | L2: 2014 | M2: 2015 | N2: 2016 | O2: 2017
A3: =VLOOKUP(B3,'PORTFOLIO RAW'!B:B,1,FALSE) -> 891399 | B3: 891399 | C3: AMAZON.COM INC - COMMON SHAREHOLDERS' EQUITY | D3: 891399(WC03501) | E3: 1197000 | F3: 2672000 | G3: 5257000 | H3: 6864000 | I3: 7757000 | J3: 8192000 | K3: 9746000 | L3: 10741000 | M3: 13384000 | N3: 19285000 | O3: 27709000
A4: =VLOOKUP(B4,'PORTFOLIO RAW'!B:B,1,FALSE) -> 916328 | B4: 916328 | C4: ABBOTT LABORATORIES - COMMON SHAREHOLDERS' EQUITY | D4: 916328(WC03501) | E4: 17778540 | F4: 17479551 | G4: 22855627 | H4: 22388135 | I4: 24439833 | J4: 26720961 | K4: 25171000 | L4: 21526000 | M4: 21211000 | N4: 20538000 | O4: 30897000
A5: =VLOOKUP(B5,'PORTFOLIO RAW'!B:B,1,FALSE) -> 545101 | B5: 545101 | C5: AES CORP - COMMON SHAREHOLDERS' EQUITY | D5: 545101(WC03501) | E5: 3164000 | F5: 3669000 | G5: 4675000 | H5: 6473000 | I5: 5946000 | J5: 4569000 | K5: 4330000 | L5: 4272000 | M5: 3149000 | N5: 2794000 | O5: 2465000
A6: =VLOOKUP(B6,'PORTFOLIO RAW'!B:B,1,FALSE) -> 906187 | B6: 906187 | C6: INT'L BUSINESS MACHS - COMMON SHAREHOLDERS' EQUITY | D6: 906187(WC03501) | E6: 28469000 | F6: 13465000 | G6: 22637000 | H6: 23046000 | I6: 20139000 | J6: 18860000 | K6: 22792000 | L6: 11869000 | M6: 14262000 | N6: 18246000 | O6: 17594000
A7: =VLOOKUP(B7,'PORTFOLIO RAW'!B:B,1,FALSE) -> 936365 | B7: 936365 | C7: ADVANCED MICRO - COMMON SHAREHOLDERS' EQUITY | D7: 936365(WC03501) | E7: 2990000 | F7: -82000 | G7: 648000 | H7: 1013000 | I7: 1590000 | J7: 538000 | K7: 544000 | L7: 187000 | M7: -412000 | N7: 416000 | O7: 611000
A8: =VLOOKUP(B8,'PORTFOLIO RAW'!B:B,1,FALSE) -> 749382 | B8: 749382 | C8: ADOBE INC - COMMON SHAREHOLDERS' EQUITY | D8: 749382(WC03501) | E8: 4649982 | F8: 4410354 | G8: 4890568 | H8: 5192387 | I8: 5783113 | J8: 6665182 | K8: 6724634 | L8: 6775905 | M8: 7001580 | N8: 7424835 | O8: 8459869
A9: =VLOOKUP(B9,'PORTFOLIO RAW'!B:B,1,FALSE) -> 905271 | B9: 905271 | C9: AIR PRODUCTS & CHEMS - COMMON SHAREHOLDERS' EQUITY | D9: 905271(WC03501) | E9: 5495600 | F9: 5030700 | G9: 4791900 | H9: 5546900 | I9: 5795800 | J9: 6477200 | K9: 7042100 | L9: 7365800 | M9: 7249000 | N9: 7079600 | O9: 10086200
A10: =VLOOKUP(B10,'PORTFOLIO RAW'!B:B,1,FALSE) -> 894371 | B10: 894371 | C10: BOSTON PROPERTIES - COMMON SHAREHOLDERS' EQUITY | D10: 894371(WC03501) | E10: 3668825 | F10: 3531267 | G10: 4446002 | H10: 4372643 | I10: 4865998 | J10: 5097065 | K10: 5541153 | L10: 5697298 | M10: 5709435 | N10: 5586295 | O10: 5613957
A11: =VLOOKUP(B11,'PORTFOLIO RAW'!B:B,1,FALSE) -> 322677 | B11: 322677 | C11: ALLSTATE CORP - COMMON SHAREHOLDERS' EQUITY | D11: 322677(WC03501) | E11: 20963000 | F11: 16379000 | G11: 17562000 | H11: 18081000 | I11: 17311000 | J11: 17746000 | K11: 19054000 | L11: 18632000 | M11: 17600000 | N11: 17715000 | O11: 19084000
A12: =VLOOKUP(B12,'PORTFOLIO RAW'!B:B,1,FALSE) -> 906191 | B12: 906191 | C12: HONEYWELL INTERNATNL - COMMON SHAREHOLDERS' EQUITY | D12: 906191(WC03501) | E12: 9222000 | F12: 7187000 | G12: 8844000 | H12: 10666000 | I12: 10806000 | J12: 12975000 | K12: 17467000 | L12: 17657000 | M12: 18283000 | N12: 19369000 | O12: 17276000
A13: =VLOOKUP(B13,'PORTFOLIO RAW'!B:B,1,FALSE) -> 938692 | B13: 938692 | C13: AMGEN INC - COMMON SHAREHOLDERS' EQUITY | D13: 938692(WC03501) | E13: 17869000 | F13: 20386000 | G13: 22667000 | H13: 23944000 | I13: 19029000 | J13: 19060000 | K13: 22096000 | L13: 25778000 | M13: 28083000 | N13: 29875000 | O13: 25241000
A14: =VLOOKUP(B14,'PORTFOLIO RAW'!B:B,1,FALSE) -> 905802 | B14: 905802 | C14: HESS CORPORATION - COMMON SHAREHOLDERS' EQUITY | D14: 905802(WC03501) | E14: 9760000 | F14: 12307000 | G14: 13384000 | H14: 16689000 | I14: 18516000 | J14: 21090000 | K14: 24720000 | L14: 22205000 | M14: 19386000 | N14: 14533000 | O14: 11050000
... A109: =VLOOKUP(B109,'PORTFOLIO RAW'!B:B,1,FALSE) -> 905016 | B109: 905016 | C109: NEXTERA ENERGY - COMMON SHAREHOLDERS' EQUITY | D109: 905016(WC03501) | E109: 10735000 | F109: 11681000 | G109: 12967000 | H109: 14461000 | I109: 14943000 | J109: 16068000 | K109: 18040000 | L109: 19916000 | M109: 22574000 | N109: 24341000 | O109: 28208000
A110: =VLOOKUP(B110,'PORTFOLIO RAW'!B:B,1,FALSE) -> 28341F | B110: 28341F | C110: ASSURANT INC - COMMON SHAREHOLDERS' EQUITY | D110: 28341F(WC03501) | E110: 4065519 | F110: 4187905 | G110: 4658699 | H110: 4367282 | I110: 4313163 | J110: 5185366 | K110: 4280981 | L110: 4361631 | M110: 4006090 | N110: 3618201 | O110: 3671500
A111: =VLOOKUP(B111,'PORTFOLIO RAW'!B:B,1,FALSE) -> 755980 | B111: 755980 | C111: FASTENAL COMPANY - COMMON SHAREHOLDERS' EQUITY | D111: 755980(WC03501) | E111: 1010161 | F111: 1142259 | G111: 1190843 | H111: 1282512 | I111: 1458976 | J111: 1560360 | K111: 1772697 | L111: 1915217 | M111: 1801289 | N111: 1933094 | O111: 2096900
A112: =VLOOKUP(B112,'PORTFOLIO RAW'!B:B,1,FALSE) -> 905994 | B112: 905994 | C112: FEDERAL REALTY INVST - COMMON SHAREHOLDERS' EQUITY | D112: 905994(WC03501) | E112: 1105438 | F112: 1104605 | G112: 1167340 | H112: 1139836 | I112: 1206095 | J112: 1276815 | K112: 1438163 | L112: 1594404 | M112: 1653752 | N112: 1966736 | O112: 2106709
A113: =VLOOKUP(B113,'PORTFOLIO RAW'!B:B,1,FALSE) -> 997198 | B113: 997198 | C113: FIFTH THIRD BANCORP - COMMON SHAREHOLDERS' EQUITY | D113: 997198(WC03501) | E113: 9152000 | F113: 7836000 | G113: 9678000 | H113: 10232000 | I113: 12790000 | J113: 13305000 | K113: 13555000 | L113: 14295000 | M113: 14508000 | N113: 14874000 | O113: 15034000
A114: =VLOOKUP(B114,'PORTFOLIO RAW'!B:B,1,FALSE) -> 951503 | B114: 951503 | C114: M&T BANK CORPORATION - COMMON SHAREHOLDERS' EQUITY | D114: 951503(WC03501) | E114: 6485256 | F114: 6184731 | G114: 6974907 | H114: 7579695 | I114: 8406624 | J114: 9321093 | K114: 10424032 | L114: 11104396 | M114: 14941789 | N114: 15255122 | O114: 15019319
A115: =VLOOKUP(B115,'PORTFOLIO RAW'!B:B,1,FALSE) -> 741123 | B115: 741123 | C115: FISERV INC - COMMON SHAREHOLDERS' EQUITY | D115: 741123(WC03501) | E115: 2467000 | F115: 2594000 | G115: 3026000 | H115: 3229000 | I115: 3258000 | J115: 3417000 | K115: 3585000 | L115: 3295000 | M115: 2660000 | N115: 2541000 | O115: 2731000
A116: =VLOOKUP(B116,'PORTFOLIO RAW'!B:B,1,FALSE) -> 546814 | B116: 546814 | C116: MACY'S INC - COMMON SHAREHOLDERS' EQUITY | D116: 546814(WC03501) | E116: 9907000 | F116: 4646000 | G116: 4701000 | H116: 5530000 | I116: 5933000 | J116: 6051000 | K116: 6249000 | L116: 5378000 | M116: 4250000 | N116: 4323000 | O116: 5673000
A117: =VLOOKUP(B117,'PORTFOLIO RAW'!B:B,1,FALSE) -> 938076 | B117: 938076 | C117: FRANKLIN RESOURCES - COMMON SHAREHOLDERS' EQUITY | D117: 938076(WC03501) | E117: 7332275 | F117: 7074364 | G117: 7632173 | H117: 7726994 | I117: 8524731 | J117: 9201300 | K117: 10073100 | L117: 11584100 | M117: 11841000 | N117: 11935800 | O117: 12620000
A118: =VLOOKUP(B118,'PORTFOLIO RAW'!B:B,1,FALSE) -> 152594 | B118: 152594 | C118: FREEPORT-MCMORAN INC - COMMON SHAREHOLDERS' EQUITY | D118: 152594(WC03501) | E118: 14259000 | F118: 2066000 | G118: 6244000 | H118: 12504000 | I118: 15642000 | J118: 17543000 | K118: 20934000 | L118: 18287000 | M118: 7828000 | N118: 6051000 | O118: 7977000
A119: =VLOOKUP(B119,'PORTFOLIO RAW'!B:B,1,FALSE) -> 951018 | B119: 951018 | C119: GAP INC - COMMON SHAREHOLDERS' EQUITY | D119: 951018(WC03501) | E119: 4274000 | F119: 4387000 | G119: 4891000 | H119: 4080000 | I119: 2755000 | J119: 2894000 | K119: 3062000 | L119: 2983000 | M119: 2545000 | N119: 2904000 | O119: 3144000
A120: =VLOOKUP(B120,'PORTFOLIO RAW'!B:B,1,FALSE) -> 907652 | B120: 907652 | C120: GENERAL DYNAMICS - COMMON SHAREHOLDERS' EQUITY | D120: 907652(WC03501) | E120: 11768000 | F120: 10053000 | G120: 12423000 | H120: 13316000 | I120: 13232000 | J120: 11390000 | K120: 14501000 | L120: 11829000 | M120: 10738000 | N120: 10976000 | O120: 11435000
A121: =VLOOKUP(B121,'PORTFOLIO RAW'!B:B,1,FALSE) -> 905801 | B121: 905801 | C121: GENERAL MILLS, INC. - COMMON SHAREHOLDERS' EQUITY | D121: 905801(WC03501) | E121: 5319000 | F121: 6215800 | G121: 5174700 | H121: 5402900 | I121: 6365500 | J121: 6421700 | K121: 6672200 | L121: 6534800 | M121: 4996700 | N121: 4930200 | O121: 4327900
A122: =VLOOKUP(B122,'PORTFOLIO RAW'!B:B,1,FALSE) -> 906511 | B122: 906511 | C122: GENUINE PARTS CO - COMMON SHAREHOLDERS' EQUITY | D122: 906511(WC03501) | E122: 2716716 | F122: 2324332 | G122: 2621330 | H122: 2793819 | I122: 2783235 | J122: 2997887 | K122: 3349074 | L122: 3301248 | M122: 3146567 | N122: 3193728 | O122: 3412152
... A236: =VLOOKUP(B236,'PORTFOLIO RAW'!B:B,1,FALSE) -> 933974 | B236: 933974 | C236: TRAVELERS COS - COMMON SHAREHOLDERS' EQUITY | D236: 933974(WC03501) | E236: 25885000 | F236: 25374000 | G236: 25475000 | H236: 23549000 | I236: 21606000 | J236: 22302000 | K236: 23474000 | L236: 22870000 | M236: 22309000 | N236: 22491000 | O236: 22777000
A237: =VLOOKUP(B237,'PORTFOLIO RAW'!B:B,1,FALSE) -> 14015T | B237: 14015T | C237: FIDELITY NATNL INF - COMMON SHAREHOLDERS' EQUITY | D237: 14015T(WC03501) | E237: 3781179 | F237: 3532800 | G237: 8308900 | H237: 6403200 | I237: 6503000 | J237: 6640900 | K237: 6580500 | L237: 6556700 | M237: 9321000 | N237: 9741000 | O237: 10835000
A238: =VLOOKUP(B238,'PORTFOLIO RAW'!B:B,1,FALSE) -> 905019 | B238: 905019 | C238: MERCK & CO INC - COMMON SHAREHOLDERS' EQUITY | D238: 905019(WC03501) | E238: 18184700 | F238: 18758300 | G238: 59058000 | H238: 54376000 | I238: 54517000 | J238: 53020000 | K238: 49765000 | L238: 48647000 | M238: 44676000 | N238: 40088000 | O238: 34336000
A239: =VLOOKUP(B239,'PORTFOLIO RAW'!B:B,1,FALSE) -> 912090 | B239: 912090 | C239: SCHLUMBERGER LIMITED - COMMON SHAREHOLDERS' EQUITY | D239: 912090(WC03501) | E239: 14876000 | F239: 16863000 | G239: 19120000 | H239: 31226000 | I239: 31263000 | J239: 34751000 | K239: 39469000 | L239: 37850000 | M239: 35633000 | N239: 41078000 | O239: 36842000
A240: =VLOOKUP(B240,'PORTFOLIO RAW'!B:B,1,FALSE) -> 755741 | B240: 755741 | C240: CHARLES SCHWAB CORP - COMMON SHAREHOLDERS' EQUITY | D240: 755741(WC03501) | E240: 3732000 | F240: 4061000 | G240: 5073000 | H240: 6226000 | I240: 7714000 | J240: 8704000 | K240: 9496000 | L240: 10918000 | M240: 11917000 | N240: 13586000 | O240: 15675000
A241: =VLOOKUP(B241,'PORTFOLIO RAW'!B:B,1,FALSE) -> 14361V | B241: 14361V | C241: ZIMMER BIOMET - COMMON SHAREHOLDERS' EQUITY | D241: 14361V(WC03501) | E241: 5449600 | F241: 5650300 | G241: 5638700 | H241: 5771300 | I241: 5507200 | J241: 5860900 | K241: 6297300 | L241: 6520800 | M241: 9887900 | N241: 9668900 | O241: 11735800
A242: =VLOOKUP(B242,'PORTFOLIO RAW'!B:B,1,FALSE) -> 154680 | B242: 154680 | C242: AMERISOURCEBERGEN - COMMON SHAREHOLDERS' EQUITY | D242: 154680(WC03501) | E242: 3099720 | F242: 2710045 | G242: 2716469 | H242: 2954297 | I242: 2866858 | J242: 2456712 | K242: 2319745 | L242: 1956899 | M242: 633520 | N242: 2129404 | O242: 2064461
A243: =VLOOKUP(B243,'PORTFOLIO RAW'!B:B,1,FALSE) -> 14698C | B243: 14698C | C243: PRINCIPAL FINL GROUP - COMMON SHAREHOLDERS' EQUITY | D243: 14698C(WC03501) | E243: 6854600 | F243: 6393600 | G243: 8284000 | H243: 9045100 | I243: 8709200 | J243: 8267500 | K243: 9434200 | L243: 10183900 | M243: 9311600 | N243: 10227300 | O243: 11335900
A244: =VLOOKUP(B244,'PORTFOLIO RAW'!B:B,1,FALSE) -> 905361 | B244: 905361 | C244: SHERWIN-WILLIAMS CO - COMMON SHAREHOLDERS' EQUITY | D244: 905361(WC03501) | E244: 1785727 | F244: 1605648 | G244: 1490950 | H244: 1609440 | I244: 1516919 | J244: 1690718 | K244: 1734129 | L244: 996470 | M244: 867910 | N244: 1878441 | O244: 3692188
A245: =VLOOKUP(B245,'PORTFOLIO RAW'!B:B,1,FALSE) -> 357834 | B245: 357834 | C245: SIMON PROPERTY GROUP - COMMON SHAREHOLDERS' EQUITY | D245: 357834(WC03501) | E245: 2833974 | F245: 2614638 | G245: 4412433 | H245: 4785405 | I245: 4604619 | J245: 5865884 | K245: 5805016 | L245: 5049115 | M245: 4427731 | N245: 4267043 | O245: 3643091
A246: =VLOOKUP(B246,'PORTFOLIO RAW'!B:B,1,FALSE) -> 906400 | B246: 906400 | C246: SNAP-ON INC - COMMON SHAREHOLDERS' EQUITY | D246: 906400(WC03501) | E246: 1280100 | F246: 1186500 | G246: 1290000 | H246: 1388500 | I246: 1530900 | J246: 1802100 | K246: 2113200 | L246: 2207800 | M246: 2412700 | N246: 2617200 | O246: 2953900
A247: =VLOOKUP(B247,'PORTFOLIO RAW'!B:B,1,FALSE) -> 14861V | B247: 14861V | C247: PRUDENTIAL FINANCIAL - COMMON SHAREHOLDERS' EQUITY | D247: 14861V(WC03501) | E247: 23057000 | F247: 20157000 | G247: 24684000 | H247: 29270000 | I247: 31588000 | J247: 27173000 | K247: 24934000 | L247: 22519000 | M247: 26117000 | N247: 27692000 | O247: 34101000
A248: =VLOOKUP(B248,'PORTFOLIO RAW'!B:B,1,FALSE) -> 14806F | B248: 14806F | C248: ADVANCE AUTO PARTS - COMMON SHAREHOLDERS' EQUITY | D248: 14806F(WC03501) | E248: 1023795 | F248: 1075166 | G248: 1282365 | H248: 1039374 | I248: 847914 | J248: 1210694 | K248: 1516205 | L248: 2002912 | M248: 2460648 | N248: 2916192 | O248: 3415196
A249: =VLOOKUP(B249,'PORTFOLIO RAW'!B:B,1,FALSE) -> 902324 | B249: 902324 | C249: EDISON INTERNATIONAL - COMMON SHAREHOLDERS' EQUITY | D249: 902324(WC03501) | E249: 8444000 | F249: 9517000 | G249: 9841000 | H249: 10583000 | I249: 10055000 | J249: 9432000 | K249: 9925000 | L249: 10960000 | M249: 11368000 | N249: 11996000 | O249: 11671000
A250: =VLOOKUP(B250,'PORTFOLIO RAW'!B:B,1,FALSE) -> 902325 | B250: 902325 | C250: SOUTHERN CO - COMMON SHAREHOLDERS' EQUITY | D250: 902325(WC03501) | E250: 12385000 | F250: 13276000 | G250: 14878000 | H250: 16202000 | I250: 17578000 | J250: 18297000 | K250: 19008000 | L250: 19949000 | M250: 20592000 | N250: 24758000 | O250: 24167000
A251: =VLOOKUP(B251,'PORTFOLIO RAW'!B:B,1,FALSE) -> 992305 | B251: 992305 | C251: BB&T CORPORATION - COMMON SHAREHOLDERS' EQUITY | D251: 992305(WC03501) | E251: 12632000 | F251: 12955000 | G251: 16191000 | H251: 16436000 | I251: 17418000 | J251: 18983000 | K251: 20156000 | L251: 21663000 | M251: 24631000 | N251: 26741000 | O251: 26508000
A252: =VLOOKUP(B252,'PORTFOLIO RAW'!B:B,1,FALSE) -> 905647 | B252: 905647 | C252: SOUTHWEST AIRLINES - COMMON SHAREHOLDERS' EQUITY | D252: 905647(WC03501) | E252: 6941000 | F252: 4953000 | G252: 5466000 | H252: 6237000 | I252: 6877000 | J252: 6992000 | K252: 7336000 | L252: 6775000 | M252: 7358000 | N252: 8441000 | O252: 10430000
A253: =VLOOKUP(B253,'PORTFOLIO RAW'!B:B,1,FALSE) -> 945388 | B253: 945388 | C253: AT&T INC - COMMON SHAREHOLDERS' EQUITY | D253: 945388(WC03501) | E253: 115367000 | F253: 96347000 | G253: 101900000 | H253: 111647000 | I253: 105534000 | J253: 92362000 | K253: 90988000 | L253: 86370000 | M253: 122671000 | N253: 123135000 | O253: 140861000
A254: =VLOOKUP(B254,'PORTFOLIO RAW'!B:B,1,FALSE) -> 905024 | B254: 905024 | C254: CHEVRON CORPORATION - COMMON SHAREHOLDERS' EQUITY | D254: 905024(WC03501) | E254: 77089000 | F254: 86648000 | G254: 91914000 | H254: 105081000 | I254: 121382000 | J254: 136524000 | K254: 149113000 | L254: 155028000 | M254: 152716000 | N254: 145556000 | O254: 148124000
A255: =VLOOKUP(B255,'PORTFOLIO RAW'!B:B,1,FALSE) -> 951052 | B255: 951052 | C255: STATE STREET CORP - COMMON SHAREHOLDERS' EQUITY | D255: 951052(WC03501) | E255: 11299000 | F255: 10891000 | G255: 14491000 | H255: 17787000 | I255: 18898000 | J255: 20380000 | K255: 19887000 | L255: 19512000 | M255: 18400000 | N255: 18023000 | O255: 19121000
A256: =VLOOKUP(B256,'PORTFOLIO RAW'!B:B,1,FALSE) -> 326143 | B256: 326143 | C256: STARBUCKS CORP - COMMON SHAREHOLDERS' EQUITY | D256: 326143(WC03501) | E256: 2284117 | F256: 2490900 | G256: 3045700 | H256: 3674700 | I256: 4384900 | J256: 5109000 | K256: 4480200 | L256: 5272000 | M256: 5818000 | N256: 5884000 | O256: 5450100
A257: =VLOOKUP(B257,'PORTFOLIO RAW'!B:B,1,FALSE) -> 905792 | B257: 905792 | C257: PUBLIC STORAGE, INC - COMMON SHAREHOLDERS' EQUITY | D257: 905792(WC03501) | E257: 5235629 | F257: 5291137 | G257: 5528630 | H257: 5280571 | I257: 5176938 | J257: 5256256 | K257: 5229230 | L257: 5155796 | M257: 5115641 | N257: 5044410 | O257: 4915009
A258: =VLOOKUP(B258,'PORTFOLIO RAW'!B:B,1,FALSE) -> 981722 | B258: 981722 | C258: STRYKER CORPORATION - COMMON SHAREHOLDERS' EQUITY | D258: 981722(WC03501) | E258: 5378500 | F258: 5406700 | G258: 6595100 | H258: 7173600 | I258: 7683000 | J258: 8597000 | K258: 9047000 | L258: 8595000 | M258: 8511000 | N258: 9550000 | O258: 9966000
A259: =VLOOKUP(B259,'PORTFOLIO RAW'!B:B,1,FALSE) -> 922725 | B259: 922725 | C259: SUNTRUST BANKS INC - COMMON SHAREHOLDERS' EQUITY | D259: 922725(WC03501) | E259: 17552518 | F259: 17166406 | G259: 17495055 | H259: 18188000 | I259: 19791000 | J259: 20260000 | K259: 20697000 | L259: 21780000 | M259: 22212000 | N259: 22393000 | O259: 22679000
A260: =VLOOKUP(B260,'PORTFOLIO RAW'!B:B,1,FALSE) -> 541900 | B260: 541900 | C260: SYMANTEC CORP - COMMON SHAREHOLDERS' EQUITY | D260: 541900(WC03501) | E260: 11601513 | F260: 10973183 | G260: 3947988 | H260: 4548000 | I260: 4528000 | J260: 5094000 | K260: 5421000 | L260: 5797000 | M260: 5935000 | N260: 3676000 | O260: 3487000
... A283: =VLOOKUP(B283,'PORTFOLIO RAW'!B:B,1,FALSE) -> 904869 | B283: 904869 | C283: WHIRLPOOL CORP - COMMON SHAREHOLDERS' EQUITY | D283: 904869(WC03501) | E283: 3911000 | F283: 3006000 | G283: 3664000 | H283: 4226000 | I283: 4181000 | J283: 4260000 | K283: 4924000 | L283: 4885000 | M283: 4743000 | N283: 4773000 | O283: 4198000
A284: =VLOOKUP(B284,'PORTFOLIO RAW'!B:B,1,FALSE) -> 26406N | B284: 26406N | C284: WYNN RESORTS, LTD - COMMON SHAREHOLDERS' EQUITY | D284: 26406N(WC03501) | E284: 1948159 | F284: 1592522 | G284: 3034338 | H284: 2237948 | I284: 2089022 | J284: -259037 | K284: -184507 | L284: -28779 | M284: -111979 | N284: 157949 | O284: 947846
A285: =VLOOKUP(B285,'PORTFOLIO RAW'!B:B,1,FALSE) -> 26393N | B285: 26393N | C285: CME GROUP INC - COMMON SHAREHOLDERS' EQUITY | D285: 26393N(WC03501) | E285: 12305637 | F285: 18688569 | G285: 19301000 | H285: 20060100 | I285: 21552000 | J285: 21419100 | K285: 21154800 | L285: 20923500 | M285: 20551800 | N285: 20340700 | O285: 22411800
A286: =VLOOKUP(B286,'PORTFOLIO RAW'!B:B,1,FALSE) -> 922407 | B286: 922407 | C286: WILLIAMS COMPANIES - COMMON SHAREHOLDERS' EQUITY | D286: 922407(WC03501) | E286: 6375000 | F286: 8440000 | G286: 8447000 | H286: 7288000 | I286: 1793000 | J286: 4752000 | K286: 4864000 | L286: 8777000 | M286: 6148000 | N286: 4643000 | O286: 9656000
A287: =VLOOKUP(B287,'PORTFOLIO RAW'!B:B,1,FALSE) -> 906979 | B287: 906979 | C287: ALLIANT ENERGY CORP - COMMON SHAREHOLDERS' EQUITY | D287: 906979(WC03501) | E287: 2681200 | F287: 2823500 | G287: 2772600 | H287: 2893600 | I287: 3013000 | J287: 3134900 | K287: 3281400 | L287: 3438700 | M287: 3724100 | N287: 3862000 | O287: 4182200
A288: =VLOOKUP(B288,'PORTFOLIO RAW'!B:B,1,FALSE) -> 877723 | B288: 877723 | C288: CARMAX INC - COMMON SHAREHOLDERS' EQUITY | D288: 877723(WC03501) | E288: 1247375 | F288: 1488926 | G288: 1593067 | H288: 1933582 | I288: 2291630 | J288: 2673112 | K288: 3019167 | L288: 3316997 | M288: 3156785 | N288: 2904786 | O288: 3108580
A289: =VLOOKUP(B289,'PORTFOLIO RAW'!B:B,1,FALSE) -> 543542 | B289: 543542 | C289: XILINX INC - COMMON SHAREHOLDERS' EQUITY | D289: 543542(WC03501) | E289: 1772740 | F289: 1671823 | G289: 1737900 | H289: 2120470 | I289: 2414617 | J289: 2707685 | K289: 2963296 | L289: 2787681 | M289: 2635541 | N289: 2602787 | O289: 2509039
A290: =VLOOKUP(B290,'PORTFOLIO RAW'!B:B,1,FALSE) -> 26276P | B290: 26276P | C290: CIMAREX ENERGY CO - COMMON SHAREHOLDERS' EQUITY | D290: 26276P(WC03501) | E290: 3259287 | F290: 2349365 | G290: 2038106 | H290: 2609832 | I290: 3130613 | J290: 3474736 | K290: 4022208 | L290: 4500632 | M290: 2797678 | N290: 2360064 | O290: 2568278
A291: =VLOOKUP(B291,'PORTFOLIO RAW'!B:B,1,FALSE) -> 921855 | B291: 921855 | C291: TJX COMPANIES INC - COMMON SHAREHOLDERS' EQUITY | D291: 921855(WC03501) | E291: 2131245 | F291: 2134557 | G291: 2889276 | H291: 3099899 | I291: 3209290 | J291: 3665937 | K291: 4229893 | L291: 4264230 | M291: 4307075 | N291: 4510599 | O291: 5148309
A292: =VLOOKUP(B292,'PORTFOLIO RAW'!B:B,1,FALSE) -> 951584 | B292: 951584 | C292: ZIONS BANCORP - COMMON SHAREHOLDERS' EQUITY | D292: 951584(WC03501) | E292: 5052800 | F292: 4919862 | G292: 4189874 | H292: 4591607 | I292: 4607748 | J292: 4923767 | K292: 5460593 | L292: 6365519 | M292: 6679029 | N292: 6924705 | O292: 7113000
A293: =VLOOKUP(B293,'PORTFOLIO RAW'!B:B,1,FALSE) -> 951051 | B293: 951051 | C293: REGIONS FINANCIAL - COMMON SHAREHOLDERS' EQUITY | D293: 951051(WC03501) | E293: 19823029 | F293: 13312837 | G293: 14113000 | H293: 13234000 | I293: 12999000 | J293: 14999000 | K293: 15268000 | L293: 15989000 | M293: 15844000 | N293: 15664000 | O293: 15192000
A294: =VLOOKUP(B294,'PORTFOLIO RAW'!B:B,1,FALSE) -> 29756N | B294: 29756N | C294: CELANESE CORPORATION - COMMON SHAREHOLDERS' EQUITY | D294: 29756N(WC03501) | E294: 1062000 | F294: 182000 | G294: 584000 | H294: 926000 | I294: 1341000 | J294: 1730000 | K294: 2699000 | L294: 2818000 | M294: 2378000 | N294: 2588000 | O294: 2887000
A295: =VLOOKUP(B295,'PORTFOLIO RAW'!B:B,1,FALSE) -> 905997 | B295: 905997 | C295: MOLSON COORS BREW - COMMON SHAREHOLDERS' EQUITY | D295: 905997(WC03501) | E295: 7149391 | F295: 5980300 | G295: 7079600 | H295: 7798800 | I295: 7647900 | J295: 7966900 | K295: 8638900 | L295: 7863300 | M295: 7043000 | N295: 11418700 | O295: 13226100
A296: =VLOOKUP(B296,'PORTFOLIO RAW'!B:B,1,FALSE) -> 31604H | B296: 31604H | C296: AMERIPRISE FIN - COMMON SHAREHOLDERS' EQUITY | D296: 31604H(WC03501) | E296: 7810000 | F296: 6178000 | G296: 9273000 | H296: 10725000 | I296: 10255000 | J296: 9092000 | K296: 8192000 | L296: 8124000 | M296: 7217000 | N296: 6292000 | O296: 5998000
A297: =VLOOKUP(B297,'PORTFOLIO RAW'!B:B,1,FALSE) -> 543487 | B297: 543487 | C297: VIACOM, INC. - COMMON SHAREHOLDERS' EQUITY | D297: 543487(WC03501) | E297: 7111200 | F297: 7033000 | G297: 8704000 | H297: 9283000 | I297: 8644000 | J297: 7448000 | K297: 5193000 | L297: 3719000 | M297: 3538000 | N297: 4277000 | O297: 6035000
A298: =VLOOKUP(B298,'PORTFOLIO RAW'!B:B,1,FALSE) -> 32480Q | B298: 32480Q | C298: CBS CORPORATION - COMMON SHAREHOLDERS' EQUITY | D298: 32480Q(WC03501) | E298: 21472400 | F298: 8597300 | G298: 9019400 | H298: 9820600 | I298: 9908000 | J298: 10213000 | K298: 9966000 | L298: 6970000 | M298: 5563000 | N298: 3689000 | O298: 1978000
A299: =VLOOKUP(B299,'PORTFOLIO RAW'!B:B,1,FALSE) -> 41071J | B299: 41071J | C299: HANESBRANDS, INC. - COMMON SHAREHOLDERS' EQUITY | D299: 41071J(WC03501) | E299: 288904 | F299: 185155 | G299: 334719 | H299: 562674 | I299: 681061 | J299: 886866 | K299: 1230623 | L299: 1386772 | M299: 1275891 | N299: 1223914 | O299: 686202
A300: =VLOOKUP(B300,'PORTFOLIO RAW'!B:B,1,FALSE) -> 41195M | B300: 41195M | C300: WESTERN UNION COMP - COMMON SHAREHOLDERS' EQUITY | D300: 41195M(WC03501) | E300: 50700 | F300: -8100 | G300: 353500 | H300: 582700 | I300: 894800 | J300: 940600 | K300: 1104700 | L300: 1300400 | M300: 1404900 | N300: 902200 | O300: -491400
A301: =VLOOKUP(B301,'PORTFOLIO RAW'!B:B,1,FALSE) -> 517465 | B301: 517465 | C301: PEOPLE'S UNITED - COMMON SHAREHOLDERS' EQUITY | D301: 517465(WC03501) | E301: 4445400 | F301: 5175500 | G301: 5100700 | H301: 5219300 | I301: 5225000 | J301: 5038800 | K301: 4568400 | L301: 4633100 | M301: 4731600 | N301: 4897800 | O301: 5575800
A302: =VLOOKUP(B302,'PORTFOLIO RAW'!B:B,1,FALSE) -> 905840 | B302: 905840 | C302: BANK OF NEW YORK - COMMON SHAREHOLDERS' EQUITY | D302: 905840(WC03501) | E302: 29403000 | F302: 25050000 | G302: 28977000 | H302: 32354000 | I302: 33417000 | J302: 35363000 | K302: 35959000 | L302: 35879000 | M302: 35485000 | N302: 35269000 | O302: 37709000
A303: =VLOOKUP(B303,'PORTFOLIO RAW'!B:B,1,FALSE) -> 51245V | B303: 51245V | C303: INVESCO LTD. - COMMON SHAREHOLDERS' EQUITY | D303: 51245V(WC03501) | E303: 6590600 | F303: 5689500 | G303: 6912900 | H303: 8264600 | I303: 8119100 | J303: 8316800 | K303: 8392600 | L303: 8326000 | M303: 7885300 | N303: 7503800 | O303: 8696100
A304: =VLOOKUP(B304,'PORTFOLIO RAW'!B:B,1,FALSE) -> 328314 | B304: 328314 | C304: CHUBB - COMMON SHAREHOLDERS' EQUITY | D304: 328314(WC03501) | E304: 16079000 | F304: 16158000 | G304: 19010000 | H304: 21575000 | I304: 22801000 | J304: 24898000 | K304: 27651000 | L304: 27736000 | M304: 28261000 | N304: 47217000 | O304: 49722000
A305: =VLOOKUP(B305,'PORTFOLIO RAW'!B:B,1,FALSE) -> 31196R | B305: 31196R | C305: DISCOVERY INC - COMMON SHAREHOLDERS' EQUITY | D305: 31196R(WC03501) | E305: 2708262 | F305: 5534000 | G305: 6206000 | H305: 6223000 | I305: 6515000 | J305: 6289000 | K305: 6194000 | L305: 5600000 | M305: 5449000 | N305: 5165000 | O305: 4610000
A306: =VLOOKUP(B306,'PORTFOLIO RAW'!B:B,1,FALSE) -> 771767 | B306: 771767 | C306: MOSAIC CO - COMMON SHAREHOLDERS' EQUITY | D306: 771767(WC03501) | E306: 4183900 | F306: 6731200 | G306: 8493000 | H306: 8722200 | I306: 11641600 | J306: 11983100 | K306: 11302300 | L306: 10703100 | M306: 9531800 | N306: 9584600 | O306: 9617500
A307: =VLOOKUP(B307,'PORTFOLIO RAW'!B:B,1,FALSE) -> 921503 | B307: 921503 | C307: STANLEY BLACK - COMMON SHAREHOLDERS' EQUITY | D307: 921503(WC03501) | E307: 1728500 | F307: 1688000 | G307: 1986100 | H307: 7017000 | I307: 7003600 | J307: 6667100 | K307: 6799200 | L307: 6429100 | M307: 5811600 | N307: 6367000 | O307: 7547100
A308: =VLOOKUP(B308,'PORTFOLIO RAW'!B:B,1,FALSE) -> 255781 | B308: 255781 | C308: GARMIN LTD. - COMMON SHAREHOLDERS' EQUITY | D308: 255781(WC03501) | E308: 2350614 | F308: 2225854 | G308: 2836447 | H308: 3049562 | I308: 3256581 | J308: 3531796 | K308: 3659706 | L308: 3403367 | M308: 3345126 | N308: 3418003 | O308: 3802466
A309: =VLOOKUP(B309,'PORTFOLIO RAW'!B:B,1,FALSE) -> 670129 | B309: 670129 | C309: PROLOGIS - COMMON SHAREHOLDERS' EQUITY | D309: 670129(WC03501) | E309: 2531452 | F309: 2282607 | G309: 2707516 | H309: 3088223 | I309: 13079439 | J309: 12486817 | K309: 13611158 | L309: 13897274 | M309: 14589700 | N309: 14912846 | O309: 15562208
A310: =VLOOKUP(B310,'PORTFOLIO RAW'!B:B,1,FALSE) -> 14352P | B310: 14352P | C310: ACCENTURE PLC - COMMON SHAREHOLDERS' EQUITY | D310: 14352P(WC03501) | E310: 2063332 | F310: 2540506 | G310: 2886593 | H310: 2835746 | I310: 3878951 | J310: 4145833 | K310: 4960186 | L310: 5732035 | M310: 6133725 | N310: 7555262 | O310: 8949477
A311: =VLOOKUP(B311,'PORTFOLIO RAW'!B:B,1,FALSE) -> 749688 | B311: 749688 | C311: HCA HEALTHCARE - COMMON SHAREHOLDERS' EQUITY | D311: 749688(WC03501) | E311: -10538000 | F311: -10255000 | G311: -8986000 | H311: -9702000 | I311: -8258000 | J311: -9660000 | K311: -8270000 | L311: -7894000 | M311: -7599000 | N311: -7302000 | O311: -6806000
A312: =VLOOKUP(B312,'PORTFOLIO RAW'!B:B,1,FALSE) -> 894145 | B312: 894145 | C312: RALPH LAUREN - COMMON SHAREHOLDERS' EQUITY | D312: 894145(WC03501) | E312: 2334900 | F312: 2389700 | G312: 2735100 | H312: 3116600 | I312: 3304700 | J312: 3652500 | K312: 3784600 | L312: 4034000 | M312: 3891000 | N312: 3744000 | O312: 3299600
A313: =VLOOKUP(B313,'PORTFOLIO RAW'!B:B,1,FALSE) -> 26599V | B313: 26599V | C313: SEAGATE TECHNOLOGY - COMMON SHAREHOLDERS' EQUITY | D313: 26599V(WC03501) | E313: 4737000 | F313: 4586000 | G313: 1524000 | H313: 2724000 | I313: 2463000 | J313: 3497000 | K313: 3495000 | L313: 2832000 | M313: 3018000 | N313: 1593000 | O313: 1364000
A314: =VLOOKUP(B314,'PORTFOLIO RAW'!B:B,1,FALSE) -> 904878 | B314: 904878 | C314: MOTOROLA SOLUTIONS - COMMON SHAREHOLDERS' EQUITY | D314: 904878(WC03501) | E314: 15447000 | F314: 9507000 | G314: 9775000 | H314: 10885000 | I314: 5214000 | J314: 3265000 | K314: 3659000 | L314: 2735000 | M314: -106000 | N314: -964000 | O314: -1742000
A315: =VLOOKUP(B315,'PORTFOLIO RAW'!B:B,1,FALSE) -> 922817 | B315: 922817 | C315: AON PLC - COMMON SHAREHOLDERS' EQUITY | D315: 922817(WC03501) | E315: 6121000 | F315: 5267000 | G315: 5335000 | H315: 8251000 | I315: 8078000 | J315: 7762000 | K315: 8145000 | L315: 6571000 | M315: 6106000 | N315: 5475000 | O315: 4583000
A316: =VLOOKUP(B316,'PORTFOLIO RAW'!B:B,1,FALSE) -> 905446 | B316: 905446 | C316: INGERSOLL-RAND - COMMON SHAREHOLDERS' EQUITY | D316: 905446(WC03501) | E316: 5416912 | F316: 4782885 | G316: 4957056 | H316: 6033435 | I316: 5345560 | J316: 5418032 | K316: 5146159 | L316: 4951580 | M316: 5357181 | N316: 6298322 | O316: 5955010
A317: =VLOOKUP(B317,'PORTFOLIO RAW'!B:B,1,FALSE) -> 28513N | B317: 28513N | C317: CBRE GROUP - COMMON SHAREHOLDERS' EQUITY | D317: 28513N(WC03501) | E317: 988603 | F317: 114686 | G317: 629122 | H317: 908215 | I317: 1151481 | J317: 1539211 | K317: 1895785 | L317: 2259830 | M317: 2712652 | N317: 3014487 | O317: 4019430
A318: =VLOOKUP(B318,'PORTFOLIO RAW'!B:B,1,FALSE) -> 31412T | B318: 31412T | C318: EXPEDIA GROUP INC - COMMON SHAREHOLDERS' EQUITY | D318: 31412T(WC03501) | E318: 4818081 | F318: 2328394 | G318: 2682681 | H318: 2672544 | I318: 2199864 | J318: 2280259 | K318: 2145464 | L318: 1784267 | M318: 4864394 | N318: 4132301 | O318: 4522335
A319: =VLOOKUP(B319,'PORTFOLIO RAW'!B:B,1,FALSE) -> 680902 | B319: 680902 | C319: AMERICAN TOWER CORP - COMMON SHAREHOLDERS' EQUITY | D319: 680902(WC03501) | E319: 3022092 | F319: 2991322 | G319: 3315082 | H319: 3501444 | I319: 3287220 | J319: 3573101 | K319: 3534165 | L319: 3953500 | M319: 4676679 | N319: 4788895 | O319: 6240100
A320: =VLOOKUP(B320,'PORTFOLIO RAW'!B:B,1,FALSE) -> 904383 | B320: 904383 | C320: DUKE ENERGY CORP - COMMON SHAREHOLDERS' EQUITY | D320: 904383(WC03501) | E320: 21199000 | F320: 20988000 | G320: 21750000 | H320: 22522000 | I320: 22772000 | J320: 40863000 | K320: 41330000 | L320: 40875000 | M320: 39727000 | N320: 41033000 | O320: 41739000
A321: =VLOOKUP(B321,'PORTFOLIO RAW'!B:B,1,FALSE) -> 13967E | B321: 13967E | C321: MONDELEZ - COMMON SHAREHOLDERS' EQUITY | D321: 13967E(WC03501) | E321: 27295000 | F321: 22200000 | G321: 25876000 | H321: 35834000 | I321: 35217000 | J321: 32215000 | K321: 32373000 | L321: 27750000 | M321: 28012000 | N321: 25161000 | O321: 26111000
A322: =VLOOKUP(B322,'PORTFOLIO RAW'!B:B,1,FALSE) -> 903749 | B322: 903749 | C322: EATON CORP PLC - COMMON SHAREHOLDERS' EQUITY | D322: 903749(WC03501) | E322: 5172000 | F322: 6317000 | G322: 6777000 | H322: 7362000 | I322: 7469000 | J322: 15086000 | K322: 16791000 | L322: 15786000 | M322: 15186000 | N322: 14897000 | O322: 17253000
A323: =VLOOKUP(B323,'PORTFOLIO RAW'!B:B,1,FALSE) -> 937343 | B323: 937343 | C323: L BRANDS INC - COMMON SHAREHOLDERS' EQUITY | D323: 937343(WC03501) | E323: 2219000 | F323: 1874000 | G323: 2183000 | H323: 1476000 | I323: 137000 | J323: -1015000 | K323: -370000 | L323: 18000 | M323: -259000 | N323: -729000 | O323: -753000
A324: =VLOOKUP(B324,'PORTFOLIO RAW'!B:B,1,FALSE) -> 905113 | B324: 905113 | C324: ARCONIC INC - COMMON SHAREHOLDERS' EQUITY | D324: 905113(WC03501) | E324: 15961000 | F324: 11680000 | G324: 12365000 | H324: 13556000 | I324: 13789000 | J324: 13144000 | K324: 10538000 | L324: 12248000 | M324: 11988000 | N324: 5057000 | O324: 4855000
A325: =VLOOKUP(B325,'PORTFOLIO RAW'!B:B,1,FALSE) -> 13967H | B325: 13967H | C325: WILLIS TOWERS WAT - COMMON SHAREHOLDERS' EQUITY | D325: 13967H(WC03501) | E325: 1347000 | F325: 1845000 | G325: 2180000 | H325: 2577000 | I325: 2486000 | J325: 1699000 | K325: 2215000 | L325: 1985000 | M325: 2229000 | N325: 10065000 | O325: 10126000
A326: =VLOOKUP(B326,'PORTFOLIO RAW'!B:B,1,FALSE) -> 921431 | B326: 921431 | C326: BAKER HUGHES A GE CO - COMMON SHAREHOLDERS' EQUITY | D326: 921431(WC03501) | E326: 6305600 | F326: 6807000 | G326: 7284000 | H326: 14100000 | I326: 15746000 | J326: 17069000 | K326: 17713000 | L326: 18625000 | M326: 16298000 | N326: 12656000 | O326: 39033000
A327: =VLOOKUP(B327,'PORTFOLIO RAW'!B:B,1,FALSE) -> 266220 | B327: 266220 | C327: TAPESTRY INC - COMMON SHAREHOLDERS' EQUITY | D327: 266220(WC03501) | E327: 1910354 | F327: 1515820 | G327: 1696042 | H327: 1505293 | I327: 1612569 | J327: 1992931 | K327: 2409158 | L327: 2420653 | M327: 2489900 | N327: 2682900 | O327: 3001900
A328: =VLOOKUP(B328,'PORTFOLIO RAW'!B:B,1,FALSE) -> 30730Q | B328: 30730Q | C328: INTERCONTINENTAL - COMMON SHAREHOLDERS' EQUITY | D328: 30730Q(WC03501) | E328: 1476856 | F328: 2006231 | G328: 2399732 | H328: 2777550 | I328: 3121525 | J328: 3643377 | K328: 12583000 | L328: 12360000 | M328: 14808000 | N328: 15717000 | O328: 16924000
A329: =VLOOKUP(B329,'PORTFOLIO RAW'!B:B,1,FALSE) -> 921925 | B329: 921925 | C329: JEFFERIES FINANCIAL - COMMON SHAREHOLDERS' EQUITY | D329: 921925(WC03501) | E329: 5570492 | F329: 2676797 | G329: 4361647 | H329: 6956758 | I329: 6174396 | J329: 6767268 | K329: 10102462 | L329: 10302158 | M329: 10401211 | N329: 10128100 | O329: 10105957
...

Sheet DEBT
B2: Code | C2: Name | D2: Code | E2: 2007 | F2: 2008 | G2: 2009 | H2: 2010 | I2: 2011 | J2: 2012 | K2: 2013 | L2: 2014 | M2: 2015 | N2: 2016 | O2: 2017
A3: =VLOOKUP(B3,'PORTFOLIO RAW'!B:B,1,FALSE) -> 891399 | B3: 891399 | C3: AMAZON.COM INC - TOTAL DEBT | D3: 891399(WC03255) | E3: 1361000 | F3: 592000 | G3: 393000 | H3: 865000 | I3: 1939000 | J3: 4964000 | K3: 6917000 | L3: 16089000 | M3: 17547000 | N3: 20410000 | O3: 44147000
A4: =VLOOKUP(B4,'PORTFOLIO RAW'!B:B,1,FALSE) -> 916328 | B4: 916328 | C4: ABBOTT LABORATORIES - TOTAL DEBT | D4: 916328(WC03255) | E4: 12213704 | F4: 11445302 | G4: 15880914 | H4: 18268283 | I4: 14734577 | J4: 19860964 | K4: 6056000 | L4: 7400000 | M4: 8562000 | N4: 21552000 | O4: 27924000
A5: =VLOOKUP(B5,'PORTFOLIO RAW'!B:B,1,FALSE) -> 545101 | B5: 545101 | C5: AES CORP - TOTAL DEBT | D5: 545101(WC03255) | E5: 17994000 | F5: 18091000 | G5: 19916000 | H5: 19733000 | I5: 22573000 | J5: 21373000 | K5: 21049000 | L5: 20858000 | M5: 20807000 | N5: 20463000 | O5: 19965000
A6: =VLOOKUP(B6,'PORTFOLIO RAW'!B:B,1,FALSE) -> 906187 | B6: 906187 | C6: INT'L BUSINESS MACHS - TOTAL DEBT | D6: 906187(WC03255) | E6: 35274000 | F6: 33925000 | G6: 26100000 | H6: 28624000 | I6: 31320000 | J6: 33269000 | K6: 39718000 | L6: 40804000 | M6: 39889000 | N6: 42168000 | O6: 46824000
A7: =VLOOKUP(B7,'PORTFOLIO RAW'!B:B,1,FALSE) -> 936365 | B7: 936365 | C7: ADVANCED MICRO - TOTAL DEBT | D7: 936365(WC03255) | E7: 5269000 | F7: 5074000 | G7: 4731000 | H7: 2421000 | I7: 2016000 | J7: 2042000 | K7: 2058000 | L7: 2212000 | M7: 2262000 | N7: 1435000 | O7: 1395000
A8: =VLOOKUP(B8,'PORTFOLIO RAW'!B:B,1,FALSE) -> 749382 | B8: 749382 | C8: ADOBE INC - TOTAL DEBT | D8: 749382(WC03255) | E8: 0 | F8: 350000 | G8: 1000000 | H8: 1522461 | I8: 1514308 | J8: 1508155 | K8: 1513973 | L8: 1514315 | M8: 1907231 | N8: 1902068 | O8: 1881421
A9: =VLOOKUP(B9,'PORTFOLIO RAW'!B:B,1,FALSE) -> 905271 | B9: 905271 | C9: AIR PRODUCTS & CHEMS - TOTAL DEBT | D9: 905271(WC03255) | E9: 3677200 | F9: 3966800 | G9: 4501500 | H9: 4159700 | I9: 4562200 | J9: 5291900 | K9: 6273600 | L9: 6118500 | M9: 5879000 | N9: 6225200 | O9: 3962800
A10: =VLOOKUP(B10,'PORTFOLIO RAW'!B:B,1,FALSE) -> 894371 | B10: 894371 | C10: BOSTON PROPERTIES - TOTAL DEBT | D10: 894371(WC03255) | E10: 5492166 | F10: 6271916 | G10: 6719771 | H10: 7786001 | I10: 8704138 | J10: 8912369 | K10: 11521509 | L10: 10086984 | M10: 9216513 | N10: 9796133 | O10: 10271611
A11: =VLOOKUP(B11,'PORTFOLIO RAW'!B:B,1,FALSE) -> 322677 | B11: 322677 | C11: ALLSTATE CORP - TOTAL DEBT | D11: 322677(WC03255) | E11: 5640000 | F11: 5659000 | G11: 5910000 | H11: 5908000 | I11: 5908000 | J11: 6057000 | K11: 6245000 | L11: 5205000 | M11: 5129000 | N11: 6347000 | O11: 6350000
A12: =VLOOKUP(B12,'PORTFOLIO RAW'!B:B,1,FALSE) -> 906191 | B12: 906191 | C12: HONEYWELL INTERNATNL - TOTAL DEBT | D12: 906191(WC03255) | E12: 7657000 | F12: 8375000 | G12: 7607000 | H12: 6644000 | I12: 7555000 | J12: 7496000 | K12: 8829000 | L12: 8683000 | M12: 12068000 | N12: 15775000 | O12: 17882000
A13: =VLOOKUP(B13,'PORTFOLIO RAW'!B:B,1,FALSE) -> 938692 | B13: 938692 | C13: AMGEN INC - TOTAL DEBT | D13: 938692(WC03255) | E13: 11177000 | F13: 10176000 | G13: 10601000 | H13: 13362000 | I13: 21428000 | J13: 26529000 | K13: 32128000 | L13: 30715000 | M13: 31556000 | N13: 34596000 | O13: 35342000
A14: =VLOOKUP(B14,'PORTFOLIO RAW'!B:B,1,FALSE) -> 905802 | B14: 905802 | C14: HESS CORPORATION - TOTAL DEBT | D14: 905802(WC03255) | E14: 3980000 | F14: 3955000 | G14: 4467000 | H14: 5583000 | I14: 6057000 | J14: 8111000 | K14: 5798000 | L14: 5987000 | M14: 6630000 | N14: 6806000 | O14: 6977000
... A109: =VLOOKUP(B109,'PORTFOLIO RAW'!B:B,1,FALSE) -> 905016 | B109: 905016 | C109: NEXTERA ENERGY - TOTAL DEBT | D109: 905016(WC03255) | E109: 13698000 | F109: 17086000 | G109: 18889000 | H109: 20822000 | I109: 22967000 | J109: 27359000 | K109: 28426000 | L109: 29024000 | M109: 29687000 | N109: 30840000 | O109: 35081000
A110: =VLOOKUP(B110,'PORTFOLIO RAW'!B:B,1,FALSE) -> 28341F | B110: 28341F | C110: ASSURANT INC - TOTAL DEBT | D110: 28341F(WC03255) | E110: 993023 | F110: 983117 | G110: 980218 | H110: 977164 | I110: 972278 | J110: 972399 | K110: 1638118 | L110: 1171079 | M110: 1171382 | N110: 1067020 | O110: 1068200
A111: =VLOOKUP(B111,'PORTFOLIO RAW'!B:B,1,FALSE) -> 755980 | B111: 755980 | C111: FASTENAL COMPANY - TOTAL DEBT | D111: 755980(WC03255) | E111: 0 | F111: 0 | G111: 0 | H111: 0 | I111: 0 | J111: 0 | K111: 0 | L111: 90000 | M111: 365000 | N111: 390000 | O111: 415000
A112: =VLOOKUP(B112,'PORTFOLIO RAW'!B:B,1,FALSE) -> 905994 | B112: 905994 | C112: FEDERAL REALTY INVST - TOTAL DEBT | D112: 905994(WC03255) | E112: 1638460 | F112: 1745785 | G112: 1793848 | H112: 1767149 | I112: 2110410 | J112: 2208602 | K112: 2321862 | L112: 2409677 | M112: 2642366 | N112: 2798452 | O112: 3284766
A113: =VLOOKUP(B113,'PORTFOLIO RAW'!B:B,1,FALSE) -> 997198 | B113: 997198 | C113: FIFTH THIRD BANCORP - TOTAL DEBT | D113: 997198(WC03255) | E113: 22031000 | F113: 23831000 | G113: 12104000 | H113: 11411000 | I113: 13267000 | J113: 14266000 | K113: 11297000 | L113: 16667000 | M113: 16920000 | N113: 17681000 | O113: 18749000
A114: =VLOOKUP(B114,'PORTFOLIO RAW'!B:B,1,FALSE) -> 951503 | B114: 951503 | C114: M&T BANK CORPORATION - TOTAL DEBT | D114: 951503(WC03255) | E114: 16139842 | F114: 15084884 | G114: 12682598 | H114: 8787583 | I114: 7468308 | J114: 5682240 | K114: 5369325 | L114: 9199635 | M114: 12786040 | N114: 9657277 | O114: 8316529
A115: =VLOOKUP(B115,'PORTFOLIO RAW'!B:B,1,FALSE) -> 741123 | B115: 741123 | C115: FISERV INC - TOTAL DEBT | D115: 741123(WC03255) | E115: 5405000 | F115: 4105000 | G115: 3641000 | H115: 3356000 | I115: 3395000 | J115: 3230000 | K115: 3848000 | L115: 3803000 | M115: 4293000 | N115: 4562000 | O115: 4900000
A116: =VLOOKUP(B116,'PORTFOLIO RAW'!B:B,1,FALSE) -> 546814 | B116: 546814 | C116: MACY'S INC - TOTAL DEBT | D116: 546814(WC03255) | E116: 9753000 | F116: 9699000 | G116: 8698000 | H116: 7425000 | I116: 7758000 | J116: 6930000 | K116: 7672000 | L116: 7341000 | M116: 7637000 | N116: 6871000 | O116: 5883000
A117: =VLOOKUP(B117,'PORTFOLIO RAW'!B:B,1,FALSE) -> 938076 | B117: 938076 | C117: FRANKLIN RESOURCES - TOTAL DEBT | D117: 938076(WC03255) | E117: 822898 | F117: 269271 | G117: 121156 | H117: 979900 | I117: 2168437 | J117: 2777200 | K117: 2295100 | L117: 2149000 | M117: 2155300 | N117: 2083400 | O117: 1097600
A118: =VLOOKUP(B118,'PORTFOLIO RAW'!B:B,1,FALSE) -> 152594 | B118: 152594 | C118: FREEPORT-MCMORAN INC - TOTAL DEBT | D118: 152594(WC03255) | E118: 7211000 | F118: 7351000 | G118: 6346000 | H118: 4755000 | I118: 3537000 | J118: 3527000 | K118: 20706000 | L118: 18970000 | M118: 20428000 | N118: 16027000 | O118: 13117000
A119: =VLOOKUP(B119,'PORTFOLIO RAW'!B:B,1,FALSE) -> 951018 | B119: 951018 | C119: GAP INC - TOTAL DEBT | D119: 951018(WC03255) | E119: 188000 | F119: 50000 | G119: 0 | H119: 0 | I119: 1665000 | J119: 1246000 | K119: 1394000 | L119: 1353000 | M119: 1731000 | N119: 1313000 | O119: 1249000
A120: =VLOOKUP(B120,'PORTFOLIO RAW'!B:B,1,FALSE) -> 907652 | B120: 907652 | C120: GENERAL DYNAMICS - TOTAL DEBT | D120: 907652(WC03255) | E120: 2791000 | F120: 4024000 | G120: 3864000 | H120: 3203000 | I120: 3930000 | J120: 3909000 | K120: 3943000 | L120: 3942000 | M120: 3431000 | N120: 3918000 | O120: 4009000
A121: =VLOOKUP(B121,'PORTFOLIO RAW'!B:B,1,FALSE) -> 905801 | B121: 905801 | C121: GENERAL MILLS, INC. - TOTAL DEBT | D121: 905801(WC03255) | E121: 6206000 | F121: 6999500 | G121: 7075500 | H121: 6425900 | I121: 6885100 | J121: 7429600 | K121: 7969100 | L121: 8785800 | M121: 9223900 | N121: 8430900 | O121: 9481700
A122: =VLOOKUP(B122,'PORTFOLIO RAW'!B:B,1,FALSE) -> 906511 | B122: 906511 | C122: GENUINE PARTS CO - TOTAL DEBT | D122: 906511(WC03255) | E122: 513707 | F122: 512708 | G122: 513504 | H122: 512622 | I122: 500000 | J122: 500000 | K122: 792473 | L122: 805506 | M122: 662642 | N122: 914221 | O122: 3300702
... A236: =VLOOKUP(B236,'PORTFOLIO RAW'!B:B,1,FALSE) -> 933974 | B236: 933974 | C236: TRAVELERS COS - TOTAL DEBT | D236: 933974(WC03255) | E236: 6242000 | F236: 6181000 | G236: 6527000 | H236: 6611000 | I236: 6605000 | J236: 6350000 | K236: 6346000 | L236: 6349000 | M236: 6344000 | N236: 6437000 | O236: 6571000
A237: =VLOOKUP(B237,'PORTFOLIO RAW'!B:B,1,FALSE) -> 14015T | B237: 14015T | C237: FIDELITY NATNL INF - TOTAL DEBT | D237: 14015T(WC03255) | E237: 4275397 | F237: 2514500 | G237: 3253300 | H237: 5240000 | I237: 4809800 | J237: 4385500 | K237: 4468600 | L237: 5067700 | M237: 11513100 | N237: 10478000 | O237: 8763000
A238: =VLOOKUP(B238,'PORTFOLIO RAW'!B:B,1,FALSE) -> 905019 | B238: 905019 | C238: MERCK & CO INC - TOTAL DEBT | D238: 905019(WC03255) | E238: 5739400 | F238: 6240400 | G238: 17660700 | H238: 17882000 | I238: 17515000 | J238: 20569000 | K238: 25060000 | L238: 21403000 | M238: 26514000 | N238: 24842000 | O238: 24410000
A239: =VLOOKUP(B239,'PORTFOLIO RAW'!B:B,1,FALSE) -> 912090 | B239: 912090 | C239: SCHLUMBERGER LIMITED - TOTAL DEBT | D239: 912090(WC03255) | E239: 5466101 | F239: 5290888 | G239: 5480000 | H239: 8099000 | I239: 9925000 | J239: 11630000 | K239: 13176000 | L239: 13330000 | M239: 18999000 | N239: 19616000 | O239: 18199000
A240: =VLOOKUP(B240,'PORTFOLIO RAW'!B:B,1,FALSE) -> 755741 | B240: 755741 | C240: CHARLES SCHWAB CORP - TOTAL DEBT | D240: 755741(WC03255) | E240: 899000 | F240: 883000 | G240: 1512000 | H240: 2006000 | I240: 2001000 | J240: 1632000 | K240: 1903000 | L240: 1899000 | M240: 2890000 | N240: 2876000 | O240: 19753000
A241: =VLOOKUP(B241,'PORTFOLIO RAW'!B:B,1,FALSE) -> 14361V | B241: 14361V | C241: ZIMMER BIOMET - TOTAL DEBT | D241: 14361V(WC03255) | E241: 104300 | F241: 460100 | G241: 1127600 | H241: 1142100 | I241: 1719300 | J241: 1820900 | K241: 1672800 | L241: 1425500 | M241: 11556300 | N241: 11241400 | O241: 10142500
A242: =VLOOKUP(B242,'PORTFOLIO RAW'!B:B,1,FALSE) -> 154680 | B242: 154680 | C242: AMERISOURCEBERGEN - TOTAL DEBT | D242: 154680(WC03255) | E242: 1227774 | F242: 1189131 | G242: 1178001 | H242: 1343580 | I242: 1364952 | J242: 1446770 | K242: 1462981 | L242: 2056532 | M242: 3597774 | N242: 4481393 | O242: 3822396
A243: =VLOOKUP(B243,'PORTFOLIO RAW'!B:B,1,FALSE) -> 14698C | B243: 14698C | C243: PRINCIPAL FINL GROUP - TOTAL DEBT | D243: 14698C(WC03255) | E243: 1689600 | F243: 1791400 | G243: 1686200 | H243: 1691600 | I243: 1670000 | J243: 2712100 | K243: 2752300 | L243: 2559200 | M243: 3514700 | N243: 3177100 | O243: 3217900
A244: =VLOOKUP(B244,'PORTFOLIO RAW'!B:B,1,FALSE) -> 905361 | B244: 905361 | C244: SHERWIN-WILLIAMS CO - TOTAL DEBT | D244: 905361(WC03255) | E244: 965448 | F244: 833735 | G244: 817611 | H244: 1044793 | I244: 993367 | J244: 1704889 | K244: 1721872 | L244: 1805416 | M244: 1962812 | N244: 1952540 | O244: 10520655
A245: =VLOOKUP(B245,'PORTFOLIO RAW'!B:B,1,FALSE) -> 357834 | B245: 357834 | C245: SIMON PROPERTY GROUP - TOTAL DEBT | D245: 357834(WC03255) | E245: 17218674 | F245: 18042532 | G245: 18630302 | H245: 17473760 | I245: 18446440 | J245: 23113007 | K245: 23588531 | L245: 20852993 | M245: 22502173 | N245: 22977104 | O245: 24632463
A246: =VLOOKUP(B246,'PORTFOLIO RAW'!B:B,1,FALSE) -> 906400 | B246: 906400 | C246: SNAP-ON INC - TOTAL DEBT | D246: 906400(WC03255) | E246: 517900 | F246: 539200 | G246: 1091500 | H246: 1193800 | I246: 1006600 | J246: 1015200 | K246: 972000 | L246: 919300 | M246: 880100 | N246: 1010200 | O246: 1186800
A247: =VLOOKUP(B247,'PORTFOLIO RAW'!B:B,1,FALSE) -> 14861V | B247: 14861V | C247: PRUDENTIAL FINANCIAL - TOTAL DEBT | D247: 14861V(WC03255) | E247: 47511000 | F247: 42913000 | G247: 33355000 | H247: 33691000 | I247: 36149000 | J247: 33031000 | K247: 37422000 | L247: 39135000 | M247: 37422000 | N247: 28930000 | O247: 28470000
A248: =VLOOKUP(B248,'PORTFOLIO RAW'!B:B,1,FALSE) -> 14806F | B248: 14806F | C248: ADVANCE AUTO PARTS - TOTAL DEBT | D248: 14806F(WC03255) | E248: 535672 | F248: 476752 | G248: 213799 | H248: 311380 | I248: 432165 | J248: 613810 | K248: 1053584 | L248: 1636893 | M248: 1213759 | N248: 1043255 | O248: 1044677
A249: =VLOOKUP(B249,'PORTFOLIO RAW'!B:B,1,FALSE) -> 902324 | B249: 902324 | C249: EDISON INTERNATIONAL - TOTAL DEBT | D249: 902324(WC03255) | E249: 9746000 | F249: 13491000 | G249: 11123000 | H249: 12534000 | I249: 14397000 | J249: 9622000 | K249: 10635000 | L249: 12029000 | M249: 11954000 | N249: 12463000 | O249: 14516000
A250: =VLOOKUP(B250,'PORTFOLIO RAW'!B:B,1,FALSE) -> 902325 | B250: 902325 | C250: SOUTHERN CO - TOTAL DEBT | D250: 902325(WC03255) | E250: 16593000 | F250: 18386000 | G250: 19883000 | H250: 20752000 | I250: 21223000 | J250: 22584000 | K250: 23295000 | L250: 24977000 | M250: 28738000 | N250: 47324000 | O250: 50793000
A251: =VLOOKUP(B251,'PORTFOLIO RAW'!B:B,1,FALSE) -> 992305 | B251: 992305 | C251: BB&T CORPORATION - TOTAL DEBT | D251: 992305(WC03255) | E251: 29327000 | F251: 28820000 | G251: 29482000 | H251: 27403000 | I251: 25369000 | J251: 21978000 | K251: 27774000 | L251: 28144000 | M251: 32686000 | N251: 23371000 | O251: 28586000
A252: =VLOOKUP(B252,'PORTFOLIO RAW'!B:B,1,FALSE) -> 905647 | B252: 905647 | C252: SOUTHWEST AIRLINES - TOTAL DEBT | D252: 905647(WC03255) | E252: 2091000 | F252: 3661000 | G252: 3515000 | H252: 3380000 | I252: 3751000 | J252: 3154000 | K252: 3110000 | L252: 2885000 | M252: 3343000 | N252: 3512000 | O252: 3753000
A253: =VLOOKUP(B253,'PORTFOLIO RAW'!B:B,1,FALSE) -> 945388 | B253: 945388 | C253: AT&T INC - TOTAL DEBT | D253: 945388(WC03255) | E253: 64115000 | F253: 74991000 | G253: 72081000 | H253: 66167000 | I253: 64753000 | J253: 69844000 | K253: 74788000 | L253: 82067000 | M253: 126151000 | N253: 123513000 | O253: 164346000
A254: =VLOOKUP(B254,'PORTFOLIO RAW'!B:B,1,FALSE) -> 905024 | B254: 905024 | C254: CHEVRON CORPORATION - TOTAL DEBT | D254: 905024(WC03255) | E254: 7232000 | F254: 8901000 | G254: 10514000 | H254: 11476000 | I254: 10152000 | J254: 12192000 | K254: 20431000 | L254: 27818000 | M254: 38592000 | N254: 46126000 | O254: 38763000
A255: =VLOOKUP(B255,'PORTFOLIO RAW'!B:B,1,FALSE) -> 951052 | B255: 951052 | C255: STATE STREET CORP - TOTAL DEBT | D255: 951052(WC03255) | E255: 24264000 | F255: 34252000 | G255: 44112000 | H255: 32591000 | I255: 22125000 | J255: 20336000 | K255: 21451000 | L255: 23369000 | M255: 17787000 | N255: 17415000 | O255: 15606000
A256: =VLOOKUP(B256,'PORTFOLIO RAW'!B:B,1,FALSE) -> 326143 | B256: 326143 | C256: STARBUCKS CORP - TOTAL DEBT | D256: 326143(WC03255) | E256: 1264244 | F256: 1270000 | G256: 557300 | H256: 552000 | I256: 550900 | J256: 549600 | K256: 1348200 | L256: 2048300 | M256: 2347500 | N256: 3602200 | O256: 3991700
A257: =VLOOKUP(B257,'PORTFOLIO RAW'!B:B,1,FALSE) -> 905792 | B257: 905792 | C257: PUBLIC STORAGE, INC - TOTAL DEBT | D257: 905792(WC03255) | E257: 1069928 | F257: 643811 | G257: 518889 | H257: 568417 | I257: 398314 | J257: 468828 | K257: 839053 | L257: 64364 | M257: 319016 | N257: 390749 | O257: 1431322
A258: =VLOOKUP(B258,'PORTFOLIO RAW'!B:B,1,FALSE) -> 981722 | B258: 981722 | C258: STRYKER CORPORATION - TOTAL DEBT | D258: 981722(WC03255) | E258: 16800 | F258: 20500 | G258: 18000 | H258: 1021800 | I258: 1768000 | J258: 1762000 | K258: 2764000 | L258: 3973000 | M258: 4022000 | N258: 6914000 | O258: 7222000
A259: =VLOOKUP(B259,'PORTFOLIO RAW'!B:B,1,FALSE) -> 922725 | B259: 922725 | C259: SUNTRUST BANKS INC - TOTAL DEBT | D259: 922725(WC03255) | E259: 35157328 | F259: 36292131 | G259: 22854884 | H259: 19469000 | I259: 22374000 | J259: 14851000 | K259: 19439000 | L259: 22208000 | M259: 13089000 | N259: 18299000 | O259: 15801000
A260: =VLOOKUP(B260,'PORTFOLIO RAW'!B:B,1,FALSE) -> 541900 | B260: 541900 | C260: SYMANTEC CORP - TOTAL DEBT | D260: 541900(WC03255) | E260: 2100000 | F260: 2300000 | G260: 2100000 | H260: 1871000 | I260: 2583000 | J260: 2039000 | K260: 3091000 | L260: 2095000 | M260: 2096000 | N260: 2207000 | O260: 8186000
... A283: =VLOOKUP(B283,'PORTFOLIO RAW'!B:B,1,FALSE) -> 904869 | B283: 904869 | C283: WHIRLPOOL CORP - TOTAL DEBT | D283: 904869(WC03255) | E283: 2093000 | F283: 2597000 | G283: 2903000 | H283: 2509000 | I283: 2491000 | J283: 2461000 | K283: 2463000 | L283: 4347000 | M283: 3998000 | N283: 4470000 | O283: 5218000
A284: =VLOOKUP(B284,'PORTFOLIO RAW'!B:B,1,FALSE) -> 26406N | B284: 26406N | C284: WYNN RESORTS, LTD - TOTAL DEBT | D284: 26406N(WC03255) | E284: 3548379 | F284: 4299177 | G284: 3569103 | H284: 3267529 | I284: 3334998 | J284: 5782820 | K284: 6587568 | L284: 7345262 | M284: 9212765 | N284: 10125352 | O284: 9645226
A285: =VLOOKUP(B285,'PORTFOLIO RAW'!B:B,1,FALSE) -> 26393N | B285: 26393N | C285: CME GROUP INC - TOTAL DEBT | D285: 26393N(WC03255) | E285: 3026461 | F285: 3672762 | G285: 2314500 | H285: 2525300 | I285: 2106800 | J285: 2856500 | K285: 2857100 | L285: 2107900 | M285: 2241400 | N285: 2231200 | O285: 2233100
A286: =VLOOKUP(B286,'PORTFOLIO RAW'!B:B,1,FALSE) -> 922407 | B286: 922407 | C286: WILLIAMS COMPANIES - TOTAL DEBT | D286: 922407(WC03255) | E286: 7900000 | F286: 7879000 | G286: 8276000 | H286: 9108000 | I286: 8722000 | J286: 10736000 | K286: 11579000 | L286: 21690000 | M286: 24487000 | N286: 23502000 | O286: 20935000
A287: =VLOOKUP(B287,'PORTFOLIO RAW'!B:B,1,FALSE) -> 906979 | B287: 906979 | C287: ALLIANT ENERGY CORP - TOTAL DEBT | D287: 906979(WC03255) | E287: 1655900 | F287: 1970800 | G287: 2696000 | H287: 2752100 | I287: 2807300 | J287: 3355600 | K287: 3617700 | L287: 3933000 | M287: 3997400 | N287: 4570300 | O287: 5286500
A288: =VLOOKUP(B288,'PORTFOLIO RAW'!B:B,1,FALSE) -> 877723 | B288: 877723 | C288: CARMAX INC - TOTAL DEBT | D288: 877723(WC03255) | E288: 185477 | F288: 327831 | G288: 337047 | H288: 150571 | I288: 4043785 | J288: 5052706 | K288: 6209036 | L288: 7583410 | M288: 9109252 | N288: 10657832 | O288: 12169704
A289: =VLOOKUP(B289,'PORTFOLIO RAW'!B:B,1,FALSE) -> 543542 | B289: 543542 | C289: XILINX INC - TOTAL DEBT | D289: 543542(WC03255) | E289: 999597 | F289: 999851 | G289: 690125 | H289: 354798 | I289: 890980 | J289: 906569 | K289: 960066 | L289: 1558871 | M289: 1570892 | N289: 1582941 | O289: 1451575
A290: =VLOOKUP(B290,'PORTFOLIO RAW'!B:B,1,FALSE) -> 26276P | B290: 26276P | C290: CIMAREX ENERGY CO - TOTAL DEBT | D290: 26276P(WC03255) | E290: 487159 | F290: 591223 | G290: 392793 | H290: 350000 | I290: 405000 | J290: 750000 | K290: 924000 | L290: 1500000 | M290: 1485620 | N290: 1487939 | O290: 1486920
A291: =VLOOKUP(B291,'PORTFOLIO RAW'!B:B,1,FALSE) -> 921855 | B291: 921855 | C291: TJX COMPANIES INC - TOTAL DEBT | D291: 921855(WC03255) | E291: 855468 | F291: 778809 | G291: 792524 | H291: 790244 | I291: 787593 | J291: 774552 | K291: 1274200 | L291: 1623900 | M291: 1709268 | N291: 2403831 | O291: 2452524
A292: =VLOOKUP(B292,'PORTFOLIO RAW'!B:B,1,FALSE) -> 951584 | B292: 951584 | C292: ZIONS BANCORP - TOTAL DEBT | D292: 951584(WC03255) | E292: 10056547 | F292: 6578168 | G292: 2983634 | H292: 2873822 | I292: 2677319 | J292: 2689735 | K292: 2613923 | L292: 1336505 | M292: 1164335 | N292: 1362119 | O292: 5359000
A293: =VLOOKUP(B293,'PORTFOLIO RAW'!B:B,1,FALSE) -> 951051 | B293: 951051 | C293: REGIONS FINANCIAL - TOTAL DEBT | D293: 951051(WC03255) | E293: 22444912 | F293: 35053239 | G293: 22132000 | H293: 17127000 | I293: 11177000 | J293: 7435000 | K293: 8371000 | L293: 5715000 | M293: 8359000 | N293: 12015000 | O293: 13632000
A294: =VLOOKUP(B294,'PORTFOLIO RAW'!B:B,1,FALSE) -> 29756N | B294: 29756N | C294: CELANESE CORPORATION - TOTAL DEBT | D294: 29756N(WC03255) | E294: 3556000 | F294: 3533000 | G294: 3501000 | H294: 3218000 | I294: 3017000 | J294: 3098000 | K294: 3064000 | L294: 2745000 | M294: 2981000 | N294: 3008000 | O294: 3641000
A295: =VLOOKUP(B295,'PORTFOLIO RAW'!B:B,1,FALSE) -> 905997 | B295: 905997 | C295: MOLSON COORS BREW - TOTAL DEBT | D295: 905997(WC03255) | E295: 2264877 | F295: 1831800 | G295: 1713000 | H295: 1960700 | I295: 1961800 | J295: 4668100 | K295: 3799900 | L295: 3186500 | M295: 2937400 | N295: 12072500 | O295: 11313500
A296: =VLOOKUP(B296,'PORTFOLIO RAW'!B:B,1,FALSE) -> 31604H | B296: 31604H | C296: AMERIPRISE FIN - TOTAL DEBT | D296: 31604H(WC03255) | E296: 2018000 | F296: 2027000 | G296: 2249000 | H296: 8249000 | I296: 8075000 | J296: 7885000 | K296: 8956000 | L296: 10129000 | M296: 10446000 | N296: 5436000 | O296: 5299000
A297: =VLOOKUP(B297,'PORTFOLIO RAW'!B:B,1,FALSE) -> 543487 | B297: 543487 | C297: VIACOM, INC. - TOTAL DEBT | D297: 543487(WC03255) | E297: 8246100 | F297: 8002000 | G297: 6773000 | H297: 6752000 | I297: 7365000 | J297: 8149000 | K297: 11885000 | L297: 12769000 | M297: 12285000 | N297: 11913000 | O297: 11119000
A298: =VLOOKUP(B298,'PORTFOLIO RAW'!B:B,1,FALSE) -> 32480Q | B298: 32480Q | C298: CBS CORPORATION - TOTAL DEBT | D298: 32480Q(WC03255) | E298: 7087700 | F298: 6996100 | G298: 6996900 | H298: 6000800 | I298: 5982000 | J298: 5922000 | K298: 6436000 | L298: 7146000 | M298: 8448000 | N298: 9375000 | O298: 10162000
A299: =VLOOKUP(B299,'PORTFOLIO RAW'!B:B,1,FALSE) -> 41071J | B299: 41071J | C299: HANESBRANDS, INC. - TOTAL DEBT | D299: 41071J(WC03255) | E299: 2334827 | F299: 2238281 | G299: 1980781 | H299: 2131413 | I299: 2037785 | J299: 1517552 | K299: 1684982 | L299: 1983752 | M299: 2624766 | N299: 3742445 | O299: 3963516
A300: =VLOOKUP(B300,'PORTFOLIO RAW'!B:B,1,FALSE) -> 41195M | B300: 41195M | C300: WESTERN UNION COMP - TOTAL DEBT | D300: 41195M(WC03255) | E300: 3338000 | F300: 3143500 | G300: 3048500 | H300: 3289900 | I300: 3583200 | J300: 4029200 | K300: 4213000 | L300: 3720400 | M300: 3225600 | N300: 2786100 | O300: 3033600
A301: =VLOOKUP(B301,'PORTFOLIO RAW'!B:B,1,FALSE) -> 517465 | B301: 517465 | C301: PEOPLE'S UNITED - TOTAL DEBT | D301: 517465(WC03255) | E301: 65400 | F301: 368400 | G301: 340700 | H301: 1192800 | I301: 1016300 | J301: 3045500 | K301: 5696100 | L301: 4725200 | M301: 5346000 | N301: 5086900 | O301: 5005400
A302: =VLOOKUP(B302,'PORTFOLIO RAW'!B:B,1,FALSE) -> 905840 | B302: 905840 | C302: BANK OF NEW YORK - TOTAL DEBT | D302: 905840(WC03255) | E302: 24985000 | F302: 23721000 | G302: 21071000 | H302: 24987000 | I302: 28384000 | J302: 27675000 | K302: 30271000 | L302: 32519000 | M302: 37072000 | N302: 35206000 | O302: 49245000
A303: =VLOOKUP(B303,'PORTFOLIO RAW'!B:B,1,FALSE) -> 51245V | B303: 51245V | C303: INVESCO LTD. - TOTAL DEBT | D303: 51245V(WC03255) | E303: 1393000 | F303: 1159200 | G303: 745700 | H303: 7181100 | I303: 6797600 | J303: 5085400 | K303: 5770300 | L303: 6738900 | M303: 7509800 | N303: 6505500 | O303: 6875600
A304: =VLOOKUP(B304,'PORTFOLIO RAW'!B:B,1,FALSE) -> 328314 | B304: 328314 | C304: CHUBB - TOTAL DEBT | D304: 328314(WC03255) | E304: 2492000 | F304: 3586000 | G304: 3628000 | H304: 4967000 | I304: 4920000 | J304: 5070000 | K304: 6017000 | L304: 6218000 | M304: 11160000 | N304: 14821000 | O304: 14285000
A305: =VLOOKUP(B305,'PORTFOLIO RAW'!B:B,1,FALSE) -> 31196R | B305: 31196R | C305: DISCOVERY INC - TOTAL DEBT | D305: 31196R(WC03255) | E305: 4141091 | F305: 3789000 | G305: 3495000 | H305: 3618000 | I305: 4245000 | J305: 5243000 | K305: 6499000 | L305: 7153000 | M305: 7735000 | N305: 7923000 | O305: 14785000
A306: =VLOOKUP(B306,'PORTFOLIO RAW'!B:B,1,FALSE) -> 771767 | B306: 771767 | C306: MOSAIC CO - TOTAL DEBT | D306: 771767(WC03255) | E306: 2360500 | F306: 1551400 | G306: 1392500 | H306: 1343900 | I306: 832900 | J306: 1053000 | K306: 3031900 | L306: 3832500 | M306: 3859600 | N306: 3818200 | O306: 5227700
A307: =VLOOKUP(B307,'PORTFOLIO RAW'!B:B,1,FALSE) -> 921503 | B307: 921503 | C307: STANLEY BLACK - TOTAL DEBT | D307: 921503(WC03255) | E307: 1504900 | F307: 1647200 | G307: 1383100 | H307: 3435800 | I307: 3452400 | J307: 3538000 | K307: 4202000 | L307: 3847300 | M307: 3844200 | N307: 3827400 | O307: 3831700
A308: =VLOOKUP(B308,'PORTFOLIO RAW'!B:B,1,FALSE) -> 255781 | B308: 255781 | C308: GARMIN LTD. - TOTAL DEBT | D308: 255781(WC03255) | E308: 0 | F308: 0 | G308: 0 | H308: 0 | I308: 0 | J308: 0 | K308: 0 | L308: 0 | M308: 0 | N308: 0 | O308: 0
A309: =VLOOKUP(B309,'PORTFOLIO RAW'!B:B,1,FALSE) -> 670129 | B309: 670129 | C309: PROLOGIS - TOTAL DEBT | D309: 670129(WC03255) | E309: 3494844 | F309: 3990185 | G309: 3212596 | H309: 3331299 | I309: 11382408 | J309: 11790794 | K309: 9011216 | L309: 9380199 | M309: 11626831 | N309: 10608294 | O309: 9412631
A310: =VLOOKUP(B310,'PORTFOLIO RAW'!B:B,1,FALSE) -> 14352P | B310: 14352P | C310: ACCENTURE PLC - TOTAL DEBT | D310: 14352P(WC03255) | E310: 26360 | F310: 8278 | G310: 955 | H310: 1588 | I310: 4419 | J310: 33 | K310: 25600 | L310: 26733 | M310: 27435 | N310: 27230 | O310: 25070
A311: =VLOOKUP(B311,'PORTFOLIO RAW'!B:B,1,FALSE) -> 749688 | B311: 749688 | C311: HCA HEALTHCARE - TOTAL DEBT | D311: 749688(WC03255) | E311: 27308000 | F311: 26989000 | G311: 25670000 | H311: 26033000 | I311: 27052000 | J311: 28930000 | K311: 28376000 | L311: 29645000 | M311: 30488000 | N311: 31376000 | O311: 33058000
A312: =VLOOKUP(B312,'PORTFOLIO RAW'!B:B,1,FALSE) -> 894145 | B312: 894145 | C312: RALPH LAUREN - TOTAL DEBT | D312: 894145(WC03255) | E312: 447500 | F312: 752400 | G312: 483000 | H312: 320300 | I312: 332300 | J312: 312700 | K312: 305000 | L312: 571000 | M312: 789000 | N312: 1000000 | O312: 861700
A313: =VLOOKUP(B313,'PORTFOLIO RAW'!B:B,1,FALSE) -> 26599V | B313: 26599V | C313: SEAGATE TECHNOLOGY - TOTAL DEBT | D313: 26599V(WC03255) | E313: 2063000 | F313: 2030000 | G313: 2727000 | H313: 2502000 | I313: 3512000 | J313: 2863000 | K313: 2777000 | L313: 3920000 | M313: 4155000 | N313: 4130000 | O313: 5021000
A314: =VLOOKUP(B314,'PORTFOLIO RAW'!B:B,1,FALSE) -> 904878 | B314: 904878 | C314: MOTOROLA SOLUTIONS - TOTAL DEBT | D314: 904878(WC03255) | E314: 4285000 | F314: 4033000 | G314: 3791000 | H314: 2729000 | I314: 1535000 | J314: 1863000 | K314: 2444000 | L314: 3400000 | M314: 4390000 | N314: 4396000 | O314: 4471000
A315: =VLOOKUP(B315,'PORTFOLIO RAW'!B:B,1,FALSE) -> 922817 | B315: 922817 | C315: AON PLC - TOTAL DEBT | D315: 922817(WC03255) | E315: 2145000 | F315: 1977000 | G315: 2008000 | H315: 4506000 | I315: 4492000 | J315: 4165000 | K315: 4593000 | L315: 5766000 | M315: 5903000 | N315: 6374000 | O315: 6119000
A316: =VLOOKUP(B316,'PORTFOLIO RAW'!B:B,1,FALSE) -> 905446 | B316: 905446 | C316: INGERSOLL-RAND - TOTAL DEBT | D316: 905446(WC03255) | E316: 995785 | F316: 3679104 | G316: 2859427 | H316: 2790775 | I316: 2812087 | J316: 2450614 | K316: 2563434 | L316: 3493579 | M316: 3904119 | N316: 3858550 | O316: 3389376
A317: =VLOOKUP(B317,'PORTFOLIO RAW'!B:B,1,FALSE) -> 28513N | B317: 28513N | C317: CBRE GROUP - TOTAL DEBT | D317: 28513N(WC03255) | E317: 2698614 | F317: 2920100 | G317: 3010677 | H317: 2515567 | I317: 3583348 | J317: 3751436 | K317: 2488249 | L317: 2424102 | M317: 4430336 | N317: 3802806 | O317: 2910393
A318: =VLOOKUP(B318,'PORTFOLIO RAW'!B:B,1,FALSE) -> 31412T | B318: 31412T | C318: EXPEDIA GROUP INC - TOTAL DEBT | D318: 31412T(WC03255) | E318: 1085000 | F318: 1544548 | G318: 895086 | H318: 1644894 | I318: 1249281 | J318: 1249345 | K318: 1331412 | L318: 1850787 | M318: 3201277 | N318: 3160336 | O318: 4249054
A319: =VLOOKUP(B319,'PORTFOLIO RAW'!B:B,1,FALSE) -> 680902 | B319: 680902 | C319: AMERICAN TOWER CORP - TOTAL DEBT | D319: 680902(WC03255) | E319: 4285284 | F319: 4333146 | G319: 4211581 | H319: 5587388 | I319: 7236308 | J319: 8753376 | K319: 14478278 | L319: 14608708 | M319: 17119009 | N319: 18533465 | O319: 20205100
A320: =VLOOKUP(B320,'PORTFOLIO RAW'!B:B,1,FALSE) -> 904383 | B320: 904383 | C320: DUKE ENERGY CORP - TOTAL DEBT | D320: 904383(WC03255) | E320: 11766000 | F320: 14439000 | G320: 17015000 | H320: 18426000 | I320: 21000000 | J320: 40518000 | K320: 41095000 | L320: 42534000 | M320: 43202000 | N320: 50382000 | O320: 54442000
A321: =VLOOKUP(B321,'PORTFOLIO RAW'!B:B,1,FALSE) -> 13967E | B321: 13967E | C321: MONDELEZ - TOTAL DEBT | D321: 13967E(WC03255) | E321: 21009000 | F321: 20251000 | G321: 18990000 | H321: 28724000 | I321: 26931000 | J321: 19425000 | K321: 17121000 | L321: 16700000 | M321: 15398000 | N321: 17199000 | O321: 17652000
A322: =VLOOKUP(B322,'PORTFOLIO RAW'!B:B,1,FALSE) -> 903749 | B322: 903749 | C322: EATON CORP PLC - TOTAL DEBT | D322: 903749(WC03255) | E322: 3417000 | F322: 4271000 | G322: 3467000 | H322: 3458000 | I322: 3773000 | J322: 10833000 | K322: 9549000 | L322: 9034000 | M322: 8449000 | N322: 8277000 | O322: 7751000
A323: =VLOOKUP(B323,'PORTFOLIO RAW'!B:B,1,FALSE) -> 937343 | B323: 937343 | C323: L BRANDS INC - TOTAL DEBT | D323: 937343(WC03255) | E323: 2912000 | F323: 2897000 | G323: 2725000 | H323: 2507000 | I323: 3538000 | J323: 4477000 | K323: 4976000 | L323: 4765000 | M323: 5721000 | N323: 5736000 | O323: 5794000
A324: =VLOOKUP(B324,'PORTFOLIO RAW'!B:B,1,FALSE) -> 905113 | B324: 905113 | C324: ARCONIC INC - TOTAL DEBT | D324: 905113(WC03255) | E324: 7998000 | F324: 10578000 | G324: 9859000 | H324: 9165000 | I324: 9371000 | J324: 8829000 | K324: 8319000 | L324: 8852000 | M324: 9103000 | N324: 8084000 | O324: 6844000
A325: =VLOOKUP(B325,'PORTFOLIO RAW'!B:B,1,FALSE) -> 13967H | B325: 13967H | C325: WILLIS TOWERS WAT - TOTAL DEBT | D325: 13967H(WC03255) | E325: 1250000 | F325: 2650000 | G325: 2374000 | H325: 2290000 | I325: 2395000 | J325: 2381000 | K325: 2326000 | L325: 2309000 | M325: 3266000 | N325: 3865000 | O325: 4535000
A326: =VLOOKUP(B326,'PORTFOLIO RAW'!B:B,1,FALSE) -> 921431 | B326: 921431 | C326: BAKER HUGHES A GE CO - TOTAL DEBT | D326: 921431(WC03255) | E326: 1084800 | F326: 2333000 | G326: 1800000 | H326: 3885000 | I326: 4069000 | J326: 4916000 | K326: 4381000 | L326: 4133000 | M326: 4041000 | N326: 3018000 | O326: 8349000
A327: =VLOOKUP(B327,'PORTFOLIO RAW'!B:B,1,FALSE) -> 266220 | B327: 266220 | C327: TAPESTRY INC - TOTAL DEBT | D327: 266220(WC03255) | E327: 3100 | F327: 2865 | G327: 33076 | H327: 24901 | I327: 24155 | J327: 23360 | K327: 985 | L327: 140485 | M327: 890400 | N327: 876200 | O327: 1579500
A328: =VLOOKUP(B328,'PORTFOLIO RAW'!B:B,1,FALSE) -> 30730Q | B328: 30730Q | C328: INTERCONTINENTAL - TOTAL DEBT | D328: 30730Q(WC03255) | E328: 221875 | F328: 379375 | G328: 307500 | H328: 578500 | I328: 887500 | J328: 1132500 | K328: 5058000 | L328: 4289000 | M328: 7308000 | N328: 6364000 | O328: 6100000
A329: =VLOOKUP(B329,'PORTFOLIO RAW'!B:B,1,FALSE) -> 921925 | B329: 921925 | C329: JEFFERIES FINANCIAL - TOTAL DEBT | D329: 921925(WC03255) | E329: 2136550 | F329: 2081456 | G329: 1970371 | H329: 1691128 | I329: 1997958 | J329: 1474054 | K329: 13564820 | L329: 14567029 | M329: 14782210 | N329: 14695978 | O329: 15164305
A330: =VLOOKUP(B330,'PORTFOLIO RAW'!B:B,1,FALSE) -> 912278 | B330: 912278 | C330: CIGNA CORP - TOTAL DEBT | D330: 912278(WC03255) | E330: 1793000 | F330: 2391000 | G330: 2540000 | H330: 2840000 | I330: 5094000 | J330: 5187000 | K330: 5247000 | L330: 5152000 | M330: 5169000 | N330: 5032000 | O330: 5439000
...

Sheet REV
B2: Code | C2: Name | D2: Code | E2: 2007 | F2: 2008 | G2: 2009 | H2: 2010 | I2: 2011 | J2: 2012 | K2: 2013 | L2: 2014 | M2: 2015 | N2: 2016 | O2: 2017
A3: =VLOOKUP(B3,'PORTFOLIO RAW'!B:B,1,FALSE) -> 891399 | B3: 891399 | C3: AMAZON.COM INC - NET SALES OR REVENUES | D3: 891399(WC01001) | E3: 14835000 | F3: 19166000 | G3: 24509000 | H3: 34204000 | I3: 48077000 | J3: 61093000 | K3: 74452000 | L3: 88988000 | M3: 107006000 | N3: 135987000 | O3: 177866000
A4: =VLOOKUP(B4,'PORTFOLIO RAW'!B:B,1,FALSE) -> 916328 | B4: 916328 | C4: ABBOTT LABORATORIES - NET SALES OR REVENUES | D4: 916328(WC01001) | E4: 25914238 | F4: 29527552 | G4: 30764707 | H4: 35166721 | I4: 38851259 | J4: 39873910 | K4: 21848000 | L4: 20247000 | M4: 20405000 | N4: 20853000 | O4: 27390000
A5: =VLOOKUP(B5,'PORTFOLIO RAW'!B:B,1,FALSE) -> 545101 | B5: 545101 | C5: AES CORP - NET SALES OR REVENUES | D5: 545101(WC01001) | E5: 13588000 | F5: 16070000 | G5: 13933000 | H5: 16568000 | I5: 17344000 | J5: 18141000 | K5: 15880000 | L5: 17141000 | M5: 14971000 | N5: 13586000 | O5: 10530000
A6: =VLOOKUP(B6,'PORTFOLIO RAW'!B:B,1,FALSE) -> 906187 | B6: 906187 | C6: INT'L BUSINESS MACHS - NET SALES OR REVENUES | D6: 906187(WC01001) | E6: 98786000 | F6: 103630000 | G6: 95758000 | H6: 99870000 | I6: 106916000 | J6: 104507000 | K6: 99751000 | L6: 92793000 | M6: 81741000 | N6: 79919000 | O6: 79139000
A7: =VLOOKUP(B7,'PORTFOLIO RAW'!B:B,1,FALSE) -> 936365 | B7: 936365 | C7: ADVANCED MICRO - NET SALES OR REVENUES | D7: 936365(WC01001) | E7: 6013000 | F7: 5808000 | G7: 5403000 | H7: 6494000 | I7: 6568000 | J7: 5422000 | K7: 5299000 | L7: 5506000 | M7: 3991000 | N7: 4272000 | O7: 5329000
A8: =VLOOKUP(B8,'PORTFOLIO RAW'!B:B,1,FALSE) -> 749382 | B8: 749382 | C8: ADOBE INC - NET SALES OR REVENUES | D8: 749382(WC01001) | E8: 3157881 | F8: 3579889 | G8: 2945853 | H8: 3779831 | I8: 4212509 | J8: 4403677 | K8: 4055240 | L8: 4147065 | M8: 4795511 | N8: 5854430 | O8: 7301505
A9: =VLOOKUP(B9,'PORTFOLIO RAW'!B:B,1,FALSE) -> 905271 | B9: 905271 | C9: AIR PRODUCTS & CHEMS - NET SALES OR REVENUES | D9: 905271(WC01001) | E9: 10037800 | F9: 10414500 | G9: 8256200 | H9: 9026000 | I9: 10082000 | J9: 9611700 | K9: 10180400 | L9: 10439000 | M9: 9894900 | N9: 9524400 | O9: 8187600
A10: =VLOOKUP(B10,'PORTFOLIO RAW'!B:B,1,FALSE) -> 894371 | B10: 894371 | C10: BOSTON PROPERTIES - NET SALES OR REVENUES | D10: 894371(WC01001) | E10: 1482289 | F10: 1488400 | G10: 1522249 | H10: 1558136 | I10: 1759526 | J10: 1876267 | K10: 2135539 | L10: 2565037 | M10: 2866716 | N10: 2631426 | O10: 2609739
A11: =VLOOKUP(B11,'PORTFOLIO RAW'!B:B,1,FALSE) -> 322677 | B11: 322677 | C11: ALLSTATE CORP - NET SALES OR REVENUES | D11: 322677(WC01001) | E11: 36639000 | F11: 31315000 | G11: 33915000 | H11: 32361000 | I11: 33162000 | J11: 33200000 | K11: 34714000 | L11: 35481000 | M11: 36105000 | N11: 36847000 | O11: 38670000
A12: =VLOOKUP(B12,'PORTFOLIO RAW'!B:B,1,FALSE) -> 906191 | B12: 906191 | C12: HONEYWELL INTERNATNL - NET SALES OR REVENUES | D12: 906191(WC01001) | E12: 34589000 | F12: 36556000 | G12: 30854000 | H12: 33389000 | I12: 36500000 | J12: 37665000 | K12: 39062000 | L12: 40306000 | M12: 38581000 | N12: 39302000 | O12: 40534000
A13: =VLOOKUP(B13,'PORTFOLIO RAW'!B:B,1,FALSE) -> 938692 | B13: 938692 | C13: AMGEN INC - NET SALES OR REVENUES | D13: 938692(WC01001) | E13: 14771000 | F13: 15003000 | G13: 14642000 | H13: 15006000 | I13: 15582000 | J13: 17265000 | K13: 18676000 | L13: 20063000 | M13: 21662000 | N13: 22991000 | O13: 22849000
A14: =VLOOKUP(B14,'PORTFOLIO RAW'!B:B,1,FALSE) -> 905802 | B14: 905802 | C14: HESS CORPORATION - NET SALES OR REVENUES | D14: 905802(WC01001) | E14: 31647000 | F14: 41165000 | G14: 29378000 | H14: 33862000 | I14: 38466000 | J14: 37691000 | K14: 22284000 | L14: 10737000 | M14: 6636000 | N14: 4762000 | O14: 5466000
... A109: =VLOOKUP(B109,'PORTFOLIO RAW'!B:B,1,FALSE) -> 905016 | B109: 905016 | C109: NEXTERA ENERGY - NET SALES OR REVENUES | D109: 905016(WC01001) | E109: 15263000 | F109: 16410000 | G109: 15479000 | H109: 14667000 | I109: 14827000 | J109: 14085000 | K109: 15136000 | L109: 16601000 | M109: 16554000 | N109: 15696000 | O109: 16741000
A110: =VLOOKUP(B110,'PORTFOLIO RAW'!B:B,1,FALSE) -> 28341F | B110: 28341F | C110: ASSURANT INC - NET SALES OR REVENUES | D110: 28341F(WC01001) | E110: 8441701 | F110: 8913986 | G110: 8721708 | H110: 8519870 | I110: 8259314 | J110: 8455532 | K110: 9052044 | L110: 10381683 | M110: 10330518 | N110: 7538654 | O110: 6415900
A111: =VLOOKUP(B111,'PORTFOLIO RAW'!B:B,1,FALSE) -> 755980 | B111: 755980 | C111: FASTENAL COMPANY - NET SALES OR REVENUES | D111: 755980(WC01001) | E111: 2061819 | F111: 2340425 | G111: 1930330 | H111: 2269471 | I111: 2766859 | J111: 3133577 | K111: 3326106 | L111: 3733507 | M111: 3869187 | N111: 3962036 | O111: 4390500
A112: =VLOOKUP(B112,'PORTFOLIO RAW'!B:B,1,FALSE) -> 905994 | B112: 905994 | C112: FEDERAL REALTY INVST - NET SALES OR REVENUES | D112: 905994(WC01001) | E112: 485892 | F112: 520525 | G112: 531019 | H112: 544674 | I112: 553059 | J112: 608018 | K112: 637413 | L112: 686090 | M112: 744012 | N112: 801591 | O112: 857348
A113: =VLOOKUP(B113,'PORTFOLIO RAW'!B:B,1,FALSE) -> 997198 | B113: 997198 | C113: FIFTH THIRD BANCORP - NET SALES OR REVENUES | D113: 997198(WC01001) | E113: 8494000 | F113: 8205000 | G113: 7298000 | H113: 6645000 | I113: 6204000 | J113: 6130000 | K113: 6813000 | L113: 6321000 | M113: 6637000 | N113: 6823000 | O113: 7666000
A114: =VLOOKUP(B114,'PORTFOLIO RAW'!B:B,1,FALSE) -> 951503 | B114: 951503 | C114: M&T BANK CORPORATION - NET SALES OR REVENUES | D114: 951503(WC01001) | E114: 4596167 | F114: 4403023 | G114: 3942920 | H114: 3920118 | I114: 4350105 | J114: 4674653 | K114: 4838665 | L114: 4752822 | M114: 5010148 | N114: 5721867 | O114: 6018938
A115: =VLOOKUP(B115,'PORTFOLIO RAW'!B:B,1,FALSE) -> 741123 | B115: 741123 | C115: FISERV INC - NET SALES OR REVENUES | D115: 741123(WC01001) | E115: 3922000 | F115: 4739000 | G115: 4077000 | H115: 4133000 | I115: 4337000 | J115: 4482000 | K115: 4814000 | L115: 5066000 | M115: 5254000 | N115: 5505000 | O115: 5696000
A116: =VLOOKUP(B116,'PORTFOLIO RAW'!B:B,1,FALSE) -> 546814 | B116: 546814 | C116: MACY'S INC - NET SALES OR REVENUES | D116: 546814(WC01001) | E116: 26313000 | F116: 24892000 | G116: 23489000 | H116: 25003000 | I116: 26405000 | J116: 27686000 | K116: 27931000 | L116: 28105000 | M116: 27079000 | N116: 25778000 | O116: 24837000
A117: =VLOOKUP(B117,'PORTFOLIO RAW'!B:B,1,FALSE) -> 938076 | B117: 938076 | C117: FRANKLIN RESOURCES - NET SALES OR REVENUES | D117: 938076(WC01001) | E117: 6205769 | F117: 6032386 | G117: 4159565 | H117: 5914140 | I117: 7209754 | J117: 7174500 | K117: 8086100 | L117: 8592500 | M117: 7968500 | N117: 6683500 | O117: 6526600
A118: =VLOOKUP(B118,'PORTFOLIO RAW'!B:B,1,FALSE) -> 152594 | B118: 152594 | C118: FREEPORT-MCMORAN INC - NET SALES OR REVENUES | D118: 152594(WC01001) | E118: 16939000 | F118: 17796000 | G118: 15040000 | H118: 18395000 | I118: 21427000 | J118: 18010000 | K118: 21391000 | L118: 21222000 | M118: 16229000 | N118: 14599000 | O118: 15888000
A119: =VLOOKUP(B119,'PORTFOLIO RAW'!B:B,1,FALSE) -> 951018 | B119: 951018 | C119: GAP INC - NET SALES OR REVENUES | D119: 951018(WC01001) | E119: 15763000 | F119: 14526000 | G119: 14197000 | H119: 14664000 | I119: 14549000 | J119: 15651000 | K119: 16148000 | L119: 16435000 | M119: 15797000 | N119: 15516000 | O119: 15855000
A120: =VLOOKUP(B120,'PORTFOLIO RAW'!B:B,1,FALSE) -> 907652 | B120: 907652 | C120: GENERAL DYNAMICS - NET SALES OR REVENUES | D120: 907652(WC01001) | E120: 27240000 | F120: 29300000 | G120: 31981000 | H120: 32466000 | I120: 32677000 | J120: 31513000 | K120: 31218000 | L120: 30852000 | M120: 31469000 | N120: 31353000 | O120: 30973000
A121: =VLOOKUP(B121,'PORTFOLIO RAW'!B:B,1,FALSE) -> 905801 | B121: 905801 | C121: GENERAL MILLS, INC. - NET SALES OR REVENUES | D121: 905801(WC01001) | E121: 12442000 | F121: 13652100 | G121: 14691300 | H121: 14796500 | I121: 14880200 | J121: 16657900 | K121: 17774100 | L121: 17909600 | M121: 17630300 | N121: 16563100 | O121: 15619800
A122: =VLOOKUP(B122,'PORTFOLIO RAW'!B:B,1,FALSE) -> 906511 | B122: 906511 | C122: GENUINE PARTS CO - NET SALES OR REVENUES | D122: 906511(WC01001) | E122: 10843195 | F122: 11015263 | G122: 10057512 | H122: 11207589 | I122: 12458877 | J122: 13013868 | K122: 14077843 | L122: 15341647 | M122: 15280044 | N122: 15339713 | O122: 16308801
... A236: =VLOOKUP(B236,'PORTFOLIO RAW'!B:B,1,FALSE) -> 933974 | B236: 933974 | C236: TRAVELERS COS - NET SALES OR REVENUES | D236: 933974(WC01001) | E236: 26087000 | F236: 24897000 | G236: 24938000 | H236: 25138000 | I236: 25471000 | J236: 25755000 | K236: 26206000 | L236: 27162000 | M236: 26852000 | N236: 27654000 | O236: 28916000
A237: =VLOOKUP(B237,'PORTFOLIO RAW'!B:B,1,FALSE) -> 14015T | B237: 14015T | C237: FIDELITY NATNL INF - NET SALES OR REVENUES | D237: 14015T(WC01001) | E237: 4758016 | F237: 3446000 | G237: 3769500 | H237: 5269500 | I237: 5745700 | J237: 5807600 | K237: 6070700 | L237: 6413800 | M237: 6595200 | N237: 9241000 | O237: 9123000
A238: =VLOOKUP(B238,'PORTFOLIO RAW'!B:B,1,FALSE) -> 905019 | B238: 905019 | C238: MERCK & CO INC - NET SALES OR REVENUES | D238: 905019(WC01001) | E238: 24197700 | F238: 23850300 | G238: 27428300 | H238: 45913000 | I238: 48132000 | J238: 47347000 | K238: 44033000 | L238: 42237000 | M238: 39498000 | N238: 39807000 | O238: 40122000
A239: =VLOOKUP(B239,'PORTFOLIO RAW'!B:B,1,FALSE) -> 912090 | B239: 912090 | C239: SCHLUMBERGER LIMITED - NET SALES OR REVENUES | D239: 912090(WC01001) | E239: 23277000 | F239: 27163000 | G239: 22702000 | H239: 27447000 | I239: 39540000 | J239: 42149000 | K239: 46294000 | L239: 48580000 | M239: 35475000 | N239: 27810000 | O239: 30440000
A240: =VLOOKUP(B240,'PORTFOLIO RAW'!B:B,1,FALSE) -> 755741 | B240: 755741 | C240: CHARLES SCHWAB CORP - NET SALES OR REVENUES | D240: 755741(WC01001) | E240: 5617000 | F240: 5393000 | G240: 4474000 | H240: 4510000 | I240: 4915000 | J240: 5081000 | K240: 5549000 | L240: 6157000 | M240: 6501000 | N240: 7644000 | O240: 8960000
A241: =VLOOKUP(B241,'PORTFOLIO RAW'!B:B,1,FALSE) -> 14361V | B241: 14361V | C241: ZIMMER BIOMET - NET SALES OR REVENUES | D241: 14361V(WC01001) | E241: 3897500 | F241: 4121100 | G241: 4095400 | H241: 4220200 | I241: 4451800 | J241: 4471700 | K241: 4623400 | L241: 4673300 | M241: 5997800 | N241: 7683900 | O241: 7824100
A242: =VLOOKUP(B242,'PORTFOLIO RAW'!B:B,1,FALSE) -> 154680 | B242: 154680 | C242: AMERISOURCEBERGEN - NET SALES OR REVENUES | D242: 154680(WC01001) | E242: 66074312 | F242: 70189733 | G242: 71759990 | H242: 77953979 | I242: 80217558 | J242: 79489596 | K242: 87959167 | L242: 119569127 | M242: 135961803 | N242: 146849686 | O242: 153143826
A243: =VLOOKUP(B243,'PORTFOLIO RAW'!B:B,1,FALSE) -> 14698C | B243: 14698C | C243: PRINCIPAL FINL GROUP - NET SALES OR REVENUES | D243: 14698C(WC01001) | E243: 10800400 | F243: 9921700 | G243: 9223300 | H243: 9298900 | I243: 8790400 | J243: 9213600 | K243: 9405500 | L243: 10555600 | M243: 11994600 | N243: 12492500 | O243: 14175000
A244: =VLOOKUP(B244,'PORTFOLIO RAW'!B:B,1,FALSE) -> 905361 | B244: 905361 | C244: SHERWIN-WILLIAMS CO - NET SALES OR REVENUES | D244: 905361(WC01001) | E244: 8005292 | F244: 7979727 | G244: 7094249 | H244: 7776424 | I244: 8765699 | J244: 9534462 | K244: 10185532 | L244: 11129533 | M244: 11339304 | N244: 11855602 | O244: 14983788
